Workbook
Name IQ_CH: 110000
Name IQ_CQ: 5000
Name IQ_CY: 10000
Name IQ_DAILY: 500000
Name IQ_FH: 100000
Name IQ_FQ: 500
Name IQ_FY: 1000
Name IQ_LTM: 2000
Name IQ_MONTH: 15000
Name IQ_NTM: 6000
Name IQ_WEEK: 50000
Name IQ_YTD: 3000

Sheet __snloffice
A1: 允䅁䙁䅕䅁䭁䅁䅁兑卂䕁䅍睑䅁䅁䅁䅁捁䅁䅁督睂䙁䄸督潂䝁䅅杣求䡁䅍睘療䡁䅕䅤䅁䅁䅙䅁畁䅁䅁兓剂䙁䄸睑療䝁䄰兢療䝁䄴睘歂䝁䅫杤時䝁䅑党橂䝁䅷兙祂䝁䅕䅚䅁䅁䅅䅁䝁䅁䅁杒剂䅁䅁杁䅁䅁䅧䅁䝂䙁䅅䅍䅁䅁䅕䅁啁䅁䅁睍癁䑁䅍免癁䑁䅉䅍祁䑁䅅䅁䑁䅁䅁䅇䅁䝁䅫兣時䝁䅕杙あ䙁䄸党㑂䝁䅍䅢䅁䍁䅉䅁㑁䅁䅁睉䩂䕁䄴杖䉂䕁䅷兓䕂䍁䅁杒噂䕁䄴睑啂䕁䅫睔佂䍁䅁䅕䉂䙁䅉兑乂䕁䅕䅖䙂䙁䅉䅁䕁䅁䅁䅆䅁䑁䅙睌穁䑁䅁睌祁䑁䅁杍硁䅁䅁睂䅁䉁䅙䅁祁䑁䅁杍祁䍁䄰䅍ㅁ䍁䄰䅍穁䅁䅁兏䅁䉁䅑䅁穁䍁䄸睍硁䍁䄸杍睁䑁䅉䅎䅁䅁䅧䅁坁䅁䅁杍睁䑁䅉䅎瑁䑁䅁杍瑁䑁䅉免䅁䑁䅑䅁啁䅁䅁兏癁䑁䅍䅍癁䑁䅉䅍祁䑁䅅䅁䩁䅁䅁杆䅁䑁䅅杍癁䑁䅍免癁䑁䅉䅍祁䑁䅉䅁䱁䅁䅁杆䅁䑁䅉䅍祁䑁䅍兌硁䑁䅅兌睁䑁䅧䅁癁䅁䅁杆䅁䑁䅅杍癁䑁䅍免癁䑁䅉䅍祁䑁䅅䅁䭁䅁䅁䅆䅁䑁䅫睌穁䑁䅁睌祁䑁䅁杍祁䅁䅁充䅁䉁䅙䅁硁䑁䅉睌穁䑁䅅睌祁䑁䅁杍穁䅁䅁䅄䅁䉁䅙䅁硁䑁䅉睌穁䑁䅅睌祁䑁䅁杍ぁ䅁䅁兄䅁䅁䅯䅁䍂䙁䅧睕䵂䅁䅁杇䅁䉁䅷䅁䩂䙁䅅睘啂䝁䄸䅤桂䝁䅷睘歂䝁䅕杙あ䅁䅁睉䅁䉁䅙䅁硁䑁䅉睌穁䑁䅅睌祁䑁䅁杍ㅁ䅁䅁杄䅁䉁䅑䅁穁䍁䄸睍硁䍁䄸杍睁䑁䅉杍䅁䅁䄸䅁啁䅁䅁李癁䑁䅍䅍癁䑁䅉䅍祁䑁䅉䅁允䅁䅁杆䅁䑁䅉䅍祁䑁䅕兌睁䑁䅕兌睁䑁䅣䅁湁䅁䅁䅆䅁䑁䅙睌穁䑁䅁睌祁䑁䅁杍穁䅁䅁杅䅁䍁䅙䅁呂䕁䄴䅔時䝁䄴党あ䙁䄸兡畂䡁䅙党穂䡁䅑睘灂䝁䄴睙䅁䍁䅅䅁䭁䅁䅁睒䍂䕁䅑睑䅁䉁䅷䅁啁䅁䅁睍癁䑁䅍免癁䑁䅉䅍祁䑁䅍䅁呁䅁䅁杆䅁䑁䅉䅍祁䑁䅍兌睁䑁䅧兌睁䑁䅫䅁煁䅁䅁杋䅁䕁䅫兕時䙁䅑睔啂䕁䅅䅔時䕁䅑兓坂䙁䄸䅕䉂䕁䅫䅒時䕁䅍杒䅁䙁䅅䅁啁䅁䅁李癁䑁䅍䅍癁䑁䅉䅍祁䑁䅕䅁啁䅁䅁杆䅁䑁䅉䅍祁䑁䅅兌睁䑁䅕兌睁䑁䅑䅁㑁䅁䅁杆䅁䑁䅉䅍祁䑁䅉兌睁䑁䅧兌睁䑁䅉䅁㥁䅁䅁䅆䅁䑁䅫睌穁䑁䅁睌祁䑁䅁杍穁䅁䅁兆䅁䉁䅑䅁㉁䍁䄸睍睁䍁䄸杍睁䑁䅉䅎䅁䉁䅙䅁坁䅁䅁杍睁䑁䅉免瑁䑁䅁兎瑁䑁䅁兎䅁䍁䅑䅁坁䅁䅁杍睁䑁䅉杍瑁䑁䅁䅏瑁䑁䅁睍䅁䍁䅫䅁啁䅁䅁兏癁䑁䅍䅍癁䑁䅉䅍祁䑁䅑䅁塁䅁䅁䅆䅁䑁䅍睌穁䑁䅅睌祁䑁䅁杍ㅁ䅁䅁䅇䅁䉁䅑䅁㕁䍁䄸睍睁䍁䄸杍睁䑁䅉兎䅁䉁䅫䅁䝁䅁䅁杔䉂䅁䅁睇䅁䅁䅯䅁偂䕁䅉䅒䑂䅁䅁先䅁䅁䅯䅁啂䕁䅍䅕䑂䅁䅁杈䅁䅁䅯䅁啂䙁䅍䅔奂䅁䅁睈䅁䉁䅙䅁祁䑁䅁杍ぁ䍁䄰䅍㑁䍁䄰䅍㍁䅁䅁睋䅁䉁䅙䅁祁䑁䅁杍ぁ䍁䄰䅍ㅁ䍁䄰䅍硁䅁䅁睏䅁䅁䅉䅁䅁䍁䅁䅁坁䅁䅁杍睁䑁䅉睍瑁䑁䅁䅏瑁䑁䅁睍䅁䑁䄴䅁坁䅁䅁杍睁䑁䅉杍瑁䑁䅁兎瑁䑁䅁䅎䅁䍁䅕䅁坁䅁䅁杍睁䑁䅉兎瑁䑁䅁䅏瑁䑁䅁李䅁䍁䅷䅁坁䅁䅁杍睁䑁䅉䅎瑁䑁䅁兎瑁䑁䅁䅏䅁䍁䅙䅁坁䅁䅁杍睁䑁䅉免瑁䑁䅁䅏瑁䑁䅁䅎䅁䍁䅧䅁坁䅁䅁杍睁䑁䅉免瑁䑁䅅免瑁䑁䅁睍䅁䍁䄰䅁坁䅁䅁杍睁䑁䅉䅎瑁䑁䅅免瑁䑁䅁李䅁䑁䅁䅁坁䅁䅁杍睁䑁䅉杍瑁䑁䅅免瑁䑁䅁杍䅁䍁䄴䅁坁䅁䅁杍睁䑁䅉兎瑁䑁䅅免瑁䑁䅁兎䅁䑁䅅䅁坁䅁䅁杍睁䑁䅉杍瑁䑁䅁杍瑁䑁䅉睍䅁䑁䅉䅁坁䅁䅁杍睁䑁䅉睍瑁䑁䅁杍瑁䑁䅉杍䅁䑁䅍䅁坁䅁䅁杍睁䑁䅉兎瑁䑁䅁杍瑁䑁䅅兏䅁䑁䅕䅁坁䅁䅁杍睁䑁䅉李瑁䑁䅁杍瑁䑁䅅䅏䅁䑁䅙䅁坁䅁䅁杍睁䑁䅉睍瑁䑁䅁兎瑁䑁䅅䅍䅁䑁䅣䅁坁䅁䅁杍睁䑁䅉睍瑁䑁䅁兎瑁䑁䅁䅏䅁䑁䅯䅁坁䅁䅁杍睁䑁䅉免瑁䑁䅁䅏瑁䑁䅁睍䅁䑁䅷䅁坁䅁䅁杍睁䑁䅉免瑁䑁䅅免瑁䑁䅁杍䅁䑁䄸䅁坁䅁䅁杍睁䑁䅉杍瑁䑁䅅免瑁䑁䅁免䅁䕁䅁䅁坁䅁䅁杍睁䑁䅉睍瑁䑁䅅免瑁䑁䅁杍䅁䕁䅅䅁坁䅁䅁杍睁䑁䅉䅎瑁䑁䅅免瑁䑁䅁兎䅁䕁䅉䅁坁䅁䅁杍睁䑁䅉兎瑁䑁䅅免瑁䑁䅁䅎䅁䕁䅍䅁坁䅁䅁杍睁䑁䅉杍瑁䑁䅁杍瑁䑁䅅睎䅁䕁䅑䅁坁䅁䅁杍睁䑁䅉睍瑁䑁䅁杍瑁䑁䅅李䅁䕁䅕䅁坁䅁䅁杍睁䑁䅉䅎瑁䑁䅁杍瑁䑁䅅兎䅁䕁䅙䅁坁䅁䅁杍睁䑁䅉兎瑁䑁䅁杍瑁䑁䅅睍䅁䕁䅣䅁坁䅁䅁杍睁䑁䅉李瑁䑁䅁杍瑁䑁䅅杍䅁䕁䅧䅁坁䅁䅁杍睁䑁䅉䅎瑁䑁䅁睎瑁䑁䅍免䅁䕁䅫䅁坁䅁䅁杍睁䑁䅉兎瑁䑁䅁睎瑁䑁䅍䅍䅁䕁䅯䅁坁䅁䅁杍睁䑁䅉兎瑁䑁䅁䅎瑁䑁䅍䅍䅁䕁䅳䅁敁䅁䅁睕兂䙁䄸䅕卂䕁䅫睑䙂䙁䄸睑䵂䕁䄸睕䙂䅁䅁䅔䅁䉁䅉䅁汁䙁䅑睑乂䙁䅍兗睁䑁䅉䅁乂䅁䅁䅈䅁䙁䅍䅕時䙁䅉兑啂䕁䅕睘坂䕁䅅䅔噂䕁䅕䅁佂䅁䅁杅䅁䍁䅕䅖䑂䕁䄰睕婂䑁䅁睍䅁䕁䄸䅁䭁䅁䅁村䩂䙁䅯䅒䅁䙁䅁䅁䥁䅁䅁杒婂䑁䅁䅁卂䅁䅁䅅䅁䕁䅫兕時䕁䅉杖兂䙁䅍䅁呂䅁䅁杉䅁䙁䅍䅕時䕁䄴兑坂䙁䄸䅕䙂䙁䅉睘呂䕁䅧兑卂䕁䅕䅁啂䅁䅁か䅕䅁杷允䅁䅁䅑䅁䑁䅁䅷䅁䭁䕁䄸䅁䭁䕁䄴䅁䙁䅁䅁䅁䅃⭃䅚允䅁䅁䅅䅁䙁佁㙆䭆䠵刴䅆䍄䉁䅁䅁兂䅁䅁䅍䅄䅁䅁䅯先䅁䅁䅯允䅁䅁䅯兂䅁䅁䅕䅁䅁䍁扂欵䉁䅁䅁允䅁䅁䅕歲桦桥畓稱䴸䅉䅅䅁䙁䅁䅁睁䵁䅁䅁权慁䅁䅁权呂䅁䅁权䙁䅁䅁兂䅁䅁䅁䵉汌䅑䅅䅁䉁䅁䅁兂㙃兓䍷祋㙣䅑杷允䅁䅁䅕䅁䑁䅁䅷䅁䭁䉁䄰䅁䭁䙁䅍䅁䭁䅁䅕䅁䙁䅁䅁䅁杁佂䅚允䅁䅁䅅䅁䙁䩁畨潅䅐楓䄵䍄䉁䅁䅁兂䅁䅁䅍䅄䅁䅁䅯䅁䅁䅁䅯允䅁䅁䅯兂䅁䅁䅕䅁䅁䅁㝃唵䉁䅁䅁允䅁䅁䅕児塲㍯㥁樲䴸䅉䅅䅁䙁䅁䅁睁䵁䅁䅁权晁䅁䅁权呂䅁䅁权䙁䅁䅁兂䅁䅁䅁䉑浪䅑䅅䅁䉁䅁䅁兂䝂癴㥐倱睧䅑杷允䅁䅁䅑䅁䑁䅁䅷䅁䭁䕁䄸䅁䭁䕁䄴䅁䙁䅁䅁䅁杂佄䅚允䅁䅁䅅䅁䙁䭁䠵場啯桲䅊䍄䉁䅁䅁兂䅁䅁䅍䅄䅁䅁䅯䅁䅁䅁䅯睕䅁䅁䅯兂䅁䅁䅕䅁䅁䵁煂欵䉁䅁䅁允䅁䅁䅕佖汏㡭杔き䵁䅉䅅䅁䕁䅁䅁睁䵁䅁䅁权偂䅁䅁权佂䅁䅁兂䅁䅁䅁䈴浺䅑䅅䅁䉁䅁䅁兂䑄匹捨㡪偉䅑杷允䅁䅁䅕䅁䑁䅁䅷䅁䭁䅁䅁䅁䭁䅁䅅䅁䭁䅁䅕䅁䙁䅁䅁䅁䅄⭬䅖允䅁䅁䅅䅁䙁䩁婱婭婭摭⽫䍄䉁䅁䅁兂䅁䅁䅍䅄䅁䅁䅯䅈䅁䅁䅯允䅁䅁䅯兂䅁䅁䅕䅁䅁䥁祁欵䉁䅁䅁允䅁䅁䅕椹捨㡪ㅌ䐲䴸䅉䅅䅁䙁䅁䅁睁䵁䅁䅁权晁䅁䅁权䉁䅁䅁权䙁䅁䅁兂䅁䅁䅁乙決䅑䅅䅁䉁䅁䅁兂乄䵺䵺䵺捺睐杷允䅁䅁䅕䅁䑁䅁䅷䅁䭁䉁䅷䅁䭁䙁䅍䅁䭁䅁䅕䅁䙁䅁䅁䅁䅄敖䅚允䅁䅁䅅䅁䙁乁欰潂噇祑䄵䍄䉁䅁䅁䅂䅁䅁䅍䅄䅁䅁䅯睔䅁䅁䅯杔䅁䅁䅕䅁䅁䕁浂欵䉁䅁䅁允䅁䅁䅕瑃橥䑣䬰啄䵁䅉䅅䅁䙁䅁䅁睁䵁䅁䅁权慁䅁䅁权䉁䅁䅁权䙁䅁䅁兂䅁䅁䅁佧汦䅑䅅䅁䉁䅁䅁兂㉄䙋偹癷杘睐杷允䅁䅁䅕䅁䑁䅁䅷䅁䭁䉁䄰䅁䭁䙁䅍䅁䭁䅁䅕䅁䙁䅁䅁䅁䅄住䅚允䅁䅁䅅䅁䙁䙁余扌摋礷䄵䍄䉁䅁䅁兂䅁䅁䅍䅄䅁䅁䅯睈䅁䅁䅯允䅁䅁䅯兂䅁䅁䅕䅁䅁䝁啁欵䉁䅁䅁允䅁䅁䅕䡰㥁瑃橥䐴䴸䅉䅅䅁䙁䅁䅁睁䵁䅁䅁权摁䅁䅁权呂䅁䅁权䙁䅁䅁兂䅁䅁䅁䥯浈䅑䅅䅁䉁䅁䅁兂獃䙈歰㕏琸䅑杷允䅁䅁䅕䅁䑁䅁䅷䅁䭁䅁䅁䅁䭁䙁䅍䅁䭁䅁䅕䅁䙁䅁䅁䅁䅁併䅖允䅁䅁䅅䅁䙁䱁䩰䅄牉穊䅊䍄䉁䅁䅁兂䅁䅁䅍䅄䅁䅁䅯䅁䅁䅁䅯睕䅁䅁䅯兂䅁䅁䅕䅁䅁䍁灁欵䉁䅁䅁允䅁䅁䅕搵楁⼲⭫き䵁䅉䅅䅁䕁䅁䅁睁䵁䅁䅁权偂䅁䅁权佂䅁䅁兂䅁䅁䅁佧汘䅑䅅䅁䉁䅁䅁兂卂䉵䘶ㄶ剅䅑杷允䅁䅁䅕䅁䑁䅁䅷䅁䭁䅁䅁䅁䭁䅁䅅䅁䭁䅁䅕䅁䙁䅁䅁䅁杄⬲䅖允䅁䅁䅅䅁䙁佁㙆䭆䠵搴⽯䍄䉁䅁䅁兂䅁䅁䅍䅄䅁䅁䅯䅁䅁䅁䅯睕䅁䅁䅯兂䅁䅁䅕䅁䅁䅁㑁欵䉁䅁䅁允䅁䅁䅕䅁䅁䅁权き䵁䅉䅅䅁䙁䅁䅁睁䵁䅁䅁权晁䅁䅁权呂䅁䅁权䙁䅁䅁兂䅁䅁䅁䱉汄䅑䅅䅁䉁䅁䅁兂㑃潈牘摕睧䅑杷允䅁䅁䅕䅁䑁䅁䅷䅁䭁䉁䄸䅁䭁䙁䅍䅁䭁䅁䅕䅁䙁䅁䅁䅁䅂數䅖允䅁䅁䅅䅁䙁䵁㉬灶愸穌䅆䍄䉁䅁䅁䅂䅁䅁䅍䅄䅁䅁䅯睔䅁䅁䅯杔䅁䅁䅯䅉䅁䅁䅅䅁䉁䅁䅁兂乄䵺䵺䵺佷䅑杷允䅁䅁䅕䅁䑁䅁䅷䅁䭁䉁䅯䅁䭁䅁䅅䅁䭁䅁䅕䅁䙁䅁䅁䅁杂敓䅚允䅁䅁䅅䅁䙁䭁睒児塲⭯⽧䍄䉁䅁䅁兂䅁䅁䅍䅄䅁䅁䅯杈䅁䅁䅯睕䅁䅁䅯兂䅁䅁䅕䅁䅁佁祄唵䉁䅁䅁允䅁䅁䅕㉣剩堷⽷䕌䵁䅉䅅䅁䙁䅁䅁睁䵁䅁䅁权慁䅁䅁权呂䅁䅁权䙁䅁䅁兂䅁䅁䅁䑙浦䅑䅅䅁䉁䅁䅁兂晁敨剴乵㘴䅑杷允䅁䅁䅕䅁䑁䅁䅷䅁䭁䅁䅁䅁䭁䅁䅅䅁䭁䅁䅕䅁䙁䅁䅁䅁䅃佇䅚允䅁䅁䅅䅁䙁䱁敧敨剴乵⼴䍄䉁䅁䅁兂䅁䅁䅍䅄䅁䅁䅯睈䅁䅁䅯允䅁䅁䅯兂䅁䅁䅕䅁䅁佁穄唵䉁䅁䅁允䅁䅁䅕場啯歲桦樲䴸䅉䅅䅁䙁䅁䅁睁䵁䅁䅁权慁䅁䅁权䉁䅁䅁权䙁䅁䅁兂䅁䅁䅁䝧浦䅑䅅䅁䉁䅁䅁兂歃䑣䬰㘱潐睐杷允䅁䅁䅑䅁䑁䅁䅷䅁䭁䕁䄸䅁䭁䕁䄴䅁䙁䅁䅁䅁权畮䅖允䅁䅁䅅䅁䙁䡁啳歲桦瑥⽑䍄䉁䅁䅁兂䅁䅁䅍䅄䅁䅁䅯䅁䅁䅁䅯睕䅁䅁䅯兂䅁䅁䅕䅁䅁䥁穄唵䉁䅁䅁允䅁䅁䅕積積積呏歍䵁䅉䅅䅁䙁䅁䅁睁䵁䅁䅁权摁䅁䅁权呂䅁䅁权䙁䅁䅁兂䅁䅁䅁佷氷䅑䅅䅁䉁䅁䅁兂浃㡭村䱳瑉䅑杷允䅁䅁䅑䅁䑁䅁䅷䅁䭁䕁䄸䅁䭁䕁䄴䅁䙁䅁䅁䅁杁余䅚允䅁䅁䅅䅁䙁䑁積積積睍䄹䍄䉁䅁䅁兂䅁䅁䅍䅄䅁䅁䅯杇䅁䅁䅯睕䅁䅁䅯兂䅁䅁䅕䅁䅁䝁䝁欵䉁䅁䅁允䅁䅁䅕牒穢搯契歏䵁䅉䅅䅁䕁䅁䅁睁䵁䅁䅁权偂䅁䅁权佂䅁䅁兂䅁䅁䅁䬴汦䅑䅅䅁䉁䅁䅁兂㝂䭆䠵場啲睐杷允䅁䅁䅑䅁䑁䅁䅷䅁䭁䕁䄸䅁䭁䕁䄴䅁䙁䅁䅁䅁䅃田䅖允䅁䅁䅅䅁䙁䡁啳歲桦来䅚䍄䉁䅁䅁兂䅁䅁䅍䅄䅁䅁䅯睈䅁䅁䅯允䅁䅁䅯兂䅁䅁䅕䅁䅁䭁㑂欵䉁䅁䅁允䅁䅁䅕牕敧敨剴䐴䴸䅉䅅䅁䕁䅁䅁睁䵁䅁䅁权偂䅁䅁权佂䅁䅁兂䅁䅁䅁乷汢䅑䅅䅁䉁䅁䅁兂乄䵺䵺䵺䵷䅑杷允䅁䅁䅕䅁䑁䅁䅷䅁䭁䉁䅯䅁䭁䅁䅅䅁䭁䅁䅕䅁䙁䅁䅁䅁䅄留䅚允䅁䅁䅅䅁䙁䭁睒児塲⭯⽧䍄䉁䅁䅁兂䅁䅁䅍䅄䅁䅁䅯䅁䅁䅁䅯允䅁䅁䅯兂䅁䅁䅕䅁䅁佁㑄唵䉁䅁䅁允䅁䅁䅕䉵䘶ㄶ㑇樳䴸䅉䅅䅁䙁䅁䅁睁䵁䅁䅁权䅁䅁䅁权呂䅁䅁权䙁䅁䅁兂䅁䅁䅁䝁浌䅑䅅䅁䉁䅁䅁兂煃搸乊瑙穁䅑杷允䅁䅁䅕䅁䑁䅁䅷䅁䭁䉁䄰䅁䭁䅁䅅䅁䭁䅁䅕䅁䙁䅁䅁䅁䅁佅䅚允䅁䅁䅅䅁䙁䉁䘫ㄶ㑇瑈⽕䍄䉁䅁䅁兂䅁䅁䅍䅄䅁䅁䅯䅁䅁䅁䅯睕䅁䅁䅯兂䅁䅁䅕䅁䅁䥁瑁欵䉁䅁䅁允䅁䅁䅕扌摋㘷䝥き䵁䅉䅅䅁䕁䅁䅁睁䵁䅁䅁权偂䅁䅁权佂䅁䅁兂䅁䅁䅁乷汈䅑䅅䅁䉁䅁䅁兂䥂場啯歲䡣䅑杷允䅁䅁䅑䅁䑁䅁䅷䅁䭁䕁䄸䅁䭁䕁䄴䅁䙁䅁䅁䅁杄敄䅚允䅁䅁䅅䅁䙁䑁䬰㘱睎剐䅊䍄䉁䅁䅁兂䅁䅁䅍䅄䅁䅁䅯先䅁䅁䅯睕䅁䅁䅯兂䅁䅁䅕䅁䅁䵁瑁欵䉁䅁䅁允䅁䅁䅕杖琴灳瘳歌䵁䅉䅅䅁䙁䅁䅁睁䵁䅁䅁权晁䅁䅁权呂䅁䅁权䙁䅁䅁兂䅁䅁䅁䍯浺䅑䅅䅁䉁䅁䅁兂⽁噎㘶卓硷䅑杷允䅁䅁䅕䅁䑁䅁䅷䅁䭁䉁䅷䅁䭁䙁䅍䅁䭁䅁䅕䅁䙁䅁䅁䅁杁畉䅚允䅁䅁䅅䅁䙁䥁䌯匹捨祄䄵䍄䉁䅁䅁兂䅁䅁䅍䅄䅁䅁䅯先䅁䅁䅯睕䅁䅁䅯兂䅁䅁䅕䅁䅁䍁牄唵䉁䅁䅁允䅁䅁䅕灰䕶䱉祃啌䵁䅉䅅䅁䙁䅁䅁睁䵁䅁䅁权晁䅁䅁权呂䅁䅁权䙁䅁䅁兂䅁䅁䅁䉧浢䅑䅅䅁䉁䅁䅁兂䝂癴㥐倱睧䅑杷允䅁䅁䅑䅁䑁䅁䅷䅁䭁䕁䄸䅁䭁䕁䄴䅁䙁䅁䅁䅁杁畇䅚允䅁䅁䅅䅁䙁䙁㑋潈牘剕䅆䍄䉁䅁䅁兂䅁䅁䅍䅄䅁䅁䅯䅁䅁䅁䅯允䅁䅁䅯兂䅁䅁䅕䅁䅁䭁瑄唵䉁䅁䅁允䅁䅁䅕敨剴䉵䘶稲䴸䅉䅅䅁䕁䅁䅁睁䵁䅁䅁权偂䅁䅁权佂䅁䅁兂䅁䅁䅁义氳䅑䅅䅁䉁䅁䅁兂慃婭婭婭䡫䅑杷允䅁䅁䅕䅁䑁䅁䅷䅁䭁䉁䅷䅁䭁䙁䅍䅁䭁䅁䅕䅁䙁䅁䅁䅁䅁⭆䅚允䅁䅁䅅䅁䙁䙁㘶兓䍷祱䄱䍄䉁䅁䅁兂䅁䅁䅍䅄䅁䅁䅯杈䅁䅁䅯睕䅁䅁䅯兂䅁䅁䅕䅁䅁䭁䑂欵䉁䅁䅁允䅁䅁䅕倹唳佥浬䕊䵁䅉䅅䅁䕁䅁䅁睁䵁䅁䅁权偂䅁䅁权佂䅁䅁兂䅁䅁䅁䑧浔䅑䅅䅁䉁䅁䅁兂獄払敧敨剳䅑杷允䅁䅁䅕䅁䑁䅁䅷䅁䭁䉁䄰䅁䭁䅁䅅䅁䭁䅁䅕䅁䙁䅁䅁䅁䅁佌䅚允䅁䅁䅅䅁䙁䝁浚浚浚瑚⽙䍄䉁䅁䅁兂䅁䅁䅍䅄䅁䅁䅯睈䅁䅁䅯允䅁䅁䅯兂䅁䅁䅕䅁䅁佁療欵䉁䅁䅁允䅁䅁䅕牕敧敨剴䐴䴸䅉䅅䅁䕁䅁䅁睁䵁䅁䅁权偂䅁䅁权佂䅁䅁兂䅁䅁䅁䍙浄䅑䅅䅁䉁䅁䅁兂䑄匹捨㡪光䅑杷允䅁䅁䅕䅁䑁䅁䅷䅁䭁䉁䅯䅁䭁䅁䅅䅁䭁䅁䅕䅁䙁䅁䅁䅁杄⭋䅚允䅁䅁䅅䅁䙁䭁睒児塲⭯⽧䍄䉁䅁䅁兂䅁䅁䅍䅄䅁䅁䅯先䅁䅁䅯睕䅁䅁䅯兂䅁䅁䅕䅁䅁䭁䵄唵䉁䅁䅁允䅁䅁䅕噋偹癷潕歌䵁䅉䅅䅁䙁䅁䅁睁䵁䅁䅁权摁䅁䅁权呂䅁䅁权䙁䅁䅁兂䅁䅁䅁䱯氷䅑䅅䅁䉁䅁䅁兂䵂㑎䉬余瑕䅑杷允䅁䅁䅕䅁䑁䅁䅷䅁䭁䉁䄰䅁䭁䙁䅍䅁䭁䅁䅕䅁䙁䅁䅁䅁䅂畑䅚允䅁䅁䅅䅁䙁䕁㉡⼸唳䍵䄵䍄䉁䅁䅁兂䅁䅁䅍䅄䅁䅁䅯杈䅁䅁䅯允䅁䅁䅯兂䅁䅁䅕䅁䅁䥁慃唵䉁䅁䅁允䅁䅁䅕積積積積稰䴸䅉䅅䅁䙁䅁䅁睁䵁䅁䅁权敁䅁䅁权呂䅁䅁权䙁䅁䅁兂䅁䅁䅁乁汔䅑䅅䅁䉁䅁䅁兂汁潂噇㑑獳䅑杷允䅁䅁䅑䅁䑁䅁䅷䅁䭁䕁䄸䅁䭁䕁䄴䅁䙁䅁䅁䅁䅂⭎䅚允䅁䅁䅅䅁䙁䅁塲㍯㥁桃䅆䍄䉁䅁䅁䅂䅁䅁䅍䅄䅁䅁䅯睔䅁䅁䅯杔䅁䅁䅕䅁䅁䥁奃唵䉁䅁䅁允䅁䅁䅕⽷潕䥘䌯呸䴸䅉䅅䅁䙁䅁䅁睁䵁䅁䅁权敁䅁䅁权呂䅁䅁权䙁䅁䅁兂䅁䅁䅁䩯氷䅑䅅䅁䉁䅁䅁兂橁⼲⭬湡煷䅑杷允䅁䅁䅑䅁䑁䅁䅷䅁䭁䕁䄸䅁䭁䕁䄴䅁䙁䅁䅁䅁䅂伶䅖允䅁䅁䅅䅁䙁佁剸䉵䘶砶䅆䍄䉁䅁䅁兂䅁䅁䅍䅄䅁䅁䅯䅁䅁䅁䅯睕䅁䅁䅯兂䅁䅁䅕䅁䅁䭁奁欵䉁䅁䅁允䅁䅁䅕硢䑋䵷䉯き䵁䅉䅅䅁䕁䅁䅁睁䵁䅁䅁权偂䅁䅁权佂䅁䅁兂䅁䅁䅁䙧浘䅑䅅䅁䉁䅁䅁兂䭁㘱睎児兯䅑杷允䅁䅁䅕䅁䑁䅁䅷䅁䭁䅁䅁䅁䭁䅁䅅䅁䭁䅁䅕䅁䙁䅁䅁䅁䅃整䅖允䅁䅁䅅䅁䙁䩁婱婭婭摭⽫䍄䉁䅁䅁䅂䅁䅁䅍䅄䅁䅁䅯睔䅁䅁䅯杔䅁䅁䅕䅁䅁䅁䩄唵䉁䅁䅁允䅁䅁䅕歲桦桥畓稫䴸䅉䅅䅁䙁䅁䅁睁䵁䅁䅁权慁䅁䅁权呂䅁䅁权䙁䅁䅁兂䅁䅁䅁䱯汦䅑䅅䅁䉁䅁䅁兂⽁噎㘶敓㕷䅑杷允䅁䅁䅕䅁䑁䅁䅷䅁䭁䅁䅁䅁䭁䅁䅅䅁䭁䅁䅕䅁䙁䅁䅁䅁杁⭸䅖允䅁䅁䅅䅁䙁䑁䬰㘱睎摐⽯䍄䉁䅁䅁兂䅁䅁䅍䅄䅁䅁䅯杈䅁䅁䅯睕䅁䅁䅯兂䅁䅁䅕䅁䅁䝁㙁欵䉁䅁䅁允䅁䅁䅕倹唳佥浬䕊䵁䅉䅅䅁䕁䅁䅁睁䵁䅁䅁权偂䅁䅁权佂䅁䅁兂䅁䅁䅁偙汪䅑䅅䅁䉁䅁䅁兂㥁瑃橥䑣到䅑杷允䅁䅁䅕䅁䑁䅁䅷䅁䭁䉁䄰䅁䭁䅁䅅䅁䭁䅁䅕䅁䙁䅁䅁䅁䅄畒䅚允䅁䅁䅅䅁䙁䭁䠵場啯瑲⽣䍄䉁䅁䅁兂䅁䅁䅍䅄䅁䅁䅯杇䅁䅁䅯允䅁䅁䅯兂䅁䅁䅕䅁䅁佁啂欵䉁䅁䅁允䅁䅁䅕䡰㥁瑃橥䐶䴸䅉䅅䅁䕁䅁䅁睁䵁䅁䅁权偂䅁䅁权佂䅁䅁兂䅁䅁䅁䡷浐䅑䅅䅁䉁䅁䅁兂䅁䅁䅁䅁䵁䅑杷允䅁䅁䅕䅁䑁䅁䅷䅁䭁䉁䄴䅁䭁䙁䅍䅁䭁䅁䅕䅁䙁䅁䅁䅁䅁但䅚允䅁䅁䅅䅁䙁䝁匸㡧䭄匴䅬䍄䉁䅁䅁兂䅁䅁䅍䅄䅁䅁䅯䅁䅁䅁䅯允䅁䅁䅯兂䅁䅁䅕䅁䅁䍁睂欵䉁䅁䅁允䅁䅁䅕䉵䘶ㄶ㑇樳䴸䅉䅅䅁䕁䅁䅁睁䵁䅁䅁权偂䅁䅁权佂䅁䅁兂䅁䅁䅁临汦䅑䅅䅁䉁䅁䅁兂㉄䙋偹癷䥕䅑杷允䅁䅁䅑䅁䑁䅁䅷䅁䭁䕁䄸䅁䭁䕁䄴䅁䙁䅁䅁䅁杁敏䅚允䅁䅁䅅䅁䙁佁㙆䭆䠵儴䄵䍄䉁䅁䅁䅂䅁䅁䅍䅄䅁䅁䅯睔䅁䅁䅯杔䅁䅁䅕䅁䅁䅁桁欵䉁䅁䅁允䅁䅁䅕浚浚浚浚䕅䵁䅉䅅䅁䙁䅁䅁睁䵁䅁䅁权摁䅁䅁权呂䅁䅁权䙁䅁䅁兂䅁䅁䅁䱉汌䅑䅅䅁䉁䅁䅁兂䭁㘱睎捐瑯䅑杷允䅁䅁䅕䅁䑁䅁䅷䅁䭁䉁䄴䅁䭁䅁䅅䅁䭁䅁䅕䅁䙁䅁䅁䅁杁佡䅚允䅁䅁䅅䅁䙁䅁䅁䅁䅁乁⽁䍄䉁䅁䅁䅂䅁䅁䅍䅄䅁䅁䅯杇䅁䅁䅯䅔䅁䅁䅯䅉䅁䅁䅅䅁䉁䅁䅁兂穁積積㍍㑍䅑杷允䅁䅁䅕䅁䑁䅁䅷䅁䭁䉁䄰䅁䭁䅁䅅䅁䭁䅁䅕䅁䙁䅁䅁䅁杂佒䅚允䅁䅁䅅䅁䙁䭁䠵場啯瑲⽣䍄䉁䅁䅁䅂䅁䅁䅍䅄䅁䅁䅯睔䅁䅁䅯杔䅁䅁䅕䅁䅁佁䝁欵䉁䅁䅁允䅁䅁䅕児塲㍯㥁歅䵁䅉䅅䅁䙁䅁䅁睁䵁䅁䅁权慁䅁䅁权呂䅁䅁权䙁䅁䅁兂䅁䅁䅁䍧浘䅑䅅䅁䉁䅁䅁兂䥂場啯煲㙣䅑杷允䅁䅁䅕䅁䑁䅁䅷䅁䭁䅁䅁䅁䭁䙁䅍䅁䭁䅁䅕䅁䙁䅁䅁䅁杁敁䅚允䅁䅁䅅䅁䙁䭁硲欰椱䑣䅊䍄䉁䅁䅁䅂䅁䅁䅍䅄䅁䅁䅯睔䅁䅁䅯杔䅁䅁䅕䅁䅁佁歃唵䉁䅁䅁允䅁䅁䅕㘱睎児塲稰䴸䅉䅅䅁䕁䅁䅁睁䵁䅁䅁权偂䅁䅁权佂䅁䅁兂䅁䅁䅁䕷浮䅑䅅䅁䉁䅁䅁兂䥂場啯歲剣䅑杷允䅁䅁䅕䅁䑁䅁䅷䅁䭁䅁䅁䅁䭁䅁䅅䅁䭁䅁䅕䅁䙁䅁䅁䅁杄⭆䅚允䅁䅁䅅䅁䙁䱁敧敨剴乵⼴䍄䉁䅁䅁兂䅁䅁䅍䅄䅁䅁䅯先䅁䅁䅯睕䅁䅁䅯兂䅁䅁䅕䅁䅁䝁婄唵䉁䅁䅁允䅁䅁䅕⽷潕䥘䌯啌䵁䅉䅅䅁䕁䅁䅁睁䵁䅁䅁权晁䅁䅁权䵂䅁䅁权杁䅁䅁允䅁䅁䅅䅁䙁偁潙䥘䌯呎䅊䍄䉁䅁䅁䅂䅁䅁䅍䅄䅁䅁䅯睔䅁䅁䅯杔䅁䅁䅕䅁䅁䭁㑁欵䉁䅁䅁允䅁䅁䅕歲桦桥畓啄䵁䅉䅅䅁䙁䅁䅁睁䵁䅁䅁权敁䅁䅁权呂䅁䅁权䙁䅁䅁兂䅁䅁䅁䑯浈䅑䅅䅁䉁䅁䅁兂䥂場啯歲浣䅑杷允䅁䅁䅑䅁䑁䅁䅷䅁䭁䕁䄸䅁䭁䕁䄴䅁䙁䅁䅁䅁杂⭕䅚允䅁䅁䅅䅁䙁䅁塲㍯㥁桃䅂䍄䉁䅁䅁兂䅁䅁䅍䅄䅁䅁䅯杇䅁䅁䅯允䅁䅁䅯兂䅁䅁䅕䅁䅁䵁硁欵䉁䅁䅁允䅁䅁䅕䡰㥁瑃橥䐶䴸䅉䅅䅁䙁䅁䅁睁䵁䅁䅁权敁䅁䅁权䉁䅁䅁权䙁䅁䅁兂䅁䅁䅁䝧浺䅑䅅䅁䉁䅁䅁兂䅁䅁䅁䅁兄睐杷允䅁䅁䅑䅁䑁䅁䅷䅁䭁䕁䄸䅁䭁䕁䄴䅁䙁䅁䅁䅁䅄佹䅖允䅁䅁䅅䅁䙁乁橥䑣䬰⼱⽳䍄䉁䅁䅁兂䅁䅁䅍䅄䅁䅁䅯䅁䅁䅁䅯允䅁䅁䅯兂䅁䅁䅕䅁䅁䵁㝃唵䉁䅁䅁允䅁䅁䅕児塲㍯㥁樲䴸䅉䅅䅁䙁䅁䅁睁䵁䅁䅁权敁䅁䅁权䉁䅁䅁权䙁䅁䅁兂䅁䅁䅁䝯浢䅑䅅䅁䉁䅁䅁兂䅁䅁䅁䅁兄睐杷允䅁䅁䅕䅁䑁䅁䅷䅁䭁䅁䅁䅁䭁䅁䅅䅁䭁䅁䅕䅁䙁䅁䅁䅁䅃⭙䅚允䅁䅁䅅䅁䙁䱁敧敨剴乵⼴䍄䉁䅁䅁兂䅁䅁䅍䅄䅁䅁䅯睈䅁䅁䅯睕䅁䅁䅯兂䅁䅁䅕䅁䅁䥁权唵䉁䅁䅁允䅁䅁䅕䵮村䡳潉啍䵁䅉䅅䅁䕁䅁䅁睁䵁䅁䅁权偂䅁䅁权佂䅁䅁兂䅁䅁䅁䉑浲䅑䅅䅁䉁䅁䅁兂卂䉵䘶ㄶ剅䅑杷允䅁䅁䅕䅁䑁䅁䅷䅁䭁䉁䄰䅁䭁䙁䅍䅁䭁䅁䅕䅁䙁䅁䅁䅁䅁⭳䅖允䅁䅁䅅䅁䙁䅁塲㍯㥁楹䄱䍄䉁䅁䅁䅂䅁䅁䅍䅄䅁䅁䅯睔䅁䅁䅯杔䅁䅁䅕䅁䅁䕁佄唵䉁䅁䅁允䅁䅁䅕体㙆䭆䠵啂䵁䅉䅅䅁䙁䅁䅁睁䵁䅁䅁权䅁䅁䅁权䉁䅁䅁权䙁䅁䅁兂䅁䅁䅁䙙洷䅑䅅䅁䉁䅁䅁兂㑃潈牘払敪睐杷允䅁䅁䅕䅁䑁䅁䅷䅁䭁䅁䅁䅁䭁䅁䅅䅁䭁䅁䅕䅁䙁䅁䅁䅁权效䅚允䅁䅁䅅䅁䙁䱁敧敨剴乵⼴䍄䉁䅁䅁兂䅁䅁䅍䅄䅁䅁䅯杇䅁䅁䅯允䅁䅁䅯兂䅁䅁䅕䅁䅁䭁穂欵䉁䅁䅁允䅁䅁䅕䡰㥁瑃橥䐶䴸䅉䅅䅁䙁䅁䅁睁䵁䅁䅁权䅁䅁䅁权呂䅁䅁权䙁䅁䅁兂䅁䅁䅁䙑浲䅑䅅䅁䉁䅁䅁兂煃搸乊瑙穁䅑杷允䅁䅁䅑䅁䑁䅁䅷䅁䭁䕁䄸䅁䭁䕁䄴䅁䙁䅁䅁䅁䅂畒䅚允䅁䅁䅅䅁䙁䕁桪桥畓硒䅆䍄䉁䅁䅁兂䅁䅁䅍䅄䅁䅁䅯睈䅁䅁䅯允䅁䅁䅯兂䅁䅁䅕䅁䅁䍁桁欵䉁䅁䅁允䅁䅁䅕椹捨㡪ㅌ䐴䴸䅉䅅䅁䙁䅁䅁睁䵁䅁䅁权摁䅁䅁权䉁䅁䅁权䙁䅁䅁兂䅁䅁䅁䉷浶䅑䅅䅁䉁䅁䅁兂晁敨剴䉵嘷睐杷允䅁䅁䅕䅁䑁䅁䅷䅁䭁䅁䅁䅁䭁䙁䅍䅁䭁䅁䅕䅁䙁䅁䅁䅁䅄畹䅖允䅁䅁䅅䅁䙁䝁渳㘫确樸䅊䍄䉁䅁䅁兂䅁䅁䅍䅄䅁䅁䅯睈䅁䅁䅯睕䅁䅁䅯兂䅁䅁䅕䅁䅁䍁歃唵䉁䅁䅁允䅁䅁䅕䉵䘶ㄶ㑆䕍䵁䅉䅅䅁䕁䅁䅁睁䵁䅁䅁权偂䅁䅁权佂䅁䅁兂䅁䅁䅁䡯浄䅑䅅䅁䉁䅁䅁兂䅁䅁䅁䅁䵁䅑杷允䅁䅁䅕䅁䑁䅁䅷䅁䭁䉁䄴䅁䭁䙁䅍䅁䭁䅁䅕䅁䙁䅁䅁䅁杂⭌䅚允䅁䅁䅅䅁䙁䕁桪桥畓祒䅚䍄䉁䅁䅁兂䅁䅁䅍䅄䅁䅁䅯杇䅁䅁䅯允䅁䅁䅯兂䅁䅁䅕䅁䅁䕁⽁欵䉁䅁䅁允䅁䅁䅕䡰㥁瑃橥䐶䴸䅉䅅䅁䙁䅁䅁睁䵁䅁䅁权摁䅁䅁权呂䅁䅁权䙁䅁䅁兂䅁䅁䅁䡁浄䅑䅅䅁䉁䅁䅁兂㍁啩杆刵畁䅑杷允䅁䅁䅕䅁䑁䅁䅷䅁䭁䉁䄰䅁䭁䙁䅍䅁䭁䅁䅕䅁䙁䅁䅁䅁杂畲䅖允䅁䅁䅅䅁䙁乁佮ㄹ橐印䄱䍄䉁䅁䅁兂䅁䅁䅍䅄䅁䅁䅯先䅁䅁䅯睕䅁䅁䅯兂䅁䅁䅕䅁䅁䅁灁欵䉁䅁䅁允䅁䅁䅕浚浚浚浢歌䵁䅉䅅䅁䕁䅁䅁睁䵁䅁䅁权偂䅁䅁权佂䅁䅁兂䅁䅁䅁䙷浘䅑䅅䅁䉁䅁䅁兂䭁㘱睎児兯䅑杷允䅁䅁䅑䅁䑁䅁䅷䅁䭁䕁䄸䅁䭁䕁䄴䅁䙁䅁䅁䅁杂整䅖允䅁䅁䅅䅁䙁䵁䴳䵺䵺乺⽷䍄䉁䅁䅁䅂䅁䅁䅍䅄䅁䅁䅯睔䅁䅁䅯杔䅁䅁䅕䅁䅁佁乂欵䉁䅁䅁允䅁䅁䅕䥘䌯匹捨啅䵁䅉䅅䅁䙁䅁䅁睁䵁䅁䅁权晁䅁䅁权䉁䅁䅁权䙁䅁䅁兂䅁䅁䅁䡷浌䅑䅅䅁䉁䅁䅁兂卂䉵䘶ㄶ杈睐杷允䅁䅁䅑䅁䑁䅁䅷䅁䭁䕁䄸䅁䭁䕁䄴䅁䙁䅁䅁䅁杁散䅚允䅁䅁䅅䅁䙁䵁䴳䵺䵺䅺䅸䍄䉁䅁䅁兂䅁䅁䅍䅄䅁䅁䅯先䅁䅁䅯允䅁䅁䅯兂䅁䅁䅕䅁䅁䭁䩄唵䉁䅁䅁允䅁䅁䅕㘱睎児塲稰䴸䅉䅅䅁䕁䅁䅁睁䵁䅁䅁权偂䅁䅁权佂䅁䅁兂䅁䅁䅁䵙汔䅑䅅䅁䉁䅁䅁兂慃婭婭婭ㅮ睐杷允䅁䅁䅑䅁䑁䅁䅷䅁䭁䕁䄸䅁䭁䕁䄴䅁䙁䅁䅁䅁权敃䅚允䅁䅁䅅䅁䙁佁㙆䭆䠵刴䅆䍄䉁䅁䅁兂䅁䅁䅍䅄䅁䅁䅯先䅁䅁䅯睕䅁䅁䅯兂䅁䅁䅕䅁䅁䕁畄唵䉁䅁䅁允䅁䅁䅕灰䕶䱉祃啌䵁䅉䅅䅁䙁䅁䅁睁䵁䅁䅁权摁䅁䅁权呂䅁䅁权䙁䅁䅁兂䅁䅁䅁䔴浘䅑䅅䅁䉁䅁䅁兂ㅂ硫䕧潖甴䅑杷允䅁䅁䅕䅁䑁䅁䅷䅁䭁䅁䅁䅁䭁䙁䅍䅁䭁䅁䅕䅁䙁䅁䅁䅁䅁⭢䅚允䅁䅁䅅䅁䙁䙁橔婰䕶䐴䅎䍄䉁䅁䅁兂䅁䅁䅍䅄䅁䅁䅯先䅁䅁䅯睕䅁䅁䅯兂䅁䅁䅕䅁䅁䥁煃唵䉁䅁䅁允䅁䅁䅕挲㌷⭕汏啌䵁䅉䅅䅁䕁䅁䅁睁䵁䅁䅁权偂䅁䅁权佂䅁䅁兂䅁䅁䅁䡙洳䅑䅅䅁䉁䅁䅁兂偃癷潕䥘䴸䅑杷允䅁䅁䅕䅁䑁䅁䅷䅁䭁䉁䄰䅁䭁䅁䅅䅁䭁䅁䅕䅁䙁䅁䅁䅁䅃佋䅚允䅁䅁䅅䅁䙁䝁浚浚浚瑚⽙䍄䉁䅁䅁兂䅁䅁䅍䅄䅁䅁䅯先䅁䅁䅯睕䅁䅁䅯兂䅁䅁䅕䅁䅁䅁⽂欵䉁䅁䅁允䅁䅁䅕䉲慸䑚晵啌䵁䅉䅅䅁䕁䅁䅁睁䵁䅁䅁权偂䅁䅁权佂䅁䅁兂䅁䅁䅁䵉汘䅑䅅䅁䉁䅁䅁兂䅁䅁䅁䅁い睐杷允䅁䅁䅑䅁䑁䅁䅷䅁䭁䕁䄸䅁䭁䕁䄴䅁䙁䅁䅁䅁杂畃䅚允䅁䅁䅅䅁䙁䕁桪桥畓硒䅊䍄䉁䅁䅁䅂䅁䅁䅍䅄䅁䅁䅯睔䅁䅁䅯杔䅁䅁䅕䅁䅁䭁時欵䉁䅁䅁允䅁䅁䅕積積積積い䵁䅉䅅䅁䙁䅁䅁睁䵁䅁䅁权慁䅁䅁权䉁䅁䅁权䙁䅁䅁兂䅁䅁䅁䩯汔䅑䅅䅁䉁䅁䅁兂䅁䅁䅁䅁杄睐杷允䅁䅁䅕䅁䑁䅁䅷䅁䭁䉁䅷䅁䭁䙁䅍䅁䭁䅁䅕䅁䙁䅁䅁䅁䅄⭦䅚允䅁䅁䅅䅁䙁䵁㉬灶愸祲䄱䍄䉁䅁䅁兂䅁䅁䅍䅄䅁䅁䅯先䅁䅁䅯允䅁䅁䅯兂䅁䅁䅕䅁䅁䥁杄唵䉁䅁䅁允䅁䅁䅕㘱睎児塲稰䴸䅉䅅䅁䕁䅁䅁睁䵁䅁䅁权䅁䅁䅁权䵂䅁䅁权杁䅁䅁允䅁䅁䅅䅁䙁䕁桪桥畓穒䅊䍄䉁䅁䅁兂䅁䅁䅍䅄䅁䅁䅯䅁䅁䅁䅯睕䅁䅁䅯兂䅁䅁䅕䅁䅁䅁䡂欵䉁䅁䅁允䅁䅁䅕潅䅐煹䙈き䵁䅉䅅䅁䙁䅁䅁睁䵁䅁䅁权敁䅁䅁权呂䅁䅁权䙁䅁䅁兂䅁䅁䅁䘴洳䅑䅅䅁䉁䅁䅁兂剃堷⽷噎椴䅑杷允䅁䅁䅕䅁䑁䅁䅷䅁䭁䅁䅁䅁䭁䙁䅍䅁䭁䅁䅕䅁䙁䅁䅁䅁杄⭚䅚允䅁䅁䅅䅁䙁䙁橔婰䕶䐴䅎䍄䉁䅁䅁兂䅁䅁䅍䅄䅁䅁䅯杈䅁䅁䅯允䅁䅁䅯兂䅁䅁䅕䅁䅁䕁⭃唵䉁䅁䅁允䅁䅁䅕積積積積稰䴸䅉䅅䅁䙁䅁䅁睁䵁䅁䅁权慁䅁䅁权呂䅁䅁权䙁䅁䅁兂䅁䅁䅁䡉浈䅑䅅䅁䉁䅁䅁兂癁匳䝑噧㝕䅑杷允䅁䅁䅕䅁䑁䅁䅷䅁䭁䉁䅷䅁䭁䙁䅍䅁䭁䅁䅕䅁䙁䅁䅁䅁杄敔䅚允䅁䅁䅅䅁䙁䝁匸㡧䭄卙䄵䍄䉁䅁䅁䅂䅁䅁䅍䅄䅁䅁䅯睔䅁䅁䅯杔䅁䅁䅕䅁䅁䭁奃唵䉁䅁䅁允䅁䅁䅕瑃橥䑣䬰穸䴸䅉䅅䅁䕁䅁䅁睁䵁䅁䅁权偂䅁䅁权佂䅁䅁兂䅁䅁䅁䑙洳䅑䅅䅁䉁䅁䅁兂䑄匹捨㡪䱉䅑杷允䅁䅁䅑䅁䑁䅁䅷䅁䭁䕁䄸䅁䭁䕁䄴䅁䙁䅁䅁䅁杂⭆䅚允䅁䅁䅅䅁䙁䑁積積積硍䅎䍄䉁䅁䅁䅂䅁䅁䅍䅄䅁䅁䅯睔䅁䅁䅯杔䅁䅁䅕䅁䅁䕁㍂欵䉁䅁䅁允䅁䅁䅕児塲㍯㥁䕄䵁䅉䅅䅁䙁䅁䅁睁䵁䅁䅁权摁䅁䅁权䉁䅁䅁权䙁䅁䅁兂䅁䅁䅁偁汶䅑䅅䅁䉁䅁䅁兂晁敨剴䉵嘷睐杷允䅁䅁䅕䅁䑁䅁䅷䅁䭁䉁䅯䅁䭁䙁䅍䅁䭁䅁䅕䅁䙁䅁䅁䅁䅃畅䅚允䅁䅁䅅䅁䙁䅁䉡啬䱏䑔䅰䍄䉁䅁䅁兂䅁䅁䅍䅄䅁䅁䅯䅈䅁䅁䅯睕䅁䅁䅯兂䅁䅁䅕䅁䅁䍁歄唵䉁䅁䅁允䅁䅁䅕桙奂扏䥒歌䵁䅉䅅䅁䙁䅁䅁睁䵁䅁䅁权捁䅁䅁权䉁䅁䅁权䙁䅁䅁兂䅁䅁䅁䭁汐䅑䅅䅁䉁䅁䅁兂偃癷潕䥘匯睐杷允䅁䅁䅑䅁䑁䅁䅷䅁䭁䕁䄸䅁䭁䕁䄴䅁䙁䅁䅁䅁䅄佡䅚允䅁䅁䅅䅁䙁䡁㥅瑃橥䅣䄱䍄䉁䅁䅁兂䅁䅁䅍䅄䅁䅁䅯䅁䅁䅁䅯睕䅁䅁䅯兂䅁䅁䅕䅁䅁䕁䵁欵䉁䅁䅁允䅁䅁䅕䙅㕧䵴坩歍䵁䅉䅅䅁䙁䅁䅁睁䵁䅁䅁权晁䅁䅁权呂䅁䅁权䙁䅁䅁兂䅁䅁䅁䔴浦䅑䅅䅁䉁䅁䅁兂䕁杖琴桳砰䅑杷允䅁䅁䅑䅁䑁䅁䅷䅁䭁䕁䄸䅁䭁䕁䄴䅁䙁䅁䅁䅁䅄敥䅚允䅁䅁䅅䅁䙁䡁啳歲桦来䅸䍄䉁䅁䅁兂䅁䅁䅍䅄䅁䅁䅯杇䅁䅁䅯睕䅁䅁䅯兂䅁䅁䅕䅁䅁䥁奃唵䉁䅁䅁允䅁䅁䅕瑃橥䑣焳䕏䵁䅉䅅䅁䙁䅁䅁睁䵁䅁䅁权䅁䅁䅁权呂䅁䅁权䙁䅁䅁兂䅁䅁䅁䩁汦䅑䅅䅁䉁䅁䅁兂㡃䩤奍䡂睙䅑杷允䅁䅁䅕䅁䑁䅁䅷䅁䭁䉁䅯䅁䭁䅁䅅䅁䭁䅁䅕䅁䙁䅁䅁䅁䅂佲䅖允䅁䅁䅅䅁䙁䅁䅁䅁䅁佁⽁䍄䉁䅁䅁兂䅁䅁䅍䅄䅁䅁䅯䅈䅁䅁䅯睕䅁䅁䅯兂䅁䅁䅕䅁䅁䥁䩂欵䉁䅁䅁允䅁䅁䅕硢䑋䵷桰歌䵁䅉䅅䅁䙁䅁䅁睁䵁䅁䅁权晁䅁䅁权䉁䅁䅁权䙁䅁䅁兂䅁䅁䅁䡷洯䅑䅅䅁䉁䅁䅁兂卂䉵䘶ㄶ杈睐杷允䅁䅁䅕䅁䑁䅁䅷䅁䭁䉁䄰䅁䭁䅁䅅䅁䭁䅁䅕䅁䙁䅁䅁䅁䅁敍䅚允䅁䅁䅅䅁䙁䭁䠵場啯瑲⽣䍄䉁䅁䅁䅂䅁䅁䅍䅄䅁䅁䅯䅈䅁䅁䅯䅔䅁䅁䅯䅉䅁䅁䅅䅁䉁䅁䅁兂㥁瑃橥䑣瀰䅑杷允䅁䅁䅕䅁䑁䅁䅷䅁䭁䅁䅁䅁䭁䅁䅅䅁䭁䅁䅕䅁䙁䅁䅁䅁杁⭎䅚允䅁䅁䅅䅁䙁䱁敧敨剴乵⼴䍄䉁䅁䅁䅂䅁䅁䅍䅄䅁䅁䅯睔䅁䅁䅯杔䅁䅁䅕䅁䅁䭁㉃唵䉁䅁䅁允䅁䅁䅕椹捨㡪ㅌ䐴䴸䅉䅅䅁䙁䅁䅁睁䵁䅁䅁权敁䅁䅁权䉁䅁䅁权䙁䅁䅁兂䅁䅁䅁䑑浢䅑䅅䅁䉁䅁䅁兂䑄匹捨㡪噌睐杷允䅁䅁䅕䅁䑁䅁䅷䅁䭁䅁䅁䅁䭁䙁䅍䅁䭁䅁䅕䅁䙁䅁䅁䅁䅂⭊䅚允䅁䅁䅅䅁䙁佁兘瑉㕶橐䅎䍄䉁䅁䅁兂䅁䅁䅍䅄䅁䅁䅯先䅁䅁䅯允䅁䅁䅯兂䅁䅁䅕䅁䅁䵁㥃唵䉁䅁䅁允䅁䅁䅕㘱睎児塲稰䴸䅉䅅䅁䙁䅁䅁睁䵁䅁䅁权䅁䅁䅁权呂䅁䅁权䙁䅁䅁兂䅁䅁䅁䙑浈䅑䅅䅁䉁䅁䅁兂㕁䵴㉨瑶稸䅑杷允䅁䅁䅑䅁䑁䅁䅷䅁䭁䕁䄸䅁䭁䕁䄴䅁䙁䅁䅁䅁权畭䅖允䅁䅁䅅䅁䙁佁㙆䭆䠵挴⽯䍄䉁䅁䅁兂䅁䅁䅍䅄䅁䅁䅯先䅁䅁䅯允䅁䅁䅯兂䅁䅁䅕䅁䅁䥁佂欵䉁䅁䅁允䅁䅁䅕歲桦桥畓稱䴸䅉䅅䅁䙁䅁䅁睁䵁䅁䅁权晁䅁䅁权䉁䅁䅁权䙁䅁䅁兂䅁䅁䅁䴴氳䅑䅅䅁䉁䅁䅁兂歃䑣䬰㘱材睐杷允䅁䅁䅑䅁䑁䅁䅷䅁䭁䕁䄸䅁䭁䕁䄴䅁䙁䅁䅁䅁权佳䅖允䅁䅁䅅䅁䙁䍁捬㡪ㅌ之⽷䍄䉁䅁䅁兂䅁䅁䅍䅄䅁䅁䅯杇䅁䅁䅯允䅁䅁䅯兂䅁䅁䅕䅁䅁佁煄唵䉁䅁䅁允䅁䅁䅕積積積積稴䴸䅉䅅䅁䙁䅁䅁睁䵁䅁䅁权摁䅁䅁权䉁䅁䅁权䙁䅁䅁兂䅁䅁䅁䭙氯䅑䅅䅁䉁䅁䅁兂塄㍯㥁瑃呦睐杷允䅁䅁䅕䅁䑁䅁䅷䅁䭁䅁䅁䅁䭁䙁䅍䅁䭁䅁䅕䅁䙁䅁䅁䅁䅂敤䅚允䅁䅁䅅䅁䙁䙁橔婰䕶䑁䅒䍄䉁䅁䅁兂䅁䅁䅍䅄䅁䅁䅯䅈䅁䅁䅯允䅁䅁䅯兂䅁䅁䅕䅁䅁䍁桁欵䉁䅁䅁允䅁䅁䅕歲桦桥畓稱䴸䅉䅅䅁䕁䅁䅁睁䵁䅁䅁权偂䅁䅁权佂䅁䅁兂䅁䅁䅁䙉浺䅑䅅䅁䉁䅁䅁兂慃婭婭婭偫䅑杷允䅁䅁䅕䅁䑁䅁䅷䅁䭁䅁䅁䅁䭁䙁䅍䅁䭁䅁䅕䅁䙁䅁䅁䅁杁當䅖允䅁䅁䅅䅁䙁偁周㘴扗䑨䅊䍄䉁䅁䅁兂䅁䅁䅍䅄䅁䅁䅯䅁䅁䅁䅯允䅁䅁䅯兂䅁䅁䅕䅁䅁䝁楃唵䉁䅁䅁允䅁䅁䅕灭婭婭婭吲䴸䅉䅅䅁䙁䅁䅁睁䵁䅁䅁权慁䅁䅁权䉁䅁䅁权䙁䅁䅁兂䅁䅁䅁䍯浔䅑䅅䅁䉁䅁䅁兂歃䑣䬰㘱潐睐杷允䅁䅁䅕䅁䑁䅁䅷䅁䭁䉁䅯䅁䭁䙁䅍䅁䭁䅁䅕䅁䙁䅁䅁䅁权敃䅚允䅁䅁䅅䅁䙁䕁㉡⼸唳䑇䅰䍄䉁䅁䅁兂䅁䅁䅍䅄䅁䅁䅯睈䅁䅁䅯睕䅁䅁䅯兂䅁䅁䅕䅁䅁佁扂欵䉁䅁䅁允䅁䅁䅕匰扌堫䬴啍䵁䅉䅅䅁䙁䅁䅁睁䵁䅁䅁权慁䅁䅁权呂䅁䅁权䙁䅁䅁兂䅁䅁䅁䝧洷䅑䅅䅁䉁䅁䅁兂癁匳䝑噧㝕䅑杷允䅁䅁䅕䅁䑁䅁䅷䅁䭁䅁䅁䅁䭁䅁䅅䅁䭁䅁䅕䅁䙁䅁䅁䅁䅂敚䅚允䅁䅁䅅䅁䙁䱁敧敨剴乵⼴䍄䉁䅁䅁兂䅁䅁䅍䅄䅁䅁䅯杈䅁䅁䅯允䅁䅁䅯兂䅁䅁䅕䅁䅁䍁扃唵䉁䅁䅁允䅁䅁䅕積積積積稰䴸䅉䅅䅁䙁䅁䅁睁䵁䅁䅁权䅁䅁䅁权呂䅁䅁权䙁䅁䅁兂䅁䅁䅁䥧浄䅑䅅䅁䉁䅁䅁兂⭄䠱灪癊穅䅑杷允䅁䅁䅕䅁䑁䅁䅷䅁䭁䉁䄰䅁䭁䅁䅅䅁䭁䅁䅕䅁䙁䅁䅁䅁杄敉䅚允䅁䅁䅅䅁䙁䉁䘫ㄶ㑇瑈⽕䍄䉁䅁䅁䅂䅁䅁䅍䅄䅁䅁䅯睔䅁䅁䅯杔䅁䅁䅕䅁䅁佁塁欵䉁䅁䅁允䅁䅁䅕㡪ㅌ䙋偹歅䵁䅉䅅䅁䕁䅁䅁睁䵁䅁䅁权偂䅁䅁权佂䅁䅁兂䅁䅁䅁䡷浌䅑䅅䅁䉁䅁䅁兂偃癷潕䥘䴸䅑杷允䅁䅁䅕䅁䑁䅁䅷䅁䭁䉁䅷䅁䭁䅁䅅䅁䭁䅁䅕䅁䙁䅁䅁䅁䅂攫䅖允䅁䅁䅅䅁䙁䉁䘫ㄶ㑇瑈⽕䍄䉁䅁䅁兂䅁䅁䅍䅄䅁䅁䅯䅁䅁䅁䅯睕䅁䅁䅯兂䅁䅁䅕䅁䅁䥁歁欵䉁䅁䅁允䅁䅁䅕搵楁⼲⭫き䵁䅉䅅䅁䕁䅁䅁睁䵁䅁䅁权偂䅁䅁权佂䅁䅁兂䅁䅁䅁䡧浪䅑䅅䅁䉁䅁䅁兂啁歲桦桥䵑䅑杷允䅁䅁䅕䅁䑁䅁䅷䅁䭁䅁䅁䅁䭁䅁䅅䅁䭁䅁䅕䅁䙁䅁䅁䅁杄畤䅚允䅁䅁䅅䅁䙁䱁敧敨剴乵⼴䍄䉁䅁䅁䅂䅁䅁䅍䅄䅁䅁䅯睔䅁䅁䅯杔䅁䅁䅕䅁䅁䥁佂欵䉁䅁䅁允䅁䅁䅕椹捨㡪ㅌ䕅䵁䅉䅅䅁䙁䅁䅁睁䵁䅁䅁权䅁䅁䅁权䉁䅁䅁权䙁䅁䅁兂䅁䅁䅁䩑汢䅑䅅䅁䉁䅁䅁兂慃婭婭婭婮睐杷允䅁䅁䅕䅁䑁䅁䅷䅁䭁䉁䄰䅁䭁䙁䅍䅁䭁䅁䅕䅁䙁䅁䅁䅁䅁敖䅚允䅁䅁䅅䅁䙁䵁ㅐ䙋偹楧䄵䍄䉁䅁䅁䅂䅁䅁䅍䅄䅁䅁䅯睔䅁䅁䅯杔䅁䅁䅕䅁䅁䝁瑄唵䉁䅁䅁允䅁䅁䅕浚浚浚浚䕅䵁䅉䅅䅁䕁䅁䅁睁䵁䅁䅁权偂䅁䅁权佂䅁䅁兂䅁䅁䅁䉧洳䅑䅅䅁䉁䅁䅁兂䭁㘱睎児兯䅑杷允䅁䅁䅕䅁䑁䅁䅷䅁䭁䉁䄰䅁䭁䅁䅅䅁䭁䅁䅕䅁䙁䅁䅁䅁䅁⭇䅚允䅁䅁䅅䅁䙁䉁䘫ㄶ㑇瑈⽕䍄䉁䅁䅁兂䅁䅁䅍䅄䅁䅁䅯䅁䅁䅁䅯允䅁䅁䅯兂䅁䅁䅕䅁䅁佁㑃唵䉁䅁䅁允䅁䅁䅕灭婭婭婭吲䴸䅉䅅䅁䙁䅁䅁睁䵁䅁䅁权敁䅁䅁权䉁䅁䅁权䙁䅁䅁兂䅁䅁䅁䑑洷䅑䅅䅁䉁䅁䅁兂䑄匹捨㡪噌睐杷允䅁䅁䅕䅁䑁䅁䅷䅁䭁䅁䅁䅁䭁䅁䅅䅁䭁䅁䅕䅁䙁䅁䅁䅁䅁畤䅚允䅁䅁䅅䅁䙁䱁敧敨剴乵⼴䍄䉁䅁䅁兂䅁䅁䅍䅄䅁䅁䅯杈䅁䅁䅯睕䅁䅁䅯兂䅁䅁䅕䅁䅁䕁獃唵䉁䅁䅁允䅁䅁䅕㝤昶楇搸か䵁䅉䅅䅁䕁䅁䅁睁䵁䅁䅁权偂䅁䅁权佂䅁䅁兂䅁䅁䅁乑汐䅑䅅䅁䉁䅁䅁兂晁敨剴䉵䠴䅑杷允䅁䅁䅕䅁䑁䅁䅷䅁䭁䉁䅯䅁䭁䙁䅍䅁䭁䅁䅕䅁䙁䅁䅁䅁䅄敒䅚允䅁䅁䅅䅁䙁䕁㍷啩杆呒䅴䍄䉁䅁䅁兂䅁䅁䅍䅄䅁䅁䅯先䅁䅁䅯允䅁䅁䅯兂䅁䅁䅕䅁䅁䍁楂欵䉁䅁䅁允䅁䅁䅕歲桦桥畓稱䴸䅉䅅䅁䙁䅁䅁睁䵁䅁䅁权䅁䅁䅁权䉁䅁䅁权䙁䅁䅁兂䅁䅁䅁䩷氯䅑䅅䅁䉁䅁䅁兂慃婭婭婭婮睐杷允䅁䅁䅕䅁䑁䅁䅷䅁䭁䅁䅁䅁䭁䅁䅅䅁䭁䅁䅕䅁䙁䅁䅁䅁杁位䅚允䅁䅁䅅䅁䙁䱁敧敨剴乵⼴䍄䉁䅁䅁兂䅁䅁䅍䅄䅁䅁䅯䅁䅁䅁䅯睕䅁䅁䅯兂䅁䅁䅕䅁䅁䍁潁欵䉁䅁䅁允䅁䅁䅕搵楁⼲⭫き䵁䅉䅅䅁䙁䅁䅁睁䵁䅁䅁权敁䅁䅁权呂䅁䅁权䙁䅁䅁兂䅁䅁䅁䩉汘䅑䅅䅁䉁䅁䅁兂䝁婧䑖㉩灷䅑杷允䅁䅁䅑䅁䑁䅁䅷䅁䭁䕁䄸䅁䭁䕁䄴䅁䙁䅁䅁䅁䅁敋䅚允䅁䅁䅅䅁䙁䅁塲㍯㥁桃䅊䍄䉁䅁䅁兂䅁䅁䅍䅄䅁䅁䅯䅁䅁䅁䅯睕䅁䅁䅯兂䅁䅁䅕䅁䅁䭁癃唵䉁䅁䅁允䅁䅁䅕歵䵫楁湳歍䵁䅉䅅䅁䙁䅁䅁睁䵁䅁䅁权捁䅁䅁权䉁䅁䅁权䙁䅁䅁兂䅁䅁䅁䑯浲䅑䅅䅁䉁䅁䅁兂㉄䙋偹癷奘睐杷允䅁䅁䅕䅁䑁䅁䅷䅁䭁䉁䅷䅁䭁䙁䅍䅁䭁䅁䅕䅁䙁䅁䅁䅁杁敺䅖允䅁䅁䅅䅁䙁䥁牘払敧卨䄵䍄䉁䅁䅁䅂䅁䅁䅍䅄䅁䅁䅯睔䅁䅁䅯杔䅁䅁䅕䅁䅁䕁䵁欵䉁䅁䅁允䅁䅁䅕䉵䘶ㄶ㑇歅䵁䅉䅅䅁䙁䅁䅁睁䵁䅁䅁权䅁䅁䅁权呂䅁䅁权䙁䅁䅁兂䅁䅁䅁䕁浔䅑䅅䅁䉁䅁䅁兂十㡧䭄捯穕䅑杷允䅁䅁䅕䅁䑁䅁䅷䅁䭁䉁䄰䅁䭁䙁䅍䅁䭁䅁䅕䅁䙁䅁䅁䅁权散䅚允䅁䅁䅅䅁䙁䑁䩥坑汄䍅䄵䍄䉁䅁䅁䅂䅁䅁䅍䅄䅁䅁䅯睔䅁䅁䅯杔䅁䅁䅕䅁䅁佁楁欵䉁䅁䅁允䅁䅁䅕⽷潕䥘䌯啅䵁䅉䅅䅁䕁䅁䅁睁䵁䅁䅁权偂䅁䅁权佂䅁䅁兂䅁䅁䅁䡯浶䅑䅅䅁䉁䅁䅁兂捂㡪ㅌ䙋乷䅑杷允䅁䅁䅕䅁䑁䅁䅷䅁䭁䉁䅷䅁䭁䙁䅍䅁䭁䅁䅕䅁䙁䅁䅁䅁䅁佹䅖允䅁䅁䅅䅁䙁䥁牘払敧卨䄵䍄䉁䅁䅁兂䅁䅁䅍䅄䅁䅁䅯䅁䅁䅁䅯睕䅁䅁䅯兂䅁䅁䅕䅁䅁䭁慄唵䉁䅁䅁允䅁䅁䅕䉯癯匳䝑き䵁䅉䅅䅁䕁䅁䅁睁䵁䅁䅁权兂䅁䅁权䵂䅁䅁权杁䅁䅁允䅁䅁䅅䅁䙁乁橥䑣䬰礱䅬䍄䉁䅁䅁兂䅁䅁䅍䅄䅁䅁䅯先䅁䅁䅯允䅁䅁䅯兂䅁䅁䅕䅁䅁䍁牄唵䉁䅁䅁允䅁䅁䅕㘱睎児塲稰䴸䅉䅅䅁䙁䅁䅁睁䵁䅁䅁权敁䅁䅁权䉁䅁䅁权䙁䅁䅁兂䅁䅁䅁䠴洷䅑䅅䅁䉁䅁䅁兂䅁䅁䅁䅁兄睐杷允䅁䅁䅕䅁䑁䅁䅷䅁䭁䅁䅁䅁䭁䙁䅍䅁䭁䅁䅕䅁䙁䅁䅁䅁杂敤䅚允䅁䅁䅅䅁䙁䙁橔婰䕶䑁䅒䍄䉁䅁䅁䅂䅁䅁䅍䅄䅁䅁䅯睔䅁䅁䅯杔䅁䅁䅕䅁䅁䍁⽃唵䉁䅁䅁允䅁䅁䅕歲桦桥畓稷䴸䅉䅅䅁䕁䅁䅁睁䵁䅁䅁权偂䅁䅁权佂䅁䅁兂䅁䅁䅁䵯汲䅑䅅䅁䉁䅁䅁兂䥂場啯歲㥦睐杷允䅁䅁䅕䅁䑁䅁䅷䅁䭁䉁䄴䅁䭁䙁䅍䅁䭁䅁䅕䅁䙁䅁䅁䅁权⬸䅖允䅁䅁䅅䅁䙁䡁潎敫㠱祐䅸䍄䉁䅁䅁兂䅁䅁䅍䅄䅁䅁䅯睈䅁䅁䅯允䅁䅁䅯兂䅁䅁䅕䅁䅁䕁䵄唵䉁䅁䅁允䅁䅁䅕䡰㥁瑃橥䐴䴸䅉䅅䅁䙁䅁䅁睁䵁䅁䅁权晁䅁䅁权呂䅁䅁权䙁䅁䅁兂䅁䅁䅁佧汘䅑䅅䅁䉁䅁䅁兂⭃确癯唳睑䅑杷允䅁䅁䅕䅁䑁䅁䅷䅁䭁䅁䅁䅁䭁䙁䅍䅁䭁䅁䅕䅁䙁䅁䅁䅁权攵䅖允䅁䅁䅅䅁䙁䉁䕫杖琴樰䅊䍄䉁䅁䅁䅂䅁䅁䅍䅄䅁䅁䅯睔䅁䅁䅯杔䅁䅁䅕䅁䅁䕁時欵䉁䅁䅁允䅁䅁䅕灭婭婭婭い䵁䅉䅅䅁䕁䅁䅁睁䵁䅁䅁权偂䅁䅁权佂䅁䅁兂䅁䅁䅁䝷洯䅑䅅䅁䉁䅁䅁兂䑄匹捨㡪䱉䅑杷允䅁䅁䅕䅁䑁䅁䅷䅁䭁䅁䅁䅁䭁䅁䅅䅁䭁䅁䅕䅁䙁䅁䅁䅁杁佂䅚允䅁䅁䅅䅁䙁䱁敧敨剴乵⼴䍄䉁䅁䅁兂䅁䅁䅍䅄䅁䅁䅯䅈䅁䅁䅯睕䅁䅁䅯兂䅁䅁䅕䅁䅁佁㍂欵䉁䅁䅁允䅁䅁䅕㉩湺㘫确啌䵁䅉䅅䅁䕁䅁䅁睁䵁䅁䅁权偂䅁䅁权佂䅁䅁兂䅁䅁䅁䩑汲䅑䅅䅁䉁䅁䅁兂慃婭婭婭䩮睐杷允䅁䅁䅕䅁䑁䅁䅷䅁䭁䉁䅷䅁䭁䙁䅍䅁䭁䅁䅕䅁䙁䅁䅁䅁䅄畁䅚允䅁䅁䅅䅁䙁偁潙䥘䌯卤䄱䍄䉁䅁䅁兂䅁䅁䅍䅄䅁䅁䅯先䅁䅁䅯睕䅁䅁䅯兂䅁䅁䅕䅁䅁䵁塂欵䉁䅁䅁允䅁䅁䅕⽷潕䥘䌫歌䵁䅉䅅䅁䕁䅁䅁睁䵁䅁䅁权偂䅁䅁权佂䅁䅁兂䅁䅁䅁佉氯䅑䅅䅁䉁䅁䅁兂捂㡪ㅌ䙋具䅑杷允䅁䅁䅑䅁䑁䅁䅷䅁䭁䕁䄸䅁䭁䕁䄴䅁䙁䅁䅁䅁杂敕䅚允䅁䅁䅅䅁䙁䑁積積積硍䅆䍄䉁䅁䅁兂䅁䅁䅍䅄䅁䅁䅯䅁䅁䅁䅯允䅁䅁䅯兂䅁䅁䅕䅁䅁䭁楂欵䉁䅁䅁允䅁䅁䅕䉵䘶ㄶ㑇樳䴸䅉䅅䅁䙁䅁䅁睁䵁䅁䅁权捁䅁䅁权呂䅁䅁权䙁䅁䅁兂䅁䅁䅁䑉浪䅑䅅䅁䉁䅁䅁兂奂扏䥔橤甴䅑杷允䅁䅁䅑䅁䑁䅁䅷䅁䭁䕁䄸䅁䭁䕁䄴䅁䙁䅁䅁䅁杂敱䅖允䅁䅁䅅䅁䙁䑁䬰㘱睎摐⽯䍄䉁䅁䅁䅂䅁䅁䅍䅄䅁䅁䅯睔䅁䅁䅯杔䅁䅁䅕䅁䅁佁煄唵䉁䅁䅁允䅁䅁䅕䭆䠵場啯啅䵁䅉䅅䅁䕁䅁䅁睁䵁䅁䅁权偂䅁䅁权佂䅁䅁兂䅁䅁䅁䅷浈䅑䅅䅁䉁䅁䅁兂灁䥘䌯匹內䅑杷允䅁䅁䅕䅁䑁䅁䅷䅁䭁䅁䅁䅁䭁䙁䅍䅁䭁䅁䅕䅁䙁䅁䅁䅁杄敆䅚允䅁䅁䅅䅁䙁䝁匸㡧䭄呁䅎䍄䉁䅁䅁兂䅁䅁䅍䅄䅁䅁䅯杇䅁䅁䅯睕䅁䅁䅯兂䅁䅁䅕䅁䅁䵁䉁欵䉁䅁䅁允䅁䅁䅕牒穢搯契歏䵁䅉䅅䅁䕁䅁䅁睁䵁䅁䅁权偂䅁䅁权佂䅁䅁兂䅁䅁䅁䭁汦䅑䅅䅁䉁䅁䅁兂穁積積積呐睐杷允䅁䅁䅑䅁䑁䅁䅷䅁䭁䕁䄸䅁䭁䕁䄴䅁䙁䅁䅁䅁杂敧䅚允䅁䅁䅅䅁䙁䭁睒児塲睯䅸䍄䉁䅁䅁兂䅁䅁䅍䅄䅁䅁䅯䅈䅁䅁䅯睕䅁䅁䅯兂䅁䅁䅕䅁䅁䥁允欵䉁䅁䅁允䅁䅁䅕牘䩰䅄牋啌䵁䅉䅅䅁䙁䅁䅁睁䵁䅁䅁权䅁䅁䅁权䉁䅁䅁权䙁䅁䅁兂䅁䅁䅁倴汈䅑䅅䅁䉁䅁䅁兂䙃ㄶ㑇潈托睐杷允䅁䅁䅕䅁䑁䅁䅷䅁䭁䉁䄰䅁䭁䅁䅅䅁䭁䅁䅕䅁䙁䅁䅁䅁杄畔䅚允䅁䅁䅅䅁䙁䭁䠵場啯瑲⽣䍄䉁䅁䅁兂䅁䅁䅍䅄䅁䅁䅯先䅁䅁䅯睕䅁䅁䅯兂䅁䅁䅕䅁䅁䥁偂欵䉁䅁䅁允䅁䅁䅕婤奍䙂佡歌䵁䅉䅅䅁䙁䅁䅁睁䵁䅁䅁权敁䅁䅁权呂䅁䅁权䙁䅁䅁兂䅁䅁䅁䉯浮䅑䅅䅁䉁䅁䅁兂婁䙂余塌灉䅑杷允䅁䅁䅕䅁䑁䅁䅷䅁䭁䅁䅁䅁䭁䙁䅍䅁䭁䅁䅕䅁䙁䅁䅁䅁䅃佗䅚允䅁䅁䅅䅁䙁䑁ね䡹⭡稳䅎䍄䉁䅁䅁兂䅁䅁䅍䅄䅁䅁䅯睈䅁䅁䅯睕䅁䅁䅯兂䅁䅁䅕䅁䅁䅁捃唵䉁䅁䅁允䅁䅁䅕䵮村䡳潉啍䵁䅉䅅䅁䙁䅁䅁睁䵁䅁䅁权晁䅁䅁权呂䅁䅁权䙁䅁䅁兂䅁䅁䅁佯氳䅑䅅䅁䉁䅁䅁兂橁⼲⭬污睷䅑杷允䅁䅁䅑䅁䑁䅁䅷䅁䭁䕁䄸䅁䭁䕁䄴䅁䙁䅁䅁䅁䅂⬵䅖允䅁䅁䅅䅁䙁䉁畓⭒㙆䉆䅊䍄䉁䅁䅁兂䅁䅁䅍䅄䅁䅁䅯杈䅁䅁䅯睕䅁䅁䅯兂䅁䅁䅕䅁䅁佁汃唵䉁䅁䅁允䅁䅁䅕㝤昶楇搸か䵁䅉䅅䅁䕁䅁䅁睁䵁䅁䅁权偂䅁䅁权佂䅁䅁兂䅁䅁䅁䉉浔䅑䅅䅁䉁䅁䅁兂晁敨剴䉵唴䅑杷允䅁䅁䅕䅁䑁䅁䅷䅁䭁䉁䄸䅁䭁䙁䅍䅁䭁䅁䅕䅁䙁䅁䅁䅁䅂⬷䅖允䅁䅁䅅䅁䙁䍁扐堫焵䑘䅂䍄䉁䅁䅁兂䅁䅁䅍䅄䅁䅁䅯䅈䅁䅁䅯允䅁䅁䅯兂䅁䅁䅕䅁䅁䥁剁欵䉁䅁䅁允䅁䅁䅕㑈牘払敧吱䴸䅉䅅䅁䕁䅁䅁睁䵁䅁䅁权偂䅁䅁权佂䅁䅁兂䅁䅁䅁䝷浘䅑䅅䅁䉁䅁䅁兂捂㡪ㅌ䙋乷䅑杷允䅁䅁䅕䅁䑁䅁䅷䅁䭁䅁䅁䅁䭁䙁䅍䅁䭁䅁䅕䅁䙁䅁䅁䅁杄⭉䅚允䅁䅁䅅䅁䙁佁兘瑉㕶橐䅎䍄䉁䅁䅁䅂䅁䅁䅍䅄䅁䅁䅯睔䅁䅁䅯杔䅁䅁䅕䅁䅁䅁噂欵䉁䅁䅁允䅁䅁䅕呣䬰㘱睎い䵁䅉䅅䅁䙁䅁䅁睁䵁䅁䅁权捁䅁䅁权呂䅁䅁权䙁䅁䅁兂䅁䅁䅁乯汄䅑䅅䅁䉁䅁䅁兂䙃ㄶ㑇潈畕䅑杷允䅁䅁䅕䅁䑁䅁䅷䅁䭁䉁䅷䅁䭁䙁䅍䅁䭁䅁䅕䅁䙁䅁䅁䅁权田䅖允䅁䅁䅅䅁䙁䕁椵䙅㕧䍴䄵䍄䉁䅁䅁兂䅁䅁䅍䅄䅁䅁䅯杇䅁䅁䅯允䅁䅁䅯兂䅁䅁䅕䅁䅁䥁剄唵䉁䅁䅁允䅁䅁䅕椹捨㡪ㅌ䐴䴸䅉䅅䅁䕁䅁䅁睁䵁䅁䅁权偂䅁䅁权佂䅁䅁兂䅁䅁䅁䭑汔䅑䅅䅁䉁䅁䅁兂㝂䭆䠵場啲睐杷允䅁䅁䅑䅁䑁䅁䅷䅁䭁䕁䄸䅁䭁䕁䄴䅁䙁䅁䅁䅁䅄⭍䅚允䅁䅁䅅䅁䙁偁潙䥘䌯刹䅆䍄䉁䅁䅁兂䅁䅁䅍䅄䅁䅁䅯䅁䅁䅁䅯允䅁䅁䅯兂䅁䅁䅕䅁䅁䵁兄唵䉁䅁䅁允䅁䅁䅕場啯歲桦樲䴸䅉䅅䅁䙁䅁䅁睁䵁䅁䅁权慁䅁䅁权䉁䅁䅁权䙁䅁䅁兂䅁䅁䅁䝉浐䅑䅅䅁䉁䅁䅁兂歃䑣䬰㘱潐睐杷允䅁䅁䅕䅁䑁䅁䅷䅁䭁䉁䅷䅁䭁䅁䅅䅁䭁䅁䅕䅁䙁䅁䅁䅁䅃改䅖允䅁䅁䅅䅁䙁䉁䘫ㄶ㑇瑈⽕䍄䉁䅁䅁兂䅁䅁䅍䅄䅁䅁䅯杈䅁䅁䅯允䅁䅁䅯兂䅁䅁䅕䅁䅁䅁穄唵䉁䅁䅁允䅁䅁䅕積積積積稰䴸䅉䅅䅁䙁䅁䅁睁䵁䅁䅁权慁䅁䅁权䉁䅁䅁权䙁䅁䅁兂䅁䅁䅁䵉汘䅑䅅䅁䉁䅁䅁兂䅁䅁䅁䅁杄睐杷允䅁䅁䅑䅁䑁䅁䅷䅁䭁䕁䄰䅁䭁䕁䄴䅁䭁䍁䅁䅁䉁䅁䅁允䅁䅁䅕䡰㥁瑃橥歄䵁䅉䅅䅁䙁䅁䅁睁䵁䅁䅁权晁䅁䅁权呂䅁䅁权䙁䅁䅁兂䅁䅁䅁䌴浔䅑䅅䅁䉁䅁䅁兂㉃⼸唳䅥硫䅑杷允䅁䅁䅑䅁䑁䅁䅷䅁䭁䕁䄸䅁䭁䕁䄴䅁䙁䅁䅁䅁䅄⭡䅚允䅁䅁䅅䅁䙁䝁浚浚浚杚䅸䍄䉁䅁䅁兂䅁䅁䅍䅄䅁䅁䅯䅈䅁䅁䅯允䅁䅁䅯兂䅁䅁䅕䅁䅁䅁㑄唵䉁䅁䅁允䅁䅁䅕㑈牘払敧吱䴸䅉䅅䅁䕁䅁䅁睁䵁䅁䅁权偂䅁䅁权佂䅁䅁兂䅁䅁䅁䱙汢䅑䅅䅁䉁䅁䅁兂慃婭婭婭桮睐杷允䅁䅁䅕䅁䑁䅁䅷䅁䭁䉁䅯䅁䭁䅁䅅䅁䭁䅁䅕䅁䙁䅁䅁䅁权佚䅚允䅁䅁䅅䅁䙁䭁睒児塲⭯⽧䍄䉁䅁䅁䅂䅁䅁䅍䅄䅁䅁䅯睔䅁䅁䅯杔䅁䅁䅕䅁䅁佁䙁欵䉁䅁䅁允䅁䅁䅕積積積積啅䵁䅉䅅䅁䕁䅁䅁睁䵁䅁䅁权偂䅁䅁权佂䅁䅁兂䅁䅁䅁䕯洯䅑䅅䅁䉁䅁䅁兂䑄匹捨㡪光䅑杷允䅁䅁䅕䅁䑁䅁䅷䅁䭁䅁䅁䅁䭁䙁䅍䅁䭁䅁䅕䅁䙁䅁䅁䅁䅃畃䅚允䅁䅁䅅䅁䙁䉁奂扏䥔橬䅊䍄䉁䅁䅁兂䅁䅁䅍䅄䅁䅁䅯杈䅁䅁䅯允䅁䅁䅯兂䅁䅁䅕䅁䅁䍁㥂欵䉁䅁䅁允䅁䅁䅕䅁䅁䅁䅁䐰䴸䅉䅅䅁䙁䅁䅁睁䵁䅁䅁权晁䅁䅁权呂䅁䅁权䙁䅁䅁兂䅁䅁䅁䕧浮䅑䅅䅁䉁䅁䅁兂䕁杖琴桳砰䅑杷允䅁䅁䅑䅁䑁䅁䅷䅁䭁䕁䄸䅁䭁䕁䄴䅁䙁䅁䅁䅁杁畤䅚允䅁䅁䅅䅁䙁䡁啳歲桦来䅸䍄䉁䅁䅁兂䅁䅁䅍䅄䅁䅁䅯杈䅁䅁䅯睕䅁䅁䅯兂䅁䅁䅕䅁䅁䵁㙂欵䉁䅁䅁允䅁䅁䅕噋偹癷潖啉䵁䅉䅅䅁䙁䅁䅁睁䵁䅁䅁权䅁䅁䅁权呂䅁䅁权䙁䅁䅁兂䅁䅁䅁䡁浺䅑䅅䅁䉁䅁䅁兂啂㘴扗䅸ぁ䅑杷允䅁䅁䅕䅁䑁䅁䅷䅁䭁䉁䄰䅁䭁䙁䅍䅁䭁䅁䅕䅁䙁䅁䅁䅁杄⭸䅖允䅁䅁䅅䅁䙁䕁㍷啩杆匵䄱䍄䉁䅁䅁兂䅁䅁䅍䅄䅁䅁䅯杇䅁䅁䅯睕䅁䅁䅯兂䅁䅁䅕䅁䅁䍁呂欵䉁䅁䅁允䅁䅁䅕⽷潕䥘椹く䵁䅉䅅䅁䙁䅁䅁睁䵁䅁䅁权晁䅁䅁权䉁䅁䅁权䙁䅁䅁兂䅁䅁䅁䱉汲䅑䅅䅁䉁䅁䅁兂䙃ㄶ㑇潈托睐杷允䅁䅁䅕䅁䑁䅁䅷䅁䭁䉁䄸䅁䭁䅁䅅䅁䭁䅁䅕䅁䙁䅁䅁䅁杄⭗䅚允䅁䅁䅅䅁䙁偁潙䥘䌯改⽁䍄䉁䅁䅁䅂䅁䅁䅍䅄䅁䅁䅯睔䅁䅁䅯杔䅁䅁䅕䅁䅁䵁獁欵䉁䅁䅁允䅁䅁䅕㘱睎児塲歅䵁䅉䅅䅁䙁䅁䅁睁䵁䅁䅁权晁䅁䅁权䉁䅁䅁权䙁䅁䅁兂䅁䅁䅁佉汌䅑䅅䅁䉁䅁䅁兂㥁瑃橥䑣愳睐杷允䅁䅁䅑䅁䑁䅁䅷䅁䭁䕁䄸䅁䭁䕁䄴䅁䙁䅁䅁䅁䅄畒䅚允䅁䅁䅅䅁䙁乁橥䑣䬰砱䅂䍄䉁䅁䅁兂䅁䅁䅍䅄䅁䅁䅯先䅁䅁䅯睕䅁䅁䅯兂䅁䅁䅕䅁䅁䥁䑁欵䉁䅁䅁允䅁䅁䅕䝭匴㡧䭂歌䵁䅉䅅䅁䙁䅁䅁睁䵁䅁䅁权䅁䅁䅁权䉁䅁䅁权䙁䅁䅁兂䅁䅁䅁偁汲䅑䅅䅁䉁䅁䅁兂㑃潈牘払敪睐杷允䅁䅁䅕䅁䑁䅁䅷䅁䭁䉁䅯䅁䭁䙁䅍䅁䭁䅁䅕䅁䙁䅁䅁䅁杄敒䅚允䅁䅁䅅䅁䙁䕁㍷啩杆呒䅴䍄䉁䅁䅁兂䅁䅁䅍䅄䅁䅁䅯䅁䅁䅁䅯允䅁䅁䅯兂䅁䅁䅕䅁䅁佁䥁欵䉁䅁䅁允䅁䅁䅕䉵䘶ㄶ㑇樳䴸䅉䅅䅁䕁䅁䅁睁䵁䅁䅁权偂䅁䅁权佂䅁䅁兂䅁䅁䅁䍷洳䅑䅅䅁䉁䅁䅁兂慃婭婭婭卫䅑杷允䅁䅁䅕䅁䑁䅁䅷䅁䭁䅁䅁䅁䭁䅁䅅䅁䭁䅁䅕䅁䙁䅁䅁䅁䅂佰䅖允䅁䅁䅅䅁䙁䩁婱婭婭摭⽫䍄䉁䅁䅁兂䅁䅁䅍䅄䅁䅁䅯杈䅁䅁䅯允䅁䅁䅯兂䅁䅁䅕䅁䅁䝁ㅃ唵䉁䅁䅁允䅁䅁䅕積積積積稰䴸䅉䅅䅁䕁䅁䅁睁䵁䅁䅁权偂䅁䅁权佂䅁䅁兂䅁䅁䅁䑁浲䅑䅅䅁䉁䅁䅁兂㉄䙋偹癷何䅑杷允䅁䅁䅕䅁䑁䅁䅷䅁䭁䉁䄸䅁䭁䙁䅍䅁䭁䅁䅕䅁䙁䅁䅁䅁杄敖䅚允䅁䅁䅅䅁䙁䡁⼰噎㘶呋䅆䍄䉁䅁䅁兂䅁䅁䅍䅄䅁䅁䅯睈䅁䅁䅯睕䅁䅁䅯兂䅁䅁䅕䅁䅁䥁㡂欵䉁䅁䅁允䅁䅁䅕牡へ硫歧啍䵁䅉䅅䅁䕁䅁䅁睁䵁䅁䅁权偂䅁䅁权佂䅁䅁兂䅁䅁䅁䡯浐䅑䅅䅁䉁䅁䅁兂㝂䭆䠵場䵯䅑杷允䅁䅁䅕䅁䑁䅁䅷䅁䭁䉁䄸䅁䭁䙁䅍䅁䭁䅁䅕䅁䙁䅁䅁䅁杁數䅖允䅁䅁䅅䅁䙁䵁㉬灶愸穌䅆䍄䉁䅁䅁兂䅁䅁䅍䅄䅁䅁䅯杈䅁䅁䅯允䅁䅁䅯兂䅁䅁䅕䅁䅁䝁牂欵䉁䅁䅁允䅁䅁䅕䅁䅁䅁䅁䐰䴸䅉䅅䅁䕁䅁䅁睁䵁䅁䅁权偂䅁䅁权佂䅁䅁兂䅁䅁䅁䡯浪䅑䅅䅁䉁䅁䅁兂䅁䅁䅁䅁䵁䅑杷允䅁䅁䅕䅁䑁䅁䅷䅁䭁䉁䅷䅁䭁䅁䅅䅁䭁䅁䅕䅁䙁䅁䅁䅁䅁敔䅚允䅁䅁䅅䅁䙁偁潙䥘䌯搹⽧䍄䉁䅁䅁兂䅁䅁䅍䅄䅁䅁䅯睈䅁䅁䅯允䅁䅁䅯兂䅁䅁䅕䅁䅁䕁䝁欵䉁䅁䅁允䅁䅁䅕䅁䅁䅁䅁䐴䴸䅉䅅䅁䕁䅁䅁睁䵁䅁䅁权摁䅁䅁权䵂䅁䅁权杁䅁䅁允䅁䅁䅅䅁䙁䭁睒児塲祯䅚䍄䉁䅁䅁䅂䅁䅁䅍䅄䅁䅁䅯䅁䅁䅁䅯睕䅁䅁䅕䅁䅁䭁䍃欵䉁䅁䅁允䅁䅁䅯䅂䅁䅁杷允䅁䅁䅑䅁䑁䅁䅷䅁䭁䉁䄴䅁䭁䕁䅷䅁䭁䍁䅁䅁䉁䅁䅁允䅁䅁䅕灭婭婭婭啄䵁䅉䅅䅁䙁䅁䅁睁䵁䅁䅁权摁䅁䅁权䉁䅁䅁权䙁䅁䅁兂䅁䅁䅁偁氯䅑䅅䅁䉁䅁䅁兂晁敨剴䉵嘷睐杷允䅁䅁䅕䅁䑁䅁䅷䅁䭁䉁䄰䅁䭁䙁䅍䅁䭁䅁䅕䅁䙁䅁䅁䅁杄畤䅚允䅁䅁䅅䅁䙁偁湃歸㍳卹䄱䍄䉁䅁䅁兂䅁䅁䅍䅄䅁䅁䅯䅁䅁䅁䅯允䅁䅁䅯兂䅁䅁䅕䅁䅁䕁⭂欵䉁䅁䅁允䅁䅁䅕䉵䘶ㄶ㑇樳䴸䅉䅅䅁䕁䅁䅁睁䵁䅁䅁权偂䅁䅁权佂䅁䅁兂䅁䅁䅁䕁浦䅑䅅䅁䉁䅁䅁兂畃⭒㙆䭆儴䅑杷允䅁䅁䅕䅁䑁䅁䅷䅁䭁䉁䄴䅁䭁䙁䅍䅁䭁䅁䅕䅁䙁䅁䅁䅁权佭䅖允䅁䅁䅅䅁䙁䅁䉡啬䱏䍢䅬䍄䉁䅁䅁兂䅁䅁䅍䅄䅁䅁䅯杈䅁䅁䅯允䅁䅁䅯兂䅁䅁䅕䅁䅁䍁楄唵䉁䅁䅁允䅁䅁䅕積積積積稰䴸䅉䅅䅁䙁䅁䅁睁䵁䅁䅁权䅁䅁䅁权呂䅁䅁权䙁䅁䅁兂䅁䅁䅁䵷汮䅑䅅䅁䉁䅁䅁兂瑂⼵灵昸祉䅑杷允䅁䅁䅕䅁䑁䅁䅷䅁䭁䉁䄸䅁䭁䅁䅅䅁䭁䅁䅕䅁䙁䅁䅁䅁䅄畦䅚允䅁䅁䅅䅁䙁䙁㑋潈牘敕⽁䍄䉁䅁䅁兂䅁䅁䅍䅄䅁䅁䅯䅁䅁䅁䅯睕䅁䅁䅯兂䅁䅁䅕䅁䅁佁敁欵䉁䅁䅁允䅁䅁䅕硢䑋䵷䉯き䵁䅉䅅䅁䙁䅁䅁睁䵁䅁䅁权摁䅁䅁权䉁䅁䅁权䙁䅁䅁兂䅁䅁䅁䝯洳䅑䅅䅁䉁䅁䅁兂畃⭒㙆䭆堷睐杷允䅁䅁䅑䅁䑁䅁䅷䅁䭁䕁䄸䅁䭁䕁䄴䅁䙁䅁䅁䅁䅁伫䅖允䅁䅁䅅䅁䙁䭁睒児塲硯䅊䍄䉁䅁䅁兂䅁䅁䅍䅄䅁䅁䅯䅈䅁䅁䅯允䅁䅁䅯兂䅁䅁䅕䅁䅁䵁摄唵䉁䅁䅁允䅁䅁䅕積積積積稰䴸䅉䅅䅁䙁䅁䅁睁䵁䅁䅁权䅁䅁䅁权䉁䅁䅁权䙁䅁䅁兂䅁䅁䅁䵑決䅑䅅䅁䉁䅁䅁兂㥁瑃橥䑣愳睐杷允䅁䅁䅕䅁䑁䅁䅷䅁䭁䉁䅯䅁䭁䅁䅅䅁䭁䅁䅕䅁䙁䅁䅁䅁杂敤䅚允䅁䅁䅅䅁䙁䭁睒児塲⭯⽧䍄䉁䅁䅁兂䅁䅁䅍䅄䅁䅁䅯杈䅁䅁䅯允䅁䅁䅯兂䅁䅁䅕䅁䅁䵁牄唵䉁䅁䅁允䅁䅁䅕積積積積稰䴸䅉䅅䅁䙁䅁䅁睁䵁䅁䅁权䅁䅁䅁权呂䅁䅁权䙁䅁䅁兂䅁䅁䅁䵁汐䅑䅅䅁䉁䅁䅁兂㑄⭕汏㑭祑䅑杷允䅁䅁䅑䅁䑁䅁䅷䅁䭁䕁䄸䅁䭁䕁䄴䅁䙁䅁䅁䅁䅄佶䅖允䅁䅁䅅䅁䙁佁㙆䭆䠵攴⽯䍄䉁䅁䅁兂䅁䅁䅍䅄䅁䅁䅯先䅁䅁䅯睕䅁䅁䅯兂䅁䅁䅕䅁䅁䭁瑂欵䉁䅁䅁允䅁䅁䅕㑎䉬余兕歌䵁䅉䅅䅁䙁䅁䅁睁䵁䅁䅁权䅁䅁䅁权䉁䅁䅁权䙁䅁䅁兂䅁䅁䅁䡑浔䅑䅅䅁䉁䅁䅁兂㑃潈牘払敪睐杷允䅁䅁䅕䅁䑁䅁䅷䅁䭁䉁䄸䅁䭁䅁䅅䅁䭁䅁䅕䅁䙁䅁䅁䅁杂⭲䅖允䅁䅁䅅䅁䙁䥁牘払敧摨⽳䍄䉁䅁䅁䅂䅁䅁䅍䅄䅁䅁䅯睔䅁䅁䅯杔䅁䅁䅕䅁䅁䥁奂欵䉁䅁䅁允䅁䅁䅕㡪ㅌ䙋偹歄䵁䅉䅅䅁䙁䅁䅁睁䵁䅁䅁权捁䅁䅁权䉁䅁䅁权䙁䅁䅁兂䅁䅁䅁䱯氷䅑䅅䅁䉁䅁䅁兂偃癷潕䥘匯睐杷允䅁䅁䅕䅁䑁䅁䅷䅁䭁䅁䅁䅁䭁䙁䅍䅁䭁䅁䅕䅁䙁䅁䅁䅁䅄伲䅖允䅁䅁䅅䅁䙁䭁慁㥌欰橂䅎䍄䉁䅁䅁兂䅁䅁䅍䅄䅁䅁䅯䅁䅁䅁䅯睕䅁䅁䅯兂䅁䅁䅕䅁䅁䝁杂欵䉁䅁䅁允䅁䅁䅕癱午坔兌き䵁䅉䅅䅁䙁䅁䅁睁䵁䅁䅁权捁䅁䅁权䉁䅁䅁权䙁䅁䅁兂䅁䅁䅁䅙浘䅑䅅䅁䉁䅁䅁兂晁敨剴䉵嘷睐杷允䅁䅁䅕䅁䑁䅁䅷䅁䭁䉁䅷䅁䭁䅁䅅䅁䭁䅁䅕䅁䙁䅁䅁䅁杁畆䅚允䅁䅁䅅䅁䙁䉁䘫ㄶ㑇瑈⽕䍄䉁䅁䅁兂䅁䅁䅍䅄䅁䅁䅯睈䅁䅁䅯允䅁䅁䅯兂䅁䅁䅕䅁䅁䭁癄唵䉁䅁䅁允䅁䅁䅕場啯歲桦樲䴸䅉䅅䅁䕁䅁䅁睁䵁䅁䅁权偂䅁䅁权佂䅁䅁兂䅁䅁䅁䩑氳䅑䅅䅁䉁䅁䅁兂塄㍯㥁瑃呦睐杷允䅁䅁䅕䅁䑁䅁䅷䅁䭁䅁䅁䅁䭁䅁䅅䅁䭁䅁䅕䅁䙁䅁䅁䅁权佳䅖允䅁䅁䅅䅁䙁䩁婱婭婭摭⽫䍄䉁䅁䅁兂䅁䅁䅍䅄䅁䅁䅯䅈䅁䅁䅯睕䅁䅁䅯兂䅁䅁䅕䅁䅁䭁䩂欵䉁䅁䅁允䅁䅁䅕硢䑋䵷桰歌䵁䅉䅅䅁䙁䅁䅁睁䵁䅁䅁权䅁䅁䅁权呂䅁䅁权䙁䅁䅁兂䅁䅁䅁䕉浦䅑䅅䅁䉁䅁䅁兂十㡧䭄捯穕䅑杷允䅁䅁䅕䅁䑁䅁䅷䅁䭁䉁䄰䅁䭁䅁䅅䅁䭁䅁䅕䅁䙁䅁䅁䅁䅃电䅖允䅁䅁䅅䅁䙁乁橥䑣䬰㤱⽍䍄䉁䅁䅁兂䅁䅁䅍䅄䅁䅁䅯先䅁䅁䅯允䅁䅁䅯兂䅁䅁䅕䅁䅁䅁牁欵䉁䅁䅁允䅁䅁䅕浚浚浚浚樱䴸䅉䅅䅁䙁䅁䅁睁䵁䅁䅁权摁䅁䅁权呂䅁䅁权䙁䅁䅁兂䅁䅁䅁䵁汌䅑䅅䅁䉁䅁䅁兂䵂㑎䉬余瑕䅑杷允䅁䅁䅑䅁䑁䅁䅷䅁䭁䕁䄸䅁䭁䕁䄴䅁䙁䅁䅁䅁杁佂䅚允䅁䅁䅅䅁䙁䭁睒児塲硯䅂䍄䉁䅁䅁兂䅁䅁䅍䅄䅁䅁䅯䅁䅁䅁䅯允䅁䅁䅯兂䅁䅁䅕䅁䅁䅁奄唵䉁䅁䅁允䅁䅁䅕場啯歲桦樲䴸䅉䅅䅁䙁䅁䅁睁䵁䅁䅁权慁䅁䅁权呂䅁䅁权䙁䅁䅁兂䅁䅁䅁䡷浌䅑䅅䅁䉁䅁䅁兂䵂㑎䉬䍙㝕䅑杷允䅁䅁䅑䅁䑁䅁䅷䅁䭁䕁䄸䅁䭁䕁䄴䅁䙁䅁䅁䅁䅁住䅚允䅁䅁䅅䅁䙁䝁浚浚浚桚䅂䍄䉁䅁䅁兂䅁䅁䅍䅄䅁䅁䅯杈䅁䅁䅯允䅁䅁䅯兂䅁䅁䅕䅁䅁䵁灂欵䉁䅁䅁允䅁䅁䅕䅁䅁䅁䅁䐰䴸䅉䅅䅁䙁䅁䅁睁䵁䅁䅁权晁䅁䅁权呂䅁䅁权䙁䅁䅁兂䅁䅁䅁䍧浺䅑䅅䅁䉁䅁䅁兂㉃⼸唳䅥硫䅑杷允䅁䅁䅕䅁䑁䅁䅷䅁䭁䉁䄰䅁䭁䅁䅅䅁䭁䅁䅕䅁䙁䅁䅁䅁䅁伱䅖允䅁䅁䅅䅁䙁乁橥䑣䬰㤱⽍䍄䉁䅁䅁兂䅁䅁䅍䅄䅁䅁䅯先䅁䅁䅯睕䅁䅁䅯兂䅁䅁䅕䅁䅁䥁䙄唵䉁䅁䅁允䅁䅁䅕䑔䩥坑汄啌䵁䅉䅅䅁䕁䅁䅁睁䵁䅁䅁权偂䅁䅁权佂䅁䅁兂䅁䅁䅁乁汘䅑䅅䅁䉁䅁䅁兂畃⭒㙆䭆䘴䅑杷允䅁䅁䅕䅁䑁䅁䅷䅁䭁䉁䄰䅁䭁䙁䅍䅁䭁䅁䅕䅁䙁䅁䅁䅁杁⭴䅖允䅁䅁䅅䅁䙁䅁塲㍯㥁楹䄱䍄䉁䅁䅁䅂䅁䅁䅍䅄䅁䅁䅯睔䅁䅁䅯杔䅁䅁䅕䅁䅁䵁兂欵䉁䅁䅁允䅁䅁䅕瑃橥䑣䬰啅䵁䅉䅅䅁䕁䅁䅁睁䵁䅁䅁权偂䅁䅁权佂䅁䅁兂䅁䅁䅁䥙浌䅑䅅䅁䉁䅁䅁兂啁歲桦桥佑䅑杷允䅁䅁䅕䅁䑁䅁䅷䅁䭁䉁䄸䅁䭁䙁䅍䅁䭁䅁䅕䅁䙁䅁䅁䅁杄⭐䅚允䅁䅁䅅䅁䙁䑁䩥坑汄䑍䅆䍄䉁䅁䅁䅂䅁䅁䅍䅄䅁䅁䅯睔䅁䅁䅯杔䅁䅁䅕䅁䅁䅁煃唵䉁䅁䅁允䅁䅁䅕䉵䘶ㄶ㑇樳䴸䅉䅅䅁䙁䅁䅁睁䵁䅁䅁权慁䅁䅁权呂䅁䅁权䙁䅁䅁兂䅁䅁䅁䥯浄䅑䅅䅁䉁䅁䅁兂㕂匶硙佃㙷䅑杷允䅁䅁䅕䅁䑁䅁䅷䅁䭁䉁䄸䅁䭁䅁䅅䅁䭁䅁䅕䅁䙁䅁䅁䅁杁⭙䅚允䅁䅁䅅䅁䙁偁潙䥘䌯改⽁䍄䉁䅁䅁䅂䅁䅁䅍䅄䅁䅁䅯睔䅁䅁䅯杔䅁䅁䅕䅁䅁䝁婁欵䉁䅁䅁允䅁䅁䅕灭婭婭婭啅䵁䅉䅅䅁䙁䅁䅁睁䵁䅁䅁权晁䅁䅁权䉁䅁䅁权䙁䅁䅁兂䅁䅁䅁䅑浦䅑䅅䅁䉁䅁䅁兂䅁䅁䅁䅁杄睐杷允䅁䅁䅕䅁䑁䅁䅷䅁䭁䅁䅁䅁䭁䅁䅅䅁䭁䅁䅕䅁䙁䅁䅁䅁䅂⭌䅚允䅁䅁䅅䅁䙁䱁敧敨剴乵⼴䍄䉁䅁䅁䅂䅁䅁䅍䅄䅁䅁䅯睔䅁䅁䅯杔䅁䅁䅕䅁䅁䥁㝂欵䉁䅁䅁允䅁䅁䅕呣䬰㘱睎啄䵁䅉䅅䅁䙁䅁䅁睁䵁䅁䅁权敁䅁䅁权呂䅁䅁权䙁䅁䅁兂䅁䅁䅁䵧汶䅑䅅䅁䉁䅁䅁兂牁硨婢牺獣䅑杷允䅁䅁䅕䅁䑁䅁䅷䅁䭁䉁䄴䅁䭁䙁䅍䅁䭁䅁䅕䅁䙁䅁䅁䅁䅄畖䅚允䅁䅁䅅䅁䙁乁㕶浦㡱䍤䅊䍄䉁䅁䅁兂䅁䅁䅍䅄䅁䅁䅯睈䅁䅁䅯睕䅁䅁䅯兂䅁䅁䅕䅁䅁䅁い唵䉁䅁䅁允䅁䅁䅕㥉㕶浦捰䕍䵁䅉䅅䅁䕁䅁䅁睁䵁䅁䅁权偂䅁䅁权佂䅁䅁兂䅁䅁䅁䥁浄䅑䅅䅁䉁䅁䅁兂晁敨剴䉵䰴䅑杷允䅁䅁䅕䅁䑁䅁䅷䅁䭁䅁䅁䅁䭁䙁䅍䅁䭁䅁䅕䅁䙁䅁䅁䅁杄畷䅖允䅁䅁䅅䅁䙁偁周㘴扗䑨䅊䍄䉁䅁䅁䅂䅁䅁䅍䅄䅁䅁䅯䅁䅁䅁䅯睕䅁䅁䅕䅁䅁䥁䍃欵䉁䅁䅁允䅁䅁䅯䅂䅁䅁杷允䅁䅁䅑䅁䑁䅁䅷䅁䭁䕁䄸䅁䭁䕁䄴䅁䙁䅁䅁䅁䅂敷䅖允䅁䅁䅅䅁䭁䉁䅳䅁䵁䅉䅅䅁䙁䅁䅁睁䵁䅁䅁权摁䅁䅁权䉁䅁䅁权䙁䅁䅁兂䅁䅁䅁䍯浔䅑䅅䅁䉁䅁䅁兂浂浚浚浚坢睐杷允䅁䅁䅕䅁䑁䅁䅷䅁䭁䉁䄴䅁䭁䙁䅍䅁䭁䅁䅕䅁䙁䅁䅁䅁䅄⭂䅚允䅁䅁䅅䅁䙁䅁䅁䅁䅁䍁䅰䍄䉁䅁䅁䅂䅁䅁䅍䅄䅁䅁䅯睔䅁䅁䅯杔䅁䅁䅕䅁䅁佁䱂欵䉁䅁䅁允䅁䅁䅕積積積積啅䵁䅉䅅䅁䙁䅁䅁睁䵁䅁䅁权䅁䅁䅁权䉁䅁䅁权䙁䅁䅁兂䅁䅁䅁䕙浌䅑䅅䅁䉁䅁䅁兂㑃潈牘払敪睐杷允䅁䅁䅕䅁䑁䅁䅷䅁䭁䉁䅷䅁䭁䙁䅍䅁䭁䅁䅕䅁䙁䅁䅁䅁权敕䅚允䅁䅁䅅䅁䙁乁欰潂噇祑䄵䍄䉁䅁䅁兂䅁䅁䅍䅄䅁䅁䅯䅈䅁䅁䅯睕䅁䅁䅯兂䅁䅁䅕䅁䅁䵁佁欵䉁䅁䅁允䅁䅁䅕牘䩰䅄牋啌䵁䅉䅅䅁䙁䅁䅁睁䵁䅁䅁权䅁䅁䅁权䉁䅁䅁权䙁䅁䅁兂䅁䅁䅁伴汢䅑䅅䅁䉁䅁䅁兂桄桥畓⭒慈睐杷允䅁䅁䅕䅁䑁䅁䅷䅁䭁䉁䄴䅁䭁䙁䅍䅁䭁䅁䅕䅁䙁䅁䅁䅁权⭰䅖允䅁䅁䅅䅁䙁䡁⭥确癯午䅴䍄䉁䅁䅁兂䅁䅁䅍䅄䅁䅁䅯䅁䅁䅁䅯睕䅁䅁䅯兂䅁䅁䅕䅁䅁䥁偁欵䉁䅁䅁允䅁䅁䅕䙅㕧䵴坩歍䵁䅉䅅䅁䙁䅁䅁睁䵁䅁䅁权慁䅁䅁权呂䅁䅁权䙁䅁䅁兂䅁䅁䅁䝙洷䅑䅅䅁䉁䅁䅁兂癁匳䝑噧㝕䅑杷允䅁䅁䅕䅁䑁䅁䅷䅁䭁䅁䅁䅁䭁䙁䅍䅁䭁䅁䅕䅁䙁䅁䅁䅁杁畡䅚允䅁䅁䅅䅁䙁䙁橔婰䕶䐴䅎䍄䉁䅁䅁兂䅁䅁䅍䅄䅁䅁䅯睈䅁䅁䅯允䅁䅁䅯兂䅁䅁䅕䅁䅁䕁噃唵䉁䅁䅁允䅁䅁䅕牕敧敨剴䐴䴸䅉䅅䅁䕁䅁䅁睁䵁䅁䅁权偂䅁䅁权佂䅁䅁兂䅁䅁䅁䱧氷䅑䅅䅁䉁䅁䅁兂乄䵺䵺䵺獺睐杷允䅁䅁䅑䅁䑁䅁䅷䅁䭁䕁䄸䅁䭁䕁䄴䅁䙁䅁䅁䅁杄伸䅖允䅁䅁䅅䅁䙁䡁㥅瑃橥䅣䄹䍄䉁䅁䅁䅂䅁䅁䅍䅄䅁䅁䅯睔䅁䅁䅯杔䅁䅁䅕䅁䅁佁㕄唵䉁䅁䅁允䅁䅁䅕䭆䠵場啯歄䵁䅉䅅䅁䕁䅁䅁睁䵁䅁䅁权偂䅁䅁权佂䅁䅁兂䅁䅁䅁䡷洷䅑䅅䅁䉁䅁䅁兂䑄匹捨㡪䱉䅑杷允䅁䅁䅕䅁䑁䅁䅷䅁䭁䅁䅁䅁䭁䙁䅍䅁䭁䅁䅕䅁䙁䅁䅁䅁䅃⭌䅚允䅁䅁䅅䅁䙁䍁礲敮渫橨䅎䍄䉁䅁䅁兂䅁䅁䅍䅄䅁䅁䅯杇䅁䅁䅯允䅁䅁䅯兂䅁䅁䅕䅁䅁䍁潁欵䉁䅁䅁允䅁䅁䅕䡰㥁瑃橥䐶䴸䅉䅅䅁䙁䅁䅁睁䵁䅁䅁权晁䅁䅁权呂䅁䅁权䙁䅁䅁兂䅁䅁䅁䭷汪䅑䅅䅁䉁䅁䅁兂㑃潈牘塕睧䅑杷允䅁䅁䅑䅁䑁䅁䅷䅁䭁䕁䄸䅁䭁䕁䄴䅁䙁䅁䅁䅁䅁佔䅚允䅁䅁䅅䅁䙁䙁㑋潈牘剕䅆䍄䉁䅁䅁兂䅁䅁䅍䅄䅁䅁䅯䅁䅁䅁䅯允䅁䅁䅯兂䅁䅁䅕䅁䅁䅁穁欵䉁䅁䅁允䅁䅁䅕䉵䘶ㄶ㑇樳䴸䅉䅅䅁䕁䅁䅁睁䵁䅁䅁权偂䅁䅁权佂䅁䅁兂䅁䅁䅁䅁浦䅑䅅䅁䉁䅁䅁兂捂㡪ㅌ䙋卷䅑杷允䅁䅁䅕䅁䑁䅁䅷䅁䭁䉁䅷䅁䭁䙁䅍䅁䭁䅁䅕䅁䙁䅁䅁䅁䅃⬰䅖允䅁䅁䅅䅁䙁䕁椵䙅㕧䍴䄵䍄䉁䅁䅁兂䅁䅁䅍䅄䅁䅁䅯先䅁䅁䅯允䅁䅁䅯兂䅁䅁䅕䅁䅁佁牄唵䉁䅁䅁允䅁䅁䅕㘱睎児塲稰䴸䅉䅅䅁䙁䅁䅁睁䵁䅁䅁权䅁䅁䅁权呂䅁䅁权䙁䅁䅁兂䅁䅁䅁䍯洷䅑䅅䅁䉁䅁䅁兂瑁灳瘳㑰穙䅑杷允䅁䅁䅕䅁䑁䅁䅷䅁䭁䉁䅷䅁䭁䙁䅍䅁䭁䅁䅕䅁䙁䅁䅁䅁䅃⬷䅖允䅁䅁䅅䅁䙁䱁䩰䅄牉祸䄱䍄䉁䅁䅁兂䅁䅁䅍䅄䅁䅁䅯睈䅁䅁䅯睕䅁䅁䅯兂䅁䅁䅕䅁䅁佁睁欵䉁䅁䅁允䅁䅁䅕穐敖歵獫啍䵁䅉䅅䅁䕁䅁䅁睁䵁䅁䅁权偂䅁䅁权佂䅁䅁兂䅁䅁䅁䙉浔䅑䅅䅁䉁䅁䅁兂硂児塲㍯偁䅑杷允䅁䅁䅕䅁䑁䅁䅷䅁䭁䅁䅁䅁䭁䅁䅅䅁䭁䅁䅕䅁䙁䅁䅁䅁权佉䅚允䅁䅁䅅䅁䙁䱁敧敨剴乵⼴䍄䉁䅁䅁兂䅁䅁䅍䅄䅁䅁䅯先䅁䅁䅯允䅁䅁䅯兂䅁䅁䅕䅁䅁䍁⭁欵䉁䅁䅁允䅁䅁䅕歲桦桥畓稱䴸䅉䅅䅁䙁䅁䅁睁䵁䅁䅁权䅁䅁䅁权䉁䅁䅁权䙁䅁䅁兂䅁䅁䅁䍙浮䅑䅅䅁䉁䅁䅁兂㑃潈牘払敪睐杷允䅁䅁䅕䅁䑁䅁䅷䅁䭁䅁䅁䅁䭁䙁䅍䅁䭁䅁䅕䅁䙁䅁䅁䅁䅄攰䅖允䅁䅁䅅䅁䙁䭁慁㥌欰橂䅎䍄䉁䅁䅁兂䅁䅁䅍䅄䅁䅁䅯杇䅁䅁䅯睕䅁䅁䅯兂䅁䅁䅕䅁䅁䵁祁欵䉁䅁䅁允䅁䅁䅕㑈牘払敪歏䵁䅉䅅䅁䙁䅁䅁睁䵁䅁䅁权晁䅁䅁权䉁䅁䅁权䙁䅁䅁兂䅁䅁䅁䩁汮䅑䅅䅁䉁䅁䅁兂卂䉵䘶ㄶ杈睐杷允䅁䅁䅕䅁䑁䅁䅷䅁䭁䉁䄸䅁䭁䙁䅍䅁䭁䅁䅕䅁䙁䅁䅁䅁杂敚䅚允䅁䅁䅅䅁䙁乁楅⼲⭬橃䅆䍄䉁䅁䅁䅂䅁䅁䅍䅄䅁䅁䅯睔䅁䅁䅯杔䅁䅁䅕䅁䅁䍁湂欵䉁䅁䅁允䅁䅁䅕敨剴䉵䘶啄䵁䅉䅅䅁䙁䅁䅁睁䵁䅁䅁权䅁䅁䅁权呂䅁䅁权䙁䅁䅁兂䅁䅁䅁䵯汪䅑䅅䅁䉁䅁䅁兂瑂⼵灵昸祉䅑杷允䅁䅁䅕䅁䑁䅁䅷䅁䭁䉁䅷䅁䭁䙁䅍䅁䭁䅁䅕䅁䙁䅁䅁䅁䅃佌䅚允䅁䅁䅅䅁䙁䥁䌯匹捨祄䄵䍄䉁䅁䅁兂䅁䅁䅍䅄䅁䅁䅯先䅁䅁䅯允䅁䅁䅯兂䅁䅁䅕䅁䅁䕁硃唵䉁䅁䅁允䅁䅁䅕㘱睎児塲稰䴸䅉䅅䅁䙁䅁䅁睁䵁䅁䅁权敁䅁䅁权呂䅁䅁权䙁䅁䅁兂䅁䅁䅁䐴洷䅑䅅䅁䉁䅁䅁兂い搯㑒圶歙䅑杷允䅁䅁䅑䅁䑁䅁䅷䅁䭁䕁䄸䅁䭁䕁䄴䅁䙁䅁䅁䅁杁佦䅚允䅁䅁䅅䅁䙁䑁積積積睍䄱䍄䉁䅁䅁䅂䅁䅁䅍䅄䅁䅁䅯睔䅁䅁䅯杔䅁䅁䅕䅁䅁䭁瑁欵䉁䅁䅁允䅁䅁䅕浚浚浚浚歅䵁䅉䅅䅁䙁䅁䅁睁䵁䅁䅁权敁䅁䅁权䉁䅁䅁权䙁䅁䅁兂䅁䅁䅁䍧浶䅑䅅䅁䉁䅁䅁兂䑄匹捨㡪噌睐杷允䅁䅁䅑䅁䑁䅁䅷䅁䭁䕁䄸䅁䭁䕁䄴䅁䙁䅁䅁䅁䅃佦䅚允䅁䅁䅅䅁䙁䵁䴳䵺䵺䅺䅸䍄䉁䅁䅁䅂䅁䅁䅍䅄䅁䅁䅯睔䅁䅁䅯杔䅁䅁䅕䅁䅁佁塃唵䉁䅁䅁允䅁䅁䅕瑃橥䑣䬰穸䴸䅉䅅䅁䕁䅁䅁睁䵁䅁䅁权偂䅁䅁权佂䅁䅁兂䅁䅁䅁乙決䅑䅅䅁䉁䅁䅁兂歃䑣䬰㘱䝍䅑杷允䅁䅁䅕䅁䑁䅁䅷䅁䭁䉁䄰䅁䭁䙁䅍䅁䭁䅁䅕䅁䙁䅁䅁䅁䅁⭮䅖允䅁䅁䅅䅁䙁䕁㉡⼸唳䍥䄱䍄䉁䅁䅁兂䅁䅁䅍䅄䅁䅁䅯杈䅁䅁䅯睕䅁䅁䅯兂䅁䅁䅕䅁䅁䵁兂欵䉁䅁䅁允䅁䅁䅕渷⽷噎㘴䕊䵁䅉䅅䅁䙁䅁䅁睁䵁䅁䅁权晁䅁䅁权䉁䅁䅁权䙁䅁䅁兂䅁䅁䅁偙氳䅑䅅䅁䉁䅁䅁兂䥂場啯歲桦睐杷允䅁䅁䅑䅁䑁䅁䅷䅁䭁䕁䄸䅁䭁䕁䄴䅁䙁䅁䅁䅁杁⭑䅚允䅁䅁䅅䅁䙁䙁偹癷潕䉘䅂䍄䉁䅁䅁䅂䅁䅁䅍䅄䅁䅁䅯睔䅁䅁䅯杔䅁䅁䅕䅁䅁䭁䉁欵䉁䅁䅁允䅁䅁䅕䘷㑇潈牘い䵁䅉䅅䅁䙁䅁䅁睁䵁䅁䅁权捁䅁䅁权䉁䅁䅁权䙁䅁䅁兂䅁䅁䅁䭉汌䅑䅅䅁䉁䅁䅁兂偃癷潕䥘匯睐杷允䅁䅁䅑䅁䑁䅁䅷䅁䭁䕁䄸䅁䭁䕁䄴䅁䙁䅁䅁䅁杂敤䅚允䅁䅁䅅䅁䙁䝁浚浚浚杚䅸䍄䉁䅁䅁兂䅁䅁䅍䅄䅁䅁䅯先䅁䅁䅯睕䅁䅁䅯兂䅁䅁䅕䅁䅁䭁獂欵䉁䅁䅁允䅁䅁䅕㑎䉬余兕歌䵁䅉䅅䅁䙁䅁䅁睁䵁䅁䅁权䅁䅁䅁权䉁䅁䅁权䙁䅁䅁兂䅁䅁䅁䨴汮䅑䅅䅁䉁䅁䅁兂慃婭婭婭婮睐杷允䅁䅁䅕䅁䑁䅁䅷䅁䭁䅁䅁䅁䭁䅁䅅䅁䭁䅁䅕䅁䙁䅁䅁䅁䅄畊䅚允䅁䅁䅅䅁䙁䱁敧敨剴乵⼴䍄䉁䅁䅁兂䅁䅁䅍䅄䅁䅁䅯杇䅁䅁䅯允䅁䅁䅯兂䅁䅁䅕䅁䅁䵁敂欵䉁䅁䅁允䅁䅁䅕䡰㥁瑃橥䐶䴸䅉䅅䅁䙁䅁䅁睁䵁䅁䅁权䅁䅁䅁权呂䅁䅁权䙁䅁䅁兂䅁䅁䅁䴴汪䅑䅅䅁䉁䅁䅁兂瑂⼵灵昸祉䅑杷允䅁䅁䅕䅁䑁䅁䅷䅁䭁䅁䅁䅁䭁䙁䅍䅁䭁䅁䅕䅁䙁䅁䅁䅁权畏䅚允䅁䅁䅅䅁䙁䅁䅁䅁䅁䑯䅎䍄䉁䅁䅁兂䅁䅁䅍䅄䅁䅁䅯䅈䅁䅁䅯睕䅁䅁䅯兂䅁䅁䅕䅁䅁䭁慄唵䉁䅁䅁允䅁䅁䅕浔光䑗ね歌䵁䅉䅅䅁䙁䅁䅁睁䵁䅁䅁权晁䅁䅁权䉁䅁䅁权䙁䅁䅁兂䅁䅁䅁䌴浺䅑䅅䅁䉁䅁䅁兂䥂場啯歲桦睐杷允䅁䅁䅕䅁䑁䅁䅷䅁䭁䉁䄴䅁䭁䙁䅍䅁䭁䅁䅕䅁䙁䅁䅁䅁䅃敇䅚允䅁䅁䅅䅁䙁䉁䕫杖琴楣䅬䍄䉁䅁䅁䅂䅁䅁䅍䅄䅁䅁䅯睔䅁䅁䅯杔䅁䅁䅕䅁䅁䕁穃唵䉁䅁䅁允䅁䅁䅕場啯歲桦樲䴸䅉䅅䅁䙁䅁䅁睁䵁䅁䅁权捁䅁䅁权䉁䅁䅁权䙁䅁䅁兂䅁䅁䅁佑氯䅑䅅䅁䉁䅁䅁兂穁積積積呐睐杷允䅁䅁䅕䅁䑁䅁䅷䅁䭁䉁䄰䅁䭁䙁䅍䅁䭁䅁䅕䅁䙁䅁䅁䅁权敏䅚允䅁䅁䅅䅁䙁䕁㉡⼸唳䍵䄵䍄䉁䅁䅁兂䅁䅁䅍䅄䅁䅁䅯䅁䅁䅁䅯睕䅁䅁䅯兂䅁䅁䅕䅁䅁䕁ぁ欵䉁䅁䅁允䅁䅁䅕扌摋㘷䝥き䵁䅉䅅䅁䙁䅁䅁睁䵁䅁䅁权敁䅁䅁权䉁䅁䅁权䙁䅁䅁兂䅁䅁䅁佁汮䅑䅅䅁䉁䅁䅁兂穁積積積呐睐杷允䅁䅁䅕䅁䑁䅁䅷䅁䭁䉁䄴䅁䭁䙁䅍䅁䭁䅁䅕䅁䙁䅁䅁䅁杂攷䅖允䅁䅁䅅䅁䙁䡁潎敫㠱祐䅸䍄䉁䅁䅁䅂䅁䅁䅍䅄䅁䅁䅯睔䅁䅁䅯杔䅁䅁䅕䅁䅁䵁硂欵䉁䅁䅁允䅁䅁䅕積積積積啄䵁䅉䅅䅁䙁䅁䅁睁䵁䅁䅁权䅁䅁䅁权䉁䅁䅁权䙁䅁䅁兂䅁䅁䅁䕉浲䅑䅅䅁䉁䅁䅁兂㑃潈牘払敪睐杷允䅁䅁䅕䅁䑁䅁䅷䅁䭁䅁䅁䅁䭁䙁䅍䅁䭁䅁䅕䅁䙁䅁䅁䅁䅂畓䅚允䅁䅁䅅䅁䙁䉁䑋䵷桱呸䅎䍄䉁䅁䅁䅂䅁䅁䅍䅄䅁䅁䅯睔䅁䅁䅯杔䅁䅁䅕䅁䅁䝁桃唵䉁䅁䅁允䅁䅁䅕浚浚浚浚樱䴸䅉䅅䅁䕁䅁䅁睁䵁䅁䅁权偂䅁䅁权佂䅁䅁兂䅁䅁䅁䌴浈䅑䅅䅁䉁䅁䅁兂啁歲桦桥剑䅑杷允䅁䅁䅕䅁䑁䅁䅷䅁䭁䉁䅷䅁䭁䅁䅅䅁䭁䅁䅕䅁䙁䅁䅁䅁䅃畁䅚允䅁䅁䅅䅁䙁䉁䘫ㄶ㑇瑈⽕䍄䉁䅁䅁兂䅁䅁䅍䅄䅁䅁䅯杈䅁䅁䅯允䅁䅁䅯兂䅁䅁䅕䅁䅁䭁汃唵䉁䅁䅁允䅁䅁䅕積積積積稰䴸䅉䅅䅁䙁䅁䅁睁䵁䅁䅁权䅁䅁䅁权呂䅁䅁权䙁䅁䅁兂䅁䅁䅁䵙汘䅑䅅䅁䉁䅁䅁兂㑄⭕汏㑭祑䅑杷允䅁䅁䅕䅁䑁䅁䅷䅁䭁䉁䄰䅁䭁䅁䅅䅁䭁䅁䅕䅁䙁䅁䅁䅁䅃畕䅚允䅁䅁䅅䅁䙁䭁䠵場啯瑲⽣䍄䉁䅁䅁兂䅁䅁䅍䅄䅁䅁䅯䅈䅁䅁䅯睕䅁䅁䅯兂䅁䅁䅕䅁䅁䵁煂欵䉁䅁䅁允䅁䅁䅕㉣剩堷⽺啌䵁䅉䅅䅁䕁䅁䅁睁䵁䅁䅁权䅁䅁䅁权啂䅁䅁兂䅁䅁䅁䥯浌䅑䅅䅁䉁䅁䅁权扁䅁䅁䍄䉁䅁䅁䅂䅁䅁䅍䅄䅁䅁䅯睔䅁䅁䅯杔䅁䅁䅕䅁䅁䥁䍃欵䉁䅁䅁允䅁䅁䅕牕敧敨剴歄䵁䅉䅅䅁䙁䅁䅁睁䵁䅁䅁权晁䅁䅁权䉁䅁䅁权䙁䅁䅁兂䅁䅁䅁䌴浮䅑䅅䅁䉁䅁䅁兂䥂場啯歲桦睐杷允䅁䅁䅕䅁䑁䅁䅷䅁䭁䅁䅁䅁䭁䅁䅅䅁䭁䅁䅕䅁䙁䅁䅁䅁杂佰䅖允䅁䅁䅅䅁䙁䩁婱婭婭摭⽫䍄䉁䅁䅁兂䅁䅁䅍䅄䅁䅁䅯杈䅁䅁䅯允䅁䅁䅯兂䅁䅁䅕䅁䅁䝁㡄唵䉁䅁䅁允䅁䅁䅕硥畓⭒㙆䐱䴸䅉䅅䅁䕁䅁䅁睁䵁䅁䅁权偂䅁䅁权佂䅁䅁兂䅁䅁䅁䭁汐䅑䅅䅁䉁䅁䅁兂浂浚浚浚坢睐杷允䅁䅁䅕䅁䑁䅁䅷䅁䭁䅁䅁䅁䭁䙁䅍䅁䭁䅁䅕䅁䙁䅁䅁䅁杁⭋䅚允䅁䅁䅅䅁䙁佁兘瑉㕶橐䅎䍄䉁䅁䅁兂䅁䅁䅍䅄䅁䅁䅯杇䅁䅁䅯睕䅁䅁䅯兂䅁䅁䅕䅁䅁䍁硄唵䉁䅁䅁允䅁䅁䅕⽷潕䥘䌯問䵁䅉䅅䅁䕁䅁䅁睁䵁䅁䅁权偂䅁䅁权佂䅁䅁兂䅁䅁䅁䅙浮䅑䅅䅁䉁䅁䅁兂獄払敧敨剳䅑杷允䅁䅁䅕䅁䑁䅁䅷䅁䭁䅁䅁䅁䭁䅁䅅䅁䭁䅁䅕䅁䙁䅁䅁䅁杂⬴䅖允䅁䅁䅅䅁䙁佁㙆䭆䠵搴⽯䍄䉁䅁䅁兂䅁䅁䅍䅄䅁䅁䅯杇䅁䅁䅯睕䅁䅁䅯兂䅁䅁䅕䅁䅁䕁䡁欵䉁䅁䅁允䅁䅁䅕牒穢搯契歏䵁䅉䅅䅁䙁䅁䅁睁䵁䅁䅁权慁䅁䅁权呂䅁䅁权䙁䅁䅁兂䅁䅁䅁䍙浌䅑䅅䅁䉁䅁䅁兂㉃⼸唳䥥㙫䅑杷允䅁䅁䅑䅁䑁䅁䅷䅁䭁䕁䄸䅁䭁䕁䄴䅁䙁䅁䅁䅁杂畑䅚允䅁䅁䅅䅁䙁乁橥䑣䬰眱䄹䍄䉁䅁䅁兂䅁䅁䅍䅄䅁䅁䅯䅈䅁䅁䅯允䅁䅁䅯兂䅁䅁䅕䅁䅁䝁䅃欵䉁䅁䅁允䅁䅁䅕椹捨㡪ㅌ䐲䴸䅉䅅䅁䙁䅁䅁睁䵁䅁䅁权摁䅁䅁权䉁䅁䅁权䙁䅁䅁兂䅁䅁䅁余氯䅑䅅䅁䉁䅁䅁兂塄㍯㥁瑃呦睐杷允䅁䅁䅑䅁䑁䅁䅷䅁䭁䕁䄸䅁䭁䕁䄴䅁䙁䅁䅁䅁杂佂䅚允䅁䅁䅅䅁䙁䡁啳歲桦桥䅆䍄䉁䅁䅁䅂䅁䅁䅍䅄䅁䅁䅯睔䅁䅁䅯杔䅁䅁䅕䅁䅁䥁潁欵䉁䅁䅁允䅁䅁䅕灭婭婭婭啅䵁䅉䅅䅁䕁䅁䅁睁䵁䅁䅁权偂䅁䅁权佂䅁䅁兂䅁䅁䅁䍙浢䅑䅅䅁䉁䅁䅁兂卂䉵䘶ㄶ剅䅑杷允䅁䅁䅑䅁䑁䅁䅷䅁䭁䕁䄸䅁䭁䕁䄴䅁䙁䅁䅁䅁杂佚䅚允䅁䅁䅅䅁䙁䡁啳歲桦来䄵䍄䉁䅁䅁兂䅁䅁䅍䅄䅁䅁䅯先䅁䅁䅯允䅁䅁䅯兂䅁䅁䅕䅁䅁䝁兂欵䉁䅁䅁允䅁䅁䅕歲桦桥畓稱䴸䅉䅅䅁䕁䅁䅁睁䵁䅁䅁权偂䅁䅁权佂䅁䅁兂䅁䅁䅁䘴浶䅑䅅䅁䉁䅁䅁兂穁積積積免䅑杷允䅁䅁䅕䅁䑁䅁䅷䅁䭁䉁䅷䅁䭁䅁䅅䅁䭁䅁䅕䅁䙁䅁䅁䅁䅃甯䅖允䅁䅁䅅䅁䙁䉁䘫ㄶ㑇瑈⽕䍄䉁䅁䅁兂䅁䅁䅍䅄䅁䅁䅯杈䅁䅁䅯睕䅁䅁䅯兂䅁䅁䅕䅁䅁佁扁欵䉁䅁䅁允䅁䅁䅕兇坒楄礱啋䵁䅉䅅䅁䙁䅁䅁睁䵁䅁䅁权䅁䅁䅁权䉁䅁䅁权䙁䅁䅁兂䅁䅁䅁䠴浌䅑䅅䅁䉁䅁䅁兂㑃潈牘払敪睐杷允䅁䅁䅑䅁䑁䅁䅷䅁䭁䕁䄸䅁䭁䕁䄴䅁䙁䅁䅁䅁䅃畡䅚允䅁䅁䅅䅁䙁䵁ㅐ䙋偹杷䅴䍄䉁䅁䅁兂䅁䅁䅍䅄䅁䅁䅯先䅁䅁䅯允䅁䅁䅯兂䅁䅁䅕䅁䅁䕁敃唵䉁䅁䅁允䅁䅁䅕㘱睎児塲稰䴸䅉䅅䅁䕁䅁䅁睁䵁䅁䅁权偂䅁䅁权佂䅁䅁兂䅁䅁䅁䥯浄䅑䅅䅁䉁䅁䅁兂浂浚浚浚䵙䅑杷允䅁䅁䅕䅁䑁䅁䅷䅁䭁䉁䄴䅁䭁䙁䅍䅁䭁䅁䅕䅁䙁䅁䅁䅁䅃畱䅖允䅁䅁䅅䅁䙁䡁⭥确癯午䅴䍄䉁䅁䅁䅂䅁䅁䅍䅄䅁䅁䅯睔䅁䅁䅯杔䅁䅁䅕䅁䅁䥁獁欵䉁䅁䅁允䅁䅁䅕硥畓⭒㙆ぅ䵁䅉䅅䅁䙁䅁䅁睁䵁䅁䅁权䅁䅁䅁权䉁䅁䅁权䙁䅁䅁兂䅁䅁䅁䵉汄䅑䅅䅁䉁䅁䅁兂㥁瑃橥䑣愳睐杷允䅁䅁䅕䅁䑁䅁䅷䅁䭁䅁䅁䅁䭁䅁䅅䅁䭁䅁䅕䅁䙁䅁䅁䅁䅄敚䅚允䅁䅁䅅䅁䙁䱁敧敨剴乵⼴䍄䉁䅁䅁兂䅁䅁䅍䅄䅁䅁䅯先䅁䅁䅯允䅁䅁䅯兂䅁䅁䅕䅁䅁䍁婂欵䉁䅁䅁允䅁䅁䅕歲桦桥畓稱䴸䅉䅅䅁䕁䅁䅁睁䵁䅁䅁权偂䅁䅁权佂䅁䅁兂䅁䅁䅁䍁洯䅑䅅䅁䉁䅁䅁兂㝂䭆䠵場卯䅑杷允䅁䅁䅕䅁䑁䅁䅷䅁䭁䉁䄴䅁䭁䙁䅍䅁䭁䅁䅕䅁䙁䅁䅁䅁䅄異䅖允䅁䅁䅅䅁䙁䡁⭥确癯午䅴䍄䉁䅁䅁兂䅁䅁䅍䅄䅁䅁䅯睈䅁䅁䅯睕䅁䅁䅯兂䅁䅁䅕䅁䅁䅁㝃唵䉁䅁䅁允䅁䅁䅕塹⭡确癯啍䵁䅉䅅䅁䙁䅁䅁睁䵁䅁䅁权摁䅁䅁权呂䅁䅁权䙁䅁䅁兂䅁䅁䅁佧決䅑䅅䅁䉁䅁䅁兂浃㡭村䱳瑉䅑杷允䅁䅁䅑䅁䑁䅁䅷䅁䭁䕁䄸䅁䭁䕁䄴䅁䙁䅁䅁䅁杁畔䅚允䅁䅁䅅䅁䙁䙁㑋潈牘剕䅆䍄䉁䅁䅁兂䅁䅁䅍䅄䅁䅁䅯杇䅁䅁䅯允䅁䅁䅯兂䅁䅁䅕䅁䅁䝁湂欵䉁䅁䅁允䅁䅁䅕䡰㥁瑃橥䐶䴸䅉䅅䅁䙁䅁䅁睁䵁䅁䅁权䅁䅁䅁权呂䅁䅁权䙁䅁䅁兂䅁䅁䅁䑷浔䅑䅅䅁䉁䅁䅁兂瑁灳瘳㑰穙䅑杷允䅁䅁䅕䅁䑁䅁䅷䅁䭁䉁䅷䅁䭁䅁䅅䅁䭁䅁䅕䅁䙁䅁䅁䅁䅁佌䅚允䅁䅁䅅䅁䙁䭁䠵場啯瑲⽣䍄䉁䅁䅁兂䅁䅁䅍䅄䅁䅁䅯杈䅁䅁䅯睕䅁䅁䅯兂䅁䅁䅕䅁䅁䭁祁欵䉁䅁䅁允䅁䅁䅕体㙆䭆䠵歊䵁䅉䅅䅁䕁䅁䅁睁䵁䅁䅁权偂䅁䅁权佂䅁䅁兂䅁䅁䅁䵷氷䅑䅅䅁䉁䅁䅁兂塄㍯㥁瑃䙣䅑杷允䅁䅁䅑䅁䑁䅁䅷䅁䭁䕁䄸䅁䭁䕁䄴䅁䙁䅁䅁䅁杁⭌䅚允䅁䅁䅅䅁䙁䡁㥅瑃橥䉣䅊䍄䉁䅁䅁兂䅁䅁䅍䅄䅁䅁䅯䅁䅁䅁䅯睕䅁䅁䅯兂䅁䅁䅕䅁䅁佁慁欵䉁䅁䅁允䅁䅁䅕硢䑋䵷䉯き䵁䅉䅅䅁䕁䅁䅁睁䵁䅁䅁权偂䅁䅁权佂䅁䅁兂䅁䅁䅁䝷浔䅑䅅䅁䉁䅁䅁兂㉄䙋偹癷何䅑杷允䅁䅁䅕䅁䑁䅁䅷䅁䭁䉁䅷䅁䭁䙁䅍䅁䭁䅁䅕䅁䙁䅁䅁䅁杂⭈䅚允䅁䅁䅅䅁䙁䱁摋㘷䝦祃䄵䍄䉁䅁䅁兂䅁䅁䅍䅄䅁䅁䅯先䅁䅁䅯睕䅁䅁䅯兂䅁䅁䅕䅁䅁䝁卄唵䉁䅁䅁允䅁䅁䅕⽷潕䥘䌯啌䵁䅉䅅䅁䕁䅁䅁睁䵁䅁䅁权偂䅁䅁权佂䅁䅁兂䅁䅁䅁䑙浄䅑䅅䅁䉁䅁䅁兂䑄匹捨㡪卉䅑杷允䅁䅁䅕䅁䑁䅁䅷䅁䭁䉁䅷䅁䭁䅁䅅䅁䭁䅁䅕䅁䙁䅁䅁䅁䅄佱䅖允䅁䅁䅅䅁䙁䥁䌯匹捨㥪⽉䍄䉁䅁䅁兂䅁䅁䅍䅄䅁䅁䅯䅈䅁䅁䅯睕䅁䅁䅯兂䅁䅁䅕䅁䅁䵁奄唵䉁䅁䅁允䅁䅁䅕浔光䑗ね歌䵁䅉䅅䅁䙁䅁䅁睁䵁䅁䅁权䅁䅁䅁权呂䅁䅁权䙁䅁䅁兂䅁䅁䅁佷汄䅑䅅䅁䉁䅁䅁兂婁䙂余摌祉䅑杷允䅁䅁䅕䅁䑁䅁䅷䅁䭁䉁䄰䅁䭁䅁䅅䅁䭁䅁䅕䅁䙁䅁䅁䅁杄伱䅖允䅁䅁䅅䅁䙁乁橥䑣䬰㤱⽍䍄䉁䅁䅁兂䅁䅁䅍䅄䅁䅁䅯杈䅁䅁䅯允䅁䅁䅯兂䅁䅁䅕䅁䅁䵁㉃唵䉁䅁䅁允䅁䅁䅕積積積積稰䴸䅉䅅䅁䕁䅁䅁睁䵁䅁䅁权偂䅁䅁权佂䅁䅁兂䅁䅁䅁䝧浦䅑䅅䅁䉁䅁䅁兂塄㍯㥁瑃乣䅑杷允䅁䅁䅕䅁䑁䅁䅷䅁䭁䅁䅁䅁䭁䅁䅅䅁䭁䅁䅕䅁䙁䅁䅁䅁杁⭓䅚允䅁䅁䅅䅁䙁䱁敧敨剴乵⼴䍄䉁䅁䅁兂䅁䅁䅍䅄䅁䅁䅯杈䅁䅁䅯睕䅁䅁䅯兂䅁䅁䅕䅁䅁䵁㉃唵䉁䅁䅁允䅁䅁䅕癴㥐䠱灨䕌䵁䅉䅅䅁䙁䅁䅁睁䵁䅁䅁权䅁䅁䅁权䉁䅁䅁权䙁䅁䅁兂䅁䅁䅁䱁汪䅑䅅䅁䉁䅁䅁兂慃婭婭婭婮睐杷允䅁䅁䅑䅁䑁䅁䅷䅁䭁䕁䄸䅁䭁䕁䄴䅁䙁䅁䅁䅁䅃畃䅚允䅁䅁䅅䅁䙁䍁捬㡪ㅌ䉋䅊䍄䉁䅁䅁兂䅁䅁䅍䅄䅁䅁䅯杇䅁䅁䅯允䅁䅁䅯兂䅁䅁䅕䅁䅁䝁䭁欵䉁䅁䅁允䅁䅁䅕浚浚浚浚樵䴸䅉䅅䅁䙁䅁䅁睁䵁䅁䅁权䅁䅁䅁权䉁䅁䅁权䙁䅁䅁兂䅁䅁䅁䡯浮䅑䅅䅁䉁䅁䅁兂㑃潈牘払敪睐杷允䅁䅁䅕䅁䑁䅁䅷䅁䭁䅁䅁䅁䭁䙁䅍䅁䭁䅁䅕䅁䙁䅁䅁䅁䅃畚䅚允䅁䅁䅅䅁䙁䙁橔婰䕶䐴䅎䍄䉁䅁䅁兂䅁䅁䅍䅄䅁䅁䅯睈䅁䅁䅯允䅁䅁䅯兂䅁䅁䅕䅁䅁䍁⭂欵䉁䅁䅁允䅁䅁䅕牕敧敨剴䐴䴸䅉䅅䅁䕁䅁䅁睁䵁䅁䅁权偂䅁䅁权佂䅁䅁兂䅁䅁䅁䕉浘䅑䅅䅁䉁䅁䅁兂䅁䅁䅁䅁剁䅑杷允䅁䅁䅕䅁䑁䅁䅷䅁䭁䉁䅷䅁䭁䅁䅅䅁䭁䅁䅕䅁䙁䅁䅁䅁䅁畒䅚允䅁䅁䅅䅁䙁偁潙䥘䌯搹⽧䍄䉁䅁䅁䅂䅁䅁䅍䅄䅁䅁䅯睔䅁䅁䅯杔䅁䅁䅕䅁䅁䥁浄唵䉁䅁䅁允䅁䅁䅕䉵䘶ㄶ㑇啅䵁䅉䅅䅁䙁䅁䅁睁䵁䅁䅁权晁䅁䅁权呂䅁䅁权䙁䅁䅁兂䅁䅁䅁偉氳䅑䅅䅁䉁䅁䅁兂偄ㄹ橐塰睳䅑杷允䅁䅁䅕䅁䑁䅁䅷䅁䭁䅁䅁䅁䭁䅁䅅䅁䭁䅁䅕䅁䙁䅁䅁䅁杁⬰䅖允䅁䅁䅅䅁䙁佁㙆䭆䠵搴⽯䍄䉁䅁䅁兂䅁䅁䅍䅄䅁䅁䅯杇䅁䅁䅯允䅁䅁䅯兂䅁䅁䅕䅁䅁䵁坃唵䉁䅁䅁允䅁䅁䅕䅁䅁䅁䅁䐴䴸䅉䅅䅁䙁䅁䅁睁䵁䅁䅁权摁䅁䅁权呂䅁䅁权䙁䅁䅁兂䅁䅁䅁䵯汮䅑䅅䅁䉁䅁䅁兂灁䥘䌯匹畧䅑杷允䅁䅁䅕䅁䑁䅁䅷䅁䭁䅁䅁䅁䭁䅁䅅䅁䭁䅁䅕䅁䙁䅁䅁䅁䅁敭䅖允䅁䅁䅅䅁䙁䩁婱婭婭摭⽫䍄䉁䅁䅁䅂䅁䅁䅍䅄䅁䅁䅯睔䅁䅁䅯杔䅁䅁䅕䅁䅁䍁摁欵䉁䅁䅁允䅁䅁䅕瑃橥䑣䬰䕅䵁䅉䅅䅁䕁䅁䅁睁䵁䅁䅁权偂䅁䅁权佂䅁䅁兂䅁䅁䅁䝷浐䅑䅅䅁䉁䅁䅁兂桄桥畓⭒佅䅑杷允䅁䅁䅑䅁䑁䅁䅷䅁䭁䕁䄸䅁䭁䕁䄴䅁䙁䅁䅁䅁杁⭵䅖允䅁䅁䅅䅁䙁䉁䘫ㄶ㑇畈⽕䍄䉁䅁䅁兂䅁䅁䅍䅄䅁䅁䅯䅁䅁䅁䅯允䅁䅁䅯兂䅁䅁䅕䅁䅁䍁佄唵䉁䅁䅁允䅁䅁䅕児塲㍯㥁樲䴸䅉䅅䅁䙁䅁䅁睁䵁䅁䅁权晁䅁䅁权䉁䅁䅁权䙁䅁䅁兂䅁䅁䅁䉑浈䅑䅅䅁䉁䅁䅁兂歃䑣䬰㘱材睐杷允䅁䅁䅕䅁䑁䅁䅷䅁䭁䅁䅁䅁䭁䙁䅍䅁䭁䅁䅕䅁䙁䅁䅁䅁杁伷䅖允䅁䅁䅅䅁䙁䑁積積積穫䅊䍄䉁䅁䅁䅂䅁䅁䅍䅄䅁䅁䅯睔䅁䅁䅯杔䅁䅁䅕䅁䅁䥁䱂欵䉁䅁䅁允䅁䅁䅕体㙆䭆䠵啅䵁䅉䅅䅁䙁䅁䅁睁䵁䅁䅁权晁䅁䅁权呂䅁䅁权䙁䅁䅁兂䅁䅁䅁乁汘䅑䅅䅁䉁䅁䅁兂扁㥌欰畂睅䅑杷允䅁䅁䅑䅁䑁䅁䅷䅁䭁䕁䄸䅁䭁䕁䄴䅁䙁䅁䅁䅁杂教䅚允䅁䅁䅅䅁䙁䵁ㅐ䙋偹杷䄱䍄䉁䅁䅁䅂䅁䅁䅍䅄䅁䅁䅯睔䅁䅁䅯杔䅁䅁䅕䅁䅁䝁䡄唵䉁䅁䅁允䅁䅁䅕䥘䌯匹捨稫䴸䅉䅅䅁䙁䅁䅁睁䵁䅁䅁权䅁䅁䅁权呂䅁䅁权䙁䅁䅁兂䅁䅁䅁䭑氯䅑䅅䅁䉁䅁䅁兂㙃兓䍷祋祣䅑杷允䅁䅁䅕䅁䑁䅁䅷䅁䭁䉁䅷䅁䭁䙁䅍䅁䭁䅁䅕䅁䙁䅁䅁䅁权敧䅚允䅁䅁䅅䅁䙁䵁㉬灶愸祲䄱䍄䉁䅁䅁䅂䅁䅁䅍䅄䅁䅁䅯睔䅁䅁䅯杔䅁䅁䅕䅁䅁䕁剁欵䉁䅁䅁允䅁䅁䅕牕敧敨剴ぅ䵁䅉䅅䅁䙁䅁䅁睁䵁䅁䅁权晁䅁䅁权呂䅁䅁权䙁䅁䅁兂䅁䅁䅁佷汲䅑䅅䅁䉁䅁䅁兂橁⼲⭬污睷䅑杷允䅁䅁䅕䅁䑁䅁䅷䅁䭁䉁䅯䅁䭁䙁䅍䅁䭁䅁䅕䅁䙁䅁䅁䅁䅁畢䅚允䅁䅁䅅䅁䙁䍁搯䅊䉡呖䅴䍄䉁䅁䅁兂䅁䅁䅍䅄䅁䅁䅯睈䅁䅁䅯睕䅁䅁䅯兂䅁䅁䅕䅁䅁䭁䩂欵䉁䅁䅁允䅁䅁䅕䙂余扌摉啍䵁䅉䅅䅁䙁䅁䅁睁䵁䅁䅁权䅁䅁䅁权呂䅁䅁权䙁䅁䅁兂䅁䅁䅁䜴浮䅑䅅䅁䉁䅁䅁兂啂㘴扗佸穁䅑杷允䅁䅁䅕䅁䑁䅁䅷䅁䭁䉁䄸䅁䭁䙁䅍䅁䭁䅁䅕䅁䙁䅁䅁䅁杄畕䅚允䅁䅁䅅䅁䙁䡁⼰噎㘶呋䅆䍄䉁䅁䅁兂䅁䅁䅍䅄䅁䅁䅯睈䅁䅁䅯睕䅁䅁䅯兂䅁䅁䅕䅁䅁䵁捄唵䉁䅁䅁允䅁䅁䅕祇搯䅊桢䕍䵁䅉䅅䅁䕁䅁䅁睁䵁䅁䅁权偂䅁䅁权佂䅁䅁兂䅁䅁䅁䝯浺䅑䅅䅁䉁䅁䅁兂䥂場啯歲乣䅑杷允䅁䅁䅕䅁䑁䅁䅷䅁䭁䅁䅁䅁䭁䙁䅍䅁䭁䅁䅕䅁䙁䅁䅁䅁权甫䅖允䅁䅁䅅䅁䙁䍁捬㡪ㅌ䑡䅊䍄䉁䅁䅁䅂䅁䅁䅍䅄䅁䅁䅯䅁䅁䅁䅯睕䅁䅁䅕䅁䅁䝁䍃欵䉁䅁䅁允䅁䅁䅯䅂䅁䅁杷允䅁䅁䅕䅁䑁䅁䅷䅁䭁䅁䅁䅁䭁䅁䅅䅁䭁䅁䅕䅁䙁䅁䅁䅁䅁敍䅚允䅁䅁䅅䅁䙁䱁敧敨剴乵⼴䍄䉁䅁䅁兂䅁䅁䅍䅄䅁䅁䅯䅁䅁䅁䅯睕䅁䅁䅯兂䅁䅁䅕䅁䅁佁䥁欵䉁䅁䅁允䅁䅁䅕癱午坔睊歍䵁䅉䅅䅁䙁䅁䅁睁䵁䅁䅁权晁䅁䅁权䉁䅁䅁权䙁䅁䅁兂䅁䅁䅁䝯浌䅑䅅䅁䉁䅁䅁兂㉄䙋偹癷杘睐杷允䅁䅁䅑䅁䑁䅁䅷䅁䭁䕁䄸䅁䭁䕁䄴䅁䙁䅁䅁䅁杂⭌䅚允䅁䅁䅅䅁䙁乁橥䑣䬰砱䅊䍄䉁䅁䅁兂䅁䅁䅍䅄䅁䅁䅯䅁䅁䅁䅯睕䅁䅁䅯兂䅁䅁䅕䅁䅁䍁㡁欵䉁䅁䅁允䅁䅁䅕䅁䅁䅁权き䵁䅉䅅䅁䕁䅁䅁睁䵁䅁䅁权偂䅁䅁权佂䅁䅁兂䅁䅁䅁偷汶䅑䅅䅁䉁䅁䅁兂㑃潈牘払䵧䅑杷允䅁䅁䅕䅁䑁䅁䅷䅁䭁䅁䅁䅁䭁䙁䅍䅁䭁䅁䅕䅁䙁䅁䅁䅁䅂敆䅚允䅁䅁䅅䅁䙁䝁匸㡧䭄呁䅎䍄䉁䅁䅁兂䅁䅁䅍䅄䅁䅁䅯先䅁䅁䅯睕䅁䅁䅯兂䅁䅁䅕䅁䅁䕁䱂欵䉁䅁䅁允䅁䅁䅕婤奍䙂佡歌䵁䅉䅅䅁䕁䅁䅁睁䵁䅁䅁权偂䅁䅁权佂䅁䅁兂䅁䅁䅁乙氯䅑䅅䅁䉁䅁䅁兂桄桥畓⭒䭅䅑杷允䅁䅁䅕䅁䑁䅁䅷䅁䭁䉁䅷䅁䭁䙁䅍䅁䭁䅁䅕䅁䙁䅁䅁䅁䅃攷䅖允䅁䅁䅅䅁䙁䱁䩰䅄牉祸䄱䍄䉁䅁䅁兂䅁䅁䅍䅄䅁䅁䅯睈䅁䅁䅯睕䅁䅁䅯兂䅁䅁䅕䅁䅁䝁祂欵䉁䅁䅁允䅁䅁䅕牡へ硫歧啍䵁䅉䅅䅁䕁䅁䅁睁䵁䅁䅁权偂䅁䅁权佂䅁䅁兂䅁䅁䅁䡧浔䅑䅅䅁䉁䅁䅁兂䑄匹捨㡪䱉䅑杷允䅁䅁䅕䅁䑁䅁䅷䅁䭁䉁䄰䅁䭁䙁䅍䅁䭁䅁䅕䅁䙁䅁䅁䅁杄敬䅖允䅁䅁䅅䅁䙁䱁へ硫䕧楖䄱䍄䉁䅁䅁兂䅁䅁䅍䅄䅁䅁䅯䅁䅁䅁䅯允䅁䅁䅯兂䅁䅁䅕䅁䅁䕁剂欵䉁䅁䅁允䅁䅁䅕䉵䘶ㄶ㑇樳䴸䅉䅅䅁䙁䅁䅁睁䵁䅁䅁权摁䅁䅁权䉁䅁䅁权䙁䅁䅁兂䅁䅁䅁䄴浘䅑䅅䅁䉁䅁䅁兂晁敨剴䉵嘷睐杷允䅁䅁䅕䅁䑁䅁䅷䅁䭁䉁䄴䅁䭁䙁䅍䅁䭁䅁䅕䅁䙁䅁䅁䅁䅄敹䅖允䅁䅁䅅䅁䙁䍁䡵瑆佮祴䅸䍄䉁䅁䅁兂䅁䅁䅍䅄䅁䅁䅯睈䅁䅁䅯允䅁䅁䅯兂䅁䅁䅕䅁䅁䅁桂欵䉁䅁䅁允䅁䅁䅕椹捨㡪ㅌ䐴䴸䅉䅅䅁䙁䅁䅁睁䵁䅁䅁权晁䅁䅁权呂䅁䅁权䙁䅁䅁兂䅁䅁䅁䉧浲䅑䅅䅁䉁䅁䅁兂䝂癴㥐倱睧䅑杷允䅁䅁䅑䅁䑁䅁䅷䅁䭁䕁䄸䅁䭁䕁䄴䅁䙁䅁䅁䅁杂畏䅚允䅁䅁䅅䅁䙁佁㙆䭆䠵儴䄵䍄䉁䅁䅁兂䅁䅁䅍䅄䅁䅁䅯䅈䅁䅁䅯允䅁䅁䅯兂䅁䅁䅕䅁䅁䥁㝂欵䉁䅁䅁允䅁䅁䅕椹捨㡪ㅌ䐲䴸䅉䅅䅁䕁䅁䅁睁䵁䅁䅁权偂䅁䅁权佂䅁䅁兂䅁䅁䅁䥑浌䅑䅅䅁䉁䅁䅁兂硂児塲㍯乁䅑杷允䅁䅁䅑䅁䑁䅁䅷䅁䭁䕁䄸䅁䭁䕁䄴䅁䙁䅁䅁䅁䅃佴䅖允䅁䅁䅅䅁䙁䍁捬㡪ㅌ之⽷䍄䉁䅁䅁䅂䅁䅁䅍䅄䅁䅁䅯睔䅁䅁䅯杔䅁䅁䅕䅁䅁䝁佄唵䉁䅁䅁允䅁䅁䅕㘱睎児塲啂䵁䅉䅅䅁䕁䅁䅁睁䵁䅁䅁权偂䅁䅁权佂䅁䅁兂䅁䅁䅁临汔䅑䅅䅁䉁䅁䅁兂晁敨剴䉵䘴䅑杷允䅁䅁䅕䅁䑁䅁䅷䅁䭁䅁䅁䅁䭁䅁䅅䅁䭁䅁䅕䅁䙁䅁䅁䅁权佅䅚允䅁䅁䅅䅁䙁䱁敧敨剴乵⼴䍄䉁䅁䅁䅂䅁䅁䅍䅄䅁䅁䅯睔䅁䅁䅯杔䅁䅁䅕䅁䅁䵁㙁欵䉁䅁䅁允䅁䅁䅕㡪ㅌ䙋偹歄䵁䅉䅅䅁䙁䅁䅁睁䵁䅁䅁权慁䅁䅁权䉁䅁䅁权䙁䅁䅁兂䅁䅁䅁䙉浲䅑䅅䅁䉁䅁䅁兂歃䑣䬰㘱潐睐杷允䅁䅁䅕䅁䑁䅁䅷䅁䭁䉁䅯䅁䭁䙁䅍䅁䭁䅁䅕䅁䙁䅁䅁䅁杄敉䅚允䅁䅁䅅䅁䙁䱁穢搯㑒呩䅰䍄䉁䅁䅁兂䅁䅁䅍䅄䅁䅁䅯先䅁䅁䅯睕䅁䅁䅯兂䅁䅁䅕䅁䅁䭁䥁欵䉁䅁䅁允䅁䅁䅕䝭匴㡧䭂歌䵁䅉䅅䅁䙁䅁䅁睁䵁䅁䅁权䅁䅁䅁权呂䅁䅁权䙁䅁䅁兂䅁䅁䅁䵉決䅑䅅䅁䉁䅁䅁兂瑂⼵灵昸祉䅑杷允䅁䅁䅑䅁䑁䅁䅷䅁䭁䕁䄸䅁䭁䕁䄴䅁䙁䅁䅁䅁杂⭥䅚允䅁䅁䅅䅁䙁䕁桪桥畓睒䄱䍄䉁䅁䅁䅂䅁䅁䅍䅄䅁䅁䅯睔䅁䅁䅯杔䅁䅁䅕䅁䅁䕁捁欵䉁䅁䅁允䅁䅁䅕噋偹癷潕䕅䵁䅉䅅䅁䕁䅁䅁睁䵁䅁䅁权偂䅁䅁权佂䅁䅁兂䅁䅁䅁䡧洯䅑䅅䅁䉁䅁䅁兂慃婭婭婭䱫䅑杷允䅁䅁䅕䅁䑁䅁䅷䅁䭁䉁䄸䅁䭁䅁䅅䅁䭁䅁䅕䅁䙁䅁䅁䅁䅂位䅚允䅁䅁䅅䅁䙁䕁桪桥畓⭒⽅䍄䉁䅁䅁兂䅁䅁䅍䅄䅁䅁䅯䅁䅁䅁䅯睕䅁䅁䅯兂䅁䅁䅕䅁䅁䍁㕄唵䉁䅁䅁允䅁䅁䅕噋偹癷潖歍䵁䅉䅅䅁䕁䅁䅁睁䵁䅁䅁权偂䅁䅁权佂䅁䅁兂䅁䅁䅁䍉浮䅑䅅䅁䉁䅁䅁兂獄払敧敨剳䅑杷允䅁䅁䅕䅁䑁䅁䅷䅁䭁䉁䄰䅁䭁䙁䅍䅁䭁䅁䅕䅁䙁䅁䅁䅁䅃敹䅖允䅁䅁䅅䅁䙁䍁捬㡪ㅌ䍋䄵䍄䉁䅁䅁兂䅁䅁䅍䅄䅁䅁䅯䅁䅁䅁䅯睕䅁䅁䅯兂䅁䅁䅕䅁䅁䵁穃唵䉁䅁䅁允䅁䅁䅕歵䵫楁湳歍䵁䅉䅅䅁䙁䅁䅁睁䵁䅁䅁权捁䅁䅁权呂䅁䅁权䙁䅁䅁兂䅁䅁䅁乁氯䅑䅅䅁䉁䅁䅁兂楂䙅㕧䕴畧䅑杷允䅁䅁䅕䅁䑁䅁䅷䅁䭁䉁䄰䅁䭁䙁䅍䅁䭁䅁䅕䅁䙁䅁䅁䅁杁敖䅚允䅁䅁䅅䅁䙁䵁ㅐ䙋偹楧䄵䍄䉁䅁䅁兂䅁䅁䅍䅄䅁䅁䅯杈䅁䅁䅯允䅁䅁䅯兂䅁䅁䅕䅁䅁䍁噁欵䉁䅁䅁允䅁䅁䅕⽷潕䥘䌯吱䴸䅉䅅䅁䕁䅁䅁睁䵁䅁䅁权偂䅁䅁权佂䅁䅁兂䅁䅁䅁䕑洳䅑䅅䅁䉁䅁䅁兂卂䉵䘶ㄶ剅䅑杷允䅁䅁䅕䅁䑁䅁䅷䅁䭁䉁䅷䅁䭁䙁䅍䅁䭁䅁䅕䅁䙁䅁䅁䅁杁佘䅚允䅁䅁䅅䅁䙁䭁䙊癴㥐䍆䄵䍄䉁䅁䅁兂䅁䅁䅍䅄䅁䅁䅯杈䅁䅁䅯睕䅁䅁䅯兂䅁䅁䅕䅁䅁䭁⽁欵䉁䅁䅁允䅁䅁䅕倹唳佥浬䕊䵁䅉䅅䅁䕁䅁䅁睁䵁䅁䅁权偂䅁䅁权佂䅁䅁兂䅁䅁䅁䡯洷䅑䅅䅁䉁䅁䅁兂硂児塲㍯䱁䅑杷允䅁䅁䅑䅁䑁䅁䅷䅁䭁䕁䄸䅁䭁䕁䄴䅁䙁䅁䅁䅁杄伷䅖允䅁䅁䅅䅁䙁䍁捬㡪ㅌ䉋䅂䍄䉁䅁䅁䅂䅁䅁䅍䅄䅁䅁䅯睔䅁䅁䅯杔䅁䅁䅕䅁䅁䅁坂欵䉁䅁䅁允䅁䅁䅕体㙆䭆䠵い䵁䅉䅅䅁䙁䅁䅁睁䵁䅁䅁权敁䅁䅁权䉁䅁䅁权䙁䅁䅁兂䅁䅁䅁䍯浐䅑䅅䅁䉁䅁䅁兂䑄匹捨㡪噌睐杷允䅁䅁䅕䅁䑁䅁䅷䅁䭁䅁䅁䅁䭁䅁䅅䅁䭁䅁䅕䅁䙁䅁䅁䅁䅂甲䅖允䅁䅁䅅䅁䙁佁㙆䭆䠵搴⽯䍄䉁䅁䅁䅂䅁䅁䅍䅄䅁䅁䅯睔䅁䅁䅯杔䅁䅁䅕䅁䅁䭁䝂欵䉁䅁䅁允䅁䅁䅕㘱睎児塲䕅䵁䅉䅅䅁䙁䅁䅁睁䵁䅁䅁权䅁䅁䅁权呂䅁䅁权䙁䅁䅁兂䅁䅁䅁䘴浘䅑䅅䅁䉁䅁䅁兂㕁䵴㉨瑶稸䅑杷允䅁䅁䅑䅁䑁䅁䅷䅁䭁䕁䄸䅁䭁䕁䄴䅁䙁䅁䅁䅁权佴䅖允䅁䅁䅅䅁䙁䥁牘払敧摨⽳䍄䉁䅁䅁兂䅁䅁䅍䅄䅁䅁䅯䅈䅁䅁䅯允䅁䅁䅯兂䅁䅁䅕䅁䅁䵁乂欵䉁䅁䅁允䅁䅁䅕椹捨㡪ㅌ䐲䴸䅉䅅䅁䙁䅁䅁睁䵁䅁䅁权慁䅁䅁权呂䅁䅁权䙁䅁䅁兂䅁䅁䅁䱑氷䅑䅅䅁䉁䅁䅁兂㙃兓䍷祋㙣䅑杷允䅁䅁䅕䅁䑁䅁䅷䅁䭁䉁䄴䅁䭁䅁䅅䅁䭁䅁䅕䅁䙁䅁䅁䅁杄畱䅖允䅁䅁䅅䅁䙁䑁積積積㥍⽍䍄䉁䅁䅁兂䅁䅁䅍䅄䅁䅁䅯睈䅁䅁䅯睕䅁䅁䅯兂䅁䅁䅕䅁䅁䥁塄唵䉁䅁䅁允䅁䅁䅕祇搯䅊桢䕍䵁䅉䅅䅁䕁䅁䅁睁䵁䅁䅁权偂䅁䅁权佂䅁䅁兂䅁䅁䅁䵑汔䅑䅅䅁䉁䅁䅁兂灁䥘䌯匹な睐杷允䅁䅁䅑䅁䑁䅁䅷䅁䭁䕁䄸䅁䭁䕁䄴䅁䙁䅁䅁䅁杁敄䅚允䅁䅁䅅䅁䙁䥁䌯匹捨硪䅊䍄䉁䅁䅁兂䅁䅁䅍䅄䅁䅁䅯先䅁䅁䅯睕䅁䅁䅯兂䅁䅁䅕䅁䅁䭁坁欵䉁䅁䅁允䅁䅁䅕歵䵫楁䡵歌䵁䅉䅅䅁䕁䅁䅁睁䵁䅁䅁权偂䅁䅁权佂䅁䅁兂䅁䅁䅁䍙浺䅑䅅䅁䉁䅁䅁兂穁積積積呍䅑杷允䅁䅁䅑䅁䑁䅁䅷䅁䭁䕁䄸䅁䭁䕁䄴䅁䙁䅁䅁䅁䅁敥䅚允䅁䅁䅅䅁䙁䝁浚浚浚杚䅸䍄䉁䅁䅁䅂䅁䅁䅍䅄䅁䅁䅯睔䅁䅁䅯杔䅁䅁䅕䅁䅁佁摄唵䉁䅁䅁允䅁䅁䅕瑃橥䑣䬰啃䵁䅉䅅䅁䕁䅁䅁睁䵁䅁䅁权偂䅁䅁权佂䅁䅁兂䅁䅁䅁䡯浌䅑䅅䅁䉁䅁䅁兂浂浚浚浚䵙䅑杷允䅁䅁䅕䅁䑁䅁䅷䅁䭁䉁䄰䅁䭁䙁䅍䅁䭁䅁䅕䅁䙁䅁䅁䅁䅃畲䅖允䅁䅁䅅䅁䙁乁佮ㄹ橐印䄱䍄䉁䅁䅁䅂䅁䅁䅍䅄䅁䅁䅯睔䅁䅁䅯杔䅁䅁䅕䅁䅁䍁楂欵䉁䅁䅁允䅁䅁䅕䉵䘶ㄶ㑇歄䵁䅉䅅䅁䙁䅁䅁睁䵁䅁䅁权慁䅁䅁权呂䅁䅁权䙁䅁䅁兂䅁䅁䅁䈴浐䅑䅅䅁䉁䅁䅁兂䝁婧䑖ど㙷䅑杷允䅁䅁䅕䅁䑁䅁䅷䅁䭁䅁䅁䅁䭁䅁䅅䅁䭁䅁䅕䅁䙁䅁䅁䅁䅄敥䅚允䅁䅁䅅䅁䙁䱁敧敨剴乵⼴䍄䉁䅁䅁兂䅁䅁䅍䅄䅁䅁䅯䅁䅁䅁䅯睕䅁䅁䅯兂䅁䅁䅕䅁䅁佁⭁欵䉁䅁䅁允䅁䅁䅕䅁䅁䅁权き䵁䅉䅅䅁䙁䅁䅁睁䵁䅁䅁权慁䅁䅁权呂䅁䅁权䙁䅁䅁兂䅁䅁䅁义汄䅑䅅䅁䉁䅁䅁兂权楇搯䕊㙙䅑杷允䅁䅁䅕䅁䑁䅁䅷䅁䭁䉁䄸䅁䭁䙁䅍䅁䭁䅁䅕䅁䙁䅁䅁䅁杂佧䅚允䅁䅁䅅䅁䙁䝁汄䌰扌含䅂䍄䉁䅁䅁䅂䅁䅁䅍䅄䅁䅁䅯睔䅁䅁䅯杔䅁䅁䅕䅁䅁䅁乁欵䉁䅁䅁允䅁䅁䅕䅁䅁䅁䅁ぅ䵁䅉䅅䅁䙁䅁䅁睁䵁䅁䅁权摁䅁䅁权呂䅁䅁权䙁䅁䅁兂䅁䅁䅁䉙浄䅑䅅䅁䉁䅁䅁兂㙃兓䍷㑋畣䅑杷允䅁䅁䅑䅁䑁䅁䅷䅁䭁䕁䄸䅁䭁䕁䄴䅁䙁䅁䅁䅁杄畸䅖允䅁䅁䅅䅁䙁䭁睒児塲⽯⽧䍄䉁䅁䅁兂䅁䅁䅍䅄䅁䅁䅯䅁䅁䅁䅯允䅁䅁䅯兂䅁䅁䅕䅁䅁䭁煂欵䉁䅁䅁允䅁䅁䅕䉵䘶ㄶ㑇樳䴸䅉䅅䅁䙁䅁䅁睁䵁䅁䅁权䅁䅁䅁权䉁䅁䅁权䙁䅁䅁兂䅁䅁䅁偁氷䅑䅅䅁䉁䅁䅁兂㑃潈牘払敪睐杷允䅁䅁䅑䅁䑁䅁䅷䅁䭁䕁䄸䅁䭁䕁䄴䅁䙁䅁䅁䅁杁畧䅚允䅁䅁䅅䅁䙁䥁牘払敧全䄱䍄䉁䅁䅁兂䅁䅁䅍䅄䅁䅁䅯杈䅁䅁䅯允䅁䅁䅯兂䅁䅁䅕䅁䅁䭁䑂欵䉁䅁䅁允䅁䅁䅕⽷潕䥘䌯吱䴸䅉䅅䅁䕁䅁䅁睁䵁䅁䅁权偂䅁䅁权佂䅁䅁兂䅁䅁䅁偧汄䅑䅅䅁䉁䅁䅁兂畃⭒㙆䭆倴䅑杷允䅁䅁䅕䅁䑁䅁䅷䅁䭁䉁䄴䅁䭁䙁䅍䅁䭁䅁䅕䅁䙁䅁䅁䅁䅃⭙䅚允䅁䅁䅅䅁䙁䩁瑈䑦ㄸ楘䅊䍄䉁䅁䅁䅂䅁䅁䅍䅄䅁䅁䅯睔䅁䅁䅯杔䅁䅁䅕䅁䅁䵁慂欵䉁䅁䅁允䅁䅁䅕児塲㍯㥁歄䵁䅉䅅䅁䙁䅁䅁睁䵁䅁䅁权慁䅁䅁权呂䅁䅁权䙁䅁䅁兂䅁䅁䅁䉉浮䅑䅅䅁䉁䅁䅁兂㉃⼸唳䥥㙫䅑杷允䅁䅁䅕䅁䑁䅁䅷䅁䭁䉁䅯䅁䭁䅁䅅䅁䭁䅁䅕䅁䙁䅁䅁䅁杂佢䅚允䅁䅁䅅䅁䙁䭁睒児塲⭯⽧䍄䉁䅁䅁兂䅁䅁䅍䅄䅁䅁䅯䅈䅁䅁䅯睕䅁䅁䅯兂䅁䅁䅕䅁䅁䅁汁欵䉁䅁䅁允䅁䅁䅕㡪ㅌ䙋偷歌䵁䅉䅅䅁䕁䅁䅁睁䵁䅁䅁权偂䅁䅁权佂䅁䅁兂䅁䅁䅁义汐䅑䅅䅁䉁䅁䅁兂䅁䅁䅁䅁䝁䅑杷允䅁䅁䅕䅁䑁䅁䅷䅁䭁䉁䄴䅁䭁䙁䅍䅁䭁䅁䅕䅁䙁䅁䅁䅁䅂佦䅚允䅁䅁䅅䅁䙁䍁捬㡪ㅌ䍡䅆䍄䉁䅁䅁䅂䅁䅁䅍䅄䅁䅁䅯睔䅁䅁䅯杔䅁䅁䅕䅁䅁䭁㙃唵䉁䅁䅁允䅁䅁䅕体㙆䭆䠵吶䴸䅉䅅䅁䙁䅁䅁睁䵁䅁䅁权晁䅁䅁权䉁䅁䅁权䙁䅁䅁兂䅁䅁䅁䈴浺䅑䅅䅁䉁䅁䅁兂㉄䙋偹癷杘睐杷允䅁䅁䅕䅁䑁䅁䅷䅁䭁䅁䅁䅁䭁䙁䅍䅁䭁䅁䅕䅁䙁䅁䅁䅁䅂畚䅚允䅁䅁䅅䅁䙁䙁橔婰䕶䐴䅎䍄䉁䅁䅁䅂䅁䅁䅍䅄䅁䅁䅯睔䅁䅁䅯杔䅁䅁䅕䅁䅁䍁偁欵䉁䅁䅁允䅁䅁䅕䉵䘶ㄶ㑇歅䵁䅉䅅䅁䙁䅁䅁睁䵁䅁䅁权敁䅁䅁权䉁䅁䅁权䙁䅁䅁兂䅁䅁䅁䱷汮䅑䅅䅁䉁䅁䅁兂穁積積積呐睐杷允䅁䅁䅕䅁䑁䅁䅷䅁䭁䅁䅁䅁䭁䅁䅅䅁䭁䅁䅕䅁䙁䅁䅁䅁杂畅䅚允䅁䅁䅅䅁䙁䱁敧敨剴乵⼴䍄䉁䅁䅁兂䅁䅁䅍䅄䅁䅁䅯䅁䅁䅁䅯睕䅁䅁䅯兂䅁䅁䅕䅁䅁佁杂欵䉁䅁䅁允䅁䅁䅕癱午坔兌き䵁䅉䅅䅁䕁䅁䅁睁䵁䅁䅁权偂䅁䅁权佂䅁䅁兂䅁䅁䅁䡯洯䅑䅅䅁䉁䅁䅁兂䑄匹捨㡪䱉䅑杷允䅁䅁䅕䅁䑁䅁䅷䅁䭁䉁䅯䅁䭁䅁䅅䅁䭁䅁䅕䅁䙁䅁䅁䅁权⬳䅖允䅁䅁䅅䅁䙁偁潙䥘䌯改⽁䍄䉁䅁䅁兂䅁䅁䅍䅄䅁䅁䅯睈䅁䅁䅯睕䅁䅁䅯兂䅁䅁䅕䅁䅁佁啄唵䉁䅁䅁允䅁䅁䅕祇搯䅊桢䕍䵁䅉䅅䅁䕁䅁䅁睁䵁䅁䅁权偂䅁䅁权佂䅁䅁兂䅁䅁䅁䥷浈䅑䅅䅁䉁䅁䅁兂獄払敧敨乳䅑杷允䅁䅁䅕䅁䑁䅁䅷䅁䭁䅁䅁䅁䭁䅁䅅䅁䭁䅁䅕䅁䙁䅁䅁䅁䅁⭐䅚允䅁䅁䅅䅁䙁䱁敧敨剴乵⼴䍄䉁䅁䅁兂䅁䅁䅍䅄䅁䅁䅯睈䅁䅁䅯允䅁䅁䅯兂䅁䅁䅕䅁䅁䕁牄唵䉁䅁䅁允䅁䅁䅕場啯歲桦樲䴸䅉䅅䅁䙁䅁䅁睁䵁䅁䅁权䅁䅁䅁权呂䅁䅁权䙁䅁䅁兂䅁䅁䅁䭧汈䅑䅅䅁䉁䅁䅁兂塄㍯㥁癃督䅑杷允䅁䅁䅕䅁䑁䅁䅷䅁䭁䉁䅷䅁䭁䅁䅅䅁䭁䅁䅕䅁䙁䅁䅁䅁杂敦䅚允䅁䅁䅅䅁䙁偁潙䥘䌯搹⽧䍄䉁䅁䅁兂䅁䅁䅍䅄䅁䅁䅯先䅁䅁䅯睕䅁䅁䅯兂䅁䅁䅕䅁䅁䝁兂欵䉁䅁䅁允䅁䅁䅕婤奍䙂佡歌䵁䅉䅅䅁䕁䅁䅁睁䵁䅁䅁权偂䅁䅁权佂䅁䅁兂䅁䅁䅁䝙浪䅑䅅䅁䉁䅁䅁兂晁敨剴䉵临䅑杷允䅁䅁䅑䅁䑁䅁䅷䅁䭁䕁䄸䅁䭁䕁䄴䅁䙁䅁䅁䅁䅃畸䅖允䅁䅁䅅䅁䙁䵁䴳䵺䵺偺⽧䍄䉁䅁䅁兂䅁䅁䅍䅄䅁䅁䅯杈䅁䅁䅯允䅁䅁䅯兂䅁䅁䅕䅁䅁䭁祄唵䉁䅁䅁允䅁䅁䅕積積積積稰䴸䅉䅅䅁䕁䅁䅁睁䵁䅁䅁权偂䅁䅁权佂䅁䅁兂䅁䅁䅁䥯浈䅑䅅䅁䉁䅁䅁兂䅁䅁䅁䅁佁䅑杷允䅁䅁䅕䅁䑁䅁䅷䅁䭁䉁䄸䅁䭁䙁䅍䅁䭁䅁䅕䅁䙁䅁䅁䅁䅃⭆䅚允䅁䅁䅅䅁䙁䕁㉡⼸唳䐫䅂䍄䉁䅁䅁兂䅁䅁䅍䅄䅁䅁䅯睈䅁䅁䅯允䅁䅁䅯兂䅁䅁䅕䅁䅁䕁䩂欵䉁䅁䅁允䅁䅁䅕䡰㥁瑃橥䐴䴸䅉䅅䅁䙁䅁䅁睁䵁䅁䅁权晁䅁䅁权呂䅁䅁权䙁䅁䅁兂䅁䅁䅁䑧浘䅑䅅䅁䉁䅁䅁兂⽁噎㘶卓硷䅑杷允䅁䅁䅑䅁䑁䅁䅷䅁䭁䕁䄸䅁䭁䕁䄴䅁䙁䅁䅁䅁䅂⭹䅖允䅁䅁䅅䅁䙁䙁㑋潈牘兕䅂䍄䉁䅁䅁兂䅁䅁䅍䅄䅁䅁䅯睈䅁䅁䅯睕䅁䅁䅯兂䅁䅁䅕䅁䅁䕁硄唵䉁䅁䅁允䅁䅁䅕㥉㕶浦捰䕍䵁䅉䅅䅁䙁䅁䅁睁䵁䅁䅁权慁䅁䅁权呂䅁䅁权䙁䅁䅁兂䅁䅁䅁䭉汮䅑䅅䅁䉁䅁䅁兂摁浗㝑㐳㔸䅑杷允䅁䅁䅑䅁䑁䅁䅷䅁䭁䕁䄸䅁䭁䕁䄴䅁䙁䅁䅁䅁杂支䅖允䅁䅁䅅䅁䙁䵁ㅐ䙋偹杷䄹䍄䉁䅁䅁兂䅁䅁䅍䅄䅁䅁䅯杈䅁䅁䅯允䅁䅁䅯兂䅁䅁䅕䅁䅁䵁偄唵䉁䅁䅁允䅁䅁䅕積積積積稰䴸䅉䅅䅁䙁䅁䅁睁䵁䅁䅁权慁䅁䅁权呂䅁䅁权䙁䅁䅁兂䅁䅁䅁䅉浪䅑䅅䅁䉁䅁䅁兂䝂癴㥐䈱㙧䅑杷允䅁䅁䅕䅁䑁䅁䅷䅁䭁䅁䅁䅁䭁䙁䅍䅁䭁䅁䅕䅁䙁䅁䅁䅁权敷䅖允䅁䅁䅅䅁䙁偁周㘴扗䑨䅊䍄䉁䅁䅁䅂䅁䅁䅍䅄䅁䅁䅯睔䅁䅁䅯杔䅁䅁䅕䅁䅁䝁卄唵䉁䅁䅁允䅁䅁䅕硥畓⭒㙆歂䵁䅉䅅䅁䙁䅁䅁睁䵁䅁䅁权捁䅁䅁权䉁䅁䅁权䙁䅁䅁兂䅁䅁䅁䅧浲䅑䅅䅁䉁䅁䅁兂晁敨剴䉵嘷睐杷允䅁䅁䅕䅁䑁䅁䅷䅁䭁䅁䅁䅁䭁䅁䅅䅁䭁䅁䅕䅁䙁䅁䅁䅁䅁佴䅖允䅁䅁䅅䅁䙁䩁婱婭婭摭⽫䍄䉁䅁䅁兂䅁䅁䅍䅄䅁䅁䅯杇䅁䅁䅯允䅁䅁䅯兂䅁䅁䅕䅁䅁䅁坂欵䉁䅁䅁允䅁䅁䅕䡰㥁瑃橥䐶䴸䅉䅅䅁䙁䅁䅁睁䵁䅁䅁权摁䅁䅁权呂䅁䅁权䙁䅁䅁兂䅁䅁䅁䑷浈䅑䅅䅁䉁䅁䅁兂坂楄礲敮甸䅑杷允䅁䅁䅕䅁䑁䅁䅷䅁䭁䉁䄸䅁䭁䙁䅍䅁䭁䅁䅕䅁䙁䅁䅁䅁䅂⭣䅚允䅁䅁䅅䅁䙁䝁㡱䩤奍䑊䅆䍄䉁䅁䅁兂䅁䅁䅍䅄䅁䅁䅯䅁䅁䅁䅯允䅁䅁䅯兂䅁䅁䅕䅁䅁䝁䱄唵䉁䅁䅁允䅁䅁䅕児塲㍯㥁樲䴸䅉䅅䅁䙁䅁䅁睁䵁䅁䅁权慁䅁䅁权呂䅁䅁权䙁䅁䅁兂䅁䅁䅁佑汄䅑䅅䅁䉁䅁䅁兂䑄匹捨⭪㕉䅑杷允䅁䅁䅑䅁䑁䅁䅷䅁䭁䕁䄸䅁䭁䕁䄴䅁䙁䅁䅁䅁杁佰䅖允䅁䅁䅅䅁䙁䡁啳歲桦瑥⽑䍄䉁䅁䅁兂䅁䅁䅍䅄䅁䅁䅯䅈䅁䅁䅯睕䅁䅁䅯兂䅁䅁䅕䅁䅁䅁⽃唵䉁䅁䅁允䅁䅁䅕場啯歲桤歌䵁䅉䅅䅁䙁䅁䅁睁䵁䅁䅁权摁䅁䅁权呂䅁䅁权䙁䅁䅁兂䅁䅁䅁䡧浪䅑䅅䅁䉁䅁䅁兂睄㡰䱚㡎瑫䅑杷允䅁䅁䅕䅁䑁䅁䅷䅁䭁䅁䅁䅁䭁䙁䅍䅁䭁䅁䅕䅁䙁䅁䅁䅁杄佅䅚允䅁䅁䅅䅁䙁䉁奂扏䥔橬䅊䍄䉁䅁䅁䅂䅁䅁䅍䅄䅁䅁䅯睔䅁䅁䅯杔䅁䅁䅕䅁䅁䝁晁欵䉁䅁䅁允䅁䅁䅕䭆䠵場啯䕅䵁䅉䅅䅁䙁䅁䅁睁䵁䅁䅁权慁䅁䅁权䉁䅁䅁权䙁䅁䅁兂䅁䅁䅁䴴汐䅑䅅䅁䉁䅁䅁兂䅁䅁䅁䅁杄睐杷允䅁䅁䅕䅁䑁䅁䅷䅁䭁䉁䄰䅁䭁䙁䅍䅁䭁䅁䅕䅁䙁䅁䅁䅁权甫䅖允䅁䅁䅅䅁䙁䝁汄䌰扌匫䄱䍄䉁䅁䅁䅂䅁䅁䅍䅄䅁䅁䅯睔䅁䅁䅯杔䅁䅁䅕䅁䅁䥁䑁欵䉁䅁䅁允䅁䅁䅕㘱睎児塲䕅䵁䅉䅅䅁䙁䅁䅁睁䵁䅁䅁权慁䅁䅁权呂䅁䅁权䙁䅁䅁兂䅁䅁䅁䭯汢䅑䅅䅁䉁䅁䅁兂摁浗㝑㐳㔸䅑杷允䅁䅁䅑䅁䑁䅁䅷䅁䭁䕁䄸䅁䭁䕁䄴䅁䙁䅁䅁䅁杁畬䅖允䅁䅁䅅䅁䙁䍁捬㡪ㅌ䵋⽷䍄䉁䅁䅁兂䅁䅁䅍䅄䅁䅁䅯杇䅁䅁䅯允䅁䅁䅯兂䅁䅁䅕䅁䅁䭁⭃唵䉁䅁䅁允䅁䅁䅕䅁䅁䅁䅁䐴䴸䅉䅅䅁䙁䅁䅁睁䵁䅁䅁权捁䅁䅁权䉁䅁䅁权䙁䅁䅁兂䅁䅁䅁倴汌䅑䅅䅁䉁䅁䅁兂穁積積積呐睐杷允䅁䅁䅕䅁䑁䅁䅷䅁䭁䉁䅷䅁䭁䙁䅍䅁䭁䅁䅕䅁䙁䅁䅁䅁䅂⭗䅚允䅁䅁䅅䅁䙁䭁䙊癴㥐䍆䄵䍄䉁䅁䅁兂䅁䅁䅍䅄䅁䅁䅯先䅁䅁䅯睕䅁䅁䅯兂䅁䅁䅕䅁䅁䅁硂欵䉁䅁䅁允䅁䅁䅕㑎䉬余兕歌䵁䅉䅅䅁䕁䅁䅁睁䵁䅁䅁权偂䅁䅁权佂䅁䅁兂䅁䅁䅁䙙浌䅑䅅䅁䉁䅁䅁兂穁積積積免䅑杷允䅁䅁䅕䅁䑁䅁䅷䅁䭁䅁䅁䅁䭁䅁䅅䅁䭁䅁䅕䅁䙁䅁䅁䅁䅃佴䅖允䅁䅁䅅䅁䙁䩁婱婭婭摭⽫䍄䉁䅁䅁兂䅁䅁䅍䅄䅁䅁䅯䅁䅁䅁䅯允䅁䅁䅯兂䅁䅁䅕䅁䅁䥁坁欵䉁䅁䅁允䅁䅁䅕䉵䘶ㄶ㑇樳䴸䅉䅅䅁䕁䅁䅁睁䵁䅁䅁权偂䅁䅁权佂䅁䅁兂䅁䅁䅁䥧浈䅑䅅䅁䉁䅁䅁兂晁敨剴䉵临䅑杷允䅁䅁䅕䅁䑁䅁䅷䅁䭁䉁䅷䅁䭁䅁䅅䅁䭁䅁䅕䅁䙁䅁䅁䅁䅄⭣䅚允䅁䅁䅅䅁䙁偁潙䥘䌯搹⽧䍄䉁䅁䅁兂䅁䅁䅍䅄䅁䅁䅯杈䅁䅁䅯睕䅁䅁䅯兂䅁䅁䅕䅁䅁䥁流欵䉁䅁䅁允䅁䅁䅕婤奍䙂佢お䵁䅉䅅䅁䕁䅁䅁睁䵁䅁䅁权偂䅁䅁权佂䅁䅁兂䅁䅁䅁䱯汘䅑䅅䅁䉁䅁䅁兂㑃潈牘払敪睐杷允䅁䅁䅕䅁䑁䅁䅷䅁䭁䅁䅁䅁䭁䅁䅅䅁䭁䅁䅕䅁䙁䅁䅁䅁杄⬳䅖允䅁䅁䅅䅁䙁佁㙆䭆䠵搴⽯䍄䉁䅁䅁兂䅁䅁䅍䅄䅁䅁䅯䅈䅁䅁䅯睕䅁䅁䅯兂䅁䅁䅕䅁䅁䝁慄唵䉁䅁䅁允䅁䅁䅕浔光䑗ね歌䵁䅉䅅䅁䙁䅁䅁睁䵁䅁䅁权䅁䅁䅁权䉁䅁䅁权䙁䅁䅁兂䅁䅁䅁䵙汲䅑䅅䅁䉁䅁䅁兂㥁瑃橥䑣愳睐杷允䅁䅁䅑䅁䑁䅁䅷䅁䭁䕁䄸䅁䭁䕁䄴䅁䙁䅁䅁䅁杂佅䅚允䅁䅁䅅䅁䙁偁潙䥘䌯刹䅊䍄䉁䅁䅁兂䅁䅁䅍䅄䅁䅁䅯䅁䅁䅁䅯允䅁䅁䅯兂䅁䅁䅕䅁䅁䕁䙁欵䉁䅁䅁允䅁䅁䅕䉵䘶ㄶ㑇樳䴸䅉䅅䅁䙁䅁䅁睁䵁䅁䅁权䅁䅁䅁权䉁䅁䅁权䙁䅁䅁兂䅁䅁䅁䙁洳䅑䅅䅁䉁䅁䅁兂㑃潈牘払敪睐杷允䅁䅁䅕䅁䑁䅁䅷䅁䭁䉁䅯䅁䭁䅁䅅䅁䭁䅁䅕䅁䙁䅁䅁䅁䅃畈䅚允䅁䅁䅅䅁䙁䭁睒児塲⭯⽧䍄䉁䅁䅁兂䅁䅁䅍䅄䅁䅁䅯䅈䅁䅁䅯允䅁䅁䅯兂䅁䅁䅕䅁䅁䅁祄唵䉁䅁䅁允䅁䅁䅕積積積積稰䴸䅉䅅䅁䕁䅁䅁睁䵁䅁䅁权偂䅁䅁权佂䅁䅁兂䅁䅁䅁䡁浺䅑䅅䅁䉁䅁䅁兂䥂場啯歲乣䅑杷允䅁䅁䅕䅁䑁䅁䅷䅁䭁䉁䅯䅁䭁䙁䅍䅁䭁䅁䅕䅁䙁䅁䅁䅁杄畐䅚允䅁䅁䅅䅁䙁䵁杕䡳潊呍䅴䍄䉁䅁䅁兂䅁䅁䅍䅄䅁䅁䅯䅁䅁䅁䅯睕䅁䅁䅯兂䅁䅁䅕䅁䅁䵁穄唵䉁䅁䅁允䅁䅁䅕積積積呏歍䵁䅉䅅䅁䙁䅁䅁睁䵁䅁䅁权敁䅁䅁权呂䅁䅁权䙁䅁䅁兂䅁䅁䅁䅁浮䅑䅅䅁䉁䅁䅁兂䅁䅁䅁䅁煁䅑杷允䅁䅁䅕䅁䑁䅁䅷䅁䭁䉁䄸䅁䭁䅁䅅䅁䭁䅁䅕䅁䙁䅁䅁䅁䅁⬫䅖允䅁䅁䅅䅁䙁䕁桪桥畓⭒⽅䍄䉁䅁䅁兂䅁䅁䅍䅄䅁䅁䅯䅁䅁䅁䅯允䅁䅁䅯兂䅁䅁䅕䅁䅁䝁湁欵䉁䅁䅁允䅁䅁䅕䉵䘶ㄶ㑇樳䴸䅉䅅䅁䙁䅁䅁睁䵁䅁䅁权慁䅁䅁权呂䅁䅁权䙁䅁䅁兂䅁䅁䅁䍙浦䅑䅅䅁䉁䅁䅁兂䥂場啯煲㙣䅑杷允䅁䅁䅑䅁䑁䅁䅷䅁䭁䕁䄸䅁䭁䕁䄴䅁䙁䅁䅁䅁䅂略䅚允䅁䅁䅅䅁䙁䱁敧敨剴䅵䅸䍄䉁䅁䅁兂䅁䅁䅍䅄䅁䅁䅯睈䅁䅁䅯允䅁䅁䅯兂䅁䅁䅕䅁䅁䍁㡁欵䉁䅁䅁允䅁䅁䅕䡰㥁瑃橥䐴䴸䅉䅅䅁䙁䅁䅁睁䵁䅁䅁权晁䅁䅁权䉁䅁䅁权䙁䅁䅁兂䅁䅁䅁䅁浌䅑䅅䅁䉁䅁䅁兂䅁䅁䅁䅁杄睐杷允䅁䅁䅕䅁䑁䅁䅷䅁䭁䅁䅁䅁䭁䙁䅍䅁䭁䅁䅕䅁䙁䅁䅁䅁䅄攵䅖允䅁䅁䅅䅁䙁䉁䕫杖琴樰䅊䍄䉁䅁䅁兂䅁䅁䅍䅄䅁䅁䅯杈䅁䅁䅯允䅁䅁䅯兂䅁䅁䅕䅁䅁䅁楂欵䉁䅁䅁允䅁䅁䅕䅁䅁䅁䅁䐰䴸䅉䅅䅁䕁䅁䅁睁䵁䅁䅁权偂䅁䅁权佂䅁䅁兂䅁䅁䅁䌴浺䅑䅅䅁䉁䅁䅁兂䙃ㄶ㑇潈单䅑杷允䅁䅁䅕䅁䑁䅁䅷䅁䭁䅁䅁䅁䭁䅁䅅䅁䭁䅁䅕䅁䙁䅁䅁䅁权⬱䅖允䅁䅁䅅䅁䙁佁㙆䭆䠵搴⽯䍄䉁䅁䅁兂䅁䅁䅍䅄䅁䅁䅯杇䅁䅁䅯睕䅁䅁䅯兂䅁䅁䅕䅁䅁佁畂欵䉁䅁䅁允䅁䅁䅕㥌欰潂噆く䵁䅉䅅䅁䕁䅁䅁睁䵁䅁䅁权偂䅁䅁权佂䅁䅁兂䅁䅁䅁乁決䅑䅅䅁䉁䅁䅁兂啁歲桦桥䥑䅑杷允䅁䅁䅑䅁䑁䅁䅷䅁䭁䕁䄸䅁䭁䕁䄴䅁䙁䅁䅁䅁䅂敧䅚允䅁䅁䅅䅁䙁䭁睒児塲睯䅸䍄䉁䅁䅁兂䅁䅁䅍䅄䅁䅁䅯先䅁䅁䅯允䅁䅁䅯兂䅁䅁䅕䅁䅁佁㍁欵䉁䅁䅁允䅁䅁䅕歲桦桥畓稱䴸䅉䅅䅁䕁䅁䅁睁䵁䅁䅁权偂䅁䅁权佂䅁䅁兂䅁䅁䅁䡁浪䅑䅅䅁䉁䅁䅁兂㝂䭆䠵場䵯䅑杷允䅁䅁䅕䅁䑁䅁䅷䅁䭁䉁䅯䅁䭁䅁䅅䅁䭁䅁䅕䅁䙁䅁䅁䅁䅃敊䅚允䅁䅁䅅䅁䙁䭁睒児塲⭯⽧䍄䉁䅁䅁䅂䅁䅁䅍䅄䅁䅁䅯睔䅁䅁䅯杔䅁䅁䅕䅁䅁䅁硁欵䉁䅁䅁允䅁䅁䅕䅁䅁䅁䅁歅䵁䅉䅅䅁䙁䅁䅁睁䵁䅁䅁权晁䅁䅁权呂䅁䅁权䙁䅁䅁兂䅁䅁䅁䙧浪䅑䅅䅁䉁䅁䅁兂㥂穐敖極硫䅑杷允䅁䅁䅑䅁䑁䅁䅷䅁䭁䕁䄸䅁䭁䕁䄴䅁䙁䅁䅁䅁杄佧䅚允䅁䅁䅅䅁䙁䱁敧敨剴䅵䅸䍄䉁䅁䅁兂䅁䅁䅍䅄䅁䅁䅯䅁䅁䅁䅯睕䅁䅁䅯兂䅁䅁䅕䅁䅁䕁㑄唵䉁䅁䅁允䅁䅁䅕噋偹癷潖歍䵁䅉䅅䅁䕁䅁䅁睁䵁䅁䅁权偂䅁䅁权佂䅁䅁兂䅁䅁䅁䑑洷䅑䅅䅁䉁䅁䅁兂䑄匹捨㡪䱉䅑杷允䅁䅁䅑䅁䑁䅁䅷䅁䭁䕁䄸䅁䭁䕁䄴䅁䙁䅁䅁䅁权敥䅚允䅁䅁䅅䅁䙁䑁䬰㘱睎児䅸䍄䉁䅁䅁兂䅁䅁䅍䅄䅁䅁䅯䅁䅁䅁䅯睕䅁䅁䅯兂䅁䅁䅕䅁䅁䍁䍄唵䉁䅁䅁允䅁䅁䅕䘫橐婰䕵歍䵁䅉䅅䅁䙁䅁䅁睁䵁䅁䅁权䅁䅁䅁权呂䅁䅁权䙁䅁䅁兂䅁䅁䅁䘴浐䅑䅅䅁䉁䅁䅁兂㕁䵴㉨瑶稸䅑杷允䅁䅁䅕䅁䑁䅁䅷䅁䭁䉁䅯䅁䭁䅁䅅䅁䭁䅁䅕䅁䙁䅁䅁䅁䅄畉䅚允䅁䅁䅅䅁䙁䭁睒児塲⭯⽧䍄䉁䅁䅁䅂䅁䅁䅍䅄䅁䅁䅯睔䅁䅁䅯杔䅁䅁䅕䅁䅁䭁汁欵䉁䅁䅁允䅁䅁䅕体㙆䭆䠵啅䵁䅉䅅䅁䙁䅁䅁睁䵁䅁䅁权捁䅁䅁权呂䅁䅁权䙁䅁䅁兂䅁䅁䅁䵙汢䅑䅅䅁䉁䅁䅁兂桄桥畓㉒畅䅑杷允䅁䅁䅕䅁䑁䅁䅷䅁䭁䉁䄸䅁䭁䅁䅅䅁䭁䅁䅕䅁䙁䅁䅁䅁䅁敷䅖允䅁䅁䅅䅁䙁䱁敧敨剴乵⼴䍄䉁䅁䅁兂䅁䅁䅍䅄䅁䅁䅯䅁䅁䅁䅯睕䅁䅁䅯兂䅁䅁䅕䅁䅁䭁婁欵䉁䅁䅁允䅁䅁䅕硢䑋䵷䉯き䵁䅉䅅䅁䙁䅁䅁睁䵁䅁䅁权慁䅁䅁权呂䅁䅁权䙁䅁䅁兂䅁䅁䅁偉汦䅑䅅䅁䉁䅁䅁兂偃癷潕佘㔸䅑杷允䅁䅁䅑䅁䑁䅁䅷䅁䭁䕁䄸䅁䭁䕁䄴䅁䙁䅁䅁䅁杁敗䅚允䅁䅁䅅䅁䙁䥁䌯匹捨睪䄵䍄䉁䅁䅁兂䅁䅁䅍䅄䅁䅁䅯先䅁䅁䅯睕䅁䅁䅯兂䅁䅁䅕䅁䅁䝁楃唵䉁䅁䅁允䅁䅁䅕牒穢搯㑒啌䵁䅉䅅䅁䙁䅁䅁睁䵁䅁䅁权晁䅁䅁权䉁䅁䅁权䙁䅁䅁兂䅁䅁䅁䝁洯䅑䅅䅁䉁䅁䅁兂卂䉵䘶ㄶ杈睐杷允䅁䅁䅕䅁䑁䅁䅷䅁䭁䅁䅁䅁䭁䅁䅅䅁䭁䅁䅕䅁䙁䅁䅁䅁䅁⭬䅖允䅁䅁䅅䅁䙁䩁婱婭婭摭⽫䍄䉁䅁䅁兂䅁䅁䅍䅄䅁䅁䅯睈䅁䅁䅯睕䅁䅁䅯兂䅁䅁䅕䅁䅁䵁䑄唵䉁䅁䅁允䅁䅁䅕塹⭡确癯啍䵁䅉䅅䅁䕁䅁䅁睁䵁䅁䅁权偂䅁䅁权佂䅁䅁兂䅁䅁䅁䱯決䅑䅅䅁䉁䅁䅁兂穁積積積牐睐杷允䅁䅁䅑䅁䑁䅁䅷䅁䭁䕁䄸䅁䭁䕁䄴䅁䙁䅁䅁䅁杁⭙䅚允䅁䅁䅅䅁䙁佁㙆䭆䠵儴䄵䍄䉁䅁䅁兂䅁䅁䅍䅄䅁䅁䅯䅈䅁䅁䅯允䅁䅁䅯兂䅁䅁䅕䅁䅁䍁捃唵䉁䅁䅁允䅁䅁䅕㡪ㅌ䙋偹樰䴸䅉䅅䅁䙁䅁䅁睁䵁䅁䅁权摁䅁䅁权呂䅁䅁权䙁䅁䅁兂䅁䅁䅁䙯浔䅑䅅䅁䉁䅁䅁兂䑄匹捨㑪畉䅑杷允䅁䅁䅕䅁䑁䅁䅷䅁䭁䉁䄸䅁䭁䅁䅅䅁䭁䅁䅕䅁䙁䅁䅁䅁权畍䅚允䅁䅁䅅䅁䙁䕁桪桥畓⭒⽅䍄䉁䅁䅁䅂䅁䅁䅍䅄䅁䅁䅯睔䅁䅁䅯杔䅁䅁䅕䅁䅁䕁䥄唵䉁䅁䅁允䅁䅁䅕場啯歲桦樫䴸䅉䅅䅁䕁䅁䅁睁䵁䅁䅁权偂䅁䅁权佂䅁䅁兂䅁䅁䅁䵁氳䅑䅅䅁䉁䅁䅁兂浂浚浚浚䕙䅑杷允䅁䅁䅕䅁䑁䅁䅷䅁䭁䉁䅯䅁䭁䙁䅍䅁䭁䅁䅕䅁䙁䅁䅁䅁权敖䅚允䅁䅁䅅䅁䙁䵁ㅐ䙋偹橙䅴䍄䉁䅁䅁兂䅁䅁䅍䅄䅁䅁䅯杈䅁䅁䅯睕䅁䅁䅯兂䅁䅁䅕䅁䅁䕁敂欵䉁䅁䅁允䅁䅁䅕敫㠱穐敖歉䵁䅉䅅䅁䕁䅁䅁睁䵁䅁䅁权偂䅁䅁权佂䅁䅁兂䅁䅁䅁䬴汲䅑䅅䅁䉁䅁䅁兂啁歲桦桥敔睐杷允䅁䅁䅕䅁䑁䅁䅷䅁䭁䉁䅷䅁䭁䅁䅅䅁䭁䅁䅕䅁䙁䅁䅁䅁䅄⭹䅖允䅁䅁䅅䅁䙁䑁積積積㥍⽍䍄䉁䅁䅁䅂䅁䅁䅍䅄䅁䅁䅯睔䅁䅁䅯杔䅁䅁䅕䅁䅁䭁乂欵䉁䅁䅁允䅁䅁䅕牕敧敨剴啅䵁䅉䅅䅁䙁䅁䅁睁䵁䅁䅁权慁䅁䅁权䉁䅁䅁权䙁䅁䅁兂䅁䅁䅁䌴浌䅑䅅䅁䉁䅁䅁兂歃䑣䬰㘱潐睐杷允䅁䅁䅕䅁䑁䅁䅷䅁䭁䉁䄰䅁䭁䙁䅍䅁䭁䅁䅕䅁䙁䅁䅁䅁权敊䅚允䅁䅁䅅䅁䙁䝁浚浚浚椵䄵䍄䉁䅁䅁兂䅁䅁䅍䅄䅁䅁䅯睈䅁䅁䅯睕䅁䅁䅯兂䅁䅁䅕䅁䅁佁煁欵䉁䅁䅁允䅁䅁䅕癴㥐䠱䩧啍䵁䅉䅅䅁䙁䅁䅁睁䵁䅁䅁权䅁䅁䅁权呂䅁䅁权䙁䅁䅁兂䅁䅁䅁偙氯䅑䅅䅁䉁䅁䅁兂煃搸乊湙祁䅑杷允䅁䅁䅑䅁䑁䅁䅷䅁䭁䕁䄸䅁䭁䕁䄴䅁䙁䅁䅁䅁䅄佧䅚允䅁䅁䅅䅁䙁䱁敧敨剴䅵䅸䍄䉁䅁䅁兂䅁䅁䅍䅄䅁䅁䅯䅁䅁䅁䅯允䅁䅁䅯兂䅁䅁䅕䅁䅁䍁潄唵䉁䅁䅁允䅁䅁䅕敨剴䉵䘶稲䴸䅉䅅䅁䙁䅁䅁睁䵁䅁䅁权晁䅁䅁权呂䅁䅁权䙁䅁䅁兂䅁䅁䅁䅯浪䅑䅅䅁䉁䅁䅁兂䑃䵷桱婒睙䅑杷允䅁䅁䅕䅁䑁䅁䅷䅁䭁䉁䄸䅁䭁䙁䅍䅁䭁䅁䅕䅁䙁䅁䅁䅁䅄畏䅚允䅁䅁䅅䅁䙁䑁䩥坑汄䑍䅆䍄䉁䅁䅁兂䅁䅁䅍䅄䅁䅁䅯䅁䅁䅁䅯睕䅁䅁䅯兂䅁䅁䅕䅁䅁䍁㡂欵䉁䅁䅁允䅁䅁䅕佖汏㡭䅑䕎䵁䅉䅅䅁䙁䅁䅁睁䵁䅁䅁权慁䅁䅁权呂䅁䅁权䙁䅁䅁兂䅁䅁䅁䵯汲䅑䅅䅁䉁䅁䅁兂权楇搯䕊㙙䅑杷允䅁䅁䅑䅁䑁䅁䅷䅁䭁䕁䄸䅁䭁䕁䄴䅁䙁䅁䅁䅁杄敮䅖允䅁䅁䅅䅁䙁䉁䘫ㄶ㑇瑈⽕䍄䉁䅁䅁兂䅁䅁䅍䅄䅁䅁䅯䅁䅁䅁䅯睕䅁䅁䅯兂䅁䅁䅕䅁䅁佁橄唵䉁䅁䅁允䅁䅁䅕兇坒楄匳歍䵁䅉䅅䅁䙁䅁䅁睁䵁䅁䅁权慁䅁䅁权呂䅁䅁权䙁䅁䅁兂䅁䅁䅁䍉浈䅑䅅䅁䉁䅁䅁兂㉃⼸唳䥥㙫䅑杷允䅁䅁䅕䅁䑁䅁䅷䅁䭁䉁䄸䅁䭁䅁䅅䅁䭁䅁䅕䅁䙁䅁䅁䅁䅃敗䅚允䅁䅁䅅䅁䙁䙁㑋潈牘敕⽁䍄䉁䅁䅁䅂䅁䅁䅍䅄䅁䅁䅯睔䅁䅁䅯杔䅁䅁䅕䅁䅁䍁十欵䉁䅁䅁允䅁䅁䅕敨剴䉵䘶ぅ䵁䅉䅅䅁䙁䅁䅁睁䵁䅁䅁权䅁䅁䅁权䉁
A2: 䅁䅁权䙁䅁䅁兂䅁䅁䅁䍑浢䅑䅅䅁䉁䅁䅁兂㑃潈牘払敪睐杷允䅁䅁䅑䅁䑁䅁䅷䅁䭁䕁䄸䅁䭁䕁䄴䅁䙁䅁䅁䅁䅃整䅖允䅁䅁䅅䅁䙁䡁㥅瑃橥乣⼰䍄䉁䅁䅁䅂䅁䅁䅍䅄䅁䅁䅯睔䅁䅁䅯杔䅁䅁䅕䅁䅁䝁湁欵䉁䅁䅁允䅁䅁䅕䡰㥁瑃橥啅䵁䅉䅅䅁䙁䅁䅁睁䵁䅁䅁权捁䅁䅁权䉁䅁䅁权䙁䅁䅁兂䅁䅁䅁乑汲䅑䅅䅁䉁䅁䅁兂穁積積積呐睐杷允䅁䅁䅕䅁䑁䅁䅷䅁䭁䉁䅷䅁䭁䙁䅍䅁䭁䅁䅕䅁䙁䅁䅁䅁䅁畒䅚允䅁䅁䅅䅁䙁䝁匸㡧䭄卙䄵䍄䉁䅁䅁䅂䅁䅁䅍䅄䅁䅁䅯睔䅁䅁䅯杔䅁䅁䅕䅁䅁䅁䍁欵䉁䅁䅁允䅁䅁䅕䘷㑇潈牘䕅䵁䅉䅅䅁䙁䅁䅁睁䵁䅁䅁权慁䅁䅁权呂䅁䅁权䙁䅁䅁兂䅁䅁䅁䭁汶䅑䅅䅁䉁䅁䅁兂摁浗㝑㐳㔸䅑杷允䅁䅁䅕䅁䑁䅁䅷䅁䭁䉁䄴䅁䭁䙁䅍䅁䭁䅁䅕䅁䙁䅁䅁䅁杄申䅖允䅁䅁䅅䅁䙁䡁㥅瑃橥䌸䅴䍄䉁䅁䅁兂䅁䅁䅍䅄䅁䅁䅯杈䅁䅁䅯睕䅁䅁䅯兂䅁䅁䅕䅁䅁䵁䥄唵䉁䅁䅁允䅁䅁䅕呣䬰㘱睍䕌䵁䅉䅅䅁䕁䅁䅁睁䵁䅁䅁权偂䅁䅁权佂䅁䅁兂䅁䅁䅁䙧浮䅑䅅䅁䉁䅁䅁兂啁歲桦桥佑䅑杷允䅁䅁䅕䅁䑁䅁䅷䅁䭁䉁䄴䅁䭁䅁䅅䅁䭁䅁䅕䅁䙁䅁䅁䅁杄⭯䅖允䅁䅁䅅䅁䙁䑁積積積㥍⽍䍄䉁䅁䅁兂䅁䅁䅍䅄䅁䅁䅯䅁䅁䅁䅯睕䅁䅁䅯兂䅁䅁䅕䅁䅁䝁坂欵䉁䅁䅁允䅁䅁䅕扏䥔牤昷き䵁䅉䅅䅁䙁䅁䅁睁䵁䅁䅁权捁䅁䅁权䉁䅁䅁权䙁䅁䅁兂䅁䅁䅁䱙汘䅑䅅䅁䉁䅁䅁兂偃癷潕䥘匯睐杷允䅁䅁䅕䅁䑁䅁䅷䅁䭁䉁䄴䅁䭁䙁䅍䅁䭁䅁䅕䅁䙁䅁䅁䅁杄畺䅖允䅁䅁䅅䅁䙁䍁䡵瑆佮祴䅸䍄䉁䅁䅁兂䅁䅁䅍䅄䅁䅁䅯睈䅁䅁䅯睕䅁䅁䅯兂䅁䅁䅕䅁䅁䅁歁欵䉁䅁䅁允䅁䅁䅕癴㥐䠱䩧啍䵁䅉䅅䅁䕁䅁䅁睁䵁䅁䅁权偂䅁䅁权佂䅁䅁兂䅁䅁䅁䥧浄䅑䅅䅁䉁䅁䅁兂䅁䅁䅁䅁䵁䅑杷允䅁䅁䅕䅁䑁䅁䅷䅁䭁䉁䄰䅁䭁䅁䅅䅁䭁䅁䅕䅁䙁䅁䅁䅁杁佲䅖允䅁䅁䅅䅁䙁乁橥䑣䬰㤱⽍䍄䉁䅁䅁兂䅁䅁䅍䅄䅁䅁䅯睈䅁䅁䅯睕䅁䅁䅯兂䅁䅁䅕䅁䅁䍁獃唵䉁䅁䅁允䅁䅁䅕䉵䘶ㄶ㑆䕍䵁䅉䅅䅁䕁䅁䅁睁䵁䅁䅁权偂䅁䅁权佂䅁䅁兂䅁䅁䅁䱑汪䅑䅅䅁䉁䅁䅁兂晁敨剴䉵氷睐杷允䅁䅁䅕䅁䑁䅁䅷䅁䭁䉁䅷䅁䭁䅁䅅䅁䭁䅁䅕䅁䙁䅁䅁䅁䅁佘䅚允䅁䅁䅅䅁䙁偁潙䥘䌯搹⽧䍄䉁䅁䅁兂䅁䅁䅍䅄䅁䅁䅯睈䅁䅁䅯睕䅁䅁䅯兂䅁䅁䅕䅁䅁䕁あ欵䉁䅁䅁允䅁䅁䅕牡へ硫歧啍䵁䅉䅅䅁䕁䅁䅁睁䵁䅁䅁权偂䅁䅁权佂䅁䅁兂䅁䅁䅁䔴浺䅑䅅䅁䉁䅁䅁兂塄㍯㥁瑃剣䅑杷允䅁䅁䅑䅁䑁䅁䅷䅁䭁䕁䄸䅁䭁䕁䄴䅁䙁䅁䅁䅁权⭃䅚允䅁䅁䅅䅁䙁䑁䬰㘱睎剐䅊䍄䉁䅁䅁䅂䅁䅁䅍䅄䅁䅁䅯睔䅁䅁䅯杔䅁䅁䅕䅁䅁䅁睂欵䉁䅁䅁允䅁䅁䅕敨剴䉵䘶ぃ䵁䅉䅅䅁䕁䅁䅁睁䵁䅁䅁权偂䅁䅁权佂䅁䅁兂䅁䅁䅁䱉汐䅑䅅䅁䉁䅁䅁兂桄桥畓⭒慈睐杷允䅁䅁䅕䅁䑁䅁䅷䅁䭁䉁䅯䅁䭁䅁䅅䅁䭁䅁䅕䅁䙁䅁䅁䅁䅄攰䅖允䅁䅁䅅䅁䙁偁潙䥘䌯改⽁䍄䉁䅁䅁䅂䅁䅁䅍䅄䅁䅁䅯睔䅁䅁䅯杔䅁䅁䅕䅁䅁佁佁欵䉁䅁䅁允䅁䅁䅕䘷㑇潈牘歅䵁䅉䅅䅁䙁䅁䅁睁䵁䅁䅁权慁䅁䅁权呂䅁䅁权䙁䅁䅁兂䅁䅁䅁䕧浌䅑䅅䅁䉁䅁䅁兂䙄䱉祂䑡㝅䅑杷允䅁䅁䅑䅁䑁䅁䅷䅁䭁䕁䄸䅁䭁䕁䄴䅁䙁䅁䅁䅁䅄低䅚允䅁䅁䅅䅁䙁䥁䌯匹捨硪䅆䍄䉁䅁䅁兂䅁䅁䅍䅄䅁䅁䅯睈䅁䅁䅯睕䅁䅁䅯兂䅁䅁䅕䅁䅁䥁允欵䉁䅁䅁允䅁䅁䅕䙂余扌㥋䕍䵁䅉䅅䅁䕁䅁䅁睁䵁䅁䅁权偂䅁䅁权佂䅁䅁兂䅁䅁䅁䕧浈䅑䅅䅁䉁䅁䅁兂桄桥畓⭒佅䅑杷允䅁䅁䅑䅁䑁䅁䅷䅁䭁䕁䄸䅁䭁䕁䄴䅁䙁䅁䅁䅁杄⭕䅚允䅁䅁䅅䅁䙁䙁偹癷潕䅘䄹䍄䉁䅁䅁兂䅁䅁䅍䅄䅁䅁䅯䅁䅁䅁䅯睕䅁䅁䅯兂䅁䅁䅕䅁䅁䍁畁欵䉁䅁䅁允䅁䅁䅕扌摋㘷䝥き䵁䅉䅅䅁䙁䅁䅁睁䵁䅁䅁权慁䅁䅁权呂䅁䅁权䙁䅁䅁兂䅁䅁䅁䭙氷䅑䅅䅁䉁䅁䅁兂摁浗㝑㐳㔸䅑杷允䅁䅁䅕䅁䑁䅁䅷䅁䭁䉁䄰䅁䭁䅁䅅䅁䭁䅁䅕䅁䙁䅁䅁䅁杁⬰䅖允䅁䅁䅅䅁䙁乁橥䑣䬰㤱⽍䍄䉁䅁䅁䅂䅁䅁䅍䅄䅁䅁䅯睔䅁䅁䅯杔䅁䅁䅕䅁䅁䅁桂欵䉁䅁䅁允䅁䅁䅕䅁䅁䅁䅁歄䵁䅉䅅䅁䙁䅁䅁睁䵁䅁䅁权捁䅁䅁权䉁䅁䅁权䙁䅁䅁兂䅁䅁䅁伴汶䅑䅅䅁䉁䅁䅁兂穁積積積呐睐杷允䅁䅁䅕䅁䑁䅁䅷䅁䭁䉁䅷䅁䭁䙁䅍䅁䭁䅁䅕䅁䙁䅁䅁䅁䅁甫䅖允䅁䅁䅅䅁䙁䙁㘶兓䍷祡䄱䍄䉁䅁䅁䅂䅁䅁䅍䅄䅁䅁䅯睔䅁䅁䅯杔䅁䅁䅕䅁䅁䍁⭂欵䉁䅁䅁允䅁䅁䅕䘷㑇潈牘ぃ䵁䅉䅅䅁䕁䅁䅁睁䵁䅁䅁权偂䅁䅁权佂䅁䅁兂䅁䅁䅁䨴汪䅑䅅䅁䉁䅁䅁兂䭁㘱睎児䡲睐杷允䅁䅁䅕䅁䑁䅁䅷䅁䭁䉁䄸䅁䭁䅁䅅䅁䭁䅁䅕䅁䙁䅁䅁䅁䅃伸䅖允䅁䅁䅅䅁䙁佁㙆䭆䠵搴⽯䍄䉁䅁䅁䅂䅁䅁䅍䅄䅁䅁䅯睔䅁䅁䅯杔䅁䅁䅕䅁䅁䵁㙃唵䉁䅁䅁允䅁䅁䅕䥘䌯匹捨稵䴸䅉䅅䅁䕁䅁䅁睁䵁䅁䅁权偂䅁䅁权佂䅁䅁兂䅁䅁䅁䕁浈䅑䅅䅁䉁䅁䅁兂乄䵺䵺䵺佷䅑杷允䅁䅁䅕䅁䑁䅁䅷䅁䭁䉁䄰䅁䭁䅁䅅䅁䭁䅁䅕䅁䙁䅁䅁䅁䅁⭳䅖允䅁䅁䅅䅁䙁乁橥䑣䬰㤱⽍䍄䉁䅁䅁兂䅁䅁䅍䅄䅁䅁䅯睈䅁䅁䅯允䅁䅁䅯兂䅁䅁䅕䅁䅁䅁䉁欵䉁䅁䅁允䅁䅁䅕䅁䅁䅁䅁䐴䴸䅉䅅䅁䙁䅁䅁睁䵁䅁䅁权晁䅁䅁权䉁䅁䅁权䙁䅁䅁兂䅁䅁䅁䕷洳䅑䅅䅁䉁䅁䅁兂歃䑣䬰㘱材睐杷允䅁䅁䅕䅁䑁䅁䅷䅁䭁䅁䅁䅁䭁䅁䅅䅁䭁䅁䅕䅁䙁䅁䅁䅁䅂敎䅚允䅁䅁䅅䅁䙁䱁敧敨剴乵⼴䍄䉁䅁䅁䅂䅁䅁䅍䅄䅁䅁䅯睔䅁䅁䅯杔䅁䅁䅕䅁䅁䥁瑄唵䉁䅁䅁允䅁䅁䅕歲桦桥畓い䵁䅉䅅䅁䕁䅁䅁睁䵁䅁䅁权偂䅁䅁权佂䅁䅁兂䅁䅁䅁䍑浪䅑䅅䅁䉁䅁䅁兂硂児塲㍯剁䅑杷允䅁䅁䅕䅁䑁䅁䅷䅁䭁䉁䄰䅁䭁䅁䅅䅁䭁䅁䅕䅁䙁䅁䅁䅁䅂攸䅖允䅁䅁䅅䅁䙁乁橥䑣䬰㤱⽍䍄䉁䅁䅁兂䅁䅁䅍䅄䅁䅁䅯䅈䅁䅁䅯允䅁䅁䅯兂䅁䅁䅕䅁䅁䕁䕁欵䉁䅁䅁允䅁䅁䅕㑈牘払敧吱䴸䅉䅅䅁䙁䅁䅁睁䵁䅁䅁权摁䅁䅁权䉁䅁䅁权䙁䅁䅁兂䅁䅁䅁䍧洯䅑䅅䅁䉁䅁䅁兂畃⭒㙆䭆堷睐杷允䅁䅁䅕䅁䑁䅁䅷䅁䭁䉁䄰䅁䭁䙁䅍䅁䭁䅁䅕䅁䙁䅁䅁䅁䅃⬳䅖允䅁䅁䅅䅁䙁䱁敧敨剴䌫䅸䍄䉁䅁䅁兂䅁䅁䅍䅄䅁䅁䅯睈䅁䅁䅯睕䅁䅁䅯兂䅁䅁䅕䅁䅁䅁扂欵䉁䅁䅁允䅁䅁䅕匰扌堫䬴啍䵁䅉䅅䅁䕁䅁䅁睁䵁䅁䅁权偂䅁䅁权佂䅁䅁兂䅁䅁䅁䑉浄䅑䅅䅁䉁䅁䅁兂灁䥘䌯匹呧䅑杷允䅁䅁䅕䅁䑁䅁䅷䅁䭁䉁䄰䅁䭁䅁䅅䅁䭁䅁䅕䅁䙁䅁䅁䅁䅃敭䅖允䅁䅁䅅䅁䙁乁橥䑣䬰㤱⽍䍄䉁䅁䅁兂䅁䅁䅍䅄䅁䅁䅯睈䅁䅁䅯睕䅁䅁䅯兂䅁䅁䅕䅁䅁䥁䉂欵䉁䅁䅁允䅁䅁䅕㑎䉬余睕啍䵁䅉䅅䅁䙁䅁䅁睁䵁䅁䅁权䅁䅁䅁权䉁䅁䅁权䙁䅁䅁兂䅁䅁䅁䍙浪䅑䅅䅁䉁䅁䅁兂㑃潈牘払敪睐杷允䅁䅁䅕䅁䑁䅁䅷䅁䭁䉁䄸䅁䭁䅁䅅䅁䭁䅁䅕䅁䙁䅁䅁䅁杂⭅䅚允䅁䅁䅅䅁䙁䭁睒児塲⭯⽁䍄䉁䅁䅁䅂䅁䅁䅍䅄䅁䅁䅯睔䅁䅁䅯杔䅁䅁䅕䅁䅁䝁䅃欵䉁䅁䅁允䅁䅁䅕䘷㑇潈牘ぃ䵁䅉䅅䅁䙁䅁䅁睁䵁䅁䅁权䅁䅁䅁权䉁䅁䅁权䙁䅁䅁兂䅁䅁䅁䱷氳䅑䅅䅁䉁䅁䅁兂㥁瑃橥䑣愳睐杷允䅁䅁䅕䅁䑁䅁䅷䅁䭁䉁䄰䅁䭁䙁䅍䅁䭁䅁䅕䅁䙁䅁䅁䅁䅁畢䅚允䅁䅁䅅䅁䙁䑁䩥坑汄䍅䄵䍄䉁䅁䅁兂䅁䅁䅍䅄䅁䅁䅯睈䅁䅁䅯允䅁䅁䅯兂䅁䅁䅕䅁䅁䝁扁欵䉁䅁䅁允䅁䅁䅕椹捨㡪ㅌ䐴䴸䅉䅅䅁䙁䅁䅁睁䵁䅁䅁权捁䅁䅁权呂䅁䅁权䙁䅁䅁兂䅁䅁䅁䉉浺䅑䅅䅁䉁䅁䅁兂祃敮渫杸畳䅑杷允䅁䅁䅑䅁䑁䅁䅷䅁䭁䕁䄸䅁䭁䕁䄴䅁䙁䅁䅁䅁䅄⭮䅖允䅁䅁䅅䅁䙁䝁浚浚浚瑚⽙䍄䉁䅁䅁兂䅁䅁䅍䅄䅁䅁䅯䅈䅁䅁䅯允䅁䅁䅯兂䅁䅁䅕䅁䅁䍁㥄唵䉁䅁䅁允䅁䅁䅕㑈牘払敧吱䴸䅉䅅䅁䙁䅁䅁睁䵁䅁䅁权摁䅁䅁权呂䅁䅁权䙁䅁䅁兂䅁䅁䅁䕙浶䅑䅅䅁䉁䅁䅁兂ㅂ硫䕧潖甴䅑杷允䅁䅁䅕䅁䑁䅁䅷䅁䭁䅁䅁䅁䭁䙁䅍䅁䭁䅁䅕䅁䙁䅁䅁䅁杁但䅚允䅁䅁䅅䅁䙁䉁奂扏䥔橬䅊䍄䉁䅁䅁兂䅁䅁䅍䅄䅁䅁䅯先䅁䅁䅯允䅁䅁䅯兂䅁䅁䅕䅁䅁佁䡁欵䉁䅁䅁允䅁䅁䅕㑈牘払敧吱䴸䅉䅅䅁䙁䅁䅁睁䵁䅁䅁权䅁䅁䅁权䉁䅁䅁权䙁䅁䅁兂䅁䅁䅁䰴汮䅑䅅䅁䉁䅁䅁兂㥁瑃橥䑣愳睐杷允䅁䅁䅕䅁䑁䅁䅷䅁䭁䉁䅷䅁䭁䅁䅅䅁䭁䅁䅕䅁䙁䅁䅁䅁䅁敃䅚允䅁䅁䅅䅁䙁䉁䘫ㄶ㑇瑈⽕䍄䉁䅁䅁兂䅁䅁䅍䅄䅁䅁䅯睈䅁䅁䅯允䅁䅁䅯兂䅁䅁䅕䅁䅁䍁䕁欵䉁䅁䅁允䅁䅁䅕䅁䅁䅁䅁䐴䴸䅉䅅䅁䙁䅁䅁睁䵁䅁䅁权晁䅁䅁权呂䅁䅁权䙁䅁䅁兂䅁䅁䅁䙑洯䅑䅅䅁䉁䅁䅁兂剄瑉㕶杦硯䅑杷允䅁䅁䅑䅁䑁䅁䅷䅁䭁䕁䄸䅁䭁䕁䄴䅁䙁䅁䅁䅁杄伲䅖允䅁䅁䅅䅁䙁䵁䴳䵺䵺䅺䅚䍄䉁䅁䅁兂䅁䅁䅍䅄䅁䅁䅯睈䅁䅁䅯允䅁䅁䅯兂䅁䅁䅕䅁䅁䍁桂欵䉁䅁䅁允䅁䅁䅕椹捨㡪ㅌ䐴䴸䅉䅅䅁䕁䅁䅁睁䵁䅁䅁权偂䅁䅁权佂䅁䅁兂䅁䅁䅁䕙浈䅑䅅䅁䉁䅁䅁权扁䅁䅁䍄䉁䅁䅁兂䅁䅁䅍䅄䅁䅁䅯先䅁䅁䅯睕䅁䅁䅯兂䅁䅁䅕䅁䅁䭁㕂欵䉁䅁䅁允䅁䅁䅕䬸䝦穓䩦啌䵁䅉䅅䅁䙁䅁䅁睁䵁䅁䅁权䅁䅁䅁权呂䅁䅁权䙁䅁䅁兂䅁䅁䅁䅧浌䅑䅅䅁䉁䅁䅁兂煃搸乊湙祁䅑杷允䅁䅁䅑䅁䑁䅁䅷䅁䭁䕁䄸䅁䭁䕁䄴䅁䙁䅁䅁䅁权⭑䅚允䅁䅁䅅䅁䙁䱁敧敨剴䉵䅂䍄䉁䅁䅁兂䅁䅁䅍䅄䅁䅁䅯先䅁䅁䅯允䅁䅁䅯兂䅁䅁䅕䅁䅁䍁㍃唵䉁䅁䅁允䅁䅁䅕㘱睎児塲稰䴸䅉䅅䅁䕁䅁䅁睁䵁䅁䅁权偂䅁䅁权佂䅁䅁兂䅁䅁䅁䍧浔䅑䅅䅁䉁䅁䅁兂獄払敧敨剳䅑杷允䅁䅁䅕䅁䑁䅁䅷䅁䭁䉁䅷䅁䭁䙁䅍䅁䭁䅁䅕䅁䙁䅁䅁䅁䅁敭䅖允䅁䅁䅅䅁䙁偁㥔䠱灪楰䅸䍄䉁䅁䅁兂䅁䅁䅍䅄䅁䅁䅯䅈䅁䅁䅯允䅁䅁䅯兂䅁䅁䅕䅁䅁䭁奂欵䉁䅁䅁允䅁䅁䅕椹捨㡪ㅌ䐲䴸䅉䅅䅁䙁䅁䅁睁䵁䅁䅁权捁䅁䅁权呂䅁䅁权䙁䅁䅁兂䅁䅁䅁䅑浲䅑䅅䅁䉁䅁䅁兂㉄䙋偹湷瑕䅑杷允䅁䅁䅕䅁䑁䅁䅷䅁䭁䉁䄴䅁䭁䙁䅍䅁䭁䅁䅕䅁䙁䅁䅁䅁䅁畖䅚允䅁䅁䅅䅁䙁乁㕶浦㡱䍤䅊䍄䉁䅁䅁䅂䅁䅁䅍䅄䅁䅁䅯睔䅁䅁䅯杔䅁䅁䅕䅁䅁䕁敂欵䉁䅁䅁允䅁䅁䅕体㙆䭆䠵い䵁䅉䅅䅁䙁䅁䅁睁䵁䅁䅁权晁䅁䅁权呂䅁䅁权䙁䅁䅁兂䅁䅁䅁䝯洳䅑䅅䅁䉁䅁䅁兂䭁㘱睎卐硯䅑杷允䅁䅁䅕䅁䑁䅁䅷䅁䭁䅁䅁䅁䭁䙁䅍䅁䭁䅁䅕䅁䙁䅁䅁䅁䅄敘䅚允䅁䅁䅅䅁䙁䭁硲欰椱䐰䅎䍄䉁䅁䅁兂䅁䅁䅍䅄䅁䅁䅯杈䅁䅁䅯允䅁䅁䅯兂䅁䅁䅕䅁䅁䕁穂欵䉁䅁䅁允䅁䅁䅕䅁䅁䅁䅁䐰䴸䅉䅅䅁䙁䅁䅁睁䵁䅁䅁权敁䅁䅁权呂䅁䅁权䙁䅁䅁兂䅁䅁䅁䍧浄䅑䅅䅁䉁䅁䅁兂婁䙂余塌灉䅑杷允䅁䅁䅕䅁䑁䅁䅷䅁䭁䉁䅷䅁䭁䙁䅍䅁䭁䅁䅕䅁䙁䅁䅁䅁杁佭䅖允䅁䅁䅅䅁䙁偁㥔䠱灪楰䅸䍄䉁䅁䅁兂䅁䅁䅍䅄䅁䅁䅯䅁䅁䅁䅯睕䅁䅁䅯兂䅁䅁䅕䅁䅁䵁䝂欵䉁䅁䅁允䅁䅁䅕潅䅐煹䙈き䵁䅉䅅䅁䙁䅁䅁睁䵁䅁䅁权慁䅁䅁权䉁䅁䅁权䙁䅁䅁兂䅁䅁䅁䕧洯䅑䅅䅁䉁䅁䅁兂歃䑣䬰㘱潐睐杷允䅁䅁䅕䅁䑁䅁䅷䅁䭁䉁䄰䅁䭁䅁䅅䅁䭁䅁䅕䅁䙁䅁䅁䅁权⭋䅚允䅁䅁䅅䅁䙁䝁浚浚浚瑚⽙䍄䉁䅁䅁䅂䅁䅁䅍䅄䅁䅁䅯睔䅁䅁䅯杔䅁䅁䅕䅁䅁䅁㕁欵䉁䅁䅁允䅁䅁䅕場啯歲桦歄䵁䅉䅅䅁䙁䅁䅁睁䵁䅁䅁权慁䅁䅁权呂䅁䅁权䙁䅁䅁兂䅁䅁䅁䑑浺䅑䅅䅁䉁䅁䅁兂䙄䱉祂䑡㝅䅑杷允䅁䅁䅑䅁䑁䅁䅷䅁䭁䕁䄸䅁䭁䕁䄴䅁䙁䅁䅁䅁杄余䅚允䅁䅁䅅䅁䙁䝁浚浚浚杚䄵䍄䉁䅁䅁兂䅁䅁䅍䅄䅁䅁䅯杈䅁䅁䅯允䅁䅁䅯兂䅁䅁䅕䅁䅁䝁坂欵䉁䅁䅁允䅁䅁䅕⽷潕䥘䌯吱䴸䅉䅅䅁䙁䅁䅁睁䵁䅁䅁权䅁䅁䅁权呂䅁䅁权䙁䅁䅁兂䅁䅁䅁䑯浔䅑䅅䅁䉁䅁䅁兂瑁灳瘳㑰穙䅑杷允䅁䅁䅕䅁䑁䅁䅷䅁䭁䉁䄴䅁䭁䅁䅅䅁䭁䅁䅕䅁䙁䅁䅁䅁杂畂䅚允䅁䅁䅅䅁䙁䡁啳歲桦瑥⽑䍄䉁䅁䅁兂䅁䅁䅍䅄䅁䅁䅯杈䅁䅁䅯允䅁䅁䅯兂䅁䅁䅕䅁䅁䕁楁欵䉁䅁䅁允䅁䅁䅕⽷潕䥘䌯吱䴸䅉䅅䅁䕁䅁䅁睁䵁䅁䅁权偂䅁䅁权佂䅁䅁兂䅁䅁䅁䠴洳䅑䅅䅁䉁䅁䅁兂䅁䅁䅁䅁䵁䅑杷允䅁䅁䅑䅁䑁䅁䅷䅁䭁䕁䄸䅁䭁䕁䄴䅁䙁䅁䅁䅁权敚䅚允䅁䅁䅅䅁䙁䉁䘫ㄶ㑇杈䄹䍄䉁䅁䅁兂䅁䅁䅍䅄䅁䅁䅯杇䅁䅁䅯允䅁䅁䅯兂䅁䅁䅕䅁䅁䥁㡂欵䉁䅁䅁允䅁䅁䅕䡰㥁瑃橥䐶䴸䅉䅅䅁䙁䅁䅁睁䵁䅁䅁权䅁䅁䅁权呂䅁䅁权䙁䅁䅁兂䅁䅁䅁䠴浘䅑䅅䅁䉁䅁䅁兂啂㘴扗䅸ぁ䅑杷允䅁䅁䅕䅁䑁䅁䅷䅁䭁䉁䅷䅁䭁䙁䅍䅁䭁䅁䅕䅁䙁䅁䅁䅁杄佲䅖允䅁䅁䅅䅁䙁偁潙䥘䌯却䄱䍄䉁䅁䅁䅂䅁䅁䅍䅄䅁䅁䅯睔䅁䅁䅯杔䅁䅁䅕䅁䅁䵁䅄唵䉁䅁䅁允䅁䅁䅕㑈牘払敧吷䴸䅉䅅䅁䙁䅁䅁睁䵁䅁䅁权䅁䅁䅁权呂䅁䅁权䙁䅁䅁兂䅁䅁䅁偑汢䅑䅅䅁䉁䅁䅁兂灁䥘䌯圹祧䅑杷允䅁䅁䅑䅁䑁䅁䅷䅁䭁䕁䄸䅁䭁䕁䄴䅁䙁䅁䅁䅁䅂⭗䅚允䅁䅁䅅䅁䙁䵁䴳䵺䵺䅺䄵䍄䉁䅁䅁兂䅁䅁䅍䅄䅁䅁䅯杇䅁䅁䅯睕䅁䅁䅯兂䅁䅁䅕䅁䅁䵁䉃欵䉁䅁䅁允䅁䅁䅕敥浫免獪歏䵁䅉䅅䅁䙁䅁䅁睁䵁䅁䅁权摁䅁䅁权䉁䅁䅁权䙁䅁䅁兂䅁䅁䅁䙑浌䅑䅅䅁䉁䅁䅁兂畃⭒㙆䭆堷睐杷允䅁䅁䅕䅁䑁䅁䅷䅁䭁䅁䅁䅁䭁䅁䅅䅁䭁䅁䅕䅁䙁䅁䅁䅁杄畮䅖允䅁䅁䅅䅁䙁䩁婱婭婭摭⽫䍄䉁䅁䅁兂䅁䅁䅍䅄䅁䅁䅯䅁䅁䅁䅯允䅁䅁䅯兂䅁䅁䅕䅁䅁䭁穁欵䉁䅁䅁允䅁䅁䅕䉵䘶ㄶ㑇樳䴸䅉䅅䅁䙁䅁䅁睁䵁䅁䅁权晁䅁䅁权呂䅁䅁权䙁䅁䅁兂䅁䅁䅁佷氳䅑䅅䅁䉁䅁䅁兂橁⼲⭬污睷䅑杷允䅁䅁䅕䅁䑁䅁䅷䅁䭁䉁䄴䅁䭁䅁䅅䅁䭁䅁䅕䅁䙁䅁䅁䅁䅂畗䅚允䅁䅁䅅䅁䙁䵁ㅐ䙋偹瑷⽕䍄䉁䅁䅁兂䅁䅁䅍䅄䅁䅁䅯杇䅁䅁䅯睕䅁䅁䅯兂䅁䅁䅕䅁䅁䕁㉂欵䉁䅁䅁允䅁䅁䅕䑔䩥坑汁く䵁䅉䅅䅁䙁䅁䅁睁䵁䅁䅁权敁䅁䅁权呂䅁䅁权䙁䅁䅁兂䅁䅁䅁䉑浲䅑䅅䅁䉁䅁䅁兂婁䙂余塌灉䅑杷允䅁䅁䅑䅁䑁䅁䅷䅁䭁䕁䄸䅁䭁䕁䄴䅁䙁䅁䅁䅁䅂敆䅚允䅁䅁䅅䅁䙁䙁偹癷潕䉘䅎䍄䉁䅁䅁兂䅁䅁䅍䅄䅁䅁䅯睈䅁䅁䅯允䅁䅁䅯兂䅁䅁䅕䅁䅁䭁奃唵䉁䅁䅁允䅁䅁䅕牕敧敨剴䐴䴸䅉䅅䅁䕁䅁䅁睁䵁䅁䅁权偂䅁䅁权佂䅁䅁兂䅁䅁䅁伴汢䅑䅅䅁䉁䅁䅁兂啁歲桦桥卑䅑杷允䅁䅁䅕䅁䑁䅁䅷䅁䭁䅁䅁䅁䭁䅁䅅䅁䭁䅁䅕䅁䙁䅁䅁䅁䅄佇䅚允䅁䅁䅅䅁䙁䱁敧敨剴乵⼴䍄䉁䅁䅁兂䅁䅁䅍䅄䅁䅁䅯先䅁䅁䅯睕䅁䅁䅯兂䅁䅁䅕䅁䅁佁䉄唵䉁䅁䅁允䅁䅁䅕䑔䩥坑汄啌䵁䅉䅅䅁䕁䅁䅁睁䵁䅁䅁权偂䅁䅁权佂䅁䅁兂䅁䅁䅁䍉浐䅑䅅䅁䉁䅁䅁兂硂児塲㍯剁䅑杷允䅁䅁䅕䅁䑁䅁䅷䅁䭁䉁䄰䅁䭁䙁䅍䅁䭁䅁䅕䅁䙁䅁䅁䅁权敆䅚允䅁䅁䅅䅁䙁䱁䩰䅄牉票䄵䍄䉁䅁䅁兂䅁䅁䅍䅄䅁䅁䅯䅁䅁䅁䅯允䅁䅁䅯兂䅁䅁䅕䅁䅁䭁剄唵䉁䅁䅁允䅁䅁䅕場啯歲桦樲䴸䅉䅅䅁䙁䅁䅁睁䵁䅁䅁权敁䅁䅁权䉁䅁䅁权䙁䅁䅁兂䅁䅁䅁䵯汘䅑䅅䅁䉁䅁䅁兂穁積積積呐睐杷允䅁䅁䅕䅁䑁䅁䅷䅁䭁䉁䄴䅁䭁䅁䅅䅁䭁䅁䅕䅁䙁䅁䅁䅁䅃伱䅖允䅁䅁䅅䅁䙁䑁積積積㥍⽍䍄䉁䅁䅁兂䅁䅁䅍䅄䅁䅁䅯杈䅁䅁䅯睕䅁䅁䅯兂䅁䅁䅕䅁䅁䭁橁欵䉁䅁䅁允䅁䅁䅕兇坒楄礱啋䵁䅉䅅䅁䕁䅁䅁睁䵁䅁䅁权偂䅁䅁权佂䅁䅁兂䅁䅁䅁䑉洳䅑䅅䅁䉁䅁䅁兂捂㡪ㅌ䙋䱷䅑杷允䅁䅁䅕䅁䑁䅁䅷䅁䭁䉁䄰䅁䭁䅁䅅䅁䭁䅁䅕䅁䙁䅁䅁䅁䅂⭱䅖允䅁䅁䅅䅁䙁乁橥䑣䬰㤱⽍䍄䉁䅁䅁䅂䅁䅁䅍䅄䅁䅁䅯睔䅁䅁䅯杔䅁䅁䅕䅁䅁䅁牄唵䉁䅁䅁允䅁䅁䅕䘷㑇潈牘䕅䵁䅉䅅䅁䙁䅁䅁睁䵁䅁䅁权敁䅁䅁权呂䅁䅁权䙁䅁䅁兂䅁䅁䅁䜴浄䅑䅅䅁䉁䅁䅁兂剃堷⽷噎椴䅑杷允䅁䅁䅕䅁䑁䅁䅷䅁䭁䅁䅁䅁䭁䅁䅅䅁䭁䅁䅕䅁䙁䅁䅁䅁权⭮䅖允䅁䅁䅅䅁䙁䩁婱婭婭摭⽫䍄䉁䅁䅁兂䅁䅁䅍䅄䅁䅁䅯䅁䅁䅁䅯允䅁䅁䅯兂䅁䅁䅕䅁䅁䍁捁欵䉁䅁䅁允䅁䅁䅕䉵䘶ㄶ㑇樳䴸䅉䅅䅁䙁䅁䅁睁䵁䅁䅁权摁䅁䅁权呂䅁䅁权䙁䅁䅁兂䅁䅁䅁临氳䅑䅅䅁䉁䅁䅁兂㑃潈牘晕獧䅑杷允䅁䅁䅕䅁䑁䅁䅷䅁䭁䉁䄸䅁䭁䙁䅍䅁䭁䅁䅕䅁䙁䅁䅁䅁杂⭱䅖允䅁䅁䅅䅁䙁䱁敧敨剴䑥䅂䍄䉁䅁䅁兂䅁䅁䅍䅄䅁䅁䅯杈䅁䅁䅯睕䅁䅁䅯兂䅁䅁䅕䅁䅁佁⽂欵䉁䅁䅁允䅁䅁䅕噋偹癷潖啉䵁䅉䅅䅁䙁䅁䅁睁䵁䅁䅁权晁䅁䅁权呂䅁䅁权䙁䅁䅁兂䅁䅁䅁䑯浈䅑䅅䅁䉁䅁䅁兂⽁噎㘶卓硷䅑杷允䅁䅁䅑䅁䑁䅁䅷䅁䭁䕁䄸䅁䭁䕁䄴䅁䙁䅁䅁䅁杄⬸䅖允䅁䅁䅅䅁䙁䅁䅁䅁䅁䅁䄵䍄䉁䅁䅁兂䅁䅁䅍䅄䅁䅁䅯䅁䅁䅁䅯允䅁䅁䅯兂䅁䅁䅕䅁䅁佁㕄唵䉁䅁䅁允䅁䅁䅕䉵䘶ㄶ㑇樳䴸䅉䅅䅁䙁䅁䅁睁䵁䅁䅁权䅁䅁䅁权呂䅁䅁权䙁䅁䅁兂䅁䅁䅁䵙汐䅑䅅䅁䉁䅁䅁兂㑄⭕汏㑭祑䅑杷允䅁䅁䅕䅁䑁䅁䅷䅁䭁䉁䅷䅁䭁䅁䅅䅁䭁䅁䅕䅁䙁䅁䅁䅁䅄佌䅚允䅁䅁䅅䅁䙁䭁䠵場啯瑲⽣䍄䉁䅁䅁䅂䅁䅁䅍䅄䅁䅁䅯睔䅁䅁䅯杔䅁䅁䅕䅁䅁佁捂欵䉁䅁䅁允䅁䅁䅕䘷㑇潈牘い䵁䅉䅅䅁䙁䅁䅁睁䵁䅁䅁权䅁䅁䅁权呂䅁䅁权䙁䅁䅁兂䅁䅁䅁䱧汦䅑䅅䅁䉁䅁䅁兂㙃兓䍷祋祣䅑杷允䅁䅁䅑䅁䑁䅁䅷䅁䭁䕁䄸䅁䭁䕁䄴䅁䙁䅁䅁䅁杄⭦䅚允䅁䅁䅅䅁䙁䭁䠵場啯杲䅴䍄䉁䅁䅁兂䅁䅁䅍䅄䅁䅁䅯䅁䅁䅁䅯睕䅁䅁䅯兂䅁䅁䅕䅁䅁佁䅂欵䉁䅁䅁允䅁䅁䅕䅁䅁䅁权き䵁䅉䅅䅁䕁䅁䅁睁䵁䅁䅁权偂䅁䅁权佂䅁䅁兂䅁䅁䅁佑氯䅑䅅䅁䉁䅁䅁兂畃⭒㙆䭆儴䅑杷允䅁䅁䅕䅁䑁䅁䅷䅁䭁䉁䅷䅁䭁䅁䅅䅁䭁䅁䅕䅁䙁䅁䅁䅁䅃敯䅖允䅁䅁䅅䅁䙁䥁䌯匹捨㥪⽉䍄䉁䅁䅁兂䅁䅁䅍䅄䅁䅁䅯䅈䅁䅁䅯允䅁䅁䅯兂䅁䅁䅕䅁䅁䝁坂欵䉁䅁䅁允䅁䅁䅕椹捨㡪ㅌ䐲䴸䅉䅅䅁䙁䅁䅁睁䵁䅁䅁权䅁䅁䅁权䉁䅁䅁权䙁䅁䅁兂䅁䅁䅁䡯洯䅑䅅䅁䉁䅁䅁兂㑃潈牘払敪睐杷允䅁䅁䅑䅁䑁䅁䅷䅁䭁䕁䄸䅁䭁䕁䄴䅁䙁䅁䅁䅁杄甫䅖允䅁䅁䅅䅁䙁偁潙䥘䌯儹䄵䍄䉁䅁䅁兂䅁䅁䅍䅄䅁䅁䅯䅈䅁䅁䅯允䅁䅁䅯兂䅁䅁䅕䅁䅁佁乂欵䉁䅁䅁允䅁䅁䅕椹捨㡪ㅌ䐲䴸䅉䅅䅁䕁䅁䅁睁䵁䅁䅁权偂䅁䅁权佂䅁䅁兂䅁䅁䅁䍷浐䅑䅅䅁䉁䅁䅁兂䙃ㄶ㑇潈剕䅑杷允䅁䅁䅑䅁䑁䅁䅷䅁䭁䕁䄸䅁䭁䕁䄴䅁䙁䅁䅁䅁䅄略䅚允䅁䅁䅅䅁䙁䙁偹癷潕䅘䄱䍄䉁䅁䅁兂䅁䅁䅍䅄䅁䅁䅯䅁䅁䅁䅯允䅁䅁䅯兂䅁䅁䅕䅁䅁䝁䕁欵䉁䅁䅁允䅁䅁䅕䉵䘶ㄶ㑇樳䴸䅉䅅䅁䕁䅁䅁睁䵁䅁䅁权偂䅁䅁权佂䅁䅁兂䅁䅁䅁䕙浘䅑䅅䅁䉁䅁䅁兂啁歲桦桥剑䅑杷允䅁䅁䅕䅁䑁䅁䅷䅁䭁䅁䅁䅁䭁䙁䅍䅁䭁䅁䅕䅁䙁䅁䅁䅁杂⭃䅚允䅁䅁䅅䅁䙁䉁奂扏䥔橬䅊䍄䉁䅁䅁兂䅁䅁䅍䅄䅁䅁䅯䅁䅁䅁䅯睕䅁䅁䅯兂䅁䅁䅕䅁䅁䝁晁欵䉁䅁䅁允䅁䅁䅕硢䑋䵷䉯き䵁䅉䅅䅁䙁䅁䅁睁䵁䅁䅁权敁䅁䅁权䉁䅁䅁权䙁䅁䅁兂䅁䅁䅁䑧浐䅑䅅䅁䉁䅁䅁兂䑄匹捨㡪噌睐杷允䅁䅁䅕䅁䑁䅁䅷䅁䭁䅁䅁䅁䭁䙁䅍䅁䭁䅁䅕䅁䙁䅁䅁䅁杄⬯䅖允䅁䅁䅅䅁䙁䭁硲欰椱䑣䅊䍄䉁䅁䅁䅂䅁䅁䅍䅄䅁䅁䅯睔䅁䅁䅯杔䅁䅁䅕䅁䅁䍁桂欵䉁䅁䅁允䅁䅁䅕䘷㑇潈牘啄䵁䅉䅅䅁䙁䅁䅁睁䵁䅁䅁权摁䅁䅁权呂䅁䅁权䙁䅁䅁兂䅁䅁䅁偁汦䅑䅅䅁䉁䅁䅁兂杂搵楁⼲瑫䅑杷允䅁䅁䅕䅁䑁䅁䅷䅁䭁䉁䄸䅁䭁䅁䅅䅁䭁䅁䅕䅁䙁䅁䅁䅁䅂伴䅖允䅁䅁䅅䅁䙁䑁䬰㘱睎摐⽯䍄䉁䅁䅁䅂䅁䅁䅍䅄䅁䅁䅯睔䅁䅁䅯杔䅁䅁䅕䅁䅁佁剄唵䉁䅁䅁允䅁䅁䅕敨剴䉵䘶あ䵁䅉䅅䅁䙁䅁䅁睁䵁䅁䅁权慁䅁䅁权䉁䅁䅁权䙁䅁䅁兂䅁䅁䅁䬴汲䅑䅅䅁䉁䅁䅁兂䅁䅁䅁䅁杄睐杷允䅁䅁䅕䅁䑁䅁䅷䅁䭁䉁䅯䅁䭁䅁䅅䅁䭁䅁䅕䅁䙁䅁䅁䅁杄敋䅚允䅁䅁䅅䅁䙁䭁睒児塲⭯⽧䍄䉁䅁䅁兂䅁䅁䅍䅄䅁䅁䅯䅁䅁䅁䅯允䅁䅁䅯兂䅁䅁䅕䅁䅁䝁㥁欵䉁䅁䅁允䅁䅁䅕䉵䘶ㄶ㑇樳䴸䅉䅅䅁䕁䅁䅁睁䵁䅁䅁权偂䅁䅁权佂䅁䅁兂䅁䅁䅁䠴浄䅑䅅䅁䉁䅁䅁兂乄䵺䵺䵺䵷䅑杷允䅁䅁䅑䅁䑁䅁䅷䅁䭁䕁䄸䅁䭁䕁䄴䅁䙁䅁䅁䅁权男䅖允䅁䅁䅅䅁䙁䉁畓⭒㙆䉆䅂䍄䉁䅁䅁兂䅁䅁䅍䅄䅁䅁䅯杇䅁䅁䅯允䅁䅁䅯兂䅁䅁䅕䅁䅁䕁瑂欵䉁䅁䅁允䅁䅁䅕䡰㥁瑃橥䐶䴸䅉䅅䅁䙁䅁䅁睁䵁䅁䅁权捁䅁䅁权呂䅁䅁权䙁䅁䅁兂䅁䅁䅁䐴洳䅑䅅䅁䉁䅁䅁兂塁挲㌷㙕畍䅑杷允䅁䅁䅕䅁䑁䅁䅷䅁䭁䅁䅁䅁䭁䙁䅍䅁䭁䅁䅕䅁䙁䅁䅁䅁䅃敊䅚允䅁䅁䅅䅁䙁佁兘瑉㕶橐䅎䍄䉁䅁䅁兂䅁䅁䅍䅄䅁䅁䅯先䅁䅁䅯允䅁䅁䅯兂䅁䅁䅕䅁䅁佁⭁欵䉁䅁䅁允䅁䅁䅕歲桦桥畓稱䴸䅉䅅䅁䙁䅁䅁睁䵁䅁䅁权敁䅁䅁权呂䅁䅁权䙁䅁䅁兂䅁䅁䅁䅧浺䅑䅅䅁䉁䅁䅁兂療潅䅐畹灅䅑杷允䅁䅁䅑䅁䑁䅁䅷䅁䭁䕁䄸䅁䭁䕁䄴䅁䙁䅁䅁䅁䅂⭥䅚允䅁䅁䅅䅁䙁䡁㥅瑃橥䅣䄱䍄䉁䅁䅁䅂䅁䅁䅍䅄䅁䅁䅯睔䅁䅁䅯杔䅁䅁䅕䅁䅁䍁時欵䉁䅁䅁允䅁䅁䅕䘷㑇潈牘い䵁䅉䅅䅁䙁䅁䅁睁䵁䅁䅁权䅁䅁䅁权呂䅁䅁权䙁䅁䅁兂䅁䅁䅁偉汌䅑䅅䅁䉁䅁䅁兂穁積積㕍祍䅑杷允䅁䅁䅕䅁䑁䅁䅷䅁䭁䉁䅯䅁䭁䅁䅅䅁䭁䅁䅕䅁䙁䅁䅁䅁䅁畇䅚允䅁䅁䅅䅁䙁䭁睒児塲⭯⽧䍄䉁䅁䅁兂䅁䅁䅍䅄䅁䅁䅯先䅁䅁䅯允䅁䅁䅯兂䅁䅁䅕䅁䅁䝁㡂欵䉁䅁䅁允䅁䅁䅕歲桦桥畓稱䴸䅉䅅䅁䕁䅁䅁睁䵁䅁䅁权偂䅁䅁权佂䅁䅁兂䅁䅁䅁䡷洯䅑䅅䅁䉁䅁䅁兂獄払敧敨䱳䅑杷允䅁䅁䅕䅁䑁䅁䅷䅁䭁䉁䅯䅁䭁䙁䅍䅁䭁䅁䅕䅁䙁䅁䅁䅁䅄伹䅖允䅁䅁䅅䅁䙁䵁ㅐ䙋偹橷䅬䍄䉁䅁䅁兂䅁䅁䅍䅄䅁䅁䅯先䅁䅁䅯允䅁䅁䅯兂䅁䅁䅕䅁䅁䵁牁欵䉁䅁䅁允䅁䅁䅕浚浚浚浚樱䴸䅉䅅䅁䕁䅁䅁睁䵁䅁䅁权偂䅁䅁权佂䅁䅁兂䅁䅁䅁䈴浶䅑䅅䅁䉁䅁䅁兂慃婭婭婭八䅑杷允䅁䅁䅕䅁䑁䅁䅷䅁䭁䉁䄰䅁䭁䙁䅍䅁䭁䅁䅕䅁䙁䅁䅁䅁权电䅖允䅁䅁䅅䅁䙁䱁敧敨剴䌫䅸䍄䉁䅁䅁䅂䅁䅁䅍䅄䅁䅁䅯睔䅁䅁䅯杔䅁䅁䅕䅁䅁䥁い唵䉁䅁䅁允䅁䅁䅕呣䬰㘱睎䕅䵁䅉䅅䅁䕁䅁䅁睁䵁䅁䅁权偂䅁䅁权佂䅁䅁兂䅁䅁䅁䅷洳䅑䅅䅁䉁䅁䅁兂䑄匹捨㡪卉䅑杷允䅁䅁䅑䅁䑁䅁䅷䅁䭁䕁䄸䅁䭁䕁䄴䅁䙁䅁䅁䅁杄畋䅚允䅁䅁䅅䅁䙁䉁畓⭒㙆䉆䅎䍄䉁䅁䅁兂䅁䅁䅍䅄䅁䅁䅯杈䅁䅁䅯允䅁䅁䅯兂䅁䅁䅕䅁䅁䅁䥄唵䉁䅁䅁允䅁䅁䅕積積積積稰䴸䅉䅅䅁䙁䅁䅁睁䵁䅁䅁权晁䅁䅁权呂䅁䅁权䙁䅁䅁兂䅁䅁䅁䅑浢䅑䅅䅁䉁䅁䅁兂䑃䵷桱婒睙䅑杷允䅁䅁䅑䅁䑁䅁䅷䅁䭁䕁䄸䅁䭁䕁䄴䅁䙁䅁䅁䅁䅃⭆䅚允䅁䅁䅅䅁䙁䑁䬰㘱睎剐䅊䍄䉁䅁䅁兂䅁䅁䅍䅄䅁䅁䅯先䅁䅁䅯允䅁䅁䅯兂䅁䅁䅕䅁䅁䥁杂欵䉁䅁䅁允䅁䅁䅕歲桦桥畓稱䴸䅉䅅䅁䕁䅁䅁睁䵁䅁䅁权偂䅁䅁权佂䅁䅁兂䅁䅁䅁䝧洳䅑䅅䅁䉁䅁䅁兂㝂䭆䠵場䵯䅑杷允䅁䅁䅕䅁䑁䅁䅷䅁䭁䉁䅯䅁䭁䅁䅅䅁䭁䅁䅕䅁䙁䅁䅁䅁䅄佸䅖允䅁䅁䅅䅁䙁䅁䅁䅁䅁佁⽁䍄䉁䅁䅁兂䅁䅁䅍䅄䅁䅁䅯杈䅁䅁䅯睕䅁䅁䅯兂䅁䅁䅕䅁䅁䅁䙁欵䉁䅁䅁允䅁䅁䅕䅁䅁䅁䅁歋䵁䅉䅅䅁䙁䅁䅁睁䵁䅁䅁权晁䅁䅁权呂䅁䅁权䙁䅁䅁兂䅁䅁䅁䭷汔䅑䅅䅁䉁䅁䅁兂㑃潈牘塕睧䅑杷允䅁䅁䅕䅁䑁䅁䅷䅁䭁䅁䅁䅁䭁䅁䅅䅁䭁䅁䅕䅁䙁䅁䅁䅁权佸䅖允䅁䅁䅅䅁䙁䑁䬰㘱睎摐⽯䍄䉁䅁䅁䅂䅁䅁䅍䅄䅁䅁䅯睔䅁䅁䅯杔䅁䅁䅕䅁䅁䍁⽂欵䉁䅁䅁允䅁䅁䅕䅁䅁䅁䅁䕄䵁䅉䅅䅁䙁䅁䅁睁䵁䅁䅁权捁䅁䅁权䉁䅁䅁权䙁䅁䅁兂䅁䅁䅁乯汐䅑䅅䅁䉁䅁䅁兂穁積積積呐睐杷允䅁䅁䅕䅁䑁䅁䅷䅁䭁䅁䅁䅁䭁䅁䅅䅁䭁䅁䅕䅁䙁䅁䅁䅁䅃數䅖允䅁䅁䅅䅁䙁䑁䬰㘱睎摐⽯䍄䉁䅁䅁兂䅁䅁䅍䅄䅁䅁䅯䅈䅁䅁䅯允䅁䅁䅯兂䅁䅁䅕䅁䅁佁塁欵䉁䅁䅁允䅁䅁䅕㑈牘払敧吱䴸䅉䅅䅁䙁䅁䅁睁䵁䅁䅁权䅁䅁䅁权䉁䅁䅁权䙁䅁䅁兂䅁䅁䅁䙙浦䅑䅅䅁䉁䅁䅁兂㑃潈牘払敪睐杷允䅁䅁䅕䅁䑁䅁䅷䅁䭁䉁䅷䅁䭁䅁䅅䅁䭁䅁䅕䅁䙁䅁䅁䅁䅂畦䅚允䅁䅁䅅䅁䙁偁潙䥘䌯搹⽧䍄䉁䅁䅁䅂䅁䅁䅍䅄䅁䅁䅯睔䅁䅁䅯杔䅁䅁䅕䅁䅁䵁硄唵䉁䅁䅁允䅁䅁䅕瑃橥䑣䬰い䵁䅉䅅䅁䙁䅁䅁睁䵁䅁䅁权捁䅁䅁权呂䅁䅁权䙁䅁䅁兂䅁䅁䅁䍉浄䅑䅅䅁䉁䅁䅁兂祃敮渫杸畳䅑杷允䅁䅁䅕䅁䑁䅁䅷䅁䭁䉁䄴䅁䭁䙁䅍䅁䭁䅁䅕䅁䙁䅁䅁䅁䅄佖䅚允䅁䅁䅅䅁䙁乁㕶浦㡱䍤䅊䍄䉁䅁䅁䅂䅁䅁䅍䅄䅁䅁䅯睔䅁䅁䅯杔䅁䅁䅕䅁䅁䵁穄唵䉁䅁䅁允䅁䅁䅕䅁䅁䅁䅁歄䵁䅉䅅䅁䙁䅁䅁睁䵁䅁䅁权慁䅁䅁权呂䅁䅁权䙁䅁䅁兂䅁䅁䅁䝁浮䅑䅅䅁䉁䅁䅁兂癁匳䝑噧㝕䅑杷允䅁䅁䅕䅁䑁䅁䅷䅁䭁䅁䅁䅁䭁䙁䅍䅁䭁䅁䅕䅁䙁䅁䅁䅁杄伸䅖允䅁䅁䅅䅁䙁䑁積積積穫䅊䍄䉁䅁䅁兂䅁䅁䅍䅄䅁䅁䅯䅈䅁䅁䅯睕䅁䅁䅯兂䅁䅁䅕䅁䅁䝁䙁欵䉁䅁䅁允䅁䅁䅕椹捨㡪ㅊ啌䵁䅉䅅䅁䙁䅁䅁睁䵁䅁䅁权捁䅁䅁权呂䅁䅁权䙁䅁䅁兂䅁䅁䅁䅷浢䅑䅅䅁䉁䅁䅁兂㉄䙋偹湷瑕䅑杷允䅁䅁䅑䅁䑁䅁䅷䅁䭁䕁䄸䅁䭁䕁䄴䅁䙁䅁䅁䅁䅃畯䅖允䅁䅁䅅䅁䙁䡁啳歲桦瑥⽑䍄䉁䅁䅁䅂䅁䅁䅍䅄䅁䅁䅯睔䅁䅁䅯杔䅁䅁䅕䅁䅁䍁㝂欵䉁䅁䅁允䅁䅁䅕䥘䌯匹捨啄䵁䅉䅅䅁䙁䅁䅁睁䵁䅁䅁权䅁䅁䅁权呂䅁䅁权䙁䅁䅁兂䅁䅁䅁䭙汪䅑䅅䅁䉁䅁䅁兂塄㍯㥁湃硣䅑杷允䅁䅁䅑䅁䑁䅁䅷䅁䭁䕁䄸䅁䭁䕁䄴䅁䙁䅁䅁䅁䅂敦䅚允䅁䅁䅅䅁䙁䝁浚浚浚杚䅸䍄䉁䅁䅁兂䅁䅁䅍䅄䅁䅁䅯䅁䅁䅁䅯睕䅁䅁䅯兂䅁䅁䅕䅁䅁䥁乄唵䉁䅁䅁允䅁䅁䅕敢㝦晱祈歍䵁䅉䅅䅁䙁䅁䅁睁䵁䅁䅁权晁䅁䅁权呂䅁䅁权䙁䅁䅁兂䅁䅁䅁佧汢䅑䅅䅁䉁䅁䅁兂⭃确癯唳睑䅑杷允䅁䅁䅑䅁䑁䅁䅷䅁䭁䕁䄸䅁䭁䕁䄴䅁䙁䅁䅁䅁权⬫䅖允䅁䅁䅅䅁䙁䝁浚浚浚杚䅸䍄䉁䅁䅁䅂䅁䅁䅍䅄䅁䅁䅯睔䅁䅁䅯杔䅁䅁䅕䅁䅁䅁敁欵䉁䅁䅁允䅁䅁䅕歲桦桥畓䕅䵁䅉䅅䅁䙁䅁䅁睁䵁䅁䅁权慁䅁䅁权䉁䅁䅁权䙁䅁䅁兂䅁䅁䅁䴴汌䅑䅅䅁䉁䅁䅁兂䅁䅁䅁䅁杄睐杷允䅁䅁䅕䅁䑁䅁䅷䅁䭁䅁䅁䅁䭁䙁䅍䅁䭁䅁䅕䅁䙁䅁䅁䅁杁⭬䅖允䅁䅁䅅䅁䙁䱁へ硫䕧橤䅂䍄䉁䅁䅁兂䅁䅁䅍䅄䅁䅁䅯先䅁䅁䅯睕䅁䅁䅯兂䅁䅁䅕䅁䅁䥁㙂欵䉁䅁䅁允䅁䅁䅕䬸䝦穓䩦啌䵁䅉䅅䅁䙁䅁䅁睁䵁䅁䅁权摁䅁䅁权呂䅁䅁权䙁䅁䅁兂䅁䅁䅁䭁汲䅑䅅䅁䉁䅁䅁兂婄発呤㘴瑕䅑杷允䅁䅁䅕䅁䑁䅁䅷䅁䭁䉁䄸䅁䭁䅁䅅䅁䭁䅁䅕䅁䙁䅁䅁䅁权佬䅖允䅁䅁䅅䅁䙁䙁㑋潈牘敕⽁䍄䉁䅁䅁兂䅁䅁䅍䅄䅁䅁䅯睈䅁䅁䅯睕䅁䅁䅯兂䅁䅁䅕䅁䅁佁偁欵䉁䅁䅁允䅁䅁䅕䙂余扌㥋䕍䵁䅉䅅䅁䙁䅁䅁睁䵁䅁䅁权晁䅁䅁权呂䅁䅁权䙁䅁䅁兂䅁䅁䅁䑙浺䅑䅅䅁䉁䅁䅁兂㍁啩杆吵硁䅑杷允䅁䅁䅑䅁䑁䅁䅷䅁䭁䕁䄸䅁䭁䕁䄴䅁䙁䅁䅁䅁权佚䅚允䅁䅁䅅䅁䙁䱁敧敨剴䅵䄵䍄䉁䅁䅁兂䅁䅁䅍䅄䅁䅁䅯䅁䅁䅁䅯允䅁䅁䅯兂䅁䅁䅕䅁䅁䭁敄唵䉁䅁䅁允䅁䅁䅕場啯歲桦樲䴸䅉䅅䅁䙁䅁䅁睁䵁䅁䅁权晁䅁䅁权䉁䅁䅁权䙁䅁䅁兂䅁䅁䅁䵷汄䅑䅅䅁䉁䅁䅁兂㑃潈牘払敪睐杷允䅁䅁䅕䅁䑁䅁䅷䅁䭁䉁䄸䅁䭁䅁䅅䅁䭁䅁䅕䅁䙁䅁䅁䅁䅄敋䅚允䅁䅁䅅䅁䙁䕁桪桥畓⭒⽅䍄䉁䅁䅁䅂䅁䅁䅍䅄䅁䅁䅯睔䅁䅁䅯杔䅁䅁䅕䅁䅁䵁扂欵䉁䅁䅁允䅁䉁䅑䅂䅁䅁䅁䅁䵁䅉䅅䅁䙁䅁䅁睁䵁䅁䅁权慁䅁䅁权䉁䅁䅁权䙁䅁䅁兂䅁䅁䅁䉷浺䅑䅅䅁䉁䅁䅁兂歃䑣䬰㘱潐睐杷允䅁䅁䅕䅁䑁䅁䅷䅁䭁䉁䅯䅁䭁䙁䅍䅁䭁䅁䅕䅁䙁䅁䅁䅁䅁住䅚允䅁䅁䅅䅁䙁䉁䘫ㄶ㑇樳䅰䍄䉁䅁䅁兂䅁䅁䅍䅄䅁䅁䅯杈䅁䅁䅯允䅁䅁䅯兂䅁䅁䅕䅁䅁䵁楂欵䉁䅁䅁允䅁䅁䅕䅁䅁䅁䅁䐰䴸䅉䅅䅁䙁䅁䅁睁䵁䅁䅁权䅁䅁䅁权呂䅁䅁权䙁䅁䅁兂䅁䅁䅁䍁浪䅑䅅䅁䉁䅁䅁兂汄䌰扌含稴䅑杷允䅁䅁䅕䅁䑁䅁䅷䅁䭁䅁䅁䅁䭁䙁䅍䅁䭁䅁䅕䅁䙁䅁䅁䅁䅃佢䅚允䅁䅁䅅䅁䙁䙁橔婰䕶䐴䅎䍄䉁䅁䅁兂䅁䅁䅍䅄䅁䅁䅯䅁䅁䅁䅯睕䅁䅁䅯兂䅁䅁䅕䅁䅁佁乂欵䉁䅁䅁允䅁䅁䅕潅䅐煹䙈き䵁䅉䅅䅁䙁䅁䅁睁䵁䅁䅁权捁䅁䅁权呂䅁䅁权䙁䅁䅁兂䅁䅁䅁䅁洳䅑䅅䅁䉁䅁䅁兂敂歵䵫煁瑳䅑杷允䅁䅁䅕䅁䑁䅁䅷䅁䭁䉁䄸䅁䭁䙁䅍䅁䭁䅁䅕䅁䙁䅁䅁䅁䅂敦䅚允䅁䅁䅅䅁䙁䝁㡱䩤奍䑊䅆䍄䉁䅁䅁䅂䅁䅁䅍䅄䅁䅁䅯睔䅁䅁䅯杔䅁䅁䅕䅁䅁䅁⽂欵䉁䅁䅁允䅁䅁䅕䅁䅁䅁䅁䕄䵁䅉䅅䅁䙁䅁䅁睁䵁䅁䅁权敁䅁䅁权呂䅁䅁权䙁䅁䅁兂䅁䅁䅁䑷洯䅑䅅䅁䉁䅁䅁兂い搯㑒圶歙䅑杷允䅁䅁䅑䅁䑁䅁䅷䅁䭁䕁䄸䅁䭁䕁䄴䅁䙁䅁䅁䅁䅄⭹䅖允䅁䅁䅅䅁䙁䑁積積積睍䅆䍄䉁䅁䅁兂䅁䅁䅍䅄䅁䅁䅯杇䅁䅁䅯允䅁䅁䅯兂䅁䅁䅕䅁䅁䍁乁欵䉁䅁䅁允䅁䅁䅕浚浚浚浚樵䴸䅉䅅䅁䙁䅁䅁睁䵁䅁䅁权䅁䅁䅁权䉁䅁䅁权䙁䅁䅁兂䅁䅁䅁䘴浌䅑䅅䅁䉁䅁䅁兂㑃潈牘払敪睐杷允䅁䅁䅕䅁䑁䅁䅷䅁䭁䅁䅁䅁䭁䙁䅍䅁䭁䅁䅕䅁䙁䅁䅁䅁杂伲䅖允䅁䅁䅅䅁䙁䭁慁㥌欰橂䅎䍄䉁䅁䅁兂䅁䅁䅍䅄䅁䅁䅯杇䅁䅁䅯睕䅁䅁䅯兂䅁䅁䅕䅁䅁佁⽁欵䉁䅁䅁允䅁䅁䅕卸睃浣硧く䵁䅉䅅䅁䕁䅁䅁睁䵁䅁䅁权偂䅁䅁权佂䅁䅁兂䅁䅁䅁䝑浌䅑䅅䅁䉁䅁䅁兂㑃潈牘払佧䅑杷允䅁䅁䅕䅁䑁䅁䅷䅁䭁䅁䅁䅁䭁䙁䅍䅁䭁䅁䅕䅁䙁䅁䅁䅁䅄佴䅖允䅁䅁䅅䅁䙁䱁䩰䅄牉穊䅊䍄䉁䅁䅁兂䅁䅁䅍䅄䅁䅁䅯杈䅁䅁䅯睕䅁䅁䅯兂䅁䅁䅕䅁䅁佁楂欵䉁䅁䅁允䅁䅁䅕敫㠱穐敖歉䵁䅉䅅䅁䕁䅁䅁睁䵁䅁䅁权偂䅁䅁权佂䅁䅁兂䅁䅁䅁䄴浦䅑䅅䅁䉁䅁䅁兂硂児塲㍯剁䅑杷允䅁䅁䅕䅁䑁䅁䅷䅁䭁䉁䅷䅁䭁䅁䅅䅁䭁䅁䅕䅁䙁䅁䅁䅁杂余䅚允䅁䅁䅅䅁䙁偁潙䥘䌯搹⽧䍄䉁䅁䅁䅂䅁䅁䅍䅄䅁䅁䅯睔䅁䅁䅯杔䅁䅁䅕䅁䅁佁⭂欵䉁䅁䅁允䅁䅁䅕䅁䅁䅁䅁䕄䵁䅉䅅䅁䙁䅁䅁睁䵁䅁䅁权摁䅁䅁权䉁䅁䅁权䙁䅁䅁兂䅁䅁䅁䅷浢䅑䅅䅁䉁䅁䅁兂晁敨剴䉵嘷睐杷允䅁䅁䅕䅁䑁䅁䅷䅁䭁䉁䄰䅁䭁䙁䅍䅁䭁䅁䅕䅁䙁䅁䅁䅁杁敕䅚允䅁䅁䅅䅁䙁䡁呗䅇坒楪䄵䍄䉁䅁䅁兂䅁䅁䅍䅄䅁䅁䅯䅈䅁䅁䅯允䅁䅁䅯兂䅁䅁䅕䅁䅁䥁䅃欵䉁䅁䅁允䅁䅁䅕椹捨㡪ㅌ䐲䴸䅉䅅䅁䙁䅁䅁睁䵁䅁䅁权䅁䅁䅁权䉁䅁䅁权䙁䅁䅁兂䅁䅁䅁余氯䅑䅅䅁䉁䅁䅁兂䙃ㄶ㑇潈托睐杷允䅁䅁䅕䅁䑁䅁䅷䅁䭁䉁䄴䅁䭁䅁䅅䅁䭁䅁䅕䅁䙁䅁䅁䅁杄敔䅚允䅁䅁䅅䅁䙁䵁ㅐ䙋偹瑷⽕䍄䉁䅁䅁兂䅁䅁䅍䅄䅁䅁䅯䅁䅁䅁䅯睕䅁䅁䅯兂䅁䅁䅕䅁䅁䥁い唵䉁䅁䅁允䅁䅁䅕噋偹癷潖歍䵁䅉䅅䅁䙁䅁䅁睁䵁䅁䅁权䅁䅁䅁权呂䅁䅁权䙁䅁䅁兂䅁䅁䅁䜴浲䅑䅅䅁䉁䅁䅁兂啂㘴扗佸穁䅑杷允䅁䅁䅑䅁䑁䅁䅷䅁䭁䕁䄸䅁䭁䕁䄴䅁䙁䅁䅁䅁杁畒䅚允䅁䅁䅅䅁䙁䑁積積積硍䅆䍄䉁䅁䅁兂䅁䅁䅍䅄䅁䅁䅯䅁䅁䅁䅯睕䅁䅁䅯兂䅁䅁䅕䅁䅁䭁噂欵䉁䅁䅁允䅁䅁䅕扏䥔牤昷き䵁䅉䅅䅁䕁䅁䅁睁䵁䅁䅁权偂䅁䅁权佂䅁䅁兂䅁䅁䅁䡁浘䅑䅅䅁䉁䅁䅁兂浂浚浚浚䵙䅑杷允䅁䅁䅕䅁䑁䅁䅷䅁䭁䉁䅯䅁䭁䅁䅅䅁䭁䅁䅕䅁䙁䅁䅁䅁䅂佋䅚允䅁䅁䅅䅁䙁䭁睒児塲⭯⽧䍄䉁䅁䅁兂䅁䅁䅍䅄䅁䅁䅯睈䅁䅁䅯睕䅁䅁䅯兂䅁䅁䅕䅁䅁䥁癄唵䉁䅁䅁允䅁䅁䅕㥉㕶浦捰䕍䵁䅉䅅䅁䕁䅁䅁睁䵁䅁䅁权偂䅁䅁权佂䅁䅁兂䅁䅁䅁䡑洷䅑䅅䅁䉁䅁䅁兂硂児塲㍯䱁䅑杷允䅁䅁䅕䅁䑁䅁䅷䅁䭁䅁䅁䅁䭁䅁䅅䅁䭁䅁䅕䅁䙁䅁䅁䅁䅁⬸䅖允䅁䅁䅅䅁䙁䥁牘払敧摨⽳䍄䉁䅁䅁䅂䅁䅁䅍䅄䅁䅁䅯睔䅁䅁䅯杔䅁䅁䅕䅁䅁䥁塂欵䉁䅁䅁允䅁䅁䅕体㙆䭆䠵い䵁䅉䅅䅁䙁䅁䅁睁䵁䅁䅁权敁䅁䅁权呂䅁䅁权䙁䅁䅁兂䅁䅁䅁乑汮䅑䅅䅁䉁䅁䅁兂汁潂噇㑑獳䅑杷允䅁䅁䅕䅁䑁䅁䅷䅁䭁䉁䄴䅁䭁䙁䅍䅁䭁䅁䅕䅁䙁䅁䅁䅁䅃⭚䅚允䅁䅁䅅䅁䙁乁楅⼲⭬楡䅆䍄䉁䅁䅁兂䅁䅁䅍䅄䅁䅁䅯睈䅁䅁䅯允䅁䅁䅯兂䅁䅁䅕䅁䅁佁楄唵䉁䅁䅁允䅁䅁䅕児塲㍯㥁樲䴸䅉䅅䅁䕁䅁䅁睁䵁䅁䅁权偂䅁䅁权佂䅁䅁兂䅁䅁䅁䝑洯䅑䅅䅁䉁䅁䅁兂捂㡪ㅌ䙋䱷䅑杷允䅁䅁䅕䅁䑁䅁䅷䅁䭁䅁䅁䅁䭁䙁䅍䅁䭁䅁䅕䅁䙁䅁䅁䅁䅁⭎䅚允䅁䅁䅅䅁䙁䍁礲敮渫橨䅎䍄䉁䅁䅁兂䅁䅁䅍䅄䅁䅁䅯䅈䅁䅁䅯睕䅁䅁䅯兂䅁䅁䅕䅁䅁䭁晃唵䉁䅁䅁允䅁䅁䅕捷桱扒穙啌䵁䅉䅅䅁䙁䅁䅁睁䵁䅁䅁权敁䅁䅁权䉁䅁䅁权䙁䅁䅁兂䅁䅁䅁䅧洯䅑䅅䅁䉁䅁䅁兂䑄匹捨㡪噌睐杷允䅁䅁䅕䅁䑁䅁䅷䅁䭁䉁䄴䅁䭁䙁䅍䅁䭁䅁䅕䅁䙁䅁䅁䅁杂伶䅖允䅁䅁䅅䅁䙁䡁㥅瑃橥䌸䅴䍄䉁䅁䅁䅂䅁䅁䅍䅄䅁䅁䅯睔䅁䅁䅯杔䅁䅁䅕䅁䅁䕁噄唵䉁䅁䅁允䅁䅁䅕䡰㥁瑃橥歂䵁䅉䅅䅁䕁䅁䅁睁䵁䅁䅁权偂䅁䅁权佂䅁䅁兂䅁䅁䅁䝁浔䅑䅅䅁䉁䅁䅁兂㑃潈牘払佧䅑杷允䅁䅁䅕䅁䑁䅁䅷䅁䭁䉁䅷䅁䭁䅁䅅䅁䭁䅁䅕䅁䙁䅁䅁䅁杄畳䅖允䅁䅁䅅䅁䙁䥁䌯匹捨㥪⽉䍄䉁䅁䅁兂䅁䅁䅍䅄䅁䅁䅯先䅁䅁䅯睕䅁䅁䅯兂䅁䅁䅕䅁䅁䅁捁欵䉁䅁䅁允䅁䅁䅕瑃橥䑣䬳歌䵁䅉䅅䅁䙁䅁䅁睁䵁䅁䅁权敁䅁䅁权呂䅁䅁权䙁䅁䅁兂䅁䅁䅁乷氯䅑䅅䅁䉁䅁䅁兂硂児塲⽯牁䅑杷允䅁䅁䅕䅁䑁䅁䅷䅁䭁䉁䅷䅁䭁䙁䅍䅁䭁䅁䅕䅁䙁䅁䅁䅁䅃敃䅚允䅁䅁䅅䅁䙁偁潙䥘䌯卤䄱䍄䉁䅁䅁兂䅁䅁䅍䅄䅁䅁䅯睈䅁䅁䅯允䅁䅁䅯兂䅁䅁䅕䅁䅁䍁桄唵䉁䅁䅁允䅁䅁䅕児塲㍯㥁樲䴸䅉䅅䅁䙁䅁䅁睁䵁䅁䅁权晁䅁䅁权呂䅁䅁权䙁䅁䅁兂䅁䅁䅁䑯浮䅑䅅䅁䉁䅁䅁兂㍁啩杆吵硁䅑杷允䅁䅁䅑䅁䑁䅁䅷䅁䭁䕁䄸䅁䭁䕁䄴䅁䙁䅁䅁䅁䅄⭈䅚允䅁䅁䅅䅁䙁䱁敧敨剴䉵䅂䍄䉁䅁䅁兂䅁䅁䅍䅄䅁䅁䅯杈䅁䅁䅯允䅁䅁䅯兂䅁䅁䅕䅁䅁䵁潃唵䉁䅁䅁允䅁䅁䅕積積積積稰䴸䅉䅅䅁䕁䅁䅁睁䵁䅁䅁权偂䅁䅁权佂䅁䅁兂䅁䅁䅁䡁洷䅑䅅䅁䉁䅁䅁兂浂浚浚浚䵙䅑杷允䅁䅁䅕䅁䑁䅁䅷䅁䭁䅁䅁䅁䭁䙁䅍䅁䭁䅁䅕䅁䙁䅁䅁䅁䅃估䅖允䅁䅁䅅䅁䙁䝁渳㘫确樸䅊䍄䉁䅁䅁兂䅁䅁䅍䅄䅁䅁䅯先䅁䅁䅯允䅁䅁䅯兂䅁䅁䅕䅁䅁䝁呂欵䉁䅁䅁允䅁䅁䅕歲桦桥畓稱䴸䅉䅅䅁䕁䅁䅁睁䵁䅁䅁权偂䅁䅁权佂䅁䅁兂䅁䅁䅁䕧浌䅑䅅䅁䉁䅁䅁兂晁敨剴䉵儴䅑杷允䅁䅁䅕䅁䑁䅁䅷䅁䭁䉁䄴䅁䭁䙁䅍䅁䭁䅁䅕䅁䙁䅁䅁䅁䅃畕䅚允䅁䅁䅅䅁䙁乁㕶浦㡱䍤䅊䍄䉁䅁䅁䅂䅁䅁䅍䅄䅁䅁䅯睔䅁䅁䅯杔䅁䅁䅕䅁䅁䵁い唵䉁䅁䅁允䅁䅁䅕灭婭婭婭䕅䵁䅉䅅䅁䙁䅁䅁睁䵁䅁䅁权䅁䅁䅁权呂䅁䅁权䙁䅁䅁兂䅁䅁䅁偁汮䅑䅅䅁䉁䅁䅁兂灁䥘䌯圹祧䅑杷允䅁䅁䅕䅁䑁䅁䅷䅁䭁䉁䅷䅁䭁䅁䅅䅁䭁䅁䅕䅁䙁䅁䅁䅁杄佘䅚允䅁䅁䅅䅁䙁偁潙䥘䌯搹⽧䍄䉁䅁䅁䅂䅁䅁䅍䅄䅁䅁䅯睔䅁䅁䅯杔䅁䅁䅕䅁䅁䅁䙁欵䉁䅁䅁允䅁䅁䅕体㙆䭆䠵啅䵁䅉䅅䅁䕁䅁䅁睁䵁䅁䅁权偂䅁䅁权佂䅁䅁兂䅁䅁䅁䙷浺䅑䅅䅁䉁䅁䅁䅆䕁䅁䅁䅁䅁䅁杷允䅁䅁䅕䅁䑁䅁䅷䅁䭁䅁䅁䅁䭁䅁䅅䅁䭁䅁䅕䅁䙁䅁䅁䅁杁畤䅚允䅁䅁䅅䅁䙁䱁敧敨剴乵⼴䍄䉁䅁䅁兂䅁䅁䅍䅄䅁䅁䅯䅁䅁䅁䅯睕䅁䅁䅯兂䅁䅁䅕䅁䅁䥁㙁欵䉁䅁䅁允䅁䅁䅕䅁䅁䅁权き䵁䅉䅅䅁䕁䅁䅁睁䵁䅁䅁权偂䅁䅁权佂䅁䅁兂䅁䅁䅁䕑浺䅑䅅䅁䉁䅁䅁兂㥁瑃橥䑣到䅑杷允䅁䅁䅕䅁䑁䅁䅷䅁䭁䉁䄰䅁䭁䙁䅍䅁䭁䅁䅕䅁䙁䅁䅁䅁杄佴䅖允䅁䅁䅅䅁䙁䅁塲㍯㥁楹䄱䍄䉁䅁䅁䅂䅁䅁䅍䅄䅁䅁䅯睔䅁䅁䅯杔䅁䅁䅕䅁䅁䕁睁欵䉁䅁䅁允䅁䅁䅕椹捨㡪ㅌ歅䵁䅉䅅䅁䙁䅁䅁睁䵁䅁䅁权摁䅁䅁权呂䅁䅁权䙁䅁䅁兂䅁䅁䅁偑氷䅑䅅䅁䉁䅁䅁兂杂搵楁⼲瑫䅑杷允䅁䅁䅕䅁䑁䅁䅷䅁䭁䉁䅯䅁䭁䙁䅍䅁䭁䅁䅕䅁䙁䅁䅁䅁权當䅖允䅁䅁䅅䅁䙁䱁䩰䅄牉穊䅰䍄䉁䅁䅁兂䅁䅁䅍䅄䅁䅁䅯杈䅁䅁䅯允䅁䅁䅯兂䅁䅁䅕䅁䅁䝁求欵䉁䅁䅁允䅁䅁䅕䅁䅁䅁䅁䐰䴸䅉䅅䅁䙁䅁䅁睁䵁䅁䅁权䅁䅁䅁权䉁䅁䅁权䙁䅁䅁兂䅁䅁䅁䕧浶䅑䅅䅁䉁䅁䅁兂㑃潈牘払敪睐杷允䅁䅁䅕䅁䑁䅁䅷䅁䭁䉁䄰䅁䭁䙁䅍䅁䭁䅁䅕䅁䙁䅁䅁䅁杁⬸䅖允䅁䅁䅅䅁䙁䭁扡䍸睃楳䄱䍄䉁䅁䅁䅂䅁䅁䅍䅄䅁䅁䅯睔䅁䅁䅯杔䅁䅁䅕䅁䅁佁楂欵䉁䅁䅁允䅁䅁䅕浚浚浚浚歄䵁䅉䅅䅁䙁䅁䅁睁䵁䅁䅁权䅁䅁䅁权呂䅁䅁权䙁䅁䅁兂䅁䅁䅁䝁浲䅑䅅䅁䉁䅁䅁兂啂㘴扗佸穁䅑杷允䅁䅁䅑䅁䑁䅁䅷䅁䭁䕁䄸䅁䭁䕁䄴䅁䙁䅁䅁䅁䅄畂䅚允䅁䅁䅅䅁䙁䑁䬰㘱睎剐䅊䍄䉁䅁䅁兂䅁䅁䅍䅄䅁䅁䅯䅁䅁䅁䅯允䅁䅁䅯兂䅁䅁䅕䅁䅁佁汁欵䉁䅁䅁允䅁䅁䅕䉵䘶ㄶ㑇樳䴸䅉䅅䅁䙁䅁䅁睁䵁䅁䅁权捁䅁䅁权呂䅁䅁权䙁䅁䅁兂䅁䅁䅁䅷洳䅑䅅䅁䉁䅁䅁兂敂歵䵫煁瑳䅑杷允䅁䅁䅑䅁䑁䅁䅷䅁䭁䕁䄸䅁䭁䕁䄴䅁䙁䅁䅁䅁䅃畣䅚允䅁䅁䅅䅁䭁䉁䅳䅁䵁䅉䅅䅁䙁䅁䅁睁䵁䅁䅁权摁䅁䅁权䉁䅁䅁权䙁䅁䅁兂䅁䅁䅁䅯浐䅑䅅䅁䉁䅁䅁兂晁敨剴䉵嘷睐杷允䅁䅁䅕䅁䑁䅁䅷䅁䭁䅁䅁䅁䭁䙁䅍䅁䭁䅁䅕䅁䙁䅁䅁䅁杂畑䅚允䅁䅁䅅䅁䙁䅁䅁䅁䅁䑯䅎䍄䉁䅁䅁䅂䅁䅁䅍䅄䅁䅁䅯睔䅁䅁䅯杔䅁䅁䅕䅁䅁䝁療欵䉁䅁䅁允䅁䅁䅕⽷潕䥘䌯ぃ䵁䅉䅅䅁䙁䅁䅁睁䵁䅁䅁权捁䅁䅁权呂䅁䅁权䙁䅁䅁兂䅁䅁䅁䅷浈䅑䅅䅁䉁䅁䅁兂㉄䙋偹湷瑕䅑杷允䅁䅁䅕䅁䑁䅁䅷䅁䭁䉁䄸䅁䭁䙁䅍䅁䭁䅁䅕䅁䙁䅁䅁䅁䅃界䅚允䅁䅁䅅䅁䙁䑁ㄸ牘䩰䑌䅆䍄䉁䅁䅁兂䅁䅁䅍䅄䅁䅁䅯䅁䅁䅁䅯允䅁䅁䅯兂䅁䅁䅕䅁䅁䕁牃唵䉁䅁䅁允䅁䅁䅕灭婭婭婭吲䴸䅉䅅䅁䙁䅁䅁睁䵁䅁䅁权敁䅁䅁权䉁䅁䅁权䙁䅁䅁兂䅁䅁䅁䑧浶䅑䅅䅁䉁䅁䅁兂䑄匹捨㡪噌睐杷允䅁䅁䅕䅁䑁䅁䅷䅁䭁䉁䄸䅁䭁䙁䅍䅁䭁䅁䅕䅁䙁䅁䅁䅁杄畖䅚允䅁䅁䅅䅁䙁䡁⼰噎㘶呋䅆䍄䉁䅁䅁䅂䅁䅁䅍䅄䅁䅁䅯睔䅁䅁䅯杔䅁䅁䅕䅁䅁䵁㥂欵䉁䅁䅁允䅁䅁䅕硥畓⭒㙆䕄䵁䅉䅅䅁䕁䅁䅁睁䵁䅁䅁权偂䅁䅁权佂䅁䅁兂䅁䅁䅁䭷汢䅑䅅䅁䉁䅁䅁兂塄㍯㥁瑃呦睐杷允䅁䅁䅕䅁䑁䅁䅷䅁䭁䅁䅁䅁䭁䙁䅍䅁䭁䅁䅕䅁䙁䅁䅁䅁杁佹䅖允䅁䅁䅅䅁䙁䝁渳㘫确樸䅊䍄䉁䅁䅁兂䅁䅁䅍䅄䅁䅁䅯杇䅁䅁䅯睕䅁䅁䅯兂䅁䅁䅕䅁䅁䵁䍁欵䉁䅁䅁允䅁䅁䅕牒穢搯契歏䵁䅉䅅䅁䙁䅁䅁睁䵁䅁䅁权晁䅁䅁权呂䅁䅁权䙁䅁䅁兂䅁䅁䅁䕑浲䅑䅅䅁䉁䅁䅁兂䕁杖琴桳砰䅑杷允䅁䅁䅑䅁䑁䅁䅷䅁䭁䕁䄸䅁䭁䕁䄴䅁䙁䅁䅁䅁杄伳䅖允䅁䅁䅅䅁䙁䍁捬㡪ㅌ䅋䅨䍄䉁䅁䅁兂䅁䅁䅍䅄䅁䅁䅯䅁䅁䅁䅯允䅁䅁䅯兂䅁䅁䅕䅁䅁䥁畂欵䉁䅁䅁允䅁䅁䅕䉵䘶ㄶ㑇樳䴸䅉䅅䅁䙁䅁䅁睁䵁䅁䅁权䅁䅁䅁权呂䅁䅁权䙁䅁䅁兂䅁䅁䅁䭧氳䅑䅅䅁䉁䅁䅁兂塄㍯㥁湃硣䅑杷允䅁䅁䅕䅁䑁䅁䅷䅁䭁䅁䅁䅁䭁䙁䅍䅁䭁䅁䅕䅁䙁䅁䅁䅁䅄畖䅚允䅁䅁䅅䅁䙁䑁ね䡹⭡稳䅎䍄䉁䅁䅁兂䅁䅁䅍䅄䅁䅁䅯䅈䅁䅁䅯睕䅁䅁䅯兂䅁䅁䅕䅁䅁䅁䩄唵䉁䅁䅁允䅁䅁䅕敨剴䉵䘶歌䵁䅉䅅䅁䕁䅁䅁睁䵁䅁䅁权偂䅁䅁权佂䅁䅁兂䅁䅁䅁临氷䅑䅅䅁䉁䅁䅁兂塄㍯㥁瑃䩣䅑杷允䅁䅁䅕䅁䑁䅁䅷䅁䭁䉁䄰䅁䭁䙁䅍䅁䭁䅁䅕䅁䙁䅁䅁䅁杂敧䅚允䅁䅁䅅䅁䙁䭁捷浗㝑祮䄱䍄䉁䅁䅁䅂䅁䅁䅍䅄䅁䅁䅯睔䅁䅁䅯杔䅁䅁䅕䅁䅁䅁灂欵䉁䅁䅁允䅁䅁䅕䉵䘶ㄶ㑇䕄䵁䅉䅅䅁䙁䅁䅁睁䵁䅁䅁权慁䅁䅁权䉁䅁䅁权䙁䅁䅁兂䅁䅁䅁䵧汢䅑䅅䅁䉁䅁䅁兂䅁䅁䅁䅁杄睐杷允䅁䅁䅑䅁䑁䅁䅷䅁䭁䕁䄸䅁䭁䕁䄴䅁䙁䅁䅁䅁䅃⭡䅚允䅁䅁䅅䅁䙁䵁ㅐ䙋偹杷䅴䍄䉁䅁䅁兂䅁䅁䅍䅄䅁䅁䅯杇䅁䅁䅯睕䅁䅁䅯兂䅁䅁䅕䅁䅁佁煂欵䉁䅁䅁允䅁䅁䅕㥌欰潂噆く䵁䅉䅅䅁䙁䅁䅁睁䵁䅁䅁权敁䅁䅁权䉁䅁䅁权䙁䅁䅁兂䅁䅁䅁䡯浲䅑䅅䅁䉁䅁䅁兂䅁䅁䅁䅁兄睐杷允䅁䅁䅕䅁䑁䅁䅷䅁䭁䅁䅁䅁䭁䙁䅍䅁䭁䅁䅕䅁䙁䅁䅁䅁䅂由䅖允䅁䅁䅅䅁䙁䭁慁㥌欰橂䅎䍄䉁䅁䅁兂䅁䅁䅍䅄䅁䅁䅯䅁䅁䅁䅯睕䅁䅁䅯兂䅁䅁䅕䅁䅁䵁㕂欵䉁䅁䅁允䅁䅁䅕佖汏㡭䅑䕎䵁䅉䅅䅁䙁䅁䅁睁䵁䅁䅁权摁䅁䅁权䉁䅁䅁权䙁䅁䅁兂䅁䅁䅁䵯汔䅑䅅䅁䉁䅁䅁兂塄㍯㥁瑃呦睐杷允䅁䅁䅕䅁䑁䅁䅷䅁䭁䉁䅯䅁䭁䅁䅅䅁䭁䅁䅕䅁䙁䅁䅁䅁杄体䅚允䅁䅁䅅䅁䙁䭁睒児塲⭯⽧䍄䉁䅁䅁䅂䅁䅁䅍䅄䅁䅁䅯睔䅁䅁䅯杔䅁䅁䅕䅁䅁佁牄唵䉁䅁䅁允䅁䅁䅕敨剴䉵䘶䕅䵁䅉䅅䅁䙁䅁䅁睁䵁䅁䅁权摁䅁䅁权呂䅁䅁权䙁䅁䅁兂䅁䅁䅁䈴洳䅑䅅䅁䉁䅁䅁兂䭁㘱睎捐畯䅑杷允䅁䅁䅕䅁䑁䅁䅷䅁䭁䅁䅁䅁䭁䅁䅅䅁䭁䅁䅕䅁䙁䅁䅁䅁䅃佂䅚允䅁䅁䅅䅁䙁䱁敧敨剴乵⼴䍄䉁䅁䅁兂䅁䅁䅍䅄䅁䅁䅯先䅁䅁䅯睕䅁䅁䅯兂䅁䅁䅕䅁䅁佁楂欵䉁䅁䅁允䅁䅁䅕呦ㄸ牘䩰歌䵁䅉䅅䅁䕁䅁䅁睁䵁䅁䅁权偂䅁䅁权佂䅁䅁兂䅁䅁䅁䕯浄䅑䅅䅁䉁䅁䅁兂桄桥畓⭒佅䅑杷允䅁䅁䅕䅁䑁䅁䅷䅁䭁䅁䅁䅁䭁䙁䅍䅁䭁䅁䅕䅁䙁䅁䅁䅁䅃佥䅚允䅁䅁䅅䅁䙁䙁橔婰䕶䑁䅒䍄䉁䅁䅁兂䅁䅁䅍䅄䅁䅁䅯先䅁䅁䅯睕䅁䅁䅯兂䅁䅁䅕䅁䅁䕁⭁欵䉁䅁䅁允䅁䅁䅕牒穢搯㑓歌䵁䅉䅅䅁䙁䅁䅁睁䵁䅁䅁权敁䅁䅁权呂䅁䅁权䙁䅁䅁兂䅁䅁䅁䵧氳䅑䅅䅁䉁䅁䅁兂牁硨婢牺獣䅑杷允䅁䅁䅕䅁䑁䅁䅷䅁䭁䉁䄰䅁䭁䙁䅍䅁䭁䅁䅕䅁䙁䅁䅁䅁䅄⭣䅚允䅁䅁䅅䅁䙁偁湃歸㍳卹䄱䍄䉁䅁䅁䅂䅁䅁䅍䅄䅁䅁䅯睔䅁䅁䅯杔䅁䅁䅕䅁䅁䥁兄唵䉁䅁䅁允䅁䅁䅕牕敧敨剴歂䵁䅉䅅䅁䙁䅁䅁睁䵁䅁䅁权敁䅁䅁权呂䅁䅁权䙁䅁䅁兂䅁䅁䅁䱯汲䅑䅅䅁䉁䅁䅁兂㉃⼸唳䝥獫䅑杷允䅁䅁䅑䅁䑁䅁䅷䅁䭁䕁䄸䅁䭁䕁䄴䅁䙁䅁䅁䅁䅄敍䅚允䅁䅁䅅䅁䙁䕁桪桥畓硒䅊䍄䉁䅁䅁兂䅁䅁䅍䅄䅁䅁䅯䅁䅁䅁䅯允䅁䅁䅯兂䅁䅁䅕䅁䅁佁乂欵䉁䅁䅁允䅁䅁䅕䉵䘶ㄶ㑇樳䴸䅉䅅䅁䙁䅁䅁睁䵁䅁䅁权捁䅁䅁权呂䅁䅁权䙁䅁䅁兂䅁䅁䅁䙯洯䅑䅅䅁䉁䅁䅁兂楃扒穢刯畑䅑杷允䅁䅁䅑䅁䑁䅁䅷䅁䭁䕁䄸䅁䭁䕁䄴䅁䙁䅁䅁䅁䅁畎䅚允䅁䅁䅅䅁䙁佁剸䉵䘶砶䅂䍄䉁䅁䅁䅂䅁䅁䅍䅄䅁䅁䅯睔䅁䅁䅯杔䅁䅁䅕䅁䅁䅁䱂欵䉁䅁䅁允䅁䅁䅕噋偹癷潕啅䵁䅉䅅䅁䙁䅁䅁睁䵁䅁䅁权敁䅁䅁权呂䅁䅁权䙁䅁䅁兂䅁䅁䅁䱁汲䅑䅅䅁䉁䅁䅁兂㉃⼸唳䝥獫䅑杷允䅁䅁䅕䅁䑁䅁䅷䅁䭁䉁䄸䅁䭁䙁䅍䅁䭁䅁䅕䅁䙁䅁䅁䅁杂教䅚允䅁䅁䅅䅁䙁乁楅⼲⭬橃䅆䍄䉁䅁䅁䅂䅁䅁䅍䅄䅁䅁䅯睔䅁䅁䅯杔䅁䅁䅕䅁䅁䍁㥂欵䉁䅁䅁允䅁䅁䅕㑈牘払敧啄䵁䅉䅅䅁䙁䅁䅁睁䵁䅁䅁权䅁䅁䅁权䉁䅁䅁权䙁䅁䅁兂䅁䅁䅁乯汪䅑䅅䅁䉁䅁䅁兂桄桥畓⭒慈睐杷允䅁䅁䅕䅁䑁䅁䅷䅁䭁䉁䄸䅁䭁䅁䅅䅁䭁䅁䅕䅁䙁䅁䅁䅁杂畐䅚允䅁䅁䅅䅁䙁䭁睒児塲⭯⽁䍄䉁䅁䅁兂䅁䅁䅍䅄䅁䅁䅯杈䅁䅁䅯允䅁䅁䅯兂䅁䅁䅕䅁䅁䥁潁欵䉁䅁䅁允䅁䅁䅕⽷潕䥘䌯吱䴸䅉䅅䅁䙁䅁䅁睁䵁䅁䅁权捁䅁䅁权呂䅁䅁权䙁䅁䅁兂䅁䅁䅁䅷浄䅑䅅䅁䉁䅁䅁兂㉄䙋偹湷瑕䅑杷允䅁䅁䅕䅁䑁䅁䅷䅁䭁䅁䅁䅁䭁䙁䅍䅁䭁䅁䅕䅁䙁䅁䅁䅁权⭃䅚允䅁䅁䅅䅁䙁䉁奂扏䥔橬䅊䍄䉁䅁䅁兂䅁䅁䅍䅄䅁䅁䅯杇䅁䅁䅯允䅁䅁䅯兂䅁䅁䅕䅁䅁䍁㑂欵䉁䅁䅁允䅁䅁䅕䡰㥁瑃橥䐶䴸䅉䅅䅁䙁䅁䅁睁䵁䅁䅁权摁䅁䅁权呂䅁䅁权䙁䅁䅁兂䅁䅁䅁佧汪䅑䅅䅁䉁䅁䅁兂浃㡭村䱳瑉䅑杷允䅁䅁䅑䅁䑁䅁䅷䅁䭁䕁䄸䅁䭁䕁䄴䅁䙁䅁䅁䅁杁⭭䅖允䅁䅁䅅䅁䙁䍁捬㡪ㅌ䵋⽷䍄䉁䅁䅁兂䅁䅁䅍䅄䅁䅁䅯䅁䅁䅁䅯睕䅁䅁䅯兂䅁䅁䅕䅁䅁䭁䙄唵䉁䅁䅁允䅁䅁䅕䘫橐婰䕵歍䵁䅉䅅䅁䙁䅁䅁睁䵁䅁䅁权䅁䅁䅁权䉁䅁䅁权䙁䅁䅁兂䅁䅁䅁䵙氷䅑䅅䅁䉁䅁䅁兂㥁瑃橥䑣愳睐杷允䅁䅁䅕䅁䑁䅁䅷䅁䭁䉁䄴䅁䭁䅁䅅䅁䭁䅁䅕䅁䙁䅁䅁䅁䅃畏䅚允䅁䅁䅅䅁䙁䵁ㅐ䙋偹瑷⽕䍄䉁䅁䅁兂䅁䅁䅍䅄䅁䅁䅯杈䅁䅁䅯睕䅁䅁䅯兂䅁䅁䅕䅁䅁䕁乁欵䉁䅁䅁允䅁䅁䅕硢䑋䵷桲啋䵁䅉䅅䅁䙁䅁䅁睁䵁䅁䅁权䅁䅁䅁权呂䅁䅁权䙁䅁䅁兂䅁䅁䅁䍑洯䅑䅅䅁䉁䅁䅁兂瑁灳瘳㑰穙䅑杷允䅁䅁䅑䅁䑁䅁䅷䅁䭁䕁䄸䅁䭁䕁䄴䅁䙁䅁䅁䅁䅁估䅖允䅁䅁䅅䅁䙁偁潙䥘䌯儹䅚䍄䉁䅁䅁兂䅁䅁䅍䅄䅁䅁䅯杇䅁䅁䅯允䅁䅁䅯兂䅁䅁䅕䅁䅁䕁塂欵䉁䅁䅁允䅁䅁䅕䡰㥁瑃橥䐶䴸䅉䅅䅁䕁䅁䅁睁䵁䅁䅁权偂䅁䅁权佂䅁䅁兂䅁䅁䅁䭷汈䅑䅅䅁䉁䅁䅁兂䑄匹捨㡪噌睐杷允䅁䅁䅑䅁䑁䅁䅷䅁䭁䕁䄸䅁䭁䕁䄴䅁䙁䅁䅁䅁杁⭯䅖允䅁䅁䅅䅁䙁䅁塲㍯㥁瑃⽣䍄䉁䅁䅁䅂䅁䅁䅍䅄䅁䅁䅯睔䅁䅁䅯杔䅁䅁䅕䅁䅁䅁牁欵䉁䅁䅁允䅁䅁䅕牕敧敨剴ぅ䵁䅉䅅䅁䙁䅁䅁睁䵁䅁䅁权敁䅁䅁权䉁䅁䅁权䙁䅁䅁兂䅁䅁䅁䅁浺䅑䅅䅁䉁䅁䅁兂䑄匹捨㡪噌睐杷允䅁䅁䅕䅁䑁䅁䅷䅁䭁䉁䄴䅁䭁䅁䅅䅁䭁䅁䅕䅁䙁䅁䅁䅁䅁畋䅚允䅁䅁䅅䅁䙁䵁ㅐ䙋偹瑷⽕䍄䉁䅁䅁兂䅁䅁䅍䅄䅁䅁䅯䅁䅁䅁䅯允䅁䅁䅯兂䅁䅁䅕䅁䅁䅁祄唵䉁䅁䅁允䅁䅁䅕敨剴䉵䘶稲䴸䅉䅅䅁䙁䅁䅁睁䵁䅁䅁权慁䅁䅁权呂䅁䅁权䙁䅁䅁兂䅁䅁䅁䭙汶䅑䅅䅁䉁䅁䅁兂摁浗㝑㐳㔸䅑杷允䅁䅁䅕䅁䑁䅁䅷䅁䭁䅁䅁䅁䭁䙁䅍䅁䭁䅁䅕䅁䙁䅁䅁䅁䅄电䅖允䅁䅁䅅䅁䙁䉁䕫杖琴樰䅊䍄䉁䅁䅁䅂䅁䅁䅍䅄䅁䅁䅯睔䅁䅁䅯杔䅁䅁䅕䅁䅁䅁啂欵䉁䅁䅁允䅁䅁䅕㘱睎児塲い䵁䅉䅅䅁䙁䅁䅁睁䵁䅁䅁权捁䅁䅁权呂䅁䅁权䙁䅁䅁兂䅁䅁䅁䡷浦䅑䅅䅁䉁䅁䅁兂䱃佢㝦晱瑅䅑杷允䅁䅁䅕䅁䑁䅁䅷䅁䭁䅁䅁䅁䭁䅁䅅䅁䭁䅁䅕䅁䙁䅁䅁䅁䅄住䅚允䅁䅁䅅䅁䙁䱁敧敨剴乵⼴䍄䉁䅁䅁䅂䅁䅁䅍䅄䅁䅁䅯睔䅁䅁䅯杔䅁䅁䅕䅁䅁䕁卄唵䉁䅁䅁允䅁䅁䅕硥畓⭒㙆歂䵁䅉䅅䅁䙁䅁䅁睁䵁䅁䅁权䅁䅁䅁权呂䅁䅁权䙁䅁䅁兂䅁䅁䅁䠴浦䅑䅅䅁䉁䅁䅁兂啂㘴扗䅸ぁ䅑杷允䅁䅁䅕䅁䑁䅁䅷䅁䭁䉁䅷䅁䭁䙁䅍䅁䭁䅁䅕䅁䙁䅁䅁䅁杄敆䅚允䅁䅁䅅䅁䙁䙁㘶兓䍷祱䄱䍄䉁䅁䅁兂䅁䅁䅍䅄䅁䅁䅯睈䅁䅁䅯睕䅁䅁䅯兂䅁䅁䅕䅁䅁䅁䥁欵䉁䅁䅁允䅁䅁䅕㡧䭄啯块䕍䵁䅉䅅䅁䙁䅁䅁睁䵁䅁䅁权捁䅁䅁权呂䅁䅁权䙁䅁䅁兂䅁䅁䅁佉汲䅑䅅䅁䉁䅁䅁兂楂䙅㕧䕴畧䅑杷允䅁䅁䅑䅁䑁䅁䅷䅁䭁䕁䄸䅁䭁䕁䄴䅁䙁䅁䅁䅁杄敲䅖允䅁䅁䅅䅁䙁䭁䠵場啯瑲⽣䍄䉁䅁䅁兂䅁䅁䅍䅄䅁䅁䅯杇䅁䅁䅯睕䅁䅁䅯兂䅁䅁䅕䅁䅁䵁瑃唵䉁䅁䅁允䅁䅁䅕噈歰㥏倫問䵁䅉䅅䅁䙁䅁䅁睁䵁䅁䅁权晁䅁䅁权呂䅁䅁权䙁䅁䅁兂䅁䅁䅁䔴浈䅑䅅䅁䉁䅁䅁兂㍁啩杆吵硁䅑杷允䅁䅁䅕䅁䑁䅁䅷䅁䭁䅁䅁䅁䭁䙁䅍䅁䭁䅁䅕䅁䙁䅁䅁䅁杂伱䅖允䅁䅁䅅䅁䙁䭁慁㥌欰橂䅎䍄䉁䅁䅁兂䅁䅁䅍䅄䅁䅁䅯杇䅁䅁䅯睕䅁䅁䅯兂䅁䅁䅕䅁䅁䭁啃唵䉁䅁䅁允䅁䅁䅕瑃橥䑣焳䕏䵁䅉䅅䅁䙁䅁䅁睁䵁䅁䅁权捁䅁䅁权呂䅁䅁权䙁䅁䅁兂䅁䅁䅁偯汐䅑䅅䅁䉁䅁䅁兂㙃兓䍷㡋瑣䅑杷允䅁䅁䅑䅁䑁䅁䅷䅁䭁䕁䄸䅁䭁䕁䄴䅁䙁䅁䅁䅁权敆䅚允䅁䅁䅅䅁䙁䡁啳歲桦桥䅎䍄䉁䅁䅁兂䅁䅁䅍䅄䅁䅁䅯杈䅁䅁䅯睕䅁䅁䅯兂䅁䅁䅕䅁䅁䕁䑁欵䉁䅁䅁允䅁䅁䅕䅁䅁䅁䅁歋䵁䅉䅅䅁䕁䅁䅁睁䵁䅁䅁权偂䅁䅁权佂䅁䅁兂䅁䅁䅁䍉浪䅑䅅䅁䉁䅁䅁兂䙃ㄶ㑇潈剕䅑杷允䅁䅁䅑䅁䑁䅁䅷䅁䭁䕁䄸䅁䭁䕁䄴䅁䙁䅁䅁䅁䅃畓䅚允䅁䅁䅅䅁䙁䝁浚浚浚桚䅆䍄䉁䅁䅁兂䅁䅁䅍䅄䅁䅁䅯杇䅁䅁䅯允䅁䅁䅯兂䅁䅁䅕䅁䅁䍁煃唵䉁䅁䅁允䅁䅁䅕䅁䅁䅁䅁䐴䴸䅉䅅䅁䙁䅁䅁睁䵁䅁䅁权摁䅁䅁权呂䅁䅁权䙁䅁䅁兂䅁䅁䅁䑁洷䅑䅅䅁䉁䅁䅁兂䝂癴㥐䰱畧䅑杷允䅁䅁䅕䅁䑁䅁䅷䅁䭁䅁䅁䅁䭁䙁䅍䅁䭁䅁䅕䅁䙁䅁䅁䅁权故䅚允䅁䅁䅅䅁䙁䉁奂扏䥔橬䅊䍄䉁䅁䅁兂䅁䅁䅍䅄䅁䅁䅯䅁䅁䅁䅯睕䅁䅁䅯兂䅁䅁䅕䅁䅁䵁捂欵䉁䅁䅁允䅁䅁䅕癱午坔兌き䵁䅉䅅䅁䕁䅁䅁睁䵁䅁䅁权偂䅁䅁权佂䅁䅁兂䅁䅁䅁䬴汄䅑䅅䅁䉁䅁䅁兂浂浚浚浚坢睐杷允䅁䅁䅕䅁䑁䅁䅷䅁䭁䅁䅁䅁䭁䙁䅍䅁䭁䅁䅕䅁䙁䅁䅁䅁杂敳䅖允䅁䅁䅅䅁䙁䱁䩰䅄牉穊䅊䍄䉁䅁䅁兂䅁䅁䅍䅄䅁䅁䅯睈䅁䅁䅯允䅁䅁䅯兂䅁䅁䅕䅁䅁佁䍁欵䉁䅁䅁允䅁䅁䅕䅁䅁䅁䅁䐴䴸䅉䅅䅁䙁䅁䅁睁䵁䅁䅁权䅁䅁䅁权呂䅁䅁权䙁䅁䅁兂䅁䅁䅁䠴浄䅑䅅䅁䉁䅁䅁兂啂㘴扗䅸ぁ䅑杷允䅁䅁䅑䅁䑁䅁䅷䅁䭁䕁䄸䅁䭁䕁䄴䅁䙁䅁䅁䅁䅃敉䅚允䅁䅁䅅䅁䙁䥁䌯匹捨硪䅂䍄䉁䅁䅁兂䅁䅁䅍䅄䅁䅁䅯䅁䅁䅁䅯允䅁䅁䅯兂䅁䅁䅕䅁䅁䝁䡄唵䉁䅁䅁允䅁䅁䅕児塲㍯㥁樲䴸䅉䅅䅁䙁䅁䅁睁䵁䅁䅁权摁䅁䅁权呂䅁䅁权䙁䅁䅁兂䅁䅁䅁䱁汮䅑䅅䅁䉁䅁䅁兂䭁㘱睎捐瑯䅑杷允䅁䅁䅑䅁䑁䅁䅷䅁䭁䕁䄸䅁䭁䕁䄴䅁䙁䅁䅁䅁杄⭮䅖允䅁䅁䅅䅁䙁䝁浚浚浚瑚⽙䍄䉁䅁䅁䅂䅁䅁䅍䅄䅁䅁䅯睔䅁䅁䅯杔䅁䅁䅕䅁䅁䕁潃唵䉁䅁䅁允䅁䅁䅕㑈牘払敧吱䴸䅉䅅䅁䙁䅁䅁睁䵁䅁䅁权捁䅁䅁权呂䅁䅁权䙁䅁䅁兂䅁䅁䅁临氳䅑䅅䅁䉁䅁䅁兂楂䙅㕧䕴畧䅑杷允䅁䅁䅕䅁䑁䅁䅷䅁䭁䉁䄴䅁䭁䙁䅍䅁䭁䅁䅕䅁䙁䅁䅁䅁䅃敤䅚允䅁䅁䅅䅁䙁䍁捬㡪ㅌ䍡䅆䍄䉁䅁䅁兂䅁䅁䅍䅄䅁䅁䅯䅈䅁䅁䅯睕䅁䅁䅯兂䅁䅁䅕䅁䅁䥁㕁欵䉁䅁䅁允䅁䅁䅕㥆佮ㄹ橏歌䵁䅉䅅䅁䕁䅁䅁睁䵁䅁䅁权偂䅁䅁权佂䅁䅁兂䅁䅁䅁䡁洳䅑䅅䅁䉁䅁䅁兂晁敨剴䉵临䅑杷允䅁䅁䅕䅁䑁䅁䅷䅁䭁䅁䅁䅁䭁䙁䅍䅁䭁䅁䅕䅁䙁䅁䅁䅁䅁⬯䅖允䅁䅁䅅䅁䙁䭁硲欰椱䑣䅊䍄䉁䅁䅁兂䅁䅁䅍䅄䅁䅁䅯睈䅁䅁䅯睕䅁䅁䅯兂䅁䅁䅕䅁䅁䕁㍂欵䉁䅁䅁允䅁䅁䅕牡へ硫歧啍䵁䅉䅅䅁䕁䅁䅁睁䵁䅁䅁权偂䅁䅁权佂䅁䅁兂䅁䅁䅁䕧浐䅑䅅䅁䉁䅁䅁兂㝂䭆䠵場兯䅑杷允䅁䅁䅕䅁䑁䅁䅷䅁䭁䅁䅁䅁䭁䙁䅍䅁䭁䅁䅕䅁䙁䅁䅁䅁权畧䅚允䅁䅁䅅䅁䙁偁唷佥浫吸䅎䍄䉁䅁䅁䅂䅁䅁䅍䅄䅁䅁䅯睔䅁䅁䅯杔䅁䅁䅕䅁䅁䕁㕃唵䉁䅁䅁允䅁䅁䅕椹捨㡪ㅌ䐶䴸䅉䅅䅁䙁䅁䅁睁䵁䅁䅁权䅁䅁䅁权呂䅁䅁权䙁䅁䅁兂䅁䅁䅁䙁浐䅑䅅䅁䉁䅁䅁兂㕁䵴㉨瑶稸䅑杷允䅁䅁䅕䅁䑁䅁䅷䅁䭁䉁䄴䅁䭁䙁䅍䅁䭁䅁䅕䅁䙁䅁䅁䅁䅄畃䅚允䅁䅁䅅䅁䙁䝁匸㡧䭄匴䅬䍄䉁䅁䅁䅂䅁䅁䅍䅄䅁䅁䅯睔䅁䅁䅯杔䅁䅁䅕䅁䅁䥁敄唵䉁䅁䅁允䅁䅁䅕㑈牘払敧啃䵁䅉䅅䅁䙁䅁䅁睁䵁䅁䅁权䅁䅁䅁权䉁䅁䅁权䙁䅁䅁兂䅁䅁䅁义汦䅑䅅䅁䉁䅁䅁兂桄桥畓⭒慈睐杷允䅁䅁䅕䅁䑁䅁䅷䅁䭁䉁䅯䅁䭁䅁䅅䅁䭁䅁䅕䅁䙁䅁䅁䅁杄敉䅚允䅁䅁䅅䅁䙁䭁睒児塲⭯⽧䍄䉁䅁䅁兂䅁䅁䅍䅄䅁䅁䅯杇䅁䅁䅯允䅁䅁䅯兂䅁䅁䅕䅁䅁䅁楂欵䉁䅁䅁允䅁䅁䅕䡰㥁瑃橥䐶䴸䅉䅅䅁䙁䅁䅁睁䵁䅁䅁权䅁䅁䅁权呂䅁䅁权䙁䅁䅁兂䅁䅁䅁临汢䅑䅅䅁䉁䅁䅁兂权楇搯䅊穙䅑杷允䅁䅁䅕䅁䑁䅁䅷䅁䭁䉁䄴䅁䭁䙁䅍䅁䭁䅁䅕䅁䙁䅁䅁䅁䅄敵䅖允䅁䅁䅅䅁䙁䱁穢搯㑒卡䅸䍄䉁䅁䅁兂䅁䅁䅍䅄䅁䅁䅯䅈䅁䅁䅯睕䅁䅁䅯兂䅁䅁䅕䅁䅁䕁睄唵䉁䅁䅁允䅁䅁䅕歵䵫楁䡶啌䵁䅉䅅䅁䙁䅁䅁睁䵁䅁䅁权敁䅁䅁权呂䅁䅁权䙁䅁䅁兂䅁䅁䅁䑁浢䅑䅅䅁䉁䅁䅁兂䥂場啯歲浣䅑杷允䅁䅁䅑䅁䑁䅁䅷䅁䭁䕁䄸䅁䭁䕁䄴䅁䙁䅁䅁䅁杂⭭䅖允䅁䅁䅅䅁䙁䱁敧敨剴䵵⼴䍄䉁䅁䅁䅂䅁䅁䅍䅄䅁䅁䅯睔䅁䅁䅯杔䅁䅁䅕䅁䅁䵁楂欵䉁䅁䅁允䅁䅁䅕場啯歲桦歄䵁䅉䅅䅁䙁䅁䅁睁䵁䅁䅁权摁䅁䅁权䉁䅁䅁权䙁䅁䅁兂䅁䅁䅁䡁浘䅑䅅䅁䉁䅁䅁兂畃⭒㙆䭆堷睐杷允䅁䅁䅕䅁䑁䅁䅷䅁䭁䅁䅁䅁䭁䙁䅍䅁䭁䅁䅕䅁䙁䅁䅁䅁权當䅖允䅁䅁䅅䅁䙁偁周㘴扗䑨䅊䍄䉁䅁䅁䅂䅁䅁䅍䅄䅁䅁䅯睔䅁䅁䅯杔䅁䅁䅕䅁䅁䝁獂欵䉁䅁䅁允䅁䅁䅕㡪ㅌ䙋偹䕄䵁䅉䅅䅁䙁䅁䅁睁䵁䅁䅁权捁䅁䅁权䉁䅁䅁权䙁䅁䅁兂䅁䅁䅁䕁浪䅑䅅䅁䉁䅁䅁兂㉄䙋偹癷奘睐杷允䅁䅁䅕䅁䑁䅁䅷䅁䭁䉁䅯䅁䭁䙁䅍䅁䭁䅁䅕䅁䙁䅁䅁䅁䅁畒䅚允䅁䅁䅅䅁䙁䕁㍷啩杆呒䅴䍄䉁䅁䅁䅂䅁䅁䅍䅄䅁䅁䅯睔䅁䅁䅯杔䅁䅁䅕䅁䅁佁䉂欵䉁䅁䅁允䅁䅁䅕場啯歲桦歄䵁䅉䅅䅁䙁䅁䅁睁䵁䅁䅁权䅁䅁䅁权呂䅁䅁权䙁䅁䅁兂䅁䅁䅁乯汪䅑䅅䅁䉁䅁䅁兂权楇搯䅊穙䅑杷允䅁䅁䅑䅁䑁䅁䅷䅁䭁䕁䄸䅁䭁䕁䄴䅁䙁䅁䅁䅁杄敏䅚允䅁䅁䅅䅁䙁䑁積積積睍䄹䍄䉁䅁䅁兂䅁䅁䅍䅄䅁䅁䅯杇䅁䅁䅯允䅁䅁䅯兂䅁䅁䅕䅁䅁䅁灄唵䉁䅁䅁允䅁䅁䅕椹捨㡪ㅌ䐴䴸䅉䅅䅁䙁䅁䅁睁䵁䅁䅁权慁䅁䅁权呂䅁䅁权䙁䅁䅁兂䅁䅁䅁佉氯䅑䅅䅁䉁䅁䅁兂䑄匹捨㡪㕉䅑杷允䅁䅁䅕䅁䑁䅁䅷䅁䭁䉁䅷䅁䭁䅁䅅䅁䭁䅁䅕䅁䙁䅁䅁䅁权⭒䅚允䅁䅁䅅䅁䙁偁潙䥘䌯搹⽧䍄䉁䅁䅁兂䅁䅁䅍䅄䅁䅁䅯䅁䅁䅁䅯睕䅁䅁䅯兂䅁䅁䅕䅁䅁䅁䥁欵䉁䅁䅁允䅁䅁䅕癱午坔睊歍䵁䅉䅅䅁䕁䅁䅁睁䵁䅁䅁权偂䅁䅁权佂䅁䅁兂䅁䅁䅁䠴浺䅑䅅䅁䉁䅁䅁兂晁敨剴䉵临䅑杷允䅁䅁䅕䅁䑁䅁䅷䅁䭁䉁䅷䅁䭁䙁䅍䅁䭁䅁䅕䅁䙁䅁䅁䅁䅁散䅚允䅁䅁䅅䅁䙁䡁潎敫㠱礯䄱䍄䉁䅁䅁䅂䅁䅁䅍䅄䅁䅁䅯睔䅁䅁䅯杔䅁䅁䅕䅁䅁䥁䙁欵䉁䅁䅁允䅁䅁䅕体㙆䭆䠵啅䵁䅉䅅䅁䙁䅁䅁睁䵁䅁䅁权捁䅁䅁权呂䅁䅁权䙁䅁䅁兂䅁䅁䅁䵷氷䅑䅅䅁䉁䅁䅁兂䙃ㄶ㑇潈畕䅑杷允䅁䅁䅕䅁䑁䅁䅷䅁䭁䉁䄰䅁䭁䙁䅍䅁䭁䅁䅕䅁䙁䅁䅁䅁䅃何䅚允䅁䅁䅅䅁䙁䡁呗䅇坒楪䄵䍄䉁䅁䅁兂䅁䅁䅍䅄䅁䅁䅯睈䅁䅁䅯睕䅁䅁䅯兂䅁䅁䅕䅁䅁䅁坄唵䉁䅁䅁允䅁䅁䅕祇搯䅊桢䕍䵁䅉䅅䅁䙁䅁䅁睁䵁䅁䅁权捁䅁䅁权䉁䅁䅁权䙁䅁䅁兂䅁䅁䅁䱯汔䅑䅅䅁䉁䅁䅁兂偃癷潕䥘匯睐杷允䅁䅁䅑䅁䑁䅁䅷䅁䭁䕁䄸䅁䭁䕁䄴䅁䙁䅁䅁䅁权畔䅚允䅁䅁䅅䅁䙁䅁䅁䅁䅁䉁䅆䍄䉁䅁䅁兂䅁䅁䅍䅄䅁䅁䅯先䅁䅁䅯睕䅁䅁䅯兂䅁䅁䅕䅁䅁䥁乄唵䉁䅁䅁允䅁䅁䅕噋偹癷潕歌䵁䅉䅅䅁䙁䅁䅁睁䵁䅁䅁权摁䅁䅁权䉁䅁䅁权䙁䅁䅁兂䅁䅁䅁䍧浶䅑䅅䅁䉁䅁䅁兂浂浚浚浚坢睐杷允䅁䅁䅑䅁䑁䅁䅷䅁䭁䕁䄸䅁䭁䕁䄴䅁䙁䅁䅁䅁杄散䅚允䅁䅁䅅䅁䙁䭁睒児塲睯䅸䍄䉁䅁䅁兂䅁䅁䅍䅄䅁䅁䅯先䅁䅁䅯睕䅁䅁䅯兂䅁䅁䅕䅁䅁䵁䝂欵䉁䅁䅁允䅁䅁䅕婤奍䙂佡歌䵁䅉䅅䅁䕁䅁䅁睁䵁䅁䅁权偂䅁䅁权佂䅁䅁兂䅁䅁䅁䠴浮䅑䅅䅁䉁䅁䅁兂㑃潈牘払䵧䅑杷允䅁䅁䅕䅁䑁䅁䅷䅁䭁䅁䅁䅁䭁䅁䅅䅁䭁䅁䅕䅁䙁䅁䅁䅁䅄⭲䅖允䅁䅁䅅䅁䙁䩁婱婭婭摭⽫䍄䉁䅁䅁兂䅁䅁䅍䅄䅁䅁䅯䅈䅁䅁䅯睕䅁䅁䅯兂䅁䅁䅕䅁䅁䥁ぁ欵䉁䅁䅁允䅁䅁䅕䑗ね䡹⭙歌䵁䅉䅅䅁䙁䅁䅁睁䵁䅁䅁权䅁䅁䅁权䉁䅁䅁权䙁䅁䅁兂䅁䅁䅁䵧汮䅑䅅䅁䉁䅁䅁兂㥁瑃橥䑣愳睐杷允䅁䅁䅕䅁䑁䅁䅷䅁䭁䉁䄸䅁䭁䅁䅅䅁䭁䅁䅕䅁䙁䅁䅁䅁杁敄䅚允䅁䅁䅅䅁䙁䭁睒児塲⭯⽁䍄䉁䅁䅁䅂䅁䅁䅍䅄䅁䅁䅯睔䅁䅁䅯杔䅁䅁䅕䅁䅁䭁楂欵䉁䅁䅁允䅁䅁䅕捺䵺䵺䵺歄䵁䅉䅅䅁䙁䅁䅁睁䵁䅁䅁权摁䅁䅁权呂䅁䅁权䙁䅁䅁兂䅁䅁䅁䙉浐䅑䅅䅁䉁䅁䅁兂䑄匹捨㑪畉䅑杷允䅁䅁䅕䅁䑁䅁䅷䅁䭁䉁䄸䅁䭁䙁䅍䅁䭁䅁䅕䅁䙁䅁䅁䅁䅁敦䅚允䅁䅁䅅䅁䙁䝁㡱䩤奍䑊䅆䍄䉁䅁䅁兂䅁䅁䅍䅄䅁䅁䅯䅁䅁䅁䅯睕䅁䅁䅯兂䅁䅁䅕䅁䅁䝁奂欵䉁䅁䅁允䅁䅁䅕扏䥔牤昷き䵁䅉䅅䅁䙁䅁䅁睁䵁䅁䅁权捁䅁䅁权呂䅁䅁权䙁䅁䅁兂䅁䅁䅁余汲䅑䅅䅁䉁䅁䅁兂楂䙅㕧䕴畧䅑杷允䅁䅁䅑䅁䑁䅁䅷䅁䭁䕁䄸䅁䭁䕁䄴䅁䙁䅁䅁䅁杂佦䅚允䅁䅁䅅䅁䙁䅁塲㍯㥁权䄱䍄䉁䅁䅁兂䅁䅁䅍䅄䅁䅁䅯䅁䅁䅁䅯允䅁䅁䅯兂䅁䅁䅕䅁䅁䕁敃唵䉁䅁䅁允䅁䅁䅕灭婭婭婭吲䴸䅉䅅䅁䕁䅁䅁睁䵁䅁䅁权偂䅁䅁权佂䅁䅁兂䅁䅁䅁䙯浈䅑䅅䅁䉁䅁䅁兂䑄匹捨㡪光䅑杷允䅁䅁䅕䅁䑁䅁䅷䅁䭁䉁䅷䅁䭁䙁䅍䅁䭁䅁䅕䅁䙁䅁䅁䅁杂⬰䅖允䅁䅁䅅䅁䙁䕁椵䙅㕧䍴䄵䍄䉁䅁䅁䅂䅁䅁䅍䅄䅁䅁䅯睔䅁䅁䅯杔䅁䅁䅕䅁䅁佁摂欵䉁䅁䅁允䅁䅁䅕椹捨㡪ㅌ歄䵁䅉䅅䅁䕁䅁䅁睁䵁䅁䅁权偂䅁䅁权佂䅁䅁兂䅁䅁䅁䡑浄䅑䅅䅁䉁䅁䅁兂獄払敧敨䱳䅑杷允䅁䅁䅕䅁䑁䅁䅷䅁䭁䉁䄴䅁䭁䙁䅍䅁䭁䅁䅕䅁䙁䅁䅁䅁杁甲䅖允䅁䅁䅅䅁䙁䍁䝕婧䑖祩䅸䍄䉁䅁䅁兂䅁䅁䅍䅄䅁䅁䅯䅁䅁䅁䅯睕䅁䅁䅯兂䅁䅁䅕䅁䅁䕁時欵䉁䅁䅁允䅁䅁䅕癱午坔兌き䵁䅉䅅䅁䕁䅁䅁睁䵁䅁䅁权偂䅁䅁权佂䅁䅁兂䅁䅁䅁䙙浢䅑䅅䅁䉁䅁䅁兂晁敨剴䉵倴䅑杷允䅁䅁䅑䅁䑁䅁䅷䅁䭁䕁䄸䅁䭁䕁䄴䅁䙁䅁䅁䅁䅂佦䅚允䅁䅁䅅䅁䙁䕁桪桥畓睒䄱䍄䉁䅁䅁䅂䅁䅁䅍䅄䅁䅁䅯睔䅁䅁䅯杔䅁䅁䅕䅁䅁䅁穁欵䉁䅁䅁允䅁䅁䅕捺䵺䵺䵺啅䵁䅉䅅䅁䙁䅁䅁睁䵁䅁䅁权䅁䅁䅁权呂䅁䅁权䙁䅁䅁兂䅁䅁䅁䘴浶䅑䅅䅁䉁䅁䅁兂煃搸乊瑙穁䅑杷允䅁䅁䅕䅁䑁䅁䅷䅁䭁䉁䅯䅁䭁䙁䅍䅁䭁䅁䅕䅁䙁䅁䅁䅁杁佔䅚允䅁䅁䅅䅁䙁䕁㍷啩杆呒䅴䍄䉁䅁䅁兂䅁䅁䅍䅄䅁䅁䅯䅁䅁䅁䅯睕䅁䅁䅯兂䅁䅁䅕䅁䅁䕁䥄唵䉁䅁䅁允䅁䅁䅕敢㝦晱祈歍䵁䅉䅅䅁䕁䅁䅁睁䵁䅁䅁权偂䅁䅁权佂䅁䅁兂䅁䅁䅁伴汮䅑䅅䅁䉁䅁䅁兂㉄䙋偹癷兕䅑杷允䅁䅁䅕䅁䑁䅁䅷䅁䭁䉁䅯䅁䭁䙁䅍䅁䭁䅁䅕䅁䙁䅁䅁䅁䅄⭡䅚允䅁䅁䅅䅁䙁䍁搯䅊䉡呖䅴䍄䉁䅁䅁䅂䅁䅁䅍䅄䅁䅁䅯睔䅁䅁䅯杔䅁䅁䅕䅁䅁䭁㥄唵䉁䅁䅁允䅁䅁䅕㑈牘払敧い䵁䅉䅅䅁䙁䅁䅁睁䵁䅁䅁权捁䅁䅁权䉁䅁䅁权䙁䅁䅁兂䅁䅁䅁䱁汶䅑䅅䅁䉁䅁䅁兂偃癷潕䥘匯睐杷允䅁䅁䅕䅁䑁䅁䅷䅁䭁䉁䅷䅁䭁䙁䅍䅁䭁䅁䅕䅁䙁䅁䅁䅁䅁敂䅚允䅁䅁䅅䅁䙁偁潙䥘䌯卤䄱䍄䉁䅁䅁䅂䅁䅁䅍䅄䅁䅁䅯睔䅁䅁䅯杔䅁䅁䅕䅁䅁䭁㙂欵䉁䅁䅁允䅁䅁䅕椹捨㡪ㅌ䕄䵁䅉䅅䅁䙁䅁䅁睁䵁䅁䅁权摁䅁䅁权呂䅁䅁权䙁䅁䅁兂䅁䅁䅁䵯汶䅑䅅䅁䉁䅁䅁兂灁䥘䌯匹畧䅑杷允䅁䅁䅕䅁䑁䅁䅷䅁䭁䉁䄰䅁䭁䙁䅍䅁䭁䅁䅕䅁䙁䅁䅁䅁杄敋䅚允䅁䅁䅅䅁䙁䝁浚浚浚椵䄵䍄䉁䅁䅁䅂䅁䅁䅍䅄䅁䅁䅯睔䅁䅁䅯杔䅁䅁䅕䅁䅁䕁坄唵䉁䅁䅁允䅁䅁䅕歲桦桥畓啃䵁䅉䅅䅁䙁䅁䅁睁䵁䅁䅁权䅁䅁䅁权䉁䅁䅁权䙁䅁䅁兂䅁䅁䅁䝑浌䅑䅅䅁䉁䅁䅁兂㑃潈牘払敪睐杷允䅁䅁䅑䅁䑁䅁䅷䅁䭁䕁䄸䅁䭁䕁䄴䅁䙁䅁䅁䅁权畖䅚允䅁䅁䅅䅁䙁䉁䘫ㄶ㑇杈䄹䍄䉁䅁䅁兂䅁䅁䅍䅄䅁䅁䅯先䅁䅁䅯睕䅁䅁䅯兂䅁䅁䅕䅁䅁䥁䅂欵䉁䅁䅁允䅁䅁䅕牒穢搯㑓歌䵁䅉䅅䅁䙁䅁䅁睁䵁䅁䅁权敁䅁䅁权䉁䅁䅁权䙁䅁䅁兂䅁䅁䅁义汘䅑䅅䅁䉁䅁䅁兂穁積積積呐睐杷允䅁䅁䅕䅁䑁䅁䅷䅁䭁䉁䅯䅁䭁䙁䅍䅁䭁䅁䅕䅁䙁䅁䅁䅁䅁攰䅖允䅁䅁䅅䅁䙁䭁慁㥌欰橒䅰䍄䉁䅁䅁兂䅁䅁䅍䅄䅁䅁䅯䅁䅁䅁䅯睕䅁䅁䅯兂䅁䅁䅕䅁䅁䵁祁欵䉁䅁䅁允䅁䅁䅕扌摋㘷䝥き䵁䅉䅅䅁䙁䅁䅁睁䵁䅁䅁权䅁䅁䅁权呂䅁䅁权䙁䅁䅁兂䅁䅁䅁䑯浘䅑䅅䅁䉁䅁䅁兂瑁灳瘳㑰穙䅑杷允䅁䅁䅕䅁䑁䅁䅷䅁䭁䅁䅁䅁䭁䙁䅍䅁䭁䅁䅕䅁䙁䅁䅁䅁权佉䅚允䅁䅁䅅䅁䙁䝁匸㡧䭄呁䅎䍄䉁䅁䅁䅂䅁䅁䅍䅄䅁䅁䅯睔䅁䅁䅯杔䅁䅁䅕䅁䅁䍁㑂欵䉁䅁䅁允䅁䅁䅕牕敧敨剴䕄䵁䅉䅅䅁䙁䅁䅁睁䵁䅁䅁权捁䅁䅁权䉁䅁䅁权䙁䅁䅁兂䅁䅁䅁䱧汔䅑䅅䅁䉁䅁䅁兂偃癷潕䥘匯睐杷允䅁䅁䅕䅁䑁䅁䅷䅁䭁䉁䄴䅁䭁䙁䅍䅁䭁䅁䅕䅁䙁䅁䅁䅁杄畈䅚允䅁䅁䅅䅁䙁䉁䕫杖琴楣䅬䍄䉁䅁䅁兂䅁䅁䅍䅄䅁䅁䅯睈䅁䅁䅯允䅁䅁䅯兂䅁䅁䅕䅁䅁䵁䍁欵䉁䅁䅁允䅁䅁䅕䅁䅁䅁䅁䐴䴸䅉䅅䅁䙁䅁䅁睁䵁䅁䅁权晁䅁䅁权呂䅁䅁权䙁䅁䅁兂䅁䅁䅁偁汲䅑䅅䅁䉁䅁䅁兂偄ㄹ橐塰睳䅑杷允䅁䅁䅕䅁䑁䅁䅷䅁䭁䉁䅷䅁䭁䙁䅍䅁䭁䅁䅕䅁䙁䅁䅁䅁䅄伯䅖允䅁䅁䅅䅁䙁䙁㘶兓䍷祡䄱䍄䉁䅁䅁兂䅁䅁䅍䅄䅁䅁䅯䅁䅁䅁䅯睕䅁䅁䅯兂䅁䅁䅕䅁䅁䍁湁欵䉁䅁䅁允䅁䅁䅕搵楁⼲⭫き䵁䅉䅅䅁䕁䅁䅁睁䵁䅁䅁权偂䅁䅁权佂䅁䅁兂䅁䅁䅁余汌䅑䅅䅁䉁䅁䅁兂乄䵺䵺䵺佷䅑杷允䅁䅁䅕䅁䑁䅁䅷䅁䭁䉁䅯䅁䭁䅁䅅䅁䭁䅁䅕䅁䙁䅁䅁䅁权畔䅚允䅁䅁䅅䅁䙁䭁睒児塲⭯⽧䍄䉁䅁䅁兂䅁䅁䅍䅄䅁䅁䅯睈䅁䅁䅯睕䅁䅁䅯兂䅁䅁䅕䅁䅁䕁㑁欵䉁䅁䅁允䅁䅁䅕㑎䉬余睕啍䵁䅉䅅䅁䕁䅁䅁睁䵁䅁䅁权偂䅁䅁权佂䅁䅁兂䅁䅁䅁䙯洳䅑䅅䅁䉁䅁䅁兂慃婭婭婭偫䅑杷允䅁䅁䅕䅁䑁䅁䅷䅁䭁䉁䅷䅁䭁䙁䅍䅁䭁䅁䅕䅁䙁䅁䅁䅁䅄敆䅚允䅁䅁䅅䅁䙁䙁㘶兓䍷祱䄱䍄䉁䅁䅁兂䅁䅁䅍䅄䅁䅁䅯睈䅁䅁䅯允䅁䅁䅯兂䅁䅁䅕䅁䅁䝁㑃唵䉁䅁䅁允䅁䅁䅕敨剴䉵䘶稲䴸䅉䅅䅁䙁䅁䅁睁䵁䅁䅁权䅁䅁䅁权呂䅁䅁权䙁䅁䅁兂䅁䅁䅁䱁汔䅑䅅䅁䉁䅁䅁兂㙃兓䍷祋祣䅑杷允䅁䅁䅕䅁䑁䅁䅷䅁䭁䉁䅯䅁䭁䅁䅅䅁䭁䅁䅕䅁䙁䅁䅁䅁杄異䅖允䅁䅁䅅䅁䙁䅁䅁䅁䅁佁⽁䍄䉁䅁䅁䅂䅁䅁䅍䅄䅁䅁䅯睔䅁䅁䅯杔䅁䅁䅕䅁䅁䍁⽁欵䉁䅁䅁允䅁䅁䅕牕敧敨剴䕄䵁䅉䅅䅁䕁䅁䅁睁䵁䅁䅁权偂䅁䅁权佂䅁䅁兂䅁䅁䅁䝁浲䅑䅅䅁䉁䅁䅁兂浂浚浚浚䵙䅑杷允䅁䅁䅑䅁䑁䅁䅷䅁䭁䕁䄸䅁䭁䕁䄴䅁䙁䅁䅁䅁䅃略䅚允䅁䅁䅅䅁䙁䡁啳歲桦来䅸䍄䉁䅁䅁兂䅁䅁䅍䅄䅁䅁䅯杇䅁䅁䅯允䅁䅁䅯兂䅁䅁䅕䅁䅁䕁呁欵䉁䅁䅁允䅁䅁䅕浚浚浚浚樵䴸䅉䅅䅁䙁䅁䅁睁䵁䅁䅁权慁䅁䅁权䉁䅁䅁权䙁䅁䅁兂䅁䅁䅁䄴浄䅑䅅䅁䉁䅁䅁兂浂浚浚浚浢睐杷允䅁䅁䅕䅁䑁䅁䅷䅁䭁䉁䄰䅁䭁䅁䅅䅁䭁䅁䅕䅁䙁䅁䅁䅁䅁佊䅚允䅁䅁䅅䅁䙁䝁浚浚浚瑚⽙䍄䉁䅁䅁䅂䅁䅁䅍䅄䅁䅁䅯睔䅁䅁䅯杔䅁䅁䅕䅁䅁䅁䅄唵䉁䅁䅁允䅁䅁䅕䥘䌯匹捨稷䴸䅉䅅䅁䙁䅁䅁睁䵁䅁䅁权䅁䅁䅁权呂䅁䅁权䙁䅁䅁兂䅁䅁䅁伴氳䅑䅅䅁䉁䅁䅁兂穁積積㕍祍䅑杷允䅁䅁䅑䅁䑁䅁䅷䅁䭁䕁䄸䅁䭁䕁䄴䅁䙁䅁䅁䅁杁⭮䅖允䅁䅁䅅䅁䙁乁橥䑣䬰㤱⽍䍄䉁䅁䅁兂䅁䅁䅍䅄䅁䅁䅯䅁䅁䅁䅯允䅁䅁䅯兂䅁䅁䅕䅁䅁佁灂欵䉁䅁䅁允䅁䅁䅕䉵䘶ㄶ㑇樳䴸䅉䅅䅁䙁䅁䅁睁䵁䅁䅁权摁䅁䅁权䉁䅁䅁权䙁䅁䅁兂䅁䅁䅁䉧浢䅑䅅䅁䉁䅁䅁兂晁敨剴䉵嘷睐杷允䅁䅁䅕䅁䑁䅁䅷䅁䭁䅁䅁䅁䭁䅁䅅䅁䭁䅁䅕䅁䙁䅁䅁䅁䅃敯䅖允䅁䅁䅅䅁䙁䩁婱婭婭摭⽫䍄䉁䅁䅁䅂䅁䅁䅍䅄䅁䅁䅯睔䅁䅁䅯杔䅁䅁䅕䅁䅁䵁㉃唵䉁䅁䅁允䅁䅁䅕䥘䌯匹捨稳䴸䅉䅅䅁䙁䅁䅁睁䵁䅁䅁权捁䅁䅁权䉁䅁䅁权䙁䅁䅁兂䅁䅁䅁䍙浺䅑䅅䅁䉁䅁䅁兂畃⭒㙆䭆堷睐杷允䅁䅁䅕䅁䑁䅁䅷䅁䭁䉁䅷䅁䭁䙁䅍䅁䭁䅁䅕䅁䙁䅁䅁䅁䅁⭋䅚允䅁䅁䅅䅁䙁䥁䌯匹捨祄䄵䍄䉁䅁䅁兂䅁䅁䅍䅄䅁䅁䅯睈䅁䅁䅯允䅁䅁䅯兂䅁䅁䅕䅁䅁䍁㉄唵䉁䅁䅁允䅁䅁䅕体㙆䭆䠵吴䴸䅉䅅䅁䙁䅁䅁睁䵁䅁䅁权捁䅁䅁权呂䅁䅁权䙁䅁䅁兂䅁䅁䅁䙷浲䅑䅅䅁䉁䅁䅁兂楃扒穢刯畑䅑杷允䅁䅁䅑䅁䑁䅁䅷䅁䭁䕁䄸䅁䭁䕁䄴䅁䙁䅁䅁䅁杁⭕䅚允䅁䅁䅅䅁䙁䅁塲㍯㥁桃䅂䍄䉁䅁䅁兂䅁䅁䅍䅄䅁䅁䅯睈䅁䅁䅯睕䅁䅁䅯兂䅁䅁䅕䅁䅁䍁㍄唵䉁䅁䅁允䅁䅁䅕⽺呤㘴㝖䕍䵁䅉䅅䅁䕁䅁䅁睁䵁䅁䅁权偂䅁䅁权佂䅁䅁兂䅁䅁䅁佯汶䅑䅅䅁䉁䅁䅁兂桄桥畓⭒充䅑杷允䅁䅁䅕䅁䑁䅁䅷䅁䭁䉁䄸䅁䭁䙁䅍䅁䭁䅁䅕䅁䙁䅁䅁䅁䅂佐䅚允䅁䅁䅅䅁䙁䑁䩥坑汄䑍䅆䍄䉁䅁䅁兂䅁䅁䅍䅄䅁䅁䅯䅁䅁䅁䅯睕䅁䅁䅯兂䅁䅁䅕䅁䅁佁畂欵䉁䅁䅁允䅁䅁䅕佖汏㡭杔き䵁䅉䅅䅁䕁䅁䅁睁䵁䅁䅁权偂䅁䅁权佂䅁䅁兂䅁䅁䅁乑決䅑䅅䅁䉁䅁䅁兂㝂䭆䠵場䝯䅑杷允䅁䅁䅕䅁䑁䅁䅷䅁䭁䉁䅷䅁䭁䙁䅍䅁䭁䅁䅕䅁䙁䅁䅁䅁杂⭱䅖允䅁䅁䅅䅁䙁偁潙䥘䌯却䄱䍄䉁䅁䅁兂䅁䅁䅍䅄䅁䅁䅯䅁䅁䅁䅯允䅁䅁䅯兂䅁䅁䅕䅁䅁䥁晁欵䉁䅁䅁允䅁䅁䅕䉵䘶ㄶ㑇樳䴸䅉䅅䅁䕁䅁䅁睁䵁䅁䅁权偂䅁䅁权佂䅁䅁兂䅁䅁䅁䡙浲䅑䅅䅁䉁䅁䅁兂偃癷潕䥘䴸䅑杷允䅁䅁䅕䅁䑁䅁䅷䅁䭁䉁䅯䅁䭁䙁䅍䅁䭁䅁䅕䅁䙁䅁䅁䅁杁⭶䅖允䅁䅁䅅䅁䙁䱁䩰䅄牉穊䅰䍄䉁䅁䅁兂䅁䅁䅍䅄䅁䅁䅯䅈䅁䅁䅯睕䅁䅁䅯兂䅁䅁䅕䅁䅁䝁橃唵䉁䅁䅁允䅁䅁䅕捷桱扒穙啌䵁䅉䅅䅁䙁䅁䅁睁䵁䅁䅁权敁䅁䅁权呂䅁䅁权䙁䅁䅁兂䅁䅁䅁䍷浮䅑䅅䅁䉁䅁䅁兂ㅂ硫䕧獖渴䅑杷允䅁䅁䅕䅁䑁䅁䅷䅁䭁䉁䄸䅁䭁䅁䅅䅁䭁䅁䅕䅁䙁䅁䅁䅁杄佖䅚允䅁䅁䅅䅁䙁䙁㑋潈牘敕⽁䍄䉁䅁䅁兂䅁䅁䅍䅄䅁䅁䅯睈䅁䅁䅯睕䅁䅁䅯兂䅁䅁䅕䅁䅁䥁㑂欵䉁䅁䅁允䅁䅁䅕牡へ硫歧啍䵁䅉䅅䅁䕁䅁䅁睁䵁䅁䅁权偂䅁䅁权佂䅁䅁兂䅁䅁䅁䙷浦䅑䅅䅁䉁䅁䅁兂塄㍯㥁瑃偣䅑杷允䅁䅁䅕䅁䑁䅁䅷䅁䭁䉁䄰䅁䭁䙁䅍䅁䭁䅁䅕䅁䙁䅁䅁䅁杄敡䅚允䅁䅁䅅䅁䙁䑁䩥坑汄䍅䄵䍄䉁䅁䅁兂䅁䅁䅍䅄䅁䅁䅯睈䅁䅁䅯睕䅁䅁䅯兂䅁䅁䅕䅁䅁䍁䅄唵䉁䅁䅁允䅁䅁䅕塹⭡确癯啍䵁䅉䅅䅁䙁䅁䅁睁䵁䅁䅁权䅁䅁䅁权呂䅁䅁权䙁䅁䅁兂䅁䅁䅁䝯浺䅑䅅䅁䉁䅁䅁兂啂㘴扗佸穁䅑杷允䅁䅁䅕䅁䑁䅁䅷䅁䭁䉁䄸䅁䭁䙁䅍䅁䭁䅁䅕䅁䙁䅁䅁䅁杄佚䅚允䅁䅁䅅䅁䙁乁楅⼲⭬橃䅆䍄䉁䅁䅁䅂䅁䅁䅍䅄䅁䅁䅯睔䅁䅁䅯杔䅁䅁䅕䅁䅁䭁獄唵䉁䅁䅁允䅁䅁䅕体㙆䭆䠵䕅䵁䅉䅅䅁䕁䅁䅁睁䵁䅁䅁权偂䅁䅁权佂䅁䅁兂䅁䅁䅁䉷浦䅑䅅䅁䉁䅁䅁兂捂㡪ㅌ䙋卷䅑杷允䅁䅁䅕䅁䑁䅁䅷䅁䭁䉁䄴䅁䭁䅁䅅䅁䭁䅁䅕䅁䙁䅁䅁䅁䅄⬫䅖允䅁䅁䅅䅁䙁䡁啳歲桦瑥⽑䍄䉁䅁䅁䅂䅁䅁䅍䅄䅁䅁䅯睔䅁䅁䅯杔䅁䅁䅕䅁䅁䥁㕂欵䉁䅁䅁允䅁䅁䅕牕敧敨剴䕄䵁䅉䅅䅁䕁䅁䅁睁䵁䅁䅁权偂䅁䅁权佂䅁䅁兂䅁䅁䅁䡙浮䅑䅅䅁䉁䅁䅁兂㥁瑃橥䑣䴰䅑杷允䅁䅁䅕䅁䑁䅁䅷䅁䭁䅁䅁䅁䭁䙁䅍䅁䭁䅁䅕䅁䙁䅁䅁䅁䅃低䅚允䅁䅁䅅䅁䙁䍁礲敮渫橨䅎䍄䉁䅁䅁兂䅁䅁䅍䅄䅁䅁䅯睈䅁䅁䅯允䅁䅁䅯兂䅁䅁䅕䅁䅁䭁䱁欵䉁䅁䅁允䅁䅁䅕䡰㥁瑃橥䐴䴸䅉䅅䅁䕁䅁䅁睁䵁䅁䅁权偂䅁䅁权佂䅁䅁兂䅁䅁䅁䵷氯䅑䅅䅁䉁䅁䅁兂㝂䭆䠵場䝯䅑杷允䅁䅁䅕䅁䑁䅁䅷䅁䭁䅁䅁䅁䭁䅁䅅䅁䭁䅁䅕䅁䙁䅁䅁䅁杄畋䅚允䅁䅁䅅䅁䙁䱁敧敨剴乵⼴䍄䉁䅁䅁兂䅁䅁䅍䅄䅁䅁䅯杈䅁䅁䅯允䅁䅁䅯兂䅁䅁䅕䅁䅁䍁䥁欵䉁䅁䅁允䅁䅁䅕硥畓⭒㙆䐱䴸䅉䅅䅁䕁䅁䅁睁䵁䅁䅁权偂䅁䅁权佂䅁䅁兂䅁䅁䅁伴汔䅑䅅䅁䉁䅁䅁兂畃⭒㙆䭆儴䅑杷允䅁䅁䅕䅁䑁䅁䅷䅁䭁䉁䅯䅁䭁䙁䅍䅁䭁䅁䅕䅁䙁䅁䅁䅁杁⭥䅚允䅁䅁䅅䅁䙁䕁㍷啩杆告䅴䍄䉁䅁䅁䅂䅁䅁䅍䅄䅁䅁䅯睔䅁䅁䅯杔䅁䅁䅕䅁䅁䕁癁欵䉁䅁䅁允䅁䅁䅕㡪ㅌ䙋偹歅䵁䅉䅅䅁䙁䅁䅁睁䵁䅁䅁权敁䅁䅁权呂䅁䅁权䙁䅁䅁兂䅁䅁䅁䙷浐䅑䅅䅁䉁䅁䅁兂扄堫焵䡶楑䅑杷允䅁䅁䅑䅁䑁䅁䅷䅁䭁䕁䄸䅁䭁䕁䄴䅁䙁䅁䅁䅁权低䅚允䅁䅁䅅䅁䙁佁剸䉵䘶砶䅆䍄䉁䅁䅁兂䅁䅁䅍䅄䅁䅁䅯杇䅁䅁䅯允䅁䅁䅯兂䅁䅁䅕䅁䅁䅁啁欵䉁䅁䅁允䅁䅁䅕浚浚浚浚樵䴸䅉䅅䅁䙁䅁䅁睁䵁䅁䅁权䅁䅁䅁权呂䅁䅁权䙁䅁䅁兂䅁䅁䅁伴汢䅑䅅䅁䉁䅁䅁兂婁䙂余摌祉䅑杷允䅁䅁䅑䅁䑁䅁䅷䅁䭁䕁䄸䅁䭁䕁䄴䅁䙁䅁䅁䅁䅄攲䅖允䅁䅁䅅䅁䙁䉁䘫ㄶ㑇杈䅬䍄䉁䅁䅁兂䅁䅁䅍䅄䅁䅁䅯先䅁䅁䅯允䅁䅁䅯兂䅁䅁䅕䅁䅁䥁歁欵䉁䅁䅁允䅁䅁䅕浚浚浚浚樱䴸䅉䅅䅁䙁䅁䅁睁䵁䅁䅁权䅁䅁䅁权䉁䅁䅁权䙁䅁䅁兂䅁䅁䅁䱯汘䅑䅅䅁䉁䅁䅁兂慃婭婭婭婮睐杷允䅁䅁䅑䅁䑁䅁䅷䅁䭁䕁䄸䅁䭁䕁䄴䅁䙁䅁䅁䅁杁攵䅖允䅁䅁䅅䅁䙁䙁㑋潈牘剕䅆䍄䉁䅁䅁䅂䅁䅁䅍䅄䅁䅁䅯睔䅁䅁䅯杔䅁䅁䅕䅁䅁䍁潂欵䉁䅁䅁允䅁䅁䅕敨剴䉵䘶啄䵁䅉䅅䅁䙁䅁䅁睁䵁䅁䅁权䅁䅁䅁权䉁䅁䅁权䙁䅁䅁兂䅁䅁䅁䅯洯䅑䅅䅁䉁䅁䅁兂㑃潈牘払敪睐杷允䅁䅁䅕䅁䑁䅁䅷䅁䭁䉁䄸䅁䭁䙁䅍䅁䭁䅁䅕䅁䙁䅁䅁䅁权敁䅚允䅁䅁䅅䅁䙁䥁䅐煹䙆橬䅂䍄䉁䅁䅁兂䅁䅁䅍䅄䅁䅁䅯先䅁䅁䅯睕䅁䅁䅯兂䅁䅁䅕䅁䅁䅁㍂欵䉁䅁䅁允䅁䅁䅕䬸䝦穓䩦啌䵁䅉䅅䅁䕁䅁䅁睁䵁䅁䅁权偂䅁䅁权佂䅁䅁兂䅁䅁䅁䠴浪䅑䅅䅁䉁䅁䅁兂浂浚浚浚䵙䅑杷允䅁䅁䅕䅁䑁䅁䅷䅁䭁䉁䅷䅁䭁䅁䅅䅁䭁䅁䅕䅁䙁䅁䅁䅁杂⭶䅖允䅁䅁䅅䅁䙁䥁䌯匹捨㥪⽉䍄䉁䅁䅁䅂䅁䅁䅍䅄䅁䅁䅯睔䅁䅁䅯杔䅁䅁䅕䅁䅁䵁奃唵䉁䅁䅁允䅁䅁䅕牕敧敨剴䑹䴸䅉䅅䅁䙁䅁䅁睁䵁䅁䅁权慁䅁䅁权䉁䅁䅁权䙁䅁䅁兂䅁䅁䅁䡯浄䅑䅅䅁䉁䅁䅁兂歃䑣䬰㘱潐睐杷允䅁䅁䅕䅁䑁䅁䅷䅁䭁䅁䅁䅁䭁䙁䅍䅁䭁䅁䅕䅁䙁䅁䅁䅁䅂敋䅚允䅁䅁䅅䅁䙁佁兘瑉㕶橐䅎䍄䉁䅁䅁兂䅁䅁䅍䅄䅁䅁䅯䅈䅁䅁䅯允䅁䅁䅯兂䅁䅁䅕䅁䅁䭁煁欵䉁䅁䅁允䅁䅁䅕歲桦桥畓稱䴸䅉䅅䅁䙁䅁䅁睁䵁䅁䅁权摁䅁䅁权呂䅁䅁权䙁䅁䅁兂䅁䅁䅁䱧汔䅑䅅䅁䉁䅁䅁兂䭁㘱睎捐瑯䅑杷允䅁䅁䅕䅁䑁䅁䅷䅁䭁䉁䄴䅁䭁䅁䅅䅁䭁䅁䅕䅁䙁䅁䅁䅁杄⭤䅚允䅁䅁䅅䅁䙁䅁䅁䅁䅁乁⽁䍄䉁䅁䅁䅂䅁䅁䅍䅄䅁䅁䅯睔䅁䅁䅯杔䅁䅁䅕䅁䅁䵁歁欵䉁䅁䅁允䅁䅁䅕⽷潕䥘䌯啅䵁䅉䅅䅁䕁䅁䅁睁䵁䅁䅁权偂䅁䅁权佂䅁䅁兂䅁䅁䅁䵑氳䅑䅅䅁䉁䅁䅁兂獄払敧敨䑳䅑杷允䅁䅁䅕䅁䑁䅁䅷䅁䭁䉁䄸䅁䭁䙁䅍䅁䭁䅁䅕䅁䙁䅁䅁䅁䅂⭇䅚允䅁䅁䅅䅁䙁䕁㉡⼸唳䐫䅂䍄䉁䅁䅁兂䅁䅁䅍䅄䅁䅁䅯杇䅁䅁䅯睕䅁䅁䅯兂䅁䅁䅕䅁䅁䭁ㅁ欵䉁䅁䅁允䅁䅁䅕㑈牘払敪歏䵁䅉䅅䅁䕁䅁䅁睁䵁䅁䅁权偂䅁䅁权佂䅁䅁兂䅁䅁䅁䍧浦䅑䅅䅁䉁䅁䅁兂畃⭒㙆䭆刴䅑杷允䅁䅁䅕䅁䑁䅁䅷䅁䭁䉁䅯䅁䭁䅁䅅䅁䭁䅁䅕䅁䙁䅁䅁䅁䅁敖䅚允䅁䅁䅅䅁䙁䭁睒児塲⭯⽧䍄䉁䅁䅁䅂䅁䅁䅍䅄䅁䅁䅯睔䅁䅁䅯杔䅁䅁䅕䅁䅁䅁歄唵䉁䅁䅁允䅁䅁䅕硥畓⭒㙆䕅䵁䅉䅅䅁䕁䅁䅁睁䵁䅁䅁权偂䅁䅁权佂䅁䅁兂䅁䅁䅁偷汌䅑䅅䅁䉁䅁䅁兂桄桥畓⭒佅䅑杷允䅁䅁䅕䅁䑁䅁䅷䅁䭁䉁䅷䅁䭁䙁䅍䅁䭁䅁䅕䅁䙁䅁䅁䅁杂畎䅚允䅁䅁䅅䅁䙁䙁㕧䵴㉨楐䄵䍄䉁䅁䅁䅂䅁䅁䅍䅄䅁䅁䅯睔䅁䅁䅯杔䅁䅁䅕䅁䅁䭁剄唵䉁䅁䅁允䅁䅁䅕捺䵺䵺䵺歂䵁䅉䅅䅁䙁䅁䅁睁䵁䅁䅁权慁䅁䅁权呂䅁䅁权䙁䅁䅁兂䅁䅁䅁䡯浔䅑䅅䅁䉁䅁䅁兂䵂㑎䉬䍙㝕䅑杷允䅁䅁䅑䅁䑁䅁䅷䅁䭁䕁䄸䅁䭁䕁䄴䅁䙁䅁䅁䅁䅂何䅚允䅁䅁䅅䅁䙁䑁積積積硍䅆䍄䉁䅁䅁兂䅁䅁䅍䅄䅁䅁䅯杇䅁䅁䅯睕䅁䅁䅯兂䅁䅁䅕䅁䅁䕁乁欵䉁䅁䅁允䅁䅁䅕潂噇㑑䵴歏䵁䅉䅅䅁䕁䅁䅁睁䵁䅁䅁权偂䅁䅁权佂䅁䅁兂䅁䅁䅁䙉浈䅑䅅䅁䉁䅁䅁兂䭁㘱睎児副䅑杷允䅁䅁䅕䅁䑁䅁䅷䅁䭁䅁䅁䅁䭁䅁䅅䅁䭁䅁䅕䅁䙁䅁䅁䅁杁⭊䅚允䅁䅁䅅䅁䙁䱁敧敨剴乵⼴䍄䉁䅁䅁兂䅁䅁䅍䅄䅁䅁䅯先䅁䅁䅯允䅁䅁䅯兂䅁䅁䅕䅁䅁䍁扃唵䉁䅁䅁允䅁䅁䅕㘱睎児塲稰䴸䅉䅅䅁䕁䅁䅁睁䵁䅁䅁权偂䅁䅁权佂䅁䅁兂䅁䅁䅁䨴決䅑䅅䅁䉁䅁䅁兂䑄匹捨㡪噌睐杷允䅁䅁䅕䅁䑁䅁䅷䅁䭁䉁䅷䅁䭁䙁䅍䅁䭁䅁䅕䅁䙁䅁䅁䅁杂⭎䅚允䅁䅁䅅䅁䙁䙁㕧䵴㉨楐䄵䍄䉁䅁䅁䅂䅁䅁䅍䅄䅁䅁䅯睔䅁䅁䅯杔䅁䅁䅕䅁䅁䍁療欵䉁䅁䅁允䅁䅁䅕䭆䠵場啯䕄䵁䅉䅅䅁䙁䅁䅁睁䵁䅁䅁权晁䅁䅁权呂䅁䅁权䙁䅁䅁兂䅁䅁䅁䔴浪䅑䅅䅁䉁䅁䅁兂䕁杖琴桳砰䅑杷允䅁䅁䅕䅁䑁䅁䅷䅁䭁䉁䅯䅁䭁䙁䅍䅁䭁䅁䅕䅁䙁䅁䅁䅁权⭲䅖允䅁䅁䅅䅁䙁䉁愱䑚晶穪䅬䍄䉁䅁䅁兂䅁䅁䅍䅄䅁䅁䅯先䅁䅁䅯允䅁䅁䅯兂䅁䅁䅕䅁䅁䍁㍄唵䉁䅁䅁允䅁䅁䅕㑈牘払敧吱䴸䅉䅅䅁䙁䅁䅁睁䵁䅁䅁权慁䅁䅁权呂䅁䅁权䙁䅁䅁兂䅁䅁䅁䅙浘䅑䅅䅁䉁䅁䅁兂䝂癴㥐䈱㙧䅑杷允䅁䅁䅕䅁䑁䅁䅷䅁䭁䉁䅷䅁䭁䙁䅍䅁䭁䅁䅕䅁䙁䅁䅁䅁权畏䅚允䅁䅁䅅䅁䙁䉁婦発呤祯䄵䍄䉁䅁䅁䅂䅁䅁䅍䅄䅁䅁䅯睔䅁䅁䅯杔䅁䅁䅕䅁䅁䵁㑂欵䉁䅁䅁允䅁䅁䅕浚浚浚浚䕄䵁䅉䅅䅁䙁䅁䅁睁䵁䅁䅁权慁䅁䅁权呂䅁䅁权䙁䅁䅁兂䅁䅁䅁偑汢䅑䅅䅁䉁䅁䅁兂䑄匹捨㡪㕉䅑杷允䅁䅁䅕䅁䑁䅁䅷䅁䭁䉁䄰䅁䭁䙁䅍䅁䭁䅁䅕䅁䙁䅁䅁䅁䅂畚䅚允䅁䅁䅅䅁䙁䡁⼰噎㘶卓䄵䍄䉁䅁䅁兂䅁䅁䅍䅄䅁䅁䅯䅁䅁䅁䅯睕䅁䅁䅯兂䅁䅁䅕䅁䅁䅁䩁欵䉁䅁䅁允䅁䅁䅕癱午坔睊歍䵁䅉䅅䅁䙁䅁䅁睁䵁䅁䅁权慁䅁䅁权䉁䅁䅁权䙁䅁䅁兂䅁䅁䅁䙉浈䅑䅅䅁䉁䅁䅁兂歃䑣䬰㘱潐睐杷允䅁䅁䅑䅁䑁䅁䅷䅁䭁䕁䄸䅁䭁䕁䄴䅁䙁䅁䅁䅁杄佶䅖允䅁䅁䅅䅁䙁䥁牘払敧敨⽳䍄䉁䅁䅁兂䅁䅁䅍䅄䅁䅁䅯䅁䅁䅁䅯睕䅁䅁䅯兂䅁䅁䅕䅁䅁䭁㝃唵䉁䅁䅁允䅁䅁䅕䘫橐婰䕵歍䵁䅉䅅䅁䙁䅁䅁睁䵁䅁䅁权䅁䅁䅁权呂䅁䅁权䙁䅁䅁兂䅁䅁䅁䙧浢䅑䅅䅁䉁䅁䅁兂㕁䵴㉨瑶稸䅑杷允䅁䅁䅑䅁䑁䅁䅷䅁䭁䕁䄸䅁䭁䕁䄴䅁䙁䅁䅁䅁杂佐䅚允䅁䅁䅅䅁䙁䅁塲㍯㥁权䄱䍄䉁䅁䅁兂䅁䅁䅍䅄䅁䅁䅯先䅁䅁䅯睕䅁䅁䅯兂䅁䅁䅕䅁䅁䵁噄唵䉁䅁䅁允䅁䅁䅕⽷潕䥘䌯啌䵁䅉䅅䅁䙁䅁䅁睁䵁䅁䅁权摁䅁䅁权呂䅁䅁权䙁䅁䅁兂䅁䅁䅁䭙汈䅑䅅䅁䉁䅁䅁兂䝂癴㥐䠱瑧䅑杷允䅁䅁䅑䅁䑁䅁䅷䅁䭁䕁䄸䅁䭁䕁䄴䅁䙁䅁䅁䅁䅁畄䅚允䅁䅁䅅䅁䙁䕁桪桥畓硒䅊䍄䉁䅁䅁兂䅁䅁䅍䅄䅁䅁䅯䅁䅁䅁䅯睕䅁䅁䅯兂䅁䅁䅕䅁䅁䕁慄唵䉁䅁䅁允䅁䅁䅕䉯癯匳䝑き䵁䅉䅅䅁䙁䅁䅁睁䵁䅁䅁权䅁䅁䅁权呂䅁䅁权䙁䅁䅁兂䅁䅁䅁䅯浔䅑䅅䅁䉁䅁䅁兂煃搸乊湙祁䅑杷允䅁䅁䅕䅁䑁䅁䅷䅁䭁䅁䅁䅁䭁䅁䅅䅁䭁䅁䅕䅁䙁䅁䅁䅁䅄畹䅖允䅁䅁䅅䅁䙁䑁䬰㘱睎摐⽯䍄䉁䅁䅁兂䅁䅁䅍䅄䅁䅁䅯先䅁䅁䅯睕䅁䅁䅯兂䅁䅁䅕䅁䅁䥁䍂欵䉁䅁䅁允䅁䅁䅕牒穢搯㑓歌䵁䅉䅅䅁䙁䅁䅁睁䵁䅁䅁权敁䅁䅁权呂䅁䅁权䙁䅁䅁兂䅁䅁䅁䭷氷䅑䅅䅁䉁䅁䅁兂㍂灶愸硌爰䅑杷允䅁䅁䅕䅁䑁䅁䅷䅁䭁䉁䅷䅁䭁䙁䅍䅁䭁䅁䅕䅁䙁䅁䅁䅁䅁佴䅖允䅁䅁䅅䅁䙁䡁⭥确癯午䄵䍄䉁䅁䅁兂䅁䅁䅍䅄䅁䅁䅯䅁䅁䅁䅯允䅁䅁䅯兂䅁䅁䅕䅁䅁䥁歂欵䉁䅁䅁允䅁䅁䅕䉵䘶ㄶ㑇樳䴸䅉䅅䅁䙁䅁䅁睁䵁䅁䅁权晁䅁䅁权呂䅁䅁权䙁䅁䅁兂䅁䅁䅁乧汐䅑䅅䅁䉁䅁䅁兂扁㥌欰畂睅䅑杷允䅁䅁䅑䅁䑁䅁䅷䅁䭁䕁䄸䅁䭁䕁䄴䅁䙁䅁䅁䅁䅃佘䅚允䅁䅁䅅䅁䙁䩁婱婭婭六䄹䍄䉁䅁䅁兂䅁䅁䅍䅄䅁䅁䅯䅁䅁䅁䅯允䅁䅁䅯兂䅁䅁䅕䅁䅁䥁噂欵䉁䅁䅁允䅁䅁䅕䉵䘶ㄶ㑇樳䴸䅉䅅䅁䙁䅁䅁睁䵁䅁䅁权䅁䅁䅁权呂䅁䅁权䙁䅁䅁兂䅁䅁䅁䍉浐䅑䅅䅁䉁䅁䅁兂汄䌰扌含稴䅑杷允䅁䅁䅑䅁䑁䅁䅷䅁䭁䕁䄸䅁䭁䕁䄴䅁䙁䅁䅁䅁䅁⭮䅖允䅁䅁䅅䅁䙁䑁積積積㥍⽍䍄䉁䅁䅁兂䅁䅁䅍䅄䅁䅁䅯䅁䅁䅁䅯睕䅁䅁䅯兂䅁䅁䅕䅁䅁䭁㡃唵䉁䅁䅁允䅁䅁䅕䘫橐婰䕵歍䵁䅉䅅䅁䙁䅁䅁睁䵁䅁䅁权捁䅁䅁权呂䅁䅁权䙁䅁䅁兂䅁䅁䅁䡙浢䅑䅅䅁䉁䅁䅁兂䱃佢㝦晱瑅䅑杷允䅁䅁䅕䅁䑁䅁䅷䅁䭁䉁䄰䅁䭁䅁䅅䅁䭁䅁䅕䅁䙁䅁䅁䅁杄体䅚允䅁䅁䅅䅁䙁䭁䠵場啯瑲⽣䍄䉁䅁䅁兂䅁䅁䅍䅄䅁䅁䅯䅁䅁䅁䅯睕䅁䅁䅯兂䅁䅁䅕䅁䅁佁牄唵䉁䅁䅁允䅁䅁䅕積積積呏歍䵁䅉䅅䅁䙁䅁䅁睁䵁䅁䅁权敁䅁䅁权呂䅁䅁权䙁䅁䅁兂䅁䅁䅁䱁氯䅑䅅䅁䉁䅁䅁兂硂児塲穯獁䅑杷允䅁䅁䅕䅁䑁䅁䅷䅁䭁䉁䅯䅁䭁䙁䅍䅁䭁䅁䅕䅁䙁䅁䅁䅁杁⭑䅚允䅁䅁䅅䅁䙁䵁杕䡳潊呍䅴䍄䉁䅁䅁兂䅁䅁䅍䅄䅁䅁䅯先䅁䅁䅯睕䅁䅁䅯兂䅁䅁䅕䅁䅁䕁乄唵䉁䅁䅁允䅁䅁䅕噋偹癷潕歌䵁䅉䅅䅁䕁䅁䅁睁䵁䅁䅁权偂䅁䅁权佂䅁䅁兂䅁䅁䅁䵑汢䅑䅅䅁䉁䅁䅁兂啁歲桦桥㉔睐杷允䅁䅁䅑䅁䑁䅁䅷䅁䭁䕁䄸䅁䭁䕁䄴䅁䙁䅁䅁䅁䅂伴䅖允䅁䅁䅅䅁䙁䩁婱婭婭六䅴䍄䉁䅁䅁兂䅁䅁䅍䅄䅁䅁䅯䅈䅁䅁䅯允䅁䅁䅯兂䅁䅁䅕䅁䅁䭁坄唵䉁䅁䅁允䅁䅁䅕積積積積稰䴸䅉䅅䅁䕁䅁䅁睁䵁䅁䅁权偂䅁䅁权佂䅁䅁兂䅁䅁䅁佯汔䅑䅅䅁䉁䅁䅁兂㝂䭆䠵場兯䅑杷允䅁䅁䅑䅁䑁䅁䅷䅁䭁䕁䄸䅁䭁䕁䄴䅁䙁䅁䅁䅁杁甫䅖允䅁䅁䅅䅁䙁䭁睒児塲睯䅸䍄䉁䅁䅁兂䅁䅁䅍䅄䅁䅁䅯睈䅁䅁䅯睕䅁䅁䅯兂䅁䅁䅕䅁䅁䥁㕂欵䉁䅁䅁允䅁䅁䅕牡へ硫歧啍䵁䅉䅅䅁䕁䅁䅁睁䵁䅁䅁权偂䅁䅁权佂䅁䅁兂䅁䅁䅁䑙浔䅑䅅䅁䉁䅁䅁兂灁䥘䌯匹卧䅑杷允䅁䅁䅑䅁䑁䅁䅷䅁䭁䕁䄸䅁䭁䕁䄴䅁䙁䅁䅁䅁䅃佇䅚允䅁䅁䅅䅁䙁䡁啳歲桦桥䅊䍄䉁䅁䅁兂䅁䅁䅍䅄䅁䅁䅯䅁䅁䅁䅯睕䅁䅁䅯兂䅁䅁䅕䅁䅁䥁橃唵䉁䅁䅁允䅁䅁䅕㘱睎児㍰啍䵁䅉䅅䅁䕁䅁䅁睁䵁䅁䅁权偂䅁䅁权佂䅁䅁兂䅁䅁䅁䠴浦䅑䅅䅁䉁䅁䅁兂㝂䭆䠵場䵯䅑杷允䅁䅁䅕䅁䑁䅁䅷䅁䭁䉁䅷䅁䭁䙁䅍䅁䭁䅁䅕䅁䙁䅁䅁䅁䅁畤䅚允䅁䅁䅅䅁䙁䥁獴⼵灵匸䄱䍄䉁䅁䅁兂䅁䅁䅍䅄䅁䅁䅯杇䅁䅁䅯允䅁䅁䅯兂䅁䅁䅕䅁䅁䕁兂欵䉁䅁䅁允䅁䅁䅕䡰㥁瑃橥䐶䴸䅉䅅䅁䙁䅁䅁睁䵁䅁䅁权捁䅁䅁权呂䅁䅁权䙁䅁䅁兂䅁䅁䅁䑁浮䅑䅅䅁䉁䅁䅁兂塁挲㌷㙕畍䅑杷允䅁䅁䅑䅁䑁䅁䅷䅁䭁䕁䄸䅁䭁䕁䄴䅁䙁䅁䅁䅁杂敉䅚允䅁䅁䅅䅁䙁䭁䠵場啯杲䄹䍄䉁䅁䅁兂䅁䅁䅍䅄䅁䅁䅯睈䅁䅁䅯允䅁䅁䅯兂䅁䅁䅕䅁䅁䕁癃唵䉁䅁䅁允䅁䅁䅯睇䅁䅁杷允䅁䅁䅕䅁䑁䅁䅷䅁䭁䉁䅯䅁䭁䙁䅍䅁䭁䅁䅕䅁䙁䅁䅁䅁䅂甶䅖允䅁䅁䅅䅁䙁䵁ㅐ䙋偹橷䅬䍄䉁䅁䅁䅂䅁䅁䅍䅄䅁䅁䅯睔䅁䅁䅯杔䅁䅁䅕䅁䅁䵁㍂欵䉁䅁䅁允䅁䅁䅕䡰㥁瑃橥䕄䵁䅉䅅䅁䙁䅁䅁睁䵁䅁䅁权䅁䅁䅁权呂䅁䅁权䙁䅁䅁兂䅁䅁䅁乧汶䅑䅅䅁䉁䅁䅁兂权楇搯䅊穙䅑杷允䅁䅁䅑䅁䑁䅁䅷䅁䭁䕁䄸䅁䭁䕁䄴䅁䙁䅁䅁䅁权敎䅚允䅁䅁䅅䅁䙁佁㙆䭆䠵刴䅂䍄䉁䅁䅁䅂䅁䅁䅍䅄䅁䅁䅯睔䅁䅁䅯杔䅁䅁䅕䅁䅁䍁塃唵䉁䅁䅁允䅁䅁䅕牕敧敨剴䑹䴸䅉䅅䅁䙁䅁䅁睁䵁䅁䅁权敁䅁䅁权䉁䅁䅁权䙁䅁䅁兂䅁䅁䅁乯汢䅑䅅䅁䉁䅁䅁兂穁積積積呐睐杷允䅁䅁䅕䅁䑁䅁䅷䅁䭁䉁䄰䅁䭁䙁䅍䅁䭁䅁䅕䅁䙁䅁䅁䅁杄畋䅚允䅁䅁䅅䅁䙁䝁浚浚浚椵䄵䍄䉁䅁䅁䅂䅁䅁䅍䅄䅁䅁䅯睔䅁䅁䅯杔䅁䅁䅕䅁䅁䭁㍂欵䉁䅁䅁允䅁䅁䅕硥畓⭒㙆䕄䵁䅉䅅䅁䙁䅁䅁睁䵁䅁䅁权䅁䅁䅁权䉁䅁䅁权䙁䅁䅁兂䅁䅁䅁䉉浐䅑䅅䅁䉁䅁䅁兂㑃潈牘払敪睐杷允䅁䅁䅑䅁䑁䅁䅷䅁䭁䕁䄸䅁䭁䕁䄴䅁䙁䅁䅁䅁䅁佮䅖允䅁䅁䅅䅁䙁䕁桪桥畓㥒⽅䍄䉁䅁䅁兂䅁䅁䅍䅄䅁䅁䅯䅁䅁䅁䅯睕䅁䅁䅯兂䅁䅁䅕䅁䅁䕁灄唵䉁䅁䅁允䅁䅁䅕積積積呏歍䵁䅉䅅䅁䕁䅁䅁睁䵁䅁䅁权偂䅁䅁权佂䅁䅁兂䅁䅁䅁䝙浦䅑䅅䅁䉁䅁䅁兂慃婭婭婭乫䅑杷允䅁䅁䅕䅁䑁䅁䅷䅁䭁䉁䅷䅁䭁䙁䅍䅁䭁䅁䅕䅁䙁䅁䅁䅁杂敓䅚允䅁䅁䅅䅁䙁䝁匸㡧䭄卙䄵䍄䉁䅁䅁兂䅁䅁䅍䅄䅁䅁䅯先䅁䅁䅯允䅁䅁䅯兂䅁䅁䅕䅁䅁䵁桃唵䉁䅁䅁允䅁䅁䅕㘱睎児塲稰䴸䅉䅅䅁䕁䅁䅁睁䵁䅁䅁权偂䅁䅁权佂䅁䅁兂䅁䅁䅁䵙汐䅑䅅䅁䉁䅁䅁兂捂㡪ㅌ䙋空睐杷允䅁䅁䅕䅁䑁䅁䅷䅁䭁䉁䄸䅁䭁䙁䅍䅁䭁䅁䅕䅁䙁䅁䅁䅁䅃⭓䅚允䅁䅁䅅䅁䙁䅁坒楄礲呈䅆䍄䉁䅁䅁䅂䅁䅁䅍䅄䅁䅁䅯睔䅁䅁䅯杔䅁䅁䅕䅁䅁佁坁欵䉁䅁䅁允䅁䅁䅕䭆䠵場啯ぅ䵁䅉䅅䅁䙁䅁䅁睁䵁䅁䅁权䅁䅁䅁权䉁䅁䅁权䙁䅁䅁兂䅁䅁䅁䡧浲䅑䅅䅁䉁䅁䅁兂㑃潈牘払敪睐杷允䅁䅁䅕䅁䑁䅁䅷䅁䭁䉁䄰䅁䭁䅁䅅䅁䭁䅁䅕䅁䙁䅁䅁䅁䅃當䅖允䅁䅁䅅䅁䙁乁橥䑣䬰㤱⽍䍄䉁䅁䅁兂䅁䅁䅍䅄䅁䅁䅯杈䅁䅁䅯允䅁䅁䅯兂䅁䅁䅕䅁䅁䅁卂欵䉁䅁䅁允䅁䅁䅕⽷潕䥘䌯吱䴸䅉䅅䅁䕁䅁䅁睁䵁䅁䅁权偂䅁䅁权佂䅁䅁兂䅁䅁䅁佉汌䅑䅅䅁䉁䅁䅁兂䅁䅁䅁䅁佁䅑杷允䅁䅁䅕䅁䑁䅁䅷䅁䭁䉁䅯䅁䭁䅁䅅䅁䭁䅁䅕䅁䙁䅁䅁䅁杂畹䅖允䅁䅁䅅䅁䙁偁潙䥘䌯改⽁䍄䉁䅁䅁兂䅁䅁䅍䅄䅁䅁䅯䅁䅁䅁䅯允䅁䅁䅯兂䅁䅁䅕䅁䅁䍁㑄唵䉁䅁䅁允䅁䅁䅕䉵䘶ㄶ㑇樳䴸䅉䅅䅁䙁䅁䅁睁䵁䅁䅁权䅁䅁䅁权呂䅁䅁权䙁䅁䅁兂䅁䅁䅁乁氷䅑䅅䅁䉁䅁䅁兂婁䙂余摌祉䅑杷允䅁䅁䅑䅁䑁䅁䅷䅁䭁䕁䄸䅁䭁䕁䄴䅁䙁䅁䅁䅁杂畉䅚允䅁䅁䅅䅁䙁䅁䅁䅁䅁䉁䅆䍄䉁䅁䅁兂䅁䅁䅍䅄䅁䅁䅯䅈䅁䅁䅯睕䅁䅁䅯兂䅁䅁䅕䅁䅁䭁䑄唵䉁䅁䅁允䅁䅁䅕場啯歲桤歌䵁䅉䅅䅁䙁䅁䅁睁䵁䅁䅁权晁䅁䅁权䉁䅁䅁权䙁䅁䅁兂䅁䅁䅁䍯浔䅑䅅䅁䉁䅁䅁兂䥂場啯歲桦睐杷允䅁䅁䅕䅁䑁䅁䅷䅁䭁䉁䄰䅁䭁䅁䅅䅁䭁䅁䅕䅁䙁䅁䅁䅁䅃佑䅚允䅁䅁䅅䅁䙁䭁䠵場啯瑲⽣䍄䉁䅁䅁兂䅁䅁䅍䅄䅁䅁䅯杈䅁䅁䅯睕䅁䅁䅯兂䅁䅁䅕䅁䅁䭁䉄唵䉁䅁䅁允䅁䅁䅕呣䬰㘱睍䕌䵁䅉䅅䅁䙁䅁䅁睁䵁䅁䅁权晁䅁䅁权䉁䅁䅁权䙁䅁䅁兂䅁䅁䅁䌴洯䅑䅅䅁䉁䅁䅁兂䥂場啯歲桦睐杷允䅁䅁䅑䅁䑁䅁䅷䅁䭁䕁䄸䅁䭁䕁䄴䅁䙁䅁䅁䅁杁佣䅚允䅁䅁䅅䅁䙁佁剸䉵䘶眶䅴䍄䉁䅁䅁兂䅁䅁䅍䅄䅁䅁䅯杇䅁䅁䅯睕䅁䅁䅯兂䅁䅁䅕䅁䅁䥁敁欵䉁䅁䅁允䅁䅁䅕癴㥐䠱䩩歏䵁䅉䅅䅁䕁䅁䅁睁䵁䅁䅁权偂䅁䅁权佂䅁䅁兂䅁䅁䅁䙉浌䅑䅅䅁䉁䅁䅁兂卂䉵䘶ㄶ充䅑杷允䅁䅁䅕䅁䑁䅁䅷䅁䭁䉁䅯䅁䭁䙁䅍䅁䭁䅁䅕䅁䙁䅁䅁䅁䅄畄䅚允䅁䅁䅅䅁䙁䅁䉡啬䱏䑔䅰䍄䉁䅁䅁䅂䅁䅁䅍䅄䅁䅁䅯睔䅁䅁䅯杔䅁䅁䅕䅁䅁佁䩁欵䉁䅁䅁允䅁䅁䅕䭆䠵場啯歅䵁䅉䅅䅁䕁䅁䅁睁䵁䅁䅁权偂䅁䅁权佂䅁䅁兂䅁䅁䅁䍁浺䅑䅅䅁䉁䅁䅁兂捂㡪ㅌ䙋呷䅑杷允䅁䅁䅑䅁䑁䅁䅷䅁䭁䕁䄸䅁䭁䕁䄴䅁䙁䅁䅁䅁䅄敡䅚允䅁䅁䅅䅁䙁䅁塲㍯㥁权䄱䍄䉁䅁䅁兂䅁䅁䅍䅄䅁䅁䅯睈䅁䅁䅯允䅁䅁䅯兂䅁䅁䅕䅁䅁䝁穂欵䉁䅁䅁允䅁䅁䅕牕敧敨剴䐴䴸䅉䅅䅁䕁䅁䅁睁䵁䅁䅁权偂䅁䅁权佂䅁䅁兂䅁䅁䅁䩷汢䅑䅅䅁䉁䅁䅁兂慃婭婭婭䩮睐杷允䅁䅁䅑䅁䑁䅁䅷䅁䭁䕁䄸䅁䭁䕁䄴䅁䙁䅁䅁䅁杁⭤䅚允䅁䅁䅅䅁䙁䅁䅁䅁䅁䅁䅸䍄䉁䅁䅁兂䅁䅁䅍䅄䅁䅁䅯先䅁䅁䅯允䅁䅁䅯兂䅁䅁䅕䅁䅁䍁卂欵䉁䅁䅁允䅁䅁䅕歲桦桥畓稱䴸䅉䅅䅁䕁䅁䅁睁䵁䅁䅁权偂䅁䅁权佂䅁䅁兂䅁䅁䅁䑙浐䅑䅅䅁䉁䅁䅁兂塄㍯㥁瑃剣䅑杷允䅁䅁䅕䅁䑁䅁䅷䅁䭁䅁䅁䅁䭁䙁䅍䅁䭁䅁䅕䅁䙁䅁䅁䅁䅁佥䅚允䅁䅁䅅䅁䙁䙁橔婰䕶䑁䅒䍄䉁䅁䅁䅂䅁䅁䅍䅄䅁䅁䅯睔䅁䅁䅯杔䅁䅁䅕䅁䅁䕁㍃唵䉁䅁䅁允䅁䅁䅕体㙆䭆䠵吴䴸䅉䅅䅁䕁䅁䅁睁䵁䅁䅁权偂䅁䅁权佂䅁䅁兂䅁䅁䅁䕁洳䅑䅅䅁䉁䅁䅁兂捂㡪ㅌ䙋剷䅑杷允䅁䅁䅕䅁䑁䅁䅷䅁䭁䉁䄰䅁䭁䅁䅅䅁䭁䅁䅕䅁䙁䅁䅁䅁权估䅖允䅁䅁䅅䅁䙁乁橥䑣䬰㤱⽍䍄䉁䅁䅁兂䅁䅁䅍䅄䅁䅁䅯杈䅁䅁䅯睕䅁䅁䅯兂䅁䅁䅕䅁䅁佁䥁欵䉁䅁䅁允䅁䅁䅕䅁䅁䅁䅁歋䵁䅉䅅䅁䙁䅁䅁睁䵁䅁䅁权晁䅁䅁权䉁䅁䅁权䙁䅁䅁兂䅁䅁䅁乯汢䅑䅅䅁䉁䅁䅁兂乄䵺䵺䵺捺睐杷允䅁䅁䅑䅁䑁䅁䅷䅁䭁䕁䄸䅁䭁䕁䄴䅁䙁䅁䅁䅁䅁⭤䅚允䅁䅁䅅䅁䙁䑁䬰㘱睎児䅸䍄䉁䅁䅁兂䅁䅁䅍䅄䅁䅁䅯杈䅁䅁䅯允䅁䅁䅯兂䅁䅁䅕䅁䅁䕁あ欵䉁䅁䅁允䅁䅁䅕䅁䅁䅁䅁䐰䴸䅉䅅䅁䙁䅁䅁睁䵁䅁䅁权䅁䅁䅁权䉁䅁䅁权䙁䅁䅁兂䅁䅁䅁䙉浌䅑䅅䅁䉁䅁䅁兂㑃潈牘払敪睐杷允䅁䅁䅕䅁䑁䅁䅷䅁䭁䉁䄴䅁䭁䅁䅅䅁䭁䅁䅕䅁䙁䅁䅁䅁䅄攵䅖允䅁䅁䅅䅁䙁䑁積積積㥍⽍䍄䉁䅁䅁兂䅁䅁䅍䅄䅁䅁䅯杇䅁䅁䅯睕䅁䅁䅯兂䅁䅁䅕䅁䅁佁浃唵䉁䅁䅁允䅁䅁䅕噈歰㥏倫問䵁䅉䅅䅁䙁䅁䅁睁䵁䅁䅁权敁䅁䅁权䉁䅁䅁权䙁䅁䅁兂䅁䅁䅁䴴氯䅑䅅䅁䉁䅁䅁兂穁積積積呐睐杷允䅁䅁䅕䅁䑁䅁䅷䅁䭁䉁䄴䅁䭁䙁䅍䅁䭁䅁䅕䅁䙁䅁䅁䅁䅂⭢䅚允䅁䅁䅅䅁䙁乁楅⼲⭬楡䅆䍄䉁䅁䅁䅂䅁䅁䅍䅄䅁䅁䅯睔䅁䅁䅯杔䅁䅁䅕䅁䅁䭁楃唵䉁䅁䅁允䅁䅁䅕⽷潕䥘䌯吱䴸䅉䅅䅁䙁䅁䅁睁䵁䅁䅁权䅁䅁䅁权呂䅁䅁权䙁䅁䅁兂䅁䅁䅁䕑浢䅑䅅䅁䉁䅁䅁兂十㡧䭄捯穕䅑杷允䅁䅁䅕䅁䑁䅁䅷䅁䭁䅁䅁䅁䭁䙁䅍䅁䭁䅁䅕䅁䙁䅁䅁䅁䅃敢䅚允䅁䅁䅅䅁䙁䙁橔婰䕶䐴䅎䍄䉁䅁䅁䅂䅁䅁䅍䅄䅁䅁䅯睔䅁䅁䅯杔䅁䅁䅕䅁䅁䅁潂欵䉁䅁䅁允䅁䅁䅕灭婭婭婭啄䵁䅉䅅䅁䙁䅁䅁睁䵁䅁䅁权慁䅁䅁权䉁䅁䅁权䙁䅁䅁兂䅁䅁䅁䕷浄䅑䅅䅁䉁䅁䅁兂歃䑣䬰㘱潐睐杷允䅁䅁䅕䅁䑁䅁䅷䅁䭁䉁䄸䅁䭁䙁䅍䅁䭁䅁䅕䅁䙁䅁䅁䅁䅁佣䅚允䅁䅁䅅䅁䙁䅁塲㍯㥁橋䅆䍄䉁䅁䅁䅂䅁䅁䅍䅄䅁䅁䅯睔䅁䅁䅯杔䅁䅁䅕䅁䅁䭁䕄唵䉁䅁䅁允䅁䅁䅕呣䬰㘱睎吹䴸䅉䅅䅁䕁䅁䅁睁䵁䅁䅁权偂䅁䅁权佂䅁䅁兂䅁䅁䅁䉑浶䅑䅅䅁䉁䅁䅁兂捂㡪ㅌ䙋具䅑杷允䅁䅁䅕䅁䑁䅁䅷䅁䭁䉁䅷䅁䭁䙁䅍䅁䭁䅁䅕䅁䙁䅁䅁䅁䅃敖䅚允䅁䅁䅅䅁䙁乁欰潂噇祑䄵䍄䉁䅁䅁䅂䅁䅁䅍䅄䅁䅁䅯睔䅁䅁䅯杔䅁䅁䅕䅁䅁䕁楄唵䉁䅁䅁允䅁䅁䅕牕敧敨剴歄䵁䅉䅅䅁䙁䅁䅁睁䵁䅁䅁权敁䅁䅁权呂䅁䅁权䙁䅁䅁兂䅁䅁䅁䵉汪䅑䅅䅁䉁䅁䅁兂硂児塲穯獁䅑杷允䅁䅁䅕䅁䑁䅁䅷䅁䭁䉁䅷䅁䭁䅁䅅䅁䭁䅁䅕䅁䙁䅁䅁䅁䅃⭑䅚允䅁䅁䅅䅁䙁偁潙䥘䌯搹⽧䍄䉁䅁䅁兂䅁䅁䅍䅄䅁䅁䅯䅈䅁䅁䅯睕䅁䅁䅯兂䅁䅁䅕䅁䅁佁允欵䉁䅁䅁允䅁䅁䅕牘䩰䅄牋啌䵁䅉䅅䅁䕁䅁䅁睁䵁䅁䅁权偂䅁䅁权佂䅁䅁兂䅁䅁䅁䉁浦䅑䅅䅁䉁䅁䅁兂穁積積積呍䅑杷允䅁䅁䅑䅁䑁䅁䅷䅁䭁䕁䄸䅁䭁䕁䄴䅁䙁䅁䅁䅁杂⭣䅚允䅁䅁䅅䅁䙁䭁睒児塲睯䅸䍄䉁䅁䅁兂䅁䅁䅍䅄䅁䅁䅯杇䅁䅁䅯允䅁䅁䅯兂䅁䅁䅕䅁䅁䥁㉄唵䉁䅁䅁允䅁䅁䅕積積積積稴䴸䅉䅅䅁䙁䅁䅁睁䵁䅁䅁权䅁䅁䅁权呂䅁䅁权䙁䅁䅁兂䅁䅁䅁佉汐䅑䅅䅁䉁䅁䅁兂婁䙂余摌祉䅑杷允䅁䅁䅕䅁䑁䅁䅷䅁䭁䉁䄴䅁䭁䙁䅍䅁䭁䅁䅕䅁䙁䅁䅁䅁杂⭘䅚允䅁䅁䅅䅁䙁䩁瑈䑦ㄸ楘䅊䍄䉁䅁䅁䅂䅁䅁䅍䅄䅁䅁䅯睔䅁䅁䅯杔䅁䅁䅕䅁䅁䥁十欵䉁䅁䅁允䅁䅁䅕体㙆䭆䠵ぅ䵁䅉䅅䅁䕁䅁䅁睁䵁䅁䅁权偂䅁䅁权佂䅁䅁兂䅁䅁䅁䉁浺䅑䅅䅁䉁䅁䅁兂㥁瑃橥䑣儰䅑杷允䅁䅁䅕䅁䑁䅁䅷䅁䭁䉁䄰䅁䭁䙁䅍䅁䭁䅁䅕䅁䙁䅁䅁䅁䅁⭉䅚允䅁䅁䅅䅁䙁䅁塲㍯㥁楹䄵䍄䉁䅁䅁兂䅁䅁䅍䅄䅁䅁䅯杈䅁䅁䅯睕䅁䅁䅯兂䅁䅁䅕䅁䅁䅁杂欵䉁䅁䅁允䅁䅁䅕敫㠱穐敖歉䵁䅉䅅䅁䙁䅁䅁睁䵁䅁䅁权䅁䅁䅁权呂䅁䅁权䙁䅁䅁兂䅁䅁䅁䍧浪䅑䅅䅁䉁䅁䅁兂汄䌰扌含稴䅑杷允䅁䅁䅕䅁䑁䅁䅷䅁䭁䉁䄴䅁䭁䙁䅍䅁䭁䅁䅕䅁䙁䅁䅁䅁杄畤䅚允䅁䅁䅅䅁䙁䍁捬㡪ㅌ䍡䅆䍄䉁䅁䅁兂䅁䅁䅍䅄䅁䅁䅯杈䅁䅁䅯睕䅁䅁䅯兂䅁䅁䅕䅁䅁䍁乁欵䉁䅁䅁允䅁䅁䅕硢䑋䵷桲啋䵁䅉䅅䅁䕁䅁䅁睁䵁䅁䅁权偂䅁䅁权佂䅁䅁兂䅁䅁䅁䑁浌䅑䅅䅁䉁䅁䅁兂畃⭒㙆䭆刴䅑杷允䅁䅁䅑䅁䑁䅁䅷䅁䭁䕁䄸䅁䭁䕁䄴䅁䙁䅁䅁䅁䅂敗䅚允䅁䅁䅅䅁䙁偁潙䥘䌯儹䄵䍄䉁䅁䅁兂䅁䅁䅍䅄䅁䅁䅯䅁䅁䅁䅯睕䅁䅁䅯兂䅁䅁䅕䅁䅁佁汄唵䉁䅁䅁允䅁䅁䅕兇坒楄匳歍䵁䅉䅅䅁䙁䅁䅁睁䵁䅁䅁权捁䅁䅁权呂䅁䅁权䙁䅁䅁兂䅁䅁䅁䭑汔䅑䅅䅁䉁䅁䅁兂䉄煹䙆橴瑍䅑杷允䅁䅁䅑䅁䑁䅁䅷䅁䭁䕁䄸䅁䭁䕁䄴䅁䙁䅁䅁䅁杄敗䅚允䅁䅁䅅䅁䙁䙁偹癷潕䅘䄱䍄䉁䅁䅁兂䅁䅁䅍䅄䅁䅁䅯䅁䅁䅁䅯允䅁䅁䅯兂䅁䅁䅕䅁䅁䍁㉁欵䉁䅁䅁允䅁䅁䅕䉵䘶ㄶ㑇樳䴸䅉䅅䅁䕁䅁䅁睁䵁䅁䅁权偂䅁䅁权佂䅁䅁兂䅁䅁䅁䩧汲䅑䅅䅁䉁䅁䅁兂桄桥畓⭒䭈睐杷允䅁䅁䅕䅁䑁䅁䅷䅁䭁䅁䅁䅁䭁䙁䅍䅁䭁䅁䅕䅁䙁䅁䅁䅁杄佋䅚允䅁䅁䅅䅁䙁佁兘瑉㕶橐䅎䍄䉁䅁䅁䅂䅁䅁䅍䅄䅁䅁䅯睔䅁䅁䅯杔䅁䅁䅕䅁䅁佁㉂欵䉁䅁䅁允䅁䅁䅕噋偹癷潕䕄䵁䅉䅅䅁䙁䅁䅁睁䵁䅁䅁权敁䅁䅁权䉁䅁䅁权䙁䅁䅁兂䅁䅁䅁䭉汢䅑䅅䅁䉁䅁䅁兂穁積積積呐睐杷允䅁䅁䅑䅁䑁䅁䅷䅁䭁䕁䄸䅁䭁䕁䄴䅁䙁䅁䅁䅁䅂甸䅖允䅁䅁䅅䅁䙁䭁睒児塲睯䄵䍄䉁䅁䅁兂䅁䅁䅍䅄䅁䅁䅯先䅁䅁䅯睕䅁䅁䅯兂䅁䅁䅕䅁䅁䥁ㅂ欵䉁䅁䅁允䅁䅁䅕䬸䝦穓䩦啌䵁䅉䅅䅁䙁䅁䅁睁䵁䅁䅁权敁䅁䅁权䉁䅁䅁权䙁䅁䅁兂䅁䅁䅁偙氷䅑䅅䅁䉁䅁䅁兂㝂䭆䠵場啲睐杷允䅁䅁䅑䅁䑁䅁䅷䅁䭁䕁䄸䅁䭁䕁䄴䅁䙁䅁䅁䅁杁異䅖允䅁䅁䅅䅁䙁䵁ㅐ䙋偹瑷⽕䍄䉁䅁䅁兂䅁䅁䅍䅄䅁䅁䅯䅁䅁䅁䅯睕䅁䅁䅯兂䅁䅁䅕䅁䅁䭁㝁欵䉁䅁䅁允䅁䅁䅕䅁䅁䅁权き䵁䅉䅅䅁䙁䅁䅁睁䵁䅁䅁权摁䅁䅁权呂䅁䅁权䙁䅁䅁兂䅁䅁䅁䕷浪䅑䅅䅁䉁䅁䅁兂ㅂ硫䕧潖甴䅑杷允䅁䅁䅕䅁䑁䅁䅷䅁䭁䅁䅁䅁䭁䙁䅍䅁䭁䅁䅕䅁䙁䅁䅁䅁杂敭䅖允䅁䅁䅅䅁䙁䱁へ硫䕧橤䅂䍄䉁䅁䅁兂䅁䅁䅍䅄䅁䅁䅯睈䅁䅁䅯允䅁䅁䅯兂䅁䅁䅕䅁䅁䕁煁欵䉁䅁䅁允䅁䅁䅕体㙆䭆䠵吴䴸䅉䅅䅁䕁䅁䅁睁䵁䅁䅁权偂䅁䅁权佂䅁䅁兂䅁䅁䅁䐴浌䅑䅅䅁䉁䅁䅁兂乄䵺䵺䵺剷䅑杷允䅁䅁䅕䅁䑁䅁䅷䅁䭁䉁䄸䅁䭁䅁䅅䅁䭁䅁䅕䅁䙁䅁䅁䅁杄甫䅖允䅁䅁䅅䅁䙁䕁桪桥畓⭒⽅䍄䉁䅁䅁䅂䅁䅁䅍䅄䅁䅁䅯睔䅁䅁䅯杔䅁䅁䅕䅁䅁䍁奃唵䉁䅁䅁允䅁䅁䅕牕敧敨剴䑹䴸䅉䅅䅁䙁䅁䅁睁䵁䅁䅁权慁䅁䅁权呂䅁䅁权䙁䅁䅁兂䅁䅁䅁䕯浢䅑䅅䅁䉁䅁䅁兂䵂㑎䉬䕙㝕䅑杷允䅁䅁䅕䅁䑁䅁䅷䅁䭁䉁䅷䅁䭁䙁䅍䅁䭁䅁䅕䅁䙁䅁䅁䅁杂攱䅖允䅁䅁䅅䅁䙁䕁椵䙅㕧䍴䄵䍄䉁䅁䅁䅂䅁䅁䅍䅄䅁䅁䅯睔䅁䅁䅯杔䅁䅁䅕䅁䅁䅁㉂欵䉁䅁䅁允䅁䅁䅕椹捨㡪ㅌ䕄䵁䅉䅅䅁䙁䅁䅁睁䵁䅁䅁权捁䅁䅁权呂䅁䅁权䙁䅁䅁兂䅁䅁䅁佷汔䅑䅅䅁䉁䅁䅁兂楂䙅㕧䕴畧䅑杷允䅁䅁䅕䅁䑁䅁䅷䅁䭁䉁䄰䅁䭁䅁䅅䅁䭁䅁䅕䅁䙁䅁䅁䅁权⭊䅚允䅁䅁䅅䅁䙁䝁浚浚浚瑚⽙䍄䉁䅁䅁䅂䅁䅁䅍䅄䅁䅁䅯睔䅁䅁䅯杔䅁䅁䅕䅁䅁䥁偁欵䉁䅁䅁允䅁䅁䅕㡪ㅌ䙋偹歅䵁䅉䅅䅁䕁䅁䅁睁䵁䅁䅁权偂䅁䅁权佂䅁䅁兂䅁䅁䅁䡷浢䅑䅅䅁䉁䅁䅁兂㝂䭆䠵場䵯䅑杷允䅁䅁䅑䅁䑁䅁䅷䅁䭁䕁䄸䅁䭁䕁䄴䅁䙁䅁䅁䅁杄畡䅚允䅁䅁䅅䅁䙁䵁ㅐ䙋偹杷䅴䍄䉁䅁䅁兂䅁䅁䅍䅄䅁䅁䅯先䅁䅁䅯允䅁䅁䅯兂䅁䅁䅕䅁䅁䝁杄唵䉁䅁䅁允䅁䅁䅕㘱睎児塲稰䴸䅉䅅䅁䙁䅁䅁睁䵁䅁䅁权捁䅁䅁权䉁䅁䅁权䙁䅁䅁兂䅁䅁䅁䍁洯䅑䅅䅁䉁䅁䅁兂㉄䙋偹癷奘睐杷允䅁䅁䅕䅁䑁䅁䅷䅁䭁䉁䄴䅁䭁䙁䅍䅁䭁䅁䅕䅁䙁䅁䅁䅁䅃畓䅚允䅁䅁䅅䅁䙁佁㠵穐敖楏䅒䍄䉁䅁䅁兂䅁䅁䅍䅄䅁䅁䅯䅁䅁䅁䅯睕䅁䅁䅯兂䅁䅁䅕䅁䅁䍁㑄唵䉁䅁䅁允䅁䅁䅕噋偹癷潖歍䵁䅉䅅䅁䙁䅁䅁睁䵁䅁䅁权慁䅁䅁权呂䅁䅁权䙁䅁䅁兂䅁䅁䅁䡧浪䅑䅅䅁䉁䅁䅁兂䵂㑎䉬䍙㝕䅑杷允䅁䅁䅑䅁䑁䅁䅷䅁䭁䕁䄸䅁䭁䕁䄴䅁䙁䅁䅁䅁䅄伯䅖允䅁䅁䅅䅁䙁䭁睒児塲睯䄵䍄䉁䅁䅁兂䅁䅁䅍䅄䅁䅁䅯䅁䅁䅁䅯睕䅁䅁䅯兂䅁䅁䅕䅁䅁䕁⽁欵䉁䅁䅁允䅁䅁䅕䅁䅁䅁权き䵁䅉䅅䅁䙁䅁䅁睁䵁䅁䅁权䅁䅁䅁权䉁䅁䅁权䙁䅁䅁兂䅁䅁䅁偧汦䅑䅅䅁䉁䅁䅁兂㑃潈牘払敪睐杷允䅁䅁䅑䅁䑁䅁䅷䅁䭁䕁䄸䅁䭁䕁䄴䅁䙁䅁䅁䅁䅂畄䅚允䅁䅁䅅䅁䙁䕁桪桥畓硒䅊䍄䉁䅁䅁兂䅁䅁䅍䅄䅁䅁䅯先䅁䅁䅯睕䅁䅁䅯兂䅁䅁䅕䅁䅁佁坄唵䉁䅁䅁允䅁䅁䅕⽷潕䥘䌯啌䵁䅉䅅䅁䙁䅁䅁睁䵁䅁䅁权敁䅁䅁权呂䅁䅁权䙁䅁䅁兂䅁䅁䅁䠴洷䅑䅅䅁䉁䅁䅁兂灁䥘䌯圹桧䅑杷允䅁䅁䅕䅁䑁䅁䅷䅁䭁䅁䅁䅁䭁䅁䅅䅁䭁䅁䅕䅁䙁䅁䅁䅁权低䅚允䅁䅁䅅䅁䙁䱁敧敨剴乵⼴䍄䉁䅁䅁兂䅁䅁䅍䅄䅁䅁䅯䅁䅁䅁䅯允䅁䅁䅯兂䅁䅁䅕䅁䅁佁㥂欵䉁䅁䅁允䅁䅁䅕䉵䘶ㄶ㑇樳䴸䅉䅅䅁䙁䅁䅁睁䵁䅁䅁权慁䅁䅁权呂䅁䅁权䙁䅁䅁兂䅁䅁䅁佧汦䅑䅅䅁䉁䅁䅁兂䑄匹捨⭪㕉䅑杷允䅁䅁䅕䅁䑁䅁䅷䅁䭁䅁䅁䅁䭁䙁䅍䅁䭁䅁䅕䅁䙁䅁䅁䅁䅄敭䅖允䅁䅁䅅䅁䙁乁橥䑣䬰稹䅂䍄䉁䅁䅁䅂䅁䅁䅍䅄䅁䅁䅯睔䅁䅁䅯杔䅁䅁䅕䅁䅁䕁灂欵䉁䅁䅁允䅁䅁䅕䡰㥁瑃橥䕄䵁䅉䅅䅁䙁䅁䅁睁䵁䅁䅁权䅁䅁䅁权䉁䅁䅁权䙁䅁䅁兂䅁䅁䅁义氷䅑䅅䅁䉁䅁䅁兂桄桥畓⭒慈睐杷允䅁䅁䅑䅁䑁䅁䅷䅁䭁䕁䄸䅁䭁䕁䄴䅁䙁䅁䅁䅁杂畤䅚允䅁䅁䅅䅁䙁䭁睒児塲睯䅸䍄䉁䅁䅁䅂䅁䅁䅍䅄䅁䅁䅯睔䅁䅁䅯杔䅁䅁䅕䅁䅁䅁牃唵䉁䅁䅁允䅁䅁䅕䭆䠵場啯樳䴸䅉䅅䅁䙁䅁䅁睁䵁䅁䅁权䅁䅁䅁权䉁䅁䅁权䙁䅁䅁兂䅁䅁䅁䍯浔䅑䅅䅁䉁䅁䅁兂㑃潈牘払敪睐杷允䅁䅁䅑䅁䑁䅁䅷䅁䭁䕁䄸䅁䭁䕁䄴䅁䙁䅁䅁䅁䅂但䅚允䅁䅁䅅䅁䙁䅁塲㍯㥁桃䅒䍄䉁䅁䅁兂䅁䅁䅍䅄䅁䅁䅯杇䅁䅁䅯睕䅁䅁䅯兂䅁䅁䅕䅁䅁䵁䑁欵䉁䅁䅁允䅁䅁䅕牒穢搯契歏䵁䅉䅅䅁䙁䅁䅁睁䵁䅁䅁权敁䅁䅁权䉁䅁䅁权䙁䅁䅁兂䅁䅁䅁佯氯䅑䅅䅁䉁䅁䅁兂穁積積積呐睐杷允䅁䅁䅑䅁䑁䅁䅷䅁䭁䕁䄸䅁䭁䕁䄴䅁䙁䅁䅁䅁䅂低䅚允䅁䅁䅅䅁䙁䙁㑋潈牘剕䅊䍄䉁䅁䅁兂䅁䅁䅍䅄䅁䅁䅯杈䅁䅁䅯睕䅁䅁䅯兂䅁䅁䅕䅁䅁䅁塁欵䉁䅁䅁允䅁䅁䅕兇坒楄礱啋䵁䅉䅅䅁䙁䅁䅁睁䵁䅁䅁权捁䅁䅁权䉁䅁䅁权䙁䅁䅁兂䅁䅁䅁䩙汘䅑䅅䅁䉁䅁䅁兂偃癷潕䥘匯睐杷允䅁䅁䅕䅁䑁䅁䅷䅁䭁䉁䅷䅁䭁䙁䅍䅁䭁䅁䅕䅁䙁䅁䅁䅁杁佔䅚允䅁䅁䅅䅁䙁䝁匸㡧䭄卙䄵䍄䉁䅁䅁兂䅁䅁䅍䅄䅁䅁䅯䅁䅁䅁䅯睕䅁䅁䅯兂䅁䅁䅕䅁䅁䕁㙂欵䉁䅁䅁允䅁䅁䅕佖汏㡭䅑䕎䵁䅉䅅䅁䙁䅁䅁睁䵁䅁䅁权晁䅁䅁权呂䅁䅁权䙁䅁䅁兂䅁䅁䅁䵑氷䅑䅅䅁䉁䅁䅁兂䭂䅄牉㥨睙䅑杷允䅁䅁䅕䅁䑁䅁䅷䅁䭁䉁䄴䅁䭁䙁䅍䅁䭁䅁䅕䅁䙁䅁䅁䅁䅃佥䅚允䅁䅁䅅䅁䙁䍁捬㡪ㅌ䍡䅆䍄䉁䅁䅁䅂䅁䅁䅍䅄䅁䅁䅯睔䅁䅁䅯杔䅁䅁䅕䅁䅁䝁䑂欵䉁䅁䅁允䅁䅁䅕㡪ㅌ䙋偹䕅䵁䅉䅅䅁䙁䅁䅁睁䵁䅁䅁权䅁䅁䅁权呂䅁䅁权䙁䅁䅁兂䅁䅁䅁䉑洯䅑䅅䅁䉁䅁䅁兂療潅䅐杹穅䅑杷允䅁䅁䅕䅁䑁䅁䅷䅁䭁䉁䄰䅁䭁䙁䅍䅁䭁䅁䅕䅁䙁䅁䅁䅁䅁⭺䅖允䅁䅁䅅䅁䙁䍁捬㡪ㅌ䍋䄵䍄䉁䅁䅁兂䅁䅁䅍䅄䅁䅁䅯䅁䅁䅁䅯允䅁䅁䅯兂䅁䅁䅕䅁䅁佁㝄唵䉁䅁䅁允䅁䅁䅕䉵䘶ㄶ㑇樳䴸䅉䅅䅁䙁䅁䅁睁䵁䅁䅁权䅁䅁䅁权呂䅁䅁权䙁䅁䅁兂䅁䅁䅁䡯浪䅑䅅䅁䉁䅁䅁兂啂㘴扗䅸ぁ䅑杷允䅁䅁䅕䅁䑁䅁䅷䅁䭁䉁䄸䅁䭁䙁䅍䅁䭁䅁䅕䅁䙁䅁䅁䅁权畚䅚允䅁䅁䅅䅁䙁䅁塲㍯㥁橋䅆䍄䉁䅁䅁兂䅁䅁䅍䅄䅁䅁䅯杈䅁䅁䅯睕䅁䅁䅯兂䅁䅁䅕䅁䅁䕁䵂欵䉁䅁䅁允䅁䅁䅕渷⽷噎㘴䕊䵁䅉䅅䅁䕁䅁䅁睁䵁䅁䅁权偂䅁䅁权佂䅁䅁兂䅁䅁䅁䕑浐䅑䅅䅁䉁䅁䅁兂卂䉵䘶ㄶ充䅑杷允䅁䅁䅕䅁䑁䅁䅷䅁䭁䉁䄰䅁䭁䅁䅅䅁䭁䅁䅕䅁䙁䅁䅁䅁䅁⭬䅖允䅁䅁䅅䅁䙁乁橥䑣䬰㤱⽍䍄䉁䅁䅁兂䅁䅁䅍䅄䅁䅁䅯䅁䅁䅁䅯允䅁䅁䅯兂䅁䅁䅕䅁䅁䭁㝄唵䉁䅁䅁允䅁䅁䅕䉵䘶ㄶ㑇樳䴸䅉䅅䅁䙁䅁䅁睁䵁䅁䅁权摁䅁䅁权䉁䅁䅁权䙁䅁䅁兂䅁䅁䅁余汢䅑䅅䅁䉁䅁䅁兂塄㍯㥁瑃呦睐杷允䅁䅁䅕䅁䑁䅁䅷䅁䭁䉁䄰䅁䭁䙁䅍䅁䭁䅁䅕䅁䙁䅁䅁䅁杂畎䅚允䅁䅁䅅䅁䙁䙁余扌摋礷䄵䍄䉁䅁䅁兂䅁䅁䅍䅄䅁䅁䅯䅁䅁䅁䅯睕䅁䅁䅯兂䅁䅁䅕䅁䅁䕁療欵䉁䅁䅁允䅁䅁䅕佖汏㡭杔き䵁䅉䅅䅁䕁䅁䅁睁䵁䅁䅁权偂䅁䅁权佂䅁䅁兂䅁䅁䅁偙汦䅑䅅䅁䉁䅁䅁兂䙃ㄶ㑇潈单䅑杷允䅁䅁䅕䅁䑁䅁䅷䅁䭁䅁䅁䅁䭁䅁䅅䅁䭁䅁䅕䅁䙁䅁䅁䅁䅃⬷䅖允䅁䅁䅅䅁䙁䥁牘払敧摨⽳䍄䉁䅁䅁兂䅁䅁䅍䅄䅁䅁䅯杇䅁䅁䅯允䅁䅁䅯兂䅁䅁䅕䅁䅁䕁潂欵䉁䅁䅁允䅁䅁䅕䡰㥁瑃橥䐶䴸䅉䅅䅁䙁䅁䅁睁䵁䅁䅁权捁䅁䅁权呂䅁䅁权䙁䅁䅁兂䅁䅁䅁䑉浄䅑䅅䅁䉁䅁䅁兂奂扏䥔橤甴䅑杷允䅁䅁䅕䅁䑁䅁䅷䅁䭁䉁䅷䅁䭁䙁䅍䅁䭁䅁䅕䅁䙁䅁䅁䅁䅃畏䅚允䅁䅁䅅䅁䙁䉁婦発呤祯䄵䍄䉁䅁䅁䅂䅁䅁䅍䅄䅁䅁䅯睔䅁䅁䅯杔䅁䅁䅕䅁䅁䝁婂欵䉁䅁䅁允䅁䅁䅕浚浚浚浚歄䵁䅉䅅䅁䙁䅁䅁睁䵁䅁䅁权敁䅁䅁权呂䅁䅁权䙁䅁䅁兂䅁䅁䅁乷汪䅑䅅䅁䉁䅁䅁兂汁潂噇㑑獳䅑杷允䅁䅁䅑䅁䑁䅁䅷䅁䭁䕁䄸䅁䭁䕁䄴䅁䙁䅁䅁䅁权⭙䅚允䅁䅁䅅䅁䙁䡁㥅瑃橥䅣䄹䍄䉁䅁䅁兂䅁䅁䅍䅄䅁䅁䅯杇䅁䅁䅯允䅁䅁䅯兂䅁䅁䅕䅁䅁䭁牁欵䉁䅁䅁允䅁䅁䅕䡰㥁瑃橥䐶䴸䅉䅅䅁䙁䅁䅁睁䵁䅁䅁权摁䅁䅁权呂䅁䅁权䙁䅁䅁兂䅁䅁䅁䉙浮䅑䅅䅁䉁䅁䅁兂䭁㘱睎捐畯䅑杷允䅁䅁䅑䅁䑁䅁䅷䅁䭁䕁䄸䅁䭁䕁䄴䅁䙁䅁䅁䅁䅂畤䅚允䅁䅁䅅䅁䙁䝁浚浚浚杚䅸䍄䉁䅁䅁兂䅁䅁䅍䅄䅁䅁䅯杈䅁䅁䅯睕䅁䅁䅯兂䅁䅁䅕䅁䅁䍁睁欵䉁䅁䅁允䅁䅁䅕体㙆䭆䠵歊䵁䅉䅅䅁䕁䅁䅁睁䵁䅁䅁权偂䅁䅁权佂䅁䅁兂䅁䅁䅁乑汮䅑䅅䅁䉁䅁䅁兂乄䵺䵺䵺䝷䅑杷允䅁䅁䅑䅁䑁䅁䅷䅁䭁䕁䄸䅁䭁䕁䄴䅁䙁䅁䅁䅁䅃余䅚允䅁䅁䅅䅁䙁佁㙆䭆䠵儴䄵䍄䉁䅁䅁䅂䅁䅁䅍䅄䅁䅁䅯睔䅁䅁䅯
A3: 杔䅁䅁䅕䅁䅁䝁求欵䉁䅁䅁允䅁䅁䅕㡪ㅌ䙋偹歄䵁䅉䅅䅁䕁䅁䅁睁䵁䅁䅁权偂䅁䅁权佂䅁䅁兂䅁䅁䅁䠴浘䅑䅅䅁䉁䅁䅁兂㑃潈牘払䵧䅑杷允䅁䅁䅕䅁䑁䅁䅷䅁䭁䉁䅯䅁䭁䅁䅅䅁䭁䅁䅕䅁䙁䅁䅁䅁杁教䅚允䅁䅁䅅䅁䙁䭁睒児塲⭯⽧䍄䉁䅁䅁兂䅁䅁䅍䅄䅁䅁䅯先䅁䅁䅯睕䅁䅁䅯兂䅁䅁䅕䅁䅁䵁偄唵䉁䅁䅁允䅁䅁䅕噋偹癷潕歌䵁䅉䅅䅁䕁䅁䅁睁䵁䅁䅁权偂䅁䅁权佂䅁䅁兂䅁䅁䅁䈴浔䅑䅅䅁䉁䅁䅁兂歃䑣䬰㘱呍䅑杷允䅁䅁䅑䅁䑁䅁䅷䅁䭁䕁䄸䅁䭁䕁䄴䅁䙁䅁䅁䅁䅃敤䅚允䅁䅁䅅䅁䙁䱁敧敨剴䅵䅸䍄䉁䅁䅁兂䅁䅁䅍䅄䅁䅁䅯䅁䅁䅁䅯允䅁䅁䅯兂䅁䅁䅕䅁䅁䭁噂欵䉁䅁䅁允䅁䅁䅕䉵䘶ㄶ㑇樳䴸䅉䅅䅁䕁䅁䅁睁䵁䅁䅁权偂䅁䅁权佂䅁䅁兂䅁䅁䅁䑯洯䅑䅅䅁䉁䅁䅁兂歃䑣䬰㘱䵍䅑杷允䅁䅁䅕䅁䑁䅁䅷䅁䭁䅁䅁䅁䭁䅁䅅䅁䭁䅁䅕䅁䙁䅁䅁䅁䅁⭗䅚允䅁䅁䅅䅁䙁䱁敧敨剴乵⼴䍄䉁䅁䅁䅂䅁䅁䅍䅄䅁䅁䅯睔䅁䅁䅯杔䅁䅁䅕䅁䅁䝁浄唵䉁䅁䅁允䅁䅁䅕捺䵺䵺䵺啅䵁䅉䅅䅁䕁䅁䅁睁䵁䅁䅁权偂䅁䅁权佂䅁䅁兂䅁䅁䅁䝯浲䅑䅅䅁䉁䅁䅁兂塄㍯㥁瑃䱣䅑杷允䅁䅁䅕䅁䑁䅁䅷䅁䭁䉁䄰䅁䭁䅁䅅䅁䭁䅁䅕䅁䙁䅁䅁䅁䅄⭆䅚允䅁䅁䅅䅁䙁䉁䘫ㄶ㑇瑈⽕䍄䉁䅁䅁䅂䅁䅁䅍䅄䅁䅁䅯睔䅁䅁䅯杔䅁䅁䅕䅁䅁䅁睁欵䉁䅁䅁允䅁䅁䅕䅁䅁䅁䅁ぅ䵁䅉䅅䅁䙁䅁䅁睁䵁䅁䅁权䅁䅁䅁权䉁䅁䅁权䙁䅁䅁兂䅁䅁䅁䭯汦䅑䅅䅁䉁䅁䅁兂慃婭婭婭婮睐杷允䅁䅁䅕䅁䑁䅁䅷䅁䭁䉁䄸䅁䭁䙁䅍䅁䭁䅁䅕䅁䙁䅁䅁䅁杂⭈䅚允䅁䅁䅅䅁䙁䕁㉡⼸唳䐫䅂䍄䉁䅁䅁兂䅁䅁䅍䅄䅁䅁䅯先䅁䅁䅯睕䅁䅁䅯兂䅁䅁䅕䅁䅁䕁潄唵䉁䅁䅁允䅁䅁䅕䉵䘶ㄶ㑈䕌䵁䅉䅅䅁䕁䅁䅁睁䵁䅁䅁权偂䅁䅁权佂䅁䅁兂䅁䅁䅁䡁浌䅑䅅䅁䉁䅁䅁兂偃癷潕䥘䴸䅑杷允䅁䅁䅕䅁䑁䅁䅷䅁䭁䅁䅁䅁䭁䅁䅅䅁䭁䅁䅕䅁䙁䅁䅁䅁杁佑䅚允䅁䅁䅅䅁䙁䱁敧敨剴乵⼴䍄䉁䅁䅁兂䅁䅁䅍䅄䅁䅁䅯䅁䅁䅁䅯睕䅁䅁䅯兂䅁䅁䅕䅁䅁䅁㡃唵䉁䅁䅁允䅁䅁䅕䘫橐婰䕵歍䵁䅉䅅䅁䙁䅁䅁睁䵁䅁䅁权䅁䅁䅁权呂䅁䅁权䙁䅁䅁兂䅁䅁䅁䙑浐䅑䅅䅁䉁䅁䅁兂㕁䵴㉨瑶稸䅑杷允䅁䅁䅑䅁䑁䅁䅷䅁䭁䕁䄸䅁䭁䕁䄴䅁䙁䅁䅁䅁杁⭸䅖允䅁䅁䅅䅁䙁䵁ㅐ䙋偹癷⽫䍄䉁䅁䅁兂䅁䅁䅍䅄䅁䅁䅯杇䅁䅁䅯睕䅁䅁䅯兂䅁䅁䅕䅁䅁䭁㝃唵䉁䅁䅁允䅁䅁䅕穐敖歵獮問䵁䅉䅅䅁䙁䅁䅁睁䵁䅁䅁权晁䅁䅁权呂䅁䅁权䙁䅁䅁兂䅁䅁䅁䕁浄䅑䅅䅁䉁䅁䅁兂㍁啩杆吵硁䅑杷允䅁䅁䅑䅁䑁䅁䅷䅁䭁䕁䄸䅁䭁䕁䄴䅁䙁䅁䅁䅁䅄敏䅚允䅁䅁䅅䅁䙁䉁畓⭒㙆䅆䄵䍄䉁䅁䅁兂䅁䅁䅍䅄䅁䅁䅯䅁䅁䅁䅯睕䅁䅁䅯兂䅁䅁䅕䅁䅁䕁㍄唵䉁䅁䅁允䅁䅁䅕噋偹癷潖歍䵁䅉䅅䅁䕁䅁䅁睁䵁䅁䅁权偂䅁䅁权佂䅁䅁兂䅁䅁䅁䑉浈䅑䅅䅁䉁䅁䅁兂㉄䙋偹癷剕䅑杷允䅁䅁䅕䅁䑁䅁䅷䅁䭁䉁䄴䅁䭁䙁䅍䅁䭁䅁䅕䅁䙁䅁䅁䅁杄畹䅖允䅁䅁䅅䅁䙁䍁䡵瑆佮祴䅸䍄䉁䅁䅁兂䅁䅁䅍䅄䅁䅁䅯杇䅁䅁䅯睕䅁䅁䅯兂䅁䅁䅕䅁䅁䝁牂欵䉁䅁䅁允䅁䅁䅕㥌欰潂噆く䵁䅉䅅䅁䙁䅁䅁睁䵁䅁䅁权䅁䅁䅁权䉁䅁䅁权䙁䅁䅁兂䅁䅁䅁䭁汦䅑䅅䅁䉁䅁䅁兂慃婭婭婭婮睐杷允䅁䅁䅕䅁䑁䅁䅷䅁䭁䅁䅁䅁䭁䙁䅍䅁䭁䅁䅕䅁䙁䅁䅁䅁杂佐䅚允䅁䅁䅅䅁䙁䅁䅁䅁䅁䑯䅎䍄䉁䅁䅁䅂䅁䅁䅍䅄䅁䅁䅯睔䅁䅁䅯杔䅁䅁䅕䅁䅁䝁䵂欵䉁䅁䅁允䅁䅁䅕㘱睎児塲啅䵁䅉䅅䅁䙁䅁䅁睁䵁䅁䅁权摁䅁䅁权䉁䅁䅁权䙁䅁䅁兂䅁䅁䅁䴴汌䅑䅅䅁䉁䅁䅁兂塄㍯㥁瑃呦睐杷允䅁䅁䅕䅁䑁䅁䅷䅁䭁䅁䅁䅁䭁䅁䅅䅁䭁䅁䅕䅁䙁䅁䅁䅁䅄⭋䅚允䅁䅁䅅䅁䙁䱁敧敨剴乵⼴䍄䉁䅁䅁兂䅁䅁䅍䅄䅁䅁䅯先䅁䅁䅯睕䅁䅁䅯兂䅁䅁䅕䅁䅁䕁祄唵䉁䅁䅁允䅁䅁䅕灰䕶䱉祃啌䵁䅉䅅䅁䙁䅁䅁睁䵁䅁䅁权䅁䅁䅁权呂䅁䅁权䙁䅁䅁兂䅁䅁䅁䙯浪䅑䅅䅁䉁䅁䅁兂㕁䵴㉨瑶稸䅑杷允䅁䅁䅑䅁䑁䅁䅷䅁䭁䕁䄸䅁䭁䕁䄴䅁䙁䅁䅁䅁䅂敤䅚允䅁䅁䅅䅁䙁䅁䅁䅁䅁䅁䅸䍄䉁䅁䅁兂䅁䅁䅍䅄䅁䅁䅯杈䅁䅁䅯睕䅁䅁䅯兂䅁䅁䅕䅁䅁䥁奂欵䉁䅁䅁允䅁䅁䅕⼲⭬牡へ歉䵁䅉䅅䅁䙁䅁䅁睁䵁䅁䅁权敁䅁䅁权呂䅁䅁权䙁䅁䅁兂䅁䅁䅁䕯浪䅑䅅䅁䉁䅁䅁兂畄䑦ㄸ橘歯䅑杷允䅁䅁䅑䅁䑁䅁䅷䅁䭁䕁䄸䅁䭁䕁䄴䅁䙁䅁䅁䅁䅂敳䅖允䅁䅁䅅䅁䙁䥁牘払敧摨⽳䍄䉁䅁䅁兂䅁䅁䅍䅄䅁䅁䅯䅈䅁䅁䅯允䅁䅁䅯兂䅁䅁䅕䅁䅁䵁偁欵䉁䅁䅁允䅁䅁䅕㑈牘払敧吱䴸䅉䅅䅁䙁䅁䅁睁䵁䅁䅁权摁䅁䅁权呂䅁䅁权䙁䅁䅁兂䅁䅁䅁䑙浘䅑䅅䅁䉁䅁䅁兂坂楄礲敮甸䅑杷允䅁䅁䅑䅁䑁䅁䅷䅁䭁䕁䄸䅁䭁䕁䄴䅁䙁䅁䅁䅁权攫䅖允䅁䅁䅅䅁䙁䍁捬㡪ㅌ䅋䄵䍄䉁䅁䅁䅂䅁䅁䅍䅄䅁䅁䅯睔䅁䅁䅯杔䅁䅁䅕䅁䅁䵁䍁欵䉁䅁䅁允䅁䅁䅕㘱睎児塲い䵁䅉䅅䅁䙁䅁䅁睁䵁䅁䅁权摁䅁䅁权䉁䅁䅁权䙁䅁䅁兂䅁䅁䅁䬴決䅑䅅䅁䉁䅁䅁兂塄㍯㥁瑃呦睐杷允䅁䅁䅕䅁䑁䅁䅷䅁䭁䅁䅁䅁䭁䙁䅍䅁䭁䅁䅕䅁䙁䅁䅁䅁䅁畁䅚允䅁䅁䅅䅁䙁䭁硲欰椱䑣䅊䍄䉁䅁䅁兂䅁䅁䅍䅄䅁䅁䅯杇䅁䅁䅯睕䅁䅁䅯兂䅁䅁䅕䅁䅁䵁䭁欵䉁䅁䅁允䅁䅁䅕牒穢搯契歏䵁䅉䅅䅁䕁䅁䅁睁䵁䅁䅁权偂䅁䅁权佂䅁䅁兂䅁䅁䅁䱷汘䅑䅅䅁䉁䅁䅁兂㉄䙋偹癷杘睐杷允䅁䅁䅕䅁䑁䅁䅷䅁䭁䉁䅯䅁䭁䅁䅅䅁䭁䅁䅕䅁䙁䅁䅁䅁䅁伳䅖允䅁䅁䅅䅁䙁偁潙䥘䌯改⽁䍄䉁䅁䅁兂䅁䅁䅍䅄䅁䅁䅯杈䅁䅁䅯睕䅁䅁䅯兂䅁䅁䅕䅁䅁䭁㕁欵䉁䅁䅁允䅁䅁䅕倹唳佥浬䕊䵁䅉䅅䅁䕁䅁䅁睁䵁䅁䅁权偂䅁䅁权佂䅁䅁兂䅁䅁䅁䅉浪䅑䅅䅁䉁䅁䅁兂浂浚浚浚剙䅑杷允䅁䅁䅕䅁䑁䅁䅷䅁䭁䉁䄸䅁䭁䙁䅍䅁䭁䅁䅕䅁䙁䅁䅁䅁权⬱䅖允䅁䅁䅅䅁䙁䉁癳匳䝑吴䅂䍄䉁䅁䅁兂䅁䅁䅍䅄䅁䅁䅯䅁䅁䅁䅯允䅁䅁䅯兂䅁䅁䅕䅁䅁䭁敂欵䉁䅁䅁允䅁䅁䅕䉵䘶ㄶ㑇樳䴸䅉䅅䅁䙁䅁䅁睁䵁䅁䅁权摁䅁䅁权䉁䅁䅁权䙁䅁䅁兂䅁䅁䅁䙙浪䅑䅅䅁䉁䅁䅁兂畃⭒㙆䭆堷睐杷允䅁䅁䅑䅁䑁䅁䅷䅁䭁䕁䄸䅁䭁䕁䄴䅁䙁䅁䅁䅁䅄救䅚允䅁䅁䅅䅁䙁䉁䘫ㄶ㑇杈䄹䍄䉁䅁䅁兂䅁䅁䅍䅄䅁䅁䅯杇䅁䅁䅯允䅁䅁䅯兂䅁䅁䅕䅁䅁䥁獄唵䉁䅁䅁允䅁䅁䅕積積積積稴䴸䅉䅅䅁䕁䅁䅁睁䵁䅁䅁权偂䅁䅁权佂䅁䅁兂䅁䅁䅁䕯浪䅑䅅䅁䉁䅁䅁兂捂㡪ㅌ䙋具䅑杷允䅁䅁䅕䅁䑁䅁䅷䅁䭁䉁䄴䅁䭁䅁䅅䅁䭁䅁䅕䅁䙁䅁䅁䅁杄但䅚允䅁䅁䅅䅁䙁䵁ㅐ䙋偹瑷⽕䍄䉁䅁䅁兂䅁䅁䅍䅄䅁䅁䅯䅈䅁䅁䅯允䅁䅁䅯兂䅁䅁䅕䅁䅁䥁⽃唵䉁䅁䅁允䅁䅁䅕㡪ㅌ䙋偹樰䴸䅉䅅䅁䙁䅁䅁睁䵁䅁䅁权敁䅁䅁权䉁䅁䅁权䙁䅁䅁兂䅁䅁䅁䤴浄䅑䅅䅁䉁䅁䅁兂䅁䅁䅁䅁兄睐杷允䅁䅁䅕䅁䑁䅁䅷䅁䭁䉁䅯䅁䭁䙁䅍䅁䭁䅁䅕䅁䙁䅁䅁䅁䅃敧䅚允䅁䅁䅅䅁䙁䡁灮橊䥅䐷䅰䍄䉁䅁䅁兂䅁䅁䅍䅄䅁䅁䅯杈䅁䅁䅯允䅁䅁䅯兂䅁䅁䅕䅁䅁䕁㉃唵䉁䅁䅁允䅁䅁䅕積積積積稰䴸䅉䅅䅁䙁䅁䅁睁䵁䅁䅁权敁䅁䅁权䉁䅁䅁权䙁䅁䅁兂䅁䅁䅁䵙汄䅑䅅䅁䉁䅁䅁兂穁積積積呐睐杷允䅁䅁䅑䅁䑁䅁䅷䅁䭁䕁䄸䅁䭁䕁䄴䅁䙁䅁䅁䅁权佤䅚允䅁䅁䅅䅁䙁佁剸䉵䘶眶䅴䍄䉁䅁䅁兂䅁䅁䅍䅄䅁䅁䅯杈䅁䅁䅯允䅁䅁䅯兂䅁䅁䅕䅁䅁䅁䉄唵䉁䅁䅁允䅁䅁䅕積積積積稰䴸䅉䅅䅁䙁䅁䅁睁䵁䅁䅁权晁䅁䅁权䉁䅁䅁权䙁䅁䅁兂䅁䅁䅁䍧浢䅑䅅䅁䉁䅁䅁兂䥂場啯歲桦睐杷允䅁䅁䅕䅁䑁䅁䅷䅁䭁䅁䅁䅁䭁䅁䅅䅁䭁䅁䅕䅁䙁䅁䅁䅁䅄敁䅚允䅁䅁䅅䅁䙁䱁敧敨剴乵⼴䍄䉁䅁䅁兂䅁䅁䅍䅄䅁䅁䅯䅈䅁䅁䅯允䅁䅁䅯兂䅁䅁䅕䅁䅁䅁睁欵䉁䅁䅁允䅁䅁䅕椹捨㡪ㅌ䐲䴸䅉䅅䅁䕁䅁䅁睁䵁䅁䅁权偂䅁䅁权佂䅁䅁兂䅁䅁䅁䉙浌䅑䅅䅁䉁䅁䅁兂浂浚浚浚呙䅑杷允䅁䅁䅕䅁䑁䅁䅷䅁䭁䉁䅷䅁䭁䅁䅅䅁䭁䅁䅕䅁䙁䅁䅁䅁䅁敖䅚允䅁䅁䅅䅁䙁偁潙䥘䌯搹⽧䍄䉁䅁䅁兂䅁䅁䅍䅄䅁䅁䅯先䅁䅁䅯睕䅁䅁䅯兂䅁䅁䅕䅁䅁䍁㙃唵䉁䅁䅁允䅁䅁䅕瑃橥䑣䬳啌䵁䅉䅅䅁䕁䅁䅁睁䵁䅁䅁权偂䅁䅁权佂䅁䅁兂䅁䅁䅁䡉浘䅑䅅䅁䉁䅁䅁兂卂䉵䘶ㄶ䵅䅑杷允䅁䅁䅕䅁䑁䅁䅷䅁䭁䉁䅯䅁䭁䅁䅅䅁䭁䅁䅕䅁䙁䅁䅁䅁杂⭔䅚允䅁䅁䅅䅁䙁䭁睒児塲⭯⽧䍄䉁䅁䅁䅂䅁䅁䅍䅄䅁䅁䅯睔䅁䅁䅯杔䅁䅁䅕䅁䅁䍁䝁欵䉁䅁䅁允䅁䅁䅕体㙆䭆䠵啅䵁䅉䅅䅁䕁䅁䅁睁䵁䅁䅁权偂䅁䅁权佂䅁䅁兂䅁䅁䅁䡙浔䅑䅅䅁䉁䅁䅁兂䑄匹捨㡪䱉䅑杷允䅁䅁䅕䅁䑁䅁䅷䅁䭁䉁䅯䅁䭁䙁䅍䅁䭁䅁䅕䅁䙁䅁䅁䅁权⭔䅚允䅁䅁䅅䅁䙁䕁㍷啩杆呒䅴䍄䉁䅁䅁兂䅁䅁䅍䅄䅁䅁䅯杈䅁䅁䅯允䅁䅁䅯兂䅁䅁䅕䅁䅁䥁㥄唵䉁䅁䅁允䅁䅁䅕硥畓⭒㙆䐱䴸䅉䅅䅁䙁䅁䅁睁䵁䅁䅁权摁䅁䅁权呂䅁䅁权䙁䅁䅁兂䅁䅁䅁䭉汲䅑䅅䅁䉁䅁䅁兂婄発呤㘴瑕䅑杷允䅁䅁䅕䅁䑁䅁䅷䅁䭁䉁䄸䅁䭁䅁䅅䅁䭁䅁䅕䅁䙁䅁䅁䅁杂何䅚允䅁䅁䅅䅁䙁䭁睒児塲⭯⽁䍄䉁䅁䅁䅂䅁䅁䅍䅄䅁䅁䅯睔䅁䅁䅯杔䅁䅁䅕䅁䅁䝁桄唵䉁䅁䅁允䅁䅁䅕䅁䅁䅁䅁䕄䵁䅉䅅䅁䙁䅁䅁睁䵁䅁䅁权䅁䅁䅁权呂䅁䅁权䙁䅁䅁兂䅁䅁䅁䝑浈䅑䅅䅁䉁䅁䅁兂煃搸乊瑙穁䅑杷允䅁䅁䅕䅁䑁䅁䅷䅁䭁䉁䄰䅁䭁䅁䅅䅁䭁䅁䅕䅁䙁䅁䅁䅁䅂伸䅖允䅁䅁䅅䅁䙁乁橥䑣䬰㤱⽍䍄䉁䅁䅁䅂䅁䅁䅍䅄䅁䅁䅯睔䅁䅁䅯杔䅁䅁䅕䅁䅁䥁畃唵䉁䅁䅁允䅁䅁䅕歲桦桥畓稱䴸䅉䅅䅁䙁䅁䅁睁䵁䅁䅁权䅁䅁䅁权䉁䅁䅁权䙁䅁䅁兂䅁䅁䅁䑑浦䅑䅅䅁䉁䅁䅁兂㑃潈牘払敪睐杷允䅁䅁䅕䅁䑁䅁䅷䅁䭁䉁䄰䅁䭁䅁䅅䅁䭁䅁䅕䅁䙁䅁䅁䅁䅄畷䅖允䅁䅁䅅䅁䙁乁橥䑣䬰㤱⽍䍄䉁䅁䅁兂䅁䅁䅍䅄䅁䅁䅯杈䅁䅁䅯睕䅁䅁䅯兂䅁䅁䅕䅁䅁佁兄唵䉁䅁䅁允䅁䅁䅕㑋坣挲㌶䕌䵁䅉䅅䅁䙁䅁䅁睁䵁䅁䅁权敁䅁䅁权呂䅁䅁权䙁䅁䅁兂䅁䅁䅁䕉浔䅑䅅䅁䉁䅁䅁兂い搯㑒圶歙䅑杷允䅁䅁䅕䅁䑁䅁䅷䅁䭁䅁䅁䅁䭁䅁䅅䅁䭁䅁䅕䅁䙁䅁䅁䅁䅄畦䅚允䅁䅁䅅䅁䙁䱁敧敨剴乵⼴䍄䉁䅁䅁兂䅁䅁䅍䅄䅁䅁䅯䅁䅁䅁䅯睕䅁䅁䅯兂䅁䅁䅕䅁䅁䅁䝁欵䉁䅁䅁允䅁䅁䅕癱午坔睊歍䵁䅉䅅䅁䙁䅁䅁睁䵁䅁䅁权晁䅁䅁权䉁䅁䅁权䙁䅁䅁兂䅁䅁䅁䩧汮䅑䅅䅁䉁䅁䅁兂卂䉵䘶ㄶ杈睐杷允䅁䅁䅕䅁䑁䅁䅷䅁䭁䅁䅁䅁䭁䙁䅍䅁䭁䅁䅕䅁䙁䅁䅁䅁权⭡䅚允䅁䅁䅅䅁䙁䙁橔婰䕶䐴䅎䍄䉁䅁䅁兂䅁䅁䅍䅄䅁䅁䅯先䅁䅁䅯睕䅁䅁䅯兂䅁䅁䅕䅁䅁佁允欵䉁䅁䅁允䅁䅁䅕歵䵫楁䡵歌䵁䅉䅅䅁䕁䅁䅁睁䵁䅁䅁权偂䅁䅁权佂䅁䅁兂䅁䅁䅁䱙決䅑䅅䅁䉁䅁䅁兂塄㍯㥁瑃牦睐杷允䅁䅁䅕䅁䑁䅁䅷䅁䭁䉁䅯䅁䭁䙁䅍䅁䭁䅁䅕䅁䙁䅁䅁䅁杂⭆䅚允䅁䅁䅅䅁䙁䱁穢搯㑒呩䅰䍄䉁䅁䅁䅂䅁䅁䅍䅄䅁䅁䅯睔䅁䅁䅯杔䅁䅁䅕䅁䅁䕁慄唵䉁䅁䅁允䅁䅁䅕㡪ㅌ䙋偹䕃䵁䅉䅅䅁䙁䅁䅁睁䵁䅁䅁权䅁䅁䅁权呂䅁䅁权䙁䅁䅁兂䅁䅁䅁乯汄䅑䅅䅁䉁䅁䅁兂权楇搯䅊穙䅑杷允䅁䅁䅑䅁䑁䅁䅷䅁䭁䕁䄸䅁䭁䕁䄴䅁䙁䅁䅁䅁䅂佤䅚允䅁䅁䅅䅁䙁䭁䠵場啯杲䅴䍄䉁䅁䅁兂䅁䅁䅍䅄䅁䅁䅯杈䅁䅁䅯允䅁䅁䅯兂䅁䅁䅕䅁䅁䵁㑄唵䉁䅁䅁允䅁䅁䅕硥畓⭒㙆䐱䴸䅉䅅䅁䙁䅁䅁睁䵁䅁䅁权敁䅁䅁权呂䅁䅁权䙁䅁䅁兂䅁䅁䅁䵑汶䅑䅅䅁䉁䅁䅁兂牁硨婢牺獣䅑杷允䅁䅁䅕䅁䑁䅁䅷䅁䭁䉁䄴䅁䭁䙁䅍䅁䭁䅁䅕䅁䙁䅁䅁䅁䅁⭷䅖允䅁䅁䅅䅁䙁䡁㥅瑃橥䍍䅸䍄䉁䅁䅁兂䅁䅁䅍䅄䅁䅁䅯睈䅁䅁䅯睕䅁䅁䅯兂䅁䅁䅕䅁䅁佁䅃欵䉁䅁䅁允䅁䅁䅕余兘瑉㕶䕍䵁䅉䅅䅁䕁䅁䅁睁䵁䅁䅁权偂䅁䅁权佂䅁䅁兂䅁䅁䅁䉙浔䅑䅅䅁䉁䅁䅁兂㑃潈牘払呧䅑杷允䅁䅁䅕䅁䑁䅁䅷䅁䭁䉁䄴䅁䭁䅁䅅䅁䭁䅁䅕䅁䙁䅁䅁䅁杁畔䅚允䅁䅁䅅䅁䙁䵁ㅐ䙋偹瑷⽕䍄䉁䅁䅁䅂䅁䅁䅍䅄䅁䅁䅯睔䅁䅁䅯杔䅁䅁䅕䅁䅁䥁癄唵䉁䅁䅁允䅁䅁䅕䡰㥁瑃橥䕅䵁䅉䅅䅁䙁䅁䅁睁䵁䅁䅁权䅁䅁䅁权呂䅁䅁权䙁䅁䅁兂䅁䅁䅁乙汈䅑䅅䅁䉁䅁䅁兂权楇搯䅊穙䅑杷允䅁䅁䅑䅁䑁䅁䅷䅁䭁䕁䄸䅁䭁䕁䄴䅁䙁䅁䅁䅁杁攱䅖允䅁䅁䅅䅁䙁䱁敧敨剴䅵䅚䍄䉁䅁䅁兂䅁䅁䅍䅄䅁䅁䅯䅁䅁䅁䅯睕䅁䅁䅯兂䅁䅁䅕䅁䅁䕁汃唵䉁䅁䅁允䅁䅁䅕㘱睎児㍰啍䵁䅉䅅䅁䙁䅁䅁睁䵁䅁䅁权䅁䅁䅁权䉁䅁䅁权䙁䅁䅁兂䅁䅁䅁䘴浘䅑䅅䅁䉁䅁䅁兂㑃潈牘払敪睐杷允䅁䅁䅕䅁䑁䅁䅷䅁䭁䉁䅯䅁䭁䙁䅍䅁䭁䅁䅕䅁䙁䅁䅁䅁杄敏䅚允䅁䅁䅅䅁䙁䵁杕䡳潊呍䅴䍄䉁䅁䅁兂䅁䅁䅍䅄䅁䅁䅯䅈䅁䅁䅯允䅁䅁䅯兂䅁䅁䅕䅁䅁䵁䑁欵䉁䅁䅁允䅁䅁䅕㑈牘払敧吱䴸䅉䅅䅁䙁䅁䅁睁䵁䅁䅁权敁䅁䅁权䉁䅁䅁权䙁䅁䅁兂䅁䅁䅁䱉氯䅑䅅䅁䉁䅁䅁兂穁積積積呐睐杷允䅁䅁䅑䅁䑁䅁䅷䅁䭁䕁䄸䅁䭁䕁䄴䅁䙁䅁䅁䅁杄⭙䅚允䅁䅁䅅䅁䙁䉁䘫ㄶ㑇杈䄹䍄䉁䅁䅁兂䅁䅁䅍䅄䅁䅁䅯先䅁䅁䅯睕䅁䅁䅯兂䅁䅁䅕䅁䅁䅁慂欵䉁䅁䅁允䅁䅁䅕⽷潕䥘䌫歌䵁䅉䅅䅁䕁䅁䅁睁䵁䅁䅁权偂䅁䅁权佂䅁䅁兂䅁䅁䅁倴汌䅑䅅䅁䉁䅁䅁兂㑃潈牘払佧䅑杷允䅁䅁䅕䅁䑁䅁䅷䅁䭁䉁䄸䅁䭁䅁䅅䅁䭁䅁䅕䅁䙁䅁䅁䅁杄⭆䅚允䅁䅁䅅䅁䙁偁潙䥘䌯改⽁䍄䉁䅁䅁兂䅁䅁䅍䅄䅁䅁䅯䅁䅁䅁䅯睕䅁䅁䅯兂䅁䅁䅕䅁䅁䭁睃唵䉁䅁䅁允䅁䅁䅕歵䵫楁湳歍䵁䅉䅅䅁䙁䅁䅁睁䵁䅁䅁权晁䅁䅁权䉁䅁䅁权䙁䅁䅁兂䅁䅁䅁乧汔䅑䅅䅁䉁䅁䅁兂乄䵺䵺䵺捺睐杷允䅁䅁䅕䅁䑁䅁䅷䅁䭁䉁䄸䅁䭁䅁䅅䅁䭁䅁䅕䅁䙁䅁䅁䅁杄由䅖允䅁䅁䅅䅁䙁䵁䴳䵺䵺乺⽷䍄䉁䅁䅁䅂䅁䅁䅍䅄䅁䅁䅯睔䅁䅁䅯杔䅁䅁䅕䅁䅁䵁䡁欵䉁䅁䅁允䅁䅁䅕䭆䠵場啯歅䵁䅉䅅䅁䙁䅁䅁睁䵁䅁䅁权䅁䅁䅁权呂䅁䅁权䙁䅁䅁兂䅁䅁䅁䑷浶䅑䅅䅁䉁䅁䅁兂䅁䅁䅁䭁穁䅑杷允䅁䅁䅕䅁䑁䅁䅷䅁䭁䉁䅯䅁䭁䙁䅍䅁䭁䅁䅕䅁䙁䅁䅁䅁䅁畵䅖允䅁䅁䅅䅁䙁䑁ㄸ牘䩰䐷䅬䍄䉁䅁䅁兂䅁䅁䅍䅄䅁䅁䅯睈䅁䅁䅯睕䅁䅁䅯兂䅁䅁䅕䅁䅁䵁䍂欵䉁䅁䅁允䅁䅁䅕㑎䉬余睕啍䵁䅉䅅䅁䕁䅁䅁睁䵁䅁䅁权偂䅁䅁权佂䅁䅁兂䅁䅁䅁䡉浔䅑䅅䅁䉁䅁䅁兂獄払敧敨䱳䅑杷允䅁䅁䅕䅁䑁䅁䅷䅁䭁䅁䅁䅁䭁䅁䅅䅁䭁䅁䅕䅁䙁䅁䅁䅁䅄敆䅚允䅁䅁䅅䅁䙁䱁敧敨剴乵⼴䍄䉁䅁䅁兂䅁䅁䅍䅄䅁䅁䅯杇䅁䅁䅯允䅁䅁䅯兂䅁䅁䅕䅁䅁䕁婄唵䉁䅁䅁允䅁䅁䅕椹捨㡪ㅌ䐴䴸䅉䅅䅁䙁䅁䅁睁䵁䅁䅁权捁䅁䅁权䉁䅁䅁权䙁䅁䅁兂䅁䅁䅁䜴浮䅑䅅䅁䉁䅁䅁兂㉄䙋偹癷奘睐杷允䅁䅁䅕䅁䑁䅁䅷䅁䭁䉁䄸䅁䭁䅁䅅䅁䭁䅁䅕䅁䙁䅁䅁䅁䅂⭤䅚允䅁䅁䅅䅁䙁䙁㑋潈牘敕⽁䍄䉁䅁䅁兂䅁䅁䅍䅄䅁䅁䅯䅁䅁䅁䅯睕䅁䅁䅯兂䅁䅁䅕䅁䅁䝁湂欵䉁䅁䅁允䅁䅁䅕佖汏㡭杔き䵁䅉䅅䅁䕁䅁䅁睁䵁䅁䅁权偂䅁䅁权佂䅁䅁兂䅁䅁䅁䅙浢䅑䅅䅁䉁䅁䅁兂㉄䙋偹癷剕䅑杷允䅁䅁䅑䅁䑁䅁䅷䅁䭁䕁䄸䅁䭁䕁䄴䅁䙁䅁䅁䅁䅄畉䅚允䅁䅁䅅䅁䙁䅁䅁䅁䅁䉁䅆䍄䉁䅁䅁兂䅁䅁䅍䅄䅁䅁䅯䅁䅁䅁䅯允䅁䅁䅯兂䅁䅁䅕䅁䅁䕁杄唵䉁䅁䅁允䅁䅁䅕場啯歲桦樲䴸䅉䅅䅁䙁䅁䅁睁䵁䅁䅁权䅁䅁䅁权䉁䅁䅁权䙁䅁䅁兂䅁䅁䅁䕷浌䅑䅅䅁䉁䅁䅁兂㑃潈牘払敪睐杷允䅁䅁䅕䅁䑁䅁䅷䅁䭁䉁䄴䅁䭁䅁䅅䅁䭁䅁䅕䅁䙁䅁䅁䅁杂⭁䅚允䅁䅁䅅䅁䙁䡁啳歲桦瑥⽑䍄䉁䅁䅁兂䅁䅁䅍䅄䅁䅁䅯睈䅁䅁䅯允䅁䅁䅯兂䅁䅁䅕䅁䅁䕁灁欵䉁䅁䅁允䅁䅁䅕体㙆䭆䠵吴䴸䅉䅅䅁䙁䅁䅁睁䵁䅁䅁权摁䅁䅁权䉁䅁䅁权䙁䅁䅁兂䅁䅁䅁䍷洳䅑䅅䅁䉁䅁䅁兂畃⭒㙆䭆堷睐杷允䅁䅁䅕䅁䑁䅁䅷䅁䭁䉁䄰䅁䭁䙁䅍䅁䭁䅁䅕䅁䙁䅁䅁䅁䅃⬲䅖允䅁䅁䅅䅁䙁䵁ㅐ䙋偹楷䄱䍄䉁䅁䅁兂䅁䅁䅍䅄䅁䅁䅯杈䅁䅁䅯睕䅁䅁䅯兂䅁䅁䅕䅁䅁䍁卂欵䉁䅁䅁允䅁䅁䅕渷⽷噎㘴䕊䵁䅉䅅䅁䙁䅁䅁睁䵁䅁䅁权晁䅁䅁权䉁䅁䅁权䙁䅁䅁兂䅁䅁䅁䝙浪䅑䅅䅁䉁䅁䅁兂卂䉵䘶ㄶ杈睐杷允䅁䅁䅑䅁䑁䅁䅷䅁䭁䕁䄸䅁䭁䕁䄴䅁䙁䅁䅁䅁䅂⭊䅚允䅁䅁䅅䅁䙁佁㙆䭆䠵刴䅆䍄䉁䅁䅁兂䅁䅁䅍䅄䅁䅁䅯睈䅁䅁䅯睕䅁䅁䅯兂䅁䅁䅕䅁䅁佁㑂欵䉁䅁䅁允䅁䅁䅕牡へ硫歧啍䵁䅉䅅䅁䕁䅁䅁睁䵁䅁䅁权偂䅁䅁权佂䅁䅁兂䅁䅁䅁偉汄䅑䅅䅁䉁䅁䅁兂㑃潈牘払內䅑杷允䅁䅁䅕䅁䑁䅁䅷䅁䭁䉁䅯䅁䭁䅁䅅䅁䭁䅁䅕䅁䙁䅁䅁䅁䅁⭤䅚允䅁䅁䅅䅁䙁䭁睒児塲⭯⽧䍄䉁䅁䅁兂䅁䅁䅍䅄䅁䅁䅯杈䅁䅁䅯允䅁䅁䅯兂䅁䅁䅕䅁䅁䥁䵄唵䉁䅁䅁允䅁䅁䅕積積積積稰䴸䅉䅅䅁䙁䅁䅁睁䵁䅁䅁权䅁䅁䅁权䉁䅁䅁权䙁䅁䅁兂䅁䅁䅁䈴洳䅑䅅䅁䉁䅁䅁兂㑃潈牘払敪睐杷允䅁䅁䅕䅁䑁䅁䅷䅁䭁䉁䄸䅁䭁䙁䅍䅁䭁䅁䅕䅁䙁䅁䅁䅁权畏䅚允䅁䅁䅅䅁䙁䑁䩥坑汄䑍䅆䍄䉁䅁䅁兂䅁䅁䅍䅄䅁䅁䅯杇䅁䅁䅯睕䅁䅁䅯兂䅁䅁䅕䅁䅁䭁㕄唵䉁䅁䅁允䅁䅁䅕㡪ㅌ䙋発問䵁䅉䅅䅁䕁䅁䅁睁䵁䅁䅁权偂䅁䅁权佂䅁䅁兂䅁䅁䅁䡧浐䅑䅅䅁䉁䅁䅁兂㑃潈牘払䵧䅑杷允䅁䅁䅕䅁䑁䅁䅷䅁䭁䉁䄰䅁䭁䙁䅍䅁䭁䅁䅕䅁䙁䅁䅁䅁䅄敡䅚允䅁䅁䅅䅁䙁䑁䩥坑汄䍅䄵䍄䉁䅁䅁兂䅁䅁䅍䅄䅁䅁䅯先䅁䅁䅯睕䅁䅁䅯兂䅁䅁䅕䅁䅁䕁慄唵䉁䅁䅁允䅁䅁䅕⽷潕䥘䌯啌䵁䅉䅅䅁䙁䅁䅁睁䵁䅁䅁权晁䅁䅁权䉁䅁䅁权䙁䅁䅁兂䅁䅁䅁䍉浐䅑䅅䅁䉁䅁䅁兂䥂場啯歲桦睐杷允䅁䅁䅕䅁䑁䅁䅷䅁䭁䉁䄸䅁䭁䅁䅅䅁䭁䅁䅕䅁䙁䅁䅁䅁䅃敚䅚允䅁䅁䅅䅁䙁䙁㑋潈牘敕⽁䍄䉁䅁䅁䅂䅁䅁䅍䅄䅁䅁䅯睔䅁䅁䅯杔䅁䅁䅕䅁䅁䥁畄唵䉁䅁䅁允䅁䉁䅑䅂䅁䅁䅁䅁䵁䅉䅅䅁䙁䅁䅁睁䵁䅁䅁权捁䅁䅁权䉁䅁䅁权䙁䅁䅁兂䅁䅁䅁倴汶䅑䅅䅁䉁䅁䅁兂晁敨剴䉵嘷睐杷允䅁䅁䅕䅁䑁䅁䅷䅁䭁䉁䅷䅁䭁䙁䅍䅁䭁䅁䅕䅁䙁䅁䅁䅁䅄敷䅖允䅁䅁䅅䅁䙁佁㙆䭆䠵卙䄵䍄䉁䅁䅁兂䅁䅁䅍䅄䅁䅁䅯杈䅁䅁䅯睕䅁䅁䅯兂䅁䅁䅕䅁䅁䍁䡁欵䉁䅁䅁允䅁䅁䅕䅁䅁䅁䅁歋䵁䅉䅅䅁䕁䅁䅁睁䵁䅁䅁权偂䅁䅁权佂䅁䅁兂䅁䅁䅁倴氷䅑䅅䅁䉁䅁䅁兂乄䵺䵺䵺佷䅑杷允䅁䅁䅑䅁䑁䅁䅷䅁䭁䕁䄸䅁䭁䕁䄴䅁䙁䅁䅁䅁杄畕䅚允䅁䅁䅅䅁䙁䡁㥅瑃橥䅣䄹䍄䉁䅁䅁䅂䅁䅁䅍䅄䅁䅁䅯睔䅁䅁䅯杔䅁䅁䅕䅁䅁䵁呂欵䉁䅁䅁允䅁䅁䅕体㙆䭆䠵い䵁䅉䅅䅁䕁䅁䅁睁䵁䅁䅁权偂䅁䅁权佂䅁䅁兂䅁䅁䅁䡑浐䅑䅅䅁䉁䅁䅁兂乄䵺䵺䵺䵷䅑杷允䅁䅁䅑䅁䑁䅁䅷䅁䭁䕁䄸䅁䭁䕁䄴䅁䙁䅁䅁䅁杁敆䅚允䅁䅁䅅䅁䙁䥁䌯匹捨硪䅎䍄䉁䅁䅁兂䅁䅁䅍䅄䅁䅁䅯睈䅁䅁䅯允䅁䅁䅯兂䅁䅁䅕䅁䅁䕁奁欵䉁䅁䅁允䅁䅁䅕椹捨㡪ㅌ䐴䴸䅉䅅䅁䕁䅁䅁睁䵁䅁䅁权偂䅁䅁权佂䅁䅁兂䅁䅁䅁䴴汲䅑䅅䅁䉁䅁䅁兂偃癷潕䥘⬯睐杷允䅁䅁䅕䅁䑁䅁䅷䅁䭁䉁䄰䅁䭁䙁䅍䅁䭁䅁䅕䅁䙁䅁䅁䅁䅂住䅚允䅁䅁䅅䅁䙁䙁余扌摋礷䄵䍄䉁䅁䅁䅂䅁䅁䅍䅄䅁䅁䅯睔䅁䅁䅯杔䅁䅁䅕䅁䅁佁睁欵䉁䅁䅁允䅁䅁䅕積積積積歅䵁䅉䅅䅁䙁䅁䅁睁䵁䅁䅁权慁䅁䅁权䉁䅁䅁权䙁䅁䅁兂䅁䅁䅁䡯浦䅑䅅䅁䉁䅁䅁兂歃䑣䬰㘱潐睐杷允䅁䅁䅕䅁䑁䅁䅷䅁䭁䅁䅁䅁䭁䅁䅅䅁䭁䅁䅕䅁䙁䅁䅁䅁䅄⬶䅖允䅁䅁䅅䅁䙁䥁牘払敧摨⽳䍄䉁䅁䅁兂䅁䅁䅍䅄䅁䅁䅯先䅁䅁䅯允䅁䅁䅯兂䅁䅁䅕䅁䅁䥁敁欵䉁䅁䅁允䅁䅁䅕㑈牘払敧吱䴸䅉䅅䅁䙁䅁䅁睁䵁䅁䅁权晁䅁䅁权呂䅁䅁权䙁䅁䅁兂䅁䅁䅁䕷洳䅑䅅䅁䉁䅁䅁兂䕁杖琴桳砰䅑杷允䅁䅁䅑䅁䑁䅁䅷䅁䭁䕁䄸䅁䭁䕁䄴䅁䙁䅁䅁䅁权敷䅖允䅁䅁䅅䅁䙁䙁偹癷潕佘⼸䍄䉁䅁䅁䅂䅁䅁䅍䅄䅁䅁䅯睔䅁䅁䅯杔䅁䅁䅕䅁䅁䝁乁欵䉁䅁䅁允䅁䅁䅕場啯歲桦歅䵁䅉䅅䅁䙁䅁䅁睁䵁䅁䅁权捁䅁䅁权呂䅁䅁权䙁䅁䅁兂䅁䅁䅁䡁浮䅑䅅䅁䉁䅁䅁兂䱃佢㝦晱瑅䅑杷允䅁䅁䅕䅁䑁䅁䅷䅁䭁䉁䅷䅁䭁䙁䅍䅁䭁䅁䅕䅁䙁䅁䅁䅁䅄⭔䅚允䅁䅁䅅䅁䙁乁欰潂噇祑䄵䍄䉁䅁䅁兂䅁䅁䅍䅄䅁䅁䅯䅁䅁䅁䅯睕䅁䅁䅯兂䅁䅁䅕䅁䅁䥁䉂欵䉁䅁䅁允䅁䅁䅕䅁䅁䅁权き䵁䅉䅅䅁䕁䅁䅁睁䵁䅁䅁权偂䅁䅁权佂䅁䅁兂䅁䅁䅁䠴浌䅑䅅䅁䉁䅁䅁兂桄桥畓⭒䵅䅑杷允䅁䅁䅑䅁䑁䅁䅷䅁䭁䕁䄸䅁䭁䕁䄴䅁䙁䅁䅁䅁䅂攸䅖允䅁䅁䅅䅁䙁䙁㑋潈牘兕䄵䍄䉁䅁䅁兂䅁䅁䅍䅄䅁䅁䅯杇䅁䅁䅯允䅁䅁䅯兂䅁䅁䅕䅁䅁䍁㙄唵䉁䅁䅁允䅁䅁䅕積積積積稴䴸䅉䅅䅁䙁䅁䅁睁䵁䅁䅁权慁䅁䅁权呂䅁䅁权䙁䅁䅁兂䅁䅁䅁䴴氯䅑䅅䅁䉁䅁䅁兂权楇搯䕊㙙䅑杷允䅁䅁䅕䅁䑁䅁䅷䅁䭁䅁䅁䅁䭁䅁䅅䅁䭁䅁䅕䅁䙁䅁䅁䅁䅄⬵䅖允䅁䅁䅅䅁䙁䥁牘払敧摨⽳䍄䉁䅁䅁兂䅁䅁䅍䅄䅁䅁䅯杇䅁䅁䅯允䅁䅁䅯兂䅁䅁䅕䅁䅁䵁允欵䉁䅁䅁允䅁䅁䅕浚浚浚浚樵䴸䅉䅅䅁䙁䅁䅁睁䵁䅁䅁权敁䅁䅁权䉁䅁䅁权䙁䅁䅁兂䅁䅁䅁䰴汶䅑䅅䅁䉁䅁䅁兂穁積積積呐睐杷允䅁䅁䅑䅁䑁䅁䅷䅁䭁䕁䄸䅁䭁䕁䄴䅁䙁䅁䅁䅁杁敢䅚允䅁䅁䅅䅁䙁䅁塲㍯㥁权䄱䍄䉁䅁䅁䅂䅁䅁䅍䅄䅁䅁䅯睔䅁䅁䅯杔䅁䅁䅕䅁䅁䵁⭁欵䉁䅁䅁允䅁䅁䅕⽷潕䥘䌯ぃ䵁䅉䅅䅁䙁䅁䅁睁䵁䅁䅁权慁䅁䅁权䉁䅁䅁权䙁䅁䅁兂䅁䅁䅁䙑洷䅑䅅䅁䉁䅁䅁兂歃䑣䬰㘱潐睐杷允䅁䅁䅑䅁䑁䅁䅷䅁䭁䕁䄸䅁䭁䕁䄴䅁䙁䅁䅁䅁䅄敘䅚允䅁䅁䅅䅁䙁䕁桪桥畓睒䄹䍄䉁䅁䅁兂䅁䅁䅍䅄䅁䅁䅯睈䅁䅁䅯睕䅁䅁䅯兂䅁䅁䅕䅁䅁䵁⽁欵䉁䅁䅁允䅁䅁䅕㑎䉬余睕啍䵁䅉䅅䅁䙁䅁䅁睁䵁䅁䅁权䅁䅁䅁权呂䅁䅁权䙁䅁䅁兂䅁䅁䅁䑷浄䅑䅅䅁䉁䅁䅁兂瑁灳瘳㑰穙䅑杷允䅁䅁䅑䅁䑁䅁䅷䅁䭁䕁䄸䅁䭁䕁䄴䅁䙁䅁䅁䅁杁佁䅚允䅁䅁䅅䅁䙁䡁啳歲桦来䅸䍄䉁䅁䅁䅂䅁䅁䅍䅄䅁䅁䅯睔䅁䅁䅯杔䅁䅁䅕䅁䅁䍁桁欵䉁䅁䅁允䅁䅁䅕㡪ㅌ䙋偹䕅䵁䅉䅅䅁䙁䅁䅁睁䵁䅁䅁权晁䅁䅁权䉁䅁䅁权䙁䅁䅁兂䅁䅁䅁䕑浺䅑䅅䅁䉁䅁䅁兂歃䑣䬰㘱材睐杷允䅁䅁䅕䅁䑁䅁䅷䅁䭁䉁䄴䅁䭁䙁䅍䅁䭁䅁䅕䅁䙁䅁䅁䅁杁留䅚允䅁䅁䅅䅁䙁䩁瑈䑦ㄸ楘䅊䍄䉁䅁䅁兂䅁䅁䅍䅄䅁䅁䅯䅁䅁䅁䅯允䅁䅁䅯兂䅁䅁䅕䅁䅁䍁祁欵䉁䅁䅁允䅁䅁䅕䉵䘶ㄶ㑇樳䴸䅉䅅䅁䙁䅁䅁睁䵁䅁䅁权慁䅁䅁权䉁䅁䅁权䙁䅁䅁兂䅁䅁䅁䰴汔䅑䅅䅁䉁䅁䅁兂䅁䅁䅁䅁杄睐杷允䅁䅁䅕䅁䑁䅁䅷䅁䭁䉁䄸䅁䭁䅁䅅䅁䭁䅁䅕䅁䙁䅁䅁䅁杁数䅖允䅁䅁䅅䅁䭁䉁䅳䅁䵁䅉䅅䅁䕁䅁䅁睁䵁䅁䅁权偂䅁䅁权佂䅁䅁兂䅁䅁䅁䩯汶䅑䅅䅁䉁䅁䅁兂穁積積積呐睐杷允䅁䅁䅕䅁䑁䅁䅷䅁䭁䉁䅯䅁䭁䙁䅍䅁䭁䅁䅕䅁䙁䅁䅁䅁䅁⭺䅖允䅁䅁䅅䅁䙁䭁慁㥌欰橒䅰䍄䉁䅁䅁兂䅁䅁䅍䅄䅁䅁䅯先䅁䅁䅯睕䅁䅁䅯兂䅁䅁䅕䅁䅁䝁䕁欵䉁䅁䅁允䅁䅁䅕䝭匴㡧䭂歌䵁䅉䅅䅁䕁䅁䅁睁䵁䅁䅁权偂䅁䅁权佂䅁䅁兂䅁䅁䅁䡙浌䅑䅅䅁䉁䅁䅁兂㝂䭆䠵場䵯䅑杷允䅁䅁䅕䅁䑁䅁䅷䅁䭁䉁䅷䅁䭁䙁䅍䅁䭁䅁䅕䅁䙁䅁䅁䅁杁畤䅚允䅁䅁䅅䅁䙁䥁獴⼵灵匸䄱䍄䉁䅁䅁兂䅁䅁䅍䅄䅁䅁䅯杈䅁䅁䅯睕䅁䅁䅯兂䅁䅁䅕䅁䅁䥁㑃唵䉁䅁䅁允䅁䅁䅕癴㥐䠱灨䕌䵁䅉䅅䅁䕁䅁䅁睁䵁䅁䅁权偂䅁䅁权佂䅁䅁兂䅁䅁䅁䵉汮䅑䅅䅁䉁䅁䅁兂灁䥘䌯匹㡪睐杷允䅁䅁䅕䅁䑁䅁䅷䅁䭁䉁䄸䅁䭁䙁䅍䅁䭁䅁䅕䅁䙁䅁䅁䅁杁敉䅚允䅁䅁䅅䅁䙁䕁㉡⼸唳䐫䅂䍄䉁䅁䅁䅂䅁䅁䅍䅄䅁䅁䅯睔䅁䅁䅯杔䅁䅁䅕䅁䅁䭁浄唵䉁䅁䅁允䅁䅁䅕児塲㍯㥁歅䵁䅉䅅䅁䕁䅁䅁睁䵁䅁䅁权偂䅁䅁权佂䅁䅁兂䅁䅁䅁倴汦䅑䅅䅁䉁䅁䅁兂硂児塲㍯十䅑杷允䅁䅁䅑䅁䑁䅁䅷䅁䭁䕁䄸䅁䭁䕁䄴䅁䙁䅁䅁䅁杂伯䅖允䅁䅁䅅䅁䙁䉁畓⭒㙆䅆䄵䍄䉁䅁䅁兂䅁䅁䅍䅄䅁䅁䅯睈䅁䅁䅯睕䅁䅁䅯兂䅁䅁䅕䅁䅁䝁塁欵䉁䅁䅁允䅁䅁䅕牒穢搯㑔䕍䵁䅉䅅䅁䕁䅁䅁睁䵁䅁䅁权偂䅁䅁权佂䅁䅁兂䅁䅁䅁䡯浈䅑䅅䅁䉁䅁䅁兂㑃潈牘払䵧䅑杷允䅁䅁䅑䅁䑁䅁䅷䅁䭁䕁䄸䅁䭁䕁䄴䅁䙁䅁䅁䅁䅄敃䅚允䅁䅁䅅䅁䙁䙁㑋潈牘剕䅊䍄䉁䅁䅁䅂䅁䅁䅍䅄䅁䅁䅯睔䅁䅁䅯杔䅁䅁䅕䅁䅁䕁⭄唵䉁䅁䅁允䅁䅁䅕積積積積啄䵁䅉䅅䅁䙁䅁䅁睁䵁䅁䅁权䅁䅁䅁权䉁䅁䅁权䙁䅁䅁兂䅁䅁䅁䵯汘䅑䅅䅁䉁䅁䅁兂㥁瑃橥䑣愳睐杷允䅁䅁䅕䅁䑁䅁䅷䅁䭁䅁䅁䅁䭁䙁䅍䅁䭁䅁䅕䅁䙁䅁䅁䅁䅃畷䅖允䅁䅁䅅䅁䙁偁周㘴扗䑨䅊䍄䉁䅁䅁兂䅁䅁䅍䅄䅁䅁䅯杈䅁䅁䅯允䅁䅁䅯兂䅁䅁䅕䅁䅁䥁塂欵䉁䅁䅁允䅁䅁䅕⽷潕䥘䌯吱䴸䅉䅅䅁䙁䅁䅁睁䵁䅁䅁权䅁䅁䅁权呂䅁䅁权䙁䅁䅁兂䅁䅁䅁临氳䅑䅅䅁䉁䅁䅁兂婁䙂余摌祉䅑杷允䅁䅁䅕䅁䑁䅁䅷䅁䭁䉁䅯䅁䭁䙁䅍䅁䭁䅁䅕䅁䙁䅁䅁䅁䅄攵䅖允䅁䅁䅅䅁䙁䵁ㅐ䙋偹樴䅬䍄䉁䅁䅁兂䅁䅁䅍䅄䅁䅁䅯杈䅁䅁䅯睕䅁䅁䅯兂䅁䅁䅕䅁䅁䝁畂欵䉁䅁䅁允䅁䅁䅕匰扌堫焵啉䵁䅉䅅䅁䕁䅁䅁睁䵁䅁䅁权偂䅁䅁权佂䅁䅁兂䅁䅁䅁䭁汄䅑䅅䅁䉁䅁䅁兂㉄䙋偹癷奘睐杷允䅁䅁䅕䅁䑁䅁䅷䅁䭁䉁䄸䅁䭁䙁䅍䅁䭁䅁䅕䅁䙁䅁䅁䅁䅁佅䅚允䅁䅁䅅䅁䙁䅁坒楄礲呶䅂䍄䉁䅁䅁䅂䅁䅁䅍䅄䅁䅁䅯睔䅁䅁䅯杔䅁䅁䅕䅁䅁䅁湂欵䉁䅁䅁允䅁䅁䅕歲桦桥畓啄䵁䅉䅅䅁䙁䅁䅁睁䵁䅁䅁权敁䅁䅁权呂䅁䅁权䙁䅁䅁兂䅁䅁䅁䑯浐䅑䅅䅁䉁䅁䅁兂䥂場啯歲浣䅑杷允䅁䅁䅑䅁䑁䅁䅷䅁䭁䕁䄸䅁䭁䕁䄴䅁䙁䅁䅁䅁䅃散䅚允䅁䅁䅅䅁䙁佁㙆䭆䠵儴䅸䍄䉁䅁䅁兂䅁䅁䅍䅄䅁䅁䅯杇䅁䅁䅯允䅁䅁䅯兂䅁䅁䅕䅁䅁䕁䭁欵䉁䅁䅁允䅁䅁䅕浚浚浚浚樵䴸䅉䅅䅁䙁䅁䅁睁䵁䅁䅁权捁䅁䅁权䉁䅁䅁权䙁䅁䅁兂䅁䅁䅁䍷浲䅑䅅䅁䉁䅁䅁兂畃⭒㙆䭆堷睐杷允䅁䅁䅑䅁䑁䅁䅷䅁䭁䕁䄸䅁䭁䕁䄴䅁䙁䅁䅁䅁杂余䅚允䅁䅁䅅䅁䙁䉁䘫ㄶ㑇杈䄹䍄䉁䅁䅁兂䅁䅁䅍䅄䅁䅁䅯杇䅁䅁䅯允䅁䅁䅯兂䅁䅁䅕䅁䅁䝁㕃唵䉁䅁䅁允䅁䅁䅕䅁䅁䅁䅁䐴䴸䅉䅅䅁䙁䅁䅁睁䵁䅁䅁权䅁䅁䅁权呂䅁䅁权䙁䅁䅁兂䅁䅁䅁䩙汢䅑䅅䅁䉁䅁䅁兂㡃䩤奍䡂睙䅑杷允䅁䅁䅕䅁䑁䅁䅷䅁䭁䉁䅷䅁䭁䅁䅅䅁䭁䅁䅕䅁䙁䅁䅁䅁䅃敁䅚允䅁䅁䅅䅁䙁䉁䘫ㄶ㑇瑈⽕䍄䉁䅁䅁兂䅁䅁䅍䅄䅁䅁䅯睈䅁䅁䅯允䅁䅁䅯兂䅁䅁䅕䅁䅁䭁䩂欵䉁䅁䅁允䅁䅁䅕䡰㥁瑃橥䐴䴸䅉䅅䅁䙁䅁䅁睁䵁䅁䅁权䅁䅁䅁权呂䅁䅁权䙁䅁䅁兂䅁䅁䅁䙧浌䅑䅅䅁䉁䅁䅁兂㕁䵴㉨瑶稸䅑杷允䅁䅁䅕䅁䑁䅁䅷䅁䭁䉁䄸䅁䭁䅁䅅䅁䭁䅁䅕䅁䙁䅁䅁䅁䅃⬲䅖允䅁䅁䅅䅁䙁䵁䴳䵺䵺乺⽷䍄䉁䅁䅁䅂䅁䅁䅍䅄䅁䅁䅯睔䅁䅁䅯杔䅁䅁䅕䅁䅁䕁求欵䉁䅁䅁允䅁䅁䅕椹捨㡪ㅌ歄䵁䅉䅅䅁䙁䅁䅁睁䵁䅁䅁权慁䅁䅁权呂䅁䅁权䙁䅁䅁兂䅁䅁䅁䍯浺䅑䅅䅁䉁䅁䅁兂䥂場啯煲㙣䅑杷允䅁䅁䅑䅁䑁䅁䅷䅁䭁䕁䄸䅁䭁䕁䄴䅁䙁䅁䅁䅁䅁散䅚允䅁䅁䅅䅁䙁佁㙆䭆䠵儴䅸䍄䉁䅁䅁兂䅁䅁䅍䅄䅁䅁䅯睈䅁䅁䅯睕䅁䅁䅯兂䅁䅁䅕䅁䅁䵁⭁欵䉁䅁䅁允䅁䅁䅕㑎䉬余睕啍䵁䅉䅅䅁䙁䅁䅁睁䵁䅁䅁权捁䅁䅁权䉁䅁䅁权䙁䅁䅁兂䅁䅁䅁䱑氯䅑䅅䅁䉁䅁䅁兂偃癷潕䥘匯睐杷允䅁䅁䅕䅁䑁䅁䅷䅁䭁䉁䄴䅁䭁䙁䅍䅁䭁䅁䅕䅁䙁䅁䅁䅁权住䅚允䅁䅁䅅䅁䙁䕁桪桥畓祒䅚䍄䉁䅁䅁兂䅁䅁䅍䅄䅁䅁䅯䅁䅁䅁䅯睕䅁䅁䅯兂䅁䅁䅕䅁䅁䅁坁欵䉁䅁䅁允䅁䅁䅕硢䑋䵷䉯き䵁䅉䅅䅁䕁䅁䅁睁䵁䅁䅁权偂䅁䅁权佂䅁䅁兂䅁䅁䅁䐴洷䅑䅅䅁䉁䅁䅁兂䙃ㄶ㑇潈䱕䅑杷允䅁䅁䅕䅁䑁䅁䅷䅁䭁䅁䅁䅁䭁䅁䅅䅁䭁䅁䅕䅁䙁䅁䅁䅁杂敚䅚允䅁䅁䅅䅁䙁䱁敧敨剴乵⼴䍄䉁䅁䅁兂䅁䅁䅍䅄䅁䅁䅯先䅁䅁䅯允䅁䅁䅯兂䅁䅁䅕䅁䅁䵁䉂欵䉁䅁䅁允䅁䅁䅕歲桦桥畓稱䴸䅉䅅䅁䙁䅁䅁睁䵁䅁䅁权慁䅁䅁权呂䅁䅁权䙁䅁䅁兂䅁䅁䅁偁汶䅑䅅䅁䉁䅁䅁兂偃癷潕佘㔸䅑杷允䅁䅁䅑䅁䑁䅁䅷䅁䭁䕁䄸䅁䭁䕁䄴䅁䙁䅁䅁䅁䅄佖䅚允䅁䅁䅅䅁䙁䅁塲㍯㥁桃䅂䍄䉁䅁䅁兂䅁䅁䅍䅄䅁䅁䅯杈䅁䅁䅯睕䅁䅁䅯兂䅁䅁䅕䅁䅁䍁䵁欵䉁䅁䅁允䅁䅁䅕硢䑋䵷桲啋䵁䅉䅅䅁䙁䅁䅁睁䵁䅁䅁权䅁䅁䅁权呂䅁䅁权䙁䅁䅁兂䅁䅁䅁䵯汮䅑䅅䅁䉁䅁䅁兂瑂⼵灵昸祉䅑杷允䅁䅁䅑䅁䑁䅁䅷䅁䭁䕁䄸䅁䭁䕁䄴䅁䙁䅁䅁䅁䅁敮䅖允䅁䅁䅅䅁䙁䝁浚浚浚瑚⽙䍄䉁䅁䅁兂䅁䅁䅍䅄䅁䅁䅯䅁䅁䅁䅯允䅁䅁䅯兂䅁䅁䅕䅁䅁䝁癃唵䉁䅁䅁允䅁䅁䅕灭婭婭婭吲䴸䅉䅅䅁䙁䅁䅁睁䵁䅁䅁权慁䅁䅁权䉁䅁䅁权䙁䅁䅁兂䅁䅁䅁䵯汘䅑䅅䅁䉁䅁䅁兂䅁䅁䅁䅁杄睐杷允䅁䅁䅑䅁䑁䅁䅷䅁䭁䕁䄸䅁䭁䕁䄴䅁䙁䅁䅁䅁䅄佣䅚允䅁䅁䅅䅁䙁䅁䅁䅁䅁䅁䅸䍄䉁䅁䅁兂䅁䅁䅍䅄䅁䅁䅯䅈䅁䅁䅯允䅁䅁䅯兂䅁䅁䅕䅁䅁佁⽄唵䉁䅁䅁允䅁䅁䅕㑈牘払敧吱䴸䅉䅅䅁䙁䅁䅁睁䵁䅁䅁权敁䅁䅁权呂䅁䅁权䙁䅁䅁兂䅁䅁䅁䕁浦䅑䅅䅁䉁䅁䅁兂畄䑦ㄸ橘歯䅑杷允䅁䅁䅕䅁䑁䅁䅷䅁䭁䅁䅁䅁䭁䙁䅍䅁䭁䅁䅕䅁䙁䅁䅁䅁䅂畂䅚允䅁䅁䅅䅁䙁䭁硲欰椱䑣䅊䍄䉁䅁䅁兂䅁䅁䅍䅄䅁䅁䅯睈䅁䅁䅯允䅁䅁䅯兂䅁䅁䅕䅁䅁䅁剄唵䉁䅁䅁允䅁䅁䅕䡰㥁瑃橥䐴䴸䅉䅅䅁䕁䅁䅁睁䵁䅁䅁权偂䅁䅁权佂䅁䅁兂䅁䅁䅁䝉浢䅑䅅䅁䉁䅁䅁兂䥂場啯歲乣䅑杷允䅁䅁䅑䅁䑁䅁䅷䅁䭁䕁䄸䅁䭁䕁䄴䅁䙁䅁䅁䅁䅃佶䅖允䅁䅁䅅䅁䙁乁橥䑣䬰⬱⽳䍄䉁䅁䅁兂䅁䅁䅍䅄䅁䅁䅯杈䅁䅁䅯睕䅁䅁䅯兂䅁䅁䅕䅁䅁䭁睂欵䉁䅁䅁允䅁䅁䅕匰扌堫焵啉䵁䅉䅅䅁䕁䅁䅁睁䵁䅁䅁权偂䅁䅁权佂䅁䅁兂䅁䅁䅁䅑浢䅑䅅䅁䉁䅁䅁兂㉄䙋偹癷剕䅑杷允䅁䅁䅑䅁䑁䅁䅷䅁䭁䕁䄸䅁䭁䕁䄴䅁䙁䅁䅁䅁䅃甹䅖允䅁䅁䅅䅁䙁䩁婱婭婭剭䅆䍄䉁䅁䅁兂䅁䅁䅍䅄䅁䅁䅯䅁䅁䅁䅯允䅁䅁䅯兂䅁䅁䅕䅁䅁䥁㝂欵䉁䅁䅁允䅁䅁䅕䉵䘶ㄶ㑇樳䴸䅉䅅䅁䙁䅁䅁睁䵁䅁䅁权捁䅁䅁权䉁䅁䅁权䙁䅁䅁兂䅁䅁䅁䭯氯䅑䅅䅁䉁䅁䅁兂偃癷潕䥘匯睐杷允䅁䅁䅕䅁䑁䅁䅷䅁䭁䉁䅷䅁䭁䙁䅍䅁䭁䅁䅕䅁䙁䅁䅁䅁䅁敬䅖允䅁䅁䅅䅁䙁偁㥔䠱灪楰䅸䍄䉁䅁䅁䅂䅁䅁䅍䅄䅁䅁䅯睔䅁䅁䅯杔䅁䅁䅕䅁䅁䕁㡁欵䉁䅁䅁允䅁䅁䅕㘱睎児塲啄䵁䅉䅅䅁䙁䅁䅁睁䵁䅁䅁权慁䅁䅁权呂䅁䅁权䙁䅁䅁兂䅁䅁䅁䙷浲䅑䅅䅁䉁䅁䅁兂䑄匹捨㉪㝉䅑杷允䅁䅁䅑䅁䑁䅁䅷䅁䭁䕁䄸䅁䭁䕁䄴䅁䙁䅁䅁䅁䅁敆䅚允䅁䅁䅅䅁䙁佁剸䉵䘶砶䅎䍄䉁䅁䅁兂䅁䅁䅍䅄䅁䅁䅯睈䅁䅁䅯允䅁䅁䅯兂䅁䅁䅕䅁䅁䕁䱁欵䉁䅁䅁允䅁䅁䅕䡰㥁瑃橥䐴䴸䅉䅅䅁䕁䅁䅁睁䵁䅁䅁权偂䅁䅁权佂䅁䅁兂䅁䅁䅁䑯浈䅑䅅䅁䉁䅁䅁兂㝂䭆䠵場卯䅑杷允䅁䅁䅕䅁䑁䅁䅷䅁䭁䉁䄸䅁䭁䙁䅍䅁䭁䅁䅕䅁䙁䅁䅁䅁䅂畑䅚允䅁䅁䅅䅁䙁䑁䩥坑汄䑍䅆䍄䉁䅁䅁兂䅁䅁䅍䅄䅁䅁䅯先䅁䅁䅯睕䅁䅁䅯兂䅁䅁䅕䅁䅁佁乂欵䉁䅁䅁允䅁䅁䅕婤奍䙂佡歌䵁䅉䅅䅁䕁䅁䅁睁䵁䅁䅁权偂䅁䅁权佂䅁䅁兂䅁䅁䅁䜴浦䅑䅅䅁䉁䅁䅁兂塄㍯㥁瑃乣䅑杷允䅁䅁䅕䅁䑁䅁䅷䅁䭁䉁䄴䅁䭁䙁䅍䅁䭁䅁䅕䅁䙁䅁䅁䅁䅄佇䅚允䅁䅁䅅䅁䙁䉁䕫杖琴楣䅬䍄䉁䅁䅁兂䅁䅁䅍䅄䅁䅁䅯睈䅁䅁䅯允䅁䅁䅯兂䅁䅁䅕䅁䅁佁煃唵䉁䅁䅁允䅁䅁䅯睇䅁䅁杷允䅁䅁䅑䅁䑁䅁䅷䅁䭁䕁䄸䅁䭁䕁䄴䅁䙁䅁䅁䅁杄⭢䅚允䅁䅁䅅䅁䙁䭁䠵場啯杲䅴䍄䉁䅁䅁兂䅁䅁䅍䅄䅁䅁䅯先䅁䅁䅯允䅁䅁䅯兂䅁䅁䅕䅁䅁䍁䵂欵䉁䅁䅁允䅁䅁䅕歲桦桥畓稱䴸䅉䅅䅁䙁䅁䅁睁䵁䅁䅁权敁䅁䅁权䉁䅁䅁权䙁䅁䅁兂䅁䅁䅁䍯浶䅑䅅䅁䉁䅁䅁兂䑄匹捨㡪噌睐杷允䅁䅁䅕䅁䑁䅁䅷䅁䭁䅁䅁䅁䭁䙁䅍䅁䭁䅁䅕䅁䙁䅁䅁䅁杁畗䅚允䅁䅁䅅䅁䙁䭁硲欰椱䐰䅎䍄䉁䅁䅁兂䅁䅁䅍䅄䅁䅁䅯䅈䅁䅁䅯睕䅁䅁䅯兂䅁䅁䅕䅁䅁䥁瑃唵䉁䅁䅁允䅁䅁䅕椹捨㡪ㅋ啌䵁䅉䅅䅁䙁䅁䅁睁䵁䅁䅁权捁䅁䅁权呂䅁䅁权䙁䅁䅁兂䅁䅁䅁䕉浲䅑䅅䅁䉁䅁䅁兂療潅䅐浹畅䅑杷允䅁䅁䅕䅁䑁䅁䅷䅁䭁䅁䅁䅁䭁䅁䅅䅁䭁䅁䅕䅁䙁䅁䅁䅁杄留䅚允䅁䅁䅅䅁䙁䱁敧敨剴乵⼴䍄䉁䅁䅁兂䅁䅁䅍䅄䅁䅁䅯䅁䅁䅁䅯睕䅁䅁䅯兂䅁䅁䅕䅁䅁佁奃唵䉁䅁䅁允䅁䅁䅕䡶呓䅇㉒䕍䵁䅉䅅䅁䙁䅁䅁睁䵁䅁䅁权䅁䅁䅁权呂䅁䅁权䙁䅁䅁兂䅁䅁䅁䡧浶䅑䅅䅁䉁䅁䅁兂啂㘴扗䅸ぁ䅑杷允䅁䅁䅕䅁䑁䅁䅷䅁䭁䉁䅯䅁䭁䅁䅅䅁䭁䅁䅕䅁䙁䅁䅁䅁杄敖䅚允䅁䅁䅅䅁䙁䭁睒児塲⭯⽧䍄䉁䅁䅁䅂䅁䅁䅍䅄䅁䅁䅯睔䅁䅁䅯杔䅁䅁䅕䅁䅁䅁奄唵䉁䅁䅁允䅁䅁䅕瑃橥䑣䬰啃䵁䅉䅅䅁䙁䅁䅁睁䵁䅁䅁权敁䅁䅁权呂䅁䅁权䙁䅁䅁兂䅁䅁䅁䌴浔䅑䅅䅁䉁䅁䅁兂ㅂ硫䕧獖渴䅑杷允䅁䅁䅑䅁䑁䅁䅷䅁䭁䕁䄸䅁䭁䕁䄴䅁䙁䅁䅁䅁杂佇䅚允䅁䅁䅅䅁䙁䝁浚浚浚桚䅊䍄䉁䅁䅁䅂䅁䅁䅍䅄䅁䅁䅯睔䅁䅁䅯杔䅁䅁䅕䅁䅁佁潂欵䉁䅁䅁允䅁䅁䅕瑃橥䑣䬰啄䵁䅉䅅䅁䕁䅁䅁睁䵁䅁䅁权偂䅁䅁权佂䅁䅁兂䅁䅁䅁义決䅑䅅䅁䉁䅁䅁兂硂児塲㍯䡁䅑杷允䅁䅁䅕䅁䑁䅁䅷䅁䭁䉁䅯䅁䭁䙁䅍䅁䭁䅁䅕䅁䙁䅁䅁䅁䅁⭋䅚允䅁䅁䅅䅁䙁䕁桪桥畓穰䅰䍄䉁䅁䅁兂䅁䅁䅍䅄䅁䅁䅯杇䅁䅁䅯睕䅁䅁䅯兂䅁䅁䅕䅁䅁䍁剂欵䉁䅁䅁允䅁䅁䅕䑔䩥坑䙂く䵁䅉䅅䅁䙁䅁䅁睁䵁䅁䅁权晁䅁䅁权呂䅁䅁权䙁䅁䅁兂䅁䅁䅁䭧汪䅑䅅䅁䉁䅁䅁兂㑃潈牘塕睧䅑杷允䅁䅁䅕䅁䑁䅁䅷䅁䭁䅁䅁䅁䭁䙁䅍䅁䭁䅁䅕䅁䙁䅁䅁䅁䅂⭺䅖允䅁䅁䅅䅁䙁䝁渳㘫确樸䅊䍄䉁䅁䅁兂䅁䅁䅍䅄䅁䅁䅯先䅁䅁䅯允䅁䅁䅯兂䅁䅁䅕䅁䅁佁噁欵䉁䅁䅁允䅁䅁䅕㑈牘払敧吱䴸䅉䅅䅁䙁䅁䅁睁䵁䅁䅁权捁䅁䅁权呂䅁䅁权䙁䅁䅁兂䅁䅁䅁䙙浲䅑䅅䅁䉁䅁䅁兂摄䅊䉡啬畍䅑杷允䅁䅁䅑䅁䑁䅁䅷䅁䭁䕁䄸䅁䭁䕁䄴䅁䙁䅁䅁䅁杂何䅚允䅁䅁䅅䅁䙁䉁䘫ㄶ㑇案䅆䍄䉁䅁䅁䅂䅁䅁䅍䅄䅁䅁䅯睔䅁䅁䅯杔䅁䅁䅕䅁䅁䝁癃唵䉁䅁䅁允䅁䅁䅕㑈牘払敧吱䴸䅉䅅䅁䙁䅁䅁睁䵁䅁䅁权䅁䅁䅁权呂䅁䅁权䙁䅁䅁兂䅁䅁䅁䵙氷䅑䅅䅁䉁䅁䅁兂瑂⼵灵昸祉䅑杷允䅁䅁䅕䅁䑁䅁䅷䅁䭁䉁䅷䅁䭁䙁䅍䅁䭁䅁䅕䅁䙁䅁䅁䅁杂界䅚允䅁䅁䅅䅁䙁䙁㕧䵴㉨楐䄵䍄䉁䅁䅁兂䅁䅁䅍䅄䅁䅁䅯杇䅁䅁䅯睕䅁䅁䅯兂䅁䅁䅕䅁䅁䥁噃唵䉁䅁䅁允䅁䅁䅕瑃橥䑣焳䕏䵁䅉䅅䅁䙁䅁䅁睁䵁䅁䅁权敁䅁䅁权呂䅁䅁权䙁䅁䅁兂䅁䅁䅁䕷浮䅑䅅䅁䉁䅁䅁兂畄䑦ㄸ橘歯䅑杷允䅁䅁䅑䅁䑁䅁䅷䅁䭁䕁䄸䅁䭁䕁䄴䅁䙁䅁䅁䅁杄由䅖允䅁䅁䅅䅁䙁䵁䴳䵺䵺䅺䅰䍄䉁䅁䅁䅂䅁䅁䅍䅄䅁䅁䅯睔䅁䅁䅯杔䅁䅁䅕䅁䅁䍁塄唵䉁䅁䅁允䅁䅁䅕捺䵺䵺䵺歃䵁䅉䅅䅁䕁䅁䅁睁䵁䅁䅁权偂䅁䅁权佂䅁䅁兂䅁䅁䅁䙯洷䅑䅅䅁䉁䅁䅁兂穁積積積偍䅑杷允䅁䅁䅕䅁䑁䅁䅷䅁䭁䉁䄸䅁䭁䅁䅅䅁䭁䅁䅕䅁䙁䅁䅁䅁䅂攱䅖允䅁䅁䅅䅁䙁䵁䴳䵺䵺乺⽷䍄䉁䅁䅁䅂䅁䅁䅍䅄䅁䅁䅯睔䅁䅁䅯杔䅁䅁䅕䅁䅁䕁楁欵䉁䅁䅁允䅁䅁䅕場啯歲桦䕅䵁䅉䅅䅁䙁䅁䅁睁䵁䅁䅁权捁䅁䅁权呂䅁䅁权䙁䅁䅁兂䅁䅁䅁䕧洯䅑䅅䅁䉁䅁䅁兂摄䅊䉡啬畍䅑杷允䅁䅁䅕䅁䑁䅁䅷䅁䭁䅁䅁䅁䭁䅁䅅䅁䭁䅁䅕䅁䙁䅁䅁䅁䅂畯䅖允䅁䅁䅅䅁䙁䩁婱婭婭摭⽫䍄䉁䅁䅁䅂䅁䅁䅍䅄䅁䅁䅯睔䅁䅁䅯杔䅁䅁䅕䅁䅁䅁療欵䉁䅁䅁允䅁䅁䅕⽷潕䥘䌯ぃ䵁䅉䅅䅁䙁䅁䅁睁䵁䅁䅁权䅁䅁䅁权呂䅁䅁权䙁䅁䅁兂䅁䅁䅁䘴浮䅑䅅䅁䉁䅁䅁兂㕁䵴㉨瑶稸䅑杷允䅁䅁䅕䅁䑁䅁䅷䅁䭁䅁䅁䅁䭁䙁䅍䅁䭁䅁䅕䅁䙁䅁䅁䅁权略䅚允䅁䅁䅅䅁䙁䙁橔婰䕶䑁䅒䍄䉁䅁䅁兂䅁䅁䅍䅄䅁䅁䅯䅈䅁䅁䅯睕䅁䅁䅯兂䅁䅁䅕䅁䅁䭁瑂欵䉁䅁䅁允䅁䅁䅕㉣剩堷⽺啌䵁䅉䅅䅁䕁䅁䅁睁䵁䅁䅁权偂䅁䅁权佂䅁䅁兂䅁䅁䅁佧決䅑䅅䅁䉁䅁䅁兂䙃ㄶ㑇潈兕䅑杷允䅁䅁䅑䅁䑁䅁䅷䅁䭁䕁䄸䅁䭁䕁䄴䅁䙁䅁䅁䅁杁畋䅚允䅁䅁䅅䅁䙁䉁畓⭒㙆䉆䅎䍄䉁䅁䅁兂䅁䅁䅍䅄䅁䅁䅯先䅁䅁䅯睕䅁䅁䅯兂䅁䅁䅕䅁䅁䥁流欵䉁䅁䅁允䅁䅁䅕浚浚浚浢歌䵁䅉䅅䅁䙁䅁䅁睁䵁䅁䅁权䅁䅁䅁权䉁䅁䅁权䙁䅁䅁兂䅁䅁䅁䵷汦䅑䅅䅁䉁䅁䅁兂㥁瑃橥䑣愳睐杷允䅁䅁䅕䅁䑁䅁䅷䅁䭁䅁䅁䅁䭁䙁䅍䅁䭁䅁䅕䅁䙁䅁䅁䅁杄畸䅖允䅁䅁䅅䅁䙁偁周㘴扗䑨䅊䍄䉁䅁䅁䅂䅁䅁䅍䅄䅁䅁䅯睔䅁䅁䅯杔䅁䅁䅕䅁䅁佁畂欵䉁䅁䅁允䅁䅁䅯睇䅁䅁杷允䅁䅁䅕䅁䑁䅁䅷䅁䭁䉁䅷䅁䭁䙁䅍䅁䭁䅁䅕䅁䙁䅁䅁䅁杄甯䅖允䅁䅁䅅䅁䙁䙁㘶兓䍷祡䄱䍄䉁䅁䅁兂䅁䅁䅍䅄䅁䅁䅯先䅁䅁䅯允䅁䅁䅯兂䅁䅁䅕䅁䅁䅁䥁欵䉁䅁䅁允䅁䅁䅕㑈牘払敧吱䴸䅉䅅䅁䙁䅁䅁睁䵁䅁䅁权摁䅁䅁权呂䅁䅁权䙁䅁䅁兂䅁䅁䅁䝁浲䅑䅅䅁䉁䅁䅁兂㍁啩杆刵畁䅑杷允䅁䅁䅕䅁䑁䅁䅷䅁䭁䅁䅁䅁䭁䙁䅍䅁䭁䅁䅕䅁䙁䅁䅁䅁杂敗䅚允䅁䅁䅅䅁䙁䑁ね䡹⭡稳䅎䍄䉁䅁䅁兂䅁䅁䅍䅄䅁䅁䅯杇䅁䅁䅯允䅁䅁䅯兂䅁䅁䅕䅁䅁䕁䍂欵䉁䅁䅁允䅁䅁䅕䡰㥁瑃橥䐶䴸䅉䅅䅁䙁䅁䅁睁䵁䅁䅁权敁䅁䅁权呂䅁䅁权䙁䅁䅁兂䅁䅁䅁䙉浔䅑䅅䅁䉁䅁䅁兂扄堫焵䡶楑䅑杷允䅁䅁䅑䅁䑁䅁䅷䅁䭁䕁䄸䅁䭁䕁䄴䅁䙁䅁䅁䅁杄⭯䅖允䅁䅁䅅䅁䙁䉁䘫ㄶ㑇瑈⽕䍄䉁䅁䅁兂䅁䅁䅍䅄䅁䅁䅯䅁䅁䅁䅯允䅁䅁䅯兂䅁䅁䅕䅁䅁佁瑃唵䉁䅁䅁允䅁䅁䅕灭婭婭婭吲䴸䅉䅅䅁䙁䅁䅁睁䵁䅁䅁权捁䅁䅁权䉁䅁䅁权䙁䅁䅁兂䅁䅁䅁䭁汲䅑䅅䅁䉁䅁䅁兂偃癷潕䥘匯睐杷允䅁䅁䅑䅁䑁䅁䅷䅁䭁䕁䄸䅁䭁䕁䄴䅁䙁䅁䅁䅁杂攱䅖允䅁䅁䅅䅁䙁偁潙䥘䌯儹䅚䍄䉁䅁䅁兂䅁䅁䅍䅄䅁䅁䅯䅈䅁䅁䅯允䅁䅁䅯兂䅁䅁䅕䅁䅁䍁牁欵䉁䅁䅁允䅁䅁䅕歲桦桥畓稱䴸䅉䅅䅁䙁䅁䅁睁䵁䅁䅁权慁䅁䅁权䉁䅁䅁权䙁䅁䅁兂䅁䅁䅁䱑汪䅑䅅䅁䉁䅁䅁兂䅁䅁䅁䅁杄睐杷允䅁䅁䅕䅁䑁䅁䅷䅁䭁䉁䄰䅁䭁䙁䅍䅁䭁䅁䅕䅁䙁䅁䅁䅁杂略䅚允䅁䅁䅅䅁䙁偁湃歸㍳卹䄱䍄䉁䅁䅁䅂䅁䅁䅍䅄䅁䅁䅯睔䅁䅁䅯杔䅁䅁䅕䅁䅁䥁汁欵䉁䅁䅁允䅁䅁䅕体㙆䭆䠵啅䵁䅉䅅䅁䙁䅁䅁睁䵁䅁䅁权慁䅁䅁权䉁䅁䅁权䙁䅁䅁兂䅁䅁䅁䕁洷䅑䅅䅁䉁䅁䅁兂歃䑣䬰㘱潐睐杷允䅁䅁䅕䅁䑁䅁䅷䅁䭁䉁䅯䅁䭁䙁䅍䅁䭁䅁䅕䅁䙁䅁䅁䅁䅄畉䅚允䅁䅁䅅䅁䙁䱁穢搯㑒呩䅰䍄䉁䅁䅁兂䅁䅁䅍䅄䅁䅁䅯睈䅁䅁䅯睕䅁䅁䅯兂䅁䅁䅕䅁䅁䅁⽃唵䉁䅁䅁允䅁䅁䅕塹⭡确癯啍䵁䅉䅅䅁䙁䅁䅁睁䵁䅁䅁权䅁䅁䅁权䉁䅁䅁权䙁䅁䅁兂䅁䅁䅁䩧汘䅑䅅䅁䉁䅁䅁兂慃婭婭婭婮睐杷允䅁䅁䅕䅁䑁䅁䅷䅁䭁䅁䅁䅁䭁䅁䅅䅁䭁䅁䅕䅁䙁䅁䅁䅁杁畡䅚允䅁䅁䅅䅁䙁䱁敧敨剴乵⼴䍄䉁䅁䅁兂䅁䅁䅍䅄䅁䅁䅯䅈䅁䅁䅯允䅁䅁䅯兂䅁䅁䅕䅁䅁䝁桃唵䉁䅁䅁允䅁䅁䅕㡪ㅌ䙋偹樰䴸䅉䅅䅁䙁䅁䅁睁䵁䅁䅁权捁䅁䅁权䉁䅁䅁权䙁䅁䅁兂䅁䅁䅁偉汮䅑䅅䅁䉁䅁䅁兂晁敨剴䉵嘷睐杷允䅁䅁䅑䅁䑁䅁䅷䅁䭁䕁䄸䅁䭁䕁䄴䅁䙁䅁䅁䅁䅃畕䅚允䅁䅁䅅䅁䙁佁剸䉵䘶眶䄹䍄䉁䅁䅁兂䅁䅁䅍䅄䅁䅁䅯杈䅁䅁䅯睕䅁䅁䅯兂䅁䅁䅕䅁䅁䝁㉁欵䉁䅁䅁允䅁䅁䅕体㙆䭆䠵歊䵁䅉䅅䅁䙁䅁䅁睁䵁䅁䅁权晁䅁䅁权䉁䅁䅁权䙁䅁䅁兂䅁䅁䅁䭁汶䅑䅅䅁䉁䅁䅁权扁䅁䅁䍄䉁䅁䅁兂䅁䅁䅍䅄䅁䅁䅯先䅁䅁䅯睕䅁䅁䅯兂䅁䅁䅕䅁䅁䥁浃唵䉁䅁䅁允䅁䅁䅕挲㌷⭕汏啌䵁䅉䅅䅁䕁䅁䅁睁䵁䅁䅁权偂䅁䅁权佂䅁䅁兂䅁䅁䅁䙁浺䅑䅅䅁䉁䅁䅁兂慃婭婭婭偫䅑杷允䅁䅁䅕䅁䑁䅁䅷䅁䭁䉁䄴䅁䭁䅁䅅䅁䭁䅁䅕䅁䙁䅁䅁䅁䅂數䅖允䅁䅁䅅䅁䙁䑁積積積㥍⽍䍄䉁䅁䅁䅂䅁䅁䅍䅄䅁䅁䅯睔䅁䅁䅯杔䅁䅁䅕䅁䅁佁䍄唵䉁䅁䅁允䅁䅁䅕浚浚浚浚樸䴸䅉䅅䅁䙁䅁䅁睁䵁䅁䅁权敁䅁䅁权䉁䅁䅁权䙁䅁䅁兂䅁䅁䅁䑙浺䅑䅅䅁䉁䅁䅁兂䑄匹捨㡪噌睐杷允䅁䅁䅑䅁䑁䅁䅷䅁䭁䕁䄸䅁䭁䕁䄴䅁䙁䅁䅁䅁䅂佢䅚允䅁䅁䅅䅁䙁䱁敧敨剴䅵䅸䍄䉁䅁䅁兂䅁䅁䅍䅄䅁䅁䅯䅁䅁䅁䅯睕䅁䅁䅯兂䅁䅁䅕䅁䅁䝁慁欵䉁䅁䅁允䅁䅁䅕硢䑋䵷䉯き䵁䅉䅅䅁䕁䅁䅁睁䵁䅁䅁权偂䅁䅁权佂䅁䅁兂䅁䅁䅁䑉浘䅑䅅䅁䉁䅁䅁兂慃婭婭婭剫䅑杷允䅁䅁䅕䅁䑁䅁䅷䅁䭁䉁䄸䅁䭁䅁䅅䅁䭁䅁䅕䅁䙁䅁䅁䅁䅄畑䅚允䅁䅁䅅䅁䙁䭁睒児塲⭯⽁䍄䉁䅁䅁䅂䅁䅁䅍䅄䅁䅁䅯睔䅁䅁䅯杔䅁䅁䅕䅁䅁䭁允欵䉁䅁䅁允䅁䅁䅕体㙆䭆䠵ぅ䵁䅉䅅䅁䙁䅁䅁睁䵁䅁䅁权敁䅁䅁权呂䅁䅁权䙁䅁䅁兂䅁䅁䅁䉉浐䅑䅅䅁䉁䅁䅁兂療潅䅐畹灅䅑杷允䅁䅁䅑䅁䑁䅁䅷䅁䭁䕁䄸䅁䭁䕁䄴䅁䙁䅁䅁䅁䅃畢䅚允䅁䅁䅅䅁䙁䍁捬㡪ㅌ䅋䅸䍄䉁䅁䅁兂䅁䅁䅍䅄䅁䅁䅯杇䅁䅁䅯允䅁䅁䅯兂䅁䅁䅕䅁䅁䥁ㅂ欵䉁䅁䅁允䅁䅁䅕䡰㥁瑃橥䐶䴸䅉䅅䅁䙁䅁䅁睁䵁䅁䅁权摁䅁䅁权呂䅁䅁权䙁䅁䅁兂䅁䅁䅁䍯浄䅑䅅䅁䉁䅁䅁兂䭁㘱睎捐畯䅑杷允䅁䅁䅑䅁䑁䅁䅷䅁䭁䕁䄸䅁䭁䕁䄴䅁䙁䅁䅁䅁权故䅚允䅁䅁䅅䅁䙁䙁㑋潈牘剕䅎䍄䉁䅁䅁兂䅁䅁䅍䅄䅁䅁䅯睈䅁䅁䅯睕䅁䅁䅯兂䅁䅁䅕䅁䅁䍁時欵䉁䅁䅁允䅁䅁䅕匰扌堫䬴啍䵁䅉䅅䅁䕁䅁䅁睁䵁䅁䅁权偂䅁䅁权佂䅁䅁兂䅁䅁䅁䝙洷䅑䅅䅁䉁䅁䅁兂㑃潈牘払䵧䅑杷允䅁䅁䅕䅁䑁䅁䅷䅁䭁䅁䅁䅁䭁䙁䅍䅁䭁䅁䅕䅁䙁䅁䅁䅁䅃敳䅖允䅁䅁䅅䅁䙁䱁䩰䅄牉穊䅊䍄䉁䅁䅁兂䅁䅁䅍䅄䅁䅁䅯䅁䅁䅁䅯允䅁䅁䅯兂䅁䅁䅕䅁䅁䥁㍃唵䉁䅁䅁允䅁䅁䅕灭婭婭婭吲䴸䅉䅅䅁䙁䅁䅁睁䵁䅁䅁权摁䅁䅁权䉁䅁䅁权䙁䅁䅁兂䅁䅁䅁䍁浮䅑䅅䅁䉁䅁䅁兂浂浚浚浚坢睐杷允䅁䅁䅕䅁䑁䅁䅷䅁䭁䅁䅁䅁䭁䅁䅅䅁䭁䅁䅕䅁䙁䅁䅁䅁杂敧䅚允䅁䅁䅅䅁䙁䱁敧敨剴乵⼴䍄䉁䅁䅁䅂䅁䅁䅍䅄䅁䅁䅯睔䅁䅁䅯杔䅁䅁䅕䅁䅁䭁塁欵䉁䅁䅁允䅁䅁䅕䉵䘶ㄶ㑇歅䵁䅉䅅䅁䙁䅁䅁睁䵁䅁䅁权晁䅁䅁权䉁䅁䅁权䙁䅁䅁兂䅁䅁䅁䱁汌䅑䅅䅁䉁䅁䅁兂䙃ㄶ㑇潈托睐杷允䅁䅁䅑䅁䑁䅁䅷䅁䭁䕁䄸䅁䭁䕁䄴䅁䙁䅁䅁䅁杄敖䅚允䅁䅁䅅䅁啁䅁䅑䅁䅁䅁䅁䍄䉁䅁䅁兂䅁䅁䅍䅄䅁䅁䅯䅁䅁䅁䅯睕䅁䅁䅯兂䅁䅁䅕䅁䅁䝁扃唵䉁䅁䅁允䅁䅁䅕㘱睎児㍲䕍䵁䅉䅅䅁䙁䅁䅁睁䵁䅁䅁权摁䅁䅁权呂䅁䅁权䙁䅁䅁兂䅁䅁䅁䝧浺䅑䅅䅁䉁䅁䅁兂㍁啩杆刵畁䅑杷允䅁䅁䅕䅁䑁䅁䅷䅁䭁䅁䅁䅁䭁䙁䅍䅁䭁䅁䅕䅁䙁䅁䅁䅁权畔䅚允䅁䅁䅅䅁䙁䉁䑋䵷桱呸䅎䍄䉁䅁䅁兂䅁䅁䅍䅄䅁䅁䅯先䅁䅁䅯允䅁䅁䅯兂䅁䅁䅕䅁䅁䥁穄唵䉁䅁䅁允䅁䅁䅕㘱睎児塲稰䴸䅉䅅䅁䕁䅁䅁睁䵁䅁䅁权偂䅁䅁权佂䅁䅁兂䅁䅁䅁䝯浮䅑䅅䅁䉁䅁䅁权扁䅁䅁䍄䉁䅁䅁兂䅁䅁䅍䅄䅁䅁䅯䅁䅁䅁䅯睕䅁䅁䅯兂䅁䅁䅕䅁䅁䵁求欵䉁䅁䅁允䅁䅁䅕佖汏㡭杔き䵁䅉䅅䅁䙁䅁䅁睁䵁䅁䅁权䅁䅁䅁权䉁䅁䅁权䙁䅁䅁兂䅁䅁䅁偧汐䅑䅅䅁䉁䅁䅁兂䙃ㄶ㑇潈托睐杷允䅁䅁䅕䅁䑁䅁䅷䅁䭁䅁䅁䅁䭁䅁䅅䅁䭁䅁䅕䅁䙁䅁䅁䅁杁畅䅚允䅁䅁䅅䅁䙁䱁敧敨剴乵⼴䍄䉁䅁䅁兂䅁䅁䅍䅄䅁䅁䅯䅁䅁䅁䅯睕䅁䅁䅯兂䅁䅁䅕䅁䅁佁獄唵䉁䅁䅁允䅁䅁䅕積積積呏歍䵁䅉䅅䅁䙁䅁䅁睁䵁䅁䅁权晁䅁䅁权䉁䅁䅁权䙁䅁䅁兂䅁䅁䅁䨴汢䅑䅅䅁䉁䅁䅁兂卂䉵䘶ㄶ杈睐杷允䅁䅁䅑䅁䑁䅁䅷䅁䭁䕁䄸䅁䭁䕁䄴䅁䙁䅁䅁䅁䅃佢䅚允䅁䅁䅅䅁䙁䵁䴳䵺䵺䅺䅸䍄䉁䅁䅁兂䅁䅁䅍䅄䅁䅁䅯杇䅁䅁䅯允䅁䅁䅯兂䅁䅁䅕䅁䅁䝁慁欵䉁䅁䅁允䅁䅁䅕䡰㥁瑃橥䐶䴸䅉䅅䅁䙁䅁䅁睁䵁䅁䅁权䅁䅁䅁权呂䅁䅁权䙁䅁䅁兂䅁䅁䅁䡉浪䅑䅅䅁䉁䅁䅁兂啂㘴扗䅸ぁ䅑杷允䅁䅁䅕䅁䑁䅁䅷䅁䭁䉁䄸䅁䭁䙁䅍䅁䭁䅁䅕䅁䙁䅁䅁䅁杂⭷䅖允䅁䅁䅅䅁䙁䵁㉬灶愸穌䅆䍄䉁䅁䅁䅂䅁䅁䅍䅄䅁䅁䅯睔䅁䅁䅯杔䅁䅁䅕䅁䅁䕁瑂欵䉁䅁䅁允䅁䅁䅕場啯歲桦䕄䵁䅉䅅䅁䙁䅁䅁睁䵁䅁䅁权䅁䅁䅁权䉁䅁䅁权䙁䅁䅁兂䅁䅁䅁䭧氯䅑䅅䅁䉁䅁䅁兂慃婭婭婭婮睐杷允䅁䅁䅕䅁䑁䅁䅷䅁䭁䉁䄰䅁䭁䙁䅍䅁䭁䅁䅕䅁䙁䅁䅁䅁䅁收䅖允䅁䅁䅅䅁䙁䭁扡䍸睃楳䄱䍄䉁䅁䅁兂䅁䅁䅍䅄䅁䅁䅯睈䅁䅁䅯睕䅁䅁䅯兂䅁䅁䅕䅁䅁䵁䉁欵䉁䅁䅁允䅁䅁䅕㡧䭄啯块䕍䵁䅉䅅䅁䕁䅁䅁睁䵁䅁䅁权偂䅁䅁权佂䅁䅁兂䅁䅁䅁䝑洷䅑䅅䅁䉁䅁䅁兂歃䑣䬰㘱䵍䅑杷允䅁䅁䅕䅁䑁䅁䅷䅁䭁䉁䅷䅁䭁䅁䅅䅁䭁䅁䅕䅁䙁䅁䅁䅁杂⭥䅚允䅁䅁䅅䅁䙁偁潙䥘䌯搹⽧䍄䉁䅁䅁兂䅁䅁䅍䅄䅁䅁䅯杈䅁䅁䅯睕䅁䅁䅯兂䅁䅁䅕䅁䅁䅁桁欵䉁䅁䅁允䅁䅁䅕兇坒楄礱啋䵁䅉䅅䅁䙁䅁䅁睁䵁䅁䅁权慁䅁䅁权呂䅁䅁权䙁䅁䅁兂䅁䅁䅁䐴浐䅑䅅䅁䉁䅁䅁兂晁敨剴乵㘴䅑杷允䅁䅁䅑䅁䑁䅁䅷䅁䭁䕁䄸䅁䭁䕁䄴䅁䙁䅁䅁䅁杁畮䅖允䅁䅁䅅䅁䙁䉁䘫ㄶ㑇瑈⽕䍄䉁䅁䅁䅂䅁䅁䅍䅄䅁䅁䅯睔䅁䅁䅯杔䅁䅁䅕䅁䅁䝁潁欵䉁䅁䅁允䅁䅁䅕灭婭婭婭啅䵁䅉䅅䅁䙁䅁䅁睁䵁䅁䅁权慁䅁䅁权䉁䅁䅁权䙁䅁䅁兂䅁䅁䅁䙑浈䅑䅅䅁䉁䅁䅁兂歃䑣䬰㘱潐睐杷允䅁䅁䅕䅁䑁䅁䅷䅁䭁䉁䄰䅁䭁䅁䅅䅁䭁䅁䅕䅁䙁䅁䅁䅁䅄⭳䅖允䅁䅁䅅䅁䙁乁橥䑣䬰㤱⽍䍄䉁䅁䅁兂䅁䅁䅍䅄䅁䅁䅯杈䅁䅁䅯允䅁䅁䅯兂䅁䅁䅕䅁䅁䭁杄唵䉁䅁䅁允䅁䅁䅕積積積積稰䴸䅉䅅䅁䕁䅁䅁睁䵁䅁䅁权偂䅁䅁权佂䅁䅁兂䅁䅁䅁䝉洷䅑䅅䅁䉁䅁䅁兂㝂䭆䠵場䵯䅑杷允䅁䅁䅕䅁䑁䅁䅷䅁䭁䅁䅁䅁䭁䙁䅍䅁䭁䅁䅕䅁䙁䅁䅁䅁䅂畴䅖允䅁䅁䅅䅁䙁䱁䩰䅄牉穊䅊䍄䉁䅁䅁兂䅁䅁䅍䅄䅁䅁䅯杇䅁䅁䅯睕䅁䅁䅯兂䅁䅁䅕䅁䅁䍁啄唵䉁䅁䅁允䅁䅁䅕祇搯䅊桙歏䵁䅉䅅䅁䙁䅁䅁睁䵁䅁䅁权捁䅁䅁权䉁䅁䅁权䙁䅁䅁兂䅁䅁䅁䭙氷䅑䅅䅁䉁䅁䅁兂偃癷潕䥘匯睐杷允䅁䅁䅕䅁䑁䅁䅷䅁䭁䉁䅷䅁䭁䅁䅅䅁䭁䅁䅕䅁䙁䅁䅁䅁杄伹䅖允䅁䅁䅅䅁䙁䉁䘫ㄶ㑇瑈⽕䍄䉁䅁䅁䅂䅁䅁䅍䅄䅁䅁䅯睔䅁䅁䅯杔䅁䅁䅕䅁䅁䵁䍄唵䉁䅁䅁允䅁䅁䅕灭婭婭婭吸䴸䅉䅅䅁䙁䅁䅁睁䵁䅁䅁权䅁䅁䅁权䉁䅁䅁权䙁䅁䅁兂䅁䅁䅁䝁浪䅑䅅䅁䉁䅁䅁兂㑃潈牘払敪睐杷允䅁䅁䅕䅁䑁䅁䅷䅁䭁䅁䅁䅁䭁䙁䅍䅁䭁䅁䅕䅁䙁䅁䅁䅁䅃敘䅚允䅁䅁䅅䅁䙁䭁硲欰椱䐰䅎䍄䉁䅁䅁兂䅁䅁䅍䅄䅁䅁䅯䅁䅁䅁䅯睕䅁䅁䅯兂䅁䅁䅕䅁䅁䥁浄唵䉁䅁䅁允䅁䅁䅕兇坒楄匳歍䵁䅉䅅䅁䕁䅁䅁睁䵁䅁䅁权偂䅁䅁权佂䅁䅁兂䅁䅁䅁䝁洷䅑䅅䅁䉁䅁䅁兂䭁㘱睎児乯䅑杷允䅁䅁䅑䅁䑁䅁䅷䅁䭁䕁䄸䅁䭁䕁䄴䅁䙁䅁䅁䅁䅂⬲䅖允䅁䅁䅅䅁䙁䅁䅁䅁䅁䅁䅰䍄䉁䅁䅁兂䅁䅁䅍䅄䅁䅁䅯先䅁䅁䅯睕䅁䅁䅯兂䅁䅁䅕䅁䅁䕁流欵䉁䅁䅁允䅁䅁䅕浚浚浚浢歌䵁䅉䅅䅁䕁䅁䅁睁䵁䅁䅁权偂䅁䅁权佂䅁䅁兂䅁䅁䅁䙧洷䅑䅅䅁䉁䅁䅁兂㑃潈牘払佧䅑杷允䅁䅁䅑䅁䑁䅁䅷䅁䭁䕁䄸䅁䭁䕁䄴䅁䙁䅁䅁䅁䅃⭙䅚允䅁䅁䅅䅁䙁佁㙆䭆䠵儴䄵䍄䉁䅁䅁䅂䅁䅁䅍䅄䅁䅁䅯睔䅁䅁䅯杔䅁䅁䅕䅁䅁䭁瑂欵䉁䅁䅁允䅁䅁䅕䉵䘶ㄶ㑇䕄䵁䅉䅅䅁䙁䅁䅁睁䵁䅁䅁权摁䅁䅁权䉁䅁䅁权䙁䅁䅁兂䅁䅁䅁䡷浮䅑䅅䅁䉁䅁䅁兂畃⭒㙆䭆堷睐杷允䅁䅁䅕䅁䑁䅁䅷䅁䭁䉁䄸䅁䭁䙁䅍䅁䭁䅁䅕䅁䙁䅁䅁䅁杁⭬䅖允䅁䅁䅅䅁䙁䅁䅁䅁䅁䐴䅂䍄䉁䅁䅁兂䅁䅁䅍䅄䅁䅁䅯睈䅁䅁䅯睕䅁䅁䅯兂䅁䅁䅕䅁䅁佁䅁欵䉁䅁䅁允䅁䅁䅕㡧䭄啯块䕍䵁䅉䅅䅁䕁䅁䅁睁䵁䅁䅁权偂䅁䅁权佂䅁䅁兂䅁䅁䅁偧氷䅑䅅䅁䉁䅁䅁兂䅁䅁䅁䅁佁䅑杷允䅁䅁䅕䅁䑁䅁䅷䅁䭁䉁䅯䅁䭁䙁䅍䅁䭁䅁䅕䅁䙁䅁䅁䅁䅄敘䅚允䅁䅁䅅䅁䙁䱁昶楇搯䑚䅴䍄䉁䅁䅁兂䅁䅁䅍䅄䅁䅁䅯先䅁䅁䅯允䅁䅁䅯兂䅁䅁䅕䅁䅁䅁噄唵䉁䅁䅁允䅁䅁䅕㘱睎児塲稰䴸䅉䅅䅁䕁䅁䅁睁䵁䅁䅁权偂䅁䅁权佂䅁䅁兂䅁䅁䅁䉁浔䅑䅅䅁䉁䅁䅁兂䭁㘱睎児啯䅑杷允䅁䅁䅕䅁䑁䅁䅷䅁䭁䉁䄴䅁䭁䙁䅍䅁䭁䅁䅕䅁䙁䅁䅁䅁杂⭲䅖允䅁䅁䅅䅁䙁䱁穢搯㑒卡䅸䍄䉁䅁䅁兂䅁䅁䅍䅄䅁䅁䅯睈䅁䅁䅯允䅁䅁䅯兂䅁䅁䅕䅁䅁䅁穄唵䉁䅁䅁允䅁䅁䅕場啯歲桦樲䴸䅉䅅䅁䙁䅁䅁睁䵁䅁䅁权晁䅁䅁权呂䅁䅁权䙁䅁䅁兂䅁䅁䅁䅁洯䅑䅅䅁䉁䅁䅁兂䕁杖琴牳眰䅑杷允䅁䅁䅕䅁䑁䅁䅷䅁䭁䉁䄸䅁䭁䙁䅍䅁䭁䅁䅕䅁䙁䅁䅁䅁杁敕䅚允䅁䅁䅅䅁䙁䡁⼰噎㘶呋䅆䍄䉁䅁䅁䅂䅁䅁䅍䅄䅁䅁䅯睔䅁䅁䅯杔䅁䅁䅕䅁䅁䕁十欵䉁䅁䅁允䅁䅁䅕捺䵺䵺䵺ぅ䵁䅉䅅䅁䙁䅁䅁睁䵁䅁䅁权敁䅁䅁权呂䅁䅁权䙁䅁䅁兂䅁䅁䅁䝙浈䅑䅅䅁䉁䅁䅁兂剃堷⽷噎椴䅑杷允䅁䅁䅑䅁䑁䅁䅷䅁䭁䕁䄸䅁䭁䕁䄴䅁䙁䅁䅁䅁杄敆䅚允䅁䅁䅅䅁䙁䅁塲㍯㥁桃䅎䍄䉁䅁䅁兂䅁䅁䅍䅄䅁䅁䅯䅁䅁䅁䅯允䅁䅁䅯兂䅁䅁䅕䅁䅁䝁㥄唵䉁䅁䅁允䅁䅁䅕䉵䘶ㄶ㑇樳䴸䅉䅅䅁䕁䅁䅁睁䵁䅁䅁权偂䅁䅁权佂䅁䅁兂䅁䅁䅁余汮䅑䅅䅁䉁䅁䅁兂畃⭒㙆䭆儴䅑杷允䅁䅁䅕䅁䑁䅁䅷䅁䭁䅁䅁䅁䭁䙁䅍䅁䭁䅁䅕䅁䙁䅁䅁䅁䅄畣䅚允䅁䅁䅅䅁䙁䙁橔婰䕶䑁䅒䍄䉁䅁䅁䅂䅁䅁䅍䅄䅁䅁䅯睔䅁䅁䅯杔䅁䅁䅕䅁䅁䝁瑂欵䉁䅁䅁允䅁䅁䅕硥畓⭒㙆䕄䵁䅉䅅䅁䕁䅁䅁睁䵁䅁䅁权偂䅁䅁权佂䅁䅁兂䅁䅁䅁䔴浪䅑䅅䅁䉁䅁䅁兂塄㍯㥁瑃兣䅑杷允䅁䅁䅕䅁䑁䅁䅷䅁䭁䉁䅯䅁䭁䅁䅅䅁䭁䅁䅕䅁䙁䅁䅁䅁䅃电䅖允䅁䅁䅅䅁䙁偁潙䥘䌯改⽁䍄䉁䅁䅁兂䅁䅁䅍䅄䅁䅁䅯睈䅁䅁䅯允䅁䅁䅯兂䅁䅁䅕䅁䅁䝁⭄唵䉁䅁䅁允䅁䅁䅕体㙆䭆䠵吴䴸䅉䅅䅁䙁䅁䅁睁䵁䅁䅁权䅁䅁䅁权䉁䅁䅁权䙁䅁䅁兂䅁䅁䅁䥷浄䅑䅅䅁䉁䅁䅁兂㑃潈牘払敪睐杷允䅁䅁䅕䅁䑁䅁䅷䅁䭁䉁䅯䅁䭁䅁䅅䅁䭁䅁䅕䅁䙁䅁䅁䅁杂畣䅚允䅁䅁䅅䅁䙁䭁睒児塲⭯⽧䍄䉁䅁䅁兂䅁䅁䅍䅄䅁䅁䅯杇䅁䅁䅯睕䅁䅁䅯兂䅁䅁䅕䅁䅁䥁䵁欵䉁䅁䅁允䅁䅁䅕潂噇㑑䵴歏䵁䅉䅅䅁䕁䅁䅁睁䵁䅁䅁权偂䅁䅁权佂䅁䅁兂䅁䅁䅁䑯浶䅑䅅䅁䉁䅁䅁兂啁歲桦桥佑䅑杷允䅁䅁䅑䅁䑁䅁䅷䅁䭁䕁䄸䅁䭁䕁䄴䅁䙁䅁䅁䅁杄敡䅚允䅁䅁䅅䅁䙁䭁睒児塲睯䅸䍄䉁䅁䅁兂䅁䅁䅍䅄䅁䅁䅯杈䅁䅁䅯睕䅁䅁䅯兂䅁䅁䅕䅁䅁䍁佂欵䉁䅁䅁允䅁䅁䅕渷⽷噎㘴䕊䵁䅉䅅䅁䙁䅁䅁睁䵁䅁䅁权敁䅁䅁权䉁䅁䅁权䙁䅁䅁兂䅁䅁䅁䉷浘䅑䅅䅁䉁䅁䅁兂䑄匹捨㡪噌睐杷允䅁䅁䅑䅁䑁䅁䅷䅁䭁䕁䄸䅁䭁䕁䄴䅁䙁䅁䅁䅁杁畸䅖允䅁䅁䅅䅁䙁䑁䬰㘱睎晐⽙䍄䉁䅁䅁兂䅁䅁䅍䅄䅁䅁䅯䅈䅁䅁䅯允䅁䅁䅯兂䅁䅁䅕䅁䅁䕁奂欵䉁䅁䅁允䅁䅁䅕椹捨㡪ㅌ䐲䴸䅉䅅䅁䙁䅁䅁睁䵁䅁䅁权晁䅁䅁权呂䅁䅁权䙁䅁䅁兂䅁䅁䅁佁決䅑䅅䅁䉁䅁䅁兂橁⼲⭬污睷䅑杷允䅁䅁䅕䅁䑁䅁䅷䅁䭁䉁䄸䅁䭁䅁䅅䅁䭁䅁䅕䅁䙁䅁䅁䅁权畵䅖允䅁䅁䅅䅁䙁䥁牘払敧摨⽳䍄䉁䅁䅁兂䅁䅁䅍䅄䅁䅁䅯䅈䅁䅁䅯睕䅁䅁䅯兂䅁䅁䅕䅁䅁䥁䍃欵䉁䅁䅁允䅁䅁䅕塹⭡确癱啌䵁䅉䅅䅁䕁䅁䅁睁䵁䅁䅁权偂䅁䅁权佂䅁䅁兂䅁䅁䅁䝑浄䅑䅅䅁䉁䅁䅁兂晁敨剴䉵倴䅑杷允䅁䅁䅕䅁䑁䅁䅷䅁䭁䅁䅁䅁䭁䅁䅅䅁䭁䅁䅕䅁䙁䅁䅁䅁䅄救䅚允䅁䅁䅅䅁䙁䱁敧敨剴乵⼴䍄䉁䅁䅁兂䅁䅁䅍䅄䅁䅁䅯睈䅁䅁䅯允䅁䅁䅯兂䅁䅁䅕䅁䅁䥁㉃唵䉁䅁䅁允䅁䅁䅕敨剴䉵䘶稲䴸䅉䅅䅁䕁䅁䅁睁䵁䅁䅁权偂䅁䅁权佂䅁䅁兂䅁䅁䅁䝷浺䅑䅅䅁䉁䅁䅁兂䥂場啯歲乣䅑杷允䅁䅁䅕䅁䑁䅁䅷䅁䭁䉁䅯䅁䭁䙁䅍䅁䭁䅁䅕䅁䙁䅁䅁䅁权⬰䅖允䅁䅁䅅䅁䙁䉁癳匳䝑呉䅰䍄䉁䅁䅁兂䅁䅁䅍䅄䅁䅁䅯先䅁䅁䅯睕䅁䅁䅯兂䅁䅁䅕䅁䅁䝁噃唵䉁䅁䅁允䅁䅁䅕䡶呓䅇坒啌䵁䅉䅅䅁䕁䅁䅁睁䵁䅁䅁权偂䅁䅁权佂䅁䅁兂䅁䅁䅁䍙洳䅑䅅䅁䉁䅁䅁兂浂浚浚浚卙䅑杷允䅁䅁䅑䅁䑁䅁䅷䅁䭁䕁䄸䅁䭁䕁䄴䅁䙁䅁䅁䅁杄⭡䅚允䅁䅁䅅䅁䙁䡁啳歲桦来䅸䍄䉁䅁䅁兂䅁䅁䅍䅄䅁䅁䅯䅈䅁䅁䅯睕䅁䅁䅯兂䅁䅁䅕䅁䅁䝁坂欵䉁䅁䅁允䅁䅁䅕匳䝑婧䑖歌䵁䅉䅅䅁䙁䅁䅁睁䵁䅁䅁权䅁䅁䅁权䉁䅁䅁权䙁䅁䅁兂䅁䅁䅁䑧浺䅑䅅䅁䉁䅁䅁兂㑃潈牘払敪睐杷允䅁䅁䅕䅁䑁䅁䅷䅁䭁䉁䄴䅁䭁䙁䅍䅁䭁䅁䅕䅁䙁䅁䅁䅁杂佯䅖允䅁䅁䅅䅁䙁䍁扐堫焵䍦䅰䍄䉁䅁䅁兂䅁䅁䅍䅄䅁䅁䅯先䅁䅁䅯睕䅁䅁䅯兂䅁䅁䅕䅁䅁䅁䍁欵䉁䅁䅁允䅁䅁䅕䝭匴㡧䭂歌䵁䅉䅅䅁䕁䅁䅁睁䵁䅁䅁权偂䅁䅁权佂䅁䅁兂䅁䅁䅁䕉浶䅑䅅䅁䉁䅁䅁兂啁歲桦桥剑䅑杷允䅁䅁䅕䅁䑁䅁䅷䅁䭁䉁䅯䅁䭁䅁䅅䅁䭁䅁䅕䅁䙁䅁䅁䅁杂敐䅚允䅁䅁䅅䅁䙁䭁睒児塲⭯⽧䍄䉁䅁䅁䅂䅁䅁䅍䅄䅁䅁䅯睔䅁䅁䅯杔䅁䅁䅕䅁䅁䭁牂欵䉁䅁䅁允䅁䅁䅕䭆䠵場啯䕄䵁䅉䅅䅁䕁䅁䅁睁䵁䅁䅁权偂䅁䅁权佂䅁䅁兂䅁䅁䅁䵧汮䅑䅅䅁䉁䅁䅁兂獄払敧敨㕶睐杷允䅁䅁䅑䅁䑁䅁䅷䅁䭁䕁䄸䅁䭁䕁䄴䅁䙁䅁䅁䅁杁敁䅚允䅁䅁䅅䅁䙁乁橥䑣䬰眱䄹䍄䉁䅁䅁䅂䅁䅁䅍䅄䅁䅁䅯睔䅁䅁䅯杔䅁䅁䅕䅁䅁䥁䩂欵䉁䅁䅁允䅁䅁䅕浚浚浚浚啅䵁䅉䅅䅁䙁䅁䅁睁䵁䅁䅁权䅁䅁䅁权䉁䅁䅁权䙁䅁䅁兂䅁䅁䅁䝯浘䅑䅅䅁䉁䅁䅁兂㑃潈牘払敪睐杷允䅁䅁䅕䅁䑁䅁䅷䅁䭁䉁䄰䅁䭁䙁䅍䅁䭁䅁䅕䅁䙁䅁䅁䅁䅄畦䅚允䅁䅁䅅䅁䙁偁湃歸㍳卹䄱䍄䉁䅁䅁䅂䅁䅁䅍䅄䅁䅁䅯睔䅁䅁䅯杔䅁䅁䅕䅁䅁䕁䱂欵䉁䅁䅁允䅁䅁䅕䭆䠵場啯啅䵁䅉䅅䅁䙁䅁䅁睁䵁䅁䅁权晁䅁䅁权呂䅁䅁权䙁䅁䅁兂䅁䅁䅁偯決䅑䅅䅁䉁䅁䅁兂偄ㄹ橐塰睳䅑杷允䅁䅁䅕䅁䑁䅁䅷䅁䭁䅁䅁䅁䭁䅁䅅䅁䭁䅁䅕䅁䙁䅁䅁䅁䅂佇䅚允䅁䅁䅅䅁䙁䱁敧敨剴乵⼴䍄䉁䅁䅁兂䅁䅁䅍䅄䅁䅁䅯杇䅁䅁䅯允䅁䅁䅯兂䅁䅁䅕䅁䅁䅁祁欵䉁䅁䅁允䅁䅁䅕䡰㥁瑃橥䐶䴸䅉䅅䅁䙁䅁䅁睁䵁䅁䅁权捁䅁䅁权呂䅁䅁权䙁䅁䅁兂䅁䅁䅁䑁洳䅑䅅䅁䉁䅁䅁兂塁挲㌷㙕畍䅑杷允䅁䅁䅕䅁䑁䅁䅷䅁䭁䅁䅁䅁䭁䙁䅍䅁䭁䅁䅕䅁䙁䅁䅁䅁䅁⭅䅚允䅁䅁䅅䅁䙁䉁奂扏䥔橬䅊䍄䉁䅁䅁兂䅁䅁䅍䅄䅁䅁䅯睈䅁䅁䅯允䅁䅁䅯兂䅁䅁䅕䅁䅁䵁汃唵䉁䅁䅁允䅁䅁䅯睇䅁䅁杷允䅁䅁䅑䅁䑁䅁䅷䅁䭁䕁䄸䅁䭁䕁䄴䅁䙁䅁䅁䅁䅁⬸䅖允䅁䅁䅅䅁䙁䅁塲㍯㥁权䄹䍄䉁䅁䅁兂䅁䅁䅍䅄䅁䅁䅯杈䅁䅁䅯睕䅁䅁䅯兂䅁䅁䅕䅁䅁䝁潂欵䉁䅁䅁允䅁䅁䅕匰扌堫焵啉䵁䅉䅅䅁䙁䅁䅁睁䵁䅁䅁权晁䅁䅁权䉁䅁䅁权䙁䅁䅁兂䅁䅁䅁义汢䅑䅅䅁䉁䅁䅁兂乄䵺䵺䵺捺睐杷允䅁䅁䅕䅁䑁䅁䅷䅁䭁䅁䅁䅁䭁䅁䅅䅁䭁䅁䅕䅁䙁䅁䅁䅁䅁畄䅚允䅁䅁䅅䅁䙁䱁敧敨剴乵⼴䍄䉁䅁䅁兂䅁䅁䅍䅄䅁䅁䅯䅁䅁䅁䅯睕䅁䅁䅯兂䅁䅁䅕䅁䅁䝁啁欵䉁䅁䅁允䅁䅁䅕䙅㕧䵴坩歍䵁䅉䅅䅁䕁䅁䅁睁䵁䅁䅁权偂䅁䅁权佂䅁䅁兂䅁䅁䅁䭯氳䅑䅅䅁䉁䅁䅁兂畃⭒㙆䭆堷睐杷允䅁䅁䅕䅁䑁䅁䅷䅁䭁䉁䅯䅁䭁䅁䅅䅁䭁䅁䅕䅁䙁䅁䅁䅁权敘䅚允䅁䅁䅅䅁䙁䭁睒児塲⭯⽧䍄䉁䅁䅁䅂䅁䅁䅍䅄䅁䅁䅯睔䅁䅁䅯杔䅁䅁䅕䅁䅁䝁牂欵䉁䅁䅁允䅁䅁䅕䅁䅁䅁䅁䕄䵁䅉䅅䅁䙁䅁䅁睁䵁䅁䅁权捁䅁䅁权䉁䅁䅁权䙁䅁䅁兂䅁䅁䅁䅉洳䅑䅅䅁䉁䅁䅁兂晁敨剴䉵嘷睐杷允䅁䅁䅕䅁䑁䅁䅷䅁䭁䅁䅁䅁䭁䙁䅍䅁䭁䅁䅕䅁䙁䅁䅁䅁䅂敢䅚允䅁䅁䅅䅁䙁䙁橔婰䕶䐴䅎䍄䉁䅁䅁兂䅁䅁䅍䅄䅁䅁䅯睈䅁䅁䅯允䅁䅁䅯兂䅁䅁䅕䅁䅁䝁䉂欵䉁䅁䅁允䅁䅁䅕䡰㥁瑃橥䐴䴸䅉䅅䅁䙁䅁䅁睁䵁䅁䅁权䅁䅁䅁权呂䅁䅁权䙁䅁䅁兂䅁䅁䅁䝉浮䅑䅅䅁䉁䅁䅁兂啂㘴扗佸穁䅑杷允䅁䅁䅕䅁䑁䅁䅷䅁䭁䉁䅯䅁䭁䅁䅅䅁䭁䅁䅕䅁䙁䅁䅁䅁䅁佮䅖允䅁䅁䅅䅁䙁䅁䅁䅁䅁佁⽁䍄䉁䅁䅁兂䅁䅁䅍䅄䅁䅁䅯杇䅁䅁䅯睕䅁䅁䅯兂䅁䅁䅕䅁䅁䵁䩁欵䉁䅁䅁允䅁䅁䅕牒穢搯契歏䵁䅉䅅䅁䙁䅁䅁睁䵁䅁䅁权敁䅁䅁权呂䅁䅁权䙁䅁䅁兂䅁䅁䅁佯汪䅑䅅䅁䉁䅁䅁兂穂䩡瑈䑦猸䅑杷允䅁䅁䅑䅁䑁䅁䅷䅁䭁䕁䄸䅁䭁䕁䄴䅁䙁䅁䅁䅁权伴䅖允䅁䅁䅅䅁䙁䙁㑋潈牘兕䅸䍄䉁䅁䅁兂䅁䅁䅍䅄䅁䅁䅯䅈䅁䅁䅯睕䅁䅁䅯兂䅁䅁䅕䅁䅁佁慁欵䉁䅁䅁允䅁䅁䅕灳瘳㡰䱙歌䵁䅉䅅䅁䙁䅁䅁睁䵁䅁䅁权摁䅁䅁权䉁䅁䅁权䙁䅁䅁兂䅁䅁䅁偯汔䅑䅅䅁䉁䅁䅁兂塄㍯㥁瑃呦睐杷允䅁䅁䅑䅁䑁䅁䅷䅁䭁䕁䄸䅁䭁䕁䄴䅁䙁䅁䅁䅁䅄男䅖允䅁䅁䅅䅁䙁䙁偹癷潕䉘䅂䍄䉁䅁䅁兂䅁䅁䅍䅄䅁䅁䅯先䅁䅁䅯允䅁䅁䅯兂䅁䅁䅕䅁䅁䵁䉃欵䉁䅁䅁允䅁䅁䅕歲桦桥畓稱䴸䅉䅅䅁䙁䅁䅁睁䵁䅁䅁权䅁䅁䅁权䉁䅁䅁权䙁䅁䅁兂䅁䅁䅁䙉浘䅑䅅䅁䉁䅁䅁兂㑃潈牘払敪睐杷允䅁䅁䅕䅁䑁䅁䅷䅁䭁䅁䅁䅁䭁䙁䅍䅁䭁䅁䅕䅁䙁䅁䅁䅁䅂佢䅚允䅁䅁䅅䅁䙁䙁橔婰䕶䐴䅎䍄䉁䅁䅁䅂䅁䅁䅍䅄䅁䅁䅯睔䅁䅁䅯杔䅁䅁䅕䅁䅁䅁牂欵䉁䅁䅁允䅁䅁䅕噋偹癷潕䕄䵁䅉䅅䅁䙁䅁䅁睁䵁䅁䅁权䅁䅁䅁权䉁䅁䅁权䙁䅁䅁兂䅁䅁䅁䱑氯䅑䅅䅁䉁䅁䅁兂㥁瑃橥䑣愳睐杷允䅁䅁䅕䅁䑁䅁䅷䅁䭁䉁䄴䅁䭁䅁䅅䅁䭁䅁䅕䅁䙁䅁䅁䅁杂畴䅖允䅁䅁䅅䅁䙁䑁積積積㥍⽍䍄䉁䅁䅁䅂䅁䅁䅍䅄䅁䅁䅯睔䅁䅁䅯杔䅁䅁䅕䅁䅁䝁睄唵䉁䅁䅁允䅁䅁䅕䉵䘶ㄶ㑇䕅䵁䅉䅅䅁䕁䅁䅁睁䵁䅁䅁权偂䅁䅁权佂䅁䅁兂䅁䅁䅁䝷浲䅑䅅䅁䉁䅁䅁兂䑄匹捨㡪䱉䅑杷允䅁䅁䅕䅁䑁䅁䅷䅁䭁䉁䄸䅁䭁䙁䅍䅁䭁䅁䅕䅁䙁䅁䅁䅁权⭦䅚允䅁䅁䅅䅁䙁䝁汄䌰扌含䅂䍄䉁䅁䅁兂䅁䅁䅍䅄䅁䅁䅯䅁䅁䅁䅯允䅁䅁䅯兂䅁䅁䅕䅁䅁䅁灄唵䉁䅁䅁允䅁䅁䅕敨剴䉵䘶稲䴸䅉䅅䅁䙁䅁䅁睁䵁䅁䅁权捁䅁䅁权呂䅁䅁权䙁䅁䅁兂䅁䅁䅁䡯浮䅑䅅䅁䉁䅁䅁兂䱃佢㝦晱瑅䅑杷允䅁䅁䅕䅁䑁䅁䅷䅁䭁䉁䄴䅁䭁䅁䅅䅁䭁䅁䅕䅁䙁䅁䅁䅁䅁攱䅖允䅁䅁䅅䅁䙁䑁積積積㥍⽍䍄䉁䅁䅁兂䅁䅁䅍䅄䅁䅁䅯䅁䅁䅁䅯睕䅁䅁䅯兂䅁䅁䅕䅁䅁䍁㥄唵䉁䅁䅁允䅁䅁䅕噋偹癷潖歍䵁䅉䅅䅁䙁䅁䅁睁䵁䅁䅁权䅁䅁䅁权呂䅁䅁权䙁䅁䅁兂䅁䅁䅁䡷洷䅑䅅䅁䉁䅁䅁兂⭄䠱灪癊穅䅑杷允䅁䅁䅑䅁䑁䅁䅷䅁䭁䕁䄸䅁䭁䕁䄴䅁䙁䅁䅁䅁䅁佃䅚允䅁䅁䅅䅁䙁乁橥䑣䬰砱䅂䍄䉁䅁䅁兂䅁䅁䅍䅄䅁䅁䅯䅈䅁䅁䅯允䅁䅁䅯兂䅁䅁䅕䅁䅁䵁歂欵䉁䅁䅁允䅁䅁䅕椹捨㡪ㅌ䐲䴸䅉䅅䅁䙁䅁䅁睁䵁䅁䅁权摁䅁䅁权呂䅁䅁权䙁䅁䅁兂䅁䅁䅁䕙浺䅑䅅䅁䉁䅁䅁兂ㅂ硫䕧潖甴䅑杷允䅁䅁䅑䅁䑁䅁䅷䅁䭁䕁䄸䅁䭁䕁䄴䅁䙁䅁䅁䅁䅃敎䅚允䅁䅁䅅䅁䙁䅁塲㍯㥁桃䅆䍄䉁䅁䅁䅂䅁䅁䅍䅄䅁䅁䅯睔䅁䅁䅯杔䅁䅁䅕䅁䅁䝁畁欵䉁䅁䅁允䅁䅁䅕瑃橥䑣䬰歅䵁䅉䅅䅁䙁䅁䅁睁䵁䅁䅁权晁䅁䅁权䉁䅁䅁权䙁䅁䅁兂䅁䅁䅁䵑汶䅑䅅䅁䉁䅁䅁兂歃䑣䬰㘱材睐杷允䅁䅁䅑䅁䑁䅁䅷䅁䭁䕁䄸䅁䭁䕁䄴䅁䙁䅁䅁䅁杁畡䅚允䅁䅁䅅䅁䙁乁橥䑣䬰眱䅴䍄䉁䅁䅁兂䅁䅁䅍䅄䅁䅁䅯杇䅁䅁䅯睕䅁䅁䅯兂䅁䅁䅕䅁䅁䭁ㅃ唵䉁䅁䅁允䅁䅁䅕穐敖歵獮問䵁䅉䅅䅁䙁䅁䅁睁䵁䅁䅁权䅁䅁䅁权呂䅁䅁权䙁䅁䅁兂䅁䅁䅁䐴洯䅑䅅䅁䉁䅁䅁兂䅁䅁䅁䭁穁䅑杷允䅁䅁䅑䅁䑁䅁䅷䅁䭁䕁䄸䅁䭁䕁䄴䅁䙁䅁䅁䅁权伲䅖允䅁䅁䅅䅁䙁䅁塲㍯㥁权䅬䍄䉁䅁䅁兂䅁䅁䅍䅄䅁䅁䅯睈䅁䅁䅯允䅁䅁䅯兂䅁䅁䅕䅁䅁䵁浄唵䉁䅁䅁允䅁䅁䅕児塲㍯㥁樲䴸䅉䅅䅁䙁䅁䅁睁䵁䅁䅁权摁䅁䅁权䉁䅁䅁权䙁䅁䅁兂䅁䅁䅁䩷汢䅑䅅䅁䉁䅁䅁兂塄㍯㥁瑃呦睐杷允䅁䅁䅕䅁䑁䅁䅷䅁䭁䉁䄰䅁䭁䅁䅅䅁䭁䅁䅕䅁䙁䅁䅁䅁䅂⭢䅚允䅁䅁䅅䅁䙁䭁䠵場啯瑲⽣䍄䉁䅁䅁䅂䅁䅁䅍䅄䅁䅁䅯睔䅁䅁䅯杔䅁䅁䅕䅁䅁䵁敁欵䉁䅁䅁允䅁䅁䅕䭆䠵場啯䕅䵁䅉䅅䅁䙁䅁䅁睁䵁䅁䅁权捁䅁䅁权呂䅁䅁权䙁䅁䅁兂䅁䅁䅁䵯汪䅑䅅䅁䉁䅁䅁兂䙃ㄶ㑇潈畕䅑杷允䅁䅁䅕䅁䑁䅁䅷䅁䭁䉁䅷䅁䭁䅁䅅䅁䭁䅁䅕䅁䙁䅁䅁䅁䅄畃䅚允䅁䅁䅅䅁䙁䉁䘫ㄶ㑇瑈⽕䍄䉁䅁䅁兂䅁䅁䅍䅄䅁䅁䅯杈䅁䅁䅯睕䅁䅁䅯兂䅁䅁䅕䅁䅁䝁㝁欵䉁䅁䅁允䅁䅁䅕倹唳佥浬䕊䵁䅉䅅䅁䕁䅁䅁睁䵁䅁䅁权偂䅁䅁权佂䅁䅁兂䅁䅁䅁䑑浶䅑䅅䅁䉁䅁䅁兂獄払敧敨乳䅑杷允䅁䅁䅑䅁䑁䅁䅷䅁䭁䕁䄸䅁䭁䕁䄴䅁䙁䅁䅁䅁杁敡䅚允䅁䅁䅅䅁䙁䵁䴳䵺䵺䅺䅸䍄䉁䅁䅁兂䅁䅁䅍䅄䅁䅁䅯睈䅁䅁䅯允䅁䅁䅯兂䅁䅁䅕䅁䅁䍁慁欵䉁䅁䅁允䅁䅁䅕椹捨㡪ㅌ䐴䴸䅉䅅䅁䙁䅁䅁睁䵁䅁䅁权慁䅁䅁权呂䅁䅁权䙁䅁䅁兂䅁䅁䅁䝷洯䅑䅅䅁䉁䅁䅁兂癁匳䝑噧㝕䅑杷允䅁䅁䅑䅁䑁䅁䅷䅁䭁䕁䄸䅁䭁䕁䄴䅁䙁䅁䅁䅁䅂畳䅖允䅁䅁䅅䅁䙁䡁㥅瑃橥乣⼰䍄䉁䅁䅁兂䅁䅁䅍䅄䅁䅁䅯先䅁䅁䅯允䅁䅁䅯兂䅁䅁䅕䅁䅁䅁䕂欵䉁䅁䅁允䅁䅁䅕歲桦桥畓稱䴸䅉䅅䅁䙁䅁䅁睁䵁䅁䅁权䅁䅁䅁权䉁䅁䅁权䙁䅁䅁兂䅁䅁䅁佯汶䅑䅅䅁䉁䅁䅁兂䙃ㄶ㑇潈托睐杷允䅁䅁䅕䅁䑁䅁䅷䅁䭁䅁䅁䅁䭁䙁䅍䅁䭁䅁䅕䅁䙁䅁䅁䅁杄⭬䅖允䅁䅁䅅䅁䙁䱁へ硫䕧橤䅂䍄䉁䅁䅁䅂䅁䅁䅍䅄䅁䅁䅯睔䅁䅁䅯杔䅁䅁䅕䅁䅁䥁㥃唵䉁䅁䅁允䅁䅁䅕瑃橥䑣䬰稷䴸䅉䅅䅁䕁䅁䅁睁䵁䅁䅁权偂䅁䅁权佂䅁䅁兂䅁䅁䅁䨴氷䅑䅅䅁䉁䅁䅁兂塄㍯㥁瑃呦睐杷允䅁䅁䅕䅁䑁䅁䅷䅁䭁䅁䅁䅁䭁䙁䅍䅁䭁䅁䅕䅁䙁䅁䅁䅁杂伸䅖允䅁䅁䅅䅁䙁䑁積積積穫䅊䍄䉁䅁䅁䅂䅁䅁䅍䅄䅁䅁䅯睔䅁䅁䅯杔䅁䅁䅕䅁䅁䝁㑃唵䉁䅁䅁允䅁䅁䅕㘱睎児塲稴䴸䅉䅅䅁䙁䅁䅁睁䵁䅁䅁权捁䅁䅁权䉁䅁䅁权䙁䅁䅁兂䅁䅁䅁䙯浺䅑䅅䅁䉁䅁䅁兂㉄䙋偹癷奘睐杷允䅁䅁䅕䅁䑁䅁䅷䅁䭁䉁䅷䅁䭁䙁䅍䅁䭁䅁䅕䅁䙁䅁䅁䅁杂但䅚允䅁䅁䅅䅁䙁䙁㘶兓䍷祱䄱䍄䉁䅁䅁兂䅁䅁䅍䅄䅁䅁䅯杈䅁䅁䅯睕䅁䅁䅯兂䅁䅁䅕䅁䅁佁㕄唵䉁䅁䅁允䅁䅁䅕䵴㉨灶愯啋䵁䅉䅅䅁䙁䅁䅁睁䵁䅁䅁权䅁䅁䅁权䉁䅁䅁权䙁䅁䅁兂䅁䅁䅁佁汌䅑䅅䅁䉁䅁䅁兂桄桥畓⭒慈睐杷允䅁䅁䅕䅁䑁䅁䅷䅁䭁䅁䅁䅁䭁䅁䅅䅁䭁䅁䅕䅁䙁䅁䅁䅁䅄佭䅖允䅁䅁䅅䅁䙁䩁婱婭婭摭⽫䍄䉁䅁䅁兂䅁䅁䅍䅄䅁䅁䅯䅁䅁䅁䅯允䅁䅁䅯兂䅁䅁䅕䅁䅁䅁坂欵䉁䅁䅁允䅁䅁䅕䉵䘶ㄶ㑇樳䴸䅉䅅䅁䙁䅁䅁睁䵁䅁䅁权敁䅁䅁权呂䅁䅁权䙁䅁䅁兂䅁䅁䅁䉯浌䅑䅅䅁䉁䅁䅁兂療潅䅐畹灅䅑杷允䅁䅁䅑䅁䑁䅁䅷䅁䭁䕁䄸䅁䭁䕁䄴䅁䙁䅁䅁䅁䅂⭕䅚允䅁䅁䅅䅁䙁乁橥䑣䬰眱䄹䍄䉁䅁䅁兂䅁䅁䅍䅄䅁䅁䅯先䅁䅁䅯睕䅁䅁䅯兂䅁䅁䅕䅁䅁䕁䝂欵䉁䅁䅁允䅁䅁䅕婤奍䙂佡歌䵁䅉䅅䅁䙁䅁䅁睁䵁䅁䅁权䅁䅁䅁权䉁䅁䅁权䙁䅁䅁兂䅁䅁䅁䉯浪䅑䅅䅁䉁䅁䅁兂㑃潈牘払敪睐杷允䅁䅁䅕䅁䑁䅁䅷䅁䭁䉁䄴䅁䭁䅁䅅䅁䭁䅁䅕䅁䙁䅁䅁䅁杂數䅖允䅁䅁䅅䅁䙁䑁積積積㥍⽍䍄䉁䅁䅁䅂䅁䅁䅍䅄䅁䅁䅯睔䅁䅁䅯杔䅁䅁䅕䅁䅁䕁㥄唵䉁䅁䅁允䅁䅁䅕䥘䌯匹捨い䵁䅉䅅䅁䕁䅁䅁睁䵁䅁䅁权偂䅁䅁权佂䅁䅁兂䅁䅁䅁䝑浪䅑䅅䅁䉁䅁䅁兂䅁䅁䅁䅁佁䅑杷允䅁䅁䅕䅁䑁䅁䅷䅁䭁䉁䅷䅁䭁䙁䅍䅁䭁䅁䅕䅁䙁䅁䅁䅁杂畧䅚允䅁䅁䅅䅁䙁䵁㉬灶愸祲䄱䍄䉁䅁䅁兂䅁䅁䅍䅄䅁䅁䅯先䅁䅁䅯睕䅁䅁䅯兂䅁䅁䅕䅁䅁䍁兄唵䉁䅁䅁允䅁䅁䅕噋偹癷潕歌䵁䅉䅅䅁䕁䅁䅁睁䵁䅁䅁权偂䅁䅁权佂䅁䅁兂䅁䅁䅁偁氷䅑䅅䅁䉁䅁䅁兂㑃潈牘払佧䅑杷允䅁䅁䅕䅁䑁䅁䅷䅁䭁䅁䅁䅁䭁䅁䅅䅁䭁䅁䅕䅁䙁䅁䅁䅁䅁佘䅚允䅁䅁䅅䅁䙁䱁敧敨剴乵⼴䍄䉁䅁䅁䅂䅁䅁䅍䅄䅁䅁䅯睔䅁䅁䅯杔䅁䅁䅕䅁䅁䥁䩁欵䉁䅁䅁允䅁䅁䅕㑈牘払敧歅䵁䅉䅅䅁䙁䅁䅁睁䵁䅁䅁权䅁䅁䅁权䉁䅁䅁权䙁䅁䅁兂䅁䅁䅁余汌䅑䅅䅁䉁䅁䅁兂桄桥畓⭒慈睐杷允䅁䅁䅕䅁䑁䅁䅷䅁䭁䅁䅁䅁䭁䅁䅅䅁䭁䅁䅕䅁䙁䅁䅁䅁杁甶䅖允䅁䅁䅅䅁䙁䥁牘払敧摨⽳䍄䉁䅁䅁䅂䅁䅁䅍䅄䅁䅁䅯睔䅁䅁䅯杔䅁䅁䅕䅁䅁䥁敁欵䉁䅁䅁允䅁䅁䅕䥘䌯匹捨䕅䵁䅉䅅䅁䙁䅁䅁睁䵁䅁䅁权捁䅁䅁权䉁䅁䅁权䙁䅁䅁兂䅁䅁䅁䡑浺䅑䅅䅁䉁䅁䅁兂㉄䙋偹癷奘睐杷允䅁䅁䅕䅁䑁䅁䅷䅁䭁䅁䅁䅁䭁䙁䅍䅁䭁䅁䅕䅁䙁䅁䅁䅁䅃佃䅚允䅁䅁䅅䅁䙁䭁硲欰椱䑣䅊䍄䉁䅁䅁兂䅁䅁䅍䅄䅁䅁䅯杈䅁䅁䅯睕䅁䅁䅯兂䅁䅁䅕䅁䅁䵁䩁欵䉁䅁䅁允䅁䅁䅕䅁䅁䅁䅁歋䵁䅉䅅䅁䙁䅁䅁睁䵁䅁䅁权敁䅁䅁权呂䅁䅁权䙁䅁䅁兂䅁䅁䅁偙氯䅑䅅䅁䉁䅁䅁兂䅁䅁䅁䅁煁䅑杷允䅁䅁䅑䅁䑁䅁䅷䅁䭁䕁䄸䅁䭁䕁䄴䅁䙁䅁䅁䅁䅂佲䅖允䅁䅁䅅䅁䙁䑁䬰㘱睎摐⽯䍄䉁䅁䅁兂䅁䅁䅍䅄䅁䅁䅯䅁䅁䅁䅯睕䅁䅁䅯兂䅁䅁䅕䅁䅁䵁㡄唵䉁䅁䅁允䅁䅁䅕噋偹癷潖歍䵁䅉䅅䅁䙁䅁䅁睁䵁䅁䅁权摁䅁䅁权呂䅁䅁权䙁䅁䅁兂䅁䅁䅁䠴浮䅑䅅䅁䉁䅁䅁兂睄㡰䱚㡎瑫䅑杷允䅁䅁䅑䅁䑁䅁䅷䅁䭁䕁䄸䅁䭁䕁䄴䅁䙁䅁䅁䅁权⭗䅚允䅁䅁䅅䅁䙁䵁ㅐ䙋偹杷䄹䍄䉁䅁䅁兂䅁䅁䅍䅄䅁䅁䅯杇䅁䅁䅯睕䅁䅁䅯兂䅁䅁䅕䅁䅁䥁橂欵䉁䅁䅁允䅁䅁䅕灶愸㥌欱く䵁䅉䅅䅁䕁䅁䅁睁䵁䅁䅁权偂䅁䅁权佂䅁䅁兂䅁䅁䅁䭧汐䅑䅅䅁䉁䅁䅁兂浂浚浚浚坢睐杷允䅁䅁䅕䅁䑁䅁䅷䅁䭁䉁䅯䅁䭁䙁䅍䅁䭁䅁䅕䅁䙁䅁䅁䅁䅁⭙䅚允䅁䅁䅅䅁䙁䱁昶楇搯䑚䅴䍄䉁䅁䅁兂䅁䅁䅍䅄䅁䅁䅯杈䅁䅁䅯睕䅁䅁䅯兂䅁䅁䅕䅁䅁䝁卄唵䉁䅁䅁允䅁䅁䅕兊䉡啬䱏䕌䵁䅉䅅䅁䕁䅁䅁睁䵁䅁䅁权偂䅁䅁权佂䅁䅁兂䅁䅁䅁乙汈䅑䅅䅁䉁䅁䅁兂硂児塲㍯䡁䅑杷允䅁䅁䅕䅁䑁䅁䅷䅁䭁䉁䄸䅁䭁䙁䅍䅁䭁䅁䅕䅁䙁䅁䅁䅁䅂佡䅚允䅁䅁䅅䅁䙁䅁塲㍯㥁橋䅆䍄䉁䅁䅁䅂䅁䅁䅍䅄䅁䅁䅯睔䅁䅁䅯杔䅁䅁䅕䅁䅁䅁橂欵䉁䅁䅁允䅁䅁䅕㡪ㅌ䙋偹歄䵁䅉䅅䅁䙁䅁䅁睁䵁䅁䅁权敁䅁䅁权䉁䅁䅁权䙁䅁䅁兂䅁䅁䅁䍯浘䅑䅅䅁䉁䅁䅁兂䑄匹捨㡪噌睐杷允䅁䅁䅕䅁䑁䅁䅷䅁䭁䉁䄸䅁䭁䙁䅍䅁䭁䅁䅕䅁䙁䅁䅁䅁杁⭯䅖允䅁䅁䅅䅁䙁䩁䕺䱉祂䑋䅆䍄䉁䅁䅁兂䅁䅁䅍䅄䅁䅁䅯䅁䅁䅁䅯允䅁䅁䅯兂䅁䅁䅕䅁䅁䍁摁欵䉁䅁䅁允䅁䅁䅕䉵䘶ㄶ㑇樳䴸䅉䅅䅁䕁䅁䅁睁䵁䅁䅁权偂䅁䅁权佂䅁䅁兂䅁䅁䅁䅑浔䅑䅅䅁䉁䅁䅁兂穁積積積前䅑杷允䅁䅁䅑䅁䑁䅁䅷䅁䭁䕁䄸䅁䭁䕁䄴䅁䙁䅁䅁䅁䅂⭚䅚允䅁䅁䅅䅁䙁䉁䘫ㄶ㑇杈䄱䍄䉁䅁䅁兂䅁䅁䅍䅄䅁䅁䅯䅁䅁䅁䅯允䅁䅁䅯兂䅁䅁䅕䅁䅁䥁塂欵䉁䅁䅁允䅁䅁䅕䉵䘶ㄶ㑇樳䴸䅉䅅䅁䙁䅁䅁睁䵁䅁䅁权敁䅁䅁权呂䅁䅁权䙁䅁䅁兂䅁䅁䅁䕧浶䅑䅅䅁䉁䅁䅁兂畄䑦ㄸ橘歯䅑杷允䅁䅁䅕䅁䑁䅁䅷䅁䭁䅁䅁䅁䭁䅁䅅䅁䭁䅁䅕䅁䙁䅁䅁䅁权佖䅚允䅁䅁䅅䅁䙁䱁敧敨剴乵⼴䍄䉁䅁䅁兂䅁䅁䅍䅄䅁䅁䅯杇䅁䅁䅯允䅁䅁䅯兂䅁䅁䅕䅁䅁䭁畄唵䉁䅁䅁允䅁䅁䅕積積積積稴䴸䅉䅅䅁䕁䅁䅁睁䵁䅁䅁权偂䅁䅁权佂䅁䅁兂䅁䅁䅁䝯浢䅑䅅䅁䉁䅁䅁兂慃婭婭婭乫䅑杷允䅁䅁䅑䅁䑁䅁䅷䅁䭁䕁䄸䅁䭁䕁䄴䅁䙁䅁䅁䅁䅂⭭䅖允䅁䅁䅅䅁䙁䍁捬㡪ㅌ䵋⽷䍄䉁䅁䅁䅂䅁䅁䅍䅄䅁䅁䅯睔䅁䅁䅯杔䅁䅁䅕䅁䅁佁ぃ唵䉁䅁䅁允䅁䅁䅕呣䬰㘱睎吳䴸䅉䅅䅁䙁䅁䅁睁䵁䅁䅁权䅁䅁䅁权呂䅁䅁权䙁䅁䅁兂䅁䅁䅁䱙氯䅑䅅䅁䉁䅁䅁兂㑄⭕汏㑭祑䅑杷允䅁䅁䅕䅁䑁䅁䅷䅁䭁䉁䄰䅁䭁䙁䅍䅁䭁䅁䅕䅁䙁䅁䅁䅁杁敋䅚允䅁䅁䅅䅁䙁䝁浚浚浚椵䄵䍄䉁䅁䅁兂䅁䅁䅍䅄䅁䅁䅯䅁䅁䅁䅯允䅁䅁䅯兂䅁䅁䅕䅁䅁䅁䡄唵䉁䅁䅁允䅁䅁䅕児塲㍯㥁樲䴸䅉䅅䅁䕁䅁䅁睁䵁䅁䅁权偂䅁䅁权佂䅁䅁兂䅁䅁䅁䍑浄䅑䅅䅁䉁䅁䅁兂歃䑣䬰㘱免䅑杷允䅁䅁䅕䅁䑁䅁䅷䅁䭁䉁䄸䅁䭁䅁䅅䅁䭁䅁䅕䅁䙁䅁䅁䅁䅁⭶䅖允䅁䅁䅅䅁䙁䱁敧敨剴乵⼴䍄䉁䅁䅁兂䅁䅁䅍䅄䅁䅁䅯杇䅁䅁䅯睕䅁䅁䅯兂䅁䅁䅕䅁䅁䕁䱁欵䉁䅁䅁允䅁䅁䅕牒穢搯契歏䵁䅉䅅䅁䕁䅁䅁睁䵁䅁䅁权偂䅁䅁权佂䅁䅁兂䅁䅁䅁䑉浺䅑䅅䅁䉁䅁䅁兂卂䉵䘶ㄶ佅䅑杷允䅁䅁䅕䅁䑁䅁䅷䅁䭁䉁䄰䅁䭁䙁䅍䅁䭁䅁䅕䅁䙁䅁䅁䅁杂整䅖允䅁䅁䅅䅁䙁䅁塲㍯㥁楹䄱䍄䉁䅁䅁兂䅁䅁䅍䅄䅁䅁䅯杈䅁䅁䅯允䅁䅁䅯兂䅁䅁䅕䅁䅁䥁㍄唵䉁䅁䅁允䅁䅁䅕硥畓⭒㙆䐱䴸䅉䅅䅁䕁䅁䅁睁䵁䅁䅁权偂䅁䅁权佂䅁䅁兂䅁䅁䅁䝧浢䅑䅅䅁䉁䅁䅁兂䥂場啯歲乣䅑杷允䅁䅁䅕䅁䑁䅁䅷䅁䭁䅁䅁䅁䭁䅁䅅䅁䭁䅁䅕䅁䙁䅁䅁䅁杁異䅖允䅁䅁䅅䅁䙁䩁婱婭婭摭⽫䍄䉁䅁䅁兂䅁䅁䅍䅄䅁䅁䅯睈䅁䅁䅯睕䅁䅁䅯兂䅁䅁䅕䅁䅁佁慁欵䉁䅁䅁允䅁䅁䅕牒穢搯㑔䕍䵁䅉䅅䅁䙁䅁䅁睁䵁䅁䅁权捁䅁䅁权呂䅁䅁权䙁䅁䅁兂䅁䅁䅁䥉浌䅑䅅䅁䉁䅁䅁兂䩄牤昶煇琸䅑杷允䅁䅁䅕䅁䑁䅁䅷䅁䭁䉁䄰䅁䭁䙁䅍䅁䭁䅁䅕䅁䙁䅁䅁䅁杂併䅖允䅁䅁䅅䅁䙁䅁塲㍯㥁楹䄱䍄䉁䅁䅁䅂䅁䅁䅍䅄䅁䅁䅯睔䅁䅁䅯杔䅁䅁䅕䅁䅁䍁噃唵䉁䅁䅁允䅁䅁䅕⽷潕䥘䌯呸䴸䅉䅅䅁䕁䅁䅁睁䵁䅁䅁权偂䅁䅁权佂䅁䅁兂䅁䅁䅁䝁浌䅑䅅䅁䉁䅁䅁兂灁䥘䌯匹佧䅑杷允䅁䅁䅕䅁䑁䅁䅷䅁䭁䉁䅯䅁䭁䅁䅅䅁䭁䅁䅕䅁䙁䅁䅁䅁杄⭄䅚允䅁䅁䅅䅁䙁䝁浚浚浚畚⽙䍄䉁䅁䅁䅂䅁䅁䅍䅄䅁䅁䅯睔䅁䅁䅯杔䅁䅁䅕䅁䅁䍁坁欵䉁䅁䅁允䅁䅁䅕硥畓⭒㙆歅䵁䅉䅅䅁䙁䅁䅁睁䵁䅁䅁权摁䅁䅁权䉁䅁䅁权䙁䅁䅁兂䅁䅁䅁䉙浮䅑䅅䅁䉁䅁䅁兂晁敨剴䉵嘷睐杷允䅁䅁䅕䅁䑁䅁䅷䅁䭁䉁䅯䅁䭁䙁䅍䅁䭁䅁䅕䅁䙁䅁䅁䅁䅃低䅚允䅁䅁䅅䅁䙁䉁䘫ㄶ㑇樳䅰䍄䉁䅁䅁兂䅁䅁䅍䅄䅁䅁䅯先䅁䅁䅯睕䅁䅁䅯兂䅁䅁䅕䅁䅁䅁奄唵䉁䅁䅁允䅁䅁䅕⽷潕䥘䌯啌䵁䅉䅅䅁䙁䅁䅁睁䵁䅁䅁权䅁䅁䅁权䉁䅁䅁权䙁䅁䅁兂䅁䅁䅁䅷浌䅑䅅䅁䉁䅁䅁兂㑃潈牘払敪睐杷允䅁䅁䅕䅁䑁䅁䅷䅁䭁䉁䅷䅁䭁䙁䅍䅁䭁䅁䅕䅁䙁䅁䅁䅁䅁畇䅚允䅁䅁䅅䅁䙁䱁摋㘷䝦祃䄵䍄䉁䅁䅁兂䅁䅁䅍䅄䅁䅁䅯䅈䅁䅁䅯睕䅁䅁䅯兂䅁䅁䅕䅁䅁䝁䕂欵䉁䅁䅁允䅁䅁䅕㥆佮ㄹ橏歌䵁䅉䅅䅁䕁䅁䅁睁䵁䅁䅁权偂䅁䅁权佂䅁䅁兂䅁䅁䅁䩧汮䅑䅅䅁䉁䅁䅁兂卂䉵䘶ㄶ䥈睐杷允䅁䅁䅑䅁䑁䅁䅷䅁䭁䕁䄸䅁䭁䕁䄴䅁䙁䅁䅁䅁䅂佖䅚允䅁䅁䅅䅁啁䅁䅑䅁䅁䅁䅁䍄䉁䅁䅁䅂䅁䅁䅍䅄䅁䅁䅯睔䅁䅁䅯杔䅁䅁䅕䅁䅁䵁敂欵䉁䅁䅁允䅁䅁䅕䭆䠵場啯䕅䵁䅉䅅䅁䙁䅁䅁睁䵁䅁䅁权捁䅁䅁权䉁䅁䅁权䙁䅁䅁兂䅁䅁䅁䕙浺䅑䅅䅁䉁䅁䅁兂㉄䙋偹癷奘睐杷允䅁䅁䅑䅁䑁䅁䅷䅁䭁䕁䄸䅁䭁䕁䄴䅁䙁䅁䅁䅁䅁⭅䅚允䅁䅁䅅䅁䭁䉁䅳䅁䵁䅉䅅䅁䕁䅁䅁睁䵁䅁䅁权偂䅁䅁权佂䅁䅁兂䅁䅁䅁䝙浢䅑䅅䅁䉁䅁䅁兂䭁㘱睎児乯䅑杷允䅁䅁䅕䅁䑁䅁䅷䅁䭁䉁䄴䅁䭁䙁䅍䅁䭁䅁䅕䅁䙁䅁䅁䅁杄敵䅖允䅁䅁䅅䅁䙁䱁穢搯㑒卡䅸䍄䉁䅁䅁䅂䅁䅁䅍䅄䅁䅁䅯睔䅁䅁䅯杔䅁䅁䅕䅁䅁䍁硃唵䉁䅁䅁允䅁䅁䅕敨剴䉵䘶稲䴸䅉䅅䅁䙁䅁䅁睁䵁䅁䅁权捁䅁䅁权呂䅁䅁权䙁䅁䅁兂䅁䅁䅁䵁氯䅑䅅䅁䉁䅁䅁兂䙃ㄶ㑇潈畕䅑杷允䅁䅁䅑䅁䑁䅁䅷䅁䭁䕁䄸䅁䭁䕁䄴䅁䙁䅁䅁䅁䅃收䅖允䅁䅁䅅䅁䭁䉁䅳䅁䵁䅉䅅䅁䕁䅁䅁睁䵁䅁䅁权偂䅁䅁权佂䅁䅁兂䅁䅁䅁䭷氷䅑䅅䅁䉁䅁䅁兂畃⭒㙆䭆堷睐杷允䅁䅁䅑䅁䑁䅁䅷䅁䭁䕁䄸䅁䭁䕁䄴䅁䙁䅁䅁䅁䅂⬶䅖允䅁䅁䅅䅁䙁䵁䴳䵺䵺䉺䅂䍄䉁䅁䅁䅂䅁䅁䅍䅄䅁䅁䅯睔䅁䅁䅯杔䅁䅁䅕䅁䅁䭁歁欵䉁䅁䅁允䅁䅁䅕䅁䅁䅁䅁歅䵁䅉䅅䅁䕁䅁䅁睁䵁䅁䅁权偂䅁䅁权佂䅁䅁兂䅁䅁䅁䉯浪䅑䅅䅁䉁䅁䅁兂㝂䭆䠵場卯䅑杷允䅁䅁䅕䅁䑁䅁䅷䅁䭁䉁䅷䅁䭁䙁䅍䅁䭁䅁䅕䅁䙁䅁䅁䅁杂⭁䅚允䅁䅁䅅䅁䙁偁潙䥘䌯卤䄱䍄䉁䅁䅁䅂䅁䅁䅍䅄䅁䅁䅯睔䅁䅁䅯杔䅁䅁䅕䅁䅁佁佂欵䉁䅁䅁允䅁䅁䅕椹捨㡪ㅌ䕅䵁䅉䅅䅁䙁䅁䅁睁䵁䅁䅁权慁䅁䅁权呂䅁䅁权䙁䅁䅁兂䅁䅁䅁䉉浐䅑䅅䅁䉁䅁䅁兂䝁婧䑖ど㙷䅑杷允䅁䅁䅕䅁䑁䅁䅷䅁䭁䉁䅷䅁䭁䅁䅅䅁䭁䅁䅕䅁䙁䅁䅁䅁䅂敋䅚允䅁䅁䅅䅁䙁䭁䠵場啯瑲⽣䍄䉁䅁䅁兂䅁䅁䅍䅄䅁䅁䅯䅁䅁䅁䅯允䅁䅁䅯兂䅁䅁䅕䅁䅁䅁乂欵䉁䅁䅁允䅁䅁䅕䉵䘶ㄶ㑇樳䴸䅉䅅䅁䕁䅁䅁睁䵁䅁䅁权偂䅁䅁权佂䅁䅁兂䅁䅁䅁䙧洳䅑䅅䅁䉁䅁䅁兂硂児塲㍯偁䅑杷允䅁䅁䅕䅁䑁䅁䅷䅁䭁䅁䅁䅁䭁䙁䅍䅁䭁䅁䅕䅁䙁䅁䅁䅁杁⭌䅚允䅁䅁䅅䅁䙁䍁礲敮渫橨䅎䍄䉁䅁䅁兂䅁䅁䅍䅄䅁䅁䅯睈䅁䅁䅯睕䅁䅁䅯兂䅁䅁䅕䅁䅁䕁剂欵䉁䅁䅁允䅁䅁䅕呦ㄸ牘灯啍䵁䅉䅅䅁䙁䅁䅁睁䵁䅁䅁权䅁䅁䅁权呂䅁䅁权䙁䅁䅁兂䅁䅁䅁乯汮䅑䅅䅁䉁䅁䅁兂权楇搯䅊穙䅑杷允䅁䅁䅕䅁䑁䅁䅷䅁䭁䉁䄰䅁䭁䙁䅍䅁䭁䅁䅕䅁䙁䅁䅁䅁杂敕䅚允䅁䅁䅅䅁䙁䵁ㅐ䙋偹楧䄵䍄䉁䅁䅁䅂䅁䅁䅍䅄䅁䅁䅯睔䅁䅁䅯杔䅁䅁䅕䅁䅁佁穃唵䉁䅁䅁允䅁䅁䅕敨剴䉵䘶稲䴸䅉䅅䅁䙁䅁䅁睁䵁䅁䅁权慁䅁䅁权呂䅁䅁权䙁䅁䅁兂䅁䅁䅁乙汌䅑䅅䅁䉁䅁䅁兂权楇搯䕊㙙䅑杷允䅁䅁䅕䅁䑁䅁䅷䅁䭁䉁䅷䅁䭁䙁䅍䅁䭁䅁䅕䅁䙁䅁䅁䅁杁⭗䅚允䅁䅁䅅䅁䙁䭁䙊癴㥐䍆䄵䍄䉁䅁䅁䅂䅁䅁䅍䅄䅁䅁䅯睔䅁䅁䅯杔䅁䅁䅕䅁䅁䝁䱄唵䉁䅁䅁允䅁䅁䅕牕敧敨剴䕁䵁䅉䅅䅁䕁䅁䅁睁䵁䅁䅁权偂䅁䅁权佂䅁䅁兂䅁䅁䅁䝧浘䅑䅅䅁䉁䅁䅁兂晁敨剴䉵倴䅑杷允䅁䅁䅕䅁䑁䅁䅷䅁䭁䉁䅯䅁䭁䙁䅍䅁䭁䅁䅕䅁䙁䅁䅁䅁䅁⭶䅖允䅁䅁䅅䅁䙁䱁䩰䅄牉穊䅰䍄䉁䅁䅁兂䅁䅁䅍䅄䅁䅁䅯杈䅁䅁䅯睕䅁䅁䅯兂䅁䅁䅕䅁䅁䕁䩂欵䉁䅁䅁允䅁䅁䅕渷⽷噎㘴䕊䵁䅉䅅䅁䕁䅁䅁睁䵁䅁䅁权偂䅁䅁权佂䅁䅁兂䅁䅁䅁䜴浔䅑䅅䅁䉁䅁䅁兂桄桥畓⭒佅䅑杷允䅁䅁䅕䅁䑁䅁䅷䅁䭁䉁䄸䅁䭁䙁䅍䅁䭁䅁䅕䅁䙁䅁䅁䅁杂畯䅖允䅁䅁䅅䅁䙁䩁䕺䱉祂䑋䅆䍄䉁䅁䅁兂䅁䅁䅍䅄䅁䅁䅯先䅁䅁䅯允䅁䅁䅯兂䅁䅁䅕䅁䅁䝁ㅄ唵䉁䅁䅁允䅁䅁䅕㘱睎児塲稰䴸䅉䅅䅁䙁䅁䅁睁䵁䅁䅁权敁䅁䅁权呂䅁䅁权䙁䅁䅁兂䅁䅁䅁䅙浌䅑䅅䅁䉁䅁䅁兂䅁䅁䅁䅁煁䅑杷允䅁䅁䅕䅁䑁䅁䅷䅁䭁䅁䅁䅁䭁䙁䅍䅁䭁䅁䅕䅁䙁䅁䅁䅁权敧䅚允䅁䅁䅅䅁䙁偁唷佥浫吸䅎䍄䉁䅁䅁䅂䅁䅁䅍䅄䅁䅁䅯睔䅁䅁䅯杔䅁䅁䅕䅁䅁䥁歂欵䉁䅁䅁允䅁䅁䅕噋偹癷潕歄䵁䅉䅅䅁䙁䅁䅁睁䵁䅁䅁权䅁䅁䅁权呂䅁䅁权䙁䅁䅁兂䅁䅁䅁䕷洳䅑䅅䅁䉁䅁䅁兂十㡧䭄捯穕䅑杷允䅁䅁䅑䅁䑁䅁䅷䅁䭁䕁䄸䅁䭁䕁䄴䅁䙁䅁䅁䅁杂敘䅚允䅁䅁䅅䅁䙁䭁䠵場啯杲䄹䍄䉁䅁䅁兂䅁䅁䅍䅄䅁䅁䅯䅁䅁䅁䅯允䅁䅁䅯兂䅁䅁䅕䅁䅁䅁煂欵䉁䅁䅁允䅁䅁䅕䉵䘶ㄶ㑇樳䴸䅉䅅䅁䙁䅁䅁睁䵁䅁䅁权敁䅁䅁权呂䅁䅁权䙁䅁䅁兂䅁䅁䅁䩉汪䅑䅅䅁䉁䅁䅁兂䝁婧䑖㉩灷䅑杷允䅁䅁䅑䅁䑁䅁䅷䅁䭁䕁䄸䅁䭁䕁䄴䅁䙁䅁䅁䅁杄畏䅚允䅁䅁䅅䅁䙁乁橥䑣䬰眱䄱䍄䉁䅁䅁兂䅁䅁䅍䅄䅁䅁䅯杇䅁䅁䅯睕䅁䅁䅯兂䅁䅁䅕䅁䅁䅁䱂欵䉁䅁䅁允䅁䅁䅕䑔䩥坑䙂く䵁䅉䅅䅁䙁䅁䅁睁䵁䅁䅁权䅁䅁䅁权䉁䅁䅁权䙁䅁䅁兂䅁䅁䅁䭷決䅑䅅䅁䉁䅁䅁兂慃婭婭婭婮睐杷允䅁䅁䅑䅁䑁䅁䅷䅁䭁䕁䄸䅁䭁䕁䄴䅁䙁䅁䅁䅁䅁⬯䅖允䅁䅁䅅䅁䙁䙁偹癷潕䅘䄱䍄䉁䅁䅁兂䅁䅁䅍䅄䅁䅁䅯䅈䅁䅁䅯睕䅁䅁䅯兂䅁䅁䅕䅁䅁䵁橂欵䉁䅁䅁允䅁䅁䅕歯㉗⼸唰歌䵁䅉䅅䅁䙁䅁䅁睁䵁䅁䅁权晁䅁䅁权䉁䅁䅁权䙁䅁䅁兂䅁䅁䅁䵯汘䅑䅅䅁䉁䅁䅁兂㑃潈牘払敪睐杷允䅁䅁䅕䅁䑁䅁䅷䅁䭁䉁䄰䅁䭁䙁䅍䅁䭁䅁䅕䅁䙁䅁䅁䅁䅂攸䅖允䅁䅁䅅䅁䙁䭁扡䍸睃楳䄱䍄䉁䅁䅁兂䅁䅁䅍䅄䅁䅁䅯睈䅁䅁䅯睕䅁䅁䅯兂䅁䅁䅕䅁䅁䭁䝂欵䉁䅁䅁允䅁䅁䅕䙂余扌摉啍䵁䅉䅅䅁䙁䅁䅁睁䵁䅁䅁权摁䅁䅁权呂䅁䅁权䙁䅁䅁兂䅁䅁䅁䕙洯䅑䅅䅁䉁䅁䅁兂ㅂ硫䕧潖甴䅑杷允䅁䅁䅑䅁䑁䅁䅷䅁䭁䕁䄸䅁䭁䕁䄴䅁䙁䅁䅁䅁䅃畱䅖允䅁䅁䅅䅁䙁䱁敧敨剴乵⼴䍄䉁䅁䅁兂䅁䅁䅍䅄䅁䅁䅯杇䅁䅁䅯允䅁䅁䅯兂䅁䅁䅕䅁䅁䭁穄唵䉁䅁䅁允䅁䅁䅕積積積積稴䴸䅉䅅䅁䕁䅁䅁睁䵁䅁䅁权偂䅁䅁权佂䅁䅁兂䅁䅁䅁䱧汶䅑䅅䅁䉁䅁䅁兂䅁䅁䅁䅁潄睐杷允䅁䅁䅕䅁䑁䅁䅷䅁䭁䉁䅯䅁䭁䅁䅅䅁䭁䅁䅕䅁䙁䅁䅁䅁䅁攱䅖允䅁䅁䅅䅁䙁偁潙䥘䌯改⽁䍄䉁䅁䅁兂䅁䅁䅍䅄䅁䅁䅯睈䅁䅁䅯允䅁䅁䅯兂䅁䅁䅕䅁䅁佁䙂欵䉁䅁䅁允䅁䅁䅕䡰㥁瑃橥䐴䴸䅉䅅䅁䙁䅁䅁睁䵁䅁䅁权慁䅁䅁权呂䅁䅁权䙁䅁䅁兂䅁䅁䅁䩑氷䅑䅅䅁䉁䅁䅁兂䡃瑆佮稹㕍䅑杷允䅁䅁䅑䅁䑁䅁䅷䅁䭁䕁䄸䅁䭁䕁䄴䅁䙁䅁䅁䅁杄效䅚允䅁䅁䅅䅁䙁䥁䌯匹捨硪䅂䍄䉁䅁䅁兂䅁䅁䅍䅄䅁䅁䅯䅁䅁䅁䅯允䅁䅁䅯兂䅁䅁䅕䅁䅁䭁䍃欵䉁䅁䅁允䅁䅁䅕䉵䘶ㄶ㑇樳䴸䅉䅅䅁䙁䅁䅁睁䵁䅁䅁权摁䅁䅁权呂䅁䅁权䙁䅁䅁兂䅁䅁䅁䩯汪䅑䅅䅁䉁䅁䅁兂㡃䩤奍䙂瑙䅑杷允䅁䅁䅑䅁䑁䅁䅷䅁䭁䕁䄸䅁䭁䕁䄴䅁䙁䅁䅁䅁䅂攴䅖允䅁䅁䅅䅁䙁䝁浚浚浚杚䅸䍄䉁䅁䅁兂䅁䅁䅍䅄䅁䅁䅯䅁䅁䅁䅯睕䅁䅁䅯兂䅁䅁䅕䅁䅁䝁楃唵䉁䅁䅁允䅁䅁䅕㘱睎児㍲䕍䵁䅉䅅䅁䙁䅁䅁睁䵁䅁䅁权捁䅁䅁权䉁䅁䅁权䙁䅁䅁兂䅁䅁䅁䩑汲䅑䅅䅁䉁䅁䅁兂偃癷潕䥘匯睐杷允䅁䅁䅕䅁䑁䅁䅷䅁䭁䉁䄰䅁䭁䅁䅅䅁䭁䅁䅕䅁䙁䅁䅁䅁䅂佔䅚允䅁䅁䅅䅁䙁䭁䠵場啯瑲⽣䍄䉁䅁䅁兂䅁䅁䅍䅄䅁䅁䅯䅁䅁䅁䅯允䅁䅁䅯兂䅁䅁䅕䅁䅁䥁牂欵䉁䅁䅁允䅁䅁䅕䉵䘶ㄶ㑇樳䴸䅉䅅䅁䕁䅁䅁睁䵁䅁䅁权偂䅁䅁权佂䅁䅁兂䅁䅁䅁䌴浶䅑䅅䅁䉁䅁䅁兂浂浚浚浚呙䅑杷允䅁䅁䅕䅁䑁䅁䅷䅁䭁䉁䅯䅁䭁䙁䅍䅁䭁䅁䅕䅁䙁䅁䅁䅁权⭷䅖允䅁䅁䅅䅁䙁䱁䩰䅄牉穊䅰䍄䉁䅁䅁䅂䅁䅁䅍䅄䅁䅁䅯睔䅁䅁䅯杔䅁䅁䅕䅁䅁佁汄唵䉁䅁䅁允䅁䅁䅕⽷潕䥘䌯啅䵁䅉䅅䅁䕁䅁䅁睁䵁䅁䅁权偂䅁䅁权佂䅁䅁兂䅁䅁䅁䍷浶䅑䅅䅁䉁䅁䅁兂晁敨剴䉵吴䅑杷允䅁䅁䅕䅁䑁䅁䅷䅁䭁䅁䅁䅁䭁䅁䅅䅁䭁䅁䅕䅁䙁䅁䅁䅁杂伶䅖允䅁䅁䅅䅁䙁䥁牘払敧摨⽳䍄䉁䅁䅁兂䅁䅁䅍䅄䅁䅁䅯䅈䅁䅁䅯睕䅁䅁䅯兂䅁䅁䅕䅁䅁䵁䡂欵䉁䅁䅁允䅁䅁䅕硢䑋䵷桰歌䵁䅉䅅䅁䙁䅁䅁睁䵁䅁䅁权䅁䅁䅁权䉁䅁䅁权䙁䅁䅁兂䅁䅁䅁䔴浘䅑䅅䅁䉁䅁䅁兂㑃潈牘払敪睐杷允䅁䅁䅑䅁䑁䅁䅷䅁䭁䕁䄸䅁䭁䕁䄴䅁䙁䅁䅁䅁杄⭍䅚允䅁䅁䅅䅁䙁䉁畓⭒㙆䉆䅊䍄䉁䅁䅁兂䅁䅁䅍䅄䅁䅁䅯杇䅁䅁䅯允䅁䅁䅯兂䅁䅁䅕䅁䅁佁坄唵䉁䅁䅁允䅁䅁䅕椹捨㡪ㅌ䐴䴸䅉䅅䅁䙁䅁䅁睁䵁䅁䅁权捁䅁䅁权䉁䅁䅁权䙁䅁䅁兂䅁䅁䅁䍉浄䅑䅅䅁䉁䅁䅁兂畃⭒㙆䭆堷睐杷允䅁䅁䅕䅁䑁䅁䅷䅁䭁䉁䄸䅁䭁䅁䅅䅁䭁䅁䅕䅁䙁䅁䅁䅁䅁畍䅚允䅁䅁䅅䅁䙁䕁桪桥畓⭒⽅䍄䉁䅁䅁兂䅁䅁䅍䅄䅁䅁䅯䅁䅁䅁䅯睕䅁䅁䅯兂䅁䅁䅕䅁䅁䕁橁欵䉁䅁䅁允䅁䅁䅕搵楁⼲⭫き䵁䅉䅅䅁䕁䅁䅁睁䵁䅁䅁权偂䅁䅁权佂䅁䅁兂䅁䅁䅁䵧氳䅑䅅䅁䉁䅁䅁兂桄桥畓⭒䕅䅑杷允䅁䅁䅑䅁䑁䅁䅷䅁䭁䕁䄸䅁䭁䕁䄴䅁䙁䅁䅁䅁杁⬴䅖允䅁䅁䅅䅁䙁乁橥䑣䬰眱䄹䍄䉁䅁䅁兂䅁䅁䅍䅄䅁䅁䅯䅁䅁䅁䅯允䅁䅁䅯兂䅁䅁䅕䅁䅁䅁橁欵䉁䅁䅁允䅁䅁䅕䉵䘶ㄶ㑇樳䴸䅉䅅䅁䕁䅁䅁睁䵁䅁䅁权偂䅁䅁权佂䅁䅁兂䅁䅁䅁䕑浘䅑䅅䅁䉁䅁䅁兂穁積積積前䅑杷允䅁䅁䅑䅁䑁䅁䅷䅁䭁䕁䄸䅁䭁䕁䄴䅁䙁䅁䅁䅁杄敒䅚允䅁䅁䅅䅁䙁偁潙䥘䌯刹䅂䍄䉁䅁䅁兂䅁䅁䅍䅄䅁䅁䅯睈䅁䅁䅯允䅁䅁䅯兂䅁䅁䅕䅁䅁䅁啁欵䉁䅁䅁允䅁䅁䅕䡰㥁瑃橥䐴䴸䅉䅅䅁䙁䅁䅁睁䵁䅁䅁权晁䅁䅁权呂䅁䅁权䙁䅁䅁兂䅁䅁䅁䙙浐䅑䅅䅁䉁䅁䅁兂㥂穐敖極硫䅑杷允䅁䅁䅕䅁䑁䅁䅷䅁䭁䅁䅁䅁䭁䅁䅅䅁䭁䅁䅕䅁䙁䅁䅁䅁䅃甯䅖允䅁䅁䅅䅁䙁䱁敧敨剴乵⼴䍄䉁䅁䅁兂䅁䅁䅍䅄䅁䅁䅯杇䅁䅁䅯睕䅁䅁䅯兂䅁䅁䅕䅁䅁䅁獃唵䉁䅁䅁允䅁䅁䅕噈歰㥏倫問䵁䅉䅅䅁䕁䅁䅁睁䵁䅁䅁权偂䅁䅁权佂䅁䅁兂䅁䅁䅁䄴浌䅑䅅䅁䉁䅁䅁兂䙃ㄶ㑇潈兕䅑杷允䅁䅁䅑䅁䑁䅁䅷䅁䭁䕁䄸䅁䭁䕁䄴䅁䙁䅁䅁䅁杄教䅚允䅁䅁䅅䅁䙁䅁䅁䅁䅁䅁䄵䍄䉁䅁䅁兂䅁䅁䅍䅄䅁䅁䅯杈䅁䅁䅯允䅁䅁䅯兂䅁䅁䅕䅁䅁䅁呁欵䉁䅁䅁允䅁䅁䅕⽷潕䥘䌯吱䴸䅉䅅䅁䙁䅁䅁睁䵁䅁䅁权晁䅁䅁权呂䅁䅁权䙁䅁䅁兂䅁䅁䅁䱧決䅑䅅䅁䉁䅁䅁兂䩄牤昶楇砸䅑杷允䅁䅁䅑䅁䑁䅁䅷䅁䭁䕁䄸䅁䭁䕁䄴䅁䙁䅁䅁䅁权攲䅖允䅁䅁䅅䅁䙁䝁浚浚浚杚䅨䍄䉁䅁䅁兂䅁䅁䅍䅄䅁䅁䅯杈䅁䅁䅯睕䅁䅁䅯兂䅁䅁䅕䅁䅁䝁㉃唵䉁䅁䅁允䅁䅁䅕癴㥐䠱灨䕌䵁䅉䅅䅁䙁䅁䅁睁䵁䅁䅁权䅁䅁䅁权䉁䅁䅁权䙁䅁䅁兂䅁䅁䅁䐴洷䅑䅅䅁䉁䅁䅁兂㑃潈牘払敪睐杷允䅁䅁䅕䅁䑁䅁䅷䅁䭁䉁䅷䅁䭁䅁䅅䅁䭁䅁䅕䅁䙁䅁䅁䅁杂⭍䅚允䅁䅁䅅䅁䙁偁潙䥘䌯搹⽧䍄䉁䅁䅁兂䅁䅁䅍䅄䅁䅁䅯先䅁䅁䅯睕䅁䅁䅯兂䅁䅁䅕䅁䅁䅁㙁欵䉁䅁䅁允䅁䅁䅕牒穢搯㑓歌䵁䅉䅅䅁䙁䅁䅁睁䵁䅁䅁权慁䅁䅁权呂䅁䅁权䙁䅁䅁兂䅁䅁䅁䬴氷䅑䅅䅁䉁䅁䅁兂摁浗㝑㐳㔸䅑杷允䅁䅁䅕䅁䑁䅁䅷䅁䭁䉁䄴䅁䭁䙁䅍䅁䭁䅁䅕䅁䙁䅁䅁䅁杁畳䅖允䅁䅁䅅䅁䙁䱁穢搯㑒卡䅸䍄䉁䅁䅁兂䅁䅁䅍䅄䅁䅁䅯杇䅁䅁䅯睕䅁䅁䅯兂䅁䅁䅕䅁䅁䕁療欵䉁䅁䅁允䅁䅁䅕㥌欰潂噆く䵁䅉䅅䅁䕁䅁䅁睁䵁䅁䅁权偂䅁䅁权佂䅁䅁兂䅁䅁䅁䉷浔䅑䅅䅁䉁䅁䅁兂偃癷潕䥘吸䅑杷允䅁䅁䅕䅁䑁䅁䅷䅁䭁䅁䅁䅁䭁䅁䅅䅁䭁䅁䅕䅁䙁䅁䅁䅁䅁⬶䅖允䅁䅁䅅䅁䙁䥁牘払敧摨⽳䍄䉁䅁䅁䅂䅁䅁䅍䅄䅁䅁䅯睔䅁䅁䅯杔䅁䅁䅕䅁䅁佁硃唵䉁䅁䅁允䅁䅁䅕敨剴䉵䘶稲䴸䅉䅅䅁䕁䅁䅁睁䵁䅁䅁权偂䅁䅁权佂䅁䅁兂䅁䅁䅁䝷浈䅑䅅䅁䉁䅁䅁兂硂児塲㍯乁䅑杷允䅁䅁䅕䅁䑁䅁䅷䅁䭁䉁䅷䅁䭁䅁䅅䅁䭁䅁䅕䅁䙁䅁䅁䅁权⭑䅚允䅁䅁䅅䅁䙁偁潙䥘䌯搹⽧䍄䉁䅁䅁兂䅁䅁䅍䅄䅁䅁䅯睈䅁䅁䅯允䅁䅁䅯兂䅁䅁䅕䅁䅁䍁穄唵䉁䅁䅁允䅁䅁䅕場啯歲桦樲䴸䅉䅅䅁䕁䅁䅁睁䵁䅁䅁权偂䅁䅁权佂䅁䅁兂䅁䅁䅁䕑浲䅑䅅䅁䉁䅁䅁兂硂児塲㍯剁䅑杷允䅁䅁䅕䅁䑁䅁䅷䅁䭁䉁䅯䅁䭁䅁䅅䅁䭁䅁䅕䅁䙁䅁䅁䅁䅄效䅚允䅁䅁䅅䅁䙁䭁睒児塲⭯⽧䍄䉁䅁䅁䅂䅁䅁䅍䅄䅁䅁䅯睔䅁䅁䅯杔䅁䅁䅕䅁䅁䍁䡂欵䉁䅁䅁允䅁䅁䅕浚浚浚浚䕅䵁䅉䅅䅁䙁䅁䅁睁䵁䅁䅁权敁䅁䅁权䉁䅁䅁权䙁䅁䅁兂䅁䅁䅁䭁汘䅑䅅䅁䉁䅁䅁兂穁積積積呐睐杷允䅁䅁䅕䅁䑁䅁䅷䅁䭁䉁䄴䅁䭁䅁䅅䅁䭁䅁䅕䅁䙁䅁䅁䅁杁畤䅚允䅁䅁䅅䅁䙁䅁䅁䅁䅁乁⽁䍄䉁䅁䅁兂䅁䅁䅍䅄䅁䅁䅯䅁䅁䅁䅯允䅁䅁䅯兂䅁䅁䅕䅁䅁䍁灂欵䉁䅁䅁允䅁䅁䅕䉵䘶ㄶ㑇樳䴸䅉䅅䅁䙁䅁䅁睁䵁䅁䅁权捁䅁䅁权呂䅁䅁权䙁䅁䅁兂䅁䅁䅁䍧浢䅑䅅䅁䉁䅁䅁兂偃癷潕䅘甸䅑杷允䅁䅁䅕䅁䑁䅁䅷䅁䭁䉁䄴䅁䭁䅁䅅䅁䭁䅁䅕䅁䙁䅁䅁䅁杄⭡䅚允䅁䅁䅅䅁䙁䅁䅁䅁䅁乁⽁䍄䉁䅁䅁䅂䅁䅁䅍䅄䅁䅁䅯睔䅁䅁䅯杔䅁䅁䅕䅁䅁䝁橄唵䉁䅁䅁允䅁䅁䅕㘱睎児塲䕅䵁䅉䅅䅁䙁䅁䅁睁䵁䅁䅁权䅁䅁䅁权䉁䅁䅁权䙁䅁䅁兂䅁䅁䅁䵷汄䅑䅅䅁䉁䅁䅁兂㥁瑃橥䑣愳睐杷允䅁䅁䅑䅁䑁䅁䅷䅁䭁䕁䄸䅁䭁䕁䄴䅁䙁䅁䅁䅁䅄⭔䅚允䅁䅁䅅䅁䙁佁剸䉵䘶砶䅂䍄䉁䅁䅁䅂䅁䅁䅍䅄䅁䅁䅯睔䅁䅁䅯杔䅁䅁䅕䅁䅁䍁䍄唵䉁䅁䅁允䅁䅁䅕瑃橥䑣䬰稷䴸䅉䅅䅁䙁䅁䅁睁䵁䅁䅁权䅁䅁䅁权䉁䅁䅁权䙁䅁䅁兂䅁䅁䅁䡯洷䅑䅅䅁䉁䅁䅁兂㑃潈牘払敪睐杷允䅁䅁䅑䅁䑁䅁䅷䅁䭁䕁䄸䅁䭁䕁䄴䅁䙁䅁䅁䅁䅂伯䅖允䅁䅁䅅䅁䙁䅁䅁䅁䅁䅁䄵䍄䉁䅁䅁兂䅁䅁䅍䅄䅁䅁䅯䅈䅁䅁䅯允䅁䅁䅯兂䅁䅁䅕䅁䅁䕁㍁欵䉁䅁䅁允䅁䅁䅕椹捨㡪ㅌ䐲䴸䅉䅅䅁䕁䅁䅁睁䵁䅁䅁权偂䅁䅁权佂䅁䅁兂䅁䅁䅁䙙洯䅑䅅䅁䉁䅁䅁兂晁敨剴䉵倴䅑杷允䅁䅁䅑䅁䑁䅁䅷䅁䭁䕁䄸䅁䭁䕁䄴䅁䙁䅁䅁䅁䅂教䅚允䅁䅁䅅䅁䙁䡁㥅瑃橥䅣䄱䍄䉁䅁䅁兂䅁䅁䅍䅄䅁䅁䅯睈䅁䅁䅯允䅁䅁䅯兂䅁䅁䅕䅁䅁䥁䭄唵䉁䅁䅁允䅁䅁䅕䡰㥁瑃橥䐴䴸䅉䅅䅁䕁䅁䅁睁䵁䅁䅁权偂䅁䅁权佂䅁䅁兂䅁䅁䅁䵯汘䅑䅅䅁䉁䅁䅁兂啁歲桦桥㉔睐杷允䅁䅁䅕䅁䑁䅁䅷䅁䭁䉁䄸䅁䭁䅁䅅䅁䭁䅁䅕䅁䙁䅁䅁䅁杁⭒䅚允䅁䅁䅅䅁䙁䭁睒児塲⭯⽁䍄䉁䅁䅁兂䅁䅁䅍䅄䅁䅁䅯杈䅁䅁䅯允䅁䅁䅯兂䅁䅁䅕䅁䅁䥁晄唵䉁䅁䅁允䅁䅁䅕積積積積稰䴸䅉䅅䅁䙁䅁䅁睁䵁䅁䅁权䅁䅁䅁权呂䅁䅁权䙁䅁䅁兂䅁䅁䅁偷汲䅑䅅䅁䉁䅁䅁兂灁䥘䌯圹祧䅑杷允䅁䅁䅕䅁䑁䅁䅷䅁䭁䉁䅯䅁䭁䙁䅍䅁䭁䅁䅕䅁䙁䅁䅁䅁权畍䅚允䅁䅁䅅䅁䙁䉁䘫ㄶ㑇樳䅰䍄䉁䅁䅁䅂䅁䅁䅍䅄䅁䅁䅯睔䅁䅁䅯杔䅁䅁䅕䅁䅁䭁畁欵䉁䅁䅁允䅁䅁䅕浚浚浚浚歅䵁䅉䅅䅁䙁䅁䅁睁䵁䅁䅁权䅁䅁䅁权䉁䅁䅁权䙁䅁䅁兂䅁䅁䅁义汶䅑䅅䅁䉁䅁䅁兂桄桥畓⭒慈睐杷允䅁䅁䅕䅁䑁䅁䅷䅁䭁䅁䅁䅁䭁䅁䅅䅁䭁䅁䅕䅁䙁䅁䅁䅁䅃伱䅖允䅁䅁䅅䅁䙁佁㙆䭆䠵搴⽯䍄䉁䅁䅁䅂䅁䅁䅍䅄䅁䅁䅯睔䅁䅁䅯杔䅁䅁䅕䅁䅁䥁㝁欵䉁䅁䅁允䅁䅁䅕⽷潕䥘䌯啄䵁䅉䅅䅁䙁䅁䅁睁䵁䅁䅁权敁䅁䅁权䉁䅁䅁权䙁䅁䅁兂䅁䅁䅁䱑汈䅑䅅䅁䉁䅁䅁兂穁積積積呐睐杷允䅁䅁䅕䅁䑁䅁䅷䅁䭁䉁䄴䅁䭁䙁䅍䅁䭁䅁䅕䅁䙁䅁䅁䅁䅄⬸䅖允䅁䅁䅅䅁䙁䡁潎敫㠱祐䅸䍄䉁䅁䅁兂䅁䅁䅍䅄䅁䅁䅯䅁䅁䅁䅯允䅁䅁䅯兂䅁䅁䅕䅁䅁䕁潂欵䉁䅁䅁允䅁䅁䅕䉵䘶ㄶ㑇樳䴸䅉䅅䅁䙁䅁䅁睁䵁䅁䅁权捁䅁䅁权䉁䅁䅁权䙁䅁䅁兂䅁䅁䅁䡑浶䅑䅅䅁䉁䅁䅁兂㉄䙋偹癷奘睐杷允䅁䅁䅑䅁䑁䅁䅷䅁䭁䕁䄸䅁䭁䕁䄴䅁䙁䅁䅁䅁䅄田䅖允䅁䅁䅅䅁䙁䙁㑋潈牘兕䅚䍄䉁䅁䅁兂䅁䅁䅍䅄䅁䅁䅯䅈䅁䅁䅯允䅁䅁䅯兂䅁䅁䅕䅁䅁䕁敂欵䉁䅁䅁允䅁䅁䅕椹捨㡪ㅌ䐲䴸䅉䅅䅁䙁䅁䅁睁䵁䅁䅁权晁䅁䅁权呂䅁䅁权䙁䅁䅁兂䅁䅁䅁䕁洯䅑䅅䅁䉁䅁䅁兂䕁杖琴桳砰䅑杷允䅁䅁䅕䅁䑁䅁䅷䅁䭁䉁䄸䅁䭁䙁䅍䅁䭁䅁䅕䅁䙁䅁䅁䅁杂畤䅚允䅁䅁䅅䅁䙁䝁㡱䩤奍䑊䅆䍄䉁䅁䅁兂䅁䅁䅍䅄䅁䅁䅯䅁䅁䅁䅯允䅁䅁䅯兂䅁䅁䅕䅁䅁䍁獃唵䉁䅁䅁允䅁䅁䅕灭婭婭婭吲䴸䅉䅅䅁䕁䅁䅁睁䵁䅁䅁权偂䅁䅁权佂䅁䅁兂䅁䅁䅁乁氷䅑䅅䅁䉁䅁䅁兂䥂場啯歲䩣䅑杷允䅁䅁䅕䅁䑁䅁䅷䅁䭁䉁䅷䅁䭁䙁䅍䅁䭁䅁䅕䅁䙁䅁䅁䅁权电䅖允䅁䅁䅅䅁䙁䝁光䑗ね䍓䄵䍄䉁䅁䅁䅂䅁䅁䅍䅄䅁䅁䅯睔䅁䅁䅯杔䅁䅁䅕䅁䅁䅁杂欵䉁䅁䅁允䅁䅁䅕呣䬰㘱睎い䵁䅉䅅䅁䙁䅁䅁睁䵁䅁䅁权䅁䅁䅁权䉁䅁䅁权䙁䅁䅁兂䅁䅁䅁䍑浈䅑䅅䅁䉁䅁䅁兂㑃潈牘払敪睐杷允䅁䅁䅑䅁䑁䅁䅷䅁䭁䕁䄸䅁䭁䕁䄴䅁䙁䅁䅁䅁䅃⭘䅚允䅁䅁䅅䅁䙁䵁䴳䵺䵺䅺䄵䍄䉁䅁䅁䅂䅁䅁䅍䅄䅁䅁䅯睔䅁䅁䅯杔䅁䅁䅕䅁䅁佁偁欵䉁䅁䅁允䅁䅁䅕䉵䘶ㄶ㑇歅䵁䅉䅅䅁䙁䅁䅁睁䵁䅁䅁权捁䅁䅁权呂䅁䅁权䙁䅁䅁兂䅁䅁䅁䘴浺䅑䅅䅁䉁䅁䅁兂楃扒穢刯畑䅑杷允䅁䅁䅕䅁䑁䅁䅷䅁䭁䉁䅯䅁䭁䅁䅅䅁䭁䅁䅕䅁䙁䅁䅁䅁䅃佳䅖允䅁䅁䅅䅁䙁䅁䅁䅁䅁佁⽁䍄䉁䅁䅁兂䅁䅁䅍䅄䅁䅁䅯杇䅁䅁䅯允䅁䅁䅯兂䅁䅁䅕䅁䅁䥁㥁欵䉁䅁䅁允䅁䅁䅕䡰㥁瑃橥䐶䴸䅉䅅䅁䙁䅁䅁睁䵁䅁䅁权晁䅁䅁权呂䅁䅁权䙁䅁䅁兂䅁䅁䅁䡑浘䅑䅅䅁䉁䅁䅁兂煂䡶呓䍇硑䅑杷允䅁䅁䅑䅁䑁䅁䅷䅁䭁䕁䄸䅁䭁䕁䄴䅁䙁䅁䅁䅁䅂界䅚允䅁䅁䅅䅁䙁䡁啳歲桦桥䅊䍄䉁䅁䅁兂䅁䅁䅍䅄䅁䅁䅯杇䅁䅁䅯允䅁䅁䅯兂䅁䅁䅕䅁䅁䍁睄唵䉁䅁䅁允䅁䅁䅕積積積積稴䴸䅉䅅䅁䙁䅁䅁睁䵁䅁䅁权慁䅁䅁权呂䅁䅁权䙁䅁䅁兂䅁䅁䅁䕑浘䅑䅅䅁䉁䅁䅁兂䵂㑎䉬䕙㝕䅑杷允䅁䅁䅑䅁䑁䅁䅷䅁䭁䕁䄸䅁䭁䕁䄴䅁䙁䅁䅁䅁䅃⬸䅖允䅁䅁䅅䅁䙁䭁䠵場啯杲䄹䍄䉁䅁䅁兂䅁䅁䅍䅄䅁䅁䅯杈䅁䅁䅯睕䅁䅁䅯兂䅁䅁䅕䅁䅁䥁偁欵䉁䅁䅁允䅁䅁䅕硢䑋䵷桲啋䵁䅉䅅䅁䕁䅁䅁睁䵁䅁䅁权偂䅁䅁权佂䅁䅁兂䅁䅁䅁䅷洯䅑䅅䅁䉁䅁䅁兂偃癷潕䥘匸䅑杷允䅁䅁䅕䅁䑁䅁䅷䅁䭁䉁䅷䅁䭁䙁䅍䅁䭁䅁䅕䅁䙁䅁䅁䅁䅁畉䅚允䅁䅁䅅䅁䙁䥁䌯匹捨祄䄵䍄䉁䅁䅁兂䅁䅁䅍䅄䅁䅁䅯䅁䅁䅁䅯睕䅁䅁䅯兂䅁䅁䅕䅁䅁䕁畄唵䉁䅁䅁允䅁䅁䅕積積積呏歍䵁䅉䅅䅁䙁䅁䅁睁䵁䅁䅁权捁䅁䅁权呂䅁䅁权䙁䅁䅁兂䅁䅁䅁余汈䅑䅅䅁䉁䅁䅁兂楂䙅㕧䕴畧䅑杷允䅁䅁䅕䅁䑁䅁䅷䅁䭁䉁䄴䅁䭁䅁䅅䅁䭁䅁䅕䅁䙁䅁䅁䅁杄⭎䅚允䅁䅁䅅䅁䙁䵁ㅐ䙋偹瑷⽕䍄䉁䅁䅁䅂䅁䅁䅍䅄䅁䅁䅯睔䅁䅁䅯杔䅁䅁䅕䅁䅁䵁灁欵䉁䅁䅁允䅁䅁䅕浚浚浚浚歅䵁䅉䅅䅁䙁䅁䅁睁䵁䅁䅁权䅁䅁䅁权䉁䅁䅁权䙁䅁䅁兂䅁䅁䅁䐴浐䅑䅅䅁䉁䅁䅁兂㑃潈牘払敪睐杷允䅁䅁䅑䅁䑁䅁䅷䅁䭁䕁䄸䅁䭁䕁䄴䅁䙁䅁䅁䅁䅁畕䅚允䅁䅁䅅䅁䙁䭁䠵場啯桲䅂䍄䉁䅁䅁䅂䅁䅁䅍䅄䅁䅁䅯睔䅁䅁䅯杔䅁䅁䅕䅁䅁䅁䑄唵䉁䅁䅁允䅁䅁䅕䉵䘶ㄶ㑇樸䴸䅉䅅䅁䙁䅁䅁睁䵁䅁䅁权摁䅁䅁权䉁䅁䅁权䙁䅁䅁兂䅁䅁䅁䕯浢䅑䅅䅁䉁䅁䅁兂畃⭒㙆䭆堷睐杷允䅁䅁䅕䅁䑁䅁䅷䅁䭁䉁䄸䅁䭁䙁䅍䅁䭁䅁䅕䅁䙁䅁䅁䅁杂⭔䅚允䅁䅁䅅䅁䙁䅁坒楄礲呈䅆䍄䉁䅁䅁䅂䅁䅁䅍䅄䅁䅁䅯睔䅁䅁䅯杔䅁䅁䅕䅁䅁佁䵁欵䉁䅁䅁允䅁䅁䅕捺䵺䵺䵺歅䵁䅉䅅䅁䙁䅁䅁睁䵁䅁䅁权摁䅁䅁权呂䅁䅁权䙁䅁䅁兂䅁䅁䅁䙉浮䅑䅅䅁䉁䅁䅁兂䑄匹捨㑪畉䅑杷允䅁䅁䅕䅁䑁䅁䅷䅁䭁䉁䅯䅁䭁䙁䅍䅁䭁䅁䅕䅁䙁䅁䅁䅁杄⭙䅚允䅁䅁䅅䅁䙁䱁昶楇搯䑚䅴䍄䉁䅁䅁䅂䅁䅁䅍䅄䅁䅁䅯睔䅁䅁䅯杔䅁䅁䅕䅁䅁䝁敂欵䉁䅁䅁允䅁䅁䅕呣䬰㘱睎い䵁䅉䅅䅁䙁䅁䅁睁䵁䅁䅁权捁䅁䅁权䉁䅁䅁权䙁䅁䅁兂䅁䅁䅁偧氳䅑䅅䅁䉁䅁䅁兂晁敨剴䉵嘷睐杷允䅁䅁䅕䅁䑁䅁䅷䅁䭁䉁䄴䅁䭁䅁䅅䅁䭁䅁䅕䅁䙁䅁䅁䅁杁當䅖允䅁䅁䅅䅁䙁䑁積積積㥍⽍䍄䉁䅁䅁䅂䅁䅁䅍䅄䅁䅁䅯睔䅁䅁䅯杔䅁䅁䅕䅁䅁䅁摂欵䉁䅁䅁允䅁䅁䅕歲桦桥畓い䵁䅉䅅䅁䙁䅁䅁睁䵁䅁䅁权䅁䅁䅁权䉁䅁䅁权䙁䅁䅁兂䅁䅁䅁䕉浢䅑䅅䅁䉁䅁䅁兂㑃潈牘払敪睐杷允䅁䅁䅕䅁䑁䅁䅷䅁䭁䉁䄸䅁䭁䙁䅍䅁䭁䅁䅕䅁䙁䅁䅁䅁杁⭱䅖允䅁䅁䅅䅁䙁䱁敧敨剴䑥䅂䍄䉁䅁䅁兂䅁䅁䅍䅄䅁䅁䅯杇䅁䅁䅯允䅁䅁䅯兂䅁䅁䅕䅁䅁䕁療欵䉁䅁䅁允䅁䅁䅕䡰㥁瑃橥䐶䴸䅉䅅䅁䙁䅁䅁睁䵁䅁䅁权敁䅁䅁权呂䅁䅁权䙁䅁䅁兂䅁䅁䅁䡉浔䅑䅅䅁䉁䅁䅁兂灁䥘䌯圹桧䅑杷允䅁䅁䅕䅁䑁䅁䅷䅁䭁䉁䄴䅁䭁䅁䅅䅁䭁䅁䅕䅁䙁䅁䅁䅁杁敍䅚允䅁䅁䅅䅁䙁䵁ㅐ䙋偹瑷⽕䍄䉁䅁䅁䅂䅁䅁䅍䅄䅁䅁䅯睔䅁䅁䅯杔䅁䅁䅕䅁䅁佁坂欵䉁䅁䅁允䅁䅁䅕体㙆䭆䠵啄䵁䅉䅅䅁䙁䅁䅁睁䵁䅁䅁权䅁䅁䅁权呂䅁䅁权䙁䅁䅁兂䅁䅁䅁䉷浪䅑䅅䅁䉁䅁䅁兂療潅䅐杹穅䅑杷允䅁䅁䅕䅁䑁䅁䅷䅁䭁䅁䅁䅁䭁䅁䅅䅁䭁䅁䅕䅁䙁䅁䅁䅁权佣䅚允䅁䅁䅅䅁䙁䱁敧敨剴乵⼴䍄䉁䅁䅁䅂䅁䅁䅍䅄䅁䅁䅯睔䅁䅁䅯杔䅁䅁䅕䅁䅁䅁奃唵䉁䅁䅁允䅁䅁䅕瑃橥䑣䬰穸䴸䅉䅅䅁䕁䅁䅁睁䵁䅁䅁权偂䅁䅁权佂䅁䅁兂䅁䅁䅁䵧汐䅑䅅䅁䉁䅁䅁兂䙃ㄶ㑇潈穘睐杷允䅁䅁䅕䅁䑁䅁䅷䅁䭁䉁䅷䅁䭁䙁䅍䅁䭁䅁䅕䅁䙁䅁䅁䅁杄佋䅚允䅁䅁䅅䅁䙁䥁䌯匹捨祄䄵䍄䉁䅁䅁兂䅁䅁䅍䅄䅁䅁䅯先䅁䅁䅯睕䅁䅁䅯兂䅁䅁䅕䅁䅁䍁楁欵䉁䅁䅁允䅁䅁䅕瑃橥䑣䬳歌䵁䅉䅅䅁䙁䅁䅁睁䵁䅁䅁权䅁䅁䅁权呂䅁䅁权䙁䅁䅁兂䅁䅁䅁䩷汦䅑䅅䅁䉁䅁䅁兂㡃䩤奍䡂睙䅑杷允䅁䅁䅕䅁䑁䅁䅷䅁䭁䅁䅁䅁䭁䙁䅍䅁䭁䅁䅕䅁䙁䅁䅁䅁权⭉䅚允䅁䅁䅅䅁䙁佁兘瑉㕶橐䅎䍄䉁䅁䅁兂䅁䅁䅍䅄䅁䅁䅯先䅁䅁䅯睕䅁䅁䅯兂䅁䅁䅕䅁䅁䭁㝂欵䉁䅁䅁允䅁䅁䅕䬸䝦穓䩦啌䵁䅉䅅䅁䕁䅁䅁睁䵁䅁䅁权偂䅁䅁权佂䅁䅁兂䅁䅁䅁䐴浪䅑䅅䅁䉁䅁䅁兂㝂䭆䠵場佯䅑杷允䅁䅁䅕䅁䑁䅁䅷䅁䭁䉁䄰䅁䭁䅁䅅䅁䭁䅁䅕䅁䙁䅁䅁䅁䅁畔䅚允䅁䅁䅅䅁䙁䭁䠵場啯瑲⽣䍄䉁䅁䅁兂䅁䅁䅍䅄䅁䅁䅯睈䅁䅁䅯睕䅁䅁䅯兂䅁䅁䅕䅁䅁䅁扁欵䉁䅁䅁允䅁䅁䅕牒穢搯㑔䕍䵁䅉䅅䅁䕁䅁䅁睁䵁䅁䅁权偂䅁䅁权佂䅁䅁兂䅁䅁䅁偙汢䅑䅅䅁䉁䅁䅁兂㑃潈牘払剧䅑杷允䅁䅁䅕䅁䑁䅁䅷䅁䭁䉁䄸䅁䭁䙁䅍䅁䭁䅁䅕䅁䙁䅁䅁䅁杄敬䅖允䅁䅁䅅䅁䙁䅁䅁䅁䅁䐴䅂䍄䉁䅁䅁兂䅁䅁䅍䅄䅁䅁䅯䅁䅁䅁䅯允䅁䅁䅯兂䅁䅁䅕䅁䅁䕁婂欵䉁䅁䅁允䅁䅁䅕䉵䘶ㄶ㑇樳䴸䅉䅅䅁䙁䅁䅁睁䵁䅁䅁权慁䅁䅁权呂䅁䅁权䙁䅁䅁兂䅁䅁䅁䑁洯䅑䅅䅁䉁䅁䅁兂䙄䱉祂䑡㝅䅑杷允䅁䅁䅕䅁䑁䅁䅷䅁䭁䉁䄸䅁䭁䙁䅍䅁䭁䅁䅕䅁䙁䅁䅁䅁䅁敭䅖允䅁䅁䅅䅁䙁䅁䅁䅁䅁䐴䅂䍄䉁䅁䅁䅂䅁䅁䅍䅄䅁䅁䅯睔䅁䅁䅯杔䅁䅁䅕䅁䅁䭁捂欵䉁䅁䅁允䅁䅁䅕灭婭婭婭い䵁䅉䅅䅁䙁䅁䅁睁䵁䅁䅁权摁䅁䅁权呂䅁䅁权䙁䅁䅁兂䅁䅁䅁䝧浦䅑䅅䅁䉁䅁䅁兂㍁啩杆刵畁䅑杷允䅁䅁䅑䅁䑁䅁䅷䅁䭁䕁䄸䅁䭁䕁䄴䅁䙁䅁䅁䅁䅃甲䅖允䅁䅁䅅䅁䙁䕁桪桥畓睒䅬䍄䉁䅁䅁兂䅁䅁䅍䅄䅁䅁䅯杇䅁䅁䅯睕䅁䅁䅯兂䅁䅁䅕䅁䅁䕁噃唵䉁䅁䅁允䅁䅁䅕瑃橥䑣焳䕏䵁䅉䅅䅁䕁䅁䅁睁䵁䅁䅁权偂䅁䅁权佂䅁䅁兂䅁䅁䅁䙉浶䅑䅅䅁䉁䅁䅁兂乄䵺䵺䵺佷䅑杷允䅁䅁䅕䅁䑁䅁䅷䅁䭁䉁䅷䅁䭁䙁䅍䅁䭁䅁䅕䅁䙁䅁䅁䅁权畡䅚允䅁䅁䅅䅁䙁䡁潎敫㠱礯䄱䍄䉁䅁䅁兂䅁䅁䅍䅄䅁䅁䅯䅁䅁䅁䅯允䅁䅁䅯兂䅁䅁䅕䅁䅁佁䝁欵䉁䅁䅁允䅁䅁䅕䉵䘶ㄶ㑇樳䴸䅉䅅䅁䙁䅁䅁睁䵁䅁䅁权䅁䅁䅁权䉁䅁䅁权䙁䅁䅁兂䅁䅁䅁䝙浄䅑䅅䅁䉁䅁䅁兂㑃潈牘払敪睐杷允䅁䅁䅕䅁䑁䅁䅷䅁䭁䉁䄴䅁䭁䙁䅍䅁䭁䅁䅕䅁䙁䅁䅁䅁䅂⭑䅚允䅁䅁䅅䅁䙁偁㥔䠱灪楚䅒䍄䉁䅁䅁䅂䅁䅁䅍䅄䅁䅁䅯睔䅁䅁䅯杔䅁䅁䅕䅁䅁䅁晄唵䉁䅁䅁允䅁䅁䅕児塲㍯㥁歃䵁䅉䅅䅁䙁䅁䅁睁䵁䅁䅁权摁䅁䅁权䉁䅁䅁权䙁䅁䅁兂䅁䅁䅁䉁浦䅑䅅䅁䉁䅁䅁兂晁敨剴䉵嘷睐杷允䅁䅁䅕䅁䑁䅁䅷䅁䭁䉁䄴䅁䭁䅁䅅䅁䭁䅁䅕䅁䙁䅁䅁䅁䅄⭬䅖允䅁䅁䅅䅁䙁䑁積積積㥍⽍䍄䉁䅁䅁䅂䅁䅁䅍䅄䅁䅁䅯睔䅁䅁䅯杔䅁䅁䅕䅁䅁䅁允欵䉁䅁䅁允䅁䅁䅕場啯歲桦歅䵁䅉䅅䅁䙁䅁䅁睁䵁䅁䅁权慁䅁䅁权呂䅁䅁权䙁䅁䅁兂䅁䅁䅁䑯浶䅑䅅䅁䉁䅁䅁兂䙄䱉祂䑡㝅䅑杷允䅁䅁䅕䅁䑁䅁䅷䅁䭁䅁䅁䅁䭁䅁䅅䅁䭁䅁䅕䅁䙁䅁䅁䅁䅂伵䅖允䅁䅁䅅䅁䙁佁㙆䭆䠵搴⽯䍄䉁䅁䅁兂䅁䅁䅍䅄䅁䅁䅯䅁䅁䅁䅯睕䅁䅁䅯兂䅁䅁䅕䅁䅁䝁䭂欵䉁䅁䅁允䅁䅁䅕潅䅐煹䙈き䵁䅉䅅䅁䙁䅁䅁睁䵁䅁䅁权䅁䅁䅁权呂䅁䅁权䙁䅁䅁兂䅁䅁䅁䌴浮䅑䅅䅁䉁䅁䅁兂汄䌰扌含稴䅑杷允䅁䅁䅕䅁䑁䅁䅷䅁䭁䉁䄴䅁䭁䙁䅍䅁䭁䅁䅕䅁䙁䅁䅁䅁䅃⭥䅚允䅁䅁䅅䅁䙁䍁捬㡪ㅌ䍡䅆䍄䉁䅁䅁䅂䅁䅁䅍䅄䅁䅁䅯睔䅁䅁䅯杔䅁䅁䅕䅁䅁䅁扂欵䉁䅁䅁允䅁䅁䅕⽷潕䥘䌯啄䵁䅉䅅䅁䙁䅁䅁睁䵁䅁䅁权䅁䅁䅁权䉁䅁䅁权䙁䅁䅁兂䅁䅁䅁䭙汲䅑䅅䅁䉁䅁䅁兂慃婭婭婭婮睐杷允䅁䅁䅑䅁䑁䅁䅷䅁䭁䕁䄸䅁䭁䕁䄴䅁䙁䅁䅁䅁䅃佱䅖允䅁䅁䅅䅁䙁乁橥䑣䬰㤱⽍䍄䉁䅁䅁兂䅁䅁䅍䅄䅁䅁䅯䅈䅁䅁䅯允䅁䅁䅯兂䅁䅁䅕䅁䅁䝁流欵䉁䅁䅁允䅁䅁䅕歲桦桥畓稱䴸䅉䅅䅁䙁䅁䅁睁䵁䅁䅁权晁䅁䅁权呂䅁䅁权䙁䅁䅁兂䅁䅁䅁䑑浘䅑䅅䅁䉁䅁䅁兂⽁噎㘶卓硷䅑杷允䅁䅁䅑䅁䑁䅁䅷䅁䭁䕁䄸䅁䭁䕁䄴䅁䙁䅁䅁䅁䅄伲䅖允䅁䅁䅅䅁䙁佁剸䉵䘶眶䅤䍄䉁䅁䅁兂䅁䅁䅍䅄䅁䅁䅯先䅁䅁䅯允䅁䅁䅯兂䅁䅁䅕䅁䅁䝁㕃唵䉁䅁䅁允䅁䅁䅕㘱睎児塲稰䴸䅉䅅䅁䕁䅁䅁睁䵁䅁䅁权偂䅁䅁权佂䅁䅁兂䅁䅁䅁䘴浔䅑䅅䅁䉁䅁䅁兂慃婭婭婭偫䅑杷允䅁䅁䅑䅁䑁䅁䅷䅁䭁䕁䄸䅁䭁䕁䄴䅁䙁䅁䅁䅁䅂敄䅚允䅁䅁䅅䅁䙁䵁ㅐ䙋偹桷䅊䍄䉁䅁䅁䅂䅁䅁䅍䅄䅁䅁䅯睔䅁䅁䅯杔䅁䅁䅕䅁䅁佁慂欵䉁䅁䅁允䅁䅁䅕㘱睎児塲啄䵁䅉䅅䅁䙁䅁䅁睁䵁䅁䅁权䅁䅁䅁权䉁䅁䅁权䙁䅁䅁兂䅁䅁䅁䡉浶䅑䅅䅁䉁䅁䅁兂㑃潈牘払敪睐杷允䅁䅁䅕䅁䑁䅁䅷䅁䭁䉁䄸䅁䭁䙁䅍䅁䭁䅁䅕䅁䙁䅁䅁䅁䅄畂䅚允䅁䅁䅅䅁䙁
A4: 䥁䅐煹䙆橬䅂䍄䉁䅁䅁䅂䅁䅁䅍䅄䅁䅁䅯睔䅁䅁䅯杔䅁䅁䅕䅁䅁䥁桄唵䉁䅁䅁允䅁䅁䅕牕敧敨剴䕄䵁䅉䅅䅁䙁䅁䅁睁䵁䅁䅁权敁䅁䅁权呂䅁䅁权䙁䅁䅁兂䅁䅁䅁䡉浘䅑䅅䅁䉁䅁䅁兂灁䥘䌯圹桧䅑杷允䅁䅁䅑䅁䑁䅁䅷䅁䭁䕁䄸䅁䭁䕁䄴䅁䙁䅁䅁䅁䅁⭇䅚允䅁䅁䅅䅁䙁䭁䠵場啯桲䅆䍄䉁䅁䅁兂䅁䅁䅍䅄䅁䅁䅯䅁䅁䅁䅯允䅁䅁䅯兂䅁䅁䅕䅁䅁䝁剄唵䉁䅁䅁允䅁䅁䅕場啯歲桦樲䴸䅉䅅䅁䙁䅁䅁睁䵁䅁䅁权䅁䅁䅁权䉁䅁䅁权䙁䅁䅁兂䅁䅁䅁偷汌䅑䅅䅁䉁䅁䅁兂䙃ㄶ㑇潈托睐杷允䅁䅁䅕䅁䑁䅁䅷䅁䭁䉁䄴䅁䭁䅁䅅䅁䭁䅁䅕䅁䙁䅁䅁䅁权⬶䅖允䅁䅁䅅䅁䙁䑁積積積㥍⽍䍄䉁䅁䅁䅂䅁䅁䅍䅄䅁䅁䅯睔䅁䅁䅯杔䅁䅁䅕䅁䅁䅁敃唵䉁䅁䅁允䅁䅁䅕㡪ㅌ䙋偹樰䴸䅉䅅䅁䙁䅁䅁睁䵁䅁䅁权慁䅁䅁权䉁䅁䅁权䙁䅁䅁兂䅁䅁䅁䕁浘䅑䅅䅁䉁䅁䅁兂歃䑣䬰㘱潐睐杷允䅁䅁䅕䅁䑁䅁䅷䅁䭁䉁䄴䅁䭁䙁䅍䅁䭁䅁䅕䅁䙁䅁䅁䅁权⭭䅖允䅁䅁䅅䅁䙁䍁扐堫焵䍦䅰䍄䉁䅁䅁䅂䅁䅁䅍䅄䅁䅁䅯睔䅁䅁䅯杔䅁䅁䅕䅁䅁䥁祁欵䉁䅁䅁允䅁䅁䅕䅁䅁䅁䅁歅䵁䅉䅅䅁䙁䅁䅁睁䵁䅁䅁权晁䅁䅁权呂䅁䅁权䙁䅁䅁兂䅁䅁䅁䭑汘䅑䅅䅁䉁䅁䅁兂㑃潈牘塕睧䅑杷允䅁䅁䅕䅁䑁䅁䅷䅁䭁䅁䅁䅁䭁䙁䅍䅁䭁䅁䅕䅁䙁䅁䅁䅁权⭺䅖允䅁䅁䅅䅁䙁䝁渳㘫确樸䅊䍄䉁䅁䅁兂䅁䅁䅍䅄䅁䅁䅯䅈䅁䅁䅯允䅁䅁䅯兂䅁䅁䅕䅁䅁䵁㕁欵䉁䅁䅁允䅁䅁䅕椹捨㡪ㅌ䐲䴸䅉䅅䅁䙁䅁䅁睁䵁䅁䅁权摁䅁䅁权呂䅁䅁权䙁䅁䅁兂䅁䅁䅁䔴浺䅑䅅䅁䉁䅁䅁兂ㅂ硫䕧潖甴䅑杷允䅁䅁䅑䅁䑁䅁䅷䅁䭁䕁䄸䅁䭁䕁䄴䅁䙁䅁䅁䅁权攳䅖允䅁䅁䅅䅁䙁䉁䘫ㄶ㑇杈䅬䍄䉁䅁䅁兂䅁䅁䅍䅄䅁䅁䅯䅁䅁䅁䅯睕䅁䅁䅯兂䅁䅁䅕䅁䅁䕁慃唵䉁䅁䅁允䅁䅁䅕㘱睎児㍲䕍䵁䅉䅅䅁䕁䅁䅁睁䵁䅁䅁权偂䅁䅁权佂䅁䅁兂䅁䅁䅁䑉浪䅑䅅䅁䉁䅁䅁兂畃⭒㙆䭆倴䅑杷允䅁䅁䅕䅁䑁䅁䅷䅁䭁䉁䅯䅁䭁䙁䅍䅁䭁䅁䅕䅁䙁䅁䅁䅁杁畇䅚允䅁䅁䅅䅁䙁䱁穢搯㑒呩䅰䍄䉁䅁䅁兂䅁䅁䅍䅄䅁䅁䅯杇䅁䅁䅯睕䅁䅁䅯兂䅁䅁䅕䅁䅁䍁㍁欵䉁䅁䅁允䅁䅁䅕㑈牘払敪歏䵁䅉䅅䅁䕁䅁䅁睁䵁䅁䅁权偂䅁䅁权佂䅁䅁兂䅁䅁䅁佑汮䅑䅅䅁䉁䅁䅁兂㉄䙋偹癷剕䅑杷允䅁䅁䅕䅁䑁䅁䅷䅁䭁䅁䅁䅁䭁䙁䅍䅁䭁䅁䅕䅁䙁䅁䅁䅁䅄⭐䅚允䅁䅁䅅䅁䙁䅁䅁䅁䅁䑯䅎䍄䉁䅁䅁兂䅁䅁䅍䅄䅁䅁䅯先䅁䅁䅯允䅁䅁䅯兂䅁䅁䅕䅁䅁䕁湂欵䉁䅁䅁允䅁䅁䅕歲桦桥畓稱䴸䅉䅅䅁䕁䅁䅁睁䵁䅁䅁权偂䅁䅁权佂䅁䅁兂䅁䅁䅁䈴浄䅑䅅䅁䉁䅁䅁兂穁積積積呍䅑杷允䅁䅁䅕䅁䑁䅁䅷䅁䭁䅁䅁䅁䭁䙁䅍䅁䭁䅁䅕䅁䙁䅁䅁䅁䅃佦䅚允䅁䅁䅅䅁䙁䙁橔婰䕶䑁䅒䍄䉁䅁䅁兂䅁䅁䅍䅄䅁䅁䅯杈䅁䅁䅯睕䅁䅁䅯兂䅁䅁䅕䅁䅁䅁ぃ唵䉁䅁䅁允䅁䅁䅕癴㥐䠱灨䕌䵁䅉䅅䅁䙁䅁䅁睁䵁䅁䅁权敁䅁䅁权䉁䅁䅁权䙁䅁䅁兂䅁䅁䅁䅷浦䅑䅅䅁䉁䅁䅁兂㝂䭆䠵場啲睐杷允䅁䅁䅑䅁䑁䅁䅷䅁䭁䕁䄸䅁䭁䕁䄴䅁䙁䅁䅁䅁权佐䅚允䅁䅁䅅䅁䙁䙁㑋潈牘兕䅸䍄䉁䅁䅁兂䅁䅁䅍䅄䅁䅁䅯睈䅁䅁䅯允䅁䅁䅯兂䅁䅁䅕䅁䅁䭁偂欵䉁䅁䅁允䅁䅁䅕䡰㥁瑃橥䐴䴸䅉䅅䅁䕁䅁䅁睁䵁䅁䅁权偂䅁䅁权佂䅁䅁兂䅁䅁䅁偑汮䅑䅅䅁䉁䅁䅁兂硂児塲㍯乁䅑杷允䅁䅁䅕䅁䑁䅁䅷䅁䭁䉁䄸䅁䭁䙁䅍䅁䭁䅁䅕䅁䙁䅁䅁䅁杂伶䅖允䅁䅁䅅䅁䙁䍁扐堫焵䑘䅂䍄䉁䅁䅁兂䅁䅁䅍䅄䅁䅁䅯睈䅁䅁䅯睕䅁䅁䅯兂䅁䅁䅕䅁䅁䝁䙂欵䉁䅁䅁允䅁䅁䅕䙂余扌摉啍䵁䅉䅅䅁䕁䅁䅁睁䵁䅁䅁权偂䅁䅁权佂䅁䅁兂䅁䅁䅁䙙浲䅑䅅䅁䉁䅁䅁兂偃癷潕䥘伸䅑杷允䅁䅁䅑䅁䑁䅁䅷䅁䭁䕁䄸䅁䭁䕁䄴䅁䙁䅁䅁䅁䅂畗䅚允䅁䅁䅅䅁䙁䥁牘払敧全䄱䍄䉁䅁䅁兂䅁䅁䅍䅄䅁䅁䅯先䅁䅁䅯睕䅁䅁䅯兂䅁䅁䅕䅁䅁䥁浂欵䉁䅁䅁允䅁䅁䅕㑎䉬余兕歌䵁䅉䅅䅁䙁䅁䅁睁䵁䅁䅁权䅁䅁䅁权呂䅁䅁权䙁䅁䅁兂䅁䅁䅁䙯洷䅑䅅䅁䉁䅁䅁兂煃搸乊瑙穁䅑杷允䅁䅁䅕䅁䑁䅁䅷䅁䭁䅁䅁䅁䭁䙁䅍䅁䭁䅁䅕䅁䙁䅁䅁䅁䅃敧䅚允䅁䅁䅅䅁䙁偁唷佥浫吸䅎䍄䉁䅁䅁兂䅁䅁䅍䅄䅁䅁䅯先䅁䅁䅯允䅁䅁䅯兂䅁䅁䅕䅁䅁䕁畄唵䉁䅁䅁允䅁䅁䅕㘱睎児塲稰䴸䅉䅅䅁䙁䅁䅁睁䵁䅁䅁权慁䅁䅁权䉁䅁䅁权䙁䅁䅁兂䅁䅁䅁䅁浺䅑䅅䅁䉁䅁䅁兂浂浚浚浚浢睐杷允䅁䅁䅕䅁䑁䅁䅷䅁䭁䉁䄴䅁䭁䙁䅍䅁䭁䅁䅕䅁䙁䅁䅁䅁权⬳䅖允䅁䅁䅅䅁䙁䡁㥅瑃橥䌸䅴䍄䉁䅁䅁䅂䅁䅁䅍䅄䅁䅁䅯睔䅁䅁䅯杔䅁䅁䅕䅁䅁䅁獄唵䉁䅁䅁允䅁䅁䅕㘱睎児塲い䵁䅉䅅䅁䙁䅁䅁睁䵁䅁䅁权慁䅁䅁权呂䅁䅁权䙁䅁䅁兂䅁䅁䅁偁汌䅑䅅䅁䉁䅁䅁兂䑄匹捨㡪㕉䅑杷允䅁䅁䅕䅁䑁䅁䅷䅁䭁䅁䅁䅁䭁䅁䅅䅁䭁䅁䅕䅁䙁䅁䅁䅁䅄效䅚允䅁䅁䅅䅁䙁䱁敧敨剴乵⼴䍄䉁䅁䅁兂䅁䅁䅍䅄䅁䅁䅯䅁䅁䅁䅯睕䅁䅁䅯兂䅁䅁䅕䅁䅁䭁晃唵䉁䅁䅁允䅁䅁䅕㘱睎児㍲䕍䵁䅉䅅䅁䙁䅁䅁睁䵁䅁䅁权摁䅁䅁权呂䅁䅁权䙁䅁䅁兂䅁䅁䅁偧氷䅑䅅䅁䉁䅁䅁兂杂搵楁⼲瑫䅑杷允䅁䅁䅑䅁䑁䅁䅷䅁䭁䕁䄸䅁䭁䕁䄴䅁䙁䅁䅁䅁杁畗䅚允䅁䅁䅅䅁䙁䭁睒児塲睯䅸䍄䉁䅁䅁兂䅁䅁䅍䅄䅁䅁䅯杇䅁䅁䅯睕䅁䅁䅯兂䅁䅁䅕䅁䅁䵁⭂欵䉁䅁䅁允䅁䅁䅕䑔䩥坑汁く䵁䅉䅅䅁䕁䅁䅁睁䵁䅁䅁权偂䅁䅁权佂䅁䅁兂䅁䅁䅁䭉氳䅑䅅䅁䉁䅁䅁兂䙃ㄶ㑇潈托睐杷允䅁䅁䅕䅁䑁䅁䅷䅁䭁䅁䅁䅁䭁䙁䅍䅁䭁䅁䅕䅁䙁䅁䅁䅁权佁䅚允䅁䅁䅅䅁䙁䭁硲欰椱䑣䅊䍄䉁䅁䅁兂䅁䅁䅍䅄䅁䅁䅯䅈䅁䅁䅯允䅁䅁䅯兂䅁䅁䅕䅁䅁䍁桄唵䉁䅁䅁允䅁䅁䅕積積積積稰䴸䅉䅅䅁䕁䅁䅁睁䵁䅁䅁权偂䅁䅁权佂䅁䅁兂䅁䅁䅁䙁浲䅑䅅䅁䉁䅁䅁兂穁積積積乍䅑杷允䅁䅁䅑䅁䑁䅁䅷䅁䭁䕁䄸䅁䭁䕁䄴䅁䙁䅁䅁䅁䅃⭰䅖允䅁䅁䅅䅁䙁乁橥䑣䬰㤱⽍䍄䉁䅁䅁兂䅁䅁䅍䅄䅁䅁䅯䅁䅁䅁䅯睕䅁䅁䅯兂䅁䅁䅕䅁䅁䕁畂欵䉁䅁䅁允䅁䅁䅕佖汏㡭杔き䵁䅉䅅䅁䙁䅁䅁睁䵁䅁䅁权摁䅁䅁权䉁䅁䅁权䙁䅁䅁兂䅁䅁䅁䜴浪䅑䅅䅁䉁䅁䅁兂畃⭒㙆䭆堷睐杷允䅁䅁䅕䅁䑁䅁䅷䅁䭁䉁䄸䅁䭁䙁䅍䅁䭁䅁䅕䅁䙁䅁䅁䅁杂体䅚允䅁䅁䅅䅁䙁䅁坒楄礲呈䅆䍄䉁䅁䅁䅂䅁䅁䅍䅄䅁䅁䅯睔䅁䅁䅯杔䅁䅁䅕䅁䅁䕁睃唵䉁䅁䅁允䅁䅁䅕䭆䠵場啯樳䴸䅉䅅䅁䙁䅁䅁睁䵁䅁䅁权敁䅁䅁权呂䅁䅁权䙁䅁䅁兂䅁䅁䅁偷汶䅑䅅䅁䉁䅁䅁兂ぃ䡹⭡㥮灯䅑杷允䅁䅁䅕䅁䑁䅁䅷䅁䭁䅁䅁䅁䭁䅁䅅䅁䭁䅁䅕䅁䙁䅁䅁䅁䅃⭃䅚允䅁䅁䅅䅁䙁䱁敧敨剴乵⼴䍄䉁䅁䅁䅂䅁䅁䅍䅄䅁䅁䅯睔䅁䅁䅯杔䅁䅁䅕䅁䅁䝁い唵䉁䅁䅁允䅁䅁䅕浚浚浚浚䕅䵁䅉䅅䅁䕁䅁䅁睁䵁䅁䅁权偂䅁䅁权佂䅁䅁兂䅁䅁䅁偁汲䅑䅅䅁䉁䅁䅁兂偃癷潕䥘䴸䅑杷允䅁䅁䅕䅁䑁䅁䅷䅁䭁䅁䅁䅁䭁䙁䅍䅁䭁䅁䅕䅁䙁䅁䅁䅁䅂畉䅚允䅁䅁䅅䅁䙁佁兘瑉㕶橐䅎䍄䉁䅁䅁䅂䅁䅁䅍䅄䅁䅁䅯睔䅁䅁䅯杔䅁䅁䅕䅁䅁䕁㥁欵䉁䅁䅁允䅁䅁䅕灭婭婭婭ぃ䵁䅉䅅䅁䕁䅁䅁睁䵁䅁䅁权偂䅁䅁权佂䅁䅁兂䅁䅁䅁䙁浮䅑䅅䅁䉁䅁䅁兂灁䥘䌯匹佧䅑杷允䅁䅁䅕䅁䑁䅁䅷䅁䭁䅁䅁䅁䭁䙁䅍䅁䭁䅁䅕䅁䙁䅁䅁䅁䅃敃䅚允䅁䅁䅅䅁䙁䉁奂扏䥔橬䅊䍄䉁䅁䅁兂䅁䅁䅍䅄䅁䅁䅯杈䅁䅁䅯睕䅁䅁䅯兂䅁䅁䅕䅁䅁佁潁欵䉁䅁䅁允䅁䅁䅕婤奍䙂佢お䵁䅉䅅䅁䙁䅁䅁睁䵁䅁䅁权晁䅁䅁权䉁䅁䅁权䙁䅁䅁兂䅁䅁䅁䥯浌䅑䅅䅁䉁䅁䅁兂卂䉵䘶ㄶ杈睐杷允䅁䅁䅕䅁䑁䅁䅷䅁䭁䉁䄰䅁䭁䙁䅍䅁䭁䅁䅕䅁䙁䅁䅁䅁䅄何䅚允䅁䅁䅅䅁䙁䡁呗䅇坒楪䄵䍄䉁䅁䅁䅂䅁䅁䅍䅄䅁䅁䅯睔䅁䅁䅯杔䅁䅁䅕䅁䅁䕁畄唵䉁䅁䅁允䅁䅁䅕䘷㑇潈牘い䵁䅉䅅䅁䙁䅁䅁睁䵁䅁䅁权慁䅁䅁权䉁䅁䅁权䙁䅁䅁兂䅁䅁䅁偷汌䅑䅅䅁䉁䅁䅁兂穁積積積橐睐杷允䅁䅁䅕䅁䑁䅁䅷䅁䭁䅁䅁䅁䭁䅁䅅䅁䭁䅁䅕䅁䙁䅁䅁䅁䅂敔䅚允䅁䅁䅅䅁䙁䱁敧敨剴乵⼴䍄䉁䅁䅁兂䅁䅁䅍䅄䅁䅁䅯先䅁䅁䅯睕䅁䅁䅯兂䅁䅁䅕䅁䅁䝁ㅂ欵䉁䅁䅁允䅁䅁䅕䬸䝦穓䩦啌䵁䅉䅅䅁䕁䅁䅁睁䵁䅁䅁权偂䅁䅁权佂䅁䅁兂䅁䅁䅁䍁浘䅑䅅䅁䉁䅁䅁兂䥂場啯歲剣䅑杷允䅁䅁䅕䅁䑁䅁䅷䅁䭁䉁䄰䅁䭁䅁䅅䅁䭁䅁䅕䅁䙁䅁䅁䅁䅄⬯䅖允䅁䅁䅅䅁䙁䉁䘫ㄶ㑇瑈⽕䍄䉁䅁䅁兂䅁䅁䅍䅄䅁䅁䅯杈䅁䅁䅯允䅁䅁䅯兂䅁䅁䅕䅁䅁䭁祁欵䉁䅁䅁允䅁䅁䅕⽷潕䥘䌯吱䴸䅉䅅䅁䙁䅁䅁睁䵁䅁䅁权捁䅁䅁权䉁䅁䅁权䙁䅁䅁兂䅁䅁䅁䅑浢䅑䅅䅁䉁䅁䅁兂晁敨剴䉵嘷睐杷允䅁䅁䅕䅁䑁䅁䅷䅁䭁䉁䄸䅁䭁䅁䅅䅁䭁䅁䅕䅁䙁䅁䅁䅁䅂攳䅖允䅁䅁䅅䅁䙁䑁䬰㘱睎摐⽯䍄䉁䅁䅁兂䅁䅁䅍䅄䅁䅁䅯睈䅁䅁䅯睕䅁䅁䅯兂䅁䅁䅕䅁䅁䥁㉁欵䉁䅁䅁允䅁䅁䅕穐敖歵獫啍䵁䅉䅅䅁䕁䅁䅁睁䵁䅁䅁权偂䅁䅁权佂䅁䅁兂䅁䅁䅁䐴洯䅑䅅䅁䉁䅁䅁兂卂䉵䘶ㄶ䵅䅑杷允䅁䅁䅕䅁䑁䅁䅷䅁䭁䅁䅁䅁䭁䙁䅍䅁䭁䅁䅕䅁䙁䅁䅁䅁杁甯䅖允䅁䅁䅅䅁䙁䭁硲欰椱䑣䅊䍄䉁䅁䅁䅂䅁䅁䅍䅄䅁䅁䅯睔䅁䅁䅯杔䅁䅁䅕䅁䅁䍁㉄唵䉁䅁䅁允䅁䅁䅕牕敧敨剴啅䵁䅉䅅䅁䙁䅁䅁睁䵁䅁䅁权晁䅁䅁权呂䅁䅁权䙁䅁䅁兂䅁䅁䅁䡧浶䅑䅅䅁䉁䅁䅁兂煂䡶呓䍇硑䅑杷允䅁䅁䅑䅁䑁䅁䅷䅁䭁䕁䄸䅁䭁䕁䄴䅁䙁䅁䅁䅁权佖䅚允䅁䅁䅅䅁䙁䉁䘫ㄶ㑇案䅂䍄䉁䅁䅁䅂䅁䅁䅍䅄䅁䅁䅯睔䅁䅁䅯杔䅁䅁䅕䅁䅁䭁奂欵䉁䅁䅁允䅁䅁䅕㡪ㅌ䙋偹歄䵁䅉䅅䅁䕁䅁䅁睁䵁䅁䅁权偂䅁䅁权佂䅁䅁兂䅁䅁䅁䅯浐䅑䅅䅁䉁䅁䅁兂畃⭒㙆䭆儴䅑杷允䅁䅁䅕䅁䑁䅁䅷䅁䭁䉁䄸䅁䭁䙁䅍䅁䭁䅁䅕䅁䙁䅁䅁䅁权佈䅚允䅁䅁䅅䅁䙁䕁㉡⼸唳䐫䅂䍄䉁䅁䅁兂䅁䅁䅍䅄䅁䅁䅯䅁䅁䅁䅯睕䅁䅁䅯兂䅁䅁䅕䅁䅁䅁灂欵䉁䅁䅁允䅁䅁䅕佖汏㡭杔き䵁䅉䅅䅁䕁䅁䅁睁䵁䅁䅁权偂䅁䅁权佂䅁䅁兂䅁䅁䅁䭯汘䅑䅅䅁䉁䅁䅁兂䑄匹捨㡪噌睐杷允䅁䅁䅕䅁䑁䅁䅷䅁䭁䉁䅯䅁䭁䅁䅅䅁䭁䅁䅕䅁䙁䅁䅁䅁杁估䅖允䅁䅁䅅䅁䙁偁潙䥘䌯改⽁䍄䉁䅁䅁䅂䅁䅁䅍䅄䅁䅁䅯睔䅁䅁䅯杔䅁䅁䅕䅁䅁䍁㙃唵䉁䅁䅁允䅁䅁䅕䡰㥁瑃橥䐶䴸䅉䅅䅁䙁䅁䅁睁䵁䅁䅁权䅁䅁䅁权呂䅁䅁权䙁䅁䅁兂䅁䅁䅁偉汐䅑䅅䅁䉁䅁䅁兂穁積積㕍祍䅑杷允䅁䅁䅕䅁䑁䅁䅷䅁䭁䉁䄴䅁䭁䅁䅅䅁䭁䅁䅕䅁䙁䅁䅁䅁䅁敗䅚允䅁䅁䅅䅁䙁䵁ㅐ䙋偹瑷⽕䍄䉁䅁䅁䅂䅁䅁䅍䅄䅁䅁䅯睔䅁䅁䅯杔䅁䅁䅕䅁䅁䝁奂欵䉁䅁䅁允䅁䅁䅕噋偹癷潕歄䵁䅉䅅䅁䙁䅁䅁睁䵁䅁䅁权敁䅁䅁权呂䅁䅁权䙁䅁䅁兂䅁䅁䅁䡷洳䅑䅅䅁䉁䅁䅁兂灁䥘䌯圹桧䅑杷允䅁䅁䅕䅁䑁䅁䅷䅁䭁䅁䅁䅁䭁䅁䅅䅁䭁䅁䅕䅁䙁䅁䅁䅁䅄伫䅖允䅁䅁䅅䅁䙁䱁敧敨剴乵⼴䍄䉁䅁䅁䅂䅁䅁䅍䅄䅁䅁䅯睔䅁䅁䅯杔䅁䅁䅕䅁䅁䭁潄唵䉁䅁䅁允䅁䅁䅕牕敧敨剴歅䵁䅉䅅䅁䙁䅁䅁睁䵁䅁䅁权摁䅁䅁权䉁䅁䅁权䙁䅁䅁兂䅁䅁䅁䙯浪䅑䅅䅁䉁䅁䅁兂畃⭒㙆䭆堷睐杷允䅁䅁䅕䅁䑁䅁䅷䅁䭁䅁䅁䅁䭁䙁䅍䅁䭁䅁䅕䅁䙁䅁䅁䅁䅃⭦䅚允䅁䅁䅅䅁䙁偁唷佥浫吸䅎䍄䉁䅁䅁兂䅁䅁䅍䅄䅁䅁䅯先䅁䅁䅯允䅁䅁䅯兂䅁䅁䅕䅁䅁䭁噁欵䉁䅁䅁允䅁䅁䅕㑈牘払敧吱䴸䅉䅅䅁䕁䅁䅁睁䵁䅁䅁权偂䅁䅁权佂䅁䅁兂䅁䅁䅁䄴浈䅑䅅䅁䉁䅁䅁兂塄㍯㥁瑃兣䅑杷允䅁䅁䅑䅁䑁䅁䅷䅁䭁䕁䄸䅁䭁䕁䄴䅁䙁䅁䅁䅁䅄佇䅚允䅁䅁䅅䅁䙁䭁䠵場啯桲䅊䍄䉁䅁䅁䅂䅁䅁䅍䅄䅁䅁䅯睔䅁䅁䅯杔䅁䅁䅕䅁䅁䥁䍁欵䉁䅁䅁允䅁䅁䅕浚浚浚浚䕅䵁䅉䅅䅁䕁䅁䅁睁䵁䅁䅁权偂䅁䅁权佂䅁䅁兂䅁䅁䅁䑯浮䅑䅅䅁䉁䅁䅁兂䅁䅁䅁䅁佁䅑杷允䅁䅁䅕䅁䑁䅁䅷䅁䭁䉁䄸䅁䭁䅁䅅䅁䭁䅁䅕䅁䙁䅁䅁䅁权敕䅚允䅁䅁䅅䅁䙁䙁㑋潈牘敕⽁䍄䉁䅁䅁兂䅁䅁䅍䅄䅁䅁䅯杇䅁䅁䅯允䅁䅁䅯兂䅁䅁䅕䅁䅁䭁㝁欵䉁䅁䅁允䅁䅁䅕䡰㥁瑃橥䐶䴸䅉䅅䅁䕁䅁䅁睁䵁䅁䅁权偂䅁䅁权佂䅁䅁兂䅁䅁䅁䙑浪䅑䅅䅁䉁䅁䅁兂乄䵺䵺䵺佷䅑杷允䅁䅁䅕䅁䑁䅁䅷䅁䭁䉁䅷䅁䭁䙁䅍䅁䭁䅁䅕䅁䙁䅁䅁䅁䅁畸䅖允䅁䅁䅅䅁䙁佁㙆䭆䠵卙䄵䍄䉁䅁䅁兂䅁䅁䅍䅄䅁䅁䅯䅁䅁䅁䅯睕䅁䅁䅯兂䅁䅁䅕䅁䅁䝁䩂欵䉁䅁䅁允䅁䅁䅕潅䅐煹䙈き䵁䅉䅅䅁䙁䅁䅁睁䵁䅁䅁权捁䅁䅁权䉁䅁䅁权䙁䅁䅁兂䅁䅁䅁䕁洷䅑䅅䅁䉁䅁䅁兂㉄䙋偹癷奘睐杷允䅁䅁䅑䅁䑁䅁䅷䅁䭁䕁䄸䅁䭁䕁䄴䅁䙁䅁䅁䅁权⬸䅖允䅁䅁䅅䅁䙁䑁積積積睍䄹䍄䉁䅁䅁兂䅁䅁䅍䅄䅁䅁䅯杈䅁䅁䅯睕䅁䅁䅯兂䅁䅁䅕䅁䅁䭁剄唵䉁䅁䅁允䅁䅁䅕兊䉡啬䱏䕌䵁䅉䅅䅁䙁䅁䅁睁䵁䅁䅁权䅁䅁䅁权䉁䅁䅁权䙁䅁䅁兂䅁䅁䅁䔴浺䅑䅅䅁䉁䅁䅁兂㑃潈牘払敪睐杷允䅁䅁䅑䅁䑁䅁䅷䅁䭁䕁䄸䅁䭁䕁䄴䅁䙁䅁䅁䅁杁佗䅚允䅁䅁䅅䅁䙁偁潙䥘䌯儹䄵䍄䉁䅁䅁兂䅁䅁䅍䅄䅁䅁䅯睈䅁䅁䅯允䅁䅁䅯兂䅁䅁䅕䅁䅁䭁慄唵䉁䅁䅁允䅁䅁䅕捺䵺䵺䵺䐳䴸䅉䅅䅁䙁䅁䅁睁䵁䅁䅁权慁䅁䅁权呂䅁䅁权䙁䅁䅁兂䅁䅁䅁䵯決䅑䅅䅁䉁䅁䅁兂权楇搯䕊㙙䅑杷允䅁䅁䅑䅁䑁䅁䅷䅁䭁䕁䄸䅁䭁䕁䄴䅁䙁䅁䅁䅁杂⭯䅖允䅁䅁䅅䅁䙁䝁浚浚浚瑚⽙䍄䉁䅁䅁兂䅁䅁䅍䅄䅁䅁䅯杈䅁䅁䅯睕䅁䅁䅯兂䅁䅁䅕䅁䅁䭁䍄唵䉁䅁䅁允䅁䅁䅕呣䬰㘱睍䕌䵁䅉䅅䅁䙁䅁䅁睁䵁䅁䅁权慁䅁䅁权呂䅁䅁权䙁䅁䅁兂䅁䅁䅁䕉浢䅑䅅䅁䉁䅁䅁兂䵂㑎䉬䕙㝕䅑杷允䅁䅁䅕䅁䑁䅁䅷䅁䭁䉁䄴䅁䭁䙁䅍䅁䭁䅁䅕䅁䙁䅁䅁䅁䅄佃䅚允䅁䅁䅅䅁䙁䅁䅁䅁䅁䍁䅰䍄䉁䅁䅁䅂䅁䅁䅍䅄䅁䅁䅯睔䅁䅁䅯杔䅁䅁䅕䅁䅁䥁奄唵䉁䅁䅁允䅁䅁䅕歲桦桥畓啃䵁䅉䅅䅁䙁䅁䅁睁䵁䅁䅁权敁䅁䅁权呂䅁䅁权䙁䅁䅁兂䅁䅁䅁䙁浺䅑䅅䅁䉁䅁䅁兂剃堷⽷噎椴䅑杷允䅁䅁䅑䅁䑁䅁䅷䅁䭁䕁䄸䅁䭁䕁䄴䅁䙁䅁䅁䅁权申䅖允䅁䅁䅅䅁䙁䥁牘払敧全䅬䍄䉁䅁䅁兂䅁䅁䅍䅄䅁䅁䅯杇䅁䅁䅯允䅁䅁䅯兂䅁䅁䅕䅁䅁䭁㡃唵䉁䅁䅁允䅁䅁䅕䅁䅁䅁䅁䐴䴸䅉䅅䅁䙁䅁䅁睁䵁䅁䅁权摁䅁䅁权䉁䅁䅁权䙁䅁䅁兂䅁䅁䅁䕧浔䅑䅅䅁䉁䅁䅁兂畃⭒㙆䭆堷睐杷允䅁䅁䅕䅁䑁䅁䅷䅁䭁䉁䄰䅁䭁䙁䅍䅁䭁䅁䅕䅁䙁䅁䅁䅁䅄敖䅚允䅁䅁䅅䅁䙁䵁ㅐ䙋偹楧䄵䍄䉁䅁䅁兂䅁䅁䅍䅄䅁䅁䅯先䅁䅁䅯睕䅁䅁䅯兂䅁䅁䅕䅁䅁䅁獁欵䉁䅁䅁允䅁䅁䅕浚浚浚浢歌䵁䅉䅅䅁䙁䅁䅁睁䵁䅁䅁权敁䅁䅁权呂䅁䅁权䙁䅁䅁兂䅁䅁䅁䙑洯䅑䅅䅁䉁䅁䅁兂剃堷⽷噎椴䅑杷允䅁䅁䅕䅁䑁䅁䅷䅁䭁䅁䅁䅁䭁䙁䅍䅁䭁䅁䅕䅁䙁䅁䅁䅁权佖䅚允䅁䅁䅅䅁䙁䑁ね䡹⭡稳䅎䍄䉁䅁䅁兂䅁䅁䅍䅄䅁䅁䅯杈䅁䅁䅯睕䅁䅁䅯兂䅁䅁䅕䅁䅁佁硄唵䉁䅁䅁允䅁䅁䅕㉣剩堷⽷䕌䵁䅉䅅䅁䕁䅁䅁睁䵁䅁䅁权偂䅁䅁权佂䅁䅁兂䅁䅁䅁䉷浶䅑䅅䅁䉁䅁䅁兂慃婭婭婭八䅑杷允䅁䅁䅕䅁䑁䅁䅷䅁䭁䉁䅷䅁䭁䙁䅍䅁䭁䅁䅕䅁䙁䅁䅁䅁䅂敕䅚允䅁䅁䅅䅁䙁乁欰潂噇祑䄵䍄䉁䅁䅁兂䅁䅁䅍䅄䅁䅁䅯䅈䅁䅁䅯睕䅁䅁䅯兂䅁䅁䅕䅁䅁䵁偄唵䉁䅁䅁允䅁䅁䅕敨剴䉵䘶歌䵁䅉䅅䅁䙁䅁䅁睁䵁䅁䅁权晁䅁䅁权呂䅁䅁权䙁䅁䅁兂䅁䅁䅁䝧浦䅑䅅䅁䉁䅁䅁兂䭁㘱睎卐硯䅑杷允䅁䅁䅕䅁䑁䅁䅷䅁䭁䅁䅁䅁䭁䅁䅅䅁䭁䅁䅕䅁䙁䅁䅁䅁杁⭭䅖允䅁䅁䅅䅁䙁䩁婱婭婭摭⽫䍄䉁䅁䅁兂䅁䅁䅍䅄䅁䅁䅯䅁䅁䅁䅯睕䅁䅁䅯兂䅁䅁䅕䅁䅁䭁求欵䉁䅁䅁允䅁䅁䅕佖汏㡭杔き䵁䅉䅅䅁䕁䅁䅁睁䵁䅁䅁权偂䅁䅁权佂䅁䅁兂䅁䅁䅁䑷浪䅑䅅䅁䉁䅁䅁兂啁歲桦桥佑䅑杷允䅁䅁䅕䅁䑁䅁䅷䅁䭁䉁䅯䅁䭁䙁䅍䅁䭁䅁䅕䅁䙁䅁䅁䅁䅃伯䅖允䅁䅁䅅䅁䙁䥁䌯匹捨稷䅬䍄䉁䅁䅁兂䅁䅁䅍䅄䅁䅁䅯䅁䅁䅁䅯允䅁䅁䅯兂䅁䅁䅕䅁䅁䅁㉁欵䉁䅁䅁允䅁䅁䅕䉵䘶ㄶ㑇樳䴸䅉䅅䅁䙁䅁䅁睁䵁䅁䅁权晁䅁䅁权䉁䅁䅁权䙁䅁䅁兂䅁䅁䅁䌴浐䅑䅅䅁䉁䅁䅁兂䥂場啯歲桦睐杷允䅁䅁䅕䅁䑁䅁䅷䅁䭁䉁䄰䅁䭁䙁䅍䅁䭁䅁䅕䅁䙁䅁䅁䅁杄攷䅖允䅁䅁䅅䅁䙁䭁扡䍸睃楳䄱䍄䉁䅁䅁兂䅁䅁䅍䅄䅁䅁䅯先䅁䅁䅯睕䅁䅁䅯兂䅁䅁䅕䅁䅁䕁䭂欵䉁䅁䅁允䅁䅁䅕婤奍䙂佡歌䵁䅉䅅䅁䙁䅁䅁睁䵁䅁䅁权晁䅁䅁权呂䅁䅁权䙁䅁䅁兂䅁䅁䅁䡷浄䅑䅅䅁䉁䅁䅁兂䭁㘱睎卐硯䅑杷允䅁䅁䅑䅁䑁䅁䅷䅁䭁䕁䄸䅁䭁䕁䄴䅁䙁䅁䅁䅁杁敔䅚允䅁䅁䅅䅁䙁䍁捬㡪ㅌ䉋䅆䍄䉁䅁䅁兂䅁䅁䅍䅄䅁䅁䅯睈䅁䅁䅯睕䅁䅁䅯兂䅁䅁䅕䅁䅁䍁㝂欵䉁䅁䅁允䅁䅁䅕牡へ硫歧啍䵁䅉䅅䅁䕁䅁䅁睁䵁䅁䅁权偂䅁䅁权佂䅁䅁兂䅁䅁䅁䙯浦䅑䅅䅁䉁䅁䅁兂乄䵺䵺䵺佷䅑杷允䅁䅁䅕䅁䑁䅁䅷䅁䭁䉁䄰䅁䭁䅁䅅䅁䭁䅁䅕䅁䙁䅁䅁䅁杁敢䅚允䅁䅁䅅䅁䙁䭁䠵場啯瑲⽣䍄䉁䅁䅁兂䅁䅁䅍䅄䅁䅁䅯䅁䅁䅁䅯允䅁䅁䅯兂䅁䅁䅕䅁䅁䥁䭁欵䉁䅁䅁允䅁䅁䅕䉵䘶ㄶ㑇樳䴸䅉䅅䅁䙁䅁䅁睁䵁䅁䅁权䅁䅁䅁权呂䅁䅁权䙁䅁䅁兂䅁䅁䅁䙷浦䅑䅅䅁䉁䅁䅁兂㕁䵴㉨瑶稸䅑杷允䅁䅁䅕䅁䑁䅁䅷䅁䭁䉁䄰䅁䭁䙁䅍䅁䭁䅁䅕䅁䙁䅁䅁䅁䅃佗䅚允䅁䅁䅅䅁䙁䵁ㅐ䙋偹楧䄵䍄䉁䅁䅁䅂䅁䅁䅍䅄䅁䅁䅯睔䅁䅁䅯杔䅁䅁䅕䅁䅁䭁䉂欵䉁䅁䅁允䅁䅁䅕䉵䘶ㄶ㑇歄䵁䅉䅅䅁䕁䅁䅁睁䵁䅁䅁权偂䅁䅁权佂䅁䅁兂䅁䅁䅁䙙浦䅑䅅䅁䉁䅁䅁兂畃⭒㙆䭆临䅑杷允䅁䅁䅕䅁䑁䅁䅷䅁䭁䉁䅷䅁䭁䙁䅍䅁䭁䅁䅕䅁䙁䅁䅁䅁杄畍䅚允䅁䅁䅅䅁䙁䙁㕧䵴㉨楐䄵䍄䉁䅁䅁兂䅁䅁䅍䅄䅁䅁䅯先䅁䅁䅯允䅁䅁䅯兂䅁䅁䅕䅁䅁䍁䡁欵䉁䅁䅁允䅁䅁䅕㑈牘払敧吱䴸䅉䅅䅁䙁䅁䅁睁䵁䅁䅁权敁䅁䅁权䉁䅁䅁权䙁䅁䅁兂䅁䅁䅁伴汢䅑䅅䅁䉁䅁䅁兂穁積積積呐睐杷允䅁䅁䅑䅁䑁䅁䅷䅁䭁䕁䄸䅁䭁䕁䄴䅁䙁䅁䅁䅁杄敐䅚允䅁䅁䅅䅁䙁䙁偹癷潕䅘䅴䍄䉁䅁䅁兂䅁䅁䅍䅄䅁䅁䅯䅈䅁䅁䅯允䅁䅁䅯兂䅁䅁䅕䅁䅁佁䍁欵䉁䅁䅁允䅁䅁䅕㑈牘払敧吱䴸䅉䅅䅁䙁䅁䅁睁䵁䅁䅁权捁䅁䅁权䉁䅁䅁权䙁䅁䅁兂䅁䅁䅁䵑汄䅑䅅䅁䉁䅁䅁兂偃癷潕䥘匯睐杷允䅁䅁䅕䅁䑁䅁䅷䅁䭁䉁䄰䅁䭁䙁䅍䅁䭁䅁䅕䅁䙁䅁䅁䅁杁⭯䅖允䅁䅁䅅䅁䙁䕁㉡⼸唳䍥䄱䍄䉁䅁䅁兂䅁䅁䅍䅄䅁䅁䅯先䅁䅁䅯睕䅁䅁䅯兂䅁䅁䅕䅁䅁䅁啁欵䉁䅁䅁允䅁䅁䅕歵䵫楁䡵歌䵁䅉䅅䅁䙁䅁䅁睁䵁䅁䅁权摁䅁䅁权呂䅁䅁权䙁䅁䅁兂䅁䅁䅁䭉決䅑䅅䅁䉁䅁䅁兂婄発呤㘴瑕䅑杷允䅁䅁䅕䅁䑁䅁䅷䅁䭁䉁䄴䅁䭁䙁䅍䅁䭁䅁䅕䅁䙁䅁䅁䅁杄敐䅚允䅁䅁䅅䅁䙁偁㥔䠱灪楚䅒䍄䉁䅁䅁兂䅁䅁䅍䅄䅁䅁䅯䅁䅁䅁䅯允䅁䅁䅯兂䅁䅁䅕䅁䅁䕁噄唵䉁䅁䅁允䅁䅁䅕場啯歲桦樲䴸䅉䅅䅁䙁䅁䅁睁䵁䅁䅁权䅁䅁䅁权呂䅁䅁权䙁䅁䅁兂䅁䅁䅁䝧浄䅑䅅䅁䉁䅁䅁兂煃搸乊瑙穁䅑杷允䅁䅁䅕䅁䑁䅁䅷䅁䭁䉁䅯䅁䭁䙁䅍䅁䭁䅁䅕䅁䙁䅁䅁䅁杄敘䅚允䅁䅁䅅䅁䙁䱁昶楇搯䑚䅴䍄䉁䅁䅁兂䅁䅁䅍䅄䅁䅁䅯䅁䅁䅁䅯允䅁䅁䅯兂䅁䅁䅕䅁䅁䕁㝁欵䉁䅁䅁允䅁䅁䅕䉵䘶ㄶ㑇樳䴸䅉䅅䅁䙁䅁䅁睁䵁䅁䅁权晁䅁䅁权呂䅁䅁权䙁䅁䅁兂䅁䅁䅁䕁浘䅑䅅䅁䉁䅁䅁兂䕁杖琴桳砰䅑杷允䅁䅁䅑䅁䑁䅁䅷䅁䭁䕁䄸䅁䭁䕁䄴䅁䙁䅁䅁䅁杄畵䅖允䅁䅁䅅䅁䙁䭁睒児塲⭯⽧䍄䉁䅁䅁兂䅁䅁䅍䅄䅁䅁䅯杇䅁䅁䅯允䅁䅁䅯兂䅁䅁䅕䅁䅁䅁䅂欵䉁䅁䅁允䅁䅁䅕䡰㥁瑃橥䐶䴸䅉䅅䅁䙁䅁䅁睁䵁䅁䅁权捁䅁䅁权呂䅁䅁权䙁䅁䅁兂䅁䅁䅁䵑氯䅑䅅䅁䉁䅁䅁兂䙃ㄶ㑇潈畕䅑杷允䅁䅁䅕䅁䑁䅁䅷䅁䭁䉁䄴䅁䭁䙁䅍䅁䭁䅁䅕䅁䙁䅁䅁䅁杂敺䅖允䅁䅁䅅䅁䙁䍁䡵瑆佮祴䅸䍄䉁䅁䅁兂䅁䅁䅍䅄䅁䅁䅯杈䅁䅁䅯允䅁䅁䅯兂䅁䅁䅕䅁䅁䥁卄唵䉁䅁䅁允䅁䅁䅕積積積積稰䴸䅉䅅䅁䕁䅁䅁睁䵁䅁䅁权偂䅁䅁权佂䅁䅁兂䅁䅁䅁䙑浦䅑䅅䅁䉁䅁䅁兂䑄匹捨㡪义䅑杷允䅁䅁䅕䅁䑁䅁䅷䅁䭁䅁䅁䅁䭁䙁䅍䅁䭁䅁䅕䅁䙁䅁䅁䅁杂佦䅚允䅁䅁䅅䅁䙁䙁橔婰䕶䑁䅒䍄䉁䅁䅁兂䅁䅁䅍䅄䅁䅁䅯先䅁䅁䅯允䅁䅁䅯兂䅁䅁䅕䅁䅁䥁噂欵䉁䅁䅁允䅁䅁䅕歲桦桥畓稱䴸䅉䅅䅁䕁䅁䅁睁䵁䅁䅁权偂䅁䅁权佂䅁䅁兂䅁䅁䅁䕁浪䅑䅅䅁䉁䅁䅁兂穁積積積免䅑杷允䅁䅁䅕䅁䑁䅁䅷䅁䭁䉁䄴䅁䭁䙁䅍䅁䭁䅁䅕䅁䙁䅁䅁䅁杁敖䅚允䅁䅁䅅䅁䙁乁㕶浦㡱䍤䅊䍄䉁䅁䅁兂䅁䅁䅍䅄䅁䅁䅯杇䅁䅁䅯睕䅁䅁䅯兂䅁䅁䅕䅁䅁䅁㝃唵䉁䅁䅁允䅁䅁䅕穐敖歵獮問䵁䅉䅅䅁䙁䅁䅁睁䵁䅁䅁权敁䅁䅁权呂䅁䅁权䙁䅁䅁兂䅁䅁䅁䅑洷䅑䅅䅁䉁䅁䅁兂療潅䅐畹灅䅑杷允䅁䅁䅑䅁䑁䅁䅷䅁䭁䕁䄸䅁䭁䕁䄴䅁䙁䅁䅁䅁䅃⬳䅖允䅁䅁䅅䅁䙁䵁䴳䵺䵺䅺䅰䍄䉁䅁䅁兂䅁䅁䅍䅄䅁䅁䅯䅁䅁䅁䅯睕䅁䅁䅯兂䅁䅁䅕䅁䅁䥁慁欵䉁䅁䅁允䅁䅁䅕硢䑋䵷䉯き䵁䅉䅅䅁䙁䅁䅁睁䵁䅁䅁权敁䅁䅁权䉁䅁䅁权䙁䅁䅁兂䅁䅁䅁䭷汔䅑䅅䅁䉁䅁䅁兂穁積積積呐睐杷允䅁䅁䅕䅁䑁䅁䅷䅁䭁䅁䅁䅁䭁䅁䅅䅁䭁䅁䅕䅁䙁䅁䅁䅁䅁佋䅚允䅁䅁䅅䅁䙁䱁敧敨剴乵⼴䍄䉁䅁䅁䅂䅁䅁䅍䅄䅁䅁䅯睔䅁䅁䅯杔䅁䅁䅕䅁䅁䅁佂欵䉁䅁䅁允䅁䅁䅕浚浚浚浚啅䵁䅉䅅䅁䙁䅁䅁睁䵁䅁䅁权䅁䅁䅁权呂䅁䅁权䙁䅁䅁兂䅁䅁䅁䱑汪䅑䅅䅁䉁䅁䅁兂㙃兓䍷祋祣䅑杷允䅁䅁䅕䅁䑁䅁䅷䅁䭁䉁䅷䅁䭁䅁䅅䅁䭁䅁䅕䅁䙁䅁䅁䅁杁甹䅖允䅁䅁䅅䅁䙁䉁䘫ㄶ㑇瑈⽕䍄䉁䅁䅁兂䅁䅁䅍䅄䅁䅁䅯先䅁䅁䅯允䅁䅁䅯兂䅁䅁䅕䅁䅁䝁楁欵䉁䅁䅁允䅁䅁䅕㑈牘払敧吱䴸䅉䅅䅁䙁䅁䅁睁䵁䅁䅁权敁䅁䅁权呂䅁䅁权䙁䅁䅁兂䅁䅁䅁䍑浦䅑䅅䅁䉁䅁䅁兂ㅂ硫䕧獖渴䅑杷允䅁䅁䅑䅁䑁䅁䅷䅁䭁䕁䄸䅁䭁䕁䄴䅁䙁䅁䅁䅁䅄畖䅚允䅁䅁䅅䅁䙁䡁㥅瑃橥䅣䄱䍄䉁䅁䅁兂䅁䅁䅍䅄䅁䅁䅯䅈䅁䅁䅯允䅁䅁䅯兂䅁䅁䅕䅁䅁䥁卄唵䉁䅁䅁允䅁䅁䅕積積積積稰䴸䅉䅅䅁䙁䅁䅁睁䵁䅁䅁权䅁䅁䅁权呂䅁䅁权䙁䅁䅁兂䅁䅁䅁䙯洯䅑䅅䅁䉁䅁䅁兂煃搸乊瑙穁䅑杷允䅁䅁䅑䅁䑁䅁䅷䅁䭁䕁䄸䅁䭁䕁䄴䅁䙁䅁䅁䅁䅄畳䅖允䅁䅁䅅䅁䙁䩁婱婭婭摭⽫䍄䉁䅁䅁兂䅁䅁䅍䅄䅁䅁䅯杇䅁䅁䅯允䅁䅁䅯兂䅁䅁䅕䅁䅁䕁奁欵䉁䅁䅁允䅁䅁䅕䡰㥁瑃橥䐶䴸䅉䅅䅁䕁䅁䅁睁䵁䅁䅁权偂䅁䅁权佂䅁䅁兂䅁䅁䅁䙧浢䅑䅅䅁䉁䅁䅁兂乄䵺䵺䵺佷䅑杷允䅁䅁䅑䅁䑁䅁䅷䅁䭁䕁䄸䅁䭁䕁䄴䅁䙁䅁䅁䅁䅄⭏䅚允䅁䅁䅅䅁䙁䙁㑋潈牘兕䄵䍄䉁䅁䅁兂䅁䅁䅍䅄䅁䅁䅯杇䅁䅁䅯允䅁䅁䅯兂䅁䅁䅕䅁䅁䅁㙄唵䉁䅁䅁允䅁䅁䅕積積積積稴䴸䅉䅅䅁䕁䅁䅁睁䵁䅁䅁权偂䅁䅁权佂䅁䅁兂䅁䅁䅁䕧浔䅑䅅䅁䉁䅁䅁兂㑃潈牘払內䅑杷允䅁䅁䅑䅁䑁䅁䅷䅁䭁䕁䄸䅁䭁䕁䄴䅁䙁䅁䅁䅁䅃佐䅚允䅁䅁䅅䅁䙁佁㙆䭆䠵儴䅸䍄䉁䅁䅁兂䅁䅁䅍䅄䅁䅁䅯䅁䅁䅁䅯允䅁䅁䅯兂䅁䅁䅕䅁䅁䅁畃唵䉁䅁䅁允䅁䅁䅕灭婭婭婭吲䴸䅉䅅䅁䙁䅁䅁睁䵁䅁䅁权敁䅁䅁权呂䅁䅁权䙁䅁䅁兂䅁䅁䅁䱙汮䅑䅅䅁䉁䅁䅁兂㉃⼸唳䝥獫䅑杷允䅁䅁䅕䅁䑁䅁䅷䅁䭁䅁䅁䅁䭁䙁䅍䅁䭁䅁䅕䅁䙁䅁䅁䅁䅂畅䅚允䅁䅁䅅䅁䙁䉁奂扏䥔橬䅊䍄䉁䅁䅁䅂䅁䅁䅍䅄䅁䅁䅯睔䅁䅁䅯杔䅁䅁䅕䅁䅁䕁桃唵䉁䅁䅁允䅁䅁䅕牕敧敨剴䐲䴸䅉䅅䅁䕁䅁䅁睁䵁䅁䅁权偂䅁䅁权佂䅁䅁兂䅁䅁䅁䱯氳䅑䅅䅁䉁䅁䅁兂䭁㘱睎児癲睐杷允䅁䅁䅕䅁䑁䅁䅷䅁䭁䉁䅷䅁䭁䙁䅍䅁䭁䅁䅕䅁䙁䅁䅁䅁杁佦䅚允䅁䅁䅅䅁䙁䥁獴⼵灵匸䄱䍄䉁䅁䅁兂䅁䅁䅍䅄䅁䅁䅯先䅁䅁䅯睕䅁䅁䅯兂䅁䅁䅕䅁䅁䕁睂欵䉁䅁䅁允䅁䅁䅕㑎䉬余兕歌䵁䅉䅅䅁䕁䅁䅁睁䵁䅁䅁权偂䅁䅁权佂䅁䅁兂䅁䅁䅁䙯浘䅑䅅䅁䉁䅁䅁兂塄㍯㥁瑃偣䅑杷允䅁䅁䅕䅁䑁䅁䅷䅁䭁䅁䅁䅁䭁䙁䅍䅁䭁䅁䅕䅁䙁䅁䅁䅁杄畲䅖允䅁䅁䅅䅁䙁䱁䩰䅄牉穊䅊䍄䉁䅁䅁兂䅁䅁䅍䅄䅁䅁䅯䅁䅁䅁䅯睕䅁䅁䅯兂䅁䅁䅕䅁䅁䝁㥁欵䉁䅁䅁允䅁䅁䅕䅁䅁䅁权き䵁䅉䅅䅁䙁䅁䅁睁䵁䅁䅁权䅁䅁䅁权呂䅁䅁权䙁䅁䅁兂䅁䅁䅁䡷洯䅑䅅䅁䉁䅁䅁兂⭄䠱灪癊穅䅑杷允䅁䅁䅑䅁䑁䅁䅷䅁䭁䕁䄸䅁䭁䕁䄴䅁䙁䅁䅁䅁杁敖䅚允䅁䅁䅅䅁䙁䙁偹癷潕䅘䄹䍄䉁䅁䅁兂䅁䅁䅍䅄䅁䅁䅯䅁䅁䅁䅯允䅁䅁䅯兂䅁䅁䅕䅁䅁䭁瑁欵䉁䅁䅁允䅁䅁䅕䉵䘶ㄶ㑇樳䴸䅉䅅䅁䙁䅁䅁睁䵁䅁䅁权敁䅁䅁权呂䅁䅁权䙁䅁䅁兂䅁䅁䅁佉汪䅑䅅䅁䉁䅁䅁兂硂児塲⽯牁䅑杷允䅁䅁䅕䅁䑁䅁䅷䅁䭁䅁䅁䅁䭁䙁䅍䅁䭁䅁䅕䅁䙁䅁䅁䅁杁⭕䅚允䅁䅁䅅䅁䙁䑁ね䡹⭡稳䅎䍄䉁䅁䅁兂䅁䅁䅍䅄䅁䅁䅯䅈䅁䅁䅯允䅁䅁䅯兂䅁䅁䅕䅁䅁䕁硁欵䉁䅁䅁允䅁䅁䅕椹捨㡪ㅌ䐲䴸䅉䅅䅁䕁䅁䅁睁䵁䅁䅁权偂䅁䅁权佂䅁䅁兂䅁䅁䅁倴汶䅑䅅䅁䉁䅁䅁兂䑄匹捨㡪义䅑杷允䅁䅁䅕䅁䑁䅁䅷䅁䭁䅁䅁䅁䭁䙁䅍䅁䭁䅁䅕䅁䙁䅁䅁䅁杁⭅䅚允䅁䅁䅅䅁䙁䉁奂扏䥔橬䅊䍄䉁䅁䅁兂䅁䅁䅍䅄䅁䅁䅯先䅁䅁䅯允䅁䅁䅯兂䅁䅁䅕䅁䅁䭁㡃唵䉁䅁䅁允䅁䅁䅕㘱睎児塲稰䴸䅉䅅䅁䕁䅁䅁睁䵁䅁䅁权偂䅁䅁权佂䅁䅁兂䅁䅁䅁偉汮䅑䅅䅁䉁䅁䅁兂獄払敧敨偳䅑杷允䅁䅁䅕䅁䑁䅁䅷䅁䭁䉁䅷䅁䭁䙁䅍䅁䭁䅁䅕䅁䙁䅁䅁䅁杁畡䅚允䅁䅁䅅䅁䙁䡁潎敫㠱礯䄱䍄䉁䅁䅁兂䅁䅁䅍䅄䅁䅁䅯䅁䅁䅁䅯允䅁䅁䅯兂䅁䅁䅕䅁䅁䥁䑄唵䉁䅁䅁允䅁䅁䅕児塲㍯㥁樲䴸䅉䅅䅁䙁䅁䅁睁䵁䅁䅁权䅁䅁䅁权呂䅁䅁权䙁䅁䅁兂䅁䅁䅁䱷汌䅑䅅䅁䉁䅁䅁兂㙃兓䍷祋祣䅑杷允䅁䅁䅑䅁䑁䅁䅷䅁䭁䕁䄸䅁䭁䕁䄴䅁䙁䅁䅁䅁权佌䅚允䅁䅁䅅䅁䙁䍁捬㡪ㅌ䉋䅎䍄䉁䅁䅁䅂䅁䅁䅍䅄䅁䅁䅯睔䅁䅁䅯杔䅁䅁䅕䅁䅁䅁佄唵䉁䅁䅁允䅁䅁䅕敨剴䉵䘶啂䵁䅉䅅䅁䙁䅁䅁睁䵁䅁䅁权慁䅁䅁权呂䅁䅁权䙁䅁䅁兂䅁䅁䅁乧汮䅑䅅䅁䉁䅁䅁兂扁㥌欰楂㙅䅑杷允䅁䅁䅕䅁䑁䅁䅷䅁䭁䉁䅯䅁䭁䙁䅍䅁䭁䅁䅕䅁䙁䅁䅁䅁杂⬴䅖允䅁䅁䅅䅁䙁䵁ㅐ䙋偹樴䅬䍄䉁䅁䅁䅂䅁䅁䅍䅄䅁䅁䅯睔䅁䅁䅯杔䅁䅁䅕䅁䅁䥁䅂欵䉁䅁䅁允䅁䅁䅕㑈牘払敧い䵁䅉䅅䅁䙁䅁䅁睁䵁䅁䅁权敁䅁䅁权呂䅁䅁权䙁䅁䅁兂䅁䅁䅁䑧浐䅑䅅䅁䉁䅁䅁兂䥂場啯歲浣䅑杷允䅁䅁䅑䅁䑁䅁䅷䅁䭁䕁䄸䅁䭁䕁䄴䅁䙁䅁䅁䅁䅄攷䅖允䅁䅁䅅䅁䙁䭁䠵場啯杲䄹䍄䉁䅁䅁䅂䅁䅁䅍䅄䅁䅁䅯睔䅁䅁䅯杔䅁䅁䅕䅁䅁䥁婁欵䉁䅁䅁允䅁䅁䅕䘷㑇潈牘啅䵁䅉䅅䅁䙁䅁䅁睁䵁䅁䅁权捁䅁䅁权䉁䅁䅁权䙁䅁䅁兂䅁䅁䅁䅷浈䅑䅅䅁䉁䅁䅁兂晁敨剴䉵嘷睐杷允䅁䅁䅕䅁䑁䅁䅷䅁䭁䉁䅯䅁䭁䙁䅍䅁䭁䅁䅕䅁䙁䅁䅁䅁䅁救䅚允䅁䅁䅅䅁䙁䵁杕䡳潊呍䅴䍄䉁䅁䅁兂䅁䅁䅍䅄䅁䅁䅯䅁䅁䅁䅯允䅁䅁䅯兂䅁䅁䅕䅁䅁䭁穃唵䉁䅁䅁允䅁䅁䅕灭婭婭婭吲䴸䅉䅅䅁䙁䅁䅁睁䵁䅁䅁权捁䅁䅁权䉁䅁䅁权䙁䅁䅁兂䅁䅁䅁乙汈䅑䅅䅁䉁䅁䅁兂穁積積積呐睐杷允䅁䅁䅕䅁䑁䅁䅷䅁䭁䅁䅁䅁䭁䙁䅍䅁䭁䅁䅕䅁䙁䅁䅁䅁䅄佡䅚允䅁䅁䅅䅁䙁䙁橔婰䕶䐴䅎䍄䉁䅁䅁兂䅁䅁䅍䅄䅁䅁䅯䅈䅁䅁䅯睕䅁䅁䅯兂䅁䅁䅕䅁䅁䕁䅁欵䉁䅁䅁允䅁䅁䅕椹捨㡪ㅊ啌䵁䅉䅅䅁䙁䅁䅁睁䵁䅁䅁权摁䅁䅁权䉁䅁䅁权䙁䅁䅁兂䅁䅁䅁佯汦䅑䅅䅁䉁䅁䅁兂塄㍯㥁瑃呦睐杷允䅁䅁䅑䅁䑁䅁䅷䅁䭁䕁䄸䅁䭁䕁䄴䅁䙁䅁䅁䅁䅃⭹䅖允䅁䅁䅅䅁䙁䉁䘫ㄶ㑇杈䅆䍄䉁䅁䅁䅂䅁䅁䅍䅄䅁䅁䅯睔䅁䅁䅯杔䅁䅁䅕䅁䅁䵁䥂欵䉁䅁䅁允䅁䅁䅕㡪ㅌ䙋偹䕅䵁䅉䅅䅁䙁䅁䅁睁䵁䅁䅁权摁䅁䅁权䉁䅁䅁权䙁䅁䅁兂䅁䅁䅁䙙浈䅑䅅䅁䉁䅁䅁兂畃⭒㙆䭆堷睐杷允䅁䅁䅕䅁䑁䅁䅷䅁䭁䅁䅁䅁䭁䙁䅍䅁䭁䅁䅕䅁䙁䅁䅁䅁䅂伸䅖允䅁䅁䅅䅁䙁䑁積積積穫䅊䍄䉁䅁䅁兂䅁䅁䅍䅄䅁䅁䅯䅁䅁䅁䅯睕䅁䅁䅯兂䅁䅁䅕䅁䅁䕁扁欵䉁䅁䅁允䅁䅁䅕硢䑋䵷䉯き䵁䅉䅅䅁䕁䅁䅁睁䵁䅁䅁权偂䅁䅁权佂䅁䅁兂䅁䅁䅁佉汪䅑䅅䅁䉁䅁䅁兂乄䵺䵺䵺剷䅑杷允䅁䅁䅕䅁䑁䅁䅷䅁䭁䉁䅷䅁䭁䅁䅅䅁䭁䅁䅕䅁䙁䅁䅁䅁䅂畄䅚允䅁䅁䅅䅁䙁䉁䘫ㄶ㑇瑈⽕䍄䉁䅁䅁兂䅁䅁䅍䅄䅁䅁䅯䅁䅁䅁䅯睕䅁䅁䅯兂䅁䅁䅕䅁䅁䅁晄唵䉁䅁䅁允䅁䅁䅕兇坒楄匳歍䵁䅉䅅䅁䙁䅁䅁睁䵁䅁䅁权慁䅁䅁权䉁䅁䅁权䙁䅁䅁兂䅁䅁䅁䡷浄䅑䅅䅁䉁䅁䅁兂歃䑣䬰㘱潐睐杷允䅁䅁䅕䅁䑁䅁䅷䅁䭁䉁䅷䅁䭁䙁䅍䅁䭁䅁䅕䅁䙁䅁䅁䅁䅄⬫䅖允䅁䅁䅅䅁䙁䙁㘶兓䍷祡䄱䍄䉁䅁䅁兂䅁䅁䅍䅄䅁䅁䅯杈䅁䅁䅯睕䅁䅁䅯兂䅁䅁䅕䅁䅁䕁㝂欵䉁䅁䅁允䅁䅁䅕噋偹癷潖啉䵁䅉䅅䅁䕁䅁䅁睁䵁䅁䅁权偂䅁䅁权佂䅁䅁兂䅁䅁䅁偉汌䅑䅅䅁䉁䅁䅁兂啁歲桦桥佑䅑杷允䅁䅁䅕䅁䑁䅁䅷䅁䭁䉁䅯䅁䭁䙁䅍䅁䭁䅁䅕䅁䙁䅁䅁䅁䅄伯䅖允䅁䅁䅅䅁䙁䥁䌯匹捨稷䅬䍄䉁䅁䅁兂䅁䅁䅍䅄䅁䅁䅯睈䅁䅁䅯睕䅁䅁䅯兂䅁䅁䅕䅁䅁䍁㕃唵䉁䅁䅁允䅁䅁䅕䉵䘶ㄶ奈䕍䵁䅉䅅䅁䕁䅁䅁睁䵁䅁䅁权偂䅁䅁权佂䅁䅁兂䅁䅁䅁䅉浘䅑䅅䅁䉁䅁䅁兂灁䥘䌯匹剧䅑杷允䅁䅁䅕䅁䑁䅁䅷䅁䭁䉁䅷䅁䭁䙁䅍䅁䭁䅁䅕䅁䙁䅁䅁䅁杁伱䅖允䅁䅁䅅䅁䙁䕁椵䙅㕧䍴䄵䍄䉁䅁䅁兂䅁䅁䅍䅄䅁䅁䅯䅁䅁䅁䅯允䅁䅁䅯兂䅁䅁䅕䅁䅁䵁⽄唵䉁䅁䅁允䅁䅁䅕䉵䘶ㄶ㑇樳䴸䅉䅅䅁䙁䅁䅁睁䵁䅁䅁权䅁䅁䅁权呂䅁䅁权䙁䅁䅁兂䅁䅁䅁䅷浲䅑䅅䅁䉁䅁䅁兂允䑗ね䩹祙䅑杷允䅁䅁䅕䅁䑁䅁䅷䅁䭁䉁䅯䅁䭁䙁䅍䅁䭁䅁䅕䅁䙁䅁䅁䅁䅄⭐䅚允䅁䅁䅅䅁䙁䵁杕䡳潊呍䅴䍄䉁䅁䅁兂䅁䅁䅍䅄䅁䅁䅯先䅁䅁䅯睕䅁䅁䅯兂䅁䅁䅕䅁䅁䵁摃唵䉁䅁䅁允䅁䅁䅕牒穢搯㑒啌䵁䅉䅅䅁䙁䅁䅁睁䵁䅁䅁权䅁䅁䅁权呂䅁䅁权䙁䅁䅁兂䅁䅁䅁䡁浢䅑䅅䅁䉁䅁䅁兂啂㘴扗䅸ぁ䅑杷允䅁䅁䅕䅁䑁䅁䅷䅁䭁䉁䅷䅁䭁䙁䅍䅁䭁䅁䅕䅁䙁䅁䅁䅁䅄畏䅚允䅁䅁䅅䅁䙁䉁婦発呤祯䄵䍄䉁䅁䅁䅂䅁䅁䅍䅄䅁䅁䅯睔䅁䅁䅯杔䅁䅁䅕䅁䅁䵁䡄唵䉁䅁䅁允䅁䅁䅕捺䵺䵺䵺䐯䴸䅉䅅䅁䙁䅁䅁睁䵁䅁䅁权敁䅁䅁权䉁䅁䅁权䙁䅁䅁兂䅁䅁䅁佁汲䅑䅅䅁䉁䅁䅁兂穁積積積呐睐杷允䅁䅁䅕䅁䑁䅁䅷䅁䭁䉁䄸䅁䭁䙁䅍䅁䭁䅁䅕䅁䙁䅁䅁䅁杂佺䅖允䅁䅁䅅䅁䙁䕁䵯楁䡵樱䅂䍄䉁䅁䅁䅂䅁䅁䅍䅄䅁䅁䅯睔䅁䅁䅯杔䅁䅁䅕䅁䅁䕁䡁欵䉁䅁䅁允䅁䅁䅕㡪ㅌ䙋偹歅䵁䅉䅅䅁䕁䅁䅁睁䵁䅁䅁权偂䅁䅁权佂䅁䅁兂䅁䅁䅁䙁浐䅑䅅䅁䉁䅁䅁兂䙃ㄶ㑇潈偕䅑杷允䅁䅁䅕䅁䑁䅁䅷䅁䭁䉁䅷䅁䭁䙁䅍䅁䭁䅁䅕䅁䙁䅁䅁䅁䅁畎䅚允䅁䅁䅅䅁䙁䙁㕧䵴㉨楐䄵䍄䉁䅁䅁兂䅁䅁䅍䅄䅁䅁䅯杈䅁䅁䅯允䅁䅁䅯兂䅁䅁䅕䅁䅁䭁奄唵䉁䅁䅁允䅁䅁䅕積積積積稰䴸䅉䅅䅁䙁䅁䅁睁䵁䅁䅁权捁䅁䅁权呂䅁䅁权䙁䅁䅁兂䅁䅁䅁䔴洯䅑䅅䅁䉁䅁䅁兂摄䅊䉡啬畍䅑杷允䅁䅁䅑䅁䑁䅁䅷䅁䭁䕁䄸䅁䭁䕁䄴䅁䙁䅁䅁䅁杂⭎䅚允䅁䅁䅅䅁䙁䵁䴳䵺䵺䉺䅂䍄䉁䅁䅁兂䅁䅁䅍䅄䅁䅁䅯杇䅁䅁䅯睕䅁䅁䅯兂䅁䅁䅕䅁䅁䍁扂欵䉁䅁䅁允䅁䅁䅕灶愸㥌欱く䵁䅉䅅䅁䙁䅁䅁睁䵁䅁䅁权捁䅁䅁权䉁䅁䅁权䙁䅁䅁兂䅁䅁䅁乧氯䅑䅅䅁䉁䅁䅁兂穁積積積呐睐杷允䅁䅁䅕䅁䑁䅁䅷䅁䭁䉁䄴䅁䭁䙁䅍䅁䭁䅁䅕䅁䙁䅁䅁䅁䅂敐䅚允䅁䅁䅅䅁䙁偁㥔䠱灪楚䅒䍄䉁䅁䅁兂䅁䅁䅍䅄䅁䅁䅯睈䅁䅁䅯允䅁䅁䅯兂䅁䅁䅕䅁䅁䕁灃唵䉁䅁䅁允䅁䅁䅯睇䅁䅁杷允䅁䅁䅕䅁䑁䅁䅷䅁䭁䅁䅁䅁䭁䙁䅍䅁䭁䅁䅕䅁䙁䅁䅁䅁䅄敄䅚允䅁䅁䅅䅁䙁䉁奂扏䥔橬䅊䍄䉁䅁䅁兂䅁䅁䅍䅄䅁䅁䅯先䅁䅁䅯睕䅁䅁䅯兂䅁䅁䅕䅁䅁䥁穄唵䉁䅁䅁允䅁䅁䅕灰䕶䱉祃啌䵁䅉䅅䅁䕁䅁䅁睁䵁䅁䅁权偂䅁䅁权佂䅁䅁兂䅁䅁䅁䔴浢䅑䅅䅁䉁䅁䅁兂畃⭒㙆䭆儴䅑杷允䅁䅁䅕䅁䑁䅁䅷䅁䭁䅁䅁䅁䭁䙁䅍䅁䭁䅁䅕䅁䙁䅁䅁䅁䅁由䅖允䅁䅁䅅䅁䙁䭁慁㥌欰橂䅎䍄䉁䅁䅁兂䅁䅁䅍䅄䅁䅁䅯䅈䅁䅁䅯睕䅁䅁䅯兂䅁䅁䅕䅁䅁䭁佂欵䉁䅁䅁允䅁䅁䅕硢䑋䵷桰歌䵁䅉䅅䅁䙁䅁䅁睁䵁䅁䅁权䅁䅁䅁权䉁䅁䅁权䙁䅁䅁兂䅁䅁䅁乙汲䅑䅅䅁䉁䅁䅁兂桄桥畓⭒慈睐杷允䅁䅁䅕䅁䑁䅁䅷䅁䭁䉁䄰䅁䭁䅁䅅䅁䭁䅁䅕䅁䙁䅁䅁䅁杄畋䅚允䅁䅁䅅䅁䙁䝁浚浚浚瑚⽙䍄䉁䅁䅁兂䅁䅁䅍䅄䅁䅁䅯睈䅁䅁䅯睕䅁䅁䅯兂䅁䅁䅕䅁䅁䍁潂欵䉁䅁䅁允䅁䅁䅕瑃橥䑣焰啍䵁䅉䅅䅁䙁䅁䅁睁䵁䅁䅁权䅁䅁䅁权呂䅁䅁权䙁䅁䅁兂䅁䅁䅁䅷洷䅑䅅䅁䉁䅁䅁兂允䑗ね䩹祙䅑杷允䅁䅁䅑䅁䑁䅁䅷䅁䭁䕁䄸䅁䭁䕁䄴䅁䙁䅁䅁䅁䅄⬱䅖允䅁䅁䅅䅁䙁䩁婱婭婭六䅬䍄䉁䅁䅁兂䅁䅁䅍䅄䅁䅁䅯䅁䅁䅁䅯睕䅁䅁䅯兂䅁䅁䅕䅁䅁䭁⭂欵䉁䅁䅁允䅁䅁䅕琯㑒匶硢き䵁䅉䅅䅁䕁䅁䅁睁䵁䅁䅁权偂䅁䅁权佂䅁䅁兂䅁䅁䅁佁汐䅑䅅䅁䉁䅁䅁兂䙃ㄶ㑇潈偕䅑杷允䅁䅁䅑䅁䑁䅁䅷䅁䭁䕁䄸䅁䭁䕁䄴䅁䙁䅁䅁䅁䅄故䅚允䅁䅁䅅䅁䙁䑁積積積硍䅎䍄䉁䅁䅁䅂䅁䅁䅍䅄䅁䅁䅯睔䅁䅁䅯杔䅁䅁䅕䅁䅁䕁卂欵䉁䅁䅁允䅁䅁䅕噋偹癷潕䕅䵁䅉䅅䅁䙁䅁䅁睁䵁䅁䅁权䅁䅁䅁权呂䅁䅁权䙁䅁䅁兂䅁䅁䅁䝯浌䅑䅅䅁䉁䅁䅁兂煃搸乊瑙穁䅑杷允䅁䅁䅕䅁䑁䅁䅷䅁䭁䉁䄴䅁䭁䙁䅍䅁䭁䅁䅕䅁䙁䅁䅁䅁杂佋䅚允䅁䅁䅅䅁䙁䡁呗䅇坒楺䅤䍄䉁䅁䅁兂䅁䅁䅍䅄䅁䅁䅯䅈䅁䅁䅯睕䅁䅁䅯兂䅁䅁䅕䅁䅁䝁煃唵䉁䅁䅁允䅁䅁䅕椹捨㡪ㅋ啌䵁䅉䅅䅁䙁䅁䅁睁䵁䅁䅁权晁䅁䅁权呂䅁䅁权䙁䅁䅁兂䅁䅁䅁䌴浌䅑䅅䅁䉁䅁䅁兂䝂癴㥐倱睧䅑杷允䅁䅁䅑䅁䑁䅁䅷䅁䭁䕁䄸䅁䭁䕁䄴䅁䙁䅁䅁䅁䅃敕䅚允䅁䅁䅅䅁䙁䉁畓⭒㙆䉆䅆䍄䉁䅁䅁兂䅁䅁䅍䅄䅁䅁䅯䅈䅁䅁䅯允䅁䅁䅯兂䅁䅁䅕䅁䅁䕁䝄唵䉁䅁䅁允䅁䅁䅕㡪ㅌ䙋偹樰䴸䅉䅅䅁䙁䅁䅁睁䵁䅁䅁权摁䅁䅁权䉁䅁䅁权䙁䅁䅁兂䅁䅁䅁䝁浮䅑䅅䅁䉁䅁䅁兂畃⭒㙆䭆堷睐杷允䅁䅁䅑䅁䑁䅁䅷䅁䭁䕁䄸䅁䭁䕁䄴䅁䙁䅁䅁䅁杂敬䅖允䅁䅁䅅䅁䙁䍁捬㡪ㅌ䵋⽷䍄䉁䅁䅁兂䅁䅁䅍䅄䅁䅁䅯䅁䅁䅁䅯允䅁䅁䅯兂䅁䅁䅕䅁䅁䥁偂欵䉁䅁䅁允䅁䅁䅕䉵䘶ㄶ㑇樳䴸䅉䅅䅁䙁䅁䅁睁䵁䅁䅁权䅁䅁䅁权呂䅁䅁权䙁䅁䅁兂䅁䅁䅁䕧浲䅑䅅䅁䉁䅁䅁兂十㡧䭄捯穕䅑杷允䅁䅁䅑䅁䑁䅁䅷䅁䭁䕁䄸䅁䭁䕁䄴䅁䙁䅁䅁䅁杂畯䅖允䅁䅁䅅䅁䙁䡁啳歲桦瑥⽑䍄䉁䅁䅁䅂䅁䅁䅍䅄䅁䅁䅯睔䅁䅁䅯杔䅁䅁䅕䅁䅁䅁㝄唵䉁䅁䅁允䅁䅁䅕硥畓⭒㙆歄䵁䅉䅅䅁䙁䅁䅁睁䵁䅁䅁权敁䅁䅁权䉁䅁䅁权䙁䅁䅁兂䅁䅁䅁䱷汌䅑䅅䅁䉁䅁䅁兂穁積積積呐睐杷允䅁䅁䅕䅁䑁䅁䅷䅁䭁䅁䅁䅁䭁䙁䅍䅁䭁䅁䅕䅁䙁䅁䅁䅁杁⭇䅚允䅁䅁䅅䅁䙁䝁匸㡧䭄呁䅎䍄䉁䅁䅁兂䅁䅁䅍䅄䅁䅁䅯䅈䅁䅁䅯允䅁䅁䅯兂䅁䅁䅕䅁䅁䭁㉄唵䉁䅁䅁允䅁䅁䅕㑈牘払敧吱䴸䅉䅅䅁䙁䅁䅁睁䵁䅁䅁权敁䅁䅁权呂䅁䅁权䙁䅁䅁兂䅁䅁䅁䩯汦䅑䅅䅁䉁䅁䅁兂䝁婧䑖㉩灷䅑杷允䅁䅁䅑䅁䑁䅁䅷䅁䭁䕁䄸䅁䭁䕁䄴䅁䙁䅁䅁䅁䅂敕䅚允䅁䅁䅅䅁䙁䙁㑋潈牘剕䅆䍄䉁䅁䅁兂䅁䅁䅍䅄䅁䅁䅯杈䅁䅁䅯睕䅁䅁䅯兂䅁䅁䅕䅁䅁䍁捄唵䉁䅁䅁允䅁䅁䅕兊䉡啬䱏䕌䵁䅉䅅䅁䕁䅁䅁睁䵁䅁䅁权偂䅁䅁权佂䅁䅁兂䅁䅁䅁䵁汈䅑䅅䅁䉁䅁䅁兂㑃潈牘払番睐杷允䅁䅁䅑䅁䑁䅁䅷䅁䭁䕁䄸䅁䭁䕁䄴䅁䙁䅁䅁䅁䅂⭸䅖允䅁䅁䅅䅁䙁䉁䘫ㄶ㑇癈⼰䍄䉁䅁䅁䅂䅁䅁䅍䅄䅁䅁䅯睔䅁䅁䅯杔䅁䅁䅕䅁䅁䭁兂欵䉁䅁䅁允䅁䅁䅕児塲㍯㥁啅䵁䅉䅅䅁䙁䅁䅁睁䵁䅁䅁权䅁䅁䅁权䉁䅁䅁权䙁䅁䅁兂䅁䅁䅁乧汪䅑䅅䅁䉁䅁䅁兂桄桥畓⭒慈睐杷允䅁䅁䅑䅁䑁䅁䅷䅁䭁䕁䄸䅁䭁䕁䄴䅁䙁䅁䅁䅁䅄畄䅚允䅁䅁䅅䅁䙁䩁婱婭婭剭䅊䍄䉁䅁䅁兂䅁䅁䅍䅄䅁䅁䅯杇䅁䅁䅯睕䅁䅁䅯兂䅁䅁䅕䅁䅁䍁牄唵䉁䅁䅁允䅁䅁䅕⽷潕䥘䌯問䵁䅉䅅䅁䙁䅁䅁睁䵁䅁䅁权䅁䅁䅁权呂䅁䅁权䙁䅁䅁兂䅁䅁䅁䩉汢䅑䅅䅁䉁䅁䅁兂㡃䩤奍䡂睙䅑杷允䅁䅁䅕䅁䑁䅁䅷䅁䭁䉁䄴䅁䭁䙁䅍䅁䭁䅁䅕䅁䙁䅁䅁䅁䅃⭘䅚允䅁䅁䅅䅁䙁䩁瑈䑦ㄸ楘䅊䍄䉁䅁䅁兂䅁䅁䅍䅄䅁䅁䅯杈䅁䅁䅯睕䅁䅁䅯兂䅁䅁䅕䅁䅁䭁偂欵䉁䅁䅁允䅁䅁䅕渷⽷噎㘴䕊䵁䅉䅅䅁䕁䅁䅁睁䵁䅁䅁权偂䅁䅁权佂䅁䅁兂䅁䅁䅁䙧浄䅑䅅䅁䉁䅁䅁兂㝂䭆䠵場副䅑杷允䅁䅁䅑䅁䑁䅁䅷䅁䭁䕁䄸䅁䭁䕁䄴䅁䙁䅁䅁䅁权佉䅚允䅁䅁䅅䅁䙁䩁婱婭婭剭䅂䍄䉁䅁䅁兂䅁䅁䅍䅄䅁䅁䅯䅁䅁䅁䅯睕䅁䅁䅯兂䅁䅁䅕䅁䅁䅁い唵䉁䅁䅁允䅁䅁䅕積積積呏歍䵁䅉䅅䅁䙁䅁䅁睁䵁䅁䅁权䅁䅁䅁权呂䅁䅁权䙁䅁䅁兂䅁䅁䅁䙙洷䅑䅅䅁䉁䅁䅁兂煃搸乊瑙穁䅑杷允䅁䅁䅕䅁䑁䅁䅷䅁䭁䉁䅷䅁䭁䅁䅅䅁䭁䅁䅕䅁䙁䅁䅁䅁杄⭳䅖允䅁䅁䅅䅁䙁䥁䌯匹捨㥪⽉䍄䉁䅁䅁䅂䅁䅁䅍䅄䅁䅁䅯睔䅁䅁䅯杔䅁䅁䅕䅁䅁䥁㥁欵䉁䅁䅁允䅁䅁䅕䥘䌯匹捨ぃ䵁䅉䅅䅁䕁䅁䅁睁䵁䅁䅁权偂䅁䅁权佂䅁䅁兂䅁䅁䅁䕙浔䅑䅅䅁䉁䅁䅁兂䙃ㄶ㑇潈兕䅑杷允䅁䅁䅕䅁䑁䅁䅷䅁䭁䉁䅯䅁䭁䅁䅅䅁䭁䅁䅕䅁䙁䅁䅁䅁杁收䅖允䅁䅁䅅䅁䙁偁潙䥘䌯改⽁䍄䉁䅁䅁䅂䅁䅁䅍䅄䅁䅁䅯睔䅁䅁䅯杔䅁䅁䅕䅁䅁䍁㑄唵䉁䅁䅁允䅁䅁䅕㘱睎児塲歅䵁䅉䅅䅁䙁䅁䅁睁䵁䅁䅁权䅁䅁䅁权呂䅁䅁权䙁䅁䅁兂䅁䅁䅁䝁洷䅑䅅䅁䉁䅁䅁兂啂㘴扗佸穁䅑杷允䅁䅁䅕䅁䑁䅁䅷䅁䭁䉁䅷䅁䭁䙁䅍䅁䭁䅁䅕䅁䙁䅁䅁䅁䅁畍䅚允䅁䅁䅅䅁䙁䙁㕧䵴㉨楐䄵䍄䉁䅁䅁兂䅁䅁䅍䅄䅁䅁䅯杈䅁䅁䅯睕䅁䅁䅯兂䅁䅁䅕䅁䅁佁捂欵䉁䅁䅁允䅁䅁䅕敫㠱穐敖歉䵁䅉䅅䅁䕁䅁䅁睁䵁䅁䅁权偂䅁䅁权佂䅁䅁兂䅁䅁䅁䕉浄䅑䅅䅁䉁䅁䅁兂㑃潈牘払佧䅑杷允䅁䅁䅕䅁䑁䅁䅷䅁䭁䉁䄴䅁䭁䙁䅍䅁䭁䅁䅕䅁䙁䅁䅁䅁䅄⭦䅚允䅁䅁䅅䅁䙁䍁捬㡪ㅌ䍡䅆䍄䉁䅁䅁䅂䅁䅁䅍䅄䅁䅁䅯睔䅁䅁䅯杔䅁䅁䅕䅁䅁䥁捃唵䉁䅁䅁允䅁䅁䅕硥畓⭒㙆䐱䴸䅉䅅䅁䙁䅁䅁睁䵁䅁䅁权摁䅁䅁权呂䅁䅁权䙁䅁䅁兂䅁䅁䅁䘴浲䅑䅅䅁䉁䅁䅁兂䑄匹捨㑪畉䅑杷允䅁䅁䅑䅁䑁䅁䅷䅁䭁䕁䄸䅁䭁䕁䄴䅁䙁䅁䅁䅁䅁佴䅖允䅁䅁䅅䅁䙁䥁牘払敧摨⽳䍄䉁䅁䅁䅂䅁䅁䅍䅄䅁䅁䅯睔䅁䅁䅯杔䅁䅁䅕䅁䅁䝁癄唵䉁䅁䅁允䅁䅁䅕䉵䘶ㄶ㑇䕅䵁䅉䅅䅁䙁䅁䅁睁䵁䅁䅁权捁䅁䅁权呂䅁䅁权䙁䅁䅁兂䅁䅁䅁䥙浄䅑䅅䅁䉁䅁䅁兂䩄牤昶煇琸䅑杷允䅁䅁䅑䅁䑁䅁䅷䅁䭁䕁䄸䅁䭁䕁䄴䅁䙁䅁䅁䅁杄⭔䅚允䅁䅁䅅䅁䙁䑁䬰㘱睎剐䅆䍄䉁䅁䅁䅂䅁䅁䅍䅄䅁䅁䅯睔䅁䅁䅯杔䅁䅁䅕䅁䅁䅁祃唵䉁䅁䅁允䅁䅁䅕噋偹癷潕䐳䴸䅉䅅䅁䙁䅁䅁睁䵁䅁䅁权䅁䅁䅁权呂䅁䅁权䙁䅁䅁兂䅁䅁䅁䑷浈䅑䅅䅁䉁䅁䅁兂瑁灳瘳㑰穙䅑杷允䅁䅁䅕䅁䑁䅁䅷䅁䭁䅁䅁䅁䭁䅁䅅䅁䭁䅁䅕䅁䙁䅁䅁䅁杂畈䅚允䅁䅁䅅䅁䙁䱁敧敨剴乵⼴䍄䉁䅁䅁䅂䅁䅁䅍䅄䅁䅁䅯睔䅁䅁䅯杔䅁䅁䅕䅁䅁䥁畁欵䉁䅁䅁允䅁䅁䅕牕敧敨剴歅䵁䅉䅅䅁䙁䅁䅁睁䵁䅁䅁权晁䅁䅁权䉁䅁䅁权䙁䅁䅁兂䅁䅁䅁䵧汘䅑䅅䅁䉁䅁䅁兂㑃潈牘払敪睐杷允䅁䅁䅕䅁䑁䅁䅷䅁䭁䉁䄸䅁䭁䅁䅅䅁䭁䅁䅕䅁䙁䅁䅁䅁杂敌䅚允䅁䅁䅅䅁䙁䕁桪桥畓⭒⽅䍄䉁䅁䅁兂䅁䅁䅍䅄䅁䅁䅯䅈䅁䅁䅯睕䅁䅁䅯兂䅁䅁䅕䅁䅁佁剄唵䉁䅁䅁允䅁䅁䅕敨剴䉵䘶歌䵁䅉䅅䅁䕁䅁䅁睁䵁䅁䅁权偂䅁䅁权佂䅁䅁兂䅁䅁䅁佧汦䅑䅅䅁䉁䅁䅁兂歃䑣䬰㘱前䅑杷允䅁䅁䅕䅁䑁䅁䅷䅁䭁䉁䄰䅁䭁䅁䅅䅁䭁䅁䅕䅁䙁䅁䅁䅁杂⭱䅖允䅁䅁䅅䅁䙁乁橥䑣䬰㤱⽍䍄䉁䅁䅁䅂䅁䅁䅍䅄䅁䅁䅯睔䅁䅁䅯杔䅁䅁䅕䅁䅁䥁偂欵䉁䅁䅁允䅁䅁䅕䅁䅁䅁䅁啅䵁䅉䅅䅁䙁䅁䅁睁䵁䅁䅁权䅁䅁䅁权䉁䅁䅁权䙁䅁䅁兂䅁䅁䅁偯汔䅑䅅䅁䉁䅁䅁兂㑃潈牘払敪睐杷允䅁䅁䅕䅁䑁䅁䅷䅁䭁䉁䅷䅁䭁䅁䅅䅁䭁䅁䅕䅁䙁䅁䅁䅁杂救䅚允䅁䅁䅅䅁䙁偁潙䥘䌯搹⽧䍄䉁䅁䅁䅂䅁䅁䅍䅄䅁䅁䅯睔䅁䅁䅯杔䅁䅁䅕䅁䅁䥁剁欵䉁䅁䅁允䅁䅁䅕㡪ㅌ䙋偹ぅ䵁䅉䅅䅁䕁䅁䅁睁䵁䅁䅁权偂䅁䅁权佂䅁䅁兂䅁䅁䅁䅑浲䅑䅅䅁䉁䅁䅁兂䭁㘱睎児卯䅑杷允䅁䅁䅕䅁䑁䅁䅷䅁䭁䅁䅁䅁䭁䅁䅅䅁䭁䅁䅕䅁䙁䅁䅁䅁䅁⭱䅖允䅁䅁䅅䅁䙁䩁婱婭婭摭⽫䍄䉁䅁䅁䅂䅁䅁䅍䅄䅁䅁䅯睔䅁䅁䅯杔䅁䅁䅕䅁䅁䝁偂欵䉁䅁䅁允䅁䅁䅕㑈牘払敧啅䵁䅉䅅䅁䙁䅁䅁睁䵁䅁䅁权䅁䅁䅁权䉁䅁䅁权䙁䅁䅁兂䅁䅁䅁义決䅑䅅䅁䉁䅁䅁兂桄桥畓⭒慈睐杷允䅁䅁䅕䅁䑁䅁䅷䅁䭁䅁䅁䅁䭁䙁䅍䅁䭁䅁䅕䅁䙁䅁䅁䅁权伴䅖允䅁䅁䅅䅁䙁䉁䕫杖琴樰䅊䍄䉁䅁䅁兂䅁䅁䅍䅄䅁䅁䅯先䅁䅁䅯睕䅁䅁䅯兂䅁䅁䅕䅁䅁䭁䩁欵䉁䅁䅁允䅁䅁䅕䝭匴㡧䭂歌䵁䅉䅅䅁䕁䅁䅁睁䵁䅁䅁权偂䅁䅁权佂䅁䅁兂䅁䅁䅁䕁洯䅑䅅䅁䉁䅁䅁兂啁歲桦桥剑䅑杷允䅁䅁䅕䅁䑁䅁䅷䅁䭁䅁䅁䅁䭁䅁䅅䅁䭁䅁䅕䅁䙁䅁䅁䅁䅄⭳䅖允䅁䅁䅅䅁䙁䩁婱婭婭摭⽫䍄䉁䅁䅁䅂䅁䅁䅍䅄䅁䅁䅯睔䅁䅁䅯杔䅁䅁䅕䅁䅁䝁睃唵䉁䅁䅁允䅁䅁䅕捺䵺䵺䵺䐳䴸䅉䅅䅁䙁䅁䅁睁䵁䅁䅁权捁䅁䅁权䉁䅁䅁权䙁䅁䅁兂䅁䅁䅁䕙浲䅑䅅䅁䉁䅁䅁兂㉄䙋偹癷奘睐杷允䅁䅁䅕䅁䑁䅁䅷䅁䭁䉁䄴䅁䭁䙁䅍䅁䭁䅁䅕䅁䙁䅁䅁䅁杁伫䅖允䅁䅁䅅䅁䙁䱁䥔牤昶椲䅬䍄䉁䅁䅁䅂䅁䅁䅍䅄䅁䅁䅯睔䅁䅁䅯杔䅁䅁䅕䅁䅁䥁塄唵䉁䅁䅁允䅁䅁䅕捺䵺䵺䵺歃䵁䅉䅅䅁䙁䅁䅁睁䵁䅁䅁权摁䅁䅁权呂䅁䅁权䙁䅁䅁兂䅁䅁䅁䜴浦䅑䅅䅁䉁䅁䅁兂㍁啩杆刵畁䅑杷允䅁䅁䅕䅁䑁䅁䅷䅁䭁䅁䅁䅁䭁䙁䅍䅁䭁䅁䅕䅁䙁䅁䅁䅁权佊䅚允䅁䅁䅅䅁䙁佁兘瑉㕶橐䅎䍄䉁䅁䅁兂䅁䅁䅍䅄䅁䅁䅯先䅁䅁䅯睕䅁䅁䅯兂䅁䅁䅕䅁䅁䕁煁欵䉁䅁䅁允䅁䅁䅕浚浚浚浢歌䵁䅉䅅䅁䙁䅁䅁睁䵁䅁䅁权摁䅁䅁权呂䅁䅁权䙁䅁䅁兂䅁䅁䅁䴴汢䅑䅅䅁䉁䅁䅁兂䵂㑎䉬余瑕䅑杷允䅁䅁䅑䅁䑁䅁䅷䅁䭁䕁䄸䅁䭁䕁䄴䅁䙁䅁䅁䅁杄敹䅖允䅁䅁䅅䅁䙁䅁塲㍯㥁癃⽳䍄䉁䅁䅁䅂䅁䅁䅍䅄䅁䅁䅯睔䅁䅁䅯杔䅁䅁䅕䅁䅁䥁瑁欵䉁䅁䅁允䅁䅁䅕敨剴䉵䘶歅䵁䅉䅅䅁䙁䅁䅁睁䵁䅁䅁权慁䅁䅁权呂䅁䅁权䙁䅁䅁兂䅁䅁䅁䍙洯䅑䅅䅁䉁䅁䅁兂晁敨剴乵㘴䅑杷允䅁䅁䅕䅁䑁䅁䅷䅁䭁䉁䄴䅁䭁䅁䅅䅁䭁䅁䅕䅁䙁䅁䅁䅁䅄攰䅖允䅁䅁䅅䅁䙁䑁積積積㥍⽍䍄䉁䅁䅁兂䅁䅁䅍䅄䅁䅁䅯杇䅁䅁䅯睕䅁䅁䅯兂䅁䅁䅕䅁䅁䭁楂欵䉁䅁䅁允䅁䅁䅕灶愸㥌欱く䵁䅉䅅䅁䙁䅁䅁睁䵁䅁䅁权敁䅁䅁权呂䅁䅁权䙁䅁䅁兂䅁䅁䅁䝯浔䅑䅅䅁䉁䅁䅁兂剃堷⽷噎椴䅑杷允䅁䅁䅑䅁䑁䅁䅷䅁䭁䕁䄸䅁䭁䕁䄴䅁䙁䅁䅁䅁杁畓䅚允䅁䅁䅅䅁䙁䡁㥅瑃橥䉣䅆䍄䉁䅁䅁兂䅁䅁䅍䅄䅁䅁䅯䅈䅁䅁䅯睕䅁䅁䅯兂䅁䅁䅕䅁䅁䥁䵄唵䉁䅁䅁允䅁䅁䅕敨剴䉵䘶歌䵁䅉䅅䅁䙁䅁䅁睁䵁䅁䅁权䅁䅁䅁权呂䅁䅁权䙁䅁䅁兂䅁䅁䅁䙉浪䅑䅅䅁䉁䅁䅁兂㕁䵴㉨瑶稸䅑杷允䅁䅁䅕䅁䑁䅁䅷䅁䭁䅁䅁䅁䭁䙁䅍䅁䭁䅁䅕䅁䙁䅁䅁䅁杂佉䅚允䅁䅁䅅䅁䙁䝁匸㡧䭄呁䅎䍄䉁䅁䅁兂䅁䅁䅍䅄䅁䅁䅯先䅁䅁䅯允䅁䅁䅯兂䅁䅁䅕䅁䅁佁㕂欵䉁䅁䅁允䅁䅁䅕歲桦桥畓稱䴸䅉䅅䅁䙁䅁䅁睁䵁䅁䅁权䅁䅁䅁权呂䅁䅁权䙁䅁䅁兂䅁䅁䅁䭑汈䅑䅅䅁䉁䅁䅁兂塄㍯㥁癃督䅑杷允䅁䅁䅕䅁䑁䅁䅷䅁䭁䅁䅁䅁䭁䙁䅍䅁䭁䅁䅕䅁䙁䅁䅁䅁䅁⭯䅖允䅁䅁䅅䅁䙁乁橥䑣䬰稹䅂䍄䉁䅁䅁䅂䅁䅁䅍䅄䅁䅁䅯睔䅁䅁䅯杔䅁䅁䅕䅁䅁䥁㉁欵䉁䅁䅁允䅁䅁䅕㑈牘払敧啅䵁䅉䅅䅁䙁䅁䅁睁䵁䅁䅁权慁䅁䅁权呂䅁䅁权䙁䅁䅁兂䅁䅁䅁䠴浌䅑䅅䅁䉁䅁䅁兂䵂㑎䉬䍙㝕䅑杷允䅁䅁䅕䅁䑁䅁䅷䅁䭁䉁䄰䅁䭁䅁䅅䅁䭁䅁䅕䅁䙁䅁䅁䅁杁敷䅖允䅁䅁䅅䅁䙁乁橥䑣䬰㤱⽍䍄䉁䅁䅁䅂䅁䅁䅍䅄䅁䅁䅯睔䅁䅁䅯杔䅁䅁䅕䅁䅁䥁㙁欵䉁䅁䅁允䅁䅁䅕浚浚浚浚歄䵁䅉䅅䅁䙁䅁䅁睁䵁䅁䅁权慁䅁䅁权呂䅁䅁权䙁䅁䅁兂䅁䅁䅁䅯浔䅑䅅䅁䉁䅁䅁兂䝂癴㥐䈱㙧䅑杷允䅁䅁䅕䅁䑁䅁䅷䅁䭁䉁䅷䅁䭁䅁䅅䅁䭁䅁䅕䅁䙁䅁䅁䅁䅄敦䅚允䅁䅁䅅䅁䙁偁潙䥘䌯搹⽧䍄䉁䅁䅁䅂䅁䅁䅍䅄䅁䅁䅯睔䅁䅁䅯杔䅁䅁䅕䅁䅁䵁佂欵䉁䅁䅁允䅁䅁䅕䭆䠵場啯啅䵁䅉䅅䅁䙁䅁䅁睁䵁䅁䅁权晁䅁䅁权䉁䅁䅁权䙁䅁䅁兂䅁䅁䅁䡁洷䅑䅅䅁䉁䅁䅁兂卂䉵䘶ㄶ杈睐杷允䅁䅁䅑䅁䑁䅁䅷䅁䭁䕁䄸䅁䭁䕁䄴䅁䙁䅁䅁䅁杂敎䅚允䅁䅁䅅䅁䙁䥁牘払敧剨䅆䍄䉁䅁䅁䅂䅁䅁䅍䅄䅁䅁䅯睔䅁䅁䅯杔䅁䅁䅕䅁䅁䵁乂欵䉁䅁䅁允䅁䅁䅕牕敧敨剴啅䵁䅉䅅䅁䙁䅁䅁睁䵁䅁䅁权敁䅁䅁权呂䅁䅁权䙁䅁䅁兂䅁䅁䅁余汄䅑䅅䅁䉁䅁䅁兂硂児塲⽯牁䅑杷允䅁䅁䅕䅁䑁䅁䅷䅁䭁䅁䅁䅁䭁䅁䅅䅁䭁䅁䅕䅁䙁䅁䅁䅁䅄故䅚允䅁䅁䅅䅁䙁䱁敧敨剴乵⼴䍄䉁䅁䅁兂䅁䅁䅍䅄䅁䅁䅯䅁䅁䅁䅯睕䅁䅁䅯兂䅁䅁䅕䅁䅁䵁ㅃ唵䉁䅁䅁允䅁䅁䅕歵䵫楁湳歍䵁䅉䅅䅁䕁䅁䅁睁䵁䅁䅁权偂䅁䅁权佂䅁䅁兂䅁䅁䅁偑汦䅑䅅䅁䉁䅁䅁兂硂児塲㍯十䅑杷允䅁䅁䅕䅁䑁䅁䅷䅁䭁䉁䄰䅁䭁䙁䅍䅁䭁䅁䅕䅁䙁䅁䅁䅁杂⭹䅖允䅁䅁䅅䅁䙁䍁捬㡪ㅌ䍋䄵䍄䉁䅁䅁䅂䅁䅁䅍䅄䅁䅁䅯睔䅁䅁䅯杔䅁䅁䅕䅁䅁䅁啄唵䉁䅁䅁允䅁䅁䅕浚浚浚浚歂䵁䅉䅅䅁䙁䅁䅁睁䵁䅁䅁权捁䅁䅁权呂䅁䅁权䙁䅁䅁兂䅁䅁䅁䍯洷䅑䅅䅁䉁䅁䅁兂奂扏䥔橤甴䅑杷允䅁䅁䅕䅁䑁䅁䅷䅁䭁䅁䅁䅁䭁䙁䅍䅁䭁䅁䅕䅁䙁䅁䅁䅁䅄故䅚允䅁䅁䅅䅁䙁䉁奂扏䥔橬䅊䍄䉁䅁䅁兂䅁䅁䅍䅄䅁䅁䅯杈䅁䅁䅯允䅁䅁䅯兂䅁䅁䅕䅁䅁䍁敄唵䉁䅁䅁允䅁䅁䅕積積積積稰䴸䅉䅅䅁䙁䅁䅁睁䵁䅁䅁权䅁䅁䅁权呂䅁䅁权䙁䅁䅁兂䅁䅁䅁䍧浶䅑䅅䅁䉁䅁䅁兂汄䌰扌含稴䅑杷允䅁䅁䅕䅁䑁䅁䅷䅁䭁䉁䄰䅁䭁䙁䅍䅁䭁䅁䅕䅁䙁䅁䅁䅁䅄教䅚允䅁䅁䅅䅁䙁䡁⼰噎㘶卓䄵䍄䉁䅁䅁䅂䅁䅁䅍䅄䅁䅁䅯睔䅁䅁䅯杔䅁䅁䅕䅁䅁佁灁欵䉁䅁䅁允䅁䅁䅕䭆䠵場啯歅䵁䅉䅅䅁䙁䅁䅁睁䵁䅁䅁权慁䅁䅁权䉁䅁䅁权䙁䅁䅁兂䅁䅁䅁乯汮䅑䅅䅁䉁䅁䅁兂㉄䙋偹癷杘睐杷允䅁䅁䅑䅁䑁䅁䅷䅁䭁䕁䄸䅁䭁䕁䄴䅁䙁䅁䅁䅁䅄敒䅚允䅁䅁䅅䅁䙁䅁䅁䅁䅁䉁䅆䍄䉁䅁䅁兂䅁䅁䅍䅄䅁䅁䅯杇䅁䅁䅯睕䅁䅁䅯兂䅁䅁䅕䅁䅁佁䕂欵䉁䅁䅁允䅁䅁䅕卸睃浣硧く䵁䅉䅅䅁䙁䅁䅁睁䵁䅁䅁权摁䅁䅁权呂䅁䅁权䙁䅁䅁兂䅁䅁䅁偁氯䅑䅅䅁䉁䅁䅁兂杂搵楁⼲瑫䅑杷允䅁䅁䅕䅁䑁䅁䅷䅁䭁䅁䅁䅁䭁䙁䅍䅁䭁䅁䅕䅁䙁䅁䅁䅁䅂敚䅚允䅁䅁䅅䅁䙁䭁硲欰椱䐰䅎䍄䉁䅁䅁兂䅁䅁䅍䅄䅁䅁䅯䅁䅁䅁䅯允䅁䅁䅯兂䅁䅁䅕䅁䅁䭁偂欵䉁䅁䅁允䅁䅁䅕䉵䘶ㄶ㑇樳䴸䅉䅅䅁䙁䅁䅁睁䵁䅁䅁权摁䅁䅁权䉁䅁䅁权䙁䅁䅁兂䅁䅁䅁偉汌䅑䅅䅁䉁䅁䅁兂塄㍯㥁瑃呦睐杷允䅁䅁䅕䅁䑁䅁䅷䅁䭁䉁䄸䅁䭁䙁䅍䅁䭁䅁䅕䅁䙁䅁䅁䅁杂佢䅚允䅁䅁䅅䅁䙁䅁塲㍯㥁橋䅆䍄䉁䅁䅁䅂䅁䅁䅍䅄䅁䅁䅯睔䅁䅁䅯杔䅁䅁䅕䅁䅁䵁牄唵䉁䅁䅁允䅁䅁䅕椹捨㡪ㅌ䕅䵁䅉䅅䅁䙁䅁䅁睁䵁䅁䅁权慁䅁䅁权䉁䅁䅁权䙁䅁䅁兂䅁䅁䅁䩧汲䅑䅅䅁䉁䅁䅁兂䅁䅁䅁䅁杄睐杷允䅁䅁䅕䅁䑁䅁䅷䅁䭁䉁䄰䅁䭁䙁䅍䅁䭁䅁䅕䅁䙁䅁䅁䅁䅁佒䅚允䅁䅁䅅䅁䙁䕁㉡⼸唳䍵䄵䍄䉁䅁䅁兂䅁䅁䅍䅄䅁䅁䅯杇䅁䅁䅯睕䅁䅁䅯兂䅁䅁䅕䅁䅁䭁䉃欵䉁䅁䅁允䅁䅁䅕敥浫免獪歏䵁䅉䅅䅁䙁䅁䅁睁䵁䅁䅁权䅁䅁䅁权呂䅁䅁权䙁䅁䅁兂䅁䅁䅁䩙汘䅑䅅䅁䉁䅁䅁兂㡃䩤奍䡂睙䅑杷允䅁䅁䅕䅁䑁䅁䅷䅁䭁䉁䄸䅁䭁䙁䅍䅁䭁䅁䅕䅁䙁䅁䅁䅁䅄伷䅖允䅁䅁䅅䅁䙁䍁扐堫焵䑘䅂䍄䉁䅁䅁䅂䅁䅁䅍䅄䅁䅁䅯睔䅁䅁䅯杔䅁䅁䅕䅁䅁䵁䵂欵䉁䅁䅁允䅁䅁䅕椹捨㡪ㅌ啅䵁䅉䅅䅁䙁䅁䅁睁䵁䅁䅁权慁䅁䅁权呂䅁䅁权䙁䅁䅁兂䅁䅁䅁䉁洳䅑䅅䅁䉁䅁䅁兂㉃⼸唳䥥㙫䅑杷允䅁䅁䅑䅁䑁䅁䅷䅁䭁䕁䄸䅁䭁䕁䄴䅁䙁䅁䅁䅁权畄䅚允䅁䅁䅅䅁䙁䕁桪桥畓硒䅊䍄䉁䅁䅁兂䅁䅁䅍䅄䅁䅁䅯杇䅁䅁䅯允䅁䅁䅯兂䅁䅁䅕䅁䅁䅁㕂欵䉁䅁䅁允䅁䅁䅕䡰㥁瑃橥䐶䴸䅉䅅䅁䙁䅁䅁睁䵁䅁䅁权䅁䅁䅁权䉁䅁䅁权䙁䅁䅁兂䅁䅁䅁䉉浢䅑䅅䅁䉁䅁䅁兂㑃潈牘払敪睐杷允䅁䅁䅕䅁䑁䅁䅷䅁䭁䉁䅷䅁䭁䙁䅍䅁䭁䅁䅕䅁䙁䅁䅁䅁权攳䅖允䅁䅁䅅䅁䙁䕁椵䙅㕧䍴䄵䍄䉁䅁䅁䅂䅁䅁䅍䅄䅁䅁䅯睔䅁䅁䅯杔䅁䅁䅕䅁䅁䕁奁欵䉁䅁䅁允䅁䅁䅕硥畓⭒㙆歅䵁䅉䅅䅁䙁䅁䅁睁䵁䅁䅁权摁䅁䅁权呂䅁䅁权䙁䅁䅁兂䅁䅁䅁偉汄䅑䅅䅁䉁䅁䅁兂浃㡭村䱳瑉䅑杷允䅁䅁䅕䅁䑁䅁䅷䅁䭁䉁䄸䅁䭁䙁䅍䅁䭁䅁䅕䅁䙁䅁䅁䅁杁畅䅚允䅁䅁䅅䅁䙁䅁坒楄礲呶䅂䍄䉁䅁䅁䅂䅁䅁䅍䅄䅁䅁䅯睔䅁䅁䅯杔䅁䅁䅕䅁䅁䭁穃唵䉁䅁䅁允䅁䅁䅕場啯歲桦樲䴸䅉䅅䅁䕁䅁䅁睁䵁䅁䅁权偂䅁䅁权佂䅁䅁兂䅁䅁䅁䍑浐䅑䅅䅁䉁䅁䅁兂㑃潈牘払剧䅑杷允䅁䅁䅕䅁䑁䅁䅷䅁䭁䅁䅁䅁䭁䙁䅍䅁䭁䅁䅕䅁䙁䅁䅁䅁杂⭘䅚允䅁䅁䅅䅁䙁䭁硲欰椱䐰䅎䍄䉁䅁䅁兂䅁䅁䅍䅄䅁䅁䅯睈䅁䅁䅯睕䅁䅁䅯兂䅁䅁䅕䅁䅁䭁兂欵䉁䅁䅁允䅁䅁䅕呦ㄸ牘灯啍䵁䅉䅅䅁䙁䅁䅁睁䵁䅁䅁权䅁䅁䅁权呂䅁䅁权䙁䅁䅁兂䅁䅁䅁䭉汔䅑䅅䅁䉁䅁䅁兂塄㍯㥁湃硣䅑杷允䅁䅁䅕䅁䑁䅁䅷䅁䭁䉁䄴䅁䭁䙁䅍䅁䭁䅁䅕䅁䙁䅁䅁䅁䅂佒䅚允䅁䅁䅅䅁䙁佁㠵穐敖楏䅒䍄䉁䅁䅁兂䅁䅁䅍䅄䅁䅁䅯先䅁䅁䅯睕䅁䅁䅯兂䅁䅁䅕䅁䅁佁䵁欵䉁䅁䅁允䅁䅁䅕歵䵫楁䡵歌䵁䅉䅅䅁䕁䅁䅁睁䵁䅁䅁权偂䅁䅁权佂䅁䅁兂䅁䅁䅁偁汄䅑䅅䅁䉁䅁䅁兂桄桥畓⭒充䅑杷允䅁䅁䅑䅁䑁䅁䅷䅁䭁䕁䄸䅁䭁䕁䄴䅁䙁䅁䅁䅁杂⭓䅚允䅁䅁䅅䅁䙁䍁捬㡪ㅌ䉋䅆䍄䉁䅁䅁䅂䅁䅁䅍䅄䅁䅁䅯睔䅁䅁䅯杔䅁䅁䅕䅁䅁䕁坃唵䉁䅁䅁允䅁䅁䅕呣䬰㘱睎呺䴸䅉䅅䅁䙁䅁䅁睁䵁䅁䅁权䅁䅁䅁权呂䅁䅁权䙁䅁䅁兂䅁䅁䅁䱁汲䅑䅅䅁䉁䅁䅁兂㑄⭕汏㑭祑䅑杷允䅁䅁䅑䅁䑁䅁䅷䅁䭁䕁䄸䅁䭁䕁䄴䅁䙁䅁䅁䅁䅂畯䅖允䅁䅁䅅䅁䙁乁橥䑣䬰㤱⽍䍄䉁䅁䅁䅂䅁䅁䅍䅄䅁䅁䅯睔䅁䅁䅯杔䅁䅁䅕䅁䅁䕁㉄唵䉁䅁䅁允䅁䅁䅕⽷潕䥘䌯啅䵁䅉䅅䅁䕁䅁䅁睁䵁䅁䅁权偂䅁䅁权佂䅁䅁兂䅁䅁䅁䕉浺䅑䅅䅁䉁䅁䅁兂㥁瑃橥䑣到䅑杷允䅁䅁䅕䅁䑁䅁䅷䅁䭁䉁䄰䅁䭁䅁䅅䅁䭁䅁䅕䅁䙁䅁䅁䅁䅄⬸䅖允䅁䅁䅅䅁䙁乁橥䑣䬰㤱⽍䍄䉁䅁䅁兂䅁䅁䅍䅄䅁䅁䅯睈䅁䅁䅯睕䅁䅁䅯兂䅁䅁䅕䅁䅁䅁獃唵䉁䅁䅁允䅁䅁䅕䉵䘶ㄶ㑆䕍䵁䅉䅅䅁䕁䅁䅁睁䵁䅁䅁权偂䅁䅁权佂䅁䅁兂䅁䅁䅁䕯浲䅑䅅䅁䉁䅁䅁兂硂児塲㍯剁䅑杷允䅁䅁䅑䅁䑁䅁䅷䅁䭁䕁䄸䅁䭁䕁䄴䅁䙁䅁䅁䅁杂畓䅚允䅁䅁䅅䅁䙁䡁㥅瑃橥䉣䅆䍄䉁䅁䅁䅂䅁䅁䅍䅄䅁䅁䅯睔䅁䅁䅯杔䅁䅁䅕䅁䅁䭁䍂欵䉁䅁䅁允䅁䅁䅕䭆䠵場啯䕅䵁䅉䅅䅁䙁䅁䅁睁䵁䅁䅁权摁䅁䅁权呂䅁䅁权䙁䅁䅁兂䅁䅁䅁䉉浮䅑䅅䅁䉁䅁䅁兂䭁㘱睎捐畯䅑杷允䅁䅁䅕䅁䑁䅁䅷䅁䭁䅁䅁䅁䭁䙁䅍䅁䭁䅁䅕䅁䙁䅁䅁䅁䅄⭤䅚允䅁䅁䅅䅁䙁䙁橔婰䕶䑁䅒䍄䉁䅁䅁兂䅁䅁䅍䅄䅁䅁䅯睈䅁䅁䅯允䅁䅁䅯兂䅁䅁䅕䅁䅁䥁㥄唵䉁䅁䅁允䅁䅁䅕体㙆䭆䠵吴䴸䅉䅅䅁䕁䅁䅁睁䵁䅁䅁权偂䅁䅁权佂䅁䅁兂䅁䅁䅁䕯浮䅑䅅䅁䉁䅁䅁兂浂浚浚浚剙䅑杷允䅁䅁䅕䅁䑁䅁䅷䅁䭁䅁䅁䅁䭁䙁䅍䅁䭁䅁䅕䅁䙁䅁䅁䅁杄佯䅖允䅁䅁䅅䅁䙁乁橥䑣䬰稹䅂䍄䉁䅁䅁兂䅁䅁䅍䅄䅁䅁䅯䅁䅁䅁䅯睕䅁䅁䅯兂䅁䅁䅕䅁䅁䵁噂欵䉁䅁䅁允䅁䅁䅕扏䥔牤昷き䵁䅉䅅䅁䕁䅁䅁睁䵁䅁䅁权偂䅁䅁权佂䅁䅁兂䅁䅁䅁乁汶䅑䅅䅁䉁䅁䅁兂穁積積積䩍䅑杷允䅁䅁䅕䅁䑁䅁䅷䅁䭁䉁䄸䅁䭁䙁䅍䅁䭁䅁䅕䅁䙁䅁䅁䅁杄佣䅚允䅁䅁䅅䅁䙁䅁塲㍯㥁橋䅆䍄䉁䅁䅁兂䅁䅁䅍䅄䅁䅁䅯䅁䅁䅁䅯允䅁䅁䅯兂䅁䅁䅕䅁䅁䕁癃唵䉁䅁䅁允䅁䅁䅕灭婭婭婭吲䴸䅉䅅䅁䙁䅁䅁睁䵁䅁䅁权敁䅁䅁权䉁䅁䅁权䙁䅁䅁兂䅁䅁䅁䭯氯䅑䅅䅁䉁䅁䅁兂穁積積積呐睐杷允䅁䅁䅕䅁䑁䅁䅷䅁䭁䅁䅁䅁䭁䅁䅅䅁䭁䅁䅕䅁䙁䅁䅁䅁杁敕䅚允䅁䅁䅅䅁䙁䱁敧敨剴乵⼴䍄䉁䅁䅁兂䅁䅁䅍䅄䅁䅁䅯䅈䅁䅁䅯睕䅁䅁䅯兂䅁䅁䅕䅁䅁䥁求欵䉁䅁䅁允䅁䅁䅕歯㉗⼸唰歌䵁䅉䅅䅁䙁䅁䅁睁䵁䅁䅁权䅁䅁䅁权䉁䅁䅁权䙁䅁䅁兂䅁䅁䅁佁汐䅑䅅䅁䉁䅁䅁兂桄桥畓⭒慈睐杷允䅁䅁䅕䅁䑁䅁䅷䅁䭁䅁䅁䅁䭁䙁䅍䅁䭁䅁䅕䅁䙁䅁䅁䅁䅄⭣䅚允䅁䅁䅅䅁䙁䙁橔婰䕶䑁䅒䍄䉁䅁䅁兂䅁䅁䅍䅄䅁䅁䅯杇䅁䅁䅯允䅁䅁䅯兂䅁䅁䅕䅁䅁䅁ぃ唵䉁䅁䅁允䅁䅁䅕䅁䅁䅁䅁䐴䴸䅉䅅䅁䙁䅁䅁睁䵁䅁䅁权敁䅁䅁权䉁䅁䅁权䙁䅁䅁兂䅁䅁䅁䅉浘䅑䅅䅁䉁䅁䅁兂㝂䭆䠵場啲睐杷允䅁䅁䅑䅁䑁䅁䅷䅁䭁䕁䄸䅁䭁䕁䄴䅁䙁䅁䅁䅁杂敓䅚允䅁䅁䅅䅁䙁佁㙆䭆䠵刴䅂䍄䉁䅁䅁兂䅁䅁䅍䅄䅁䅁䅯䅁䅁䅁䅯睕䅁䅁䅯兂䅁䅁䅕䅁䅁䅁䝂欵䉁䅁䅁允䅁䅁䅕潅䅐煹䙈き䵁䅉䅅䅁䙁䅁䅁睁䵁䅁䅁权摁䅁䅁权呂䅁䅁权䙁䅁䅁兂䅁䅁䅁䭉氳䅑䅅䅁䉁䅁䅁兂婄発呤㘴瑕䅑杷允䅁䅁䅑䅁䑁䅁䅷䅁䭁䕁䄸䅁䭁䕁䄴䅁䙁䅁䅁䅁杁畄䅚允䅁䅁䅅䅁䙁䍁捬㡪ㅌ䉋䅊䍄䉁䅁䅁兂䅁䅁䅍䅄䅁䅁䅯䅈䅁䅁䅯允䅁䅁䅯兂䅁䅁䅕䅁䅁䥁䙄唵䉁䅁䅁允䅁䅁䅕㡪ㅌ䙋偹樰䴸䅉䅅䅁䙁䅁䅁睁䵁䅁䅁权摁䅁䅁权呂䅁䅁权䙁䅁䅁兂䅁䅁䅁䭯汄䅑䅅䅁䉁䅁䅁兂䝂癴㥐䠱瑧䅑杷允䅁䅁䅑䅁䑁䅁䅷䅁䭁䕁䄸䅁䭁䕁䄴䅁䙁䅁䅁䅁权畈䅚允䅁䅁䅅䅁䙁䝁浚浚浚桚䅂䍄䉁䅁䅁兂䅁䅁䅍䅄䅁䅁䅯杇䅁䅁䅯睕䅁䅁䅯兂䅁䅁䅕䅁䅁䕁癄唵䉁䅁䅁允䅁䅁䅕⽷潕䥘䌯問䵁䅉䅅䅁䙁䅁䅁睁䵁䅁䅁权捁䅁䅁权呂䅁䅁权䙁䅁䅁兂䅁䅁䅁偁汐䅑䅅䅁䉁䅁䅁兂㙃兓䍷㡋瑣䅑杷允䅁䅁䅑䅁䑁䅁䅷䅁䭁䕁䄸䅁䭁䕁䄴䅁䙁䅁䅁䅁权佯䅖允䅁䅁䅅䅁䙁䵁ㅐ䙋偹瑷⽕䍄䉁䅁䅁兂䅁䅁䅍䅄䅁䅁䅯先䅁䅁䅯睕䅁䅁䅯兂䅁䅁䅕䅁䅁䍁潄唵䉁䅁䅁允䅁䅁䅕䉵䘶ㄶ㑈䕌䵁䅉䅅䅁䙁䅁䅁睁䵁䅁䅁权䅁䅁䅁权呂䅁䅁权䙁䅁䅁兂䅁䅁䅁䩷汪䅑䅅䅁䉁䅁䅁兂㡃䩤奍䡂睙䅑杷允䅁䅁䅕䅁䑁䅁䅷䅁䭁䉁䄸䅁䭁䙁䅍䅁䭁䅁䅕䅁䙁䅁䅁䅁䅂⭶䅖允䅁䅁䅅䅁䙁䵁㉬灶愸穌䅆䍄䉁䅁䅁䅂䅁䅁䅍䅄䅁䅁䅯睔䅁䅁䅯杔䅁䅁䅕䅁䅁佁䡂欵䉁䅁䅁允䅁䅁䅕浚浚浚浚䕅䵁䅉䅅䅁䕁䅁䅁睁䵁䅁䅁权偂䅁䅁权佂䅁䅁兂䅁䅁䅁䕑浮䅑䅅䅁䉁䅁䅁兂桄桥畓⭒充䅑杷允䅁䅁䅕䅁䑁䅁䅷䅁䭁䉁䄸䅁䭁䙁䅍䅁䭁䅁䅕䅁䙁䅁䅁䅁杄佃䅚允䅁䅁䅅䅁䙁䥁䅐煹䙆橬䅂䍄䉁䅁䅁䅂䅁䅁䅍䅄䅁䅁䅯睔䅁䅁䅯杔䅁䅁䅕䅁䅁䝁啄唵䉁䅁䅁允䅁䅁䅕瑃橥䑣䬰啂䵁䅉䅅䅁䙁䅁䅁睁䵁䅁䅁权捁䅁䅁权䉁䅁䅁权䙁䅁䅁兂䅁䅁䅁䭙汪䅑䅅䅁䉁䅁䅁兂偃癷潕䥘匯睐杷允䅁䅁䅕䅁䑁䅁䅷䅁䭁䉁䅷䅁䭁䙁䅍䅁䭁䅁䅕䅁䙁䅁䅁䅁杂⭘䅚允䅁䅁䅅䅁䙁䭁䙊癴㥐䍆䄵䍄䉁䅁䅁兂䅁䅁䅍䅄䅁䅁䅯先䅁䅁䅯睕䅁䅁䅯兂䅁䅁䅕䅁䅁䵁歄唵䉁䅁䅁允䅁䅁䅕䉵䘶ㄶ㑈䕌䵁䅉䅅䅁䙁䅁䅁睁䵁䅁䅁权敁䅁䅁权呂䅁䅁权䙁䅁䅁兂䅁䅁䅁䙙洳䅑䅅䅁䉁䅁䅁兂剃堷⽷噎椴䅑杷允䅁䅁䅕䅁䑁䅁䅷䅁䭁䉁䄸䅁䭁䅁䅅䅁䭁䅁䅕䅁䙁䅁䅁䅁权⭑䅚允䅁䅁䅅䅁䙁䭁睒児塲⭯⽁䍄䉁䅁䅁䅂䅁䅁䅍䅄䅁䅁䅯睔䅁䅁䅯杔䅁䅁䅕䅁䅁䝁⽄唵䉁䅁䅁允䅁䅁䅕瑃橥䑣䬰啄䵁䅉䅅䅁䙁䅁䅁睁䵁䅁䅁权敁䅁䅁权䉁䅁䅁权䙁䅁䅁兂䅁䅁䅁乑氳䅑䅅䅁䉁䅁䅁兂穁積積積呐睐杷允䅁䅁䅕䅁䑁䅁䅷䅁䭁䉁䅷䅁䭁䙁䅍䅁䭁䅁䅕䅁䙁䅁䅁䅁杂位䅚允䅁䅁䅅䅁䙁䙁㕧䵴㉨楐䄵䍄䉁䅁䅁䅂䅁䅁䅍䅄䅁䅁䅯睔䅁䅁䅯杔䅁䅁䅕䅁䅁䥁䥂欵䉁䅁䅁允䅁䅁䅕牕敧敨剴䕅䵁䅉䅅䅁䙁䅁䅁睁䵁䅁䅁权捁䅁䅁权呂䅁䅁权䙁䅁䅁兂䅁䅁䅁佯汈䅑䅅䅁䉁䅁䅁兂楂䙅㕧䕴畧䅑杷允䅁䅁䅕䅁䑁䅁䅷䅁䭁䉁䅯䅁䭁䙁䅍䅁䭁䅁䅕䅁䙁䅁䅁䅁杂佧䅚允䅁䅁䅅䅁䙁䡁灮橊䥅䐷䅰䍄䉁䅁䅁兂䅁䅁䅍䅄䅁䅁䅯䅁䅁䅁䅯睕䅁䅁䅯兂䅁䅁䅕䅁䅁䅁⽂欵䉁䅁䅁允䅁䅁䅕琯㑒匶硢き䵁䅉䅅䅁䕁䅁䅁睁䵁䅁䅁权偂䅁䅁权佂䅁䅁兂䅁䅁䅁䩁汦䅑䅅䅁䉁䅁䅁兂卂䉵䘶ㄶ䥈睐杷允䅁䅁䅑䅁䑁䅁䅷䅁䭁䕁䄸䅁䭁䕁䄴䅁䙁䅁䅁䅁杄⭌䅚允䅁䅁䅅䅁䭁䉁䅳䅁䵁䅉䅅䅁䙁䅁䅁睁䵁䅁䅁权䅁䅁䅁权䉁䅁䅁权䙁䅁䅁兂䅁䅁䅁䙑浌䅑䅅䅁䉁䅁䅁兂㑃潈牘払敪睐杷允䅁䅁䅕䅁䑁䅁䅷䅁䭁䅁䅁䅁䭁䅁䅅䅁䭁䅁䅕䅁䙁䅁䅁䅁杄⬹䅖允䅁䅁䅅䅁䙁䱁敧敨剴乵⼴䍄䉁䅁䅁兂䅁䅁䅍䅄䅁䅁䅯䅁䅁䅁䅯睕䅁䅁䅯兂䅁䅁䅕䅁䅁佁乄唵䉁䅁䅁允䅁䅁䅕敢㝦晱祈歍䵁䅉䅅䅁䙁䅁䅁睁䵁䅁䅁权捁䅁䅁权䉁䅁䅁权䙁䅁䅁兂䅁䅁䅁䉧洷䅑䅅䅁䉁䅁䅁兂畃⭒㙆䭆堷睐杷允䅁䅁䅑䅁䑁䅁䅷䅁䭁䕁䄸䅁䭁䕁䄴䅁䙁䅁䅁䅁杂体䅚允䅁䅁䅅䅁䙁䙁偹癷潕䉘䅂䍄䉁䅁䅁兂䅁䅁䅍䅄䅁䅁䅯䅁䅁䅁䅯睕䅁䅁䅯兂䅁䅁䅕䅁䅁䝁杄唵䉁䅁䅁允䅁䅁䅕兇坒楄匳歍䵁䅉䅅䅁䙁䅁䅁睁䵁䅁䅁权敁䅁䅁权呂䅁䅁权䙁䅁䅁兂䅁䅁䅁䥙浈䅑䅅䅁䉁䅁䅁兂㥂穐敖歵捫䅑杷允䅁䅁䅕䅁䑁䅁䅷䅁䭁䅁䅁䅁䭁䙁䅍䅁䭁䅁䅕䅁䙁䅁䅁䅁杂甴䅖允䅁䅁䅅䅁䙁䉁䕫杖琴樰䅊䍄䉁䅁䅁兂䅁䅁䅍䅄䅁䅁䅯睈䅁䅁䅯允䅁䅁䅯兂䅁䅁䅕䅁䅁䅁摁欵䉁䅁䅁允䅁䅁䅕椹捨㡪ㅌ䐴䴸䅉䅅䅁䙁䅁䅁睁䵁䅁䅁权䅁䅁䅁权呂䅁䅁权䙁䅁䅁兂䅁䅁䅁䍉浌䅑䅅䅁䉁䅁䅁兂汄䌰扌含稴䅑杷允䅁䅁䅕䅁䑁䅁䅷䅁䭁䉁䅯䅁䭁䙁䅍䅁䭁䅁䅕䅁䙁䅁䅁䅁杂⬲䅖允䅁䅁䅅䅁䙁䉁癳匳䝑呉䅰䍄䉁䅁䅁兂䅁䅁䅍䅄䅁䅁䅯䅈䅁䅁䅯睕䅁䅁䅯兂䅁䅁䅕䅁䅁䝁⭁欵䉁䅁䅁允䅁䅁䅕㥆佮ㄹ橏歌䵁䅉䅅䅁䙁䅁䅁睁䵁䅁䅁权摁䅁䅁权呂䅁䅁权䙁䅁䅁兂䅁䅁䅁䉉洳䅑䅅䅁䉁䅁䅁兂䭁㘱睎捐畯䅑杷允䅁䅁䅕䅁䑁䅁䅷䅁䭁䉁䄸䅁䭁䙁䅍䅁䭁䅁䅕䅁䙁䅁䅁䅁杂佌䅚允䅁䅁䅅䅁䙁䱁穢搯㑒呃䅆䍄䉁䅁䅁䅂䅁䅁䅍䅄䅁䅁䅯睔䅁䅁䅯杔䅁䅁䅕䅁䅁䵁流欵䉁䅁䅁允䅁䅁䅕瑃橥䑣䬰歅䵁䅉䅅䅁䙁䅁䅁睁䵁䅁䅁权敁䅁䅁权䉁䅁䅁权䙁䅁䅁兂䅁䅁䅁䑷洷䅑䅅䅁䉁䅁䅁兂䑄匹捨㡪噌睐杷允䅁䅁䅕䅁䑁䅁䅷䅁䭁䉁䄴䅁䭁䙁䅍䅁䭁䅁䅕䅁䙁䅁䅁䅁䅄畏䅚允䅁䅁䅅䅁䙁偁㥔䠱灪楚䅒䍄䉁䅁䅁䅂䅁䅁䅍䅄䅁䅁䅯睔䅁䅁䅯杔䅁䅁䅕䅁䅁䵁摁欵䉁䅁䅁允䅁䅁䅕体㙆䭆䠵䕅䵁䅉䅅䅁䙁䅁䅁睁䵁䅁䅁权摁䅁䅁权呂䅁䅁权䙁䅁䅁兂䅁䅁䅁余汢䅑䅅䅁䉁䅁䅁兂㑃潈牘晕獧䅑杷允䅁䅁䅕䅁䑁䅁䅷䅁䭁䅁䅁䅁䭁䅁䅅䅁䭁䅁䅕䅁䙁䅁䅁䅁权伴䅖允䅁䅁䅅䅁䙁佁㙆䭆䠵搴⽯䍄䉁䅁䅁兂䅁䅁䅍䅄䅁䅁䅯睈䅁䅁䅯睕䅁䅁䅯兂䅁䅁䅕䅁䅁䵁灂欵䉁䅁䅁允䅁䅁䅕瑃橥䑣焰啍䵁䅉䅅䅁䙁䅁䅁睁䵁䅁䅁权䅁䅁䅁权呂䅁䅁权䙁䅁䅁兂䅁䅁䅁䅯浦䅑䅅䅁䉁䅁䅁兂煃搸乊湙祁䅑杷允䅁䅁䅑䅁䑁䅁䅷䅁䭁䕁䄸䅁䭁䕁䄴䅁䙁䅁䅁䅁䅄⭒䅚允䅁䅁䅅䅁䙁䙁偹癷潕䉘䅂䍄䉁䅁䅁兂䅁䅁䅍䅄䅁䅁䅯杇䅁䅁䅯允䅁䅁䅯兂䅁䅁䅕䅁䅁䥁杄唵䉁䅁䅁允䅁䅁䅕椹捨㡪ㅌ䐴䴸䅉䅅䅁䙁䅁䅁睁䵁䅁䅁权捁䅁䅁权䉁䅁䅁权䙁䅁䅁兂䅁䅁䅁䙷洳䅑䅅䅁䉁䅁䅁兂㉄䙋偹癷奘睐杷允䅁䅁䅕䅁䑁䅁䅷䅁䭁䅁䅁䅁䭁䅁䅅䅁䭁䅁䅕䅁䙁䅁䅁䅁杁敤䅚允䅁䅁䅅䅁䙁䱁敧敨剴乵⼴䍄䉁䅁䅁兂䅁䅁䅍䅄䅁䅁䅯杇䅁䅁䅯允䅁䅁䅯兂䅁䅁䅕䅁䅁䅁䝂欵䉁䅁䅁允䅁䅁䅕䡰㥁瑃橥䐶䴸䅉䅅䅁䙁䅁䅁睁䵁䅁䅁权慁䅁䅁权呂䅁䅁权䙁䅁䅁兂䅁䅁䅁䕑浐䅑䅅䅁䉁䅁䅁兂䙄䱉祂䑡㝅䅑杷允䅁䅁䅕䅁䑁䅁䅷䅁䭁䉁䅷䅁䭁䅁䅅䅁䭁䅁䅕䅁䙁䅁䅁䅁杁敁䅚允䅁䅁䅅䅁䙁䉁䘫ㄶ㑇瑈⽕䍄䉁䅁䅁䅂䅁䅁䅍䅄䅁䅁䅯睔䅁䅁䅯杔䅁䅁䅕䅁䅁䭁䡂欵䉁䅁䅁允䅁䅁䅕敨剴䉵䘶䕅䵁䅉䅅䅁䙁䅁䅁睁䵁䅁䅁权敁䅁䅁权呂䅁䅁权䙁䅁䅁兂䅁䅁䅁䍷浘䅑䅅䅁䉁䅁䅁兂ㅂ硫䕧獖渴䅑杷允䅁䅁䅕䅁䑁䅁䅷䅁䭁䉁䄴䅁䭁䙁䅍䅁䭁䅁䅕䅁䙁䅁䅁䅁权敥䅚允䅁䅁䅅䅁䙁䍁捬㡪ㅌ䍡䅆䍄䉁䅁䅁䅂䅁䅁䅍䅄䅁䅁䅯睔䅁䅁䅯杔䅁䅁䅕䅁䅁䅁䭄唵䉁䅁䅁允䅁䅁䅕䘷㑇潈牘含䴸䅉䅅䅁䕁䅁䅁睁䵁䅁䅁权偂䅁䅁权佂䅁䅁兂䅁䅁䅁䔴浄䅑䅅䅁䉁䅁䅁兂䭁㘱睎児偯䅑杷允䅁䅁䅕䅁䑁䅁䅷䅁䭁䅁䅁䅁䭁䅁䅅䅁䭁䅁䅕䅁䙁䅁䅁䅁䅃敤䅚允䅁䅁䅅䅁䙁䱁敧敨剴乵⼴䍄䉁䅁䅁䅂䅁䅁䅍䅄䅁䅁䅯睔䅁䅁䅯杔䅁䅁䅕䅁䅁䝁灁欵䉁䅁䅁允䅁䅁䅕噋偹癷潕歅䵁䅉䅅䅁䙁䅁䅁睁䵁䅁䅁权䅁䅁䅁权䉁䅁䅁权䙁䅁䅁兂䅁䅁䅁䍧浢䅑䅅䅁䉁䅁䅁兂㑃潈牘払敪睐杷允䅁䅁䅕䅁䑁䅁䅷䅁䭁䅁䅁䅁䭁䙁䅍䅁䭁䅁䅕䅁䙁䅁䅁䅁杄畬䅖允䅁䅁䅅䅁䙁䱁へ硫䕧橤䅂䍄䉁䅁䅁兂䅁䅁䅍䅄䅁䅁䅯先䅁䅁䅯睕䅁䅁䅯兂䅁䅁䅕䅁䅁䝁歃唵䉁䅁䅁允䅁䅁䅕挲㌷⭕汏啌䵁䅉䅅䅁䙁䅁䅁睁䵁䅁䅁权晁䅁䅁权呂䅁䅁权䙁䅁䅁兂䅁䅁䅁䔴浔䅑䅅䅁䉁䅁䅁兂䕁杖琴桳砰䅑杷允䅁䅁䅑䅁䑁䅁䅷䅁䭁䕁䄸䅁䭁䕁䄴䅁䙁䅁䅁䅁䅃⭒䅚允䅁䅁䅅䅁䙁䡁㥅瑃橥䉣䅂䍄䉁䅁䅁兂䅁䅁䅍䅄䅁䅁䅯睈䅁䅁䅯允䅁䅁䅯兂䅁䅁䅕䅁䅁䝁楃唵䉁䅁䅁允䅁䅁䅕呣䬰㘱睎吳䴸䅉䅅䅁䙁䅁䅁睁䵁䅁䅁权晁䅁䅁权呂䅁䅁权䙁䅁䅁兂䅁䅁䅁䙷浐䅑䅅䅁䉁䅁䅁兂㥂穐敖極硫䅑杷允䅁䅁䅑䅁䑁䅁䅷䅁䭁䕁䄸䅁䭁䕁䄴䅁䙁䅁䅁䅁䅂甶䅖允䅁䅁䅅䅁䙁佁㙆䭆䠵刴䅂䍄䉁䅁䅁䅂䅁䅁䅍䅄䅁䅁䅯睔䅁䅁䅯杔䅁䅁䅕䅁䅁䥁䕄唵䉁䅁䅁允䅁䅁䅕体㙆䭆䠵吹䴸䅉䅅䅁䙁䅁䅁睁䵁䅁䅁权摁䅁䅁权䉁䅁䅁权䙁䅁䅁兂䅁䅁䅁䱯氳䅑䅅䅁䉁䅁䅁兂塄㍯㥁瑃呦睐杷允䅁䅁䅕䅁䑁䅁䅷䅁䭁䉁䄰䅁䭁䙁䅍䅁䭁䅁䅕䅁䙁䅁䅁䅁䅁畎䅚允䅁䅁䅅䅁䙁䙁余扌摋礷䄵䍄䉁䅁䅁䅂䅁䅁䅍䅄䅁䅁䅯睔䅁䅁䅯杔䅁䅁䅕䅁䅁䅁灄唵䉁䅁䅁允䅁䅁䅕敨剴䉵䘶歅䵁䅉䅅䅁䕁䅁䅁睁䵁䅁䅁权偂䅁䅁权佂䅁䅁兂䅁䅁䅁䕁浢䅑䅅䅁䉁䅁䅁兂䭁㘱睎児副䅑杷允䅁䅁䅑䅁䑁䅁䅷䅁䭁䕁䄸䅁䭁䕁䄴䅁䙁䅁䅁䅁䅃畆䅚允䅁䅁䅅䅁䙁佁㙆䭆䠵刴䅊䍄䉁䅁䅁兂䅁䅁䅍䅄䅁䅁䅯䅈䅁䅁䅯睕䅁䅁䅯兂䅁䅁䅕䅁䅁䕁㉁欵䉁䅁䅁允䅁䅁䅕䑗ね䡹⭙歌䵁䅉䅅䅁䕁䅁䅁睁䵁䅁䅁权偂䅁䅁权佂䅁䅁兂䅁䅁䅁䕁浘䅑䅅䅁䉁䅁䅁兂灁䥘䌯匹剧䅑杷允䅁䅁䅕䅁䑁䅁䅷䅁䭁䉁䅷䅁䭁䅁䅅䅁䭁䅁䅕䅁䙁䅁䅁䅁䅂佁䅚允䅁䅁䅅䅁䙁䉁䘫ㄶ㑇瑈⽕䍄䉁䅁䅁兂䅁䅁䅍䅄䅁䅁䅯䅁䅁䅁䅯允䅁䅁䅯兂䅁䅁䅕䅁䅁佁牂欵䉁䅁䅁允䅁䅁䅕䉵䘶ㄶ㑇樳䴸䅉䅅䅁䕁䅁䅁睁䵁䅁䅁权偂䅁䅁权佂䅁䅁兂䅁䅁䅁䔴浔䅑䅅䅁䉁䅁䅁权扁䅁䅁䍄䉁䅁䅁兂䅁䅁䅍䅄䅁䅁䅯䅁䅁䅁䅯睕䅁䅁䅯兂䅁䅁䅕䅁䅁䝁䕄唵䉁䅁䅁允䅁䅁䅕䘫橐婰䕵歍䵁䅉䅅䅁䙁䅁䅁睁䵁䅁䅁权晁䅁䅁权䉁䅁䅁权䙁䅁䅁兂䅁䅁䅁䩧氯䅑䅅䅁䉁䅁䅁兂硂児塲㍯摄睐杷允䅁䅁䅑䅁䑁䅁䅷䅁䭁䕁䄸䅁䭁䕁䄴䅁䙁䅁䅁䅁䅂佒䅚允䅁䅁䅅䅁䙁䵁䴳䵺䵺䉺䅂䍄䉁䅁䅁䅂䅁䅁䅍䅄䅁䅁䅯睔䅁䅁䅯杔䅁䅁䅕䅁䅁䍁㍄唵䉁䅁䅁允䅁䅁䅕瑃橥䑣䬰歅䵁䅉䅅䅁䙁䅁䅁睁䵁䅁䅁权䅁䅁䅁权呂䅁䅁权䙁䅁䅁兂䅁䅁䅁䭁汦䅑䅅䅁䉁䅁䅁兂塄㍯㥁湃硣䅑杷允䅁䅁䅕䅁䑁䅁䅷䅁䭁䉁䄴䅁䭁䅁䅅䅁䭁䅁䅕䅁䙁䅁䅁䅁杁佔䅚允䅁䅁䅅䅁䙁䵁ㅐ䙋偹瑷⽕䍄䉁䅁䅁兂䅁䅁䅍䅄䅁䅁䅯杈䅁䅁䅯睕䅁䅁䅯兂䅁䅁䅕䅁䅁䵁㝁欵䉁䅁䅁允䅁䅁䅕倹唳佥浬䕊䵁䅉䅅䅁䕁䅁䅁睁䵁䅁䅁权偂䅁䅁权佂䅁䅁兂䅁䅁䅁䅯浪䅑䅅䅁䉁䅁䅁兂浂浚浚浚剙䅑杷允䅁䅁䅕䅁䑁䅁䅷䅁䭁䉁䄰䅁䭁䙁䅍䅁䭁䅁䅕䅁䙁䅁䅁䅁杄⬶䅖允䅁䅁䅅䅁䙁䭁扡䍸睃楳䄱䍄䉁䅁䅁䅂䅁䅁䅍䅄䅁䅁䅯睔䅁䅁䅯杔䅁䅁䅕䅁䅁䍁䕂欵䉁䅁䅁允䅁䅁䅕呣䬰㘱睎䕅䵁䅉䅅䅁䙁䅁䅁睁䵁䅁䅁权晁䅁䅁权呂䅁䅁权䙁䅁䅁兂䅁䅁䅁䉉浔䅑䅅䅁䉁䅁䅁兂䕁杖琴牳眰䅑杷允䅁䅁䅕䅁䑁䅁䅷䅁䭁䉁䄸䅁䭁䅁䅅䅁䭁䅁䅕䅁䙁䅁䅁䅁䅄畮䅖允䅁䅁䅅䅁䙁䡁㥅瑃橥乣⼰䍄䉁䅁䅁兂䅁䅁䅍䅄䅁䅁䅯睈䅁䅁䅯睕䅁䅁䅯兂䅁䅁䅕䅁䅁䕁㥃唵䉁䅁䅁允䅁䅁䅕塹⭡确癯啍䵁䅉䅅䅁䙁䅁䅁睁䵁䅁䅁权䅁䅁䅁权䉁䅁䅁权䙁䅁䅁兂䅁䅁䅁䝯浐䅑䅅䅁䉁䅁䅁兂㑃潈牘払敪睐杷允䅁䅁䅕䅁䑁䅁䅷䅁䭁䉁䄸䅁䭁䅁䅅䅁䭁䅁䅕䅁䙁䅁䅁䅁杂⭃䅚允䅁䅁䅅䅁䙁䭁睒児塲⭯⽁䍄䉁䅁䅁兂䅁䅁䅍䅄䅁䅁䅯睈䅁䅁䅯允䅁䅁䅯兂䅁䅁䅕䅁䅁䥁䱂欵䉁䅁䅁允䅁䅁䅕䡰㥁瑃橥䐴䴸䅉䅅䅁䙁䅁䅁睁䵁䅁䅁权慁䅁䅁权呂䅁䅁权䙁䅁䅁兂䅁䅁䅁倴汈䅑䅅䅁䉁䅁䅁兂䑄匹捨㡪㕉䅑杷允䅁䅁䅑䅁䑁䅁䅷䅁䭁䕁䄸䅁䭁䕁䄴䅁䙁䅁䅁䅁䅁佒䅚允䅁䅁䅅䅁䙁䝁浚浚浚桚䅂䍄䉁䅁䅁兂䅁䅁䅍䅄䅁䅁䅯䅁䅁䅁䅯睕䅁䅁䅯兂䅁䅁䅕䅁䅁䥁㝄唵䉁䅁䅁允䅁䅁䅕噋偹癷潖歍䵁䅉䅅䅁䙁䅁䅁睁䵁䅁䅁权摁䅁䅁权䉁䅁䅁权䙁䅁䅁兂䅁䅁䅁䐴浈䅑䅅䅁䉁䅁䅁兂畃⭒㙆䭆堷睐杷允䅁䅁䅑䅁䑁䅁䅷䅁䭁䕁䄸䅁䭁䕁䄴䅁䙁䅁䅁䅁䅄畑䅚允䅁䅁䅅䅁䙁䑁積積積硍䅂䍄䉁䅁䅁兂䅁䅁䅍䅄䅁䅁䅯杈䅁䅁䅯睕䅁䅁䅯兂䅁䅁䅕䅁䅁䕁灁欵䉁䅁䅁允䅁䅁䅕婤奍䙂佢お䵁䅉䅅䅁䙁䅁䅁睁䵁䅁䅁权䅁䅁䅁权䉁䅁䅁权䙁䅁䅁兂䅁䅁䅁䙉浶䅑䅅䅁䉁䅁䅁兂㑃潈牘払敪睐杷允䅁䅁䅕䅁䑁䅁䅷䅁䭁䅁䅁䅁䭁䙁䅍䅁䭁䅁䅕䅁䙁䅁䅁䅁䅂⬴䅖允䅁䅁䅅䅁䙁䉁䕫杖琴樰䅊䍄䉁䅁䅁兂䅁䅁䅍䅄䅁䅁䅯先䅁䅁䅯允䅁䅁䅯兂䅁䅁䅕䅁䅁佁呁欵䉁䅁䅁允䅁䅁䅕㑈牘払敧吱䴸䅉䅅䅁䙁䅁䅁睁䵁䅁䅁权䅁䅁䅁权呂䅁䅁权䙁䅁䅁兂䅁䅁䅁䡉浘䅑䅅䅁䉁䅁䅁兂啂㘴扗䅸ぁ䅑杷允䅁䅁䅑䅁䑁䅁䅷䅁䭁䕁䄸䅁䭁䕁䄴䅁䙁䅁䅁䅁䅃佅䅚允䅁䅁䅅䅁䙁䍁捬㡪ㅌ䉋䅎䍄䉁䅁䅁兂䅁䅁䅍䅄䅁䅁䅯䅁䅁䅁䅯睕䅁䅁䅯兂䅁䅁䅕䅁䅁䅁睂欵䉁䅁䅁允䅁䅁䅕佖汏㡭杔き䵁䅉䅅䅁䙁䅁䅁睁䵁䅁䅁权慁䅁䅁权䉁䅁䅁权䙁䅁䅁兂䅁䅁䅁䉉洳䅑䅅䅁䉁䅁䅁兂歃䑣䬰㘱潐睐杷允䅁䅁䅑䅁䑁䅁䅷䅁䭁䕁䄸䅁䭁䕁䄴䅁䙁䅁䅁䅁杁⭅䅚允䅁䅁䅅䅁䙁偁潙䥘䌯刹䅊䍄䉁䅁䅁兂䅁䅁䅍䅄䅁䅁䅯先䅁䅁䅯睕䅁䅁䅯兂䅁䅁䅕䅁䅁䭁癃唵䉁䅁䅁允䅁䅁䅕瑃橥䑣䬳啌䵁䅉䅅䅁䙁䅁䅁睁䵁䅁䅁权晁䅁䅁权䉁䅁䅁权䙁䅁䅁兂䅁䅁䅁䑁洯䅑䅅䅁䉁䅁䅁兂歃䑣䬰㘱材睐杷允䅁䅁䅑䅁䑁䅁䅷䅁䭁䕁䄸䅁䭁䕁䄴䅁䙁䅁䅁䅁䅂畑䅚允䅁䅁䅅䅁䙁䩁婱婭婭六䄹䍄䉁䅁䅁兂䅁䅁䅍䅄䅁䅁䅯䅁䅁䅁䅯睕䅁䅁䅯兂䅁䅁䅕䅁䅁䥁䉁欵䉁䅁䅁允䅁䅁䅕癱午坔睊歍䵁䅉䅅䅁䕁䅁䅁睁䵁䅁䅁权偂䅁䅁权佂䅁䅁兂䅁䅁䅁䕷浄䅑䅅䅁䉁䅁䅁兂晁敨剴䉵倴䅑杷允䅁䅁䅕䅁䑁䅁䅷䅁䭁䉁䅯䅁䭁䅁䅅䅁䭁䅁䅕䅁䙁䅁䅁䅁䅁敺䅖允䅁䅁䅅䅁䙁偁潙䥘䌯改⽁䍄䉁䅁䅁兂䅁䅁䅍䅄䅁䅁䅯先䅁䅁䅯睕䅁䅁䅯兂䅁䅁䅕䅁䅁䅁㥂欵䉁䅁䅁允䅁䅁䅕䬸䝦穓䩦啌䵁䅉䅅䅁䕁䅁䅁睁䵁䅁䅁权偂䅁䅁权佂䅁䅁兂䅁䅁䅁䍉浔䅑䅅䅁䉁䅁䅁兂乄䵺䵺䵺剷䅑杷允䅁䅁䅕䅁䑁䅁䅷䅁䭁䅁䅁䅁䭁䙁䅍䅁䭁䅁䅕䅁䙁䅁䅁䅁䅃⬱䅖允䅁䅁䅅䅁䙁䭁慁㥌欰橂䅎䍄䉁䅁䅁䅂䅁䅁䅍䅄䅁䅁䅯睔䅁䅁䅯杔䅁䅁䅕䅁䅁䅁䅂欵䉁䅁䅁允䅁䅁䅕椹捨㡪ㅌ䕄䵁䅉䅅䅁䙁䅁䅁睁䵁䅁䅁权䅁䅁䅁权呂䅁䅁权䙁䅁䅁兂䅁䅁䅁䄴浺䅑䅅䅁䉁䅁䅁兂允䑗ね䩹祙䅑杷允䅁䅁䅕䅁䑁䅁䅷䅁䭁䅁䅁䅁䭁䙁䅍䅁䭁䅁䅕䅁䙁䅁䅁䅁杄畤䅚允䅁䅁䅅䅁䙁䙁橔婰䕶䑁䅒䍄䉁䅁䅁兂䅁䅁䅍䅄䅁䅁䅯杇䅁䅁䅯允䅁䅁䅯兂䅁䅁䅕䅁䅁佁穁欵䉁䅁䅁允䅁䅁䅕䡰㥁瑃橥䐶䴸䅉䅅䅁䙁䅁䅁睁䵁䅁䅁权慁䅁䅁权呂䅁䅁权䙁䅁䅁兂䅁䅁䅁乁汔䅑䅅䅁䉁䅁䅁兂扁㥌欰楂㙅䅑杷允䅁䅁䅕䅁䑁䅁䅷䅁䭁䉁䅯䅁䭁䙁䅍䅁䭁䅁䅕䅁䙁䅁䅁䅁杂余䅚允䅁䅁䅅䅁䙁䱁昶楇搯䑚䅴䍄䉁䅁䅁兂䅁䅁䅍䅄䅁䅁䅯䅁䅁䅁䅯睕䅁䅁䅯兂䅁䅁䅕䅁䅁䅁畃唵䉁䅁䅁允䅁䅁䅕㘱睎児㍰啍䵁䅉䅅䅁䙁䅁䅁睁䵁䅁䅁权捁䅁䅁权䉁䅁䅁权䙁䅁䅁兂䅁䅁䅁䝑浮䅑䅅䅁䉁䅁䅁兂㉄䙋偹癷奘睐杷允䅁䅁䅑䅁䑁䅁䅷䅁䭁䕁䄸䅁䭁䕁䄴䅁䙁䅁䅁䅁䅄⭐䅚允䅁䅁䅅䅁䙁䍁捬㡪ㅌ䅋䅸䍄䉁䅁䅁兂䅁䅁䅍䅄䅁䅁䅯䅁䅁䅁䅯睕䅁䅁䅯兂䅁䅁䅕䅁䅁䍁浂欵䉁䅁䅁允䅁䅁䅕佖汏㡭杔き䵁䅉䅅䅁䕁䅁䅁睁䵁䅁䅁权偂䅁䅁权佂䅁䅁兂䅁䅁䅁䅑浄䅑䅅䅁䉁䅁䅁兂穁積積積乍䅑杷允䅁䅁䅕䅁䑁䅁䅷䅁䭁䅁䅁䅁䭁䙁䅍䅁䭁䅁䅕䅁䙁䅁䅁䅁䅂佰䅖允䅁䅁䅅䅁䙁乁橥䑣䬰穤䅆䍄䉁䅁䅁兂䅁䅁䅍䅄䅁䅁䅯䅈䅁䅁䅯睕䅁䅁䅯兂䅁䅁䅕䅁䅁䍁⽁欵䉁䅁䅁允䅁䅁䅕㥆佮ㄹ橏歌䵁䅉䅅䅁䕁䅁䅁睁䵁䅁䅁权偂䅁䅁权佂䅁䅁兂䅁䅁䅁䑑浈䅑䅅䅁䉁䅁䅁兂慃婭婭婭卫䅑杷允䅁䅁䅕䅁䑁䅁䅷䅁䭁䅁䅁䅁䭁䅁䅅䅁䭁䅁䅕䅁䙁䅁䅁䅁杂佳䅖允䅁䅁䅅䅁䙁䩁婱婭婭摭⽫䍄䉁䅁䅁兂䅁䅁䅍䅄䅁䅁䅯杈䅁䅁䅯睕䅁䅁䅯兂䅁䅁䅕䅁䅁䝁十欵䉁䅁䅁允䅁䅁䅕硢䑋䵷桲啋䵁䅉䅅䅁䙁䅁䅁睁䵁䅁䅁权敁䅁䅁权呂䅁䅁权䙁䅁䅁兂䅁䅁䅁䉙浮䅑䅅䅁䉁䅁䅁兂婁䙂余塌灉䅑杷允䅁䅁䅕䅁䑁䅁䅷䅁䭁䉁䄸䅁䭁䅁䅅䅁䭁䅁䅕䅁䙁䅁䅁䅁䅁畹䅖允䅁䅁䅅䅁䙁䭁睒児塲⭯⽁䍄䉁䅁䅁兂䅁䅁䅍䅄䅁䅁䅯䅁䅁䅁䅯睕䅁䅁䅯兂䅁䅁䅕䅁䅁䍁啂欵䉁䅁䅁允䅁䅁䅕扏䥔牤昷き䵁䅉䅅䅁䙁䅁䅁睁䵁䅁䅁权慁䅁䅁权䉁䅁䅁权䙁䅁䅁兂䅁䅁䅁䕑浺䅑䅅䅁䉁䅁䅁兂歃䑣䬰㘱潐睐杷允䅁䅁䅕䅁䑁䅁䅷䅁䭁䉁䄰䅁䭁䅁䅅䅁䭁䅁䅕䅁䙁䅁䅁䅁杁敖䅚允䅁䅁䅅䅁䙁䭁䠵場啯瑲⽣䍄䉁䅁䅁䅂䅁䅁䅍䅄䅁䅁䅯睔䅁䅁䅯杔䅁䅁䅕䅁䅁䕁⽁欵䉁䅁䅁允䅁䅁䅕䘷㑇潈牘ぃ䵁䅉䅅䅁䙁䅁䅁睁䵁䅁䅁权慁䅁䅁权䉁䅁䅁权䙁䅁䅁兂䅁䅁䅁䍑洷䅑䅅䅁䉁䅁䅁兂歃䑣䬰㘱潐睐杷允䅁䅁䅕䅁䑁䅁䅷䅁䭁䉁䄰䅁䭁䙁䅍䅁䭁䅁䅕䅁䙁䅁䅁䅁杁佃䅚允䅁䅁䅅䅁䙁䩁畨潅䅐楓䄵䍄䉁䅁䅁兂䅁䅁䅍䅄䅁䅁䅯䅁䅁䅁䅯睕䅁䅁䅯兂䅁䅁䅕䅁䅁䍁⽁欵䉁䅁䅁允䅁䅁䅕䅁䅁䅁权き䵁䅉䅅䅁䕁䅁䅁睁䵁䅁䅁权偂䅁䅁权佂䅁䅁兂䅁䅁䅁䍑浈䅑䅅䅁䉁䅁䅁兂穁積積積免䅑杷允䅁䅁䅕䅁䑁䅁䅷䅁䭁䅁䅁䅁䭁䅁䅅䅁䭁䅁䅕䅁䙁䅁䅁䅁杄佦䅚允䅁䅁䅅䅁䙁䱁敧敨剴乵⼴䍄䉁䅁䅁兂䅁䅁䅍䅄䅁䅁䅯先䅁䅁䅯睕䅁䅁䅯兂䅁䅁䅕䅁䅁䕁㡂欵䉁䅁䅁允䅁䅁䅕䬸䝦穓䩦啌䵁䅉䅅䅁䙁䅁䅁睁䵁䅁䅁权晁䅁䅁权䉁䅁䅁权䙁䅁䅁兂䅁䅁䅁䘴浐䅑䅅䅁䉁䅁䅁兂卂䉵䘶ㄶ杈睐杷允䅁䅁䅕䅁䑁䅁䅷䅁䭁䉁䅯䅁䭁䙁䅍䅁䭁䅁䅕䅁䙁䅁䅁䅁杂佡䅚允䅁䅁䅅䅁䙁䍁搯䅊䉡呖䅴䍄䉁䅁䅁兂䅁䅁䅍䅄䅁䅁䅯睈䅁䅁䅯允䅁䅁䅯兂䅁䅁䅕䅁䅁䝁㍃唵䉁䅁䅁允䅁䅁䅕敨剴䉵䘶稲䴸䅉䅅䅁䙁䅁䅁睁䵁䅁䅁权䅁䅁䅁权䉁䅁䅁权䙁䅁䅁兂䅁䅁䅁䅯浲䅑䅅䅁䉁䅁䅁兂㑃潈牘払敪睐杷允䅁䅁䅑䅁䑁䅁䅷䅁䭁䕁䄸䅁䭁䕁䄴䅁䙁䅁䅁䅁杂畈䅚允䅁䅁䅅䅁䙁䡁㥅瑃橥䉣䅂䍄䉁䅁䅁䅂䅁䅁䅍䅄䅁䅁䅯睔䅁䅁䅯杔䅁䅁䅕䅁䅁䅁⽁欵䉁䅁䅁允䅁䅁䅕䘷㑇潈牘ぃ䵁䅉䅅䅁䙁䅁䅁睁䵁䅁䅁权晁䅁䅁权呂䅁䅁权䙁䅁䅁兂䅁䅁䅁䍉浲䅑䅅䅁䉁䅁䅁兂㉃⼸唳䅥硫䅑杷允䅁䅁䅕䅁䑁䅁䅷䅁䭁䉁䄸䅁䭁䙁䅍䅁䭁䅁䅕䅁䙁䅁䅁䅁䅄敓䅚允䅁䅁䅅䅁䙁䅁坒楄礲呈䅆䍄䉁䅁䅁䅂䅁䅁䅍䅄䅁䅁䅯睔䅁䅁䅯杔䅁䅁䅕䅁䅁佁㍁欵䉁䅁䅁允䅁䅁䅕䡰㥁瑃橥䕅䵁䅉䅅䅁䕁䅁䅁睁䵁䅁䅁权偂䅁䅁权佂䅁䅁兂䅁䅁䅁偙氷䅑䅅䅁䉁䅁䅁兂偃癷潕䥘伸䅑杷允䅁䅁䅕䅁䑁䅁䅷䅁䭁䅁䅁䅁䭁䅁䅅䅁䭁䅁䅕䅁䙁䅁䅁䅁杁敉䅚允䅁䅁䅅䅁䙁䱁敧敨剴乵⼴䍄䉁䅁䅁兂䅁䅁䅍䅄䅁䅁䅯䅁䅁䅁䅯睕䅁䅁䅯兂䅁䅁䅕䅁䅁佁㝃唵䉁䅁䅁允䅁䅁䅕䘫橐婰䕵歍䵁䅉䅅䅁䕁䅁䅁睁䵁䅁䅁权偂䅁䅁权佂䅁䅁兂䅁䅁䅁䅉浺䅑䅅䅁䉁䅁䅁兂偃癷潕䥘匸䅑杷允䅁䅁䅑䅁䑁䅁䅷䅁䭁䕁䄸䅁䭁䕁䄴䅁䙁䅁䅁䅁䅂敌䅚允䅁䅁䅅䅁䙁䥁䌯匹捨硪䅊䍄䉁䅁䅁兂䅁䅁䅍䅄䅁䅁䅯杇䅁䅁䅯允䅁䅁䅯兂䅁䅁䅕䅁䅁䥁捃唵䉁䅁䅁允䅁䅁䅕䅁䅁䅁䅁䐴䴸䅉䅅䅁䙁䅁䅁睁䵁䅁䅁权䅁䅁䅁权呂䅁䅁权䙁䅁䅁兂䅁䅁䅁䙙浈䅑䅅䅁䉁䅁䅁兂㕁䵴㉨瑶稸䅑杷允䅁䅁䅕䅁䑁䅁䅷䅁䭁䉁䄸䅁䭁䙁䅍䅁䭁䅁䅕䅁䙁䅁䅁䅁权畦䅚允䅁䅁䅅䅁䙁䝁汄䌰扌含䅂䍄䉁䅁䅁䅂䅁䅁䅍䅄䅁䅁䅯睔䅁䅁䅯杔䅁䅁䅕䅁䅁䍁睃唵䉁䅁䅁允䅁䅁䅕敨剴䉵䘶稲䴸䅉䅅䅁䕁䅁䅁睁䵁䅁䅁权偂䅁䅁权佂䅁䅁兂䅁䅁䅁䑙洷䅑䅅䅁䉁䅁䅁兂畃⭒㙆䭆䰴䅑杷允䅁䅁䅕䅁䑁䅁䅷䅁䭁䉁䄰䅁䭁䙁䅍䅁䭁䅁䅕䅁䙁䅁䅁䅁䅂佖䅚允䅁䅁䅅䅁䙁䵁ㅐ䙋偹楧䄵䍄䉁䅁䅁兂䅁䅁䅍䅄䅁䅁䅯䅁䅁䅁䅯允䅁䅁䅯兂䅁䅁䅕䅁䅁䵁慂欵䉁䅁䅁允䅁䅁䅕䉵䘶ㄶ㑇樳䴸䅉䅅䅁䙁䅁䅁睁䵁䅁䅁权摁䅁䅁权呂䅁䅁权䙁䅁䅁兂䅁䅁䅁䵉汮䅑䅅䅁䉁䅁䅁兂灁䥘䌯匹畧䅑杷允䅁䅁䅕䅁䑁䅁䅷䅁䭁䅁䅁䅁䭁䅁䅅䅁䭁䅁䅕䅁䙁䅁䅁䅁䅄敵䅖允䅁䅁䅅䅁䙁䩁婱婭婭摭⽫䍄䉁䅁䅁䅂䅁䅁䅍䅄䅁䅁䅯睔䅁䅁䅯杔䅁䅁䅕䅁䅁䍁㥄唵䉁䅁䅁允䅁䅁䅕䥘䌯匹捨い䵁䅉䅅䅁䙁䅁䅁睁䵁䅁䅁权䅁䅁䅁权䉁䅁䅁权䙁䅁䅁兂䅁䅁䅁䙧浮䅑䅅䅁䉁䅁䅁兂㑃潈牘払敪睐杷允䅁䅁䅑䅁䑁䅁䅷䅁䭁䕁䄸䅁䭁䕁䄴䅁䙁䅁䅁䅁杁畐䅚允䅁䅁䅅䅁䙁佁剸䉵䘶眶䅴䍄䉁䅁䅁䅂䅁䅁䅍䅄䅁䅁䅯睔䅁䅁䅯杔䅁䅁䅕䅁䅁䕁ㅁ欵䉁䅁䅁允䅁䅁䅕硥畓⭒㙆啅䵁䅉䅅䅁䙁䅁䅁睁䵁䅁䅁权捁䅁䅁权呂䅁䅁权䙁䅁䅁兂䅁䅁䅁䝯浌䅑䅅䅁䉁䅁䅁兂楃扒穢刯畑䅑杷允䅁䅁䅕䅁䑁䅁䅷䅁䭁䉁䄸䅁䭁䅁䅅䅁䭁䅁䅕䅁䙁䅁䅁䅁杁敲䅖允䅁䅁䅅䅁䭁䉁䅳䅁䵁䅉䅅䅁䕁䅁䅁睁䵁䅁䅁权偂䅁䅁权佂䅁䅁兂䅁䅁䅁䑁洷䅑䅅䅁䉁䅁䅁兂慃婭婭婭䱫䅑杷允䅁䅁䅕䅁䑁䅁䅷䅁䭁䉁䅷䅁䭁䅁䅅䅁䭁䅁䅕䅁䙁䅁䅁䅁权支䅖允䅁䅁䅅䅁䙁䉁䘫ㄶ㑇瑈⽕䍄䉁䅁䅁䅂䅁䅁䅍䅄䅁䅁䅯睔䅁䅁䅯杔䅁䅁䅕䅁䅁䭁慄唵䉁䅁䅁允䅁䅁䅕㑈牘払敧啃䵁䅉䅅䅁䙁䅁䅁睁䵁䅁䅁权䅁䅁䅁权呂䅁䅁权䙁䅁䅁兂䅁䅁䅁䐴洳䅑䅅䅁䉁䅁䅁兂䅁䅁䅁䭁穁䅑杷允䅁䅁䅕䅁䑁䅁䅷䅁䭁䉁䅯䅁䭁䙁䅍䅁䭁䅁䅕䅁䙁䅁䅁䅁杄佥䅚允䅁䅁䅅䅁䙁䕁㍷啩杆告䅴䍄䉁䅁䅁兂䅁䅁䅍䅄䅁䅁䅯䅁䅁䅁䅯睕䅁䅁䅯兂䅁䅁䅕䅁䅁䵁䡁欵䉁䅁䅁允䅁䅁䅕癱午坔睊歍䵁䅉䅅䅁䕁䅁䅁睁䵁䅁䅁权偂䅁䅁权佂䅁䅁兂䅁䅁䅁䅉浦䅑䅅䅁䉁䅁䅁兂㑃潈牘払卧䅑杷允䅁䅁䅕䅁䑁䅁䅷䅁䭁䅁䅁䅁䭁䅁䅅䅁䭁䅁䅕䅁䙁䅁䅁䅁权男䅖允䅁䅁䅅䅁䙁䥁牘払敧摨⽳䍄䉁䅁䅁兂䅁䅁䅍䅄䅁䅁䅯䅁䅁䅁䅯睕䅁䅁䅯兂䅁䅁䅕䅁䅁䕁潃唵䉁䅁䅁允䅁䅁䅕㘱睎児㍰啍䵁䅉䅅䅁䕁䅁䅁睁䵁䅁䅁权偂䅁䅁权佂䅁䅁兂䅁䅁䅁䑁洳䅑䅅䅁䉁䅁䅁兂卂䉵䘶ㄶ䵅䅑杷允䅁䅁䅕䅁䑁䅁䅷䅁䭁䉁䅷䅁䭁䙁䅍䅁䭁䅁䅕䅁䙁䅁䅁䅁权異䅖允䅁䅁䅅䅁䙁偁潙䥘䌯却䄱䍄䉁䅁䅁兂䅁䅁䅍䅄䅁䅁䅯睈䅁䅁䅯允䅁䅁䅯兂䅁䅁䅕䅁䅁䵁敂欵䉁䅁䅁允䅁䅁䅕椹捨㡪ㅌ䐴䴸䅉䅅䅁䕁䅁䅁睁䵁䅁䅁权偂䅁䅁权佂䅁䅁兂䅁䅁䅁䑙浶䅑䅅䅁䉁䅁䅁兂䑄匹捨㡪义䅑杷允䅁䅁䅕䅁䑁䅁䅷䅁䭁䉁䄰䅁䭁䅁䅅䅁䭁䅁䅕䅁䙁䅁䅁䅁杁敲䅖允䅁䅁䅅䅁䙁乁橥䑣䬰㤱⽍䍄䉁䅁䅁兂䅁䅁䅍䅄䅁䅁䅯先䅁䅁䅯睕䅁䅁䅯兂䅁䅁䅕䅁䅁䕁噄唵䉁䅁䅁允䅁䅁䅕⽷潕䥘䌯啌䵁䅉䅅䅁䙁䅁䅁睁䵁䅁䅁权捁䅁䅁权䉁䅁䅁权䙁䅁䅁兂䅁䅁䅁偙氷䅑䅅䅁䉁䅁䅁兂晁敨剴䉵嘷睐杷允䅁䅁䅑䅁䑁䅁䅷䅁䭁䕁䄸䅁䭁䕁䄴䅁䙁䅁䅁䅁权畏䅚允䅁䅁䅅䅁䙁佁剸䉵䘶眶䄱䍄䉁䅁䅁兂䅁䅁䅍䅄䅁䅁䅯䅈䅁䅁䅯允䅁䅁䅯兂䅁䅁䅕䅁䅁䍁橂欵䉁䅁䅁允䅁䅁䅕椹捨㡪ㅌ䐲䴸䅉䅅䅁䙁䅁䅁睁䵁䅁䅁权晁䅁䅁权呂䅁䅁权䙁䅁䅁兂䅁䅁䅁䩷汲䅑䅅䅁䉁䅁䅁兂捃䍸睃楣硧䅑杷允䅁䅁䅕䅁䑁䅁䅷䅁䭁䅁䅁䅁䭁䅁䅅䅁䭁䅁䅕䅁䙁䅁䅁䅁杄⭯䅖允䅁䅁䅅䅁䙁䩁婱婭婭摭⽫䍄䉁䅁䅁兂䅁䅁䅍䅄䅁䅁䅯杇䅁䅁䅯允䅁䅁䅯兂䅁䅁䅕䅁䅁䭁歄唵䉁䅁䅁允䅁䅁䅕椹捨㡪ㅌ䐴䴸䅉䅅䅁䙁䅁䅁睁䵁䅁䅁权䅁䅁䅁权䉁䅁䅁权䙁䅁䅁兂䅁䅁䅁䝉浄䅑䅅䅁䉁䅁䅁兂㑃潈牘払敪睐杷允䅁䅁䅑䅁䑁䅁䅷䅁䭁䕁䄸䅁䭁䕁䄴䅁䙁䅁䅁䅁䅃敱䅖允䅁䅁䅅䅁䙁䥁牘払敧摨⽳䍄䉁䅁䅁䅂䅁䅁䅍䅄䅁䅁䅯睔䅁䅁䅯杔䅁䅁䅕䅁䅁䥁䕁欵䉁䅁䅁允䅁䅁䅕䘷㑇潈牘䕅䵁䅉䅅䅁䕁䅁䅁睁䵁䅁䅁权偂䅁䅁权佂䅁䅁兂䅁䅁䅁䑧浮䅑䅅䅁䉁䅁䅁兂偃癷潕䥘伸䅑杷允䅁䅁䅕䅁䑁䅁䅷䅁䭁䉁䅯䅁䭁䅁䅅䅁䭁䅁䅕䅁䙁䅁䅁䅁䅁佷䅖允䅁䅁䅅䅁䙁䅁䅁䅁䅁佁⽁䍄䉁䅁䅁兂䅁䅁䅍䅄䅁䅁䅯先䅁䅁䅯睕䅁䅁䅯兂䅁䅁䅕䅁䅁䕁橄唵䉁䅁䅁允䅁䅁䅕䉵䘶ㄶ㑈䕌䵁䅉䅅䅁䙁䅁䅁睁䵁䅁䅁权摁䅁䅁权呂䅁䅁权䙁䅁䅁兂䅁䅁䅁䍑浪䅑䅅䅁䉁䅁䅁兂浂浚浚畚留䅑杷允䅁䅁䅕䅁䑁䅁䅷䅁䭁䉁䄸䅁䭁䅁䅅䅁䭁䅁䅕䅁䙁䅁䅁䅁䅁⭇䅚允䅁䅁䅅䅁䙁偁潙䥘䌯改⽁䍄䉁䅁䅁兂䅁䅁䅍䅄䅁䅁䅯䅁䅁䅁䅯允䅁䅁䅯兂䅁䅁䅕䅁䅁䵁敃唵䉁䅁䅁允䅁䅁䅕灭婭婭婭吲䴸䅉䅅䅁䙁䅁䅁睁䵁䅁䅁权摁䅁䅁权䉁䅁䅁权䙁䅁䅁兂䅁䅁䅁乁氯䅑䅅䅁䉁䅁䅁兂塄㍯㥁瑃呦睐杷允䅁䅁䅑䅁䑁䅁䅷䅁䭁䕁䄸䅁䭁䕁䄴䅁䙁䅁䅁䅁䅂住䅚允䅁䅁䅅䅁䙁䩁婱婭婭六䄱䍄䉁䅁䅁兂䅁䅁䅍䅄䅁䅁䅯杇䅁䅁䅯睕䅁䅁䅯兂䅁䅁䅕䅁䅁䅁啂欵䉁䅁䅁允䅁䅁䅕⽷潕䥘椹く䵁䅉䅅䅁䙁䅁䅁睁䵁䅁䅁权䅁䅁䅁权呂䅁䅁权䙁䅁䅁兂䅁䅁䅁䅷浈䅑䅅䅁䉁䅁䅁兂煃搸乊湙祁䅑杷允䅁䅁䅕䅁䑁䅁䅷䅁䭁䉁䄰䅁䭁䅁䅅䅁䭁䅁䅕䅁䙁䅁䅁䅁䅃⭮䅖允䅁䅁䅅䅁䙁乁橥䑣䬰㤱⽍䍄䉁䅁䅁䅂䅁䅁䅍䅄䅁䅁䅯睔䅁䅁䅯杔䅁䅁䅕䅁䅁䥁䥁欵䉁䅁䅁允䅁䅁䅕䥘䌯匹捨啅䵁䅉䅅䅁䙁䅁䅁睁䵁䅁䅁权䅁䅁䅁权呂䅁䅁权䙁䅁䅁兂䅁䅁䅁䝑浪䅑䅅䅁䉁䅁䅁兂啂㘴扗佸穁䅑杷允䅁䅁䅕䅁䑁䅁䅷䅁䭁䉁䄴䅁䭁䙁䅍䅁䭁䅁䅕䅁䙁䅁䅁䅁䅁⭂䅚允䅁䅁䅅䅁䙁䅁䅁䅁䅁䍁䅰䍄䉁䅁䅁䅂䅁䅁䅍䅄䅁䅁䅯睔䅁䅁䅯杔䅁䅁䅕䅁䅁䵁塃唵䉁䅁䅁允䅁䅁䅕瑃橥䑣䬰穸䴸䅉䅅䅁䙁䅁䅁睁䵁䅁䅁权䅁䅁䅁权䉁䅁䅁权䙁䅁䅁兂䅁䅁䅁䐴洳䅑䅅䅁䉁䅁䅁兂㑃潈牘払敪睐杷允䅁䅁䅑䅁䑁䅁䅷䅁䭁䕁䄸䅁䭁䕁䄴䅁䙁䅁䅁䅁䅄⭎䅚允䅁䅁䅅䅁䙁䵁ㅐ䙋偹桷䅂䍄䉁䅁䅁兂䅁䅁䅍䅄䅁䅁䅯䅁䅁䅁䅯允䅁䅁䅯兂䅁䅁䅕䅁䅁䥁㡄唵䉁䅁䅁允䅁䅁䅕䉵䘶ㄶ㑇樳䴸䅉䅅䅁䙁䅁䅁睁䵁䅁䅁权䅁䅁䅁权呂䅁䅁权䙁䅁䅁兂䅁䅁䅁余汪䅑䅅䅁䉁䅁䅁兂穁積積㕍祍䅑杷允䅁䅁䅕䅁䑁䅁䅷䅁䭁䅁䅁䅁䭁䅁䅅䅁䭁䅁䅕䅁䙁䅁䅁䅁䅁佚䅚允䅁䅁䅅䅁䙁䱁敧敨剴乵⼴䍄䉁䅁䅁兂䅁䅁䅍䅄䅁䅁䅯睈䅁䅁䅯睕䅁䅁䅯兂䅁䅁䅕䅁䅁䵁浄唵䉁䅁䅁允䅁䅁䅕灶愸㥌䔱䕍䵁䅉䅅䅁䙁䅁䅁睁䵁䅁䅁权䅁䅁䅁权䉁䅁䅁权䙁䅁䅁兂䅁䅁䅁䉑浮䅑䅅䅁䉁䅁䅁兂㑃潈牘払敪睐杷允䅁䅁䅕䅁䑁䅁䅷䅁䭁䉁䅷䅁䭁䙁䅍䅁䭁䅁䅕䅁䙁䅁䅁䅁杂何䅚允䅁䅁䅅䅁䙁乁欰潂噇祑䄵䍄䉁䅁䅁䅂䅁䅁䅍䅄䅁䅁䅯睔䅁䅁䅯杔䅁䅁䅕䅁䅁䕁啄唵䉁䅁䅁允䅁䅁䅕瑃橥䑣䬰啂䵁䅉䅅䅁䕁䅁䅁睁䵁䅁䅁权偂䅁䅁权佂䅁䅁兂䅁䅁䅁偁汦䅑䅅䅁䉁䅁䅁兂㉄䙋偹癷剕䅑杷允䅁䅁䅕䅁䑁䅁䅷䅁䭁䉁䄸䅁䭁䙁䅍䅁䭁䅁䅕䅁䙁䅁䅁䅁䅂攫䅖允䅁䅁䅅䅁䙁䵁㌯⭕汏穥䅂䍄䉁䅁䅁兂䅁䅁䅍䅄䅁䅁䅯杈䅁䅁䅯睕䅁䅁䅯兂䅁䅁䅕䅁䅁䍁獃唵䉁䅁䅁允䅁䅁䅕㝤昶楇搸か䵁䅉䅅䅁䙁䅁䅁睁䵁䅁䅁权䅁䅁䅁权䉁䅁䅁权䙁䅁䅁兂䅁䅁䅁䩁汘䅑䅅䅁䉁䅁䅁兂慃婭婭婭婮睐杷允䅁䅁䅕䅁䑁䅁䅷䅁䭁䉁䄰䅁䭁䅁䅅䅁䭁䅁䅕䅁䙁䅁䅁䅁权佘䅚允䅁䅁䅅䅁䙁䭁䠵場啯瑲⽣䍄䉁䅁䅁兂䅁䅁䅍䅄䅁䅁䅯䅁䅁䅁䅯允䅁䅁䅯兂䅁䅁䅕䅁䅁䥁桁欵䉁䅁䅁允䅁䅁䅕䉵䘶ㄶ㑇樳䴸䅉䅅䅁䕁䅁䅁睁䵁䅁䅁权偂䅁䅁权佂䅁䅁兂䅁䅁䅁䑉浦䅑䅅䅁䉁䅁䅁兂㉄䙋偹癷兕䅑杷允䅁䅁䅕䅁䑁䅁䅷䅁䭁䉁䄰䅁䭁䅁䅅䅁䭁䅁䅕䅁䙁䅁䅁䅁杁畚䅚允䅁䅁䅅䅁䙁䭁䠵場啯瑲⽣䍄䉁䅁䅁兂䅁䅁䅍䅄䅁䅁䅯䅈䅁䅁䅯允䅁䅁䅯兂䅁䅁䅕䅁䅁佁牂欵䉁䅁䅁允䅁䅁䅕椹捨㡪ㅌ䐲䴸䅉䅅䅁䙁䅁䅁睁䵁䅁䅁权摁䅁䅁权呂䅁䅁权䙁䅁䅁兂䅁䅁䅁䠴浈䅑䅅䅁䉁䅁䅁兂睄㡰䱚㡎瑫䅑杷允䅁䅁䅕䅁䑁䅁䅷䅁䭁䅁䅁䅁䭁䙁䅍䅁䭁䅁䅕䅁䙁䅁䅁䅁䅂畦䅚允䅁䅁䅅䅁䙁偁唷佥浫吸䅎䍄䉁䅁䅁䅂䅁䅁䅍䅄䅁䅁䅯睔䅁䅁䅯杔䅁䅁䅕䅁䅁䍁湁欵䉁䅁䅁允䅁䅁䅕䭆䠵場啯歅䵁䅉䅅䅁䙁䅁䅁睁䵁䅁䅁权晁䅁䅁权呂䅁䅁权䙁䅁䅁兂䅁䅁䅁䵙汘䅑䅅䅁䉁䅁䅁兂䩄牤昶楇砸䅑杷允䅁䅁䅑䅁䑁䅁䅷䅁䭁䕁䄸䅁䭁䕁䄴䅁䙁䅁䅁䅁䅁⭎䅚允䅁䅁䅅䅁䙁䅁塲㍯㥁桃䅆䍄䉁䅁䅁兂䅁䅁䅍䅄䅁䅁䅯杇䅁䅁䅯允䅁䅁䅯兂䅁䅁䅕䅁䅁䕁ㅄ唵䉁䅁䅁允䅁䅁䅕積積積積稴䴸䅉䅅䅁䙁䅁䅁睁䵁䅁䅁权敁䅁䅁权呂䅁䅁权䙁䅁䅁兂䅁䅁䅁义汦䅑䅅䅁䉁䅁䅁兂汁潂噇㑑獳䅑杷允䅁䅁䅕䅁䑁䅁䅷䅁䭁䉁䄰䅁䭁䙁䅍䅁䭁䅁䅕䅁䙁䅁䅁䅁杂敃䅚允䅁䅁䅅䅁䙁䩁畨潅䅐楓䄵䍄䉁䅁䅁䅂䅁䅁䅍䅄䅁䅁䅯睔䅁䅁䅯杔䅁䅁䅕䅁䅁䍁桄唵䉁䅁䅁允䅁䅁䅕敨剴䉵䘶ぃ䵁䅉䅅䅁䙁䅁䅁睁䵁䅁䅁权敁䅁䅁权䉁䅁䅁权䙁䅁䅁兂䅁䅁䅁䅑浐䅑䅅䅁䉁䅁䅁兂㝂䭆䠵場啲睐杷允䅁䅁䅕䅁䑁䅁䅷䅁䭁䉁䄸䅁䭁䙁䅍䅁䭁䅁䅕䅁䙁䅁䅁䅁䅂畗䅚允䅁䅁䅅䅁䙁乁楅⼲⭬橃䅆䍄䉁䅁䅁䅂䅁䅁䅍䅄䅁䅁䅯睔䅁䅁䅯杔䅁䅁䅕䅁䅁䥁㝄唵䉁䅁䅁允䅁䅁䅕捺䵺䵺䵺䕄䵁䅉䅅䅁䙁䅁䅁睁䵁䅁䅁权捁䅁䅁权呂䅁䅁权䙁䅁䅁兂䅁䅁䅁偯汲䅑䅅䅁䉁䅁䅁兂敂歵䵫流瑳䅑杷允䅁䅁䅕䅁䑁䅁䅷䅁䭁䉁䄴䅁䭁䙁䅍䅁䭁䅁䅕䅁䙁䅁䅁䅁杂⭍䅚允䅁䅁䅅䅁䙁䕁桪桥畓祒䅚䍄䉁䅁䅁兂䅁䅁䅍䅄䅁䅁䅯䅁䅁䅁䅯睕䅁䅁䅯兂䅁䅁䅕䅁䅁䵁㑁欵䉁䅁䅁允䅁䅁䅕䅁䅁䅁权き䵁䅉䅅䅁䙁䅁䅁睁䵁䅁䅁权䅁䅁䅁权䉁䅁䅁权䙁䅁䅁兂䅁䅁䅁佯汈䅑䅅䅁䉁䅁䅁兂桄桥畓⭒慈睐杷允䅁䅁䅕䅁䑁䅁䅷䅁䭁䉁䄴䅁䭁䙁䅍䅁䭁䅁䅕䅁䙁䅁䅁䅁杂佗䅚允䅁䅁䅅䅁䙁乁㕶浦㡱䍤䅊䍄䉁䅁䅁兂䅁䅁䅍䅄䅁䅁䅯睈䅁䅁䅯睕䅁䅁䅯兂䅁䅁䅕䅁䅁佁㙄唵䉁䅁䅁允䅁䅁䅕⽺呤㘴㝖䕍䵁䅉䅅䅁䙁䅁䅁睁䵁䅁䅁权敁䅁䅁权呂䅁䅁权䙁䅁䅁兂䅁䅁䅁䴴汪䅑䅅䅁䉁䅁䅁兂硂児塲穯獁䅑杷允䅁䅁䅕䅁䑁䅁䅷䅁䭁䉁䄸䅁䭁䅁䅅䅁䭁䅁䅕䅁䙁䅁䅁䅁杁敔䅚允䅁䅁䅅䅁䙁䭁睒児塲⭯⽁䍄䉁䅁䅁䅂䅁䅁䅍䅄䅁䅁䅯睔䅁䅁䅯杔䅁䅁䅕䅁䅁佁硄唵䉁䅁䅁允䅁䅁䅕場啯歲桦歄䵁䅉䅅䅁䙁䅁䅁睁䵁䅁䅁权慁䅁䅁权呂䅁䅁权䙁䅁䅁兂䅁䅁䅁䑯浮䅑䅅䅁䉁䅁䅁兂䙄䱉祂䑡㝅䅑杷允䅁䅁䅑䅁䑁䅁䅷䅁䭁䕁䄸䅁䭁䕁䄴䅁䙁䅁䅁䅁䅂敋䅚允䅁䅁䅅䅁䙁乁橥䑣䬰砱䅆䍄䉁䅁䅁兂䅁䅁䅍䅄䅁䅁䅯杈䅁䅁䅯允䅁䅁䅯兂䅁䅁䅕䅁䅁䍁慂欵䉁䅁䅁允䅁䅁䅕⽷潕䥘䌯吱䴸䅉䅅䅁䙁䅁䅁睁䵁䅁䅁权䅁䅁䅁权呂䅁䅁权䙁䅁䅁兂䅁䅁䅁䡧浌䅑䅅䅁䉁䅁䅁兂啂㘴扗䅸ぁ䅑杷允䅁䅁䅕䅁䑁䅁䅷䅁䭁䉁䄴䅁䭁䙁䅍䅁䭁䅁䅕䅁䙁䅁䅁䅁杄畎䅚允䅁䅁䅅䅁䙁䕁桪桥畓祒䅚䍄䉁䅁䅁兂䅁䅁䅍䅄䅁䅁䅯杈䅁䅁䅯睕䅁䅁䅯兂䅁䅁䅕䅁䅁䵁䡂欵䉁䅁䅁允䅁䅁䅕渷⽷噎㘴䕊䵁䅉䅅䅁䕁䅁䅁睁䵁䅁䅁权偂䅁䅁权佂䅁䅁兂䅁䅁䅁䐴浢䅑䅅䅁䉁䅁䅁兂灁䥘䌯匹剧䅑杷允䅁䅁䅕䅁䑁䅁䅷䅁䭁䉁䅷䅁䭁䅁䅅䅁䭁䅁䅕䅁䙁䅁䅁䅁杁位䅚允䅁䅁䅅䅁䙁偁潙䥘䌯搹⽧䍄䉁䅁䅁䅂䅁䅁䅍䅄䅁䅁䅯睔䅁䅁䅯杔䅁䅁䅕䅁䅁䅁䥄唵䉁䅁䅁允䅁䅁䅕䅁䅁䅁䅁䐯䴸䅉䅅䅁䕁䅁䅁睁䵁䅁䅁权偂䅁䅁权佂䅁䅁兂䅁䅁䅁䑙浢䅑䅅䅁䉁䅁䅁兂㉄䙋偹癷兕䅑杷允䅁䅁䅕䅁䑁䅁䅷䅁䭁䉁䄸䅁䭁䙁䅍䅁䭁䅁䅕䅁䙁䅁䅁䅁䅂教䅚允䅁䅁䅅䅁䙁乁楅⼲⭬橃䅆䍄䉁䅁䅁兂䅁䅁䅍䅄䅁䅁䅯䅈䅁䅁䅯睕䅁䅁䅯兂䅁䅁䅕䅁䅁䍁呂欵䉁䅁䅁允䅁䅁䅕匳䝑婧䑖歌䵁䅉䅅䅁䙁䅁䅁睁䵁䅁䅁权晁䅁䅁权䉁䅁䅁权䙁䅁䅁兂䅁䅁䅁䩧汪䅑䅅䅁䉁䅁䅁兂卂䉵䘶ㄶ杈睐杷允䅁䅁䅕䅁䑁䅁䅷䅁䭁䉁䅷䅁䭁䙁䅍䅁䭁䅁䅕䅁䙁䅁䅁䅁䅄佃䅚允䅁䅁䅅䅁䙁偁潙䥘䌯卤䄱䍄䉁䅁䅁兂䅁䅁䅍䅄䅁䅁䅯睈䅁䅁䅯睕䅁䅁䅯兂䅁䅁䅕䅁䅁䭁ㅁ欵䉁䅁䅁允䅁䅁䅕穐敖歵獫啍䵁䅉䅅䅁䕁䅁䅁睁䵁䅁䅁权偂䅁䅁权佂䅁䅁兂䅁䅁䅁䑑浢䅑䅅䅁䉁䅁䅁兂䑄匹捨㡪光䅑杷允䅁䅁䅕䅁䑁䅁䅷䅁䭁䉁䄰䅁䭁䙁䅍䅁䭁䅁䅕䅁䙁䅁䅁䅁杄甫䅖允䅁䅁䅅䅁䙁䝁汄䌰扌匫䄱䍄䉁䅁䅁兂䅁䅁䅍䅄䅁䅁䅯䅁䅁䅁䅯允䅁䅁䅯兂䅁䅁䅕䅁䅁䵁摄唵䉁䅁䅁允䅁䅁䅕場啯歲桦樲䴸䅉䅅䅁䕁䅁䅁睁䵁䅁䅁权偂䅁䅁权佂䅁䅁兂䅁䅁䅁䍉浄䅑䅅䅁䉁䅁䅁兂偃癷潕䥘儸䅑杷允䅁䅁䅕䅁䑁䅁䅷䅁䭁䉁䄸䅁䭁䙁䅍䅁䭁䅁䅕䅁䙁䅁䅁䅁䅁救䅚允䅁䅁䅅䅁䙁䑁䩥坑汄䑍䅆䍄䉁䅁䅁兂䅁䅁䅍䅄䅁䅁䅯䅈䅁䅁䅯睕䅁䅁䅯兂䅁䅁䅕䅁䅁佁⽁欵䉁䅁䅁允䅁䅁䅕㥆佮ㄹ橏歌䵁䅉䅅䅁䙁䅁䅁睁䵁䅁䅁权摁䅁䅁权呂䅁䅁权䙁䅁䅁兂䅁䅁䅁䱙汄䅑䅅䅁䉁䅁䅁兂䭁㘱睎捐瑯䅑杷允䅁䅁䅑䅁䑁䅁䅷䅁䭁䕁䄸䅁䭁䕁䄴䅁䙁䅁䅁䅁杁畎䅚允䅁䅁䅅䅁䙁乁橥䑣䬰砱䅂䍄䉁䅁䅁兂䅁䅁䅍䅄䅁䅁䅯䅁䅁䅁䅯睕䅁䅁䅯兂䅁䅁䅕䅁䅁䕁䱄唵䉁䅁䅁允䅁䅁䅕敢㝦晱祈歍䵁䅉䅅䅁䙁䅁䅁睁䵁䅁䅁权䅁䅁䅁权呂䅁䅁权䙁䅁䅁兂䅁䅁䅁乷氳䅑䅅䅁䉁䅁䅁兂婁䙂余摌祉䅑杷允䅁䅁䅑䅁䑁䅁䅷䅁䭁䕁䄸䅁䭁䕁䄴䅁䙁䅁䅁䅁杂⭅䅚允䅁䅁䅅䅁䙁䕁桪桥畓硒䅎䍄䉁䅁䅁䅂䅁䅁䅍䅄䅁䅁䅯睔䅁䅁䅯杔䅁䅁䅕䅁䅁䭁穁欵䉁䅁䅁允䅁䅁䅕㑈牘払敧歅䵁䅉䅅䅁䙁䅁䅁睁䵁䅁䅁权捁䅁䅁权䉁䅁䅁权䙁䅁䅁兂䅁䅁䅁倴汪䅑䅅䅁䉁䅁䅁兂晁敨剴䉵嘷睐杷允䅁䅁䅑䅁䑁䅁䅷䅁䭁䕁䄸䅁䭁䕁䄴䅁䙁䅁䅁䅁权當䅖允䅁䅁䅅䅁䙁䥁牘払敧敨⽳䍄䉁䅁䅁䅂䅁䅁䅍䅄䅁䅁䅯睔䅁䅁䅯杔䅁䅁䅕䅁䅁䵁睁欵䉁䅁䅁允䅁䅁䅕硥畓⭒㙆歅䵁䅉䅅䅁䙁䅁䅁睁䵁䅁䅁权敁䅁䅁权䉁䅁䅁权䙁䅁䅁兂䅁䅁䅁䉙浶䅑䅅䅁䉁䅁䅁兂䑄匹捨㡪噌睐杷允䅁䅁䅑䅁䑁䅁䅷䅁䭁䕁䄸䅁䭁䕁䄴䅁䙁䅁䅁䅁䅃⭍䅚允䅁䅁䅅䅁䙁䵁䴳䵺䵺䉺䅆䍄䉁䅁䅁䅂䅁䅁䅍䅄䅁䅁䅯睔䅁䅁䅯杔䅁䅁䅕䅁䅁䥁㥄唵䉁䅁䅁允䅁䅁䅕椹捨㡪ㅌ歄䵁䅉䅅䅁䙁䅁䅁睁䵁䅁䅁权慁䅁䅁权䉁䅁䅁权䙁䅁䅁兂䅁䅁䅁䉑浶䅑䅅䅁䉁䅁䅁兂歃䑣䬰㘱潐睐杷允䅁䅁䅕䅁䑁䅁䅷䅁䭁䉁䄴䅁䭁䅁䅅䅁䭁䅁䅕䅁䙁䅁䅁䅁杁佗䅚允䅁䅁䅅䅁䙁䵁ㅐ䙋偹瑷⽕䍄䉁䅁䅁兂䅁䅁䅍䅄䅁䅁䅯杇䅁䅁䅯睕䅁䅁䅯兂䅁䅁䅕䅁䅁䭁䑁欵䉁䅁䅁允䅁䅁䅕牒穢搯契歏䵁䅉䅅䅁䙁䅁䅁睁䵁䅁䅁权捁䅁䅁权呂䅁䅁权䙁䅁䅁兂䅁䅁䅁䍙浦䅑䅅䅁䉁䅁䅁兂偃癷潕䅘甸䅑杷允䅁䅁䅑䅁䑁䅁䅷䅁䭁䕁䄸䅁䭁䕁䄴䅁䙁䅁䅁䅁权⭋䅚允䅁䅁䅅䅁䙁䅁塲㍯㥁桃䅎䍄䉁䅁䅁兂䅁䅁䅍䅄䅁䅁䅯先䅁䅁䅯允䅁䅁䅯兂䅁䅁䅕䅁䅁䥁獄唵䉁䅁䅁允䅁䅁䅕㘱睎児塲稰䴸䅉䅅䅁䙁䅁䅁睁䵁䅁䅁权晁䅁䅁权䉁䅁䅁权䙁䅁䅁兂䅁䅁䅁䉙洷䅑䅅䅁䉁䅁䅁兂㉄䙋偹癷杘睐杷允䅁䅁䅑䅁䑁䅁䅷䅁䭁䕁䄸䅁䭁䕁䄴䅁䙁䅁䅁䅁䅁⭸䅖允䅁䅁䅅䅁䙁䡁㥅瑃橥偣⽫䍄䉁䅁䅁兂䅁䅁䅍䅄䅁䅁䅯杈䅁䅁䅯允䅁䅁䅯兂䅁䅁䅕䅁䅁䝁㑄唵䉁䅁䅁允䅁䅁䅕硥畓⭒㙆䐱䴸䅉䅅䅁䙁䅁䅁睁䵁䅁䅁权䅁䅁䅁权呂䅁䅁权䙁䅁䅁兂䅁䅁䅁䡁洳䅑䅅䅁䉁䅁䅁兂啂㘴扗䅸ぁ䅑杷允䅁䅁䅑䅁䑁䅁䅷䅁䭁䕁䄸䅁䭁䕁䄴䅁䙁䅁䅁䅁䅄畍䅚允䅁䅁䅅䅁䙁䱁敧敨剴䉵䅆䍄䉁䅁䅁兂䅁䅁䅍䅄䅁䅁䅯先䅁䅁䅯睕䅁䅁䅯兂䅁䅁䅕䅁䅁䵁㑂欵䉁䅁䅁允䅁䅁䅕䬸䝦穓䩦啌䵁䅉䅅䅁䕁䅁䅁睁䵁䅁䅁权偂䅁䅁权佂䅁䅁兂䅁䅁䅁偁汈䅑䅅䅁䉁䅁䅁兂䙃ㄶ㑇潈偕䅑杷允䅁䅁䅕䅁䑁䅁䅷䅁䭁䅁䅁䅁䭁䙁䅍䅁䭁䅁䅕䅁䙁䅁䅁䅁䅂攫䅖允䅁䅁䅅䅁䙁䍁捬㡪ㅌ䑡䅊䍄䉁䅁䅁䅂䅁䅁䅍䅄䅁䅁䅯睔䅁䅁䅯杔䅁䅁䅕䅁䅁䥁流欵䉁䅁䅁允䅁䅁䅕硥畓⭒㙆啅䵁䅉䅅䅁䙁䅁䅁睁䵁䅁䅁权慁䅁䅁权呂䅁䅁权䙁䅁䅁兂䅁䅁䅁乷氯䅑䅅䅁䉁䅁䅁兂䑄匹捨⭪㕉䅑杷允䅁䅁䅕䅁䑁䅁䅷䅁䭁䉁䅷䅁䭁䅁䅅䅁䭁䅁䅕䅁䙁䅁䅁䅁杄異䅖允䅁䅁䅅䅁䙁䥁䌯匹捨㥪⽉䍄䉁䅁䅁䅂䅁䅁䅍䅄䅁䅁䅯睔䅁䅁䅯杔䅁䅁䅕䅁䅁䭁塃唵䉁䅁䅁允䅁䅁䅕⽷潕䥘䌯呸䴸䅉䅅䅁䙁䅁䅁睁䵁䅁䅁权慁䅁䅁权䉁䅁䅁权䙁䅁䅁兂䅁䅁䅁䉷洯䅑䅅䅁䉁䅁䅁兂歃䑣䬰㘱潐睐杷允䅁䅁䅕䅁䑁䅁䅷䅁䭁䉁䄰䅁䭁䙁䅍䅁䭁䅁䅕䅁䙁䅁䅁䅁䅄⭷䅖允䅁䅁䅅䅁䙁䕁㍷啩杆匵䄱䍄䉁䅁䅁兂䅁䅁䅍䅄䅁䅁䅯杈䅁䅁䅯睕䅁䅁䅯兂䅁䅁䅕䅁䅁䭁楂欵䉁䅁䅁允䅁䅁䅕敫㠱穐敖歉䵁䅉䅅䅁䙁䅁䅁睁䵁䅁䅁权䅁䅁䅁权呂䅁䅁权䙁䅁䅁兂䅁䅁䅁䵧決䅑䅅䅁䉁䅁䅁兂瑂⼵灵昸祉䅑杷允䅁䅁䅑䅁䑁䅁䅷䅁䭁䕁䄸䅁䭁䕁䄴䅁䙁䅁䅁䅁权畍䅚允䅁䅁䅅䅁䙁䱁敧敨剴䉵䅆䍄䉁䅁䅁兂䅁䅁䅍䅄䅁䅁䅯杈䅁䅁䅯允䅁䅁䅯兂䅁䅁䅕䅁䅁佁䝂欵䉁䅁䅁允䅁䅁䅕⽷潕䥘䌯吱䴸䅉䅅䅁䙁䅁䅁睁䵁䅁䅁权敁䅁䅁权呂䅁䅁权䙁䅁䅁兂䅁䅁䅁䕷浢䅑䅅䅁䉁䅁䅁兂畄䑦ㄸ橘歯䅑杷允䅁䅁䅕䅁䑁䅁䅷䅁䭁䅁䅁䅁䭁䅁䅅䅁䭁䅁䅕䅁䙁䅁䅁䅁䅃改䅖允䅁䅁䅅䅁䙁䱁敧敨剴乵⼴䍄䉁䅁䅁兂䅁䅁䅍䅄䅁䅁䅯睈䅁䅁䅯睕䅁䅁䅯兂䅁䅁䅕䅁䅁䍁䑂欵䉁䅁䅁允䅁䅁䅕㑎䉬余睕啍䵁䅉䅅䅁䕁䅁䅁睁䵁䅁䅁权偂䅁䅁权佂䅁䅁兂䅁䅁䅁佁汘䅑䅅䅁䉁䅁䅁兂㉄䙋偹癷兕䅑杷允䅁䅁䅕䅁䑁䅁䅷䅁䭁䉁䅯䅁䭁䙁䅍䅁䭁䅁䅕䅁䙁䅁䅁䅁杄效䅚允䅁䅁䅅䅁䙁䱁穢搯㑒呩䅰䍄䉁䅁䅁兂䅁䅁䅍䅄䅁䅁䅯先䅁䅁䅯睕䅁䅁䅯兂䅁䅁䅕䅁䅁䅁汁欵䉁䅁䅁允䅁䅁䅕浚浚浚浢歌䵁䅉䅅䅁䕁䅁䅁睁䵁䅁䅁权偂䅁䅁权佂䅁䅁兂䅁䅁䅁䅯洯䅑䅅䅁䉁䅁䅁兂歃䑣䬰㘱卍䅑杷允䅁䅁䅕䅁䑁䅁䅷䅁䭁䉁䅷䅁䭁䅁䅅䅁䭁䅁䅕䅁䙁䅁䅁䅁杁教䅚允䅁䅁䅅䅁䙁偁潙䥘䌯搹⽧䍄䉁䅁䅁兂䅁䅁䅍䅄䅁䅁䅯睈䅁䅁䅯允䅁䅁䅯兂䅁䅁䅕䅁䅁䕁獂欵䉁䅁䅁允䅁䅁䅕牕敧敨剴䐴䴸䅉䅅䅁䕁䅁䅁睁䵁䅁䅁权偂䅁䅁权佂䅁䅁兂䅁䅁䅁䑉浌䅑䅅䅁䉁䅁䅁兂歃䑣䬰㘱前䅑杷允䅁䅁䅕䅁䑁䅁䅷䅁䭁䉁䄸䅁䭁䅁䅅䅁䭁䅁䅕䅁䙁䅁䅁䅁䅂甶䅖允䅁䅁䅅䅁䙁佁㙆䭆䠵搴⽯䍄䉁䅁䅁兂䅁䅁䅍䅄䅁䅁䅯䅁䅁䅁䅯允䅁䅁䅯兂䅁䅁䅕䅁䅁䥁呁欵䉁䅁䅁允䅁䅁䅕䉵䘶ㄶ㑇樳䴸䅉䅅䅁䙁䅁䅁睁䵁䅁䅁权捁䅁䅁权䉁䅁䅁权䙁䅁䅁兂䅁䅁䅁䵷汲䅑䅅䅁䉁䅁䅁兂穁積積積呐睐杷允䅁䅁䅕䅁䑁䅁䅷䅁䭁䉁䄸䅁䭁䅁䅅䅁䭁䅁䅕䅁䙁䅁䅁䅁权佚䅚允䅁䅁䅅䅁䙁偁潙䥘䌯改⽁䍄䉁䅁䅁䅂䅁䅁䅍䅄䅁䅁䅯睔䅁䅁䅯杔䅁䅁䅕䅁䅁䅁瑃唵䉁䅁䅁允䅁䅁䅕敨剴䉵䘶稲䴸䅉䅅䅁䕁䅁䅁睁䵁䅁䅁权偂䅁䅁权佂䅁䅁兂䅁䅁䅁䉉浮䅑䅅䅁䉁䅁䅁兂浂浚浚浚卙䅑杷允䅁䅁䅕䅁䑁䅁䅷䅁䭁䉁䄴䅁䭁䅁䅅䅁䭁䅁䅕䅁䙁䅁䅁䅁䅁⭱䅖允䅁䅁䅅䅁䙁䑁積積積㥍⽍䍄䉁䅁䅁兂䅁䅁䅍䅄䅁䅁䅯杈䅁䅁䅯睕䅁䅁䅯兂䅁䅁䅕䅁䅁䭁䕄唵䉁䅁䅁允䅁䅁䅕呣䬰㘱睍䕌䵁䅉䅅䅁䙁䅁䅁睁䵁䅁䅁权慁䅁䅁权䉁䅁䅁权䙁䅁䅁兂䅁䅁䅁䱷汢䅑䅅䅁䉁䅁䅁兂䅁䅁䅁䅁杄睐杷允䅁䅁䅕䅁䑁䅁䅷䅁䭁䉁䅷䅁䭁䅁䅅䅁䭁䅁䅕䅁䙁䅁䅁䅁䅂⭳䅖允䅁䅁䅅䅁䙁䥁䌯匹捨㥪⽉䍄䉁䅁䅁兂䅁䅁䅍䅄䅁䅁䅯杇䅁䅁䅯允䅁䅁䅯兂䅁䅁䅕䅁䅁䭁潄唵䉁䅁䅁允䅁䅁䅕椹捨㡪ㅌ䐴䴸䅉䅅䅁䙁䅁䅁睁䵁䅁䅁权晁䅁䅁权呂䅁䅁权䙁䅁䅁兂䅁䅁䅁䙁浲䅑䅅䅁䉁䅁䅁兂㥂穐敖極硫䅑杷允䅁䅁䅕䅁䑁䅁䅷䅁䭁䉁䅯䅁䭁䙁䅍䅁䭁䅁䅕䅁䙁䅁䅁䅁䅁畔䅚允䅁䅁䅅䅁䙁䕁㍷啩杆呒䅴䍄䉁䅁䅁兂䅁䅁䅍䅄䅁䅁䅯䅁䅁䅁䅯睕䅁䅁䅯兂䅁䅁䅕䅁䅁䍁汃唵䉁䅁䅁允䅁䅁䅕㘱睎児㍰啍䵁䅉䅅䅁䙁䅁䅁睁䵁䅁䅁权慁䅁䅁权呂䅁䅁权䙁䅁䅁兂䅁䅁䅁䙧浮䅑䅅䅁䉁䅁䅁兂䑄匹捨㉪㝉䅑杷允䅁䅁䅕䅁䑁䅁䅷䅁䭁䉁䅯䅁䭁䙁䅍䅁䭁䅁䅕䅁䙁䅁䅁䅁杁佖䅚允䅁䅁䅅䅁䙁䵁ㅐ䙋偹橙䅴䍄䉁䅁䅁兂䅁䅁䅍䅄䅁䅁䅯杈䅁䅁䅯睕䅁䅁䅯兂䅁䅁䅕䅁䅁䭁楃唵䉁䅁䅁允䅁䅁䅕㥉㕶浦㡰歋䵁䅉䅅䅁䙁䅁䅁睁䵁䅁䅁权摁䅁䅁权呂䅁䅁权䙁䅁䅁兂䅁䅁䅁䵑汘䅑䅅䅁䉁䅁䅁兂䵂㑎䉬余瑕䅑杷允䅁䅁䅑䅁䑁䅁䅷䅁䭁䕁䄸䅁䭁䕁䄴䅁䙁䅁䅁䅁杄敍䅚允䅁䅁䅅䅁䙁佁剸䉵䘶砶䅆䍄䉁䅁䅁兂䅁䅁䅍䅄䅁䅁䅯䅁䅁䅁䅯允䅁䅁䅯兂䅁䅁䅕䅁䅁䝁䍁欵䉁䅁䅁允䅁䅁䅕䉵䘶ㄶ㑇樳䴸䅉䅅䅁䙁䅁䅁睁䵁䅁䅁权摁䅁䅁权呂䅁䅁权䙁䅁䅁兂䅁䅁䅁偑汄䅑䅅䅁䉁䅁䅁兂浃㡭村䱳瑉䅑杷允䅁䅁䅕䅁䑁䅁䅷䅁䭁䉁䄸䅁䭁䙁䅍䅁䭁䅁䅕䅁䙁䅁䅁䅁杁敖䅚允䅁䅁䅅䅁䙁䡁⼰噎㘶呋䅆䍄䉁䅁䅁兂䅁䅁䅍䅄䅁䅁䅯䅁䅁䅁䅯睕䅁䅁䅯兂䅁䅁䅕䅁䅁䭁扃唵䉁䅁䅁允䅁䅁䅕㘱睎児㍲䕍䵁䅉䅅䅁䙁䅁䅁睁䵁䅁䅁权捁䅁䅁权䉁䅁䅁权䙁䅁䅁兂䅁䅁䅁佧汌䅑䅅䅁䉁䅁䅁兂穁積積積呐睐杷允䅁䅁䅑䅁䑁䅁䅷䅁䭁䕁䄸䅁䭁䕁䄴䅁䙁䅁䅁䅁杁伷䅖允䅁䅁䅅䅁䙁佁剸䉵䘶眶䄹䍄䉁䅁䅁兂䅁䅁䅍䅄䅁䅁䅯睈䅁䅁䅯允䅁䅁䅯兂䅁䅁䅕䅁䅁䝁桂欵䉁䅁䅁允䅁䅁䅕椹捨㡪ㅌ䐴䴸䅉䅅䅁䕁䅁䅁睁䵁䅁䅁权偂䅁䅁权佂䅁䅁兂䅁䅁䅁䍧洯䅑䅅䅁䉁䅁䅁兂塄㍯㥁瑃卣䅑杷允䅁䅁䅕䅁䑁䅁䅷䅁䭁䅁䅁䅁䭁䅁䅅䅁䭁䅁䅕䅁䙁䅁䅁䅁杂整䅖允䅁䅁䅅䅁䙁䩁婱婭婭摭⽫䍄䉁䅁䅁兂䅁䅁䅍䅄䅁䅁䅯睈䅁䅁䅯允䅁䅁䅯兂䅁䅁䅕䅁䅁䅁䩁欵䉁䅁䅁允䅁䅁䅕䅁䅁䅁䅁䐴䴸䅉䅅䅁䕁䅁䅁睁䵁䅁䅁权偂䅁䅁权佂䅁䅁兂䅁䅁䅁䉉浶䅑䅅䅁䉁䅁䅁兂㑃潈牘払內䅑杷允䅁䅁䅕䅁䑁䅁䅷䅁䭁䅁䅁䅁䭁䙁䅍䅁䭁䅁䅕䅁䙁䅁䅁䅁杄敭䅖允䅁䅁䅅䅁䙁乁橥䑣䬰稹䅂䍄䉁䅁䅁䅂䅁䅁䅍䅄䅁䅁䅯睔䅁䅁䅯杔䅁䅁䅕䅁䅁䅁坁欵䉁䅁䅁允䅁䅁䅕㑈牘払敧ぅ䵁䅉䅅䅁䕁䅁䅁睁䵁䅁䅁权偂䅁䅁权佂䅁䅁兂䅁䅁䅁䉑洯䅑䅅䅁䉁䅁䅁兂捂㡪ㅌ䙋偷䅑杷允䅁䅁䅕䅁䑁䅁䅷䅁䭁䉁䄴䅁䭁䙁䅍䅁䭁䅁䅕䅁䙁䅁䅁䅁䅃⬵䅖允䅁䅁䅅䅁䙁䡁㥅瑃橥䌸䅴䍄䉁䅁䅁兂䅁䅁䅍䅄䅁䅁䅯䅁䅁䅁䅯睕䅁䅁䅯兂䅁䅁䅕䅁䅁䅁杂欵䉁䅁䅁允䅁䅁䅕癱午坔兌き䵁䅉䅅䅁䙁䅁䅁睁䵁䅁䅁权慁䅁䅁权呂䅁䅁权䙁䅁䅁兂䅁䅁䅁䵁汲䅑䅅䅁䉁䅁䅁兂权楇搯䕊㙙䅑杷允䅁䅁䅕䅁䑁䅁䅷䅁䭁䉁䄴䅁䭁䅁䅅䅁䭁䅁䅕䅁䙁䅁䅁䅁䅁⭇䅚允䅁䅁䅅䅁䙁䵁ㅐ䙋偹瑷⽕䍄䉁䅁䅁䅂䅁䅁䅍䅄䅁䅁䅯睔䅁䅁䅯杔䅁䅁䅕䅁䅁䍁畁欵䉁䅁䅁允䅁䅁䅕䡰㥁瑃橥歅䵁䅉䅅䅁䙁䅁䅁睁䵁䅁䅁权䅁䅁䅁权呂䅁䅁权䙁䅁䅁兂䅁䅁䅁䡁浌䅑䅅䅁䉁䅁䅁兂啂㘴扗䅸ぁ䅑杷允䅁䅁䅕䅁䑁䅁䅷
A5: 䅁䭁䉁䅯䅁䭁䅁䅅䅁䭁䅁䅕䅁䙁䅁䅁䅁䅄伵䅖允䅁䅁䅅䅁䙁偁潙䥘䌯改⽁䍄䉁䅁䅁兂䅁䅁䅍䅄䅁䅁䅯先䅁䅁䅯允䅁䅁䅯兂䅁䅁䅕䅁䅁䍁獄唵䉁䅁䅁允䅁䅁䅕㘱睎児塲稰䴸䅉䅅䅁䙁䅁䅁睁䵁䅁䅁权晁䅁䅁权䉁䅁䅁权䙁䅁䅁兂䅁䅁䅁伴汔䅑䅅䅁䉁䅁䅁兂㥁瑃橥䑣愳睐杷允䅁䅁䅕䅁䑁䅁䅷䅁䭁䉁䅯䅁䭁䙁䅍䅁䭁䅁䅕䅁䙁䅁䅁䅁杄畔䅚允䅁䅁䅅䅁䙁䕁㍷啩杆呒䅴䍄䉁䅁䅁兂䅁䅁䅍䅄䅁䅁䅯先䅁䅁䅯允䅁䅁䅯兂䅁䅁䅕䅁䅁佁坂欵䉁䅁䅁允䅁䅁䅕歲桦桥畓稱䴸䅉䅅䅁䕁䅁䅁睁䵁䅁䅁权偂䅁䅁权佂䅁䅁兂䅁䅁䅁䍙浘䅑䅅䅁䉁䅁䅁兂偃癷潕䥘券䅑杷允䅁䅁䅕䅁䑁䅁䅷䅁䭁䉁䄰䅁䭁䙁䅍䅁䭁䅁䅕䅁䙁䅁䅁䅁杁畯䅖允䅁䅁䅅䅁䙁䕁㉡⼸唳䍥䄱䍄䉁䅁䅁兂䅁䅁䅍䅄䅁䅁䅯杈䅁䅁䅯允䅁䅁䅯兂䅁䅁䅕䅁䅁䝁䕄唵䉁䅁䅁允䅁䅁䅕積積積積稰䴸䅉䅅䅁䙁䅁䅁睁䵁䅁䅁权摁䅁䅁权呂䅁䅁权䙁䅁䅁兂䅁䅁䅁䡷浮䅑䅅䅁䉁䅁䅁兂睄㡰䱚㡎瑫䅑杷允䅁䅁䅕䅁䑁䅁䅷䅁䭁䅁䅁䅁䭁䅁䅅䅁䭁䅁䅕䅁䙁䅁䅁䅁䅂佣䅚允䅁䅁䅅䅁䙁䱁敧敨剴乵⼴䍄䉁䅁䅁兂䅁䅁䅍䅄䅁䅁䅯先䅁䅁䅯允䅁䅁䅯兂䅁䅁䅕䅁䅁䵁㕄唵䉁䅁䅁允䅁䅁䅕㑈牘払敧吱䴸䅉䅅䅁䙁䅁䅁睁䵁䅁䅁权䅁䅁䅁权䉁䅁䅁权䙁䅁䅁兂䅁䅁䅁䅉浄䅑䅅䅁䉁䅁䅁兂㑃潈牘払敪睐杷允䅁䅁䅕䅁䑁䅁䅷䅁䭁䅁䅁䅁䭁䙁䅍䅁䭁䅁䅕䅁䙁䅁䅁䅁䅂畋䅚允䅁䅁䅅䅁䙁佁兘瑉㕶橐䅎䍄䉁䅁䅁兂䅁䅁䅍䅄䅁䅁䅯䅁䅁䅁䅯睕䅁䅁䅯兂䅁䅁䅕䅁䅁䥁奃唵䉁䅁䅁允䅁䅁䅕䡶呓䅇㉒䕍䵁䅉䅅䅁䙁䅁䅁睁䵁䅁䅁权慁䅁䅁权䉁䅁䅁权䙁䅁䅁兂䅁䅁䅁䝉浪䅑䅅䅁䉁䅁䅁兂歃䑣䬰㘱潐睐杷允䅁䅁䅕䅁䑁䅁䅷䅁䭁䉁䅯䅁䭁䙁䅍䅁䭁䅁䅕䅁䙁䅁䅁䅁权畧䅚允䅁䅁䅅䅁䙁䡁灮橊䥅䐷䅰䍄䉁䅁䅁䅂䅁䅁䅍䅄䅁䅁䅯睔䅁䅁䅯杔䅁䅁䅕䅁䅁䅁獃唵䉁䅁䅁允䅁䅁䅕児塲㍯㥁樲䴸䅉䅅䅁䙁䅁䅁睁䵁䅁䅁权摁䅁䅁权呂䅁䅁权䙁䅁䅁兂䅁䅁䅁䝑洷䅑䅅䅁䉁䅁䅁兂㍁啩杆刵畁䅑杷允䅁䅁䅑䅁䑁䅁䅷䅁䭁䕁䄸䅁䭁䕁䄴䅁䙁䅁䅁䅁䅃⭋䅚允䅁䅁䅅䅁䙁䑁䬰㘱睎剐䅎䍄䉁䅁䅁兂䅁䅁䅍䅄䅁䅁䅯䅁䅁䅁䅯睕䅁䅁䅯兂䅁䅁䅕䅁䅁䅁汁欵䉁䅁䅁允䅁䅁䅕搵楁⼲⭫き䵁䅉䅅䅁䕁䅁䅁睁䵁䅁䅁权偂䅁䅁权佂䅁䅁兂䅁䅁䅁䍉浶䅑䅅䅁䉁䅁䅁兂㥁瑃橥䑣吰䅑杷允䅁䅁䅕䅁䑁䅁䅷䅁䭁䉁䄰䅁䭁䙁䅍䅁䭁䅁䅕䅁䙁䅁䅁䅁杁⭂䅚允䅁䅁䅅䅁䙁䩁畨潅䅐楓䄵䍄䉁䅁䅁䅂䅁䅁䅍䅄䅁䅁䅯睔䅁䅁䅯杔䅁䅁䅕䅁䅁䵁煁欵䉁䅁䅁允䅁䅁䅕牕敧敨剴ぅ䵁䅉䅅䅁䙁䅁䅁睁䵁䅁䅁权䅁䅁䅁权呂䅁䅁权䙁䅁䅁兂䅁䅁䅁䍉浔䅑䅅䅁䉁䅁䅁兂汄䌰扌含稴䅑杷允䅁䅁䅕䅁䑁䅁䅷䅁䭁䉁䅯䅁䭁䙁䅍䅁䭁䅁䅕䅁䙁䅁䅁䅁杁⭙䅚允䅁䅁䅅䅁䙁䱁昶楇搯䑚䅴䍄䉁䅁䅁䅂䅁䅁䅍䅄䅁䅁䅯睔䅁䅁䅯杔䅁䅁䅕䅁䅁䭁煁欵䉁䅁䅁允䅁䅁䅕㑈牘払敧ぅ䵁䅉䅅䅁䙁䅁䅁睁䵁䅁䅁权䅁䅁䅁权䉁䅁䅁权䙁䅁䅁兂䅁䅁䅁䅷浮䅑䅅䅁䉁䅁䅁兂㑃潈牘払敪睐杷允䅁䅁䅕䅁䑁䅁䅷䅁䭁䉁䄴䅁䭁䙁䅍䅁䭁䅁䅕䅁䙁䅁䅁䅁杂⬷䅖允䅁䅁䅅䅁䙁䡁潎敫㠱祐䅸䍄䉁䅁䅁兂䅁䅁䅍䅄䅁䅁䅯䅁䅁䅁䅯允䅁䅁䅯兂䅁䅁䅕䅁䅁佁权唵䉁䅁䅁允䅁䅁䅕灭婭婭婭吲䴸䅉䅅䅁䙁䅁䅁睁䵁䅁䅁权䅁䅁䅁权䉁䅁䅁权䙁䅁䅁兂䅁䅁䅁乯汐䅑䅅䅁䉁䅁䅁兂桄桥畓⭒慈睐杷允䅁䅁䅑䅁䑁䅁䅷䅁䭁䕁䄸䅁䭁䕁䄴䅁䙁䅁䅁䅁䅂畋䅚允䅁䅁䅅䅁䙁䵁䴳䵺䵺䉺䅊䍄䉁䅁䅁兂䅁䅁䅍䅄䅁䅁䅯杇䅁䅁䅯睕䅁䅁䅯兂䅁䅁䅕䅁䅁䍁桂欵䉁䅁䅁允䅁䅁䅕灶愸㥌欱く䵁䅉䅅䅁䙁䅁䅁睁䵁䅁䅁权敁䅁䅁权䉁䅁䅁权䙁䅁䅁兂䅁䅁䅁䙷洳䅑䅅䅁䉁䅁䅁兂䅁䅁䅁䅁兄睐杷允䅁䅁䅑䅁䑁䅁䅷䅁䭁䕁䄸䅁䭁䕁䄴䅁䙁䅁䅁䅁䅁畲䅖允䅁䅁䅅䅁䙁䙁㑋潈牘摕⽧䍄䉁䅁䅁兂䅁䅁䅍䅄䅁䅁䅯睈䅁䅁䅯允䅁䅁䅯兂䅁䅁䅕䅁䅁䝁湁欵䉁䅁䅁允䅁䅁䅕体㙆䭆䠵吴䴸䅉䅅䅁䕁䅁䅁睁䵁䅁䅁权偂䅁䅁权佂䅁䅁兂䅁䅁䅁䴴汈䅑䅅䅁䉁䅁䅁兂畃⭒㙆䭆瘷睐杷允䅁䅁䅕䅁䑁䅁䅷䅁䭁䅁䅁䅁䭁䅁䅅䅁䭁䅁䅕䅁䙁䅁䅁䅁䅂攴䅖允䅁䅁䅅䅁䙁佁㙆䭆䠵搴⽯䍄䉁䅁䅁兂䅁䅁䅍䅄䅁䅁䅯杈䅁䅁䅯允䅁䅁䅯兂䅁䅁䅕䅁䅁佁㑂欵䉁䅁䅁允䅁䅁䅕䅁䅁䅁䅁䐰䴸䅉䅅䅁䙁䅁䅁睁䵁䅁䅁权䅁䅁䅁权呂䅁䅁权䙁䅁䅁兂䅁䅁䅁䝧浔䅑䅅䅁䉁䅁䅁兂煃搸乊瑙穁䅑杷允䅁䅁䅕䅁䑁䅁䅷䅁䭁䉁䄸䅁䭁䙁䅍䅁䭁䅁䅕䅁䙁䅁䅁䅁䅁敹䅖允䅁䅁䅅䅁䙁䕁䵯楁䡵樱䅂䍄䉁䅁䅁䅂䅁䅁䅍䅄䅁䅁䅯睔䅁䅁䅯杔䅁䅁䅕䅁䅁䭁䕁欵䉁䅁䅁允䅁䅁䅕体㙆䭆䠵啅䵁䅉䅅䅁䙁䅁䅁睁䵁䅁䅁权捁䅁䅁权呂䅁䅁权䙁䅁䅁兂䅁䅁䅁䍧浄䅑䅅䅁䉁䅁䅁兂祃敮渫杸畳䅑杷允䅁䅁䅕䅁䑁䅁䅷䅁䭁䅁䅁䅁䭁䙁䅍䅁䭁䅁䅕䅁䙁䅁䅁䅁权⬶䅖允䅁䅁䅅䅁䙁䑁積積積穫䅊䍄䉁䅁䅁䅂䅁䅁䅍䅄䅁䅁䅯睔䅁䅁䅯杔䅁䅁䅕䅁䅁䍁煃唵䉁䅁䅁允䅁䅁䅕噋偹癷潕䐳䴸䅉䅅䅁䙁䅁䅁睁䵁䅁䅁权晁䅁䅁权䉁䅁䅁权䙁䅁䅁兂䅁䅁䅁偷汌䅑䅅䅁䉁䅁䅁兂桄桥畓⭒慈睐杷允䅁䅁䅑䅁䑁䅁䅷䅁䭁䕁䄸䅁䭁䕁䄴䅁䙁䅁䅁䅁杁佷䅖允䅁䅁䅅䅁啁䅁䅅䅁䅁䅁䅁䍄䉁䅁䅁䅂䅁䅁䅍䅄䅁䅁䅯睔䅁䅁䅯杔䅁䅁䅕䅁䅁䅁煁欵䉁䅁䅁允䅁䅁䅕䭆䠵場啯ぅ䵁䅉䅅䅁䙁䅁䅁睁䵁䅁䅁权敁䅁䅁权呂䅁䅁权䙁䅁䅁兂䅁䅁䅁䡙浲䅑䅅䅁䉁䅁䅁兂灁䥘䌯圹桧䅑杷允䅁䅁䅑䅁䑁䅁䅷䅁䭁䕁䄸䅁䭁䕁䄴䅁䙁䅁䅁䅁杁敵䅖允䅁䅁䅅䅁䙁䝁浚浚浚畚⽙䍄䉁䅁䅁䅂䅁䅁䅍䅄䅁䅁䅯睔䅁䅁䅯杔䅁䅁䅕䅁䅁䵁瑃唵䉁䅁䅁允䅁䅁䅕椹捨㡪ㅌ䐲䴸䅉䅅䅁䕁䅁䅁睁䵁䅁䅁权偂䅁䅁权佂䅁䅁兂䅁䅁䅁䌴浪䅑䅅䅁䉁䅁䅁兂䭁㘱睎児卯䅑杷允䅁䅁䅕䅁䑁䅁䅷䅁䭁䉁䅷䅁䭁䅁䅅䅁䭁䅁䅕䅁䙁䅁䅁䅁䅃敢䅚允䅁䅁䅅䅁䙁偁潙䥘䌯搹⽧䍄䉁䅁䅁䅂䅁䅁䅍䅄䅁䅁䅯睔䅁䅁䅯杔䅁䅁䅕䅁䅁䅁潁欵䉁䅁䅁允䅁䅁䅕㡪ㅌ䙋偹啅䵁䅉䅅䅁䙁䅁䅁睁䵁䅁䅁权摁䅁䅁权䉁䅁䅁权䙁䅁䅁兂䅁䅁䅁䝯浺䅑䅅䅁䉁䅁䅁兂畃⭒㙆䭆堷睐杷允䅁䅁䅕䅁䑁䅁䅷䅁䭁䉁䅯䅁䭁䅁䅅䅁䭁䅁䅕䅁䙁䅁䅁䅁杁甲䅖允䅁䅁䅅䅁䙁偁潙䥘䌯改⽁䍄䉁䅁䅁䅂䅁䅁䅍䅄䅁䅁䅯睔䅁䅁䅯杔䅁䅁䅕䅁䅁䭁湁欵䉁䅁䅁允䅁䅁䅕呣䬰㘱睎啅䵁䅉䅅䅁䙁䅁䅁睁䵁䅁䅁权慁䅁䅁权䉁䅁䅁权䙁䅁䅁兂䅁䅁䅁䭙汮䅑䅅䅁䉁䅁䅁兂䅁䅁䅁䅁杄睐杷允䅁䅁䅑䅁䑁䅁䅷䅁䭁䕁䄸䅁䭁䕁䄴䅁䙁䅁䅁䅁杂畁䅚允䅁䅁䅅䅁䙁佁剸䉵䘶砶䅂䍄䉁䅁䅁兂䅁䅁䅍䅄䅁䅁䅯先䅁䅁䅯允䅁䅁䅯兂䅁䅁䅕䅁䅁䕁ㅁ欵䉁䅁䅁允䅁䅁䅕歲桦桥畓稱䴸䅉䅅䅁䕁䅁䅁睁䵁䅁䅁权偂䅁䅁权佂䅁䅁兂䅁䅁䅁䍯浢䅑䅅䅁䉁䅁䅁兂塄㍯㥁瑃剣䅑杷允䅁䅁䅕䅁䑁䅁䅷䅁䭁䅁䅁䅁䭁䅁䅅䅁䭁䅁䅕䅁䙁䅁䅁䅁杂伹䅖允䅁䅁䅅䅁䙁䥁牘払敧摨⽳䍄䉁䅁䅁䅂䅁䅁䅍䅄䅁䅁䅯睔䅁䅁䅯杔䅁䅁䅕䅁䅁䕁流欵䉁䅁䅁允䅁䅁䅕瑃橥䑣䬰啅䵁䅉䅅䅁䙁䅁䅁睁䵁䅁䅁权捁䅁䅁权呂䅁䅁权䙁䅁䅁兂䅁䅁䅁䉯洷䅑䅅䅁䉁䅁䅁兂祃敮渫杸畳䅑杷允䅁䅁䅕䅁䑁䅁䅷䅁䭁䉁䅯䅁䭁䙁䅍䅁䭁䅁䅕䅁䙁䅁䅁䅁权畵䅖允䅁䅁䅅䅁䙁䑁ㄸ牘䩰䐷䅬䍄䉁䅁䅁䅂䅁䅁䅍䅄䅁䅁䅯睔䅁䅁䅯杔䅁䅁䅕䅁䅁䭁㙄唵䉁䅁䅁允䅁䅁䅕䉵䘶ㄶ㑇歄䵁䅉䅅䅁䙁䅁䅁睁䵁䅁䅁权䅁䅁䅁权䉁䅁䅁权䙁䅁䅁兂䅁䅁䅁䍷浐䅑䅅䅁䉁䅁䅁兂㑃潈牘払敪睐杷允䅁䅁䅕䅁䑁䅁䅷䅁䭁䉁䅷䅁䭁䙁䅍䅁䭁䅁䅕䅁䙁䅁䅁䅁杄佑䅚允䅁䅁䅅䅁䙁䉁婦発呤祯䄵䍄䉁䅁䅁兂䅁䅁䅍䅄䅁䅁䅯䅁䅁䅁䅯允䅁䅁䅯兂䅁䅁䅕䅁䅁䅁歃唵䉁䅁䅁允䅁䅁䅕灭婭婭婭吲䴸䅉䅅䅁䙁䅁䅁睁䵁䅁䅁权摁䅁䅁权䉁䅁䅁权䙁䅁䅁兂䅁䅁䅁佯汪䅑䅅䅁䉁䅁䅁兂塄㍯㥁瑃呦睐杷允䅁䅁䅕䅁䑁䅁䅷䅁䭁䅁䅁䅁䭁䙁䅍䅁䭁䅁䅕䅁䙁䅁䅁䅁䅂⭤䅚允䅁䅁䅅䅁䙁䙁橔婰䕶䑁䅒䍄䉁䅁䅁䅂䅁䅁䅍䅄䅁䅁䅯睔䅁䅁䅯杔䅁䅁䅕䅁䅁佁汁欵䉁䅁䅁允䅁䅁䅕䅁䅁䅁䅁啅䵁䅉䅅䅁䙁䅁䅁睁䵁䅁䅁权摁䅁䅁权呂䅁䅁权䙁䅁䅁兂䅁䅁䅁䱧汘䅑䅅䅁䉁䅁䅁兂䭁㘱睎捐瑯䅑杷允䅁䅁䅕䅁䑁䅁䅷䅁䭁䉁䄰䅁䭁䙁䅍䅁䭁䅁䅕䅁䙁䅁䅁䅁杁甶䅖允䅁䅁䅅䅁䙁䭁扡䍸睃楳䄱䍄䉁䅁䅁䅂䅁䅁䅍䅄䅁䅁䅯睔䅁䅁䅯杔䅁䅁䅕䅁䅁䵁汁欵䉁䅁䅁允䅁䅁䅕㑈牘払敧啅䵁䅉䅅䅁䙁䅁䅁睁䵁䅁䅁权䅁䅁䅁权呂䅁䅁权䙁䅁䅁兂䅁䅁䅁䑑洳䅑䅅䅁䉁䅁䅁兂䅁䅁䅁䭁穁䅑杷允䅁䅁䅕䅁䑁䅁䅷䅁䭁䉁䅷䅁䭁䅁䅅䅁䭁䅁䅕䅁䙁䅁䅁䅁杁⭓䅚允䅁䅁䅅䅁䙁偁潙䥘䌯搹⽧䍄䉁䅁䅁䅂䅁䅁䅍䅄䅁䅁䅯睔䅁䅁䅯杔䅁䅁䅕䅁䅁佁呁欵䉁䅁䅁允䅁䅁䅕硥畓⭒㙆ぅ䵁䅉䅅䅁䕁䅁䅁睁䵁䅁䅁权偂䅁䅁权佂䅁䅁兂䅁䅁䅁䌴浔䅑䅅䅁䉁䅁䅁兂㑃潈牘払剧䅑杷允䅁䅁䅕䅁䑁䅁䅷䅁䭁䉁䅯䅁䭁䙁䅍䅁䭁䅁䅕䅁䙁䅁䅁䅁杄伫䅖允䅁䅁䅅䅁䙁䥁䌯匹捨稷䅬䍄䉁䅁䅁䅂䅁䅁䅍䅄䅁䅁䅯睔䅁䅁䅯杔䅁䅁䅕䅁䅁䅁楄唵䉁䅁䅁允䅁䅁䅕捺䵺䵺䵺䕄䵁䅉䅅䅁䙁䅁䅁睁䵁䅁䅁权䅁䅁䅁权䉁䅁䅁权䙁䅁䅁兂䅁䅁䅁佧汢䅑䅅䅁䉁䅁䅁兂桄桥畓⭒慈睐杷允䅁䅁䅑䅁䑁䅁䅷䅁䭁䕁䄸䅁䭁䕁䄴䅁䙁䅁䅁䅁䅁攷䅖允䅁䅁䅅䅁䙁䕁桪桥畓硒䅂䍄䉁䅁䅁兂䅁䅁䅍䅄䅁䅁䅯䅁䅁䅁䅯睕䅁䅁䅯兂䅁䅁䅕䅁䅁䅁橁欵䉁䅁䅁允䅁䅁䅕搵楁⼲⭫き䵁䅉䅅䅁䙁䅁䅁睁䵁䅁䅁权敁䅁䅁权䉁䅁䅁权䙁䅁䅁兂䅁䅁䅁䅁浄䅑䅅䅁䉁䅁䅁兂㝂䭆䠵場啲睐杷允䅁䅁䅑䅁䑁䅁䅷䅁䭁䕁䄸䅁䭁䕁䄴䅁䙁䅁䅁䅁权佹䅖允䅁䅁䅅䅁䙁佁㙆䭆䠵昴⽯䍄䉁䅁䅁兂䅁䅁䅍䅄䅁䅁䅯䅈䅁䅁䅯睕䅁䅁䅯兂䅁䅁䅕䅁䅁䍁塄唵䉁䅁䅁允䅁䅁䅕浔光䑗ね歌䵁䅉䅅䅁䙁䅁䅁睁䵁䅁䅁权捁䅁䅁权呂䅁䅁权䙁䅁䅁兂䅁䅁䅁䉁浘䅑䅅䅁䉁䅁䅁兂敂歵䵫煁瑳䅑杷允䅁䅁䅑䅁䑁䅁䅷䅁䭁䕁䄸䅁䭁䕁䄴䅁䙁䅁䅁䅁䅁佊䅚允䅁䅁䅅䅁䙁偁潙䥘䌯刹䅆䍄䉁䅁䅁兂䅁䅁䅍䅄䅁䅁䅯先䅁䅁䅯睕䅁䅁䅯兂䅁䅁䅕䅁䅁䕁あ欵䉁䅁䅁允䅁䅁䅕䬸䝦穓䩦啌䵁䅉䅅䅁䙁䅁䅁睁䵁䅁䅁权䅁䅁䅁权呂䅁䅁权䙁䅁䅁兂䅁䅁䅁乯汌䅑䅅䅁䉁䅁䅁兂权楇搯䅊穙䅑杷允䅁䅁䅕䅁䑁䅁䅷䅁䭁䉁䅷䅁䭁䅁䅅䅁䭁䅁䅕䅁䙁䅁䅁䅁杄佄䅚允䅁䅁䅅䅁䙁䉁䘫ㄶ㑇瑈⽕䍄䉁䅁䅁兂䅁䅁䅍䅄䅁䅁䅯䅁䅁䅁䅯睕䅁䅁䅯兂䅁䅁䅕䅁䅁䕁兂欵䉁䅁䅁允䅁䅁䅕扏䥔牤昷き䵁䅉䅅䅁䙁䅁䅁睁䵁䅁䅁权晁䅁䅁权䉁䅁䅁权䙁䅁䅁兂䅁䅁䅁䍷浌䅑䅅䅁䉁䅁䅁兂㉄䙋偹癷杘睐杷允䅁䅁䅑䅁䑁䅁䅷䅁䭁䕁䄸䅁䭁䕁䄴䅁䙁䅁䅁䅁杂伶䅖允䅁䅁䅅䅁䙁䍁捬㡪ㅌ䉋䅊䍄䉁䅁䅁兂䅁䅁䅍䅄䅁䅁䅯杈䅁䅁䅯允䅁䅁䅯兂䅁䅁䅕䅁䅁䝁㍃唵䉁䅁䅁允䅁䅁䅕積積積積稰䴸䅉䅅䅁䕁䅁䅁睁䵁䅁䅁权偂䅁䅁权佂䅁䅁兂䅁䅁䅁䌴浐䅑䅅䅁䉁䅁䅁兂㑃潈牘払剧䅑杷允䅁䅁䅕䅁䑁䅁䅷䅁䭁䉁䄸䅁䭁䙁䅍䅁䭁䅁䅕䅁䙁䅁䅁䅁杁佔䅚允䅁䅁䅅䅁䙁䅁坒楄礲呈䅆䍄䉁䅁䅁兂䅁䅁䅍䅄䅁䅁䅯䅁䅁䅁䅯睕䅁䅁䅯兂䅁䅁䅕䅁䅁䵁㥃唵䉁䅁䅁允䅁䅁䅕䘫橐婰䕵歍䵁䅉䅅䅁䕁䅁䅁睁䵁䅁䅁权偂䅁䅁权佂䅁䅁兂䅁䅁䅁䉧浲䅑䅅䅁䉁䅁䅁兂乄䵺䵺䵺剷䅑杷允䅁䅁䅕䅁䑁䅁䅷䅁䭁䅁䅁䅁䭁䅁䅅䅁䭁䅁䅕䅁䙁䅁䅁䅁权何䅚允䅁䅁䅅䅁䙁䱁敧敨剴乵⼴䍄䉁䅁䅁兂䅁䅁䅍䅄䅁䅁䅯杇䅁䅁䅯允䅁䅁䅯兂䅁䅁䅕䅁䅁䕁⭄唵䉁䅁䅁允䅁䅁䅕積積積積稴䴸䅉䅅䅁䙁䅁䅁睁䵁䅁䅁权晁䅁䅁权呂䅁䅁权䙁䅁䅁兂䅁䅁䅁䈴浢䅑䅅䅁䉁䅁䅁兂䝂癴㥐倱睧䅑杷允䅁䅁䅑䅁䑁䅁䅷䅁䭁䕁䄸䅁䭁䕁䄴䅁䙁䅁䅁䅁权⭉䅚允䅁䅁䅅䅁䭁䉁䅳䅁䵁䅉䅅䅁䙁䅁䅁睁䵁䅁䅁权䅁䅁䅁权呂䅁䅁权䙁䅁䅁兂䅁䅁䅁䕷浺䅑䅅䅁䉁䅁䅁兂十㡧䭄捯穕䅑杷允䅁䅁䅕䅁䑁䅁䅷䅁䭁䅁䅁䅁䭁䙁䅍䅁䭁䅁䅕䅁䙁䅁䅁䅁杄留䅚允䅁䅁䅅䅁䙁䭁硲欰椱䐰䅎䍄䉁䅁䅁兂䅁䅁䅍䅄䅁䅁䅯杇䅁䅁䅯允䅁䅁䅯兂䅁䅁䅕䅁䅁䭁瑂欵䉁䅁䅁允䅁䅁䅕䡰㥁瑃橥䐶䴸䅉䅅䅁䙁䅁䅁睁䵁䅁䅁权敁䅁䅁权䉁䅁䅁权䙁䅁䅁兂䅁䅁䅁䱯汶䅑䅅䅁䉁䅁䅁兂穁積積積呐睐杷允䅁䅁䅕䅁䑁䅁䅷䅁䭁䅁䅁䅁䭁䙁䅍䅁䭁䅁䅕䅁䙁䅁䅁䅁䅂敎䅚允䅁䅁䅅䅁䙁䍁礲敮渫橨䅎䍄䉁䅁䅁兂䅁䅁䅍䅄䅁䅁䅯杇䅁䅁䅯允䅁䅁䅯兂䅁䅁䅕䅁䅁佁䡄唵䉁䅁䅁允䅁䅁䅕䅁䅁䅁䅁䐴䴸䅉䅅䅁䙁䅁䅁睁䵁䅁䅁权摁䅁䅁权呂䅁䅁权䙁䅁䅁兂䅁䅁䅁䱙汦䅑䅅䅁䉁䅁䅁兂䭁㘱睎捐瑯䅑杷允䅁䅁䅑䅁䑁䅁䅷䅁䭁䕁䄸䅁䭁䕁䄴䅁䙁䅁䅁䅁䅁⭉䅚允䅁䅁䅅䅁䙁䥁牘払敧剨䅆䍄䉁䅁䅁兂䅁䅁䅍䅄䅁䅁䅯䅁䅁䅁䅯睕䅁䅁䅯兂䅁䅁䅕䅁䅁佁䑄唵䉁䅁䅁允䅁䅁䅕䘫橐婰䕵歍䵁䅉䅅䅁䙁䅁䅁睁䵁䅁䅁权䅁䅁䅁权呂䅁䅁权䙁䅁䅁兂䅁䅁䅁䭙汮䅑䅅䅁䉁䅁䅁兂塄㍯㥁湃硣䅑杷允䅁䅁䅑䅁䑁䅁䅷䅁䭁䕁䄸䅁䭁䕁䄴䅁䙁䅁䅁䅁杁伱䅖允䅁䅁䅅䅁䙁䕁桪桥畓睒䅖䍄䉁䅁䅁兂䅁䅁䅍䅄䅁䅁䅯䅈䅁䅁䅯睕䅁䅁䅯兂䅁䅁䅕䅁䅁䝁㉃唵䉁䅁䅁允䅁䅁䅕㝤昶楇搸歌䵁䅉䅅䅁䕁䅁䅁睁䵁䅁䅁权偂䅁䅁权佂䅁䅁兂䅁䅁䅁䍉浌䅑䅅䅁䉁䅁䅁兂歃䑣䬰㘱免䅑杷允䅁䅁䅕䅁䑁䅁䅷䅁䭁䅁䅁䅁䭁䙁䅍䅁䭁䅁䅕䅁䙁䅁䅁䅁䅃敶䅖允䅁䅁䅅䅁䙁偁周㘴扗䑨䅊䍄䉁䅁䅁兂䅁䅁䅍䅄䅁䅁䅯杇䅁䅁䅯允䅁䅁䅯兂䅁䅁䅕䅁䅁䝁乁欵䉁䅁䅁允䅁䅁䅕浚浚浚浚樵䴸䅉䅅䅁䕁䅁䅁睁䵁䅁䅁权偂䅁䅁权佂䅁䅁兂䅁䅁䅁䩙決䅑䅅䅁䉁䅁䅁兂㝂䭆䠵場啲睐杷允䅁䅁䅕䅁䑁䅁䅷䅁䭁䉁䅯䅁䭁䙁䅍䅁䭁䅁䅕䅁䙁䅁䅁䅁杂伴䅖允䅁䅁䅅䅁䙁䵁ㅐ䙋偹樴䅬䍄䉁䅁䅁兂䅁䅁䅍䅄䅁䅁䅯先䅁䅁䅯允䅁䅁䅯兂䅁䅁䅕䅁䅁䥁扄唵䉁䅁䅁允䅁䅁䅕㘱睎児塲稰䴸䅉䅅䅁䙁䅁䅁睁䵁䅁䅁权䅁䅁䅁权呂䅁䅁权䙁䅁䅁兂䅁䅁䅁䡙浌䅑䅅䅁䉁䅁䅁兂啂㘴扗䅸ぁ䅑杷允䅁䅁䅕䅁䑁䅁䅷䅁䭁䉁䅯䅁䭁䙁䅍䅁䭁䅁䅕䅁䙁䅁䅁䅁䅂⭶䅖允䅁䅁䅅䅁䙁䱁䩰䅄牉穊䅰䍄䉁䅁䅁䅂䅁䅁䅍䅄䅁䅁䅯睔䅁䅁䅯杔䅁䅁䅕䅁䅁䵁湄唵䉁䅁䅁允䅁䅁䅕敨剴䉵䘶啅䵁䅉䅅䅁䙁䅁䅁睁䵁䅁䅁权敁䅁䅁权䉁䅁䅁权䙁䅁䅁兂䅁䅁䅁佧汮䅑䅅䅁䉁䅁䅁兂穁積積積呐睐杷允䅁䅁䅑䅁䑁䅁䅷䅁䭁䕁䄸䅁䭁䕁䄴䅁䙁䅁䅁䅁䅄敆䅚允䅁䅁䅅䅁䙁䩁婱婭婭剭䅎䍄䉁䅁䅁䅂䅁䅁䅍䅄䅁䅁䅯睔䅁䅁䅯杔䅁䅁䅕䅁䅁䅁楁欵䉁䅁䅁允䅁䅁䅕㡪ㅌ䙋偹䕅䵁䅉䅅䅁䕁䅁䅁睁䵁䅁䅁权偂䅁䅁权佂䅁䅁兂䅁䅁䅁䉑浮䅑䅅䅁䉁䅁䅁兂㉄䙋偹癷剕䅑杷允䅁䅁䅑䅁䑁䅁䅷䅁䭁䕁䄸䅁䭁䕁䄴䅁䙁䅁䅁䅁䅃佉䅚允䅁䅁䅅䅁䙁䡁啳歲桦桥䅂䍄䉁䅁䅁兂䅁䅁䅍䅄䅁䅁䅯䅁䅁䅁䅯允䅁䅁䅯兂䅁䅁䅕䅁䅁䕁佄唵䉁䅁䅁允䅁䅁䅕児塲㍯㥁樲䴸䅉䅅䅁䙁䅁䅁睁䵁䅁䅁权䅁䅁䅁权䉁䅁䅁权䙁䅁䅁兂䅁䅁䅁䑉洷䅑䅅䅁䉁䅁䅁兂㑃潈牘払敪睐杷允䅁䅁䅑䅁䑁䅁䅷䅁䭁䕁䄸䅁䭁䕁䄴䅁䙁䅁䅁䅁杄畳䅖允䅁䅁䅅䅁䙁䩁婱婭婭摭⽫䍄䉁䅁䅁兂䅁䅁䅍䅄䅁䅁䅯杈䅁䅁䅯睕䅁䅁䅯兂䅁䅁䅕䅁䅁䭁獁欵䉁䅁䅁允䅁䅁䅕体㙆䭆䠵歊䵁䅉䅅䅁䕁䅁䅁睁䵁䅁䅁权偂䅁䅁权佂䅁䅁兂䅁䅁䅁偙汘䅑䅅䅁䉁䅁䅁兂䥂場啯歲剣䅑杷允䅁䅁䅕䅁䑁䅁䅷䅁䭁䅁䅁䅁䭁䙁䅍䅁䭁䅁䅕䅁䙁䅁䅁䅁䅂畤䅚允䅁䅁䅅䅁䙁䙁橔婰䕶䑁䅒䍄䉁䅁䅁兂䅁䅁䅍䅄䅁䅁䅯杈䅁䅁䅯允䅁䅁䅯兂䅁䅁䅕䅁䅁佁塁欵䉁䅁䅁允䅁䅁䅕⽷潕䥘䌯吱䴸䅉䅅䅁䙁䅁䅁睁䵁䅁䅁权晁䅁䅁权䉁䅁䅁权䙁䅁䅁兂䅁䅁䅁余汄䅑䅅䅁䉁䅁䅁兂㥁瑃橥䑣愳睐杷允䅁䅁䅕䅁䑁䅁䅷䅁䭁䉁䄴䅁䭁䙁䅍䅁䭁䅁䅕䅁䙁䅁䅁䅁杂⭢䅚允䅁䅁䅅䅁䙁乁楅⼲⭬楡䅆䍄䉁䅁䅁䅂䅁䅁䅍䅄䅁䅁䅯睔䅁䅁䅯杔䅁䅁䅕䅁䅁䭁晁欵䉁䅁䅁允䅁䅁䅕敨剴䉵䘶䕅䵁䅉䅅䅁䙁䅁䅁睁䵁䅁䅁权捁䅁䅁权䉁䅁䅁权䙁䅁䅁兂䅁䅁䅁䱧氳䅑䅅䅁䉁䅁䅁兂偃癷潕䥘匯睐杷允䅁䅁䅕䅁䑁䅁䅷䅁䭁䉁䄸䅁䭁䅁䅅䅁䭁䅁䅕䅁䙁䅁䅁䅁权敶䅖允䅁䅁䅅䅁䙁䱁敧敨剴乵⼴䍄䉁䅁䅁䅂䅁䅁䅍䅄䅁䅁䅯睔䅁䅁䅯杔䅁䅁䅕䅁䅁䕁敃唵䉁䅁䅁允䅁䅁䅕㑈牘払敧吱䴸䅉䅅䅁䙁䅁䅁睁䵁䅁䅁权慁䅁䅁权呂䅁䅁权䙁䅁䅁兂䅁䅁䅁䠴浢䅑䅅䅁䉁䅁䅁兂䵂㑎䉬䍙㝕䅑杷允䅁䅁䅑䅁䑁䅁䅷䅁䭁䕁䄸䅁䭁䕁䄴䅁䙁䅁䅁䅁䅃⭈䅚允䅁䅁䅅䅁䙁䡁啳歲桦桥䅂䍄䉁䅁䅁兂䅁䅁䅍䅄䅁䅁䅯睈䅁䅁䅯睕䅁䅁䅯兂䅁䅁䅕䅁䅁佁煂欵䉁䅁䅁允䅁䅁䅕瑃橥䑣焰啍䵁䅉䅅䅁䕁䅁䅁睁䵁䅁䅁权偂䅁䅁权佂䅁䅁兂䅁䅁䅁䅁浄䅑䅅䅁䉁䅁䅁兂浂浚浚浚䵙䅑杷允䅁䅁䅕䅁䑁䅁䅷䅁䭁䉁䄴䅁䭁䅁䅅䅁䭁䅁䅕䅁䙁䅁䅁䅁䅂畳䅖允䅁䅁䅅䅁䙁䑁積積積㥍⽍䍄䉁䅁䅁兂䅁䅁䅍䅄䅁䅁䅯睈䅁䅁䅯允䅁䅁䅯兂䅁䅁䅕䅁䅁䥁㉁欵䉁䅁䅁允䅁䅁䅕体㙆䭆䠵吴䴸䅉䅅䅁䙁䅁䅁睁䵁䅁䅁权䅁䅁䅁权呂䅁䅁权䙁䅁䅁兂䅁䅁䅁䕧浮䅑䅅䅁䉁䅁䅁兂十㡧䭄捯穕䅑杷允䅁䅁䅕䅁䑁䅁䅷䅁䭁䉁䅯䅁䭁䙁䅍䅁䭁䅁䅕䅁䙁䅁䅁䅁权⭍䅚允䅁䅁䅅䅁䙁䉁䘫ㄶ㑇樳䅰䍄䉁䅁䅁䅂䅁䅁䅍䅄䅁䅁䅯睔䅁䅁䅯杔䅁䅁䅕䅁䅁佁敁欵䉁䅁䅁允䅁䅁䅕䥘䌯匹捨い䵁䅉䅅䅁䙁䅁䅁睁䵁䅁䅁权慁䅁䅁权呂䅁䅁权䙁䅁䅁兂䅁䅁䅁䙉浲䅑䅅䅁䉁䅁䅁兂䑄匹捨㉪㝉䅑杷允䅁䅁䅑䅁䑁䅁䅷䅁䭁䕁䄸䅁䭁䕁䄴䅁䙁䅁䅁䅁杁伵䅖允䅁䅁䅅䅁䙁䵁ㅐ䙋偹桷䅂䍄䉁䅁䅁兂䅁䅁䅍䅄䅁䅁䅯睈䅁䅁䅯睕䅁䅁䅯兂䅁䅁䅕䅁䅁䭁偂欵䉁䅁䅁允䅁䅁䅕䙂余扌摉啍䵁䅉䅅䅁䙁䅁䅁睁䵁䅁䅁权䅁䅁䅁权䉁䅁䅁权䙁䅁䅁兂䅁䅁䅁䡯浐䅑䅅䅁䉁䅁䅁兂㑃潈牘払敪睐杷允䅁䅁䅕䅁䑁䅁䅷䅁䭁䉁䄴䅁䭁䙁䅍䅁䭁䅁䅕䅁䙁䅁䅁䅁杂余䅚允䅁䅁䅅䅁䙁䩁瑈䑦ㄸ楘䅊䍄䉁䅁䅁兂䅁䅁䅍䅄䅁䅁䅯睈䅁䅁䅯睕䅁䅁䅯兂䅁䅁䅕䅁䅁䍁䝁欵䉁䅁䅁允䅁䅁䅕㡧䭄啯块䕍䵁䅉䅅䅁䕁䅁䅁睁䵁䅁䅁权偂䅁䅁权佂䅁䅁兂䅁䅁䅁乧汔䅑䅅䅁䉁䅁䅁兂晁敨剴䉵䘴䅑杷允䅁䅁䅕䅁䑁䅁䅷䅁䭁䉁䅷䅁䭁䙁䅍䅁䭁䅁䅕䅁䙁䅁䅁䅁䅃佸䅖允䅁䅁䅅䅁䙁佁㙆䭆䠵卙䄵䍄䉁䅁䅁兂䅁䅁䅍䅄䅁䅁䅯先䅁䅁䅯睕䅁䅁䅯兂䅁䅁䅕䅁䅁䕁湄唵䉁䅁䅁允䅁䅁䅕䉵䘶ㄶ㑈䕌䵁䅉䅅䅁䙁䅁䅁睁䵁䅁䅁权敁䅁䅁权呂䅁䅁权䙁䅁䅁兂䅁䅁䅁䭁氳䅑䅅䅁䉁䅁䅁兂㍂灶愸硌爰䅑杷允䅁䅁䅑䅁䑁䅁䅷䅁䭁䕁䄸䅁䭁䕁䄴䅁䙁䅁䅁䅁杄⬯䅖允䅁䅁䅅䅁䙁䙁偹癷潕䅘䄱䍄䉁䅁䅁䅂䅁䅁䅍䅄䅁䅁䅯睔䅁䅁䅯杔䅁䅁䅕䅁䅁䵁捁欵䉁䅁䅁允䅁䅁䅕積積積積䕅䵁䅉䅅䅁䙁䅁䅁睁䵁䅁䅁权慁䅁䅁权䉁䅁䅁权䙁䅁䅁兂䅁䅁䅁䱉汈䅑䅅䅁䉁䅁䅁兂䅁䅁䅁䅁杄睐杷允䅁䅁䅕䅁䑁䅁䅷䅁䭁䉁䄰䅁䭁䙁䅍䅁䭁䅁䅕䅁䙁䅁䅁䅁䅄佔䅚允䅁䅁䅅䅁䙁䡁呗䅇坒楪䄵䍄䉁䅁䅁䅂䅁䅁䅍䅄䅁䅁䅯睔䅁䅁䅯杔䅁䅁䅕䅁䅁䭁い唵䉁䅁䅁允䅁䅁䅕牕敧敨剴䕅䵁䅉䅅䅁䙁䅁䅁睁䵁䅁䅁权摁䅁䅁权呂䅁䅁权䙁䅁䅁兂䅁䅁䅁临決䅑䅅䅁䉁䅁䅁兂䑄匹捨㡪瑉䅑杷允䅁䅁䅕䅁䑁䅁䅷䅁䭁䅁䅁䅁䭁䙁䅍䅁䭁䅁䅕䅁䙁䅁䅁䅁䅃⭊䅚允䅁䅁䅅䅁䙁佁兘瑉㕶橐䅎䍄䉁䅁䅁䅂䅁䅁䅍䅄䅁䅁䅯睔䅁䅁䅯杔䅁䅁䅕䅁䅁䥁⽃唵䉁䅁䅁允䅁䅁䅕䥘䌯匹捨稷䴸䅉䅅䅁䙁䅁䅁睁䵁䅁䅁权捁䅁䅁权䉁䅁䅁权䙁䅁䅁兂䅁䅁䅁䱷汔䅑䅅䅁䉁䅁䅁兂偃癷潕䥘匯睐杷允䅁䅁䅑䅁䑁䅁䅷䅁䭁䕁䄸䅁䭁䕁䄴䅁䙁䅁䅁䅁权效䅚允䅁䅁䅅䅁䙁䙁偹癷潕䉘䅂䍄䉁䅁䅁兂䅁䅁䅍䅄䅁䅁䅯杈䅁䅁䅯允䅁䅁䅯兂䅁䅁䅕䅁䅁佁硂欵䉁䅁䅁允䅁䅁䅕䅁䅁䅁䅁䐰䴸䅉䅅䅁䙁䅁䅁睁䵁䅁䅁权晁䅁䅁权䉁䅁䅁权䙁䅁䅁兂䅁䅁䅁䍉浲䅑䅅䅁䉁䅁䅁兂䥂場啯歲桦睐杷允䅁䅁䅕䅁䑁䅁䅷䅁䭁䉁䅯䅁䭁䙁䅍䅁䭁䅁䅕䅁䙁䅁䅁䅁䅄敄䅚允䅁䅁䅅䅁䙁䅁䉡啬䱏䑔䅰䍄䉁䅁䅁兂䅁䅁䅍䅄䅁䅁䅯杈䅁䅁䅯允䅁䅁䅯兂䅁䅁䅕䅁䅁䥁扄唵䉁䅁䅁允䅁䅁䅕積積積積稰䴸䅉䅅䅁䕁䅁䅁睁䵁䅁䅁权偂䅁䅁权佂䅁䅁兂䅁䅁䅁䉁洳䅑䅅䅁䉁䅁䅁兂啁歲桦桥兑䅑杷允䅁䅁䅕䅁䑁䅁䅷䅁䭁䅁䅁䅁䭁䙁䅍䅁䭁䅁䅕䅁䙁䅁䅁䅁䅁畔䅚允䅁䅁䅅䅁䙁䉁䑋䵷桱呸䅎䍄䉁䅁䅁䅂䅁䅁䅍䅄䅁䅁䅯睔䅁䅁䅯杔䅁䅁䅕䅁䅁䍁ぃ唵䉁䅁䅁允䅁䅁䅕捺䵺䵺䵺䐳䴸䅉䅅䅁䙁䅁䅁睁䵁䅁䅁权摁䅁䅁权䉁䅁䅁权䙁䅁䅁兂䅁䅁䅁䈴浦䅑䅅䅁䉁䅁䅁兂晁敨剴䉵嘷睐杷允䅁䅁䅕䅁䑁䅁䅷䅁䭁䉁䄰䅁䭁䙁䅍䅁䭁䅁䅕䅁䙁䅁䅁䅁䅄⬵䅖允䅁䅁䅅䅁䙁䱁敧敨剴䌫䅸䍄䉁䅁䅁䅂䅁䅁䅍䅄䅁䅁䅯睔䅁䅁䅯杔䅁䅁䅕䅁䅁䥁呄唵䉁䅁䅁允䅁䅁䅕児塲㍯㥁歂䵁䅉䅅䅁䙁䅁䅁睁䵁䅁䅁权䅁䅁䅁权䉁䅁䅁权䙁䅁䅁兂䅁䅁䅁䙉浐䅑䅅䅁䉁䅁䅁兂㑃潈牘払敪睐杷允䅁䅁䅑䅁䑁䅁䅷䅁䭁䕁䄸䅁䭁䕁䄴䅁䙁䅁䅁䅁杄⬲䅖允䅁䅁䅅䅁䙁乁橥䑣䬰眱䅤䍄䉁䅁䅁兂䅁䅁䅍䅄䅁䅁䅯䅁䅁䅁䅯允䅁䅁䅯兂䅁䅁䅕䅁䅁佁䉄唵䉁䅁䅁允䅁䅁䅕児塲㍯㥁樲䴸䅉䅅䅁䙁䅁䅁睁䵁䅁䅁权慁䅁䅁权䉁䅁䅁权䙁䅁䅁兂䅁䅁䅁䅧浪䅑䅅䅁䉁䅁䅁兂浂浚浚浚浢睐杷允䅁䅁䅕䅁䑁䅁䅷䅁䭁䉁䅯䅁䭁䙁䅍䅁䭁䅁䅕䅁䙁䅁䅁䅁䅄敯䅖允䅁䅁䅅䅁䙁䥁坣挲㌷積䅬䍄䉁䅁䅁䅂䅁䅁䅍䅄䅁䅁䅯睔䅁䅁䅯杔䅁䅁䅕䅁䅁䅁㙃唵䉁䅁䅁允䅁䅁䅕䡰㥁瑃橥䐶䴸䅉䅅䅁䙁䅁䅁睁䵁䅁䅁权捁䅁䅁权呂䅁䅁权䙁䅁䅁兂䅁䅁䅁䍯浺䅑䅅䅁䉁䅁䅁兂偃癷潕䅘甸䅑杷允䅁䅁䅕䅁䑁䅁䅷䅁䭁䉁䄰䅁䭁䙁䅍䅁䭁䅁䅕䅁䙁䅁䅁䅁䅄佚䅚允䅁䅁䅅䅁䙁䡁⼰噎㘶卓䄵䍄䉁䅁䅁兂䅁䅁䅍䅄䅁䅁䅯先䅁䅁䅯睕䅁䅁䅯兂䅁䅁䅕䅁䅁䍁㍂欵䉁䅁䅁允䅁䅁䅕䬸䝦穓䩦啌䵁䅉䅅䅁䕁䅁䅁睁䵁䅁䅁权偂䅁䅁权佂䅁䅁兂䅁䅁䅁䉯浺䅑䅅䅁䉁䅁䅁兂灁䥘䌯匹內䅑杷允䅁䅁䅕䅁䑁䅁䅷䅁䭁䅁䅁䅁䭁䅁䅅䅁䭁䅁䅕䅁䙁䅁䅁䅁䅃敃䅚允䅁䅁䅅䅁䙁䱁敧敨剴乵⼴䍄䉁䅁䅁兂䅁䅁䅍䅄䅁䅁䅯睈䅁䅁䅯睕䅁䅁䅯兂䅁䅁䅕䅁䅁䍁⭁欵䉁䅁䅁允䅁䅁䅕㑎䉬余睕啍䵁䅉䅅䅁䙁䅁䅁睁䵁䅁䅁权晁䅁䅁权呂䅁䅁权䙁䅁䅁兂䅁䅁䅁䙁浘䅑䅅䅁䉁䅁䅁兂㥂穐敖極硫䅑杷允䅁䅁䅕䅁䑁䅁䅷䅁䭁䅁䅁䅁䭁䅁䅅䅁䭁䅁䅕䅁䙁䅁䅁䅁䅃佮䅖允䅁䅁䅅䅁䙁䩁婱婭婭摭⽫䍄䉁䅁䅁兂䅁䅁䅍䅄䅁䅁䅯杈䅁䅁䅯睕䅁䅁䅯兂䅁䅁䅕䅁䅁䥁扄唵䉁䅁䅁允䅁䅁䅕兊䉡啬䱏䕌䵁䅉䅅䅁䕁䅁䅁睁䵁䅁䅁权偂䅁䅁权佂䅁䅁兂䅁䅁䅁䉉浺䅑䅅䅁䉁䅁䅁兂㥁瑃橥䑣儰䅑杷允䅁䅁䅕䅁䑁䅁䅷䅁䭁䉁䄸䅁䭁䅁䅅䅁䭁䅁䅕䅁䙁䅁䅁䅁杁⭅䅚允䅁䅁䅅䅁䙁䭁睒児塲⭯⽁䍄䉁䅁䅁䅂䅁䅁䅍䅄䅁䅁䅯睔䅁䅁䅯杔䅁䅁䅕䅁䅁䝁扁欵䉁䅁䅁允䅁䅁䅕敨剴䉵䘶䕅䵁䅉䅅䅁䕁䅁䅁睁䵁䅁䅁权偂䅁䅁权佂䅁䅁兂䅁䅁䅁䈴浲䅑䅅䅁䉁䅁䅁兂畃⭒㙆䭆刴䅑杷允䅁䅁䅕䅁䑁䅁䅷䅁䭁䉁䅯䅁䭁䙁䅍䅁䭁䅁䅕䅁䙁䅁䅁䅁䅂佄䅚允䅁䅁䅅䅁䙁䅁䉡啬䱏䑔䅰䍄䉁䅁䅁兂䅁䅁䅍䅄䅁䅁䅯先䅁䅁䅯允䅁䅁䅯兂䅁䅁䅕䅁䅁䍁あ欵䉁䅁䅁允䅁䅁䅕歲桦桥畓稱䴸䅉䅅䅁䕁䅁䅁睁䵁䅁䅁权偂䅁䅁权佂䅁䅁兂䅁䅁䅁䱑氳䅑䅅䅁䉁䅁䅁兂浂浚浚浚畢睐杷允䅁䅁䅑䅁䑁䅁䅷䅁䭁䕁䄸䅁䭁䕁䄴䅁䙁䅁䅁䅁杂畇䅚允䅁䅁䅅䅁䙁䑁䬰㘱睎剐䅆䍄䉁䅁䅁䅂䅁䅁䅍䅄䅁䅁䅯睔䅁䅁䅯杔䅁䅁䅕䅁䅁佁噄唵䉁䅁䅁允䅁䅁䅕体㙆䭆䠵あ䵁䅉䅅䅁䙁䅁䅁睁䵁䅁䅁权䅁䅁䅁权䉁䅁䅁权䙁䅁䅁兂䅁䅁䅁䱧氯䅑䅅䅁䉁䅁䅁兂㥁瑃橥䑣愳睐杷允䅁䅁䅕䅁䑁䅁䅷䅁䭁䉁䄴䅁䭁䙁䅍䅁䭁䅁䅕䅁䙁䅁䅁䅁䅄⭙䅚允䅁䅁䅅䅁䙁䩁瑈䑦ㄸ楘䅊䍄䉁䅁䅁兂䅁䅁䅍䅄䅁䅁䅯睈䅁䅁䅯允䅁䅁䅯兂䅁䅁䅕䅁䅁䵁䉃欵䉁䅁䅁允䅁䅁䅕牕敧敨剴䐴䴸䅉䅅䅁䕁䅁䅁睁䵁䅁䅁权偂䅁䅁权佂䅁䅁兂䅁䅁䅁䉁浲䅑䅅䅁䉁䅁䅁兂慃婭婭婭剫䅑杷允䅁䅁䅑䅁䑁䅁䅷䅁䭁䕁䄸䅁䭁䕁䄴䅁䙁䅁䅁䅁权伯䅖允䅁䅁䅅䅁䙁䩁婱婭婭六䄱䍄䉁䅁䅁兂䅁䅁䅍䅄䅁䅁䅯杇䅁䅁䅯允䅁䅁䅯兂䅁䅁䅕䅁䅁佁煂欵䉁䅁䅁允䅁䅁䅕䡰㥁瑃橥䐶䴸䅉䅅䅁䙁䅁䅁睁䵁䅁䅁权敁䅁䅁权䉁䅁䅁权䙁䅁䅁兂䅁䅁䅁䕑浐䅑䅅䅁䉁䅁䅁兂䑄匹捨㡪噌睐杷允䅁䅁䅕䅁䑁䅁䅷䅁䭁䉁䄰䅁䭁䅁䅅䅁䭁䅁䅕䅁䙁䅁䅁䅁杁⭄䅚允䅁䅁䅅䅁䙁䉁䘫ㄶ㑇瑈⽕䍄䉁䅁䅁兂䅁䅁䅍䅄䅁䅁䅯䅁䅁䅁䅯睕䅁䅁䅯兂䅁䅁䅕䅁䅁䵁塁欵䉁䅁䅁允䅁䅁䅕硢䑋䵷䉯き䵁䅉䅅䅁䙁䅁䅁睁䵁䅁䅁权摁䅁䅁权呂䅁䅁权䙁䅁䅁兂䅁䅁䅁䩧汶䅑䅅䅁䉁䅁䅁兂䝂癴㥐䠱瑧䅑杷允䅁䅁䅕䅁䑁䅁䅷䅁䭁䉁䅷䅁䭁䙁䅍䅁䭁䅁䅕䅁䙁䅁䅁䅁杂余䅚允䅁䅁䅅䅁䙁䭁䙊癴㥐䍆䄵䍄䉁䅁䅁䅂䅁䅁䅍䅄䅁䅁䅯睔䅁䅁䅯杔䅁䅁䅕䅁䅁佁䑄唵䉁䅁䅁允䅁䅁䅕噋偹癷潕䐹䴸䅉䅅䅁䙁䅁䅁睁䵁䅁䅁权慁䅁䅁权呂䅁䅁权䙁䅁䅁兂䅁䅁䅁䜴洯䅑䅅䅁䉁䅁䅁兂癁匳䝑噧㝕䅑杷允䅁䅁䅕䅁䑁䅁䅷䅁䭁䉁䄴䅁䭁䙁䅍䅁䭁䅁䅕䅁䙁䅁䅁䅁䅃敧䅚允䅁䅁䅅䅁䙁䡁⼰噎㘶剓䅸䍄䉁䅁䅁䅂䅁䅁䅍䅄䅁䅁䅯睔䅁䅁䅯杔䅁䅁䅕䅁䅁䭁婁欵䉁䅁䅁允䅁䅁䅕児塲㍯㥁啅䵁䅉䅅䅁䙁䅁䅁睁䵁䅁䅁权敁䅁䅁权䉁䅁䅁权䙁䅁䅁兂䅁䅁䅁䭁決䅑䅅䅁䉁䅁䅁兂穁積積積呐睐杷允䅁䅁䅕䅁䑁䅁䅷䅁䭁䉁䄸䅁䭁䙁䅍䅁䭁䅁䅕䅁䙁䅁䅁䅁䅃佧䅚允䅁䅁䅅䅁䙁䝁汄䌰扌含䅂䍄䉁䅁䅁兂䅁䅁䅍䅄䅁䅁䅯䅁䅁䅁䅯允䅁䅁䅯兂䅁䅁䅕䅁䅁䅁䥄唵䉁䅁䅁允䅁䅁䅕児塲㍯㥁樲䴸䅉䅅䅁䙁䅁䅁睁䵁䅁䅁权摁䅁䅁权䉁䅁䅁权䙁䅁䅁兂䅁䅁䅁䡯浮䅑䅅䅁䉁䅁䅁兂畃⭒㙆䭆堷睐杷允䅁䅁䅕䅁䑁䅁䅷䅁䭁䉁䄴䅁䭁䅁䅅䅁䭁䅁䅕䅁䙁䅁䅁䅁权畁䅚允䅁䅁䅅䅁䙁䡁啳歲桦瑥⽑䍄䉁䅁䅁兂䅁䅁䅍䅄䅁䅁䅯䅈䅁䅁䅯允䅁䅁䅯兂䅁䅁䅕䅁䅁䥁⽂欵䉁䅁䅁允䅁䅁䅕椹捨㡪ㅌ䐲䴸䅉䅅䅁䕁䅁䅁睁䵁䅁䅁权偂䅁䅁权佂䅁䅁兂䅁䅁䅁䩙氳䅑䅅䅁䉁䅁䅁兂䑄匹捨㡪噌睐杷允䅁䅁䅕䅁䑁䅁䅷䅁䭁䉁䄴䅁䭁䅁䅅䅁䭁䅁䅕䅁䙁䅁䅁䅁权⭗䅚允䅁䅁䅅䅁䙁䅁䅁䅁䅁乁⽁䍄䉁䅁䅁兂䅁䅁䅍䅄䅁䅁䅯杇䅁䅁䅯允䅁䅁䅯兂䅁䅁䅕䅁䅁䥁⽃唵䉁䅁䅁允䅁䅁䅕䅁䅁䅁䅁䐴䴸䅉䅅䅁䕁䅁䅁睁䵁䅁䅁权偂䅁䅁权佂䅁䅁兂䅁䅁䅁䭙汲䅑䅅䅁䉁䅁䅁兂㑃潈牘払敪睐杷允䅁䅁䅕䅁䑁䅁䅷䅁䭁䉁䅯䅁䭁䅁䅅䅁䭁䅁䅕䅁䙁䅁䅁䅁䅁畋䅚允䅁䅁䅅䅁䙁䭁睒児塲⭯⽧䍄䉁䅁䅁兂䅁䅁䅍䅄䅁䅁䅯杇䅁䅁䅯允䅁䅁䅯兂䅁䅁䅕䅁䅁䝁灁欵䉁䅁䅁允䅁䅁䅕䡰㥁瑃橥䐶䴸䅉䅅䅁䙁䅁䅁睁䵁䅁䅁权䅁䅁䅁权呂䅁䅁权䙁䅁䅁兂䅁䅁䅁䭉汲䅑䅅䅁䉁䅁䅁兂塄㍯㥁湃硣䅑杷允䅁䅁䅕䅁䑁䅁䅷䅁䭁䉁䅯䅁䭁䙁䅍䅁䭁䅁䅕䅁䙁䅁䅁䅁䅄估䅖允䅁䅁䅅䅁䙁䭁慁㥌欰橒䅰䍄䉁䅁䅁兂䅁䅁䅍䅄䅁䅁䅯杇䅁䅁䅯睕䅁䅁䅯兂䅁䅁䅕䅁䅁䕁ぁ欵䉁䅁䅁允䅁䅁䅕㑈牘払敪歏䵁䅉䅅䅁䕁䅁䅁睁䵁䅁䅁权偂䅁䅁权佂䅁䅁兂䅁䅁䅁䩑決䅑䅅䅁䉁䅁䅁兂偃癷潕䥘匯睐杷允䅁䅁䅕䅁䑁䅁䅷䅁䭁䉁䄸䅁䭁䙁䅍䅁䭁䅁䅕䅁䙁䅁䅁䅁䅃⭘䅚允䅁䅁䅅䅁䙁乁楅⼲⭬橃䅆䍄䉁䅁䅁兂䅁䅁䅍䅄䅁䅁䅯䅁䅁䅁䅯睕䅁䅁䅯兂䅁䅁䅕䅁䅁䍁捃唵䉁䅁䅁允䅁䅁䅕㘱睎児㍲䕍䵁䅉䅅䅁䙁䅁䅁睁䵁䅁䅁权摁䅁䅁权呂䅁䅁权䙁䅁䅁兂䅁䅁䅁䡯洷䅑䅅䅁䉁䅁䅁兂睄㡰䱚㡎瑫䅑杷允䅁䅁䅑䅁䑁䅁䅷䅁䭁䕁䄸䅁䭁䕁䄴䅁䙁䅁䅁䅁䅄⭵䅖允䅁䅁䅅䅁䙁䥁䌯匹捨⭪⽯䍄䉁䅁䅁兂䅁䅁䅍䅄䅁䅁䅯䅁䅁䅁䅯睕䅁䅁䅯兂䅁䅁䅕䅁䅁䝁奁欵䉁䅁䅁允䅁䅁䅕硢䑋䵷䉯き䵁䅉䅅䅁䕁䅁䅁睁䵁䅁䅁权偂䅁䅁权佂䅁䅁兂䅁䅁䅁䉷浄䅑䅅䅁䉁䅁䅁兂浂浚浚浚呙䅑杷允䅁䅁䅕䅁䑁䅁䅷䅁䭁䉁䅯䅁䭁䙁䅍䅁䭁䅁䅕䅁䙁䅁䅁䅁杂畹䅖允䅁䅁䅅䅁䙁䭁慁㥌欰橒䅰䍄䉁䅁䅁䅂䅁䅁䅍䅄䅁䅁䅯睔䅁䅁䅯杔䅁䅁䅕䅁䅁䵁坁欵䉁䅁䅁允䅁䅁䅕灭婭婭婭歅䵁䅉䅅䅁䙁䅁䅁睁䵁䅁䅁权晁䅁䅁权䉁䅁䅁权䙁䅁䅁兂䅁䅁䅁佯氳䅑䅅䅁䉁䅁䅁兂桄桥畓⭒慈睐杷允䅁䅁䅕䅁䑁䅁䅷䅁䭁䉁䅷䅁䭁䅁䅅䅁䭁䅁䅕䅁䙁䅁䅁䅁䅂何䅚允䅁䅁䅅䅁䙁偁潙䥘䌯搹⽧䍄䉁䅁䅁兂䅁䅁䅍䅄䅁䅁䅯䅁䅁䅁䅯允䅁䅁䅯兂䅁䅁䅕䅁䅁佁䕂欵䉁䅁䅁允䅁䅁䅕䉵䘶ㄶ㑇樳䴸䅉䅅䅁䙁䅁䅁睁䵁䅁䅁权䅁䅁䅁权䉁䅁䅁权䙁䅁䅁兂䅁䅁䅁䅧浪䅑䅅䅁䉁䅁䅁兂㑃潈牘払敪睐杷允䅁䅁䅑䅁䑁䅁䅷䅁䭁䕁䄸䅁䭁䕁䄴䅁䙁䅁䅁䅁杂攲䅖允䅁䅁䅅䅁䙁䥁䌯匹捨睪䅚䍄䉁䅁䅁兂䅁䅁䅍䅄䅁䅁䅯睈䅁䅁䅯允䅁䅁䅯兂䅁䅁䅕䅁䅁䕁硃唵䉁䅁䅁允䅁䅁䅕敨剴䉵䘶稲䴸䅉䅅䅁䙁䅁䅁睁䵁䅁䅁权晁䅁䅁权䉁䅁䅁权䙁䅁䅁兂䅁䅁䅁䐴浐䅑䅅䅁䉁䅁䅁兂䥂場啯歲桦睐杷允䅁䅁䅑䅁䑁䅁䅷䅁䭁䕁䄸䅁䭁䕁䄴䅁䙁䅁䅁䅁权畆䅚允䅁䅁䅅䅁䙁䥁䌯匹捨硪䅊䍄䉁䅁䅁兂䅁䅁䅍䅄䅁䅁䅯杇䅁䅁䅯睕䅁䅁䅯兂䅁䅁䅕䅁䅁䭁㑁欵䉁䅁䅁允䅁䅁䅕㑈牘払敪歏䵁䅉䅅䅁䙁䅁䅁睁䵁䅁䅁权晁䅁䅁权呂䅁䅁权䙁䅁䅁兂䅁䅁䅁䑉浌䅑䅅䅁䉁䅁䅁兂⽁噎㘶卓硷䅑杷允䅁䅁䅕䅁䑁䅁䅷䅁䭁䅁䅁䅁䭁䙁䅍䅁䭁䅁䅕䅁䙁䅁䅁䅁杂⭹䅖允䅁䅁䅅䅁䙁䝁渳㘫确樸䅊䍄䉁䅁䅁兂䅁䅁䅍䅄䅁䅁䅯先䅁䅁䅯允䅁䅁䅯兂䅁䅁䅕䅁䅁䥁䩂欵䉁䅁䅁允䅁䅁䅕歲桦桥畓稱䴸䅉䅅䅁䕁䅁䅁睁䵁䅁䅁权偂䅁䅁权佂䅁䅁兂䅁䅁䅁䱙汮䅑䅅䅁䉁䅁䅁兂䥂場啯歲灦睐杷允䅁䅁䅕䅁䑁䅁䅷䅁䭁䉁䅯䅁䭁䅁䅅䅁䭁䅁䅕䅁䙁䅁䅁䅁䅁⭔䅚允䅁䅁䅅䅁䙁䭁睒児塲⭯⽧䍄䉁䅁䅁兂䅁䅁䅍䅄䅁䅁䅯䅈䅁䅁䅯睕䅁䅁䅯兂䅁䅁䅕䅁䅁䵁摃唵䉁䅁䅁允䅁䅁䅕捷桱扒穙啌䵁䅉䅅䅁䕁䅁䅁睁䵁䅁䅁权偂䅁䅁权佂䅁䅁兂䅁䅁䅁佷汄䅑䅅䅁䉁䅁䅁兂䙃ㄶ㑇潈䱕䅑杷允䅁䅁䅕䅁䑁䅁䅷䅁䭁䉁䅷䅁䭁䅁䅅䅁䭁䅁䅕䅁䙁䅁䅁䅁杂佰䅖允䅁䅁䅅䅁䙁䥁䌯匹捨㥪⽉䍄䉁䅁䅁兂䅁䅁䅍䅄䅁䅁䅯睈䅁䅁䅯允䅁䅁䅯兂䅁䅁䅕䅁䅁䅁偁欵䉁䅁䅁允䅁䅁䅕䡰㥁瑃橥䐴䴸䅉䅅䅁䙁䅁䅁睁䵁䅁䅁权䅁䅁䅁权䉁䅁䅁权䙁䅁䅁兂䅁䅁䅁䝷浮䅑䅅䅁䉁䅁䅁兂㑃潈牘払敪睐杷允䅁䅁䅕䅁䑁䅁䅷䅁䭁䅁䅁䅁䭁䙁䅍䅁䭁䅁䅕䅁䙁䅁䅁䅁杄併䅖允䅁䅁䅅䅁䙁䱁䩰䅄牉穊䅊䍄䉁䅁䅁兂䅁䅁䅍䅄䅁䅁䅯䅈䅁䅁䅯允䅁䅁䅯兂䅁䅁䅕䅁䅁䥁奂欵䉁䅁䅁允䅁䅁䅕椹捨㡪ㅌ䐲䴸䅉䅅䅁䕁䅁䅁睁䵁䅁䅁权偂䅁䅁权佂䅁䅁兂䅁䅁䅁䅯浦䅑䅅䅁䉁䅁䅁兂灁䥘䌯匹卧䅑杷允䅁䅁䅕䅁䑁䅁䅷䅁䭁䉁䄸䅁䭁䅁䅅䅁䭁䅁䅕䅁䙁䅁䅁䅁䅂畑䅚允䅁䅁䅅䅁䙁䭁睒児塲⭯⽁䍄䉁䅁䅁兂䅁䅁䅍䅄䅁䅁䅯睈䅁䅁䅯睕䅁䅁䅯兂䅁䅁䅕䅁䅁䕁潄唵䉁䅁䅁允䅁䅁䅕㥉㕶浦捰䕍䵁䅉䅅䅁䕁䅁䅁睁䵁䅁䅁权偂䅁䅁权佂䅁䅁兂䅁䅁䅁䉧浐䅑䅅䅁䉁䅁䅁兂穁積積積呍䅑杷允䅁䅁䅕䅁䑁䅁䅷䅁䭁䉁䅯䅁䭁䅁䅅䅁䭁䅁䅕䅁䙁䅁䅁䅁权畚䅚允䅁䅁䅅䅁䙁䭁睒児塲⭯⽧䍄䉁䅁䅁兂䅁䅁䅍䅄䅁䅁䅯䅁䅁䅁䅯允䅁䅁䅯兂䅁䅁䅕䅁䅁䅁䵁欵䉁䅁䅁允䅁䅁䅕䉵䘶ㄶ㑇樳䴸䅉䅅䅁䙁䅁䅁睁䵁䅁䅁权䅁䅁䅁权呂䅁䅁权䙁䅁䅁兂䅁䅁䅁䱁汶䅑䅅䅁䉁䅁䅁兂㑄⭕汏㑭祑䅑杷允䅁䅁䅑䅁䑁䅁䅷䅁䭁䕁䄸䅁䭁䕁䄴䅁䙁䅁䅁䅁䅂⭅䅚允䅁䅁䅅䅁䙁佁剸䉵䘶砶䅊䍄䉁䅁䅁䅂䅁䅁䅍䅄䅁䅁䅯睔䅁䅁䅯杔䅁䅁䅕䅁䅁䭁十欵䉁䅁䅁允䅁䅁䅕硥畓⭒㙆ぅ䵁䅉䅅䅁䕁䅁䅁睁䵁䅁䅁权偂䅁䅁权佂䅁䅁兂䅁䅁䅁䩙汢䅑䅅䅁䉁䅁䅁兂慃婭婭婭䩮睐杷允䅁䅁䅕䅁䑁䅁䅷䅁䭁䅁䅁䅁䭁䙁䅍䅁䭁䅁䅕䅁䙁䅁䅁䅁䅄⭈䅚允䅁䅁䅅䅁䙁䝁匸㡧䭄呁䅎䍄䉁䅁䅁兂䅁䅁䅍䅄䅁䅁䅯䅁䅁䅁䅯睕䅁䅁䅯兂䅁䅁䅕䅁䅁䕁杂欵䉁䅁䅁允䅁䅁䅕癱午坔兌き䵁䅉䅅䅁䙁䅁䅁睁䵁䅁䅁权䅁䅁䅁权呂䅁䅁权䙁䅁䅁兂䅁䅁䅁䵁汈䅑䅅䅁䉁䅁䅁兂㑄⭕汏㑭祑䅑杷允䅁䅁䅕䅁䑁䅁䅷䅁䭁䉁䄴䅁䭁䙁䅍䅁䭁䅁䅕䅁䙁䅁䅁䅁䅁佃䅚允䅁䅁䅅䅁䙁䅁䅁䅁䅁䍁䅰䍄䉁䅁䅁兂䅁䅁䅍䅄䅁䅁䅯睈䅁䅁䅯睕䅁䅁䅯兂䅁䅁䅕䅁䅁䅁睁欵䉁䅁䅁允䅁䅁䅕穐敖歵獫啍䵁䅉䅅䅁䕁䅁䅁睁䵁䅁䅁权偂䅁䅁权佂䅁䅁兂䅁䅁䅁佷汢䅑䅅䅁䉁䅁䅁兂歃䑣䬰㘱卍䅑杷允䅁䅁䅕䅁䑁䅁䅷䅁䭁䉁䅯䅁䭁䅁䅅䅁䭁䅁䅕䅁䙁䅁䅁䅁杁佉䅚允䅁䅁䅅䅁䙁䭁睒児塲⭯⽧䍄䉁䅁䅁兂䅁䅁䅍䅄䅁䅁䅯䅁䅁䅁䅯允䅁䅁䅯兂䅁䅁䅕䅁䅁䥁塁欵䉁䅁䅁允䅁䅁䅕䉵䘶ㄶ㑇樳䴸䅉䅅䅁䙁䅁䅁睁䵁䅁䅁权䅁䅁䅁权呂䅁䅁权䙁䅁䅁兂䅁䅁䅁䅧浶䅑䅅䅁䉁䅁䅁兂允䑗ね䩹祙䅑杷允䅁䅁䅕䅁䑁䅁䅷䅁䭁䉁䅷䅁䭁䙁䅍䅁䭁䅁䅕䅁䙁䅁䅁䅁䅂數䅖允䅁䅁䅅䅁䙁佁㙆䭆䠵卙䄵䍄䉁䅁䅁兂䅁䅁䅍䅄䅁䅁䅯睈䅁䅁䅯睕䅁䅁䅯兂䅁䅁䅕䅁䅁䥁䅂欵䉁䅁䅁允䅁䅁䅕㑎䉬余睕啍䵁䅉䅅䅁䙁䅁䅁睁䵁䅁䅁权晁䅁䅁权呂䅁䅁权䙁䅁䅁兂䅁䅁䅁䘴浔䅑䅅䅁䉁䅁䅁兂㥂穐敖極硫䅑杷允䅁䅁䅑䅁䑁䅁䅷䅁䭁䕁䄸䅁䭁䕁䄴䅁䙁䅁䅁䅁杂故䅚允䅁䅁䅅䅁䙁䙁偹癷潕䉘䅎䍄䉁䅁䅁兂䅁䅁䅍䅄䅁䅁䅯杈䅁䅁䅯允䅁䅁䅯兂䅁䅁䅕䅁䅁䕁啄唵䉁䅁䅁允䅁䅁䅕積積積積稰䴸䅉䅅䅁䙁䅁䅁睁䵁䅁䅁权晁䅁䅁权䉁䅁䅁权䙁䅁䅁兂䅁䅁䅁䕷浈䅑䅅䅁䉁䅁䅁兂歃䑣䬰㘱材睐杷允䅁䅁䅑䅁䑁䅁䅷䅁䭁䕁䄸䅁䭁䕁䄴䅁䙁䅁䅁䅁䅂⭁䅚允䅁䅁䅅䅁䙁䝁浚浚浚桚䅂䍄䉁䅁䅁兂䅁䅁䅍䅄䅁䅁䅯杈䅁䅁䅯睕䅁䅁䅯兂䅁䅁䅕䅁䅁䅁㙁欵䉁䅁䅁允䅁䅁䅕倹唳佥浬䕊䵁䅉䅅䅁䕁䅁䅁睁䵁䅁䅁权偂䅁䅁权佂䅁䅁兂䅁䅁䅁䅁洯䅑䅅䅁䉁䅁䅁兂歃䑣䬰㘱卍䅑杷允䅁䅁䅕䅁䑁䅁䅷䅁䭁䉁䄸䅁䭁䙁䅍䅁䭁䅁䅕䅁䙁䅁䅁䅁䅄伵䅖允䅁䅁䅅䅁䙁䱁昶楇搯䑒䅂䍄䉁䅁䅁兂䅁䅁䅍䅄䅁䅁䅯䅈䅁䅁䅯允䅁䅁䅯兂䅁䅁䅕䅁䅁䥁慁欵䉁䅁䅁允䅁䅁䅕歲桦桥畓稱䴸䅉䅅䅁䙁䅁䅁睁䵁䅁䅁权晁䅁䅁权呂䅁䅁权䙁䅁䅁兂䅁䅁䅁偙決䅑䅅䅁䉁䅁䅁兂偄ㄹ橐塰睳䅑杷允䅁䅁䅕䅁䑁䅁䅷䅁䭁䅁䅁䅁䭁䅁䅅䅁䭁䅁䅕䅁䙁䅁䅁䅁䅄⭁䅚允䅁䅁䅅䅁䙁䱁敧敨剴乵⼴䍄䉁䅁䅁兂䅁䅁䅍䅄䅁䅁䅯䅁䅁䅁䅯睕䅁䅁䅯兂䅁䅁䅕䅁䅁佁䱂欵䉁䅁䅁允䅁䅁䅕潅䅐煹䙈き䵁䅉䅅䅁䕁䅁䅁睁䵁䅁䅁权偂䅁䅁权佂䅁䅁兂䅁䅁䅁䱙汦䅑䅅䅁䉁䅁䅁兂慃婭婭婭桮睐杷允䅁䅁䅕䅁䑁䅁䅷䅁䭁䉁䄰䅁䭁䙁䅍䅁䭁䅁䅕䅁䙁䅁䅁䅁杁佘䅚允䅁䅁䅅䅁䙁䡁⼰噎㘶卓䄵䍄䉁䅁䅁䅂䅁䅁䅍䅄䅁䅁䅯睔䅁䅁䅯杔䅁䅁䅕䅁䅁䝁慄唵䉁䅁䅁允䅁䅁䅕㑈牘払敧啃䵁䅉䅅䅁䙁䅁䅁睁䵁䅁䅁权慁䅁䅁权呂䅁䅁权䙁䅁䅁兂䅁䅁䅁䉯洯䅑䅅䅁䉁䅁䅁兂㉃⼸唳䥥㙫䅑杷允䅁䅁䅑䅁䑁䅁䅷䅁䭁䕁䄸䅁䭁䕁䄴䅁䙁䅁䅁䅁䅃伴䅖允䅁䅁䅅䅁䙁䭁䠵場啯杲䅴䍄䉁䅁䅁兂䅁䅁䅍䅄䅁䅁䅯杇䅁䅁䅯允䅁䅁䅯兂䅁䅁䅕䅁䅁䥁偁欵䉁䅁䅁允䅁䅁䅕浚浚浚浚樵䴸䅉䅅䅁䙁䅁䅁睁䵁䅁䅁权敁䅁䅁权呂䅁䅁权䙁䅁䅁兂䅁䅁䅁䉑浶䅑䅅䅁䉁䅁䅁兂婁䙂余塌灉䅑杷允䅁䅁䅕䅁䑁䅁䅷䅁䭁䅁䅁䅁䭁䙁䅍䅁䭁䅁䅕䅁䙁䅁䅁䅁杁攵䅖允䅁䅁䅅䅁䙁䉁䕫杖琴樰䅊䍄䉁䅁䅁兂䅁䅁䅍䅄䅁䅁䅯䅁䅁䅁䅯睕䅁䅁䅯兂䅁䅁䅕䅁䅁佁摃唵䉁䅁䅁允䅁䅁䅕㘱睎児㍲䕍䵁䅉䅅䅁䙁䅁䅁睁䵁䅁䅁权摁䅁䅁权䉁䅁䅁权䙁䅁䅁兂䅁䅁䅁䡑浺䅑䅅䅁䉁䅁䅁兂畃⭒㙆䭆堷睐杷允䅁䅁䅕䅁䑁䅁䅷䅁䭁䉁䄴䅁䭁䙁䅍䅁䭁䅁䅕䅁䙁䅁䅁䅁杂佔䅚允䅁䅁䅅䅁䙁佁㠵穐敖楏䅒䍄䉁䅁䅁兂䅁䅁䅍䅄䅁䅁䅯䅈䅁䅁䅯允䅁䅁䅯兂䅁䅁䅕䅁䅁䥁㍃唵䉁䅁䅁允䅁䅁䅕㡪ㅌ䙋偹樰䴸䅉䅅䅁䙁䅁䅁睁䵁䅁䅁权捁䅁䅁权呂䅁䅁权䙁䅁䅁兂䅁䅁䅁佑氯䅑䅅䅁䉁䅁䅁兂㙃兓䍷㡋瑣䅑杷允䅁䅁䅑䅁䑁䅁䅷䅁䭁䕁䄸䅁䭁䕁䄴䅁䙁䅁䅁䅁䅃佄䅚允䅁䅁䅅䅁䙁䥁牘払敧剨䅊䍄䉁䅁䅁䅂䅁䅁䅍䅄䅁䅁䅯睔䅁䅁䅯杔䅁䅁䅕䅁䅁佁牃唵䉁䅁䅁允䅁䅁䅕場啯歲桦樲䴸䅉䅅䅁䙁䅁䅁睁䵁䅁䅁权晁䅁䅁权䉁䅁䅁权䙁䅁䅁兂䅁䅁䅁䍁浈䅑䅅䅁䉁䅁䅁兂㉄䙋偹癷杘睐杷允䅁䅁䅑䅁䑁䅁䅷䅁䭁䕁䄸䅁䭁䕁䄴䅁䙁䅁䅁䅁䅁佄䅚允䅁䅁䅅䅁䙁䥁䌯匹捨硪䅊䍄䉁䅁䅁䅂䅁䅁䅍䅄䅁䅁䅯睔䅁䅁䅯杔䅁䅁䅕䅁䅁䕁㙃唵䉁䅁䅁允䅁䅁䅕䅁䅁䅁䅁䐶䴸䅉䅅䅁䕁䅁䅁睁䵁䅁䅁权偂䅁䅁权佂䅁䅁兂䅁䅁䅁䅙浶䅑䅅䅁䉁䅁䅁兂歃䑣䬰㘱前䅑杷允䅁䅁䅕䅁䑁䅁䅷䅁䭁䅁䅁䅁䭁䅁䅅䅁䭁䅁䅕䅁䙁䅁䅁䅁杂數䅖允䅁䅁䅅䅁䙁䑁䬰㘱睎摐⽯䍄䉁䅁䅁兂䅁䅁䅍䅄䅁䅁䅯䅁䅁䅁䅯允䅁䅁䅯兂䅁䅁䅕䅁䅁䍁牁欵䉁䅁䅁允䅁䅁䅕䉵䘶ㄶ㑇樳䴸䅉䅅䅁䙁䅁䅁睁䵁䅁䅁权䅁䅁䅁权呂䅁䅁权䙁䅁䅁兂䅁䅁䅁䉯洯䅑䅅䅁䉁䅁䅁兂療潅䅐杹穅䅑杷允䅁䅁䅕䅁䑁䅁䅷䅁䭁䉁䅯䅁䭁䅁䅅䅁䭁䅁䅕䅁䙁䅁䅁䅁䅄畒䅚允䅁䅁䅅䅁䙁䭁睒児塲⭯⽧䍄䉁䅁䅁兂䅁䅁䅍䅄䅁䅁䅯先䅁䅁䅯允䅁䅁䅯兂䅁䅁䅕䅁䅁佁祁欵䉁䅁䅁允䅁䅁䅕歲桦桥畓稱䴸䅉䅅䅁䕁䅁䅁睁䵁䅁䅁权偂䅁䅁权佂䅁䅁兂䅁䅁䅁䅑浶䅑䅅䅁䉁䅁䅁兂硂児塲㍯剁䅑杷允䅁䅁䅕䅁䑁䅁䅷䅁䭁䉁䄰䅁䭁䙁䅍䅁䭁䅁䅕䅁䙁䅁䅁䅁杁敦䅚允䅁䅁䅅䅁䙁偁湃歸㍳卹䄱䍄䉁䅁䅁兂䅁䅁䅍䅄䅁䅁䅯䅈䅁䅁䅯睕䅁䅁䅯兂䅁䅁䅕䅁䅁䕁䍃欵䉁䅁䅁允䅁䅁䅕塹⭡确癱啌䵁䅉䅅䅁䙁䅁䅁睁䵁䅁䅁权䅁䅁䅁权䉁䅁䅁权䙁䅁䅁兂䅁䅁䅁䝙浺䅑䅅䅁䉁䅁䅁兂㑃潈牘払敪睐杷允䅁䅁䅕䅁䑁䅁䅷䅁䭁䉁䄰䅁䭁䅁䅅䅁䭁䅁䅕䅁䙁䅁䅁䅁杂⭯䅖允䅁䅁䅅䅁䙁乁橥䑣䬰㤱⽍䍄䉁䅁䅁䅂䅁䅁䅍䅄䅁䅁䅯睔䅁䅁䅯杔䅁䅁䅕䅁䅁䍁䱁欵䉁䅁䅁允䅁䅁䅕⽷潕䥘䌯啅䵁䅉䅅䅁䙁䅁䅁睁䵁䅁䅁权摁䅁䅁权呂䅁䅁权䙁䅁䅁兂䅁䅁䅁䵁汢䅑䅅䅁䉁䅁䅁兂䵂㑎䉬余瑕䅑杷允䅁䅁䅕䅁䑁䅁䅷䅁䭁䅁䅁䅁䭁䅁䅅䅁䭁䅁䅕䅁䙁䅁䅁䅁权畈䅚允䅁䅁䅅䅁䙁䱁敧敨剴乵⼴䍄䉁䅁䅁兂䅁䅁䅍䅄䅁䅁䅯䅁䅁䅁䅯睕䅁䅁䅯兂䅁䅁䅕䅁䅁䝁癁欵䉁䅁䅁允䅁䅁䅕扌摋㘷䝥き䵁䅉䅅䅁䙁䅁䅁睁䵁䅁䅁权敁䅁䅁权呂䅁䅁权䙁䅁䅁兂䅁䅁䅁䴴氳䅑䅅䅁䉁䅁䅁兂牁硨婢牺獣䅑杷允䅁䅁䅕䅁䑁䅁䅷䅁䭁䉁䄸䅁䭁䙁䅍䅁䭁䅁䅕䅁䙁䅁䅁䅁䅃敶䅖允䅁䅁䅅䅁䙁䵁㉬灶愸穌䅆䍄䉁䅁䅁䅂䅁䅁䅍䅄䅁䅁䅯睔䅁䅁䅯杔䅁䅁䅕䅁䅁䭁畃唵䉁䅁䅁允䅁䅁䅕牕敧敨剴䐲䴸䅉䅅䅁䙁䅁䅁睁䵁䅁䅁权慁䅁䅁权䉁䅁䅁权䙁䅁䅁兂䅁䅁䅁䱷汐䅑䅅䅁䉁䅁䅁兂䅁䅁䅁䅁杄睐杷允䅁䅁䅕䅁䑁䅁䅷䅁䭁䉁䄴䅁䭁䅁䅅䅁䭁䅁䅕䅁䙁䅁䅁䅁䅂佔䅚允䅁䅁䅅䅁䙁䵁ㅐ䙋偹瑷⽕䍄䉁䅁䅁䅂䅁䅁䅍䅄䅁䅁䅯睔䅁䅁䅯杔䅁䅁䅕䅁䅁䵁䭁欵䉁䅁䅁允䅁䅁䅕捺䵺䵺䵺啅䵁䅉䅅䅁䙁䅁䅁睁䵁䅁䅁权慁䅁䅁权呂䅁䅁权䙁䅁䅁兂䅁䅁䅁䑧浘䅑䅅䅁䉁䅁䅁兂晁敨剴乵㘴䅑杷允䅁䅁䅕䅁䑁䅁䅷䅁䭁䅁䅁䅁䭁䙁䅍䅁䭁䅁䅕䅁䙁䅁䅁䅁杄畕䅚允䅁䅁䅅䅁䙁䑁ね䡹⭡稳䅎䍄䉁䅁䅁兂䅁䅁䅍䅄䅁䅁䅯先䅁䅁䅯睕䅁䅁䅯兂䅁䅁䅕䅁䅁䥁婄唵䉁䅁䅁允䅁䅁䅕⽷潕䥘䌯啌䵁䅉䅅䅁䙁䅁䅁睁䵁䅁䅁权捁䅁䅁权䉁䅁䅁权䙁䅁䅁兂䅁䅁䅁倴汮䅑䅅䅁䉁䅁䅁兂晁敨剴䉵嘷睐杷允䅁䅁䅕䅁䑁䅁䅷䅁䭁䉁䅷䅁䭁䙁䅍䅁䭁䅁䅕䅁䙁䅁䅁䅁䅃略䅚允䅁䅁䅅䅁䙁䥁獴⼵灵匸䄱䍄䉁䅁䅁兂䅁䅁䅍䅄䅁䅁䅯䅁䅁䅁䅯睕䅁䅁䅯兂䅁䅁䅕䅁䅁佁㕁欵䉁䅁䅁允䅁䅁䅕䅁䅁䅁权き䵁䅉䅅䅁䙁䅁䅁睁䵁䅁䅁权敁䅁䅁权呂䅁䅁权䙁䅁䅁兂䅁䅁䅁䙷洷䅑䅅䅁䉁䅁䅁兂剃堷⽷噎椴䅑杷允䅁䅁䅑䅁䑁䅁䅷䅁䭁䕁䄸䅁䭁䕁䄴䅁䙁䅁䅁䅁权畃䅚允䅁䅁䅅䅁䙁䙁㑋潈牘剕䅊䍄䉁䅁䅁兂䅁䅁䅍䅄䅁䅁䅯杇䅁䅁䅯允䅁䅁䅯兂䅁䅁䅕䅁䅁䕁乁欵䉁䅁䅁允䅁䅁䅕浚浚浚浚樵䴸䅉䅅䅁䕁䅁䅁睁䵁䅁䅁权偂䅁䅁权佂䅁䅁兂䅁䅁䅁䅁浮䅑䅅䅁䉁䅁䅁兂䑄匹捨㡪剉䅑杷允䅁䅁䅑䅁䑁䅁䅷䅁䭁䕁䄸䅁䭁䕁䄴䅁䙁䅁䅁䅁杄佃䅚允䅁䅁䅅䅁䙁䱁敧敨剴䉵䅆䍄䉁䅁䅁兂䅁䅁䅍䅄䅁䅁䅯䅁䅁䅁䅯允䅁䅁䅯兂䅁䅁䅕䅁䅁䵁乂欵䉁䅁䅁允䅁䅁䅕䉵䘶ㄶ㑇樳䴸䅉䅅䅁䙁䅁䅁睁䵁䅁䅁权敁䅁䅁权䉁䅁䅁权䙁䅁䅁兂䅁䅁䅁䕯洳䅑䅅䅁䉁䅁䅁兂䑄匹捨㡪噌睐杷允䅁䅁䅕䅁䑁䅁䅷䅁䭁䅁䅁䅁䭁䙁䅍䅁䭁䅁䅕䅁䙁䅁䅁䅁䅂敺䅖允䅁䅁䅅䅁䙁䝁渳㘫确樸䅊䍄䉁䅁䅁兂䅁䅁䅍䅄䅁䅁䅯䅁䅁䅁䅯睕䅁䅁䅯兂䅁䅁䅕䅁䅁䵁湄唵䉁䅁䅁允䅁䅁䅕積積積呏歍䵁䅉䅅䅁䙁䅁䅁睁䵁䅁䅁权摁䅁䅁权䉁䅁䅁权䙁䅁䅁兂䅁䅁䅁䴴汪䅑䅅䅁䉁䅁䅁兂塄㍯㥁瑃呦睐杷允䅁䅁䅕䅁䑁䅁䅷䅁䭁䉁䄰䅁䭁䙁䅍䅁䭁䅁䅕䅁䙁䅁䅁䅁䅄伹䅖允䅁䅁䅅䅁䙁䭁扡䍸睃楳䄱䍄䉁䅁䅁兂䅁䅁䅍䅄䅁䅁䅯杈䅁䅁䅯睕䅁䅁䅯兂䅁䅁䅕䅁䅁䕁佄唵䉁䅁䅁允䅁䅁䅕㑋坣挲㌶䕌䵁䅉䅅䅁䙁䅁䅁睁䵁䅁䅁权慁䅁䅁权呂䅁䅁权䙁䅁䅁兂䅁䅁䅁䝑浮䅑䅅䅁䉁䅁䅁兂癁匳䝑噧㝕䅑杷允䅁䅁䅑䅁䑁䅁䅷䅁䭁䕁䄸䅁䭁䕁䄴䅁䙁䅁䅁䅁䅄佃䅚允䅁䅁䅅䅁䙁䙁偹癷潕䉘䅆䍄䉁䅁䅁兂䅁䅁䅍䅄䅁䅁䅯先䅁䅁䅯允䅁䅁䅯兂䅁䅁䅕䅁䅁䍁啂欵䉁䅁䅁允䅁䅁䅕歲桦桥畓稱䴸䅉䅅䅁䙁䅁䅁睁䵁䅁䅁权䅁䅁䅁权䉁䅁䅁权䙁䅁䅁兂䅁䅁䅁偯汮䅑䅅䅁䉁䅁䅁兂㑃潈牘払敪睐杷允䅁䅁䅕䅁䑁䅁䅷䅁䭁䅁䅁䅁䭁䅁䅅䅁䭁䅁䅕䅁䙁䅁䅁䅁杄位䅚允䅁䅁䅅䅁䙁䱁敧敨剴乵⼴䍄䉁䅁䅁兂䅁䅁䅍䅄䅁䅁䅯䅁䅁䅁䅯睕䅁䅁䅯兂䅁䅁䅕䅁䅁䅁橄唵䉁䅁䅁允䅁䅁䅕兇坒楄匳歍䵁䅉䅅䅁䙁䅁䅁睁䵁䅁䅁权慁䅁䅁权䉁䅁䅁权䙁䅁䅁兂䅁䅁䅁偙汢䅑䅅䅁䉁䅁䅁兂穁積積積橐睐杷允䅁䅁䅕䅁䑁䅁䅷䅁䭁䉁䄰䅁䭁䅁䅅䅁䭁䅁䅕䅁䙁䅁䅁䅁权畦䅚允䅁䅁䅅䅁䙁䭁䠵場啯瑲⽣䍄䉁䅁䅁兂䅁䅁䅍䅄䅁䅁䅯杈䅁䅁䅯睕䅁䅁䅯兂䅁䅁䅕䅁䅁䍁晃唵䉁䅁䅁允䅁䅁䅕㥉㕶浦㡰歋䵁䅉䅅䅁䙁䅁䅁睁䵁䅁䅁权敁䅁䅁权呂䅁䅁权䙁䅁䅁兂䅁䅁䅁䈴浦䅑䅅䅁䉁䅁䅁兂婁䙂余塌灉䅑杷允䅁䅁䅑䅁䑁䅁䅷䅁䭁䕁䄸䅁䭁䕁䄴䅁䙁䅁䅁䅁权⬷䅖允䅁䅁䅅䅁䙁佁㙆䭆䠵刴䅂䍄䉁䅁䅁兂䅁䅁䅍䅄䅁䅁䅯杇䅁䅁䅯允䅁䅁䅯兂䅁䅁䅕䅁䅁䝁䉂欵䉁䅁䅁允䅁䅁䅕䡰㥁瑃橥䐶䴸䅉䅅䅁䙁䅁䅁睁䵁䅁䅁权慁䅁䅁权呂䅁䅁权䙁䅁䅁兂䅁䅁䅁佷氳䅑䅅䅁䉁䅁䅁兂䑄匹捨㡪㕉䅑杷允䅁䅁䅕䅁䑁䅁䅷䅁䭁䅁䅁䅁䭁䙁䅍䅁䭁䅁䅕䅁䙁䅁䅁䅁䅂⬰䅖允䅁䅁䅅䅁䙁䭁慁㥌欰橂䅎䍄䉁䅁䅁䅂䅁䅁䅍䅄䅁䅁䅯睔䅁䅁䅯杔䅁䅁䅕䅁䅁䅁䝁欵䉁䅁䅁允䅁䅁䅕敨剴䉵䘶啅䵁䅉䅅䅁䙁䅁䅁睁䵁䅁䅁权䅁䅁䅁权呂䅁䅁权䙁䅁䅁兂䅁䅁䅁偷汪䅑䅅䅁䉁䅁䅁兂灁䥘䌯圹祧䅑杷允䅁䅁䅕䅁䑁䅁䅷䅁䭁䉁䄸䅁䭁䅁䅅䅁䭁䅁䅕䅁䙁䅁䅁䅁䅄⭇䅚允䅁䅁䅅䅁䙁偁潙䥘䌯改⽁䍄䉁䅁䅁兂䅁䅁䅍䅄䅁䅁䅯䅁䅁䅁䅯允䅁䅁䅯兂䅁䅁䅕䅁䅁䝁允欵䉁䅁䅁允䅁䅁䅕䉵䘶ㄶ㑇樳䴸䅉䅅䅁䙁䅁䅁睁䵁䅁䅁权䅁䅁䅁权䉁䅁䅁权䙁䅁䅁兂䅁䅁䅁乙汶䅑䅅䅁䉁䅁䅁兂桄桥畓⭒慈睐杷允䅁䅁䅕䅁䑁䅁䅷䅁䭁䉁䅷䅁䭁䙁䅍䅁䭁䅁䅕䅁䙁䅁䅁䅁䅄攰䅖允䅁䅁䅅䅁䙁䥁牘払敧卨䄵䍄䉁䅁䅁兂䅁䅁䅍䅄䅁䅁䅯先䅁䅁䅯允䅁䅁䅯兂䅁䅁䅕䅁䅁䝁䭄唵䉁䅁䅁允䅁䅁䅕㘱睎児塲稰䴸䅉䅅䅁䙁䅁䅁睁䵁䅁䅁权䅁䅁䅁权呂䅁䅁权䙁䅁䅁兂䅁䅁䅁䵯決䅑䅅䅁䉁䅁䅁兂瑂⼵灵昸祉䅑杷允䅁䅁䅑䅁䑁䅁䅷䅁䭁䕁䄸䅁䭁䕁䄴䅁䙁䅁䅁䅁杂敂䅚允䅁䅁䅅䅁䙁䡁啳歲桦桥䅆䍄䉁䅁䅁兂䅁䅁䅍䅄䅁䅁䅯杇䅁䅁䅯允䅁䅁䅯兂䅁䅁䅕䅁䅁䥁晄唵䉁䅁䅁允䅁䅁䅕椹捨㡪ㅌ䐴䴸䅉䅅䅁䙁䅁䅁睁䵁䅁䅁权䅁䅁䅁权䉁䅁䅁权䙁䅁䅁兂䅁䅁䅁乧汮䅑䅅䅁䉁䅁䅁兂桄桥畓⭒慈睐杷允䅁䅁䅕䅁䑁䅁䅷䅁䭁䉁䅯䅁䭁䙁䅍䅁䭁䅁䅕䅁䙁䅁䅁䅁杄住䅚允䅁䅁䅅䅁䙁䵁杕䡳潊呍䅴䍄䉁䅁䅁兂䅁䅁䅍䅄䅁䅁䅯先䅁䅁䅯允䅁䅁䅯兂䅁䅁䅕䅁䅁䵁奄唵䉁䅁䅁允䅁䅁䅕㘱睎児塲稰䴸䅉䅅䅁䙁䅁䅁睁䵁䅁䅁权晁䅁䅁权呂䅁䅁权䙁䅁䅁兂䅁䅁䅁䩁汪䅑䅅䅁䉁䅁䅁兂䅁䅁䅁佁睁䅑杷允䅁䅁䅕䅁䑁䅁䅷䅁䭁䉁䄸䅁䭁䙁䅍䅁䭁䅁䅕䅁䙁䅁䅁䅁杁敮䅖允䅁䅁䅅䅁䙁䩁䕺䱉祂䑋䅆䍄䉁䅁䅁兂䅁䅁䅍䅄䅁䅁䅯䅁䅁䅁䅯睕䅁䅁䅯兂䅁䅁䅕䅁䅁䥁塂欵䉁䅁䅁允䅁䅁䅕扏䥔牤昷き䵁䅉䅅䅁䙁䅁䅁睁䵁䅁䅁权敁䅁䅁权呂䅁䅁权䙁䅁䅁兂䅁䅁䅁䍁浲䅑䅅䅁䉁䅁䅁兂ㅂ硫䕧獖渴䅑杷允䅁䅁䅑䅁䑁䅁䅷䅁䭁䕁䄸䅁䭁䕁䄴䅁䙁䅁䅁䅁杄估䅖允䅁䅁䅅䅁䙁䝁浚浚浚杚䅚䍄䉁䅁䅁兂䅁䅁䅍䅄䅁䅁䅯先䅁䅁䅯睕䅁䅁䅯兂䅁䅁䅕䅁䅁䕁⽃唵䉁䅁䅁允䅁䅁䅕䑔䩥坑汄啌䵁䅉䅅䅁䙁䅁䅁睁䵁䅁䅁权晁䅁䅁权呂䅁䅁权䙁䅁䅁兂䅁䅁䅁佷汘䅑䅅䅁䉁䅁䅁兂⭃确癯唳睑䅑杷允䅁䅁䅑䅁䑁䅁䅷䅁䭁䕁䄸䅁䭁䕁䄴䅁䙁䅁䅁䅁䅂敂䅚允䅁䅁䅅䅁䙁䍁捬㡪ㅌ䉋䅆䍄䉁䅁䅁兂䅁䅁䅍䅄䅁䅁䅯睈䅁䅁䅯睕䅁䅁䅯兂䅁䅁䅕䅁䅁䥁扃唵䉁䅁䅁允䅁䅁䅕䵮村䡳潉啍䵁䅉䅅䅁䙁䅁䅁睁䵁䅁䅁权䅁䅁䅁权䉁䅁䅁权䙁䅁䅁兂䅁䅁䅁䥧浄䅑䅅䅁䉁䅁䅁兂㑃潈牘払敪睐杷允䅁䅁䅕䅁䑁䅁䅷䅁䭁䉁䄴䅁䭁䙁䅍䅁䭁䅁䅕䅁䙁䅁䅁䅁杂甲䅖允䅁䅁䅅䅁䙁䍁䝕婧䑖祩䅸䍄䉁䅁䅁䅂䅁䅁䅍䅄䅁䅁䅯睔䅁䅁䅯杔䅁䅁䅕䅁䅁䍁摃唵䉁䅁䅁允䅁䅁䅕硥畓⭒㙆䐱䴸䅉䅅䅁䕁䅁䅁睁䵁䅁䅁权偂䅁䅁权佂䅁䅁兂䅁䅁䅁䰴汶䅑䅅䅁䉁䅁䅁权扁䅁䅁䍄䉁䅁䅁兂䅁䅁䅍䅄䅁䅁䅯睈䅁䅁䅯睕䅁䅁䅯兂䅁䅁䅕䅁䅁䥁㉄唵䉁䅁䅁允䅁䅁䅕⽺呤㘴㝖䕍䵁䅉䅅䅁䙁䅁䅁睁䵁䅁䅁权敁䅁䅁权呂䅁䅁权䙁䅁䅁兂䅁䅁䅁䑉洯䅑䅅䅁䉁䅁䅁兂い搯㑒圶歙䅑杷允䅁䅁䅑䅁䑁䅁䅷䅁䭁䕁䄸䅁䭁䕁䄴䅁䙁䅁䅁䅁䅂當䅖允䅁䅁䅅䅁䙁佁剸䉵䘶⬶⽫䍄䉁䅁䅁兂䅁䅁䅍䅄䅁䅁䅯睈䅁䅁䅯睕䅁䅁䅯兂䅁䅁䅕䅁䅁䥁兄唵䉁䅁䅁允䅁䅁䅕杓䍷㑋坦䕍䵁䅉䅅䅁䕁䅁䅁睁䵁䅁䅁权偂䅁䅁权佂䅁䅁兂䅁䅁䅁䅷浐䅑䅅䅁䉁䅁䅁兂獄払敧敨关䅑杷允䅁䅁䅕䅁䑁䅁䅷䅁䭁䉁䄰䅁䭁䅁䅅䅁䭁䅁䅕䅁䙁䅁䅁䅁权敍䅚允䅁䅁䅅䅁䙁䭁䠵場啯瑲⽣䍄䉁䅁䅁兂䅁䅁䅍䅄䅁䅁䅯䅁䅁䅁䅯允䅁䅁䅯兂䅁䅁䅕䅁䅁佁噄唵䉁䅁䅁允䅁䅁䅕場啯歲桦樲䴸䅉䅅䅁䙁䅁䅁睁䵁䅁䅁权摁䅁䅁权呂䅁䅁权䙁䅁䅁兂䅁䅁䅁䄴洳䅑䅅䅁䉁䅁䅁兂㙃兓䍷㑋畣䅑杷允䅁䅁䅕䅁䑁䅁䅷䅁䭁䉁䅷䅁䭁䙁䅍䅁䭁䅁䅕䅁䙁䅁䅁䅁䅂⭕䅚允䅁䅁䅅䅁䙁乁欰潂噇祑䄵䍄䉁䅁䅁兂䅁䅁䅍䅄䅁䅁䅯䅁䅁䅁䅯睕䅁䅁䅯兂䅁䅁䅕䅁䅁䥁䙄唵䉁䅁䅁允䅁䅁䅕䘫橐婰䕵歍䵁䅉䅅䅁䙁䅁䅁睁䵁䅁䅁权捁䅁䅁权䉁䅁䅁权䙁䅁䅁兂䅁䅁䅁䍁浘䅑䅅䅁䉁䅁䅁兂畃⭒㙆䭆堷睐杷允䅁䅁䅕䅁䑁䅁䅷䅁䭁䉁䅯䅁䭁䙁䅍䅁䭁䅁䅕䅁䙁䅁䅁䅁䅃佦䅚允䅁䅁䅅䅁䙁䕁㍷啩杆告䅴䍄䉁䅁䅁䅂䅁䅁䅍䅄䅁䅁䅯睔䅁䅁䅯杔䅁䅁䅕䅁䅁䝁䑁欵䉁䅁䅁允䅁䅁䅕灭婭婭婭䕅䵁䅉䅅䅁䙁䅁䅁睁䵁䅁䅁权晁䅁䅁权呂䅁䅁权䙁䅁䅁兂䅁䅁䅁䕙浌䅑䅅䅁䉁䅁䅁兂㍁啩杆吵硁䅑杷允䅁䅁䅕䅁䑁䅁䅷䅁䭁䉁䅯䅁䭁䅁䅅䅁䭁䅁䅕䅁䙁䅁䅁䅁䅂佹䅖允䅁䅁䅅䅁䙁䅁䅁䅁䅁佁⽁䍄䉁䅁䅁兂䅁䅁䅍䅄䅁䅁䅯杇䅁䅁䅯睕䅁䅁䅯兂䅁䅁䅕䅁䅁䭁杄唵䉁䅁䅁允䅁䅁䅕⽷潕䥘椯問䵁䅉䅅䅁䙁䅁䅁睁䵁䅁䅁权敁䅁䅁权䉁䅁䅁权䙁䅁䅁兂䅁䅁䅁䩯汪䅑䅅䅁䉁䅁䅁兂穁積積積呐睐杷允䅁䅁䅑䅁䑁䅁䅷䅁䭁䕁䄸䅁䭁䕁䄴䅁䙁䅁䅁䅁权畁䅚允䅁䅁䅅䅁䙁䍁捬㡪ㅌ䉋䅂䍄䉁䅁䅁兂䅁䅁䅍䅄䅁䅁䅯䅁䅁䅁䅯睕䅁䅁䅯兂䅁䅁䅕䅁䅁䅁䅁欵䉁䅁䅁允䅁䅁䅕癱午坔睊歍䵁䅉䅅䅁䕁䅁䅁睁䵁䅁䅁权偂䅁䅁权佂䅁䅁兂䅁䅁䅁乁汈䅑䅅䅁䉁䅁䅁兂㉄䙋偹癷䝕䅑杷允䅁䅁䅑䅁䑁䅁䅷䅁䭁䕁䄸䅁䭁䕁䄴䅁䙁䅁䅁䅁䅃敁䅚允䅁䅁䅅䅁䙁乁橥䑣䬰眱䄹䍄䉁䅁䅁兂䅁䅁䅍䅄䅁䅁䅯䅈䅁䅁䅯允䅁䅁䅯兂䅁䅁䅕䅁䅁䕁慁欵䉁䅁䅁允䅁䅁䅕歲桦桥畓稱䴸䅉䅅䅁䙁䅁䅁睁䵁䅁䅁权捁䅁䅁权呂䅁䅁权䙁䅁䅁兂䅁䅁䅁䍉浔䅑䅅䅁䉁䅁䅁兂偃癷潕䅘甸䅑杷允䅁䅁䅕䅁䑁䅁䅷䅁䭁䉁䄸䅁䭁䙁䅍䅁䭁䅁䅕䅁䙁䅁䅁䅁权畋䅚允䅁䅁䅅䅁䙁䱁穢搯㑒呃䅆䍄䉁䅁䅁䅂䅁䅁䅍䅄䅁䅁䅯睔䅁䅁䅯杔䅁䅁䅕䅁䅁䅁䉁欵䉁䅁䅁允䅁䅁䅕敨剴䉵䘶い䵁䅉䅅䅁䙁䅁䅁睁䵁䅁䅁权捁䅁䅁权呂䅁䅁权䙁䅁䅁兂䅁䅁䅁䭷汶䅑䅅䅁䉁䅁䅁兂㉄䙋偹牷瑕䅑杷允䅁䅁䅑䅁䑁䅁䅷䅁䭁䕁䄸䅁䭁䕁䄴䅁䙁䅁䅁䅁杄佁䅚允䅁䅁䅅䅁䙁䝁浚浚浚杚䄵䍄䉁䅁䅁兂䅁䅁䅍䅄䅁䅁䅯䅁䅁䅁䅯睕䅁䅁䅯兂䅁䅁䅕䅁䅁佁塄唵䉁䅁䅁允䅁䅁䅕䉯癯匳䝑き䵁䅉䅅䅁䙁䅁䅁睁䵁䅁䅁权慁䅁䅁权呂䅁䅁权䙁䅁䅁兂䅁䅁䅁䡑浦䅑䅅䅁䉁䅁䅁兂䵂㑎䉬䍙㝕䅑杷允䅁䅁䅑䅁䑁䅁䅷䅁䭁䕁䄸䅁䭁䕁䄴䅁䙁䅁䅁䅁䅁佶䅖允䅁䅁䅅䅁䙁䑁積積積⭍⽳䍄䉁䅁䅁䅂䅁䅁䅍䅄䅁䅁䅯睔䅁䅁䅯杔䅁䅁䅕䅁䅁䥁㍄唵䉁䅁䅁允䅁䅁䅕浚浚浚浚歅䵁䅉䅅䅁䙁䅁䅁睁䵁䅁䅁权䅁䅁䅁权呂䅁䅁权䙁䅁䅁兂䅁䅁䅁䑁洯䅑䅅䅁䉁䅁䅁兂䅁䅁䅁䭁穁䅑杷允䅁䅁䅑䅁䑁䅁䅷䅁䭁䕁䄸䅁䭁䕁䄴䅁䙁䅁䅁䅁䅄佁䅚允䅁䅁䅅䅁䙁佁剸䉵䘶眶䄱䍄䉁䅁䅁兂䅁䅁䅍䅄䅁䅁䅯杈䅁䅁䅯睕䅁䅁䅯兂䅁䅁䅕䅁䅁䝁獂欵䉁䅁䅁允䅁䅁䅕匰扌堫焵啉䵁䅉䅅䅁䙁䅁䅁睁䵁䅁䅁权䅁䅁䅁权呂䅁䅁权䙁䅁䅁兂䅁䅁䅁䵑汘䅑䅅䅁䉁䅁䅁兂㑄⭕汏㑭祑䅑杷允䅁䅁䅕䅁䑁䅁䅷䅁䭁䅁䅁䅁䭁䙁䅍䅁䭁䅁䅕䅁䙁䅁䅁䅁杂教䅚允䅁䅁䅅䅁䙁䭁硲欰椱䐰䅎䍄䉁䅁䅁兂䅁䅁䅍䅄䅁䅁䅯睈䅁䅁䅯睕䅁䅁䅯兂䅁䅁䅕䅁䅁佁慂欵䉁䅁䅁允䅁䅁䅕匰扌堫䬴啍䵁䅉䅅䅁䙁䅁䅁睁䵁䅁䅁权䅁䅁䅁权呂䅁䅁权䙁䅁䅁兂䅁䅁䅁䔴浪䅑䅅䅁䉁䅁䅁兂十㡧䭄捯穕䅑杷允䅁䅁䅕䅁䑁䅁䅷䅁䭁䉁䄴䅁䭁䅁䅅䅁䭁䅁䅕䅁䙁䅁䅁䅁杂畺䅖允䅁䅁䅅䅁䙁䑁積積積㥍⽍䍄䉁䅁䅁兂䅁䅁䅍䅄䅁䅁䅯䅈䅁䅁䅯允䅁䅁䅯兂䅁䅁䅕䅁䅁䝁畄唵䉁䅁䅁允䅁䅁䅕積積積積稰䴸䅉䅅䅁䙁䅁䅁睁䵁䅁䅁权捁䅁䅁权䉁䅁䅁权䙁䅁䅁兂䅁䅁䅁䅁浺䅑䅅䅁䉁䅁䅁兂晁敨剴䉵嘷睐杷允䅁䅁䅕䅁䑁䅁䅷䅁䭁䉁䅷䅁䭁䅁䅅䅁䭁䅁䅕䅁䙁䅁䅁䅁杁畡䅚允䅁䅁䅅䅁䙁偁潙䥘䌯搹⽧䍄䉁䅁䅁䅂䅁䅁䅍䅄䅁䅁䅯睔䅁䅁䅯杔䅁䅁䅕䅁䅁䭁䅁欵䉁䅁䅁允䅁䅁䅕䥘䌯匹捨啄䵁䅉䅅䅁䙁䅁䅁睁䵁䅁䅁权摁䅁䅁权呂䅁䅁权䙁䅁䅁兂䅁䅁䅁䡧浐䅑䅅䅁䉁䅁䅁兂睄㡰䱚㡎瑫䅑杷允䅁䅁䅕䅁䑁䅁䅷䅁䭁䅁䅁䅁䭁䅁䅅䅁䭁䅁䅕䅁䙁䅁䅁䅁䅃敁䅚允䅁䅁䅅䅁䙁䱁敧敨剴乵⼴䍄䉁䅁䅁䅂䅁䅁䅍䅄䅁䅁䅯睔䅁䅁䅯杔䅁䅁䅕䅁䅁䵁⽄唵䉁䅁䅁允䅁䅁䅕灭婭婭婭啄䵁䅉䅅䅁䕁䅁䅁睁䵁䅁䅁权偂䅁䅁权佂䅁䅁兂䅁䅁䅁乑氳䅑䅅䅁䉁䅁䅁兂硂児塲㍯䩁䅑杷允䅁䅁䅕䅁䑁䅁䅷䅁䭁䉁䅯䅁䭁䅁䅅䅁䭁䅁䅕䅁䙁䅁䅁䅁杂畚䅚允䅁䅁䅅䅁䙁䭁睒児塲⭯⽧䍄䉁䅁䅁兂䅁䅁䅍䅄䅁䅁䅯䅁䅁䅁䅯睕䅁䅁䅯兂䅁䅁䅕䅁䅁䭁㝄唵䉁䅁䅁允䅁䅁䅕噋偹癷潖歍䵁䅉䅅䅁䕁䅁䅁睁䵁䅁䅁权偂䅁䅁权佂䅁䅁兂䅁䅁䅁偑氯䅑䅅䅁䉁䅁䅁兂䑄匹捨㡪䱉䅑杷允䅁䅁䅕䅁䑁䅁䅷䅁䭁䉁䅷䅁䭁䙁䅍䅁䭁䅁䅕䅁䙁䅁䅁䅁杂⭑䅚允䅁䅁䅅䅁䙁䉁婦発呤祯䄵䍄䉁䅁䅁兂䅁䅁䅍䅄䅁䅁䅯先䅁䅁䅯睕䅁䅁䅯兂䅁䅁䅕䅁䅁佁⽃唵䉁䅁䅁允䅁䅁䅕䑔䩥坑汄啌䵁䅉䅅䅁䙁䅁䅁睁䵁䅁䅁权䅁䅁䅁权呂䅁䅁权䙁䅁䅁兂䅁䅁䅁䌴浘䅑䅅䅁䉁䅁䅁兂汄䌰扌含稴䅑杷允䅁䅁䅕䅁䑁䅁䅷䅁䭁䉁䄸䅁䭁䅁䅅䅁䭁䅁䅕䅁䙁䅁䅁䅁䅂⭁䅚允䅁䅁䅅䅁䙁䅁䅁䅁䅁佁⽁䍄䉁䅁䅁兂䅁䅁䅍䅄䅁䅁䅯睈䅁䅁䅯睕䅁䅁䅯兂䅁䅁䅕䅁䅁䥁㝁欵䉁䅁䅁允䅁䅁䅕㑎䉬余睕啍䵁䅉䅅䅁䕁䅁䅁睁䵁䅁䅁权偂䅁䅁权佂䅁䅁兂䅁䅁䅁䭁汘䅑䅅䅁䉁䅁䅁兂浂浚浚浚坢睐杷允䅁䅁䅕䅁䑁䅁䅷䅁䭁䉁䅷䅁䭁䙁䅍䅁䭁䅁䅕䅁䙁䅁䅁䅁杄⭉䅚允䅁䅁䅅䅁䙁䥁䌯匹捨祄䄵䍄䉁䅁䅁䅂䅁䅁䅍䅄䅁䅁䅯睔䅁䅁䅯杔䅁䅁䅕䅁䅁䭁癃唵䉁䅁䅁允䅁䅁䅕牕敧敨剴䐲䴸䅉䅅䅁䕁䅁䅁睁䵁䅁䅁权偂䅁䅁权佂䅁䅁兂䅁䅁䅁䭷汪䅑䅅䅁䉁䅁䅁兂塄㍯㥁瑃呦睐杷允䅁䅁䅕䅁䑁䅁䅷䅁䭁䉁䄰䅁䭁䙁䅍䅁䭁䅁䅕䅁䙁䅁䅁䅁杄⭕䅚允䅁䅁䅅䅁䙁䵁ㅐ䙋偹楧䄵䍄䉁䅁䅁兂䅁䅁䅍䅄䅁䅁䅯䅁䅁䅁䅯睕䅁䅁䅯兂䅁䅁䅕䅁䅁佁䡂欵䉁䅁䅁允䅁䅁䅕潅䅐煹䙈き䵁䅉䅅䅁䙁䅁䅁睁䵁䅁䅁权慁䅁䅁权呂䅁䅁权䙁䅁䅁兂䅁䅁䅁䰴汮䅑䅅䅁䉁䅁䅁兂⽁噎㘶敓㕷䅑杷允䅁䅁䅑䅁䑁䅁䅷䅁䭁䕁䄸䅁䭁䕁䄴䅁䙁䅁䅁䅁杁⬯䅖允䅁䅁䅅䅁䙁䭁睒児塲睯䅸䍄䉁䅁䅁兂䅁䅁䅍䅄䅁䅁䅯杇䅁䅁䅯睕䅁䅁䅯兂䅁䅁䅕䅁䅁䭁䭂欵䉁䅁䅁允䅁䅁䅕䑔䩥坑䙂く䵁䅉䅅䅁䕁䅁䅁睁䵁䅁䅁权偂䅁䅁权佂䅁䅁兂䅁䅁䅁偉氷䅑䅅䅁䉁䅁䅁兂㉄䙋偹癷䵕䅑杷允䅁䅁䅑䅁䑁䅁䅷䅁䭁䕁䄸䅁䭁䕁䄴䅁䙁䅁䅁䅁杁佮䅖允䅁䅁䅅䅁䙁䭁睒児塲㥯⽁䍄䉁䅁䅁兂䅁䅁䅍䅄䅁䅁䅯䅁䅁䅁䅯允䅁䅁䅯兂䅁䅁䅕䅁䅁䅁䅃欵䉁䅁䅁允䅁䅁䅕䉵䘶ㄶ㑇樳䴸䅉䅅䅁䙁䅁䅁睁䵁䅁䅁权捁䅁䅁权䉁䅁䅁权䙁䅁䅁兂䅁䅁䅁乷汪䅑䅅䅁䉁䅁䅁兂穁積積積呐睐杷允䅁䅁䅕䅁䑁䅁䅷䅁䭁䉁䄸䅁䭁䙁䅍䅁䭁䅁䅕䅁䙁䅁䅁䅁杂佸䅖允䅁䅁䅅䅁䙁䵁㉬灶愸穌䅆䍄䉁䅁䅁䅂䅁䅁䅍䅄䅁䅁䅯睔䅁䅁䅯杔䅁䅁䅕䅁䅁䵁䑄唵䉁䅁䅁允䅁䅁䅕場啯歲桦樸䴸䅉䅅䅁䙁䅁䅁睁䵁䅁䅁权慁䅁䅁权䉁䅁䅁权䙁䅁䅁兂䅁䅁䅁䉁浶䅑䅅䅁䉁䅁䅁兂歃䑣䬰㘱潐睐杷允䅁䅁䅕䅁䑁䅁䅷䅁䭁䉁䄸䅁䭁䅁䅅䅁䭁䅁䅕䅁䙁䅁䅁䅁䅃畕䅚允䅁䅁䅅䅁䙁䙁㑋潈牘敕⽁䍄䉁䅁䅁䅂䅁䅁䅍䅄䅁䅁䅯睔䅁䅁䅯杔䅁䅁䅕䅁䅁䥁㡄唵䉁䅁䅁允䅁䅁䅕呣䬰㘱睎啄䵁䅉䅅䅁䙁䅁䅁睁䵁䅁䅁权捁䅁䅁权䉁䅁䅁权䙁䅁䅁兂䅁䅁䅁佑汔䅑䅅䅁䉁䅁䅁兂穁積積積呐睐杷允䅁䅁䅕䅁䑁䅁䅷䅁䭁䉁䄰䅁䭁䅁䅅䅁䭁䅁䅕䅁䙁䅁䅁䅁杄佥䅚允䅁䅁䅅䅁䙁䭁䠵場啯瑲⽣䍄䉁䅁䅁兂䅁䅁䅍䅄䅁䅁䅯先䅁䅁䅯睕䅁䅁䅯兂䅁䅁䅕䅁䅁䕁乁欵䉁䅁䅁允䅁䅁䅕歵䵫楁䡵歌䵁䅉䅅䅁䙁䅁䅁睁䵁䅁䅁权慁䅁䅁权䉁䅁䅁权䙁䅁䅁兂䅁䅁䅁䡯浮䅑䅅䅁䉁䅁䅁兂歃䑣䬰㘱潐睐杷允䅁䅁䅕䅁䑁䅁䅷䅁䭁䅁䅁䅁䭁䙁䅍䅁䭁䅁䅕䅁䙁䅁䅁䅁䅃略䅚允䅁䅁䅅䅁䙁䙁橔婰䕶䑁䅒䍄䉁䅁䅁兂䅁䅁䅍䅄䅁䅁䅯杇䅁䅁䅯睕䅁䅁䅯兂䅁䅁䅕䅁䅁䅁浄唵䉁䅁䅁允䅁䅁䅕⽷潕䥘椯問䵁䅉䅅䅁䙁䅁䅁睁䵁䅁䅁权慁䅁䅁权呂䅁䅁权䙁䅁䅁兂䅁䅁䅁䕷浌䅑䅅䅁䉁䅁䅁兂䙄䱉祂䑡㝅䅑杷允䅁䅁䅕䅁䑁䅁䅷䅁䭁䉁䄰䅁䭁䙁䅍䅁䭁䅁䅕䅁䙁䅁䅁䅁杁敁䅚允䅁䅁䅅䅁䙁䩁畨潅䅐楓䄵䍄䉁䅁䅁䅂䅁䅁䅍䅄䅁䅁䅯睔䅁䅁䅯杔䅁䅁䅕䅁䅁䝁㝄唵䉁䅁䅁允䅁䅁䅕㘱睎児塲啄䵁䅉䅅䅁䙁䅁䅁睁䵁䅁䅁权䅁䅁䅁权呂䅁䅁权䙁䅁䅁兂䅁䅁䅁䉷浶䅑䅅䅁䉁䅁䅁兂療潅䅐杹穅䅑杷允䅁䅁䅑䅁䑁䅁䅷䅁䭁䕁䄸䅁䭁䕁䄴䅁䙁䅁䅁䅁杄⬳䅖允䅁䅁䅅䅁䙁䑁積積積睍䅴䍄䉁䅁䅁兂䅁䅁䅍䅄䅁䅁䅯先䅁䅁䅯睕䅁䅁䅯兂䅁䅁䅕䅁䅁䝁乁欵䉁䅁䅁允䅁䅁䅕歵䵫楁䡵歌䵁䅉䅅䅁䙁䅁䅁睁䵁䅁䅁权晁䅁䅁权䉁䅁䅁权䙁䅁䅁兂䅁䅁䅁佧汪䅑䅅䅁䉁䅁䅁兂桄桥畓⭒慈睐杷允䅁䅁䅑䅁䑁䅁䅷䅁䭁䕁䄸䅁䭁䕁䄴䅁䙁䅁䅁䅁䅄甫䅖允䅁䅁䅅䅁䙁偁潙䥘䌯儹䄵䍄䉁䅁䅁兂䅁䅁䅍䅄䅁䅁䅯睈䅁䅁䅯睕䅁䅁䅯兂䅁䅁䅕䅁䅁䝁䍁欵䉁䅁䅁允䅁䅁䅕㡧䭄啯块䕍䵁䅉䅅䅁䙁䅁䅁睁䵁䅁䅁权䅁䅁䅁权䉁䅁䅁权䙁䅁䅁兂䅁䅁䅁偑氯䅑䅅䅁䉁䅁䅁兂㑃潈牘払敪睐杷允䅁䅁䅕䅁䑁䅁䅷䅁䭁䉁䅷䅁䭁䙁䅍䅁䭁䅁䅕䅁䙁䅁䅁䅁杄⭰䅖允䅁䅁䅅䅁䙁偁潙䥘䌯却䄱䍄䉁䅁䅁䅂䅁䅁䅍䅄䅁䅁䅯睔䅁䅁䅯杔䅁䅁䅕䅁䅁䵁歄唵䉁䅁䅁允䅁䅁䅕牕敧敨剴䕅䵁䅉䅅䅁䕁䅁䅁睁䵁䅁䅁权偂䅁䅁权佂䅁䅁兂䅁䅁䅁偧汲䅑䅅䅁䉁䅁䅁兂卂䉵䘶ㄶ佅䅑杷允䅁䅁䅕䅁䑁䅁䅷䅁䭁䅁䅁䅁䭁䅁䅅䅁䭁䅁䅕䅁䙁䅁䅁䅁䅄畍䅚允䅁䅁䅅䅁䙁䱁敧敨剴乵⼴䍄䉁䅁䅁兂䅁䅁䅍䅄䅁䅁䅯睈䅁䅁䅯睕䅁䅁䅯兂䅁䅁䅕䅁䅁䕁䵁欵䉁䅁䅁允䅁䅁䅕䙂余扌㥋䕍䵁䅉䅅䅁䕁䅁䅁睁䵁䅁䅁权偂䅁䅁权佂䅁䅁兂䅁䅁䅁偷汮䅑䅅䅁䉁䅁䅁兂塄㍯㥁瑃偣䅑杷允䅁䅁䅕䅁䑁䅁䅷䅁䭁䉁䅷䅁䭁䅁䅅䅁䭁䅁䅕䅁䙁䅁䅁䅁杁⭉䅚允䅁䅁䅅䅁䙁䭁䠵場啯瑲⽣䍄䉁䅁䅁兂䅁䅁䅍䅄䅁䅁䅯䅁䅁䅁䅯允䅁䅁䅯兂䅁䅁䅕䅁䅁䍁偁欵䉁䅁䅁允䅁䅁䅕䉵䘶ㄶ㑇樳䴸䅉䅅䅁䕁䅁䅁睁䵁䅁䅁权偂䅁䅁权佂䅁䅁兂䅁䅁䅁偁汮䅑䅅䅁䉁䅁䅁兂歃䑣䬰㘱位䅑杷允䅁䅁䅕䅁䑁䅁䅷䅁䭁䉁䅷䅁䭁䅁䅅䅁䭁䅁䅕䅁䙁䅁䅁䅁䅁佯䅖允䅁䅁䅅䅁䙁䥁䌯匹捨㥪⽉䍄䉁䅁䅁兂䅁䅁䅍䅄䅁䅁䅯䅁䅁䅁䅯允䅁䅁䅯兂䅁䅁䅕䅁䅁䍁癄唵䉁䅁䅁允䅁䅁䅕敨剴䉵䘶稲䴸䅉䅅䅁䙁䅁䅁睁䵁䅁䅁权摁䅁䅁权呂䅁䅁权䙁䅁䅁兂䅁䅁䅁余汐䅑䅅䅁䉁䅁䅁兂㑃潈牘晕獧䅑杷允䅁䅁䅕䅁䑁䅁䅷䅁䭁䉁䄴䅁䭁䙁䅍䅁䭁䅁䅕䅁䙁䅁䅁䅁䅂敺䅖允䅁䅁䅅䅁䙁䍁䡵瑆佮祴䅸䍄䉁䅁䅁兂䅁䅁䅍䅄䅁䅁䅯杈䅁䅁䅯睕䅁䅁䅯兂䅁䅁䅕䅁䅁䕁癁欵䉁䅁䅁允䅁䅁䅕体㙆䭆䠵歊䵁䅉䅅䅁䙁䅁䅁睁䵁䅁䅁权慁䅁䅁权䉁䅁䅁权䙁䅁䅁兂䅁䅁䅁䕯浮䅑䅅䅁䉁䅁䅁兂歃䑣䬰㘱潐睐杷允䅁䅁䅕䅁䑁䅁䅷䅁䭁䅁䅁䅁䭁䙁䅍䅁䭁䅁䅕䅁䙁䅁䅁䅁䅂⭶䅖允䅁䅁䅅䅁䙁偁周㘴扗䑨䅊䍄䉁䅁䅁䅂䅁䅁䅍䅄䅁䅁䅯睔䅁䅁䅯杔䅁䅁䅕䅁䅁佁汃唵䉁䅁䅁允䅁䅁䅕浚浚浚浚樱䴸䅉䅅䅁䙁䅁䅁睁䵁䅁䅁权摁䅁䅁权䉁䅁䅁权䙁䅁䅁兂䅁䅁䅁䵁氳䅑䅅䅁䉁䅁䅁兂塄㍯㥁瑃呦睐杷允䅁䅁䅕䅁䑁䅁䅷䅁䭁䅁䅁䅁䭁䅁䅅䅁䭁䅁䅕䅁䙁䅁䅁䅁䅁畸䅖允䅁䅁䅅䅁䙁䑁䬰㘱睎摐⽯䍄䉁䅁䅁兂䅁䅁䅍䅄䅁䅁䅯睈䅁䅁䅯睕䅁䅁䅯兂䅁䅁䅕䅁䅁䭁㡁欵䉁䅁䅁允䅁䅁䅕㑎䉬余睕啍䵁䅉䅅䅁䕁䅁䅁睁䵁䅁䅁权偂䅁䅁权佂䅁䅁兂䅁䅁䅁倴汪䅑䅅䅁䉁䅁䅁兂穁積積積免䅑杷允䅁䅁䅕䅁䑁䅁䅷䅁䭁䉁䄸䅁䭁䙁䅍䅁䭁䅁䅕䅁䙁䅁䅁䅁䅄畮䅖允䅁䅁䅅䅁䙁䩁䕺䱉祂䑋䅆䍄䉁䅁䅁䅂䅁䅁䅍䅄䅁䅁䅯睔䅁䅁䅯杔䅁䅁䅕䅁䅁䵁㑄唵䉁䅁䅁允䅁䅁䅕瑃橥䑣䬰い䵁䅉䅅䅁䙁䅁䅁睁䵁䅁䅁权䅁䅁䅁权䉁䅁䅁权䙁䅁䅁兂䅁䅁䅁䉁洷䅑䅅䅁䉁䅁䅁兂㑃潈牘払敪睐杷允䅁䅁䅕䅁䑁䅁䅷䅁䭁䉁䅯䅁䭁䙁䅍䅁䭁䅁䅕䅁䙁䅁䅁䅁杂男䅖允䅁䅁䅅䅁䙁䵁ㅐ䙋偹橷䅬䍄䉁䅁䅁兂䅁䅁䅍䅄䅁䅁䅯先䅁䅁䅯允䅁䅁䅯兂䅁䅁䅕䅁䅁佁㝄唵䉁䅁䅁允䅁䅁䅕㑈牘払敧吱䴸䅉䅅䅁䕁䅁䅁睁䵁䅁䅁权偂䅁䅁权佂䅁䅁兂䅁䅁䅁偑汪䅑䅅䅁䉁䅁䅁兂㥁瑃橥䑣匰䅑杷允䅁䅁䅕䅁䑁䅁䅷䅁䭁䉁䅷䅁䭁䙁䅍䅁䭁䅁䅕䅁䙁䅁䅁䅁杁畋䅚允䅁䅁䅅䅁䙁䥁䌯匹捨祄䄵䍄䉁䅁䅁兂䅁䅁䅍䅄䅁䅁䅯杇䅁䅁䅯睕䅁䅁䅯兂䅁䅁䅕䅁䅁䕁㡂欵䉁䅁䅁允䅁䅁䅕䑔䩥坑汁く䵁䅉䅅䅁䙁䅁䅁睁䵁䅁䅁权䅁䅁䅁权䉁䅁䅁权䙁䅁䅁兂䅁䅁䅁偙汢䅑䅅䅁䉁䅁䅁兂㑃潈牘払敪睐杷允䅁䅁䅕䅁䑁䅁䅷䅁䭁䉁䅷䅁䭁䙁䅍䅁䭁䅁䅕䅁䙁䅁䅁䅁杂⬲䅖允䅁䅁䅅䅁䙁䕁椵䙅㕧䍴䄵䍄䉁䅁䅁䅂䅁䅁䅍䅄䅁䅁䅯睔䅁䅁䅯杔䅁䅁䅕䅁䅁䭁㉄唵䉁䅁䅁允䅁䅁䅕䭆䠵場啯歅䵁䅉䅅䅁䕁䅁䅁睁䵁䅁䅁权偂䅁䅁权佂䅁䅁兂䅁䅁䅁偷汘䅑䅅䅁䉁䅁䅁兂卂䉵䘶ㄶ剅䅑杷允䅁䅁䅑䅁䑁䅁䅷䅁䭁䕁䄸䅁䭁䕁䄴䅁䙁䅁䅁䅁杂數䅖允䅁䅁䅅䅁䙁䑁䬰㘱睎晐⽙䍄䉁䅁䅁兂䅁䅁䅍䅄䅁䅁䅯䅁䅁䅁䅯睕䅁䅁䅯兂䅁䅁䅕䅁䅁䝁牂欵䉁䅁䅁允䅁䅁䅕佖汏㡭杔き䵁䅉䅅䅁䙁䅁䅁睁䵁䅁䅁权敁䅁䅁权䉁䅁䅁权䙁䅁䅁兂䅁䅁䅁䥑浈䅑䅅䅁䉁䅁䅁兂䅁䅁䅁䅁兄睐杷允䅁䅁䅕䅁䑁䅁䅷䅁䭁䉁䅷䅁䭁䅁䅅䅁䭁䅁䅕䅁䙁䅁䅁䅁䅂住䅚允䅁䅁䅅䅁䙁偁潙䥘䌯搹⽧䍄䉁䅁䅁兂䅁䅁䅍䅄䅁䅁䅯䅈䅁䅁䅯睕䅁䅁䅯兂䅁䅁䅕䅁䅁䝁婂欵䉁䅁䅁允䅁䅁䅕匳䝑婧䑖歌䵁䅉䅅䅁䕁䅁䅁睁䵁䅁䅁权偂䅁䅁权佂䅁䅁兂䅁䅁䅁偯汘䅑䅅䅁䉁䅁䅁兂浂浚浚浚剙䅑杷允䅁䅁䅕䅁䑁䅁䅷䅁䭁䉁䅯䅁䭁䅁䅅䅁䭁䅁䅕䅁䙁䅁䅁䅁杂佗䅚允䅁䅁䅅䅁䙁䭁睒児塲⭯⽧䍄䉁䅁䅁兂䅁䅁䅍䅄䅁䅁䅯䅈䅁䅁䅯睕䅁䅁䅯兂䅁䅁䅕䅁䅁佁坄唵䉁䅁䅁允䅁䅁䅕浔光䑗ね歌䵁䅉䅅䅁䙁䅁䅁睁䵁䅁䅁权䅁䅁䅁权呂䅁䅁权䙁䅁䅁兂䅁䅁䅁䙑浔䅑䅅䅁䉁䅁䅁兂㕁䵴㉨瑶稸䅑杷允䅁䅁䅑䅁䑁䅁䅷䅁䭁䕁䄸䅁䭁䕁䄴䅁䙁䅁䅁䅁权攷䅖允䅁䅁䅅䅁䙁䥁牘払敧全䄹䍄䉁䅁䅁兂䅁䅁䅍䅄䅁䅁䅯䅁䅁䅁䅯允䅁䅁䅯兂䅁䅁䅕䅁䅁䅁摃唵䉁䅁䅁允䅁䅁䅕灭婭婭婭吲䴸䅉䅅䅁䙁䅁䅁睁䵁䅁䅁权晁䅁䅁权䉁䅁䅁权䙁䅁䅁兂䅁䅁䅁乁汶䅑䅅䅁䉁䅁䅁兂乄䵺䵺䵺捺睐杷允䅁䅁䅑䅁䑁䅁䅷䅁䭁䕁䄸䅁䭁䕁䄴䅁䙁䅁䅁䅁䅃改䅖允䅁䅁䅅䅁䙁䝁浚浚浚桚䅆䍄䉁䅁䅁兂䅁䅁䅍䅄䅁䅁䅯䅁䅁䅁䅯睕䅁䅁䅯兂䅁䅁䅕䅁䅁䭁坄唵䉁䅁䅁允䅁䅁䅕䉯癯匳䝑き䵁䅉䅅䅁䙁䅁䅁睁䵁䅁䅁权慁䅁䅁权呂䅁䅁权䙁䅁䅁兂䅁䅁䅁䱯決䅑䅅䅁䉁䅁䅁兂㙃兓䍷祋㙣䅑杷允䅁䅁䅑䅁䑁䅁䅷䅁䭁䕁䄸䅁䭁䕁䄴䅁䙁䅁䅁䅁䅂改䅖允䅁䅁䅅䅁䙁佁㙆䭆䠵刴䅂䍄䉁䅁䅁兂䅁䅁䅍䅄䅁䅁䅯䅈䅁䅁䅯允䅁䅁䅯兂䅁䅁䅕䅁䅁䵁噄唵䉁䅁䅁允䅁䅁䅕積積積積稰䴸䅉䅅䅁䕁䅁䅁睁䵁䅁䅁权偂䅁䅁权佂䅁䅁兂䅁䅁䅁倴汔䅑䅅䅁䉁䅁䅁兂䑄匹捨㡪光䅑杷允䅁䅁䅕䅁䑁䅁䅷䅁䭁䅁䅁䅁䭁䙁䅍䅁䭁䅁䅕䅁䙁䅁䅁䅁䅂甯䅖允䅁䅁䅅䅁䙁䭁硲欰椱䑣䅊䍄䉁䅁䅁兂䅁䅁䅍䅄䅁䅁䅯䅁䅁䅁䅯睕䅁䅁䅯兂䅁䅁䅕䅁䅁䝁㉁欵䉁䅁䅁允䅁䅁䅕扌摋㘷䝥き䵁䅉䅅䅁䙁䅁䅁睁䵁䅁䅁权慁䅁䅁权䉁䅁䅁权䙁䅁䅁兂䅁䅁䅁䅧浌䅑䅅䅁䉁䅁䅁兂浂浚浚浚浢睐杷允䅁䅁䅑䅁䑁䅁䅷䅁䭁䕁䄸䅁䭁䕁䄴䅁䙁䅁䅁䅁䅂佷䅖允䅁䅁䅅䅁䙁䡁㥅瑃橥佣⼰䍄䉁䅁䅁兂䅁䅁䅍䅄䅁䅁䅯䅁䅁䅁䅯允䅁䅁䅯兂䅁䅁䅕䅁䅁䅁瑃唵䉁䅁䅁允䅁䅁䅕灭婭婭婭吲䴸䅉䅅䅁䙁䅁䅁睁䵁䅁䅁权晁䅁䅁权䉁䅁䅁权䙁䅁䅁兂䅁䅁䅁乙汐䅑䅅䅁䉁䅁䅁兂乄䵺䵺䵺捺睐杷允䅁䅁䅑䅁䑁䅁䅷䅁䭁䕁䄸䅁䭁䕁䄴䅁䙁䅁䅁䅁䅁伹䅖允䅁䅁䅅䅁䙁䭁䠵場啯杲䄹䍄䉁䅁䅁兂䅁䅁䅍䅄䅁䅁䅯杇䅁䅁䅯允䅁䅁䅯兂䅁䅁䅕䅁䅁䍁㝃唵䉁䅁䅁允䅁䅁䅕䅁䅁䅁䅁䐴䴸䅉䅅䅁䙁䅁䅁睁䵁䅁䅁权晁䅁䅁权呂䅁䅁权䙁䅁䅁兂䅁䅁䅁䩉汢䅑䅅䅁䉁䅁䅁兂䅁䅁䅁佁睁䅑杷允䅁䅁䅕䅁䑁䅁䅷䅁䭁䅁䅁䅁䭁䅁䅅䅁䭁䅁䅕䅁䙁䅁䅁䅁䅃收䅖允䅁䅁䅅䅁䙁䥁牘払敧摨⽳䍄䉁䅁䅁兂䅁䅁䅍䅄䅁䅁䅯杇䅁䅁䅯睕䅁䅁䅯兂䅁䅁䅕䅁䅁䥁㝃唵䉁䅁䅁允䅁䅁䅕穐敖歵獮問䵁䅉䅅䅁䕁䅁䅁睁䵁䅁䅁权偂䅁䅁权佂䅁䅁兂䅁䅁䅁䱷汐䅑䅅䅁䉁䅁䅁兂乄䵺䵺䵺捺睐杷允䅁䅁䅕䅁䑁䅁䅷䅁䭁䅁䅁䅁䭁䅁䅅䅁䭁䅁䅕䅁䙁䅁䅁䅁䅂甯䅖允䅁䅁䅅䅁䙁䱁敧敨剴乵⼴䍄䉁䅁䅁兂䅁䅁䅍䅄䅁䅁䅯杈䅁䅁䅯睕䅁䅁䅯兂䅁䅁䅕䅁䅁䝁流欵䉁䅁䅁允䅁䅁䅕婤奍䙂佢お䵁䅉䅅䅁䙁䅁䅁睁䵁䅁䅁权捁䅁䅁权呂䅁䅁权䙁䅁䅁兂䅁䅁䅁䕁浄䅑䅅䅁䉁䅁䅁兂塁挲㌷㙕畍䅑杷允䅁䅁䅕䅁䑁䅁䅷䅁䭁䉁䄴䅁䭁䅁䅅䅁䭁䅁䅕䅁䙁䅁䅁䅁杂畤䅚允䅁䅁䅅䅁䙁䅁䅁䅁䅁乁⽁䍄䉁䅁䅁兂䅁䅁䅍䅄䅁䅁䅯䅁䅁䅁䅯允䅁䅁䅯兂䅁䅁䅕䅁䅁䭁㝂欵䉁䅁䅁允䅁䅁䅕䉵䘶ㄶ㑇樳䴸䅉䅅䅁䙁䅁䅁睁䵁䅁䅁权䅁䅁䅁权呂䅁䅁权䙁䅁䅁兂䅁䅁䅁䍯浢䅑䅅䅁䉁䅁䅁兂汄䌰扌含稴䅑杷允䅁䅁䅕䅁䑁䅁䅷䅁䭁䉁䄸䅁䭁䙁䅍䅁䭁䅁䅕䅁䙁䅁䅁䅁权佤䅚允䅁䅁䅅䅁䙁䝁㡱䩤奍䑊䅆䍄䉁䅁䅁䅂䅁䅁䅍䅄䅁䅁䅯睔䅁䅁䅯杔䅁䅁䅕䅁䅁䕁汃唵䉁䅁䅁允䅁䅁䅕㑈牘払敧吱䴸䅉䅅䅁䕁䅁䅁睁䵁䅁䅁权偂䅁䅁权佂䅁䅁兂䅁䅁䅁偉汐䅑䅅䅁䉁䅁䅁兂穁積積積偍䅑杷允䅁䅁䅕䅁䑁䅁䅷䅁䭁䉁䄰䅁䭁䙁䅍䅁䭁䅁䅕䅁䙁䅁䅁䅁权敱䅖允䅁䅁䅅䅁䙁乁佮ㄹ橐印䄱䍄䉁䅁䅁兂䅁䅁䅍䅄䅁䅁䅯杈䅁䅁䅯允䅁䅁䅯兂䅁䅁䅕䅁䅁䍁卂欵䉁䅁䅁允䅁䅁䅕⽷潕䥘䌯吱䴸䅉䅅䅁䙁䅁䅁睁䵁䅁䅁权䅁䅁䅁权䉁䅁䅁权䙁䅁䅁兂䅁䅁䅁临決䅑䅅䅁䉁䅁䅁兂桄桥畓⭒慈睐杷允䅁䅁䅕䅁䑁䅁䅷䅁䭁䉁䅷䅁䭁䅁䅅䅁䭁䅁䅕䅁䙁䅁䅁䅁䅂畊䅚允䅁䅁䅅䅁䙁䭁䠵場啯瑲⽣䍄䉁䅁䅁兂䅁䅁䅍䅄䅁䅁䅯䅁䅁䅁䅯允䅁䅁䅯兂䅁䅁䅕䅁䅁佁歂欵䉁䅁䅁允䅁䅁䅕䉵䘶ㄶ㑇樳䴸䅉䅅䅁䙁䅁䅁睁䵁䅁䅁权摁䅁䅁权呂䅁䅁权䙁䅁䅁兂䅁䅁䅁䱉汪䅑䅅䅁䉁䅁䅁兂䭁㘱睎捐瑯䅑杷允䅁䅁䅕䅁䑁䅁䅷䅁䭁䉁䅷䅁䭁䙁䅍䅁䭁䅁䅕䅁䙁䅁䅁䅁䅂佔䅚允䅁䅁䅅䅁䙁䝁匸㡧䭄卙䄵䍄䉁䅁䅁䅂䅁䅁䅍䅄䅁䅁䅯睔䅁䅁䅯杔䅁䅁䅕䅁䅁䭁浃唵䉁䅁䅁允䅁䅁䅕積積積積稰䴸䅉䅅䅁䙁䅁䅁睁䵁䅁䅁权䅁䅁䅁权䉁䅁䅁权䙁䅁䅁兂䅁䅁䅁䕙浈䅑䅅䅁䉁䅁䅁兂㑃潈牘払敪睐杷允䅁䅁䅕䅁䑁䅁䅷䅁䭁䅁䅁䅁䭁䅁䅅䅁䭁䅁䅕䅁䙁䅁䅁䅁䅄⭇䅚允䅁䅁䅅䅁䙁䱁敧敨剴乵⼴䍄䉁䅁䅁兂䅁䅁䅍䅄䅁䅁䅯䅈䅁䅁䅯睕䅁䅁䅯兂䅁䅁䅕䅁䅁䝁い唵䉁䅁䅁允䅁䅁䅕歵䵫楁䡶啌䵁䅉䅅䅁䙁䅁䅁睁䵁䅁䅁权捁䅁䅁权䉁䅁䅁权䙁䅁䅁兂䅁䅁䅁䔴浺䅑䅅䅁䉁䅁䅁兂㉄䙋偹癷奘睐杷允䅁䅁䅑䅁䑁䅁䅷䅁䭁䕁䄸䅁䭁䕁䄴䅁䙁䅁䅁䅁䅃佳䅖允䅁䅁䅅䅁䙁䡁㥅瑃橥乣⼰䍄䉁䅁䅁䅂䅁䅁䅍䅄䅁䅁䅯睔䅁䅁䅯杔䅁䅁䅕䅁䅁䭁祄唵䉁䅁䅁允䅁䅁䅕瑃橥䑣䬰い䵁䅉䅅䅁䙁䅁䅁睁䵁䅁䅁权摁䅁䅁权呂䅁䅁权䙁䅁䅁兂䅁䅁䅁䕉浄䅑䅅䅁䉁䅁䅁兂䝂癴㥐䰱畧䅑杷允䅁䅁䅕䅁䑁䅁䅷䅁䭁䉁䄸䅁䭁䅁䅅䅁䭁䅁䅕䅁䙁䅁䅁䅁䅂⭎䅚允䅁䅁䅅䅁䙁䕁桪桥畓⭒⽅䍄䉁䅁䅁䅂䅁䅁䅍䅄䅁䅁䅯睔䅁䅁䅯杔䅁䅁䅕䅁䅁䅁祄唵䉁䅁䅁允䅁䅁䅕⽷潕䥘䌯啄䵁䅉䅅䅁䕁䅁䅁睁䵁䅁䅁权偂䅁䅁权佂䅁䅁兂䅁䅁䅁偙汈䅑䅅䅁䉁䅁䅁兂䭁㘱睎児偯䅑杷允䅁䅁䅑䅁䑁䅁䅷䅁䭁䕁䄸䅁䭁䕁䄴䅁䙁䅁䅁䅁杁攸䅖允䅁䅁䅅䅁䙁䑁積積積睍䄹䍄䉁䅁䅁兂䅁䅁䅍䅄䅁䅁䅯䅁䅁䅁䅯睕䅁䅁䅯兂䅁䅁䅕䅁䅁䝁䍃欵䉁䅁䅁允䅁䅁䅕琯㑒匶硢き䵁䅉䅅䅁䕁䅁䅁睁䵁䅁䅁权偂䅁䅁权佂䅁䅁兂䅁䅁䅁䩑汘䅑䅅䅁䉁䅁䅁兂慃婭婭婭䩮睐杷允䅁䅁䅑䅁䑁䅁䅷䅁䭁䕁䄸䅁䭁䕁䄴䅁䙁䅁䅁䅁䅂伸䅖允䅁䅁䅅䅁䙁䡁㥅瑃橥䉣䅂䍄䉁䅁䅁䅂䅁䅁䅍䅄䅁䅁䅯睔䅁䅁䅯杔䅁䅁䅕䅁䅁䝁畄唵䉁䅁䅁允䅁䅁䅕㑈牘払敧䕅䵁䅉䅅䅁䙁䅁䅁睁䵁䅁䅁权捁䅁䅁权䉁䅁䅁权䙁䅁䅁兂䅁䅁䅁䕉浄䅑䅅䅁䉁䅁䅁兂㉄䙋偹癷奘睐杷允䅁䅁䅕䅁䑁䅁䅷䅁䭁䉁䄰䅁䭁䅁䅅䅁䭁䅁䅕䅁䙁䅁䅁䅁杁⭕䅚允䅁䅁䅅䅁䙁䭁䠵場啯瑲⽣䍄䉁䅁䅁兂䅁䅁䅍䅄䅁䅁䅯先䅁䅁䅯睕䅁䅁䅯兂䅁䅁䅕䅁䅁䥁晁欵䉁䅁䅁允䅁䅁䅕瑃橥䑣䬳歌䵁䅉䅅䅁䙁䅁䅁睁䵁䅁䅁权敁䅁䅁权䉁䅁䅁权䙁䅁䅁兂䅁䅁䅁䍧浦䅑䅅䅁䉁䅁䅁兂䑄匹捨㡪噌睐杷允䅁䅁䅑䅁䑁䅁䅷䅁䭁䕁䄸䅁䭁䕁䄴䅁䙁䅁䅁䅁杄攷䅖允䅁䅁䅅䅁䙁䕁桪桥畓睒䄹䍄䉁䅁䅁兂䅁䅁䅍䅄䅁䅁䅯䅁䅁䅁䅯睕䅁䅁䅯兂䅁䅁䅕䅁䅁䅁㕃唵䉁䅁䅁允䅁䅁䅕歵䵫楁湳歍䵁䅉䅅䅁䙁䅁䅁睁䵁䅁䅁权摁䅁䅁权呂䅁䅁权䙁䅁䅁兂䅁䅁䅁䉉浺䅑䅅䅁䉁䅁䅁兂䭁㘱睎捐畯䅑杷允䅁䅁䅕䅁䑁䅁䅷䅁䭁䅁䅁䅁䭁䙁䅍䅁䭁䅁䅕䅁䙁䅁䅁䅁䅁数䅖允䅁䅁䅅䅁䙁乁橥䑣䬰穤䅆䍄䉁䅁䅁兂䅁䅁䅍䅄䅁䅁䅯杈䅁䅁䅯允䅁䅁䅯兂䅁䅁䅕䅁䅁䅁橃唵䉁䅁䅁允䅁䅁䅕積積積積稰䴸䅉䅅䅁䙁䅁䅁睁䵁䅁䅁权捁䅁䅁权䉁䅁䅁权䙁䅁䅁兂䅁䅁䅁临氯䅑䅅䅁䉁䅁䅁兂穁積積積呐睐杷允䅁䅁䅕䅁䑁䅁䅷䅁䭁䉁䅷䅁䭁䅁䅅䅁䭁䅁䅕䅁䙁䅁䅁䅁权留䅚允䅁䅁䅅䅁䙁偁潙䥘䌯搹⽧䍄䉁䅁䅁䅂䅁䅁䅍䅄䅁䅁䅯睔䅁䅁䅯杔䅁䅁䅕䅁䅁䵁獄唵䉁䅁䅁允䅁䅁䅕⽷潕䥘䌯い䵁䅉䅅䅁䙁䅁䅁睁䵁䅁䅁权䅁䅁䅁权呂䅁䅁权䙁䅁䅁兂䅁䅁䅁䝉洯䅑䅅䅁䉁䅁䅁兂啂㘴扗佸穁䅑杷允䅁䅁䅕䅁䑁䅁䅷䅁䭁䉁䄴䅁䭁䙁䅍䅁䭁䅁䅕䅁䙁䅁䅁䅁䅃伯䅖允䅁䅁䅅䅁䙁䱁䥔牤昶椲䅬䍄䉁䅁䅁䅂䅁䅁䅍䅄䅁䅁䅯睔䅁䅁䅯杔䅁䅁䅕䅁䅁䍁牄唵䉁䅁䅁允䅁䅁䅕䘷㑇潈牘䕅䵁䅉䅅䅁䕁䅁䅁睁䵁䅁䅁权偂䅁䅁权佂䅁䅁兂䅁䅁䅁佷汲䅑䅅䅁䉁䅁䅁兂䥂場啯歲剣䅑杷允䅁䅁䅕䅁䑁䅁䅷䅁䭁䅁䅁䅁䭁䅁䅅䅁䭁䅁䅕䅁䙁䅁䅁䅁杁伷䅖允䅁䅁䅅䅁䙁䥁牘払敧摨⽳䍄䉁䅁䅁兂䅁䅁䅍䅄䅁䅁䅯䅈䅁䅁䅯允䅁䅁䅯兂䅁䅁䅕䅁䅁䝁求欵䉁䅁䅁允䅁䅁䅕椹捨㡪ㅌ䐲䴸䅉䅅䅁䙁䅁䅁睁䵁䅁䅁权摁䅁䅁权呂䅁䅁权䙁䅁䅁兂䅁䅁䅁䉙浈䅑䅅䅁䉁䅁䅁兂㙃兓䍷㑋畣䅑杷允䅁䅁䅕䅁䑁䅁䅷䅁䭁䉁䄴䅁䭁䅁䅅䅁䭁䅁䅕䅁䙁䅁䅁䅁杄畁䅚允䅁䅁䅅䅁䙁䡁啳歲桦瑥⽑䍄䉁䅁䅁兂䅁䅁䅍䅄䅁䅁䅯杈䅁䅁䅯睕䅁䅁䅯兂䅁䅁䅕䅁䅁佁灁欵䉁䅁䅁允䅁䅁䅕婤奍䙂佢お䵁䅉䅅䅁䙁䅁䅁睁䵁䅁䅁权晁䅁䅁权呂䅁䅁权䙁䅁䅁兂䅁䅁䅁䜴洷䅑䅅䅁䉁䅁䅁兂䭁㘱睎卐硯䅑杷允䅁䅁䅑䅁䑁䅁䅷䅁䭁䕁䄸䅁䭁䕁䄴䅁䙁䅁䅁䅁杂甶䅖允䅁䅁䅅䅁䙁䉁䘫ㄶ㑇案䅆䍄䉁䅁䅁兂䅁䅁䅍䅄䅁䅁䅯杇䅁䅁䅯睕䅁䅁䅯兂䅁䅁䅕䅁䅁䅁⭁欵䉁䅁䅁允䅁䅁䅕卸睃浣硧く䵁䅉䅅䅁䙁䅁䅁睁䵁䅁䅁权晁䅁䅁权呂䅁䅁权䙁䅁䅁兂䅁䅁䅁䅉浈䅑䅅䅁䉁䅁䅁兂䑃䵷桱婒睙䅑杷允䅁䅁䅑䅁䑁䅁䅷䅁䭁䕁䄸䅁䭁䕁䄴䅁䙁䅁䅁䅁杁甶䅖允䅁䅁䅅䅁䙁䥁牘払敧剨䅂䍄䉁䅁䅁兂䅁䅁䅍䅄䅁䅁䅯先䅁䅁䅯睕䅁䅁䅯兂䅁䅁䅕䅁䅁佁⭁欵䉁䅁䅁允䅁䅁䅕牒穢搯㑓歌䵁䅉䅅䅁䙁䅁䅁睁䵁䅁䅁权慁䅁䅁权呂䅁䅁权䙁䅁䅁兂䅁䅁䅁䄴浌䅑䅅䅁䉁䅁䅁兂䝂癴㥐䈱㙧䅑杷允䅁䅁䅕䅁䑁䅁䅷䅁䭁䉁䄴䅁䭁䙁䅍䅁䭁䅁䅕䅁䙁䅁䅁䅁䅂敡䅚允䅁䅁䅅䅁䙁乁楅⼲⭬楡䅆䍄䉁䅁䅁兂䅁䅁䅍䅄䅁䅁䅯䅁䅁䅁䅯睕䅁䅁䅯兂䅁䅁䅕䅁䅁䅁⭂欵䉁䅁䅁允䅁䅁䅕琯㑒匶硢き䵁䅉䅅䅁䙁䅁䅁睁䵁䅁䅁权䅁䅁䅁权呂䅁䅁权䙁䅁䅁兂䅁䅁䅁䡯洯䅑䅅䅁䉁䅁䅁兂⭄䠱灪癊穅䅑杷允䅁䅁䅕䅁䑁䅁䅷䅁䭁䉁䄰䅁䭁䙁䅍䅁䭁䅁䅕䅁䙁䅁䅁䅁䅂畎䅚允䅁䅁䅅䅁䙁䙁余扌摋礷䄵䍄䉁䅁䅁兂䅁䅁䅍䅄䅁䅁䅯杈䅁䅁䅯睕䅁䅁䅯兂䅁䅁䅕䅁䅁䭁䥄唵䉁䅁䅁允䅁䅁䅕呣䬰㘱睍䕌䵁䅉䅅䅁䕁䅁䅁睁䵁䅁䅁权偂䅁䅁权佂䅁䅁兂䅁䅁䅁佁汲䅑䅅䅁䉁䅁䅁兂畃⭒㙆䭆儴䅑杷允䅁䅁䅕䅁䑁䅁䅷䅁䭁䅁䅁䅁䭁䅁䅅䅁䭁䅁䅕䅁䙁䅁䅁䅁䅄攷䅖允䅁䅁䅅䅁䙁䥁牘払敧摨⽳䍄䉁䅁䅁䅂䅁䅁䅍䅄䅁䅁䅯睔䅁䅁䅯杔䅁䅁䅕䅁䅁䍁灄唵䉁䅁䅁允䅁䅁䅕積積積積歅䵁䅉䅅䅁䕁䅁䅁睁䵁䅁䅁权偂䅁䅁权佂䅁䅁兂䅁䅁䅁佧汪䅑䅅䅁䉁䅁䅁兂䙃ㄶ㑇潈单䅑杷允䅁䅁䅕䅁䑁䅁䅷䅁䭁䉁䄰䅁䭁䙁䅍䅁䭁䅁䅕䅁䙁䅁䅁䅁䅂併䅖允䅁䅁䅅䅁䙁䅁塲㍯㥁楹䄱䍄䉁䅁䅁兂䅁䅁䅍䅄䅁䅁䅯杈䅁䅁䅯睕䅁䅁䅯兂䅁䅁䅕䅁䅁䥁睃唵䉁䅁䅁允䅁䅁䅕癴㥐䠱灨䕌䵁䅉䅅䅁䙁䅁䅁睁䵁䅁䅁权慁䅁䅁权呂䅁䅁权䙁䅁䅁兂䅁䅁䅁䭉汶䅑䅅䅁䉁䅁䅁兂摁浗㝑㐳㔸䅑杷允䅁䅁䅕䅁䑁䅁䅷䅁䭁䉁䄰䅁䭁䙁䅍䅁䭁䅁䅕䅁䙁䅁䅁䅁䅄⭳䅖允䅁䅁䅅䅁䙁䅁塲㍯㥁楹䄱䍄䉁䅁䅁兂䅁䅁䅍䅄䅁䅁䅯䅁䅁䅁䅯允䅁䅁䅯兂䅁䅁䅕䅁䅁䵁塄唵䉁䅁䅁允䅁䅁䅕場啯歲桦樲䴸䅉䅅䅁䙁䅁䅁睁䵁䅁䅁权慁䅁䅁权呂䅁䅁权䙁䅁䅁兂䅁䅁䅁佉汘䅑䅅䅁䉁䅁䅁兂䑄匹捨⭪㕉䅑杷允䅁䅁䅕䅁䑁䅁䅷䅁䭁䅁䅁䅁䭁䅁䅅䅁䭁䅁䅕䅁䙁䅁䅁䅁䅄伹䅖允䅁䅁䅅䅁䙁䱁敧敨剴乵⼴䍄䉁䅁䅁䅂䅁䅁䅍䅄䅁䅁䅯睔䅁䅁䅯杔䅁䅁䅕䅁䅁䝁权唵䉁䅁䅁允䅁䅁䅕歲桦桥畓稱䴸䅉䅅䅁䙁䅁䅁睁䵁䅁䅁权慁䅁䅁权呂䅁䅁权䙁䅁䅁兂䅁䅁䅁䕑浔䅑䅅䅁䉁䅁䅁兂䙄䱉祂䑡㝅䅑杷允䅁䅁䅕䅁䑁䅁䅷䅁䭁䉁䄴䅁䭁䙁䅍䅁䭁䅁䅕䅁䙁䅁䅁䅁䅁佥䅚允䅁䅁䅅䅁䙁䍁捬㡪ㅌ䍡䅆䍄䉁䅁䅁䅂䅁䅁䅍䅄䅁䅁䅯睔䅁䅁䅯杔䅁䅁䅕䅁䅁䭁湄唵䉁䅁䅁允䅁䅁䅕噋偹癷潕啅䵁䅉䅅䅁䙁䅁䅁睁䵁䅁䅁权摁䅁䅁权呂䅁䅁权䙁䅁䅁兂䅁䅁䅁䕑浔䅑䅅䅁䉁䅁䅁兂ㅂ硫䕧潖甴䅑杷允䅁䅁䅑䅁䑁䅁䅷䅁䭁䕁䄸䅁䭁䕁䄴䅁䙁䅁䅁䅁䅄畮䅖允䅁䅁䅅䅁䙁乁橥䑣䬰㤱⽍䍄䉁䅁䅁兂䅁䅁䅍䅄䅁䅁䅯䅁䅁䅁䅯睕䅁䅁䅯兂䅁䅁䅕䅁䅁䭁敁欵䉁䅁䅁允䅁䅁䅕硢䑋䵷䉯き䵁䅉䅅䅁䙁䅁䅁睁䵁䅁䅁权摁䅁䅁权呂䅁䅁权䙁䅁䅁兂䅁䅁䅁䑯浌䅑䅅䅁䉁䅁䅁兂坂楄礲敮甸䅑杷允䅁䅁䅑䅁䑁䅁䅷䅁䭁䕁䄸䅁䭁䕁䄴䅁䙁䅁䅁䅁杂⬵䅖允䅁䅁䅅䅁䙁䵁䴳䵺䵺䉺䅆䍄䉁䅁䅁䅂䅁䅁䅍䅄䅁䅁䅯睔䅁䅁䅯杔䅁䅁䅕䅁䅁䵁牃唵䉁䅁䅁允䅁䅁䅕捺䵺䵺䵺䐳䴸䅉䅅䅁䙁䅁䅁睁䵁䅁䅁权敁䅁䅁权䉁䅁䅁权䙁䅁䅁兂䅁䅁䅁䑷浪䅑䅅䅁䉁䅁䅁兂䑄匹捨㡪噌睐杷允䅁䅁䅕䅁䑁䅁䅷䅁䭁䉁䄴䅁䭁䙁䅍䅁䭁䅁䅕䅁䙁䅁䅁䅁䅄佶䅖允䅁䅁䅅䅁䙁䡁㥅瑃橥䍍䅸䍄䉁䅁䅁䅂䅁䅁䅍䅄䅁䅁䅯睔䅁䅁䅯杔䅁䅁䅕䅁䅁䍁䵄唵䉁䅁䅁允䅁䅁䅕䉵䘶ㄶ㑇歁䵁䅉䅅䅁䙁䅁䅁睁䵁䅁䅁权晁䅁䅁权呂䅁䅁权䙁䅁䅁兂䅁䅁䅁䡧浔䅑䅅䅁䉁䅁䅁兂煂䡶呓䍇硑䅑杷允䅁䅁䅑䅁䑁䅁䅷䅁䭁䕁䄸䅁䭁䕁䄴䅁䙁䅁䅁䅁权⭴䅖允䅁䅁䅅䅁䙁佁㙆䭆䠵攴⽉䍄䉁䅁䅁兂䅁䅁䅍䅄䅁䅁䅯杇䅁䅁䅯睕䅁䅁䅯兂䅁䅁䅕䅁䅁䝁祂欵䉁䅁䅁允䅁䅁䅕䑔䩥坑汁く䵁䅉䅅䅁䙁䅁䅁睁䵁䅁䅁权䅁䅁䅁权呂䅁䅁权䙁䅁䅁兂䅁䅁䅁䬴氳䅑䅅䅁䉁䅁䅁兂塄㍯㥁湃硣䅑杷允䅁䅁䅑䅁䑁䅁䅷䅁䭁䕁䄸䅁䭁䕁䄴䅁䙁䅁䅁䅁䅁电䅖允䅁䅁䅅䅁䙁佁㙆䭆䠵刴䅆䍄䉁䅁䅁䅂䅁䅁䅍䅄䅁䅁䅯睔䅁䅁䅯杔䅁䅁䅕䅁䅁䵁汄唵䉁䅁䅁允䅁䅁䅕噋偹癷潕啅䵁䅉䅅䅁䙁䅁䅁睁䵁䅁䅁权䅁䅁䅁权䉁䅁䅁权䙁䅁䅁兂䅁䅁䅁䕁浈䅑䅅䅁䉁䅁䅁兂㑃潈牘払敪睐杷允䅁䅁䅕䅁䑁䅁䅷䅁䭁䉁䄰䅁䭁䅁䅅䅁䭁䅁䅕䅁䙁䅁䅁䅁杄收䅖允䅁䅁䅅䅁䙁乁橥䑣䬰㤱⽍䍄䉁䅁䅁䅂䅁䅁䅍䅄䅁䅁䅯睔䅁䅁䅯杔䅁䅁䅕䅁䅁䭁汄唵䉁䅁䅁允䅁䅁䅕児塲㍯㥁啅䵁䅉䅅䅁䙁䅁䅁睁䵁䅁䅁权摁䅁䅁权呂䅁䅁权䙁䅁䅁兂䅁䅁䅁乧汈䅑䅅䅁䉁䅁䅁兂灁䥘䌯匹畧䅑杷允䅁䅁䅕䅁䑁䅁䅷䅁䭁䉁䅷䅁䭁䅁䅅䅁䭁䅁䅕䅁䙁䅁䅁䅁杄敹䅖允䅁䅁䅅䅁䙁䑁積積積㥍⽍䍄䉁䅁䅁兂䅁䅁䅍䅄䅁䅁䅯睈䅁䅁䅯睕䅁䅁䅯兂䅁䅁䅕䅁䅁䥁い唵䉁䅁䅁允䅁䅁䅕㥉㕶浦捰䕍䵁䅉䅅䅁䕁䅁䅁睁䵁䅁䅁权偂䅁䅁权佂䅁䅁兂䅁䅁䅁䵯汶䅑䅅䅁䉁䅁䅁兂晁敨剴䉵䈴䅑杷允䅁䅁䅕䅁䑁䅁䅷䅁䭁䅁䅁䅁䭁䅁䅅䅁䭁䅁䅕䅁䙁䅁䅁䅁杂佤䅚允䅁䅁䅅䅁䙁䱁敧敨剴乵⼴䍄䉁䅁䅁兂䅁䅁䅍䅄䅁䅁䅯杈䅁䅁䅯睕䅁䅁䅯兂䅁䅁䅕䅁䅁䍁汃唵䉁䅁䅁允䅁䅁䅕㝤昶楇搸か䵁䅉䅅䅁䙁䅁䅁睁䵁䅁䅁权䅁䅁䅁权呂䅁䅁权䙁䅁䅁兂䅁䅁䅁佑汄䅑䅅䅁䉁䅁䅁兂婁䙂余摌祉䅑杷允䅁䅁䅑䅁䑁䅁䅷䅁䭁䕁䄸䅁䭁䕁䄴䅁䙁䅁䅁䅁䅂伵䅖允䅁䅁䅅䅁䙁䅁䅁䅁䅁䉁䅆䍄䉁䅁䅁兂䅁䅁䅍䅄䅁䅁䅯先䅁䅁䅯睕䅁䅁䅯兂䅁䅁䅕䅁䅁䝁穁欵䉁䅁䅁允䅁䅁䅕杖琴灳瘳歌䵁䅉䅅䅁䙁䅁䅁睁䵁䅁䅁权晁䅁䅁权呂䅁䅁权䙁䅁䅁兂䅁䅁䅁䍙浢䅑䅅䅁䉁䅁䅁兂㉃⼸唳䅥硫䅑杷允䅁䅁䅑䅁䑁䅁䅷䅁䭁䕁䄸䅁䭁䕁䄴䅁䙁䅁䅁䅁杄⬴䅖允䅁䅁䅅䅁䙁䥁䌯匹捨硪䅆䍄䉁䅁䅁兂䅁䅁䅍䅄䅁䅁䅯杈䅁䅁䅯允䅁䅁䅯兂䅁䅁䅕䅁䅁䭁䕄唵䉁䅁䅁允䅁䅁䅕積積積積稰䴸䅉䅅䅁䙁䅁䅁睁䵁䅁䅁权䅁䅁䅁权呂䅁䅁权䙁䅁䅁兂䅁䅁䅁䵁氷䅑䅅䅁䉁䅁䅁兂瑂⼵灵昸祉䅑杷允䅁䅁䅕䅁䑁䅁䅷䅁䭁䅁䅁䅁䭁䅁䅅䅁䭁䅁䅕䅁䙁䅁䅁䅁杁⭶䅖允䅁䅁䅅䅁䙁䑁䬰㘱睎摐⽯䍄䉁䅁䅁兂䅁䅁䅍䅄䅁䅁䅯先䅁䅁䅯允䅁䅁䅯兂䅁䅁䅕䅁䅁佁啁欵䉁䅁䅁允䅁䅁䅕㑈牘払敧吱䴸䅉䅅䅁䕁䅁䅁睁䵁䅁䅁权偂䅁䅁权佂䅁䅁兂䅁䅁䅁佷汐䅑䅅䅁䉁䅁䅁兂㝂䭆䠵場副䅑杷允䅁䅁䅕䅁䑁䅁䅷䅁䭁䅁䅁䅁䭁䙁䅍䅁䭁䅁䅕䅁䙁䅁䅁䅁䅁畏䅚允䅁䅁䅅䅁䙁䅁䅁䅁䅁䑯䅎䍄䉁䅁䅁兂䅁䅁䅍䅄䅁䅁䅯先䅁䅁䅯睕䅁䅁䅯兂䅁䅁䅕䅁䅁䭁歂欵䉁䅁䅁允䅁䅁䅕呦ㄸ牘䩰歌䵁䅉䅅䅁䕁䅁䅁睁䵁䅁䅁权偂䅁䅁权佂䅁䅁兂䅁䅁䅁乷氯䅑䅅䅁䉁䅁䅁兂㉄䙋偹癷䭕䅑杷允䅁䅁䅑䅁䑁䅁䅷䅁䭁䕁䄸䅁䭁䕁䄴䅁䙁䅁䅁䅁䅂⬴䅖允䅁䅁䅅䅁䙁䡁啳歲桦桥䅂䍄䉁䅁䅁兂䅁䅁䅍䅄䅁䅁䅯睈䅁䅁䅯允䅁䅁䅯兂䅁䅁䅕䅁䅁䭁潃唵䉁䅁䅁允䅁䅁䅯睇䅁䅁杷允䅁䅁䅕䅁䑁䅁䅷䅁䭁䉁䄴䅁䭁䙁䅍䅁䭁䅁䅕䅁䙁䅁䅁䅁杂佉䅚允䅁䅁䅅䅁䙁䉁䕫杖琴楣䅬䍄䉁䅁䅁䅂䅁䅁䅍䅄䅁䅁䅯睔䅁䅁䅯杔䅁䅁䅕䅁䅁䍁扄唵䉁䅁䅁允䅁䅁䅕⽷潕䥘䌯啃䵁䅉䅅䅁䙁䅁䅁睁䵁䅁䅁权䅁䅁䅁权䉁䅁䅁权䙁䅁䅁兂䅁䅁䅁䝙浦䅑䅅䅁䉁䅁䅁兂㑃潈牘払敪睐杷允䅁䅁䅑䅁䑁䅁䅷䅁䭁䕁䄸䅁䭁䕁䄴䅁䙁䅁䅁䅁杄甴䅖允䅁䅁䅅䅁䙁䑁積積積睍䄹䍄䉁䅁䅁兂䅁䅁䅍䅄䅁䅁䅯先䅁䅁䅯睕䅁䅁䅯兂䅁䅁䅕䅁䅁䭁䭁欵䉁䅁䅁允䅁䅁䅕䝭匴㡧䭂歌䵁䅉䅅䅁䙁䅁䅁睁䵁䅁䅁权敁䅁䅁权呂䅁䅁权䙁䅁䅁兂䅁䅁䅁佷汶䅑䅅䅁䉁䅁䅁兂穂䩡瑈䑦猸䅑杷允䅁䅁䅑䅁䑁䅁䅷䅁䭁䕁䄸䅁䭁䕁䄴䅁䙁䅁䅁䅁杁估䅖允䅁䅁䅅䅁䙁䅁塲㍯㥁权䅤䍄䉁䅁䅁兂䅁䅁䅍䅄䅁䅁䅯先䅁䅁䅯睕䅁䅁䅯兂䅁䅁䅕䅁䅁䍁⭄唵䉁䅁䅁允䅁䅁䅕余兘瑉㕶啌䵁䅉䅅䅁䙁䅁䅁睁䵁䅁䅁权摁䅁䅁权呂䅁䅁权䙁䅁䅁兂䅁䅁䅁䉷浔䅑䅅䅁䉁䅁䅁兂㙃兓䍷㑋畣䅑杷允䅁䅁䅕䅁䑁䅁䅷䅁䭁䅁䅁䅁䭁䅁䅅䅁䭁䅁䅕䅁䙁䅁䅁䅁䅂伳䅖允䅁䅁䅅䅁䙁佁㙆䭆䠵搴⽯䍄䉁䅁䅁兂䅁䅁䅍䅄䅁䅁䅯先䅁䅁䅯允䅁䅁䅯兂䅁䅁䅕䅁䅁䝁ㅃ唵䉁䅁䅁允䅁䅁䅕㘱睎児塲稰䴸䅉䅅䅁䙁䅁䅁睁䵁䅁䅁权䅁䅁䅁权呂䅁䅁权䙁䅁䅁兂䅁䅁䅁䱉汲䅑䅅䅁䉁䅁䅁兂㑄⭕汏㑭祑䅑杷允䅁䅁䅑䅁䑁䅁䅷䅁䭁䕁䄸䅁䭁䕁䄴䅁䙁䅁䅁䅁䅃甴䅖允䅁䅁䅅䅁䙁䡁啳歲桦来䄵䍄䉁䅁䅁兂䅁䅁䅍䅄䅁䅁䅯杇䅁䅁䅯睕䅁䅁䅯兂䅁䅁䅕䅁䅁佁歂欵䉁䅁䅁允䅁䅁䅕灶愸㥌欱く䵁䅉䅅䅁䙁䅁䅁睁䵁䅁䅁权敁䅁䅁权䉁䅁䅁权䙁䅁䅁兂䅁䅁䅁䠴浺䅑䅅䅁䉁䅁䅁兂䅁䅁䅁䅁兄睐杷允䅁䅁䅕䅁䑁䅁䅷䅁䭁䉁䅷䅁䭁䙁䅍䅁䭁䅁䅕䅁䙁䅁䅁䅁权佁䅚允䅁䅁䅅䅁䙁偁潙䥘䌯卤䄱䍄䉁䅁䅁兂䅁䅁䅍䅄䅁䅁䅯䅁䅁䅁䅯睕䅁䅁䅯兂䅁䅁䅕䅁䅁佁佂欵䉁䅁䅁允䅁䅁䅕潅䅐煹䙈き䵁䅉䅅䅁䕁䅁䅁睁䵁䅁䅁权偂䅁䅁权佂䅁䅁兂䅁䅁䅁佯汈䅑䅅䅁䉁䅁䅁兂桄桥畓⭒䵅䅑杷允䅁䅁䅕䅁䑁䅁䅷䅁䭁䉁䅯䅁䭁䅁䅅䅁䭁䅁䅕䅁䙁䅁䅁䅁䅄佁䅚允䅁䅁䅅䅁䙁䝁浚浚浚畚⽙䍄䉁䅁䅁兂䅁䅁䅍䅄䅁䅁䅯先䅁䅁䅯允䅁䅁䅯兂䅁䅁䅕䅁䅁䵁⭂欵䉁䅁䅁允䅁䅁䅕歲桦桥畓稱䴸䅉䅅䅁䕁䅁䅁睁䵁䅁䅁权偂䅁䅁权佂䅁䅁兂䅁䅁䅁余汄䅑䅅䅁䉁䅁䅁兂䑄匹捨㡪䱉䅑杷允䅁䅁䅑䅁䑁䅁䅷䅁䭁䕁䄸䅁䭁䕁䄴䅁䙁䅁䅁䅁杁畯䅖允䅁䅁䅅䅁䙁䵁ㅐ䙋偹瑷⽕䍄䉁䅁䅁兂䅁䅁䅍䅄䅁䅁䅯杇䅁䅁䅯允䅁䅁䅯兂䅁䅁䅕䅁䅁䝁ㅁ欵䉁䅁䅁允䅁䅁䅕䡰㥁瑃橥䐶䴸䅉䅅䅁䙁䅁䅁睁䵁䅁䅁权䅁䅁䅁权䉁䅁䅁权䙁䅁䅁兂䅁䅁䅁䙉浮䅑䅅䅁䉁䅁䅁兂㑃潈牘払敪睐杷允䅁䅁䅕䅁䑁䅁䅷䅁䭁䉁䄸䅁䭁䙁䅍䅁䭁䅁䅕䅁䙁䅁䅁䅁䅂畘䅚允䅁䅁䅅䅁䙁乁楅⼲⭬橃䅆䍄䉁䅁䅁䅂䅁䅁䅍䅄䅁䅁䅯睔䅁䅁䅯杔䅁䅁䅕䅁䅁䭁晄唵䉁䅁䅁允䅁䅁䅕積積積積ぃ䵁䅉䅅䅁䙁䅁䅁睁䵁䅁䅁权慁䅁䅁权呂䅁䅁权䙁䅁䅁兂䅁䅁䅁䉷浪䅑䅅䅁䉁䅁䅁兂㉃⼸唳䥥㙫䅑杷允䅁䅁䅕䅁䑁䅁䅷䅁䭁䉁䄰䅁䭁䅁䅅䅁䭁䅁䅕䅁䙁䅁䅁䅁䅁併䅖允䅁䅁䅅䅁䙁乁橥䑣䬰㤱⽍䍄䉁䅁䅁兂䅁䅁䅍䅄䅁䅁䅯䅈䅁䅁䅯睕䅁䅁䅯兂䅁䅁䅕䅁䅁䭁䩁欵䉁䅁䅁允䅁䅁䅕椹捨㡪ㅊ啌䵁䅉䅅䅁䕁䅁䅁睁䵁䅁䅁权偂䅁䅁权佂䅁䅁兂䅁䅁䅁䱷汮䅑䅅䅁䉁䅁䅁兂卂䉵䘶ㄶ潈睐杷允䅁䅁䅕䅁䑁䅁䅷䅁䭁䉁䅷䅁䭁䙁䅍䅁䭁䅁䅕䅁䙁䅁䅁䅁杁⭥䅚允䅁䅁䅅䅁䙁䥁獴⼵灵匸䄱䍄䉁䅁䅁䅂䅁䅁䅍䅄䅁䅁䅯睔䅁䅁䅯杔䅁䅁䅕䅁䅁䍁䥄唵䉁䅁䅁允䅁䅁䅕積積積積稫䴸䅉䅅䅁䙁䅁䅁睁䵁䅁䅁权晁䅁䅁权呂䅁䅁权䙁䅁䅁兂䅁䅁䅁䩑汘䅑䅅䅁䉁䅁䅁兂䅁䅁䅁佁睁䅑杷允䅁䅁䅕䅁䑁䅁䅷䅁䭁䅁䅁䅁䭁䅁䅅䅁䭁䅁䅕䅁䙁䅁䅁䅁权畴䅖允䅁䅁䅅䅁䙁䩁婱婭婭摭⽫䍄䉁䅁䅁䅂䅁䅁䅍䅄䅁䅁䅯睔䅁䅁䅯杔䅁䅁䅕䅁䅁䵁敄唵䉁䅁䅁允䅁䅁䅕噋偹癷潕歃䵁䅉䅅䅁䙁䅁䅁睁䵁䅁䅁权敁䅁䅁权呂䅁䅁权䙁䅁䅁兂䅁䅁䅁䰴汔䅑䅅䅁䉁䅁䅁兂㉃⼸唳䝥獫䅑杷允䅁䅁䅕䅁䑁䅁䅷䅁䭁䅁䅁䅁䭁䅁䅅䅁䭁䅁䅕䅁䙁䅁䅁䅁䅃何䅚允䅁䅁䅅䅁䙁䱁敧敨剴乵⼴䍄䉁䅁䅁兂䅁䅁䅍䅄䅁䅁䅯䅁䅁䅁䅯睕䅁䅁䅯兂䅁䅁䅕䅁䅁䵁㕃唵䉁䅁䅁允䅁䅁䅕歵䵫楁湳歍䵁䅉䅅䅁䙁䅁䅁睁䵁䅁䅁权䅁䅁䅁权呂䅁䅁权䙁䅁䅁兂䅁䅁䅁䅉洷䅑䅅䅁䉁䅁䅁兂允䑗ね䩹祙䅑杷允䅁䅁䅑䅁䑁䅁䅷䅁䭁䕁䄸䅁䭁䕁䄴䅁䙁䅁䅁䅁䅃佯䅖允䅁䅁䅅䅁䙁䝁浚浚浚瑚⽙䍄䉁䅁䅁兂䅁䅁䅍䅄䅁䅁䅯睈䅁䅁䅯睕䅁䅁䅯兂䅁䅁䅕䅁䅁佁㡃唵䉁䅁䅁允䅁䅁䅕塹⭡确癯啍䵁䅉䅅䅁䕁䅁䅁睁䵁䅁䅁权偂䅁䅁权佂䅁䅁兂䅁䅁䅁乯汢䅑䅅䅁䉁䅁䅁兂㝂䭆䠵場䵯䅑杷允䅁䅁䅕䅁䑁䅁䅷䅁䭁䅁䅁䅁䭁䅁䅅䅁䭁䅁䅕䅁䙁䅁䅁䅁䅄佯䅖允䅁䅁䅅䅁䙁䩁婱婭婭摭⽫䍄䉁䅁䅁䅂䅁䅁䅍䅄䅁䅁䅯睔䅁䅁䅯杔䅁䅁䅕䅁䅁䍁敄唵䉁䅁䅁允䅁䅁䅕呣䬰㘱睎啃䵁䅉䅅䅁䙁䅁䅁睁䵁䅁䅁权敁䅁䅁权呂䅁䅁权䙁䅁䅁兂䅁䅁䅁䝑洳䅑䅅䅁䉁䅁䅁兂剄瑉㕶浦桯䅑杷允䅁䅁䅑䅁䑁䅁䅷䅁䭁䕁䄸䅁䭁䕁䄴䅁䙁䅁䅁䅁䅄攳䅖允䅁䅁䅅䅁䙁䩁婱婭婭六䅬䍄䉁䅁䅁兂䅁䅁䅍䅄䅁䅁䅯睈䅁䅁䅯睕䅁䅁䅯兂䅁䅁䅕䅁䅁佁祄唵䉁䅁䅁允䅁䅁䅕㥉㕶浦捰䕍䵁䅉䅅䅁䙁䅁䅁睁䵁䅁䅁权慁䅁䅁权䉁䅁䅁权䙁䅁䅁兂䅁䅁䅁䙷浄䅑䅅䅁䉁䅁䅁兂歃䑣䬰㘱潐睐杷允䅁䅁䅕䅁䑁䅁䅷䅁䭁䉁䄸䅁䭁䙁䅍䅁䭁䅁䅕䅁䙁䅁䅁䅁䅂畧䅚允䅁䅁䅅䅁䙁䝁汄䌰扌含䅂䍄䉁䅁䅁䅂䅁䅁䅍䅄䅁䅁䅯睔䅁䅁䅯杔䅁䅁䅕䅁䅁䭁塄唵䉁䅁䅁允䅁䅁䅕捺䵺䵺䵺歃䵁䅉䅅䅁䙁䅁䅁睁䵁䅁䅁权敁䅁䅁权呂䅁䅁权䙁䅁䅁兂䅁䅁䅁乧氯䅑䅅䅁䉁䅁䅁兂硂児塲⽯牁䅑杷允䅁䅁䅕䅁䑁䅁䅷䅁䭁䉁䅯䅁䭁䙁䅍䅁䭁䅁䅕䅁䙁䅁䅁䅁权攷䅖允䅁䅁䅅䅁䙁䵁ㅐ䙋偹橷䅬䍄䉁䅁䅁兂䅁䅁䅍䅄䅁䅁䅯䅁䅁䅁䅯睕䅁䅁䅯兂䅁䅁䅕䅁䅁䭁䝂欵䉁䅁䅁允䅁䅁䅕潅䅐煹䙈き䵁䅉䅅䅁䙁䅁䅁睁䵁䅁䅁权敁䅁䅁权呂䅁䅁权䙁䅁䅁兂䅁䅁䅁䵷汲䅑䅅䅁䉁䅁䅁兂牁硨婢牺獣䅑杷允䅁䅁䅑䅁䑁䅁䅷䅁䭁䕁䄸䅁䭁䕁䄴䅁䙁䅁䅁䅁䅁攳䅖允䅁䅁䅅䅁䙁䙁㑋潈牘兕䅨䍄䉁䅁䅁兂䅁䅁䅍䅄䅁䅁䅯杇䅁䅁䅯允䅁䅁䅯兂䅁䅁䅕䅁䅁䕁摄唵䉁䅁䅁允䅁䅁䅕椹捨㡪ㅌ䐴䴸䅉䅅䅁䙁䅁䅁睁䵁䅁䅁权䅁䅁䅁权呂䅁䅁权䙁䅁䅁兂䅁䅁䅁偙汦䅑䅅䅁䉁䅁䅁兂灁䥘䌯圹祧䅑杷允䅁䅁䅑䅁䑁䅁䅷䅁䭁䕁䄸䅁䭁䕁䄴䅁䙁䅁䅁䅁䅄伳䅖允䅁䅁䅅䅁䙁䥁䌯匹捨睪䅚䍄䉁䅁䅁䅂䅁䅁䅍䅄䅁䅁䅯睔䅁䅁䅯杔䅁䅁䅕䅁䅁䥁扄唵䉁䅁䅁允䅁䅁䅕呣䬰㘱睎あ䵁䅉䅅䅁䙁䅁䅁睁䵁䅁䅁权捁䅁䅁权呂䅁䅁权䙁䅁䅁兂䅁䅁䅁䍑浦䅑䅅䅁䉁䅁䅁兂偃癷潕䅘甸䅑杷允䅁䅁䅕䅁䑁䅁䅷䅁䭁䅁䅁䅁䭁䙁䅍䅁䭁䅁䅕䅁䙁䅁䅁䅁䅃畱䅖允䅁䅁䅅䅁䙁乁橥䑣䬰穤䅆䍄䉁䅁䅁兂䅁䅁䅍䅄䅁䅁䅯䅁䅁䅁䅯允䅁䅁䅯兂䅁䅁䅕䅁䅁佁啁欵䉁䅁䅁允䅁䅁䅕䉵䘶ㄶ㑇樳䴸䅉䅅䅁䙁䅁䅁睁䵁䅁䅁权敁䅁䅁权呂䅁䅁权䙁䅁䅁兂䅁䅁䅁䙧浮䅑䅅䅁䉁䅁䅁兂扄堫焵䡶楑䅑杷允䅁䅁䅕䅁䑁䅁䅷䅁䭁䅁䅁䅁䭁䅁䅅䅁䭁䅁䅕䅁䙁䅁䅁䅁䅁畕䅚允䅁䅁䅅䅁䙁䱁敧敨剴乵⼴䍄䉁䅁䅁兂䅁䅁䅍䅄䅁䅁䅯杇䅁䅁䅯允䅁䅁䅯兂䅁䅁䅕䅁䅁䭁奄唵䉁䅁䅁允䅁䅁䅕椹捨㡪ㅌ䐴䴸䅉䅅䅁䙁䅁䅁睁䵁䅁䅁权捁䅁䅁权呂䅁䅁权䙁䅁䅁兂䅁䅁䅁乧汶䅑䅅䅁䉁䅁䅁兂佂桙奂扏畑䅑杷允䅁䅁䅕䅁䑁䅁䅷䅁䭁䅁䅁䅁䭁䙁䅍䅁䭁䅁䅕䅁䙁䅁䅁䅁杄畦䅚允䅁䅁䅅䅁䙁偁唷佥浫吸䅎䍄䉁䅁䅁䅂䅁䅁䅍䅄䅁䅁䅯睔䅁䅁䅯杔䅁䅁䅕䅁䅁䝁扄唵䉁䅁䅁允䅁䅁䅕㡪ㅌ䙋偹䕃䵁䅉䅅䅁䙁䅁䅁睁䵁䅁䅁权慁䅁䅁权䉁䅁䅁权䙁䅁䅁兂䅁䅁䅁䍉浌䅑䅅䅁䉁䅁䅁兂歃䑣䬰㘱潐睐杷允䅁䅁䅕䅁䑁䅁䅷䅁䭁䉁䄸䅁䭁䅁䅅䅁䭁䅁䅕䅁䙁䅁䅁䅁权低䅚允䅁䅁䅅䅁䙁䕁桪桥畓⭒⽅䍄䉁䅁䅁䅂䅁䅁䅍䅄䅁䅁䅯睔䅁䅁䅯杔䅁䅁䅕䅁䅁䍁慄唵䉁䅁䅁允䅁䅁䅕䉵䘶ㄶ㑇䕃䵁䅉䅅䅁䙁䅁䅁睁䵁䅁䅁权晁䅁䅁权呂䅁䅁权䙁䅁䅁兂䅁䅁䅁倴汐䅑䅅䅁䉁䅁䅁兂橁⼲⭬污睷䅑杷允䅁䅁䅑䅁䑁䅁䅷䅁䭁䕁䄸䅁䭁䕁䄴䅁䙁䅁䅁䅁杄佹䅖允䅁䅁䅅䅁䙁䡁啳歲桦癥⽷䍄䉁䅁䅁䅂䅁䅁䅍䅄䅁䅁䅯睔䅁䅁䅯杔䅁䅁䅕䅁䅁䥁婄唵䉁䅁䅁允䅁䅁䅕䘷㑇潈牘あ䵁䅉䅅䅁䙁䅁䅁睁䵁䅁䅁权䅁䅁䅁权呂䅁䅁权䙁䅁䅁兂䅁䅁䅁䩧汘䅑䅅䅁䉁䅁䅁兂㡃䩤奍䡂睙䅑杷允䅁䅁䅕䅁䑁䅁䅷䅁䭁䅁䅁䅁䭁䙁䅍䅁䭁䅁䅕䅁䙁䅁䅁䅁䅁⭂䅚允䅁䅁䅅䅁䙁䭁硲欰椱䑣䅊䍄䉁䅁䅁兂䅁䅁䅍䅄䅁䅁䅯䅁䅁䅁䅯睕䅁䅁䅯兂䅁䅁䅕䅁䅁䵁偂欵䉁䅁䅁允䅁䅁䅕扏䥔牤昷き䵁䅉䅅䅁䕁䅁䅁睁䵁䅁䅁权偂䅁䅁权佂䅁䅁兂䅁䅁䅁乙汪䅑䅅䅁䉁䅁䅁兂畃⭒㙆䭆䨴䅑杷允䅁䅁䅕䅁䑁䅁䅷䅁䭁䅁䅁䅁䭁䙁䅍䅁䭁䅁䅕䅁䙁䅁䅁䅁杁敇䅚允䅁䅁䅅䅁䙁䝁匸㡧䭄呁䅎䍄䉁䅁䅁兂䅁䅁䅍䅄䅁䅁䅯先䅁䅁䅯允䅁䅁䅯兂䅁䅁䅕䅁䅁佁㑄唵䉁䅁䅁允䅁䅁䅕㑈牘払敧吱䴸䅉䅅䅁䙁䅁䅁睁䵁䅁䅁权摁䅁䅁权呂䅁䅁权䙁䅁䅁兂䅁䅁䅁䕧浪䅑䅅䅁䉁䅁䅁兂ㅂ硫䕧潖甴䅑杷允䅁䅁䅑䅁䑁䅁䅷䅁䭁䕁䄸䅁䭁䕁䄴䅁䙁䅁䅁䅁䅁⬱䅖允䅁䅁䅅䅁䙁䭁睒児塲睯䅰䍄䉁䅁䅁兂䅁䅁䅍䅄䅁䅁䅯䅁䅁䅁䅯允䅁䅁䅯兂䅁䅁䅕䅁䅁䵁㙁欵䉁䅁䅁允䅁䅁䅕䉵䘶ㄶ㑇樳䴸䅉䅅䅁䙁䅁䅁睁䵁䅁䅁权摁䅁䅁权䉁䅁䅁权䙁䅁䅁兂䅁䅁䅁䅯浔䅑䅅䅁䉁䅁䅁兂晁敨剴䉵嘷睐杷允䅁䅁䅕䅁䑁䅁䅷䅁䭁䅁䅁䅁䭁䙁䅍䅁䭁䅁䅕䅁䙁䅁䅁䅁杄畗䅚允䅁䅁䅅䅁䙁䭁硲欰椱䐰䅎䍄䉁䅁䅁兂䅁䅁䅍䅄䅁䅁䅯䅈䅁䅁䅯睕䅁䅁䅯兂䅁䅁䅕䅁䅁䥁睃唵䉁䅁䅁允䅁䅁䅕㝤昶楇搸歌䵁䅉䅅䅁䙁䅁䅁睁䵁䅁䅁权晁䅁䅁权呂䅁䅁权䙁䅁䅁兂䅁䅁䅁䉷浺䅑䅅䅁䉁䅁䅁兂䝂癴㥐倱睧䅑杷允䅁䅁䅕䅁䑁䅁䅷䅁䭁䉁䄰䅁䭁䙁䅍䅁䭁䅁䅕䅁䙁䅁䅁䅁杄救䅚允䅁䅁䅅䅁䙁䕁㉡⼸唳䍵䄵䍄䉁䅁䅁䅂䅁䅁䅍䅄䅁䅁䅯睔䅁䅁䅯杔䅁䅁䅕䅁䅁䍁坄唵䉁䅁䅁允䅁䅁䅕䘷㑇潈牘あ䵁䅉䅅䅁䙁䅁䅁睁䵁䅁䅁权慁䅁䅁权呂䅁䅁权䙁䅁䅁兂䅁䅁䅁䉙浶䅑䅅䅁䉁䅁䅁兂㉃⼸唳䥥㙫䅑杷允䅁䅁䅕䅁䑁䅁䅷䅁䭁䅁䅁䅁䭁䙁䅍䅁䭁䅁䅕䅁䙁䅁䅁䅁䅄佖䅚允䅁䅁䅅䅁䙁䑁ね䡹⭡稳䅎䍄䉁䅁䅁䅂䅁䅁䅍䅄䅁䅁䅯睔䅁䅁䅯杔䅁䅁䅕䅁䅁䅁坄唵䉁䅁䅁允䅁䅁䅕敨剴䉵䘶あ䵁䅉䅅䅁䙁䅁䅁睁䵁䅁䅁权敁䅁䅁权䉁䅁䅁权䙁䅁䅁兂䅁䅁䅁伴汔䅑䅅䅁䉁䅁䅁兂穁積積積呐睐杷允䅁䅁䅕䅁䑁䅁䅷䅁䭁䅁䅁䅁䭁䅁䅅䅁䭁䅁䅕䅁䙁䅁䅁䅁䅄由䅖允䅁䅁䅅䅁䙁佁㙆䭆䠵搴⽯䍄䉁䅁䅁兂䅁䅁䅍䅄䅁䅁䅯䅁䅁䅁䅯允䅁䅁䅯兂䅁䅁䅕䅁䅁䅁䵂欵䉁䅁䅁允䅁䅁䅕䉵䘶ㄶ㑇樳䴸䅉䅅䅁䙁䅁䅁睁䵁䅁䅁权䅁䅁䅁权䉁䅁䅁权䙁䅁䅁兂䅁䅁䅁䉑浶䅑䅅䅁䉁䅁䅁兂㑃潈牘払敪睐杷允䅁䅁䅕䅁䑁䅁䅷䅁䭁䅁䅁䅁䭁䙁䅍䅁䭁䅁䅕䅁䙁䅁䅁䅁杁畕䅚允䅁䅁䅅䅁䙁䑁ね䡹⭡稳䅎䍄䉁䅁䅁䅂䅁䅁䅍䅄䅁䅁䅯睔䅁䅁䅯杔䅁䅁䅕䅁䅁佁乄唵䉁䅁䅁允䅁䅁䅕場啯歲桦䕂䵁䅉䅅䅁䙁䅁䅁睁䵁䅁䅁权捁䅁䅁权䉁䅁䅁权䙁䅁䅁兂䅁䅁䅁䕑浶䅑䅅䅁䉁䅁䅁兂㉄䙋偹癷奘睐杷允䅁䅁䅕䅁䑁䅁䅷䅁䭁䉁䄸䅁䭁䙁䅍䅁䭁䅁䅕䅁䙁䅁䅁䅁权⬸䅖允䅁䅁䅅䅁䙁䍁扐堫焵䑘䅂䍄䉁䅁䅁兂䅁䅁䅍䅄䅁䅁䅯杈䅁䅁䅯睕䅁䅁䅯兂䅁䅁䅕䅁䅁䕁楁欵䉁䅁䅁允䅁䅁䅕兇坒楄礱啋䵁䅉䅅䅁䙁䅁䅁睁䵁䅁䅁权捁䅁䅁权呂䅁䅁权䙁䅁䅁兂䅁䅁䅁䑷浦䅑䅅䅁䉁䅁䅁兂奂扏䥔橤甴䅑杷允䅁䅁䅑䅁䑁䅁䅷䅁䭁䕁䄸䅁䭁䕁䄴䅁䙁䅁䅁䅁䅄攱䅖允䅁䅁䅅䅁䙁䥁牘払敧全䅤䍄䉁䅁䅁兂䅁䅁䅍䅄䅁䅁䅯䅁䅁䅁䅯允䅁䅁䅯兂䅁䅁䅕䅁䅁䥁䕂欵䉁䅁䅁允䅁䅁䅕䉵䘶ㄶ㑇樳䴸䅉䅅䅁䙁䅁䅁睁䵁䅁䅁权慁䅁䅁权䉁䅁䅁权䙁䅁䅁兂䅁䅁䅁倴汦䅑䅅䅁䉁䅁䅁兂穁積積積橐睐杷允䅁䅁䅕䅁䑁䅁䅷䅁䭁䅁䅁䅁䭁䅁䅅䅁䭁䅁䅕䅁䙁䅁䅁䅁䅄伴䅖允䅁䅁䅅䅁䙁佁㙆䭆䠵搴⽯䍄䉁䅁䅁兂䅁䅁䅍䅄䅁䅁䅯䅁䅁䅁䅯允䅁䅁䅯兂䅁䅁䅕䅁䅁佁癁欵䉁䅁䅁允䅁䅁䅕䉵䘶ㄶ㑇樳䴸䅉䅅䅁䙁䅁䅁睁䵁䅁䅁权䅁䅁䅁权呂䅁䅁权䙁䅁䅁兂䅁䅁䅁乧汔䅑䅅䅁䉁䅁䅁兂权楇搯䅊穙䅑杷允䅁䅁䅑䅁䑁䅁䅷䅁䭁䕁䄸䅁䭁䕁䄴䅁䙁䅁䅁䅁权⬰䅖允䅁䅁䅅䅁䙁乁橥䑣䬰眱䅖䍄䉁䅁䅁兂䅁䅁䅍䅄䅁䅁䅯䅁䅁䅁䅯允䅁䅁䅯兂䅁䅁䅕䅁䅁䭁㡄唵䉁䅁䅁允䅁䅁䅕䉵䘶ㄶ㑇樳䴸䅉䅅䅁䙁䅁䅁睁䵁䅁䅁权捁䅁䅁权呂䅁䅁权䙁䅁䅁兂䅁䅁䅁乯汢䅑䅅䅁䉁䅁䅁兂佂桙奂扏畑䅑杷允䅁䅁䅕䅁䑁䅁䅷䅁䭁䅁䅁䅁䭁䙁䅍䅁䭁䅁䅕䅁䙁䅁䅁䅁杂甶䅖允䅁䅁䅅䅁䙁䑁積積積穫䅊䍄䉁䅁䅁兂䅁䅁䅍䅄䅁䅁䅯䅁䅁䅁䅯睕䅁䅁䅯兂䅁䅁䅕䅁䅁䕁䍂欵䉁䅁䅁允䅁䅁䅕䅁䅁䅁权き䵁䅉䅅䅁䙁䅁䅁睁䵁䅁䅁权敁䅁䅁权呂䅁䅁权䙁䅁䅁兂䅁䅁䅁佁汮䅑䅅䅁䉁䅁䅁兂穂䩡瑈䑦猸䅑杷允䅁䅁䅑䅁䑁䅁䅷䅁䭁䕁䄸䅁䭁䕁䄴䅁䙁䅁䅁䅁䅃敯䅖允䅁䅁䅅䅁䙁䝁浚浚浚瑚⽙䍄䉁䅁䅁兂䅁䅁䅍䅄䅁䅁䅯䅁䅁䅁䅯允䅁䅁䅯兂䅁䅁䅕䅁䅁佁桂欵䉁䅁䅁允䅁䅁䅕䉵䘶ㄶ㑇樳䴸䅉䅅䅁䙁䅁䅁睁䵁䅁䅁权摁䅁䅁权呂䅁䅁权䙁䅁䅁兂䅁䅁䅁䝑浄䅑䅅䅁䉁䅁䅁兂㥂穐敖歵畫䅑杷允䅁䅁䅕䅁䑁䅁䅷䅁䭁䅁䅁䅁䭁䅁䅅䅁䭁䅁䅕䅁䙁䅁䅁䅁䅄敘䅚允䅁䅁䅅䅁䙁䱁敧敨剴乵⼴䍄䉁䅁䅁兂䅁䅁䅍䅄䅁䅁䅯䅁䅁䅁䅯睕䅁䅁䅯兂䅁䅁䅕䅁䅁䅁婂欵䉁䅁䅁允䅁䅁䅕扏䥔牤昷き䵁䅉䅅䅁䙁䅁䅁睁䵁䅁䅁权慁䅁䅁权呂䅁䅁权䙁䅁䅁兂䅁䅁䅁䑁浌䅑䅅䅁䉁䅁䅁兂晁敨剴乵㘴䅑杷允䅁䅁䅑䅁䑁䅁䅷䅁䭁䕁䄸䅁䭁䕁䄴䅁䙁䅁䅁䅁杂⬰䅖允䅁䅁䅅䅁䙁䱁敧敨剴䅵䅚䍄䉁䅁䅁䅂䅁䅁䅍䅄䅁䅁䅯睔䅁䅁䅯杔䅁䅁䅕䅁䅁䭁卄唵䉁䅁䅁允䅁䅁䅕㘱睎児塲啂䵁䅉䅅䅁䙁䅁䅁睁䵁䅁䅁权晁䅁䅁权呂䅁䅁权䙁䅁䅁兂䅁䅁䅁佑汶䅑䅅䅁䉁䅁䅁兂橁⼲⭬污睷䅑杷允䅁䅁䅕䅁䑁䅁䅷䅁䭁䅁䅁䅁䭁䅁䅅䅁䭁䅁䅕䅁䙁䅁䅁䅁䅄体䅚允䅁䅁䅅䅁䙁䱁敧敨剴乵⼴䍄䉁䅁䅁兂䅁䅁䅍䅄䅁䅁䅯䅁䅁䅁䅯睕䅁䅁䅯兂䅁䅁䅕䅁䅁䵁硂欵䉁䅁䅁允䅁䅁䅕佖汏㡭䅑䕎䵁䅉䅅䅁䕁䅁䅁睁䵁䅁䅁权偂䅁䅁权佂䅁䅁兂䅁䅁䅁䭷汦䅑䅅䅁䉁䅁䅁兂䑄匹捨㡪噌睐杷允䅁䅁䅕䅁䑁䅁䅷䅁䭁䉁䅯䅁䭁䅁䅅䅁䭁䅁䅕䅁䙁䅁䅁䅁权⭖䅚允䅁䅁䅅䅁䙁䭁睒児塲⭯⽧䍄䉁䅁䅁兂䅁䅁䅍䅄䅁䅁䅯杈䅁䅁䅯睕䅁䅁䅯兂䅁䅁䅕䅁䅁䅁敄唵䉁䅁䅁允䅁䅁䅕呣䬰㘱睐か䵁䅉䅅䅁䕁䅁䅁睁䵁䅁䅁权偂䅁䅁权佂䅁䅁兂䅁䅁䅁乧汈䅑䅅䅁䉁䅁䅁兂慃婭婭婭䡫䅑杷允䅁䅁䅕䅁䑁䅁䅷䅁䭁䉁䅯䅁䭁䅁䅅䅁䭁䅁䅕䅁䙁䅁䅁䅁䅄⭂䅚允䅁䅁䅅䅁䙁䝁浚浚浚畚⽙䍄䉁䅁䅁兂䅁䅁䅍䅄䅁䅁䅯先䅁䅁䅯睕䅁䅁䅯兂䅁䅁䅕䅁䅁䅁穄唵䉁䅁䅁允䅁䅁䅕灰䕶䱉祃啌䵁䅉䅅䅁䕁䅁䅁睁䵁䅁䅁权偂䅁䅁权佂䅁䅁兂䅁䅁䅁乷汄䅑䅅䅁䉁䅁䅁兂䅁䅁䅁䅁䝁䅑杷允䅁䅁䅑䅁䑁䅁䅷䅁䭁䕁䄸䅁䭁䕁䄴䅁䙁䅁䅁䅁权估䅖允䅁䅁䅅䅁䙁䵁ㅐ䙋偹杷䅖䍄䉁䅁䅁兂䅁䅁䅍䅄䅁䅁䅯䅁䅁䅁䅯允䅁䅁䅯兂䅁䅁䅕䅁䅁䅁灂欵䉁䅁䅁允䅁䅁䅕䉵䘶ㄶ㑇樳䴸䅉䅅䅁䙁䅁䅁睁䵁䅁䅁权䅁䅁䅁权呂䅁䅁权䙁䅁䅁兂䅁䅁䅁䱉汮䅑䅅䅁䉁䅁䅁兂㙃兓䍷祋祣䅑杷允䅁䅁䅕䅁䑁䅁䅷䅁䭁䅁䅁䅁䭁䙁䅍䅁䭁䅁䅕䅁䙁䅁䅁䅁杁敺䅖允䅁䅁䅅䅁䙁䝁渳㘫确樸䅊䍄䉁䅁䅁兂䅁䅁䅍䅄䅁䅁䅯䅁䅁䅁䅯睕䅁䅁䅯兂䅁䅁䅕䅁䅁䥁䍃欵䉁䅁䅁允䅁䅁䅕琯㑒匶硢き䵁䅉䅅䅁䙁䅁䅁睁䵁䅁䅁权晁䅁䅁权呂䅁䅁权䙁䅁䅁兂䅁䅁䅁䙉浌䅑䅅䅁䉁䅁䅁兂㥂穐敖極硫䅑杷允䅁䅁䅕䅁䑁䅁䅷䅁䭁䅁䅁䅁䭁䙁䅍䅁䭁䅁䅕䅁䙁䅁䅁䅁䅂佔䅚允䅁䅁䅅䅁䙁䉁䑋䵷桱呸䅎䍄䉁䅁䅁䅂䅁䅁䅍䅄䅁䅁䅯睔䅁䅁䅯杔䅁䅁䅕䅁䅁佁畃唵䉁䅁䅁允䅁䅁䅕浚浚浚浚樱䴸䅉䅅䅁䙁䅁䅁睁䵁䅁䅁权䅁䅁䅁权呂䅁䅁权䙁䅁䅁兂䅁䅁䅁䌴浲䅑䅅䅁䉁䅁䅁兂汄䌰扌含稴䅑杷允䅁䅁䅕䅁䑁䅁䅷䅁䭁䉁䄴䅁䭁䙁䅍䅁䭁䅁䅕䅁䙁䅁䅁䅁杁當䅖允䅁䅁䅅䅁䙁䡁㥅瑃橥䍍䅸䍄䉁䅁䅁兂䅁䅁䅍䅄䅁䅁䅯䅈䅁䅁䅯睕䅁䅁䅯兂䅁䅁䅕䅁䅁䥁坂欵䉁䅁䅁允䅁䅁䅕匳䝑婧䑖歌䵁䅉䅅䅁䕁䅁䅁睁䵁䅁䅁权偂䅁䅁权佂䅁䅁兂䅁䅁䅁䴴氯䅑䅅䅁䉁䅁䅁兂卂䉵䘶ㄶ䝅䅑杷允䅁䅁䅕䅁䑁䅁䅷䅁䭁䅁䅁䅁䭁䙁䅍䅁䭁䅁䅕䅁䙁䅁䅁䅁䅃⬷䅖允䅁䅁䅅䅁䙁䑁積積積穫䅊䍄䉁䅁䅁䅂䅁䅁䅍䅄䅁䅁䅯睔䅁䅁䅯杔䅁䅁䅕䅁䅁䭁偄唵䉁䅁䅁允䅁䅁䅕呣䬰㘱睎啂䵁䅉䅅䅁䙁䅁䅁睁䵁䅁䅁权慁䅁䅁权䉁䅁䅁权䙁䅁䅁兂䅁䅁䅁䡑洷䅑䅅䅁䉁䅁䅁兂歃䑣䬰㘱潐睐杷允䅁䅁䅕䅁䑁䅁䅷䅁䭁䉁䄴䅁䭁䅁䅅䅁䭁䅁䅕䅁䙁䅁䅁䅁䅃敁䅚允䅁䅁䅅䅁䙁䡁啳歲桦瑥⽑䍄䉁䅁䅁兂䅁䅁䅍䅄䅁䅁䅯睈䅁䅁䅯睕䅁䅁䅯兂䅁䅁䅕䅁䅁䕁晁欵䉁䅁䅁允䅁䅁䅕牒穢搯㑔䕍䵁䅉䅅䅁䙁䅁䅁睁䵁䅁䅁权䅁䅁䅁权呂䅁䅁权䙁䅁䅁兂䅁䅁䅁䕷浈䅑䅅䅁䉁䅁䅁兂䅁䅁䅁䭁穁
A6: 䅑杷允䅁䅁䅕䅁䑁䅁䅷䅁䭁䉁䅯䅁䭁䅁䅅䅁䭁䅁䅕䅁䙁䅁䅁䅁䅃併䅖允䅁䅁䅅䅁䙁䅁䅁䅁䅁佁⽁䍄䉁䅁䅁䅂䅁䅁䅍䅄䅁䅁䅯睔䅁䅁䅯杔䅁䅁䅕䅁䅁䕁偄唵䉁䅁䅁允䅁䅁䅕䥘䌯匹捨啂䵁䅉䅅䅁䙁䅁䅁睁䵁䅁䅁权慁䅁䅁权呂䅁䅁权䙁䅁䅁兂䅁䅁䅁伴汢䅑䅅䅁䉁䅁䅁兂䑄匹捨⭪㕉䅑杷允䅁䅁䅕䅁䑁䅁䅷䅁䭁䉁䅯䅁䭁䅁䅅䅁䭁䅁䅕䅁䙁䅁䅁䅁杂故䅚允䅁䅁䅅䅁䙁䝁浚浚浚畚⽙䍄䉁䅁䅁兂䅁䅁䅍䅄䅁䅁䅯先䅁䅁䅯允䅁䅁䅯兂䅁䅁䅕䅁䅁䝁㉃唵䉁䅁䅁允䅁䅁䅕㘱睎児塲稰䴸䅉䅅䅁䙁䅁䅁睁䵁䅁䅁权䅁䅁䅁权呂䅁䅁权䙁䅁䅁兂䅁䅁䅁䙯浢䅑䅅䅁䉁䅁䅁兂㕁䵴㉨瑶稸䅑杷允䅁䅁䅑䅁䑁䅁䅷䅁䭁䕁䄸䅁䭁䕁䄴䅁䙁䅁䅁䅁杁⭺䅖允䅁䅁䅅䅁䙁䙁偹癷潕䅘䅖䍄䉁䅁䅁兂䅁䅁䅍䅄䅁䅁䅯先䅁䅁䅯睕䅁䅁䅯兂䅁䅁䅕䅁䅁䅁潂欵䉁䅁䅁允䅁䅁䅕㑎䉬余兕歌䵁䅉䅅䅁䙁䅁䅁睁䵁䅁䅁权敁䅁䅁权呂䅁䅁权䙁䅁䅁兂䅁䅁䅁䕙浐䅑䅅䅁䉁䅁䅁兂い搯㑒圶歙䅑杷允䅁䅁䅕䅁䑁䅁䅷䅁䭁䉁䄸䅁䭁䙁䅍䅁䭁䅁䅕䅁䙁䅁䅁䅁杁⭳䅖允䅁䅁䅅䅁䙁䱁敧敨剴䐲䅂䍄䉁䅁䅁䅂䅁䅁䅍䅄䅁䅁䅯睔䅁䅁䅯杔䅁䅁䅕䅁䅁䅁㝃唵䉁䅁䅁允䅁䅁䅕䭆䠵場啯樵䴸䅉䅅䅁䙁䅁䅁睁䵁䅁䅁权捁䅁䅁权䉁䅁䅁权䙁䅁䅁兂䅁䅁䅁䩷汢䅑䅅䅁䉁䅁䅁兂偃癷潕䥘匯睐杷允䅁䅁䅕䅁䑁䅁䅷䅁䭁䉁䅷䅁䭁䅁䅅䅁䭁䅁䅕䅁䙁䅁䅁䅁杂⭷䅖允䅁䅁䅅䅁䙁䥁䌯匹捨㥪⽉䍄䉁䅁䅁兂䅁䅁䅍䅄䅁䅁䅯先䅁䅁䅯允䅁䅁䅯兂䅁䅁䅕䅁䅁䅁婂欵䉁䅁䅁允䅁䅁䅕歲桦桥畓稱䴸䅉䅅䅁䙁䅁䅁睁䵁䅁䅁权摁䅁䅁权呂䅁䅁权䙁䅁䅁兂䅁䅁䅁䕧浐䅑䅅䅁䉁䅁䅁兂䝂癴㥐䰱畧䅑杷允䅁䅁䅕䅁䑁䅁䅷䅁䭁䉁䄸䅁䭁䅁䅅䅁䭁䅁䅕䅁䙁䅁䅁䅁权佂䅚允䅁䅁䅅䅁䙁䅁䅁䅁䅁佁⽁䍄䉁䅁䅁兂䅁䅁䅍䅄䅁䅁䅯䅁䅁䅁䅯允䅁䅁䅯兂䅁䅁䅕䅁䅁佁牃唵䉁䅁䅁允䅁䅁䅕灭婭婭婭吲䴸䅉䅅䅁䙁䅁䅁睁䵁䅁䅁权晁䅁䅁权呂䅁䅁权䙁䅁䅁兂䅁䅁䅁偑汌䅑䅅䅁䉁䅁䅁兂橁⼲⭬污睷䅑杷允䅁䅁䅕䅁䑁䅁䅷䅁䭁䅁䅁䅁䭁䙁䅍䅁䭁䅁䅕䅁䙁䅁䅁䅁杁⬶䅖允䅁䅁䅅䅁䙁䑁積積積穫䅊䍄䉁䅁䅁兂䅁䅁䅍䅄䅁䅁䅯䅁䅁䅁䅯睕䅁䅁䅯兂䅁䅁䅕䅁䅁䕁敂欵䉁䅁䅁允䅁䅁䅕癱午坔兌き䵁䅉䅅䅁䕁䅁䅁睁䵁䅁䅁权偂䅁䅁权佂䅁䅁兂䅁䅁䅁䵁氯䅑䅅䅁䉁䅁䅁兂偃癷潕䥘䔸䅑杷允䅁䅁䅕䅁䑁䅁䅷䅁䭁䉁䅷䅁䭁䙁䅍䅁䭁䅁䅕䅁䙁䅁䅁䅁杂畳䅖允䅁䅁䅅䅁䙁䡁⭥确癯午䄵䍄䉁䅁䅁兂䅁䅁䅍䅄䅁䅁䅯先䅁䅁䅯睕䅁䅁䅯兂䅁䅁䅕䅁䅁䥁㙄唵䉁䅁䅁允䅁䅁䅕余兘瑉㕶啌䵁䅉䅅䅁䙁䅁䅁睁䵁䅁䅁权捁䅁䅁权呂䅁䅁权䙁䅁䅁兂䅁䅁䅁䝉浌䅑䅅䅁䉁䅁䅁兂楃扒穢刯畑䅑杷允䅁䅁䅑䅁䑁䅁䅷䅁䭁䕁䄸䅁䭁䕁䄴䅁䙁䅁䅁䅁杄畺䅖允䅁䅁䅅䅁䙁䭁睒児塲睯䅒䍄䉁䅁䅁兂䅁䅁䅍䅄䅁䅁䅯先䅁䅁䅯睕䅁䅁䅯兂䅁䅁䅕䅁䅁䍁䱂欵䉁䅁䅁允䅁䅁䅕婤奍䙂佡歌䵁䅉䅅䅁䙁䅁䅁睁䵁䅁䅁权慁䅁䅁权呂䅁䅁权䙁䅁䅁兂䅁䅁䅁䵑氯䅑䅅䅁䉁䅁䅁兂权楇搯䕊㙙䅑杷允䅁䅁䅑䅁䑁䅁䅷䅁䭁䕁䄸䅁䭁䕁䄴䅁䙁䅁䅁䅁杂⭰䅖允䅁䅁䅅䅁䙁䑁積積積㥍⽍䍄䉁䅁䅁兂䅁䅁䅍䅄䅁䅁䅯䅁䅁䅁䅯允䅁䅁䅯兂䅁䅁䅕䅁䅁䵁㍂欵䉁䅁䅁允䅁䅁䅕䉵䘶ㄶ㑇樳䴸䅉䅅䅁䙁䅁䅁睁䵁䅁䅁权慁䅁䅁权呂䅁䅁权䙁䅁䅁兂䅁䅁䅁乁汘䅑䅅䅁䉁䅁䅁兂扁㥌欰楂㙅䅑杷允䅁䅁䅕䅁䑁䅁䅷䅁䭁䉁䅷䅁䭁䅁䅅䅁䭁䅁䅕䅁䙁䅁䅁䅁杄畈䅚允䅁䅁䅅䅁䙁䭁䠵場啯瑲⽣䍄䉁䅁䅁兂䅁䅁䅍䅄䅁䅁䅯杈䅁䅁䅯睕䅁䅁䅯兂䅁䅁䅕䅁䅁䕁㡄唵䉁䅁䅁允䅁䅁䅕䵴㉨灶愯啋䵁䅉䅅䅁䙁䅁䅁睁䵁䅁䅁权晁䅁䅁权呂䅁䅁权䙁䅁䅁兂䅁䅁䅁䡷浦䅑䅅䅁䉁䅁䅁兂煂䡶呓䍇硑䅑杷允䅁䅁䅕䅁䑁䅁䅷䅁䭁䅁䅁䅁䭁䙁䅍䅁䭁䅁䅕䅁䙁䅁䅁䅁䅃異䅖允䅁䅁䅅䅁䙁乁橥䑣䬰穤䅆䍄䉁䅁䅁䅂䅁䅁䅍䅄䅁䅁䅯睔䅁䅁䅯杔䅁䅁䅕䅁䅁䍁佄唵䉁䅁䅁允䅁䅁䅕䥘䌯匹捨啂䵁䅉䅅䅁䙁䅁䅁睁䵁䅁䅁权敁䅁䅁权䉁䅁䅁权䙁䅁䅁兂䅁䅁䅁乁氳䅑䅅䅁䉁䅁䅁兂穁積積積呐睐杷允䅁䅁䅕䅁䑁䅁䅷䅁䭁䉁䄴䅁䭁䙁䅍䅁䭁䅁䅕䅁䙁䅁䅁䅁䅂畳䅖允䅁䅁䅅䅁䙁䱁穢搯㑒卡䅸䍄䉁䅁䅁䅂䅁䅁䅍䅄䅁䅁䅯睔䅁䅁䅯杔䅁䅁䅕䅁䅁䝁乄唵䉁䅁䅁允䅁䅁䅕灭婭婭婭ぁ䵁䅉䅅䅁䕁䅁䅁睁䵁䅁䅁权偂䅁䅁权佂䅁䅁兂䅁䅁䅁䵉氳䅑䅅䅁䉁䅁䅁兂卂䉵䘶ㄶ䕅䅑杷允䅁䅁䅕䅁䑁䅁䅷䅁䭁䉁䅷䅁䭁䙁䅍䅁䭁䅁䅕䅁䙁䅁䅁䅁杄⬲䅖允䅁䅁䅅䅁䙁䕁椵䙅㕧䍴䄵䍄䉁䅁䅁兂䅁䅁䅍䅄䅁䅁䅯杈䅁䅁䅯睕䅁䅁䅯兂䅁䅁䅕䅁䅁䍁灃唵䉁䅁䅁允䅁䅁䅕㝤昶楇搸か䵁䅉䅅䅁䙁䅁䅁睁䵁䅁䅁权慁䅁䅁权䉁䅁䅁权䙁䅁䅁兂䅁䅁䅁䡁浄䅑䅅䅁䉁䅁䅁兂歃䑣䬰㘱潐睐杷允䅁䅁䅕䅁䑁䅁䅷䅁䭁䉁䅯䅁䭁䙁䅍䅁䭁䅁䅕䅁䙁䅁䅁䅁䅂畓䅚允䅁䅁䅅䅁䙁䕁㍷啩杆呒䅴䍄䉁䅁䅁兂䅁䅁䅍䅄䅁䅁䅯先䅁䅁䅯睕䅁䅁䅯兂䅁䅁䅕䅁䅁䅁穁欵䉁䅁䅁允䅁䅁䅕杖琴灳瘳歌䵁䅉䅅䅁䙁䅁䅁睁䵁䅁䅁权䅁䅁䅁权䉁䅁䅁权䙁䅁䅁兂䅁䅁䅁䭉汌䅑䅅䅁䉁䅁䅁兂慃婭婭婭婮睐杷允䅁䅁䅕䅁䑁䅁䅷䅁䭁䉁䄸䅁䭁䙁䅍䅁䭁䅁䅕䅁䙁䅁䅁䅁杂敺䅖允䅁䅁䅅䅁䙁䕁䵯楁䡵樱䅂䍄䉁䅁䅁兂䅁䅁䅍䅄䅁䅁䅯䅁䅁䅁䅯允䅁䅁䅯兂䅁䅁䅕䅁䅁䵁佁欵䉁䅁䅁允䅁䅁䅕䉵䘶ㄶ㑇樳䴸䅉䅅䅁䙁䅁䅁睁䵁䅁䅁权摁䅁䅁权呂䅁䅁权䙁䅁䅁兂䅁䅁䅁乁氯䅑䅅䅁䉁䅁䅁兂㑃潈牘晕獧䅑杷允䅁䅁䅕䅁䑁䅁䅷䅁䭁䉁䄰䅁䭁䅁䅅䅁䭁䅁䅕䅁䙁䅁䅁䅁䅃佌䅚允䅁䅁䅅䅁䙁䝁浚浚浚瑚⽙䍄䉁䅁䅁兂䅁䅁䅍䅄䅁䅁䅯䅁䅁䅁䅯睕䅁䅁䅯兂䅁䅁䅕䅁䅁䥁㑃唵䉁䅁䅁允䅁䅁䅕歵䵫楁湳歍䵁䅉䅅䅁䕁䅁䅁睁䵁䅁䅁权偂䅁䅁权佂䅁䅁兂䅁䅁䅁䵯決䅑䅅䅁䉁䅁䅁兂啁歲桦桥䕑䅑杷允䅁䅁䅕䅁䑁䅁䅷䅁䭁䅁䅁䅁䭁䙁䅍䅁䭁䅁䅕䅁䙁䅁䅁䅁杁畍䅚允䅁䅁䅅䅁䙁䍁礲敮渫橨䅎䍄䉁䅁䅁兂䅁䅁䅍䅄䅁䅁䅯䅈䅁䅁䅯睕䅁䅁䅯兂䅁䅁䅕䅁䅁䵁䡄唵䉁䅁䅁允䅁䅁䅕敨剴䉵䘶歌䵁䅉䅅䅁䕁䅁䅁睁䵁䅁䅁权偂䅁䅁权佂䅁䅁兂䅁䅁䅁䴴汄䅑䅅䅁䉁䅁䅁兂㑃潈牘払番睐杷允䅁䅁䅑䅁䑁䅁䅷䅁䭁䕁䄸䅁䭁䕁䄴䅁䙁䅁䅁䅁䅃佺䅖允䅁䅁䅅䅁䙁䵁䴳䵺䵺䅺䅊䍄䉁䅁䅁兂䅁䅁䅍䅄䅁䅁䅯䅁䅁䅁䅯允䅁䅁䅯兂䅁䅁䅕䅁䅁佁䱂欵䉁䅁䅁允䅁䅁䅕䉵䘶ㄶ㑇樳䴸䅉䅅䅁䙁䅁䅁睁䵁䅁䅁权䅁䅁䅁权呂䅁䅁权䙁䅁䅁兂䅁䅁䅁䥉浌䅑䅅䅁䉁䅁䅁兂⭄䠱灪癊穅䅑杷允䅁䅁䅕䅁䑁䅁䅷䅁䭁䉁䅯䅁䭁䙁䅍䅁䭁䅁䅕䅁䙁䅁䅁䅁䅃收䅖允䅁䅁䅅䅁䙁䵁ㅐ䙋偹橷䅬䍄䉁䅁䅁兂䅁䅁䅍䅄䅁䅁䅯睈䅁䅁䅯允䅁䅁䅯兂䅁䅁䅕䅁䅁䭁坁欵䉁䅁䅁允䅁䅁䅕椹捨㡪ㅌ䐴䴸䅉䅅䅁䙁䅁䅁睁䵁䅁䅁权䅁䅁䅁权呂䅁䅁权䙁䅁䅁兂䅁䅁䅁䕯洯䅑䅅䅁䉁䅁䅁兂㕁䵴㉨瑶稸䅑杷允䅁䅁䅕䅁䑁䅁䅷䅁䭁䉁䅯䅁䭁䙁䅍䅁䭁䅁䅕䅁䙁䅁䅁䅁杄⭉䅚允䅁䅁䅅䅁䙁䱁穢搯㑒呩䅰䍄䉁䅁䅁䅂䅁䅁䅍䅄䅁䅁䅯睔䅁䅁䅯杔䅁䅁䅕䅁䅁䝁䵄唵䉁䅁䅁允䅁䅁䅕㡪ㅌ䙋偹歁䵁䅉䅅䅁䙁䅁䅁睁䵁䅁䅁权捁䅁䅁权呂䅁䅁权䙁䅁䅁兂䅁䅁䅁䍁浮䅑䅅䅁䉁䅁䅁兂偃癷潕䅘甸䅑杷允䅁䅁䅕䅁䑁䅁䅷䅁䭁䅁䅁䅁䭁䙁䅍䅁䭁䅁䅕䅁䙁䅁䅁䅁杁佉䅚允䅁䅁䅅䅁䙁䝁匸㡧䭄呁䅎䍄䉁䅁䅁兂䅁䅁䅍䅄䅁䅁䅯先䅁䅁䅯允䅁䅁䅯兂䅁䅁䅕䅁䅁䍁䑂欵䉁䅁䅁允䅁䅁䅕歲桦桥畓稱䴸䅉䅅䅁䙁䅁䅁睁䵁䅁䅁权慁䅁䅁权䉁䅁䅁权䙁䅁䅁兂䅁䅁䅁䝷浘䅑䅅䅁䉁䅁䅁兂歃䑣䬰㘱潐睐杷允䅁䅁䅕䅁䑁䅁䅷䅁䭁䉁䅷䅁䭁䅁䅅䅁䭁䅁䅕䅁䙁䅁䅁䅁䅄⭳䅖允䅁䅁䅅䅁䙁䥁䌯匹捨㥪⽉䍄䉁䅁䅁䅂䅁䅁䅍䅄䅁䅁䅯睔䅁䅁䅯杔䅁䅁䅕䅁䅁䕁䵄唵䉁䅁䅁允䅁䅁䅕瑃橥䑣䬰ぁ䵁䅉䅅䅁䙁䅁䅁睁䵁䅁䅁权晁䅁䅁权䉁䅁䅁权䙁䅁䅁兂䅁䅁䅁偑氯䅑䅅䅁䉁䅁䅁兂䥂場啯歲桦睐杷允䅁䅁䅑䅁䑁䅁䅷䅁䭁䕁䄸䅁䭁䕁䄴䅁䙁䅁䅁䅁杂佱䅖允䅁䅁䅅䅁䙁䡁啳歲桦瑥⽑䍄䉁䅁䅁兂䅁䅁䅍䅄䅁䅁䅯先䅁䅁䅯允䅁䅁䅯兂䅁䅁䅕䅁䅁䍁時欵䉁䅁䅁允䅁䅁䅕歲桦桥畓稱䴸䅉䅅䅁䙁䅁䅁睁䵁䅁䅁权摁䅁䅁权呂䅁䅁权䙁䅁䅁兂䅁䅁䅁余汪䅑䅅䅁䉁䅁䅁兂浃㡭村䱳瑉䅑杷允䅁䅁䅕䅁䑁䅁䅷䅁䭁䅁䅁䅁䭁䙁䅍䅁䭁䅁䅕䅁䙁䅁䅁䅁杂界䅚允䅁䅁䅅䅁䙁䍁礲敮渫橨䅎䍄䉁䅁䅁兂䅁䅁䅍䅄䅁䅁䅯杈䅁䅁䅯睕䅁䅁䅯兂䅁䅁䅕䅁䅁䅁歂欵䉁䅁䅁允䅁䅁䅕敫㠱穐敖歉䵁䅉䅅䅁䕁䅁䅁睁䵁䅁䅁权偂䅁䅁权佂䅁䅁兂䅁䅁䅁䵷汲䅑䅅䅁䉁䅁䅁兂啁歲桦桥⭔睐杷允䅁䅁䅕䅁䑁䅁䅷䅁䭁䉁䄴䅁䭁䙁䅍䅁䭁䅁䅕䅁䙁䅁䅁䅁䅁佦䅚允䅁䅁䅅䅁䙁䍁捬㡪ㅌ䍡䅆䍄䉁䅁䅁兂䅁䅁䅍䅄䅁䅁䅯䅁䅁䅁䅯允䅁䅁䅯兂䅁䅁䅕䅁䅁佁呁欵䉁䅁䅁允䅁䅁䅕䉵䘶ㄶ㑇樳䴸䅉䅅䅁䙁䅁䅁睁䵁䅁䅁权䅁䅁䅁权呂䅁䅁权䙁䅁䅁兂䅁䅁䅁䙷浐䅑䅅䅁䉁䅁䅁兂㕁䵴㉨瑶稸䅑杷允䅁䅁䅕䅁䑁䅁䅷䅁䭁䉁䅷䅁䭁䙁䅍䅁䭁䅁䅕䅁䙁䅁䅁䅁权⭉䅚允䅁䅁䅅䅁䙁䥁䌯匹捨祄䄵䍄䉁䅁䅁䅂䅁䅁䅍䅄䅁䅁䅯睔䅁䅁䅯杔䅁䅁䅕䅁䅁䝁䭄唵䉁䅁䅁允䅁䅁䅕場啯歲桦樫䴸䅉䅅䅁䙁䅁䅁睁䵁䅁䅁权䅁䅁䅁权䉁䅁䅁权䙁䅁䅁兂䅁䅁䅁䅁浘䅑䅅䅁䉁䅁䅁兂㑃潈牘払敪睐杷允䅁䅁䅑䅁䑁䅁䅷䅁䭁䕁䄸䅁䭁䕁䄴䅁䙁䅁䅁䅁䅃畹䅖允䅁䅁䅅䅁䙁䡁啳歲桦癥⽷䍄䉁䅁䅁兂䅁䅁䅍䅄䅁䅁䅯䅈䅁䅁䅯睕䅁䅁䅯兂䅁䅁䅕䅁䅁䅁㡂欵䉁䅁䅁允䅁䅁䅕㉩湺㘫确啌䵁䅉䅅䅁䙁䅁䅁睁䵁䅁䅁权敁䅁䅁权呂䅁䅁权䙁䅁䅁兂䅁䅁䅁佯汄䅑䅅䅁䉁䅁䅁兂硂児塲⽯牁䅑杷允䅁䅁䅕䅁䑁䅁䅷䅁䭁䅁䅁䅁䭁䅁䅅䅁䭁䅁䅕䅁䙁䅁䅁䅁䅄佌䅚允䅁䅁䅅䅁䙁䱁敧敨剴乵⼴䍄䉁䅁䅁䅂䅁䅁䅍䅄䅁䅁䅯睔䅁䅁䅯杔䅁䅁䅕䅁䅁䵁䩄唵䉁䅁䅁允䅁䅁䅕䉵䘶ㄶ㑇樫䴸䅉䅅䅁䙁䅁䅁睁䵁䅁䅁权䅁䅁䅁权䉁䅁䅁权䙁䅁䅁兂䅁䅁䅁䵧決䅑䅅䅁䉁䅁䅁兂㥁瑃橥䑣愳睐杷允䅁䅁䅕䅁䑁䅁䅷䅁䭁䉁䄴䅁䭁䅁䅅䅁䭁䅁䅕䅁䙁䅁䅁䅁䅂收䅖允䅁䅁䅅䅁䙁䑁積積積㥍⽍䍄䉁䅁䅁䅂䅁䅁䅍䅄䅁䅁䅯睔䅁䅁䅯杔䅁䅁䅕䅁䅁䅁浃唵䉁䅁䅁允䅁䅁䅕⽷潕䥘䌯吱䴸䅉䅅䅁䙁䅁䅁睁䵁䅁䅁权䅁䅁䅁权呂䅁䅁权䙁䅁䅁兂䅁䅁䅁䐴浦䅑䅅䅁䉁䅁䅁兂䅁䅁䅁䭁穁䅑杷允䅁䅁䅕䅁䑁䅁䅷䅁䭁䉁䄸䅁䭁䅁䅅䅁䭁䅁䅕䅁䙁䅁䅁䅁权畈䅚允䅁䅁䅅䅁䙁偁潙䥘䌯改⽁䍄䉁䅁䅁兂䅁䅁䅍䅄䅁䅁䅯䅁䅁䅁䅯睕䅁䅁䅯兂䅁䅁䅕䅁䅁䅁牂欵䉁䅁䅁允䅁䅁䅕佖汏㡭杔き䵁䅉䅅䅁䙁䅁䅁睁䵁䅁䅁权敁䅁䅁权䉁䅁䅁权䙁䅁䅁兂䅁䅁䅁䡯浈䅑䅅䅁䉁䅁䅁兂䅁䅁䅁䅁兄睐杷允䅁䅁䅑䅁䑁䅁䅷䅁䭁䕁䄸䅁䭁䕁䄴䅁䙁䅁䅁䅁权敹䅖允䅁䅁䅅䅁䙁䥁牘払敧晨⽣䍄䉁䅁䅁兂䅁䅁䅍䅄䅁䅁䅯杈䅁䅁䅯睕䅁䅁䅯兂䅁䅁䅕䅁䅁䝁佄唵䉁䅁䅁允䅁䅁䅕㑋坣挲㌶䕌䵁䅉䅅䅁䙁䅁䅁睁䵁䅁䅁权䅁䅁䅁权䉁䅁䅁权䙁䅁䅁兂䅁䅁䅁䕧浪䅑䅅䅁䉁䅁䅁兂㑃潈牘払敪睐杷允䅁䅁䅕䅁䑁䅁䅷䅁䭁䉁䅷䅁䭁䅁䅅䅁䭁䅁䅕䅁䙁䅁䅁䅁杂畏䅚允䅁䅁䅅䅁䙁偁潙䥘䌯搹⽧䍄䉁䅁䅁兂䅁䅁䅍䅄䅁䅁䅯睈䅁䅁䅯允䅁䅁䅯兂䅁䅁䅕䅁䅁䕁歄唵䉁䅁䅁允䅁䅁䅕児塲㍯㥁樲䴸䅉䅅䅁䕁䅁䅁睁䵁䅁䅁权偂䅁䅁权佂䅁䅁兂䅁䅁䅁䭧汢䅑䅅䅁䉁䅁䅁兂㝂䭆䠵場啲睐杷允䅁䅁䅑䅁䑁䅁䅷䅁䭁䕁䄸䅁䭁䕁䄴䅁䙁䅁䅁䅁杄⭸䅖允䅁䅁䅅䅁䙁䵁䴳䵺䵺偺⽷䍄䉁䅁䅁兂䅁䅁䅍䅄䅁䅁䅯杇䅁䅁䅯睕䅁䅁䅯兂䅁䅁䅕䅁䅁䥁塁欵䉁䅁䅁允䅁䅁䅕癴㥐䠱䩩歏䵁䅉䅅䅁䕁䅁䅁睁䵁䅁䅁权偂䅁䅁权佂䅁䅁兂䅁䅁䅁䵙汢䅑䅅䅁䉁䅁䅁兂㑃潈牘払㉪睐杷允䅁䅁䅕䅁䑁䅁䅷䅁䭁䅁䅁䅁䭁䙁䅍䅁䭁䅁䅕䅁䙁䅁䅁䅁䅄⭷䅖允䅁䅁䅅䅁䙁偁周㘴扗䑨䅊䍄䉁䅁䅁䅂䅁䅁䅍䅄䅁䅁䅯睔䅁䅁䅯杔䅁䅁䅕䅁䅁䅁䝄唵䉁䅁䅁允䅁䅁䅕児塲㍯㥁樹䴸䅉䅅䅁䙁䅁䅁睁䵁䅁䅁权摁䅁䅁权呂䅁䅁权䙁䅁䅁兂䅁䅁䅁䩙汢䅑䅅䅁䉁䅁䅁兂㡃䩤奍䙂瑙䅑杷允䅁䅁䅕䅁䑁䅁䅷䅁䭁䉁䄸䅁䭁䅁䅅䅁䭁䅁䅕䅁䙁䅁䅁䅁䅂住䅚允䅁䅁䅅䅁䙁䭁睒児塲⭯⽁䍄䉁䅁䅁䅂䅁䅁䅍䅄䅁䅁䅯睔䅁䅁䅯杔䅁䅁䅕䅁䅁䥁䙄唵䉁䅁䅁允䅁䅁䅕場啯歲桦樹䴸䅉䅅䅁䙁䅁䅁睁䵁䅁䅁权摁䅁䅁权䉁䅁䅁权䙁䅁䅁兂䅁䅁䅁䝑洳䅑䅅䅁䉁䅁䅁兂畃⭒㙆䭆堷睐杷允䅁䅁䅑䅁䑁䅁䅷䅁䭁䕁䄸䅁䭁䕁䄴䅁䙁䅁䅁䅁䅂數䅖允䅁䅁䅅䅁䙁䡁啳歲桦癥⽑䍄䉁䅁䅁兂䅁䅁䅍䅄䅁䅁䅯䅁䅁䅁䅯睕䅁䅁䅯兂䅁䅁䅕䅁䅁䥁晄唵䉁䅁䅁允䅁䅁䅕兇坒楄匳歍䵁䅉䅅䅁䙁䅁䅁睁䵁䅁䅁权䅁䅁䅁权呂䅁䅁权䙁䅁䅁兂䅁䅁䅁䙯浈䅑䅅䅁䉁䅁䅁兂㕁䵴㉨瑶稸䅑杷允䅁䅁䅕䅁䑁䅁䅷䅁䭁䉁䅯䅁䭁䅁䅅䅁䭁䅁䅕䅁䙁䅁䅁䅁杂畗䅚允䅁䅁䅅䅁䙁䭁睒児塲⭯⽧䍄䉁䅁䅁䅂䅁䅁䅍䅄䅁䅁䅯睔䅁䅁䅯杔䅁䅁䅕䅁䅁䵁䕄唵䉁䅁䅁允䅁䅁䅕硥畓⭒㙆䐹䴸䅉䅅䅁䕁䅁䅁睁䵁䅁䅁权偂䅁䅁权佂䅁䅁兂䅁䅁䅁䵯汐䅑䅅䅁䉁䅁䅁兂捂㡪ㅌ䙋空睐杷允䅁䅁䅕䅁䑁䅁䅷䅁䭁䅁䅁䅁䭁䅁䅅䅁䭁䅁䅕䅁䙁䅁䅁䅁杄畁䅚允䅁䅁䅅䅁䙁䱁敧敨剴乵⼴䍄䉁䅁䅁䅂䅁䅁䅍䅄䅁䅁䅯睔䅁䅁䅯杔䅁䅁䅕䅁䅁䭁䍄唵䉁䅁䅁允䅁䅁䅕牕敧敨剴䐸䴸䅉䅅䅁䙁䅁䅁睁䵁䅁䅁权䅁䅁䅁权䉁䅁䅁权䙁䅁䅁兂䅁䅁䅁䭉汲䅑䅅䅁䉁䅁䅁兂慃婭婭婭婮睐杷允䅁䅁䅕䅁䑁䅁䅷䅁䭁䅁䅁䅁䭁䙁䅍䅁䭁䅁䅕䅁䙁䅁䅁䅁䅂⭗䅚允䅁䅁䅅䅁䙁䭁硲欰椱䐰䅎䍄䉁䅁䅁兂䅁䅁䅍䅄䅁䅁䅯杇䅁䅁䅯允䅁䅁䅯兂䅁䅁䅕䅁䅁䍁扂欵䉁䅁䅁允䅁䅁䅕䡰㥁瑃橥䐶䴸䅉䅅䅁䙁䅁䅁睁䵁䅁䅁权晁䅁䅁权呂䅁䅁权䙁䅁䅁兂䅁䅁䅁䨴汮䅑䅅䅁䉁䅁䅁兂䅁䅁䅁佁睁䅑杷允䅁䅁䅑䅁䑁䅁䅷䅁䭁䕁䄸䅁䭁䕁䄴䅁䙁䅁䅁䅁䅃畷䅖允䅁䅁䅅䅁䙁䭁睒児塲⽯⽁䍄䉁䅁䅁兂䅁䅁䅍䅄䅁䅁䅯杇䅁䅁䅯睕䅁䅁䅯兂䅁䅁䅕䅁䅁䅁硃唵䉁䅁䅁允䅁䅁䅕穐敖歵獮問䵁䅉䅅䅁䕁䅁䅁睁䵁䅁䅁权偂䅁䅁权佂䅁䅁兂䅁䅁䅁䵁汌䅑䅅䅁䉁䅁䅁兂捂㡪ㅌ䙋発睐杷允䅁䅁䅕䅁䑁䅁䅷䅁䭁䉁䅷䅁䭁䅁䅅䅁䭁䅁䅕䅁䙁䅁䅁䅁杂畧䅚允䅁䅁䅅䅁䙁偁潙䥘䌯搹⽧䍄䉁䅁䅁兂䅁䅁䅍䅄䅁䅁䅯䅁䅁䅁䅯睕䅁䅁䅯兂䅁䅁䅕䅁䅁佁㡂欵䉁䅁䅁允䅁䅁䅕佖汏㡭䅑䕎䵁䅉䅅䅁䙁䅁䅁睁䵁䅁䅁权慁䅁䅁权呂䅁䅁权䙁䅁䅁兂䅁䅁䅁佷汄䅑䅅䅁䉁䅁䅁兂䑄匹捨⭪㕉䅑杷允䅁䅁䅕䅁䑁䅁䅷䅁䭁䅁䅁䅁䭁䅁䅅䅁䭁䅁䅕䅁䙁䅁䅁䅁䅂敯䅖允䅁䅁䅅䅁䙁䩁婱婭婭摭⽫䍄䉁䅁䅁兂䅁䅁䅍䅄䅁䅁䅯睈䅁䅁䅯允䅁䅁䅯兂䅁䅁䅕䅁䅁䥁捂欵䉁䅁䅁允䅁䅁䅕椹捨㡪ㅌ䐴䴸䅉䅅䅁䕁䅁䅁睁䵁䅁䅁权偂䅁䅁权佂䅁䅁兂䅁䅁䅁䱁汘䅑䅅䅁䉁䅁䅁兂啁歲桦桥敔睐杷允䅁䅁䅕䅁䑁䅁䅷䅁䭁䅁䅁䅁䭁䙁䅍䅁䭁䅁䅕䅁䙁䅁䅁䅁䅂但䅚允䅁䅁䅅䅁䙁䉁奂扏䥔橬䅊䍄䉁䅁䅁兂䅁䅁䅍䅄䅁䅁䅯先䅁䅁䅯允䅁䅁䅯兂䅁䅁䅕䅁䅁䍁十欵䉁䅁䅁允䅁䅁䅕㑈牘払敧吱䴸䅉䅅䅁䕁䅁䅁睁䵁䅁䅁权偂䅁䅁权佂䅁䅁兂䅁䅁䅁䵷汈䅑䅅䅁䉁䅁䅁兂畃⭒㙆䭆瘷睐杷允䅁䅁䅕䅁䑁䅁䅷䅁䭁䉁䄸䅁䭁䙁䅍䅁䭁䅁䅕䅁䙁䅁䅁䅁䅄⭙䅚允䅁䅁䅅䅁䙁乁楅⼲⭬橃䅆䍄䉁䅁䅁䅂䅁䅁䅍䅄䅁䅁䅯睔䅁䅁䅯杔䅁䅁䅕䅁䅁䍁䉄唵䉁䅁䅁允䅁䅁䅕瑃橥䑣䬰稷䴸䅉䅅䅁䙁䅁䅁睁䵁䅁䅁权敁䅁䅁权䉁䅁䅁权䙁䅁䅁兂䅁䅁䅁䉯浦䅑䅅䅁䉁䅁䅁兂䑄匹捨㡪噌睐杷允䅁䅁䅕䅁䑁䅁䅷䅁䭁䅁䅁䅁䭁䅁䅅䅁䭁䅁䅕䅁䙁䅁䅁䅁杄⭰䅖允䅁䅁䅅䅁䙁䩁婱婭婭摭⽫䍄䉁䅁䅁䅂䅁䅁䅍䅄䅁䅁䅯睔䅁䅁䅯杔䅁䅁䅕䅁䅁䝁䅄唵䉁䅁䅁允䅁䅁䅕⽷潕䥘䌯吷䴸䅉䅅䅁䙁䅁䅁睁䵁䅁䅁权捁䅁䅁权呂䅁䅁权䙁䅁䅁兂䅁䅁䅁䱙氷䅑䅅䅁䉁䅁䅁兂桄桥畓㉒畅䅑杷允䅁䅁䅕䅁䑁䅁䅷䅁䭁䉁䄴䅁䭁䅁䅅䅁䭁䅁䅕䅁䙁䅁䅁䅁权佴䅖允䅁䅁䅅䅁䙁䑁積積積㥍⽍䍄䉁䅁䅁兂䅁䅁䅍䅄䅁䅁䅯杈䅁䅁䅯睕䅁䅁䅯兂䅁䅁䅕䅁䅁䥁䕄唵䉁䅁䅁允䅁䅁䅕呣䬰㘱睍䕌䵁䅉䅅䅁䕁䅁䅁睁䵁䅁䅁权偂䅁䅁权佂䅁䅁兂䅁䅁䅁䰴氯䅑䅅䅁䉁䅁䅁兂浂浚浚浚畢睐杷允䅁䅁䅑䅁䑁䅁䅷䅁䭁䕁䄸䅁䭁䕁䄴䅁䙁䅁䅁䅁杂⭶䅖允䅁䅁䅅䅁䙁䭁䠵場啯畲⼸䍄䉁䅁䅁兂䅁䅁䅍䅄䅁䅁䅯杈䅁䅁䅯允䅁䅁䅯兂䅁䅁䅕䅁䅁䝁灃唵䉁䅁䅁允䅁䅁䅕積積積積稰䴸䅉䅅䅁䙁䅁䅁睁䵁䅁䅁权䅁䅁䅁权呂䅁䅁权䙁䅁䅁兂䅁䅁䅁䑁浐䅑䅅䅁䉁䅁䅁兂瑁灳瘳㑰穙䅑杷允䅁䅁䅑䅁䑁䅁䅷䅁䭁䕁䄸䅁䭁䕁䄴䅁䙁䅁䅁䅁䅂⭶䅖允䅁䅁䅅䅁䙁䭁䠵場啯畲⼸䍄䉁䅁䅁兂䅁䅁䅍䅄䅁䅁䅯䅈䅁䅁䅯睕䅁䅁䅯兂䅁䅁䅕䅁䅁䍁扄唵䉁䅁䅁允䅁䅁䅕浔光䑗ね歌䵁䅉䅅䅁䕁䅁䅁睁䵁䅁䅁权偂䅁䅁权佂䅁䅁兂䅁䅁䅁䱁氯䅑䅅䅁䉁䅁䅁兂晁敨剴䉵琷睐杷允䅁䅁䅑䅁䑁䅁䅷䅁䭁䅁䅁䅁䭁䙁䅑䅁䙁䅁䅁䅁杂畧䅚允䅁䅁䅅䅁䭁䉁䅳䅁䵁䅉䅅䅁䙁䅁䅁睁䵁䅁䅁权䅁䅁䅁权䉁䅁䅁权䙁䅁䅁兂䅁䅁䅁䍧浔䅑䅅䅁䉁䅁䅁兂㑃潈牘払敪睐杷允䅁䅁䅕䅁䑁䅁䅷䅁䭁䉁䅯䅁䭁䙁䅍䅁䭁䅁䅕䅁䙁䅁䅁䅁权畚䅚允䅁䅁䅅䅁䙁䍁搯䅊䉡呖䅴䍄䉁䅁䅁䅂䅁䅁䅍䅄䅁䅁䅯睔䅁䅁䅯杔䅁䅁䅕䅁䅁䝁⭃唵䉁䅁䅁允䅁䅁䅕積積積積稶䴸䅉䅅䅁䙁䅁䅁睁䵁䅁䅁权摁䅁䅁权呂䅁䅁权䙁䅁䅁兂䅁䅁䅁䘴浮䅑䅅䅁䉁䅁䅁兂䑄匹捨㑪畉䅑杷允䅁䅁䅕䅁䑁䅁䅷䅁䭁䉁䄴䅁䭁䙁䅍䅁䭁䅁䅕䅁䙁䅁䅁䅁杁敒䅚允䅁䅁䅅䅁䙁佁㠵穐敖楏䅒䍄䉁䅁䅁䅂䅁䅁䅍䅄䅁䅁䅯睔䅁䅁䅯杔䅁䅁䅕䅁䅁䍁⭃唵䉁䅁䅁允䅁䅁䅕㡪ㅌ䙋偹樶䴸䅉䅅䅁䙁䅁䅁睁䵁䅁䅁权捁䅁䅁权䉁䅁䅁权䙁䅁䅁兂䅁䅁䅁䙉浌䅑䅅䅁䉁䅁䅁兂㉄䙋偹癷奘睐杷允䅁䅁䅕䅁䑁䅁䅷䅁䭁䉁䄸䅁䭁䅁䅅䅁䭁䅁䅕䅁䙁䅁䅁䅁䅄伷䅖允䅁䅁䅅䅁䙁佁㙆䭆䠵搴⽯䍄䉁䅁䅁䅂䅁䅁䅍䅄䅁䅁䅯睔䅁䅁䅯杔䅁䅁䅕䅁䅁䵁㥃唵䉁䅁䅁允䅁䅁䅕䘷㑇潈牘吶䴸䅉䅅䅁䙁䅁䅁睁䵁䅁䅁权䅁䅁䅁权呂䅁䅁权䙁䅁䅁兂䅁䅁䅁偁汲䅑䅅䅁䉁䅁䅁兂灁䥘䌯圹祧䅑杷允䅁䅁䅕䅁䑁䅁䅷䅁䭁䉁䄰䅁䭁䅁䅅䅁䭁䅁䅕䅁䙁䅁䅁䅁䅄⭣䅚允䅁䅁䅅䅁䙁䭁䠵場啯瑲⽣䍄䉁䅁䅁兂䅁䅁䅍䅄䅁䅁䅯䅁䅁䅁䅯睕䅁䅁䅯兂䅁䅁䅕䅁䅁䍁坁欵䉁䅁䅁允䅁䅁䅕硢䑋䵷䉯き䵁䅉䅅䅁䕁䅁䅁睁䵁䅁䅁权偂䅁䅁权佂䅁䅁兂䅁䅁䅁䱙氳䅑䅅䅁䉁䅁䅁兂浂浚浚浚畢睐杷允䅁䅁䅕䅁䑁䅁䅷䅁䭁䉁䅯䅁䭁䙁䅍䅁䭁䅁䅕䅁䙁䅁䅁䅁䅁佧䅚允䅁䅁䅅䅁䙁䡁灮橊䥅䐷䅰䍄䉁䅁䅁兂䅁䅁䅍䅄䅁䅁䅯睈䅁䅁䅯允䅁䅁䅯兂䅁䅁䅕䅁䅁佁䥄唵䉁䅁䅁允䅁䅁䅕䡰㥁瑃橥䐴䴸䅉䅅䅁䙁䅁䅁睁䵁䅁䅁权慁䅁䅁权呂䅁䅁权䙁䅁䅁兂䅁䅁䅁䝷浮䅑䅅䅁䉁䅁䅁兂癁匳䝑噧㝕䅑杷允䅁䅁䅕䅁䑁䅁䅷䅁䭁䅁䅁䅁䭁䙁䅍䅁䭁䅁䅕䅁䙁䅁䅁䅁䅄⭢䅚允䅁䅁䅅䅁䙁䙁橔婰䕶䐴䅎䍄䉁䅁䅁䅂䅁䅁䅍䅄䅁䅁䅯睔䅁䅁䅯杔䅁䅁䅕䅁䅁䭁㝃唵䉁䅁䅁允䅁䅁䅕䉵䘶ㄶ㑇樵䴸䅉䅅䅁䕁䅁䅁睁䵁䅁䅁权偂䅁䅁权佂䅁䅁兂䅁䅁䅁䱙汈䅑䅅䅁䉁䅁䅁兂灁䥘䌯匹捪睐杷允䅁䅁䅕䅁䑁䅁䅷䅁䭁䉁䄰䅁䭁䙁䅍䅁䭁䅁䅕䅁䙁䅁䅁䅁䅄畐䅚允䅁䅁䅅䅁䙁䕁㉡⼸唳䍵䄵䍄䉁䅁䅁兂䅁䅁䅍䅄䅁䅁䅯䅁䅁䅁䅯睕䅁䅁䅯兂䅁䅁䅕䅁䅁䕁湄唵䉁䅁䅁允䅁䅁䅕兇坒楄匳歍䵁䅉䅅䅁䕁䅁䅁睁䵁䅁䅁权偂䅁䅁权佂䅁䅁兂䅁䅁䅁䰴汮䅑䅅䅁䉁䅁䅁兂歃䑣䬰㘱潐睐杷允䅁䅁䅕䅁䑁䅁䅷䅁䭁䅁䅁䅁䭁䅁䅅䅁䭁䅁䅕䅁䙁䅁䅁䅁杄敺䅖允䅁䅁䅅䅁䙁䑁䬰㘱睎摐⽯䍄䉁䅁䅁兂䅁䅁䅍䅄䅁䅁䅯先䅁䅁䅯睕䅁䅁䅯兂䅁䅁䅕䅁䅁佁㑃唵䉁䅁䅁允䅁䅁䅕瑃橥䑣䬳啌䵁䅉䅅䅁䙁䅁䅁睁䵁䅁䅁权晁䅁䅁权呂䅁䅁权䙁䅁䅁兂䅁䅁䅁䉑浺䅑䅅䅁䉁䅁䅁兂䝂癴㥐倱睧䅑杷允䅁䅁䅑䅁䑁䅁䅷䅁䭁䕁䄸䅁䭁䕁䄴䅁䙁䅁䅁䅁䅁敵䅖允䅁䅁䅅䅁䙁䱁敧敨剴併⽙䍄䉁䅁䅁兂䅁䅁䅍䅄䅁䅁䅯杈䅁䅁䅯睕䅁䅁䅯兂䅁䅁䅕䅁䅁䵁祄唵䉁䅁䅁允䅁䅁䅕㉣剩堷⽷䕌䵁䅉䅅䅁䙁䅁䅁睁䵁䅁䅁权䅁䅁䅁权䉁䅁䅁权䙁䅁䅁兂䅁䅁䅁䭧汌䅑䅅䅁䉁䅁䅁兂慃婭婭婭婮睐杷允䅁䅁䅕䅁䑁䅁䅷䅁䭁䅁䅁䅁䭁䙁䅍䅁䭁䅁䅕䅁䙁䅁䅁䅁䅁散䅚允䅁䅁䅅䅁䙁䙁橔婰䕶䑁䅒䍄䉁䅁䅁兂䅁䅁䅍䅄䅁䅁䅯先䅁䅁䅯允䅁䅁䅯兂䅁䅁䅕䅁䅁䝁祂欵䉁䅁䅁允䅁䅁䅕歲桦桥畓稱䴸䅉䅅䅁䙁䅁䅁睁䵁䅁䅁权晁䅁䅁权呂䅁䅁权䙁䅁䅁兂䅁䅁䅁义汶䅑䅅䅁䉁䅁䅁兂扁㥌欰畂睅䅑杷允䅁䅁䅑䅁䑁䅁䅷䅁䭁䕁䄸䅁䭁䕁䄴䅁䙁䅁䅁䅁杄併䅖允䅁䅁䅅䅁䙁䅁塲㍯㥁畃⽣䍄䉁䅁䅁兂䅁䅁䅍䅄䅁䅁䅯䅁䅁䅁䅯允䅁䅁䅯兂䅁䅁䅕䅁䅁䕁畂欵䉁䅁䅁允䅁䅁䅕䉵䘶ㄶ㑇樳䴸䅉䅅䅁䙁䅁䅁睁䵁䅁䅁权晁䅁䅁权䉁䅁䅁权䙁䅁䅁兂䅁䅁䅁䥷浄䅑䅅䅁䉁䅁䅁兂卂䉵䘶ㄶ杈睐杷允䅁䅁䅕䅁䑁䅁䅷䅁䭁䉁䄸䅁䭁䙁䅍䅁䭁䅁䅕䅁䙁䅁䅁䅁杂畹䅖允䅁䅁䅅䅁䙁䕁䵯楁䡵樱䅂䍄䉁䅁䅁䅂䅁䅁䅍䅄䅁䅁䅯睔䅁䅁䅯杔䅁䅁䅕䅁䅁䥁㑃唵䉁䅁䅁允䅁䅁䅕浚浚浚浚樵䴸䅉䅅䅁䙁䅁䅁睁䵁䅁䅁权慁䅁䅁权䉁䅁䅁权䙁䅁䅁兂䅁䅁䅁䭙汲䅑䅅䅁䉁䅁䅁兂䅁䅁䅁䅁杄睐杷允䅁䅁䅕䅁䑁䅁䅷䅁䭁䉁䄰䅁䭁䅁䅅䅁䭁䅁䅕䅁䙁䅁䅁䅁杄攳䅖允䅁䅁䅅䅁䙁乁橥䑣䬰㤱⽍䍄䉁䅁䅁兂䅁䅁䅍䅄䅁䅁䅯杈䅁䅁䅯允䅁䅁䅯兂䅁䅁䅕䅁䅁佁㡃唵䉁䅁䅁允䅁䅁䅕積積積積稰䴸䅉䅅䅁䙁䅁䅁睁䵁䅁䅁权晁䅁䅁权呂䅁䅁权䙁䅁䅁兂䅁䅁䅁䅑浘䅑䅅䅁䉁䅁䅁兂䑃䵷桱婒睙䅑杷允䅁䅁䅑䅁䑁䅁䅷䅁䭁䕁䄸䅁䭁䕁䄴䅁䙁䅁䅁䅁杁併䅖允䅁䅁䅅䅁䙁䡁啳歲桦略⽑䍄䉁䅁䅁兂䅁䅁䅍䅄䅁䅁䅯䅈䅁䅁䅯睕䅁䅁䅯兂䅁䅁䅕䅁䅁䵁奁欵䉁䅁䅁允䅁䅁䅕灳瘳㡰䱙歌䵁䅉䅅䅁䙁䅁䅁睁䵁䅁䅁权敁䅁䅁权呂䅁䅁权䙁䅁䅁兂䅁䅁䅁䝷浺䅑䅅䅁䉁䅁䅁兂剄瑉㕶浦桯䅑杷允䅁䅁䅕䅁䑁䅁䅷䅁䭁䅁䅁䅁䭁䙁䅍䅁䭁䅁䅕䅁䙁䅁䅁䅁䅁佅䅚允䅁䅁䅅䅁䙁䉁奂扏䥔橬䅊䍄䉁䅁䅁兂䅁䅁䅍䅄䅁䅁䅯䅁䅁䅁䅯睕䅁䅁䅯兂䅁䅁䅕䅁䅁佁橃唵䉁䅁䅁允䅁䅁䅕㘱睎児㍰啍䵁䅉䅅䅁䕁䅁䅁睁䵁䅁䅁权偂䅁䅁权佂䅁䅁兂䅁䅁䅁䨴汮䅑䅅䅁䉁䅁䅁兂慃婭婭婭䩮睐杷允䅁䅁䅑䅁䑁䅁䅷䅁䭁䕁䄸䅁䭁䕁䄴䅁䙁䅁䅁䅁䅁併䅖允䅁䅁䅅䅁䙁佁㙆䭆䠵攴⽉䍄䉁䅁䅁兂䅁䅁䅍䅄䅁䅁䅯杈䅁䅁䅯睕䅁䅁䅯兂䅁䅁䅕䅁䅁䵁ㅄ唵䉁䅁䅁允䅁䅁䅕㉣剩堷⽷䕌䵁䅉䅅䅁䙁䅁䅁睁䵁䅁䅁权敁䅁䅁权呂䅁䅁权䙁䅁䅁兂䅁䅁䅁䩷汦䅑䅅䅁䉁䅁䅁兂䝁婧䑖㉩灷䅑杷允䅁䅁䅕䅁䑁䅁䅷䅁䭁䉁䄸䅁䭁䅁䅅䅁䭁䅁䅕䅁䙁䅁䅁䅁䅃⭰䅖允䅁䅁䅅䅁䭁䉁䅳䅁䵁䅉䅅䅁䕁䅁䅁睁䵁䅁䅁权偂䅁䅁权佂䅁䅁兂䅁䅁䅁䱧汦䅑䅅䅁䉁䅁䅁兂㥁瑃橥䑣椳睐杷允䅁䅁䅕䅁䑁䅁䅷䅁䭁䅁䅁䅁䭁䅁䅅䅁䭁䅁䅕䅁䙁䅁䅁䅁䅄佹䅖允䅁䅁䅅䅁䙁䑁䬰㘱睎摐⽯䍄䉁䅁䅁兂䅁䅁䅍䅄䅁䅁䅯杈䅁䅁䅯允䅁䅁䅯兂䅁䅁䅕䅁䅁䅁䉁欵䉁䅁䅁允䅁䅁䅕硥畓⭒㙆䐱䴸䅉䅅䅁䙁䅁䅁睁䵁䅁䅁权敁䅁䅁权䉁䅁䅁权䙁䅁䅁兂䅁䅁䅁佉汮䅑䅅䅁䉁䅁䅁兂穁積積積呐睐杷允䅁䅁䅕䅁䑁䅁䅷䅁䭁䉁䄸䅁䭁䙁䅍䅁䭁䅁䅕䅁䙁䅁䅁䅁䅄佧䅚允䅁䅁䅅䅁䙁䝁汄䌰扌含䅂䍄䉁䅁䅁䅂䅁䅁䅍䅄䅁䅁䅯睔䅁䅁䅯杔䅁䅁䅕䅁䅁䍁㍃唵䉁䅁䅁允䅁䅁䅕䡰㥁瑃橥䐴䴸䅉䅅䅁䙁䅁䅁睁䵁䅁䅁权慁䅁䅁权呂䅁䅁权䙁䅁䅁兂䅁䅁䅁䡙浮䅑䅅䅁䉁䅁䅁兂䵂㑎䉬䍙㝕䅑杷允䅁䅁䅕䅁䑁䅁䅷䅁䭁䉁䅯䅁䭁䙁䅍䅁䭁䅁䅕䅁䙁䅁䅁䅁䅃當䅖允䅁䅁䅅䅁䙁䱁䩰䅄牉穊䅰䍄䉁䅁䅁䅂䅁䅁䅍䅄䅁䅁䅯睔䅁䅁䅯杔䅁䅁䅕䅁䅁䥁㉃唵䉁䅁䅁允䅁䅁䅕灭婭婭婭吴䴸䅉䅅䅁䕁䅁䅁睁䵁䅁䅁权偂䅁䅁权佂䅁䅁兂䅁䅁䅁䱑汢䅑䅅䅁䉁䅁䅁兂獄払敧敨桶睐杷允䅁䅁䅕䅁䑁䅁䅷䅁䭁䉁䅷䅁䭁䅁䅅䅁䭁䅁䅕䅁䙁䅁䅁䅁杄伸䅖允䅁䅁䅅䅁䙁䑁積積積㥍⽍䍄䉁䅁䅁兂䅁䅁䅍䅄䅁䅁䅯先䅁䅁䅯睕䅁䅁䅯兂䅁䅁䅕䅁䅁䵁䩁欵䉁䅁䅁允䅁䅁䅕䝭匴㡧䭂歌䵁䅉䅅䅁䙁䅁䅁睁䵁䅁䅁权捁䅁䅁权䉁䅁䅁权䙁䅁䅁兂䅁䅁䅁䱙汪䅑䅅䅁䉁䅁䅁兂偃癷潕䥘匯睐杷允䅁䅁䅕䅁䑁䅁䅷䅁䭁䉁䄰䅁䭁䙁䅍䅁䭁䅁䅕䅁䙁䅁䅁䅁权⬰䅖允䅁䅁䅅䅁䙁䵁ㅐ䙋偹楷䄱䍄䉁䅁䅁䅂䅁䅁䅍䅄䅁䅁䅯睔䅁䅁䅯杔䅁䅁䅕䅁䅁佁ㅃ唵䉁䅁䅁允䅁䅁䅕灭婭婭婭吴䴸䅉䅅䅁䙁䅁䅁睁䵁䅁䅁权摁䅁䅁权呂䅁䅁权䙁䅁䅁兂䅁䅁䅁䭙汐䅑䅅䅁䉁䅁䅁兂䝂癴㥐䠱瑧䅑杷允䅁䅁䅕䅁䑁䅁䅷䅁䭁䉁䄴䅁䭁䅁䅅䅁䭁䅁䅕䅁䙁䅁䅁䅁杂畘䅚允䅁䅁䅅䅁䙁䅁䅁䅁䅁乁⽁䍄䉁䅁䅁兂䅁䅁䅍䅄䅁䅁䅯䅁䅁䅁䅯允䅁䅁䅯兂䅁䅁䅕䅁䅁䭁㉄唵䉁䅁䅁允䅁䅁䅕䉵䘶ㄶ㑇樳䴸䅉䅅䅁䙁䅁䅁睁䵁䅁䅁权䅁䅁䅁权呂䅁䅁权䙁䅁䅁兂䅁䅁䅁䕙浪䅑䅅䅁䉁䅁䅁兂十㡧䭄捯穕䅑杷允䅁䅁䅕䅁䑁䅁䅷䅁䭁䉁䅷䅁䭁䙁䅍䅁䭁䅁䅕䅁䙁䅁䅁䅁䅂佤䅚允䅁䅁䅅䅁䙁䥁獴⼵灵匸䄱䍄䉁䅁䅁兂䅁䅁䅍䅄䅁䅁䅯睈䅁䅁䅯睕䅁䅁䅯兂䅁䅁䅕䅁䅁䅁浄唵䉁䅁䅁允䅁䅁䅕灶愸㥌䔱䕍䵁䅉䅅䅁䕁䅁䅁睁䵁䅁䅁权偂䅁䅁权佂䅁䅁兂䅁䅁䅁䱷汔䅑䅅䅁䉁䅁䅁兂䙃ㄶ㑇潈托睐杷允䅁䅁䅕䅁䑁䅁䅷䅁䭁䉁䅯䅁䭁䙁䅍䅁䭁䅁䅕䅁䙁䅁䅁䅁杁畢䅚允䅁䅁䅅䅁䙁䍁搯䅊䉡呖䅴䍄䉁䅁䅁䅂䅁䅁䅍䅄䅁䅁䅯睔䅁䅁䅯杔䅁䅁䅕䅁䅁䅁穃唵䉁䅁䅁允䅁䅁䅕場啯歲桦樲䴸䅉䅅䅁䙁䅁䅁睁䵁䅁䅁权䅁䅁䅁权呂䅁䅁权䙁䅁䅁兂䅁䅁䅁䝁浐䅑䅅䅁䉁䅁䅁兂煃搸乊瑙穁䅑杷允䅁䅁䅑䅁䑁䅁䅷䅁䭁䕁䄸䅁䭁䕁䄴䅁䙁䅁䅁䅁杂畳䅖允䅁䅁䅅䅁䙁䑁䬰㘱睎摐⽯䍄䉁䅁䅁兂䅁䅁䅍䅄䅁䅁䅯先䅁䅁䅯睕䅁䅁䅯兂䅁䅁䅕䅁䅁䝁婃唵䉁䅁䅁允䅁䅁䅕䡶呓䅇坒啌䵁䅉䅅䅁䕁䅁䅁睁䵁䅁䅁权偂䅁䅁权佂䅁䅁兂䅁䅁䅁䱉汌䅑䅅䅁䉁䅁䅁兂啁歲桦桥敔睐杷允䅁䅁䅕䅁䑁䅁䅷䅁䭁䉁䅷䅁䭁䅁䅅䅁䭁䅁䅕䅁䙁䅁䅁䅁䅄⭮䅖允䅁䅁䅅䅁䙁䥁䌯匹捨㥪⽉䍄䉁䅁䅁兂䅁䅁䅍䅄䅁䅁䅯䅈䅁䅁䅯允䅁䅁䅯兂䅁䅁䅕䅁䅁佁⭄唵䉁䅁䅁允䅁䅁䅕㑈牘払敧吱䴸䅉䅅䅁䙁䅁䅁睁䵁䅁䅁权䅁䅁䅁权呂䅁䅁权䙁䅁䅁兂䅁䅁䅁偑汈䅑䅅䅁䉁䅁䅁兂穁積積㕍祍䅑杷允䅁䅁䅕䅁䑁䅁䅷䅁䭁䉁䄰䅁䭁䅁䅅䅁䭁䅁䅕䅁䙁䅁䅁䅁杂攴䅖允䅁䅁䅅䅁䙁乁橥䑣䬰㤱⽍䍄䉁䅁䅁兂䅁䅁䅍䅄䅁䅁䅯杈䅁䅁䅯允䅁䅁䅯兂䅁䅁䅕䅁䅁䕁卂欵䉁䅁䅁允䅁䅁䅕⽷潕䥘䌯吱䴸䅉䅅䅁䙁䅁䅁睁䵁䅁䅁权䅁䅁䅁权䉁䅁䅁权䙁䅁䅁兂䅁䅁䅁䍉浮䅑䅅䅁䉁䅁䅁兂㑃潈牘払敪睐杷允䅁䅁䅕䅁䑁䅁䅷䅁䭁䉁䄸䅁䭁䙁䅍䅁䭁䅁䅕䅁䙁䅁䅁䅁权敃䅚允䅁䅁䅅䅁䙁䥁䅐煹䙆橬䅂䍄䉁䅁䅁䅂䅁䅁䅍䅄䅁䅁䅯睔䅁䅁䅯杔䅁䅁䅕䅁䅁䭁啃唵䉁䅁䅁允䅁䅁䅕⽷潕䥘䌯呸䴸䅉䅅䅁䕁䅁䅁睁䵁䅁䅁权偂䅁䅁权佂䅁䅁兂䅁䅁䅁䱧汈䅑䅅䅁䉁䅁䅁兂灁䥘䌯匹捪睐杷允䅁䅁䅕䅁䑁䅁䅷䅁䭁䅁䅁䅁䭁䅁䅅䅁䭁䅁䅕䅁䙁䅁䅁䅁杂⭁䅚允䅁䅁䅅䅁䙁䱁敧敨剴乵⼴䍄䉁䅁䅁兂䅁䅁䅍䅄䅁䅁䅯杇䅁䅁䅯允䅁䅁䅯兂䅁䅁䅕䅁䅁䭁穁欵䉁䅁䅁允䅁䅁䅕䡰㥁瑃橥䐶䴸䅉䅅䅁䙁䅁䅁睁䵁䅁䅁权䅁䅁䅁权呂䅁䅁权䙁䅁䅁兂䅁䅁䅁临汶䅑䅅䅁䉁䅁䅁兂权楇搯䅊穙䅑杷允䅁䅁䅕䅁䑁䅁䅷䅁䭁䅁䅁䅁䭁䅁䅅䅁䭁䅁䅕䅁䙁䅁䅁䅁杁佒䅚允䅁䅁䅅䅁䙁䱁敧敨剴乵⼴䍄䉁䅁䅁兂䅁䅁䅍䅄䅁䅁䅯先䅁䅁䅯睕䅁䅁䅯兂䅁䅁䅕䅁䅁䕁卂欵䉁䅁䅁允䅁䅁䅕⽷潕䥘䌫歌䵁䅉䅅䅁䕁䅁䅁睁䵁䅁䅁权偂䅁䅁权佂䅁䅁兂䅁䅁䅁䱁汈䅑䅅䅁䉁䅁䅁兂桄桥畓⭒慈睐杷允䅁䅁䅕䅁䑁䅁䅷䅁䭁䉁䄴䅁䭁䙁䅍䅁䭁䅁䅕䅁䙁䅁䅁䅁杁教䅚允䅁䅁䅅䅁䙁䩁瑈䑦ㄸ楘䅊䍄䉁䅁䅁䅂䅁䅁䅍䅄䅁䅁䅯睔䅁䅁䅯杔䅁䅁䅕䅁䅁䵁癃唵䉁䅁䅁允䅁䅁䅕場啯歲桦樲䴸䅉䅅䅁䙁䅁䅁睁䵁䅁䅁权晁䅁䅁权䉁䅁䅁权䙁䅁䅁兂䅁䅁䅁佷汦䅑䅅䅁䉁䅁䅁兂㥁瑃橥䑣愳睐杷允䅁䅁䅕䅁䑁䅁䅷䅁䭁䉁䅷䅁䭁䙁䅍䅁䭁䅁䅕䅁䙁䅁䅁䅁䅃佋䅚允䅁䅁䅅䅁䙁䥁䌯匹捨祄䄵䍄䉁䅁䅁兂䅁䅁䅍䅄䅁䅁䅯杈䅁䅁䅯睕䅁䅁䅯兂䅁䅁䅕䅁䅁䥁塁欵䉁䅁䅁允䅁䅁䅕兇坒楄礱啋䵁䅉䅅䅁䕁䅁䅁睁䵁䅁䅁权偂䅁䅁权佂䅁䅁兂䅁䅁䅁䭧氯䅑䅅䅁䉁䅁䅁兂䑄匹捨㡪噌睐杷允䅁䅁䅕䅁䑁䅁䅷䅁䭁䅁䅁䅁䭁䙁䅍䅁䭁䅁䅕䅁䙁䅁䅁䅁䅄佰䅖允䅁䅁䅅䅁䙁乁橥䑣䬰穤䅆䍄䉁䅁䅁兂䅁䅁䅍䅄䅁䅁䅯杈䅁䅁䅯允䅁䅁䅯兂䅁䅁䅕䅁䅁䝁灄唵䉁䅁䅁允䅁䅁䅕積積積積稰䴸䅉䅅䅁䙁䅁䅁睁䵁䅁䅁权敁䅁䅁权䉁䅁䅁权䙁䅁䅁兂䅁䅁䅁䱉汐䅑䅅䅁䉁䅁䅁兂穁積積積呐睐杷允䅁䅁䅕䅁䑁䅁䅷䅁䭁䉁䅷䅁䭁䅁䅅䅁䭁䅁䅕䅁䙁䅁䅁䅁䅄改䅖允䅁䅁䅅䅁䙁䉁䘫ㄶ㑇瑈⽕䍄䉁䅁䅁兂䅁䅁䅍䅄䅁䅁䅯杈䅁䅁䅯睕䅁䅁䅯兂䅁䅁䅕䅁䅁佁䙂欵䉁䅁䅁允䅁䅁䅕渷⽷噎㘴䕊䵁䅉䅅䅁䕁䅁䅁睁䵁䅁䅁权偂䅁䅁权佂䅁䅁兂䅁䅁䅁䭑氯䅑䅅䅁䉁䅁䅁兂晁敨剴䉵嘷睐杷允䅁䅁䅑䅁䑁䅁䅷䅁䭁䕁䄸䅁䭁䕁䄴䅁䙁䅁䅁䅁杂畲䅖允䅁䅁䅅䅁䙁䙁㑋潈牘摕⽧䍄䉁䅁䅁兂䅁䅁䅍䅄䅁䅁䅯䅁䅁䅁䅯睕䅁䅁䅯兂䅁䅁䅕䅁䅁䍁婂欵䉁䅁䅁允䅁䅁䅕扏䥔牤昷き䵁䅉䅅䅁䙁䅁䅁睁䵁䅁䅁权晁䅁䅁权呂䅁䅁权䙁䅁䅁兂䅁䅁䅁䙙浄䅑䅅䅁䉁䅁䅁兂䕁杖琴桳砰䅑杷允䅁䅁䅑䅁䑁䅁䅷䅁䭁䕁䄸䅁䭁䕁䄴䅁䙁䅁䅁䅁䅃敲䅖允䅁䅁䅅䅁䙁䙁㑋潈牘摕⽧䍄䉁䅁䅁兂䅁䅁䅍䅄䅁䅁䅯䅁䅁䅁䅯睕䅁䅁䅯兂䅁䅁䅕䅁䅁䵁䩁欵䉁䅁䅁允䅁䅁䅕䙅㕧䵴坩歍䵁䅉䅅䅁䕁䅁䅁睁䵁䅁䅁权偂䅁䅁权佂䅁䅁兂䅁䅁䅁䬴決䅑䅅䅁䉁䅁䅁兂灁䥘䌯匹捪睐杷允䅁䅁䅕䅁䑁䅁䅷䅁䭁䉁䅷䅁䭁䅁䅅䅁䭁䅁䅕䅁䙁䅁䅁䅁杄攷䅖允䅁䅁䅅䅁䙁䑁積積積㥍⽍䍄䉁䅁䅁兂䅁䅁䅍䅄䅁䅁䅯先䅁䅁䅯睕䅁䅁䅯兂䅁䅁䅕䅁䅁䕁療欵䉁䅁䅁允䅁䅁䅕㑎䉬余兕歌䵁䅉䅅䅁䕁䅁䅁睁䵁䅁䅁权偂䅁䅁权佂䅁䅁兂䅁䅁䅁䭷決䅑䅅䅁䉁䅁䅁兂啁歲桦桥敔睐杷允䅁䅁䅕䅁䑁䅁䅷䅁䭁䅁䅁䅁䭁䅁䅅䅁䭁䅁䅕䅁䙁䅁䅁䅁杁留䅚允䅁䅁䅅䅁䙁䱁敧敨剴乵⼴䍄䉁䅁䅁兂䅁䅁䅍䅄䅁䅁䅯睈䅁䅁䅯睕䅁䅁䅯兂䅁䅁䅕䅁䅁佁祃唵䉁䅁䅁允䅁䅁䅕䉵䘶ㄶ奈䕍䵁䅉䅅䅁䕁䅁䅁睁䵁䅁䅁权偂䅁䅁权佂䅁䅁兂䅁䅁䅁䭯決䅑䅅䅁䉁䅁䅁兂䙃ㄶ㑇潈托睐杷允䅁䅁䅕䅁䑁䅁䅷䅁䭁䉁䄸䅁䭁䙁䅍䅁䭁䅁䅕䅁䙁䅁䅁䅁杄⭙䅚允䅁䅁䅅䅁䙁乁楅⼲⭬橃䅆䍄䉁䅁䅁兂䅁䅁䅍䅄䅁䅁䅯杈䅁䅁䅯睕䅁䅁䅯兂䅁䅁䅕䅁䅁䝁桄唵䉁䅁䅁允䅁䅁䅕呣䬰㘱睐か䵁䅉䅅䅁䕁䅁䅁睁䵁䅁䅁权偂䅁䅁权佂䅁䅁兂䅁䅁䅁䭉決䅑䅅䅁䉁䅁䅁兂畃⭒㙆䭆堷睐杷允䅁䅁䅑䅁䑁䅁䅷䅁䭁䕁䄸䅁䭁䕁䄴䅁䙁䅁䅁䅁杂⭱䅖允䅁䅁䅅䅁䙁䵁䴳䵺䵺乺⽷䍄䉁䅁䅁兂䅁䅁䅍䅄䅁䅁䅯䅈䅁䅁䅯睕䅁䅁䅯兂䅁䅁䅕䅁䅁䕁㡁欵䉁䅁䅁允䅁䅁䅕㥆佮ㄹ橏歌䵁䅉䅅䅁䕁䅁䅁睁䵁䅁䅁权偂䅁䅁权佂䅁䅁兂䅁䅁䅁䭑汶䅑䅅䅁䉁䅁䅁兂啁歲桦桥敔睐杷允䅁䅁䅕䅁䑁䅁䅷䅁䭁䅁䅁䅁䭁䙁䅍䅁䭁䅁䅕䅁䙁䅁䅁䅁䅃敐䅚允䅁䅁䅅䅁䙁䅁䅁䅁䅁䑯䅎䍄䉁䅁䅁兂䅁䅁䅍䅄䅁䅁䅯䅁䅁䅁䅯睕䅁䅁䅯兂䅁䅁䅕䅁䅁䕁睁欵䉁䅁䅁允䅁䅁䅕扌摋㘷䝥き䵁䅉䅅䅁䙁䅁䅁睁䵁䅁䅁权慁䅁䅁权呂䅁䅁权䙁䅁䅁兂䅁䅁䅁䅧浪䅑䅅䅁䉁䅁䅁兂䝂癴㥐䈱㙧䅑杷允䅁䅁䅕䅁䑁䅁䅷䅁䭁䉁䄸䅁䭁䙁䅍䅁䭁䅁䅕䅁䙁䅁䅁䅁䅄畉䅚允䅁䅁䅅䅁䙁䕁㉡⼸唳䐫䅂䍄䉁䅁䅁兂䅁䅁䅍䅄䅁䅁䅯先䅁䅁䅯睕䅁䅁䅯兂䅁䅁䅕䅁䅁䕁塂欵䉁䅁䅁允䅁䅁䅕⽷潕䥘䌫歌䵁䅉䅅䅁䕁䅁䅁睁䵁䅁䅁权偂䅁䅁权佂䅁䅁兂䅁䅁䅁䭉汶䅑䅅䅁䉁䅁䅁兂硂児塲㍯摄睐杷允䅁䅁䅕䅁䑁䅁䅷䅁䭁䉁䄸䅁䭁䙁䅍䅁䭁䅁䅕䅁䙁䅁䅁䅁杂敯䅖允䅁䅁䅅䅁䙁䩁䕺䱉祂䑋䅆䍄䉁䅁䅁兂䅁䅁䅍䅄䅁䅁䅯杇䅁䅁䅯睕䅁䅁䅯兂䅁䅁䅕䅁䅁佁㡂欵䉁䅁䅁允䅁䅁䅕䑔䩥坑汁く䵁䅉䅅䅁䙁䅁䅁睁䵁䅁䅁权䅁䅁䅁权䉁䅁䅁权䙁䅁䅁兂䅁䅁䅁偉汲䅑䅅䅁䉁䅁䅁兂㑃潈牘払敪睐杷允䅁䅁䅕䅁䑁䅁䅷䅁䭁䅁䅁䅁䭁䅁䅅䅁䭁䅁䅕䅁䙁䅁䅁䅁䅁⭓䅚允䅁䅁䅅䅁䙁䱁敧敨剴乵⼴䍄䉁䅁䅁兂䅁䅁䅍䅄䅁䅁䅯䅁䅁䅁䅯睕䅁䅁䅯兂䅁䅁䅕䅁䅁䅁獄唵䉁䅁䅁允䅁䅁䅕積積積呏歍䵁䅉䅅䅁䙁䅁䅁睁䵁䅁䅁权摁䅁䅁权呂䅁䅁权䙁䅁䅁兂䅁䅁䅁䡯浐䅑䅅䅁䉁䅁䅁兂睄㡰䱚㡎瑫䅑杷允䅁䅁䅕䅁䑁䅁䅷䅁䭁䉁䄴䅁䭁䙁䅍䅁䭁䅁䅕䅁䙁䅁䅁䅁杁佋䅚允䅁䅁䅅䅁䙁䡁呗䅇坒楺䅤䍄䉁䅁䅁兂䅁䅁䅍䅄䅁䅁䅯睈䅁䅁䅯允䅁䅁䅯兂䅁䅁䅕䅁䅁䅁塄唵䉁䅁䅁允䅁䅁䅕捺䵺䵺䵺䐳䴸䅉䅅䅁䕁䅁䅁睁䵁䅁䅁权偂䅁䅁权佂䅁䅁兂䅁䅁䅁䭑汲䅑䅅䅁䉁䅁䅁兂啁歲桦桥敔睐杷允䅁䅁䅕䅁䑁䅁䅷䅁䭁䅁䅁䅁䭁䅁䅅䅁䭁䅁䅕䅁䙁䅁䅁䅁䅂伫䅖允䅁䅁䅅䅁䙁䱁敧敨剴乵⼴䍄䉁䅁䅁兂䅁䅁䅍䅄䅁䅁䅯睈䅁䅁䅯睕䅁䅁䅯兂䅁䅁䅕䅁䅁䝁歃唵䉁䅁䅁允䅁䅁䅕䉵䘶ㄶ㑆䕍䵁䅉䅅䅁䙁䅁䅁睁䵁䅁䅁权䅁䅁䅁权䉁䅁䅁权䙁䅁䅁兂䅁䅁䅁䅯浄䅑䅅䅁䉁䅁䅁兂㑃潈牘払敪睐杷允䅁䅁䅕䅁䑁䅁䅷䅁䭁䅁䅁䅁䭁䅁䅅䅁䭁䅁䅕䅁䙁䅁䅁䅁杁界䅚允䅁䅁䅅䅁䙁䱁敧敨剴乵⼴䍄䉁䅁䅁兂䅁䅁䅍䅄䅁䅁䅯睈䅁䅁䅯允䅁䅁䅯兂䅁䅁䅕䅁䅁䝁ㅄ唵䉁䅁䅁允䅁䅁䅕場啯歲桦樲䴸䅉䅅䅁䕁䅁䅁睁䵁䅁䅁权偂䅁䅁权佂䅁䅁兂䅁䅁䅁䭯汮䅑䅅䅁䉁䅁䅁兂啁歲桦桥敔睐杷允䅁䅁䅕䅁䑁䅁䅷䅁䭁䉁䄸䅁䭁䙁䅍䅁䭁䅁䅕䅁䙁䅁䅁䅁杁佘䅚允䅁䅁䅅䅁䙁乁楅⼲⭬橃䅆䍄䉁䅁䅁兂䅁䅁䅍䅄䅁䅁䅯䅁䅁䅁䅯允䅁䅁䅯兂䅁䅁䅕䅁䅁䵁ㅄ唵䉁䅁䅁允䅁䅁䅕䉵䘶ㄶ㑇樳䴸䅉䅅䅁䙁䅁䅁睁䵁䅁䅁权敁䅁䅁权呂䅁䅁权䙁䅁䅁兂䅁䅁䅁䌴浘䅑䅅䅁䉁䅁䅁兂ㅂ硫䕧獖渴䅑杷允䅁䅁䅑䅁䑁䅁䅷䅁䭁䕁䄸䅁䭁䕁䄴䅁䙁䅁䅁䅁䅂敱䅖允䅁䅁䅅䅁䙁䵁ㅐ䙋偹瑷⽕䍄䉁䅁䅁兂䅁䅁䅍䅄䅁䅁䅯䅁䅁䅁䅯睕䅁䅁䅯兂䅁䅁䅕䅁䅁䥁兂欵䉁䅁䅁允䅁䅁䅕扏䥔牤昷き䵁䅉䅅䅁䙁䅁䅁睁䵁䅁䅁权慁䅁䅁权䉁䅁䅁权䙁䅁䅁兂䅁䅁䅁䱁汲䅑䅅䅁䉁䅁䅁兂䅁䅁䅁䅁杄睐杷允䅁䅁䅕䅁䑁䅁䅷䅁䭁䉁䅷䅁䭁䅁䅅䅁䭁䅁䅕䅁䙁䅁䅁䅁䅂⬰䅖允䅁䅁䅅䅁䙁䑁積積積㥍⽍䍄䉁䅁䅁兂䅁䅁䅍䅄䅁䅁䅯䅈䅁䅁䅯睕䅁䅁䅯兂䅁䅁䅕䅁䅁䕁畁欵䉁䅁䅁允䅁䅁䅕䑗ね䡹⭙歌䵁䅉䅅䅁䙁䅁䅁睁䵁䅁䅁权摁䅁䅁权呂䅁䅁权䙁䅁䅁兂䅁䅁䅁䙙浌䅑䅅䅁䉁䅁䅁兂䑄匹捨㑪畉䅑杷允䅁䅁䅑䅁䑁䅁䅷䅁䭁䕁䄸䅁䭁䕁䄴䅁䙁䅁䅁䅁杁敱䅖允䅁䅁䅅䅁䙁䉁䘫ㄶ㑇瑈⽕䍄䉁䅁䅁兂䅁䅁䅍䅄䅁䅁䅯䅁䅁䅁䅯允䅁䅁䅯兂䅁䅁䅕䅁䅁䕁噃唵䉁䅁䅁允䅁䅁䅕灭婭婭婭吲䴸䅉䅅䅁䕁䅁䅁睁䵁䅁䅁权偂䅁䅁权佂䅁䅁兂䅁䅁䅁䭯汪䅑䅅䅁䉁䅁䅁兂穁積積積呐睐杷允䅁䅁䅕䅁䑁䅁䅷䅁䭁䅁䅁䅁䭁䙁䅍䅁䭁䅁䅕䅁䙁䅁䅁䅁杄畏䅚允䅁䅁䅅䅁䙁䅁䅁䅁䅁䑯䅎䍄䉁䅁䅁兂䅁䅁䅍䅄䅁䅁䅯杇䅁䅁䅯允䅁䅁䅯兂䅁䅁䅕䅁䅁䕁㥃唵䉁䅁䅁允䅁䅁䅕䅁䅁䅁䅁䐴䴸䅉䅅䅁䙁䅁䅁睁䵁䅁䅁权捁䅁䅁权䉁䅁䅁权䙁䅁䅁兂䅁䅁䅁䉁浔䅑䅅䅁䉁䅁䅁兂晁敨剴䉵嘷睐杷允䅁䅁䅕䅁䑁䅁䅷䅁䭁䉁䄸䅁䭁䅁䅅䅁䭁䅁䅕䅁䙁䅁䅁䅁䅂佲䅖允䅁䅁䅅䅁䭁䉁䅳䅁䵁䅉䅅䅁䙁䅁䅁睁䵁䅁䅁权敁䅁䅁权呂䅁䅁权䙁䅁䅁兂䅁䅁䅁䍷浶䅑䅅䅁䉁䅁䅁兂ㅂ硫䕧獖渴䅑杷允䅁䅁䅕䅁䑁䅁䅷䅁䭁䅁䅁䅁䭁䅁䅅䅁䭁䅁䅕䅁䙁䅁䅁䅁䅄⬫䅖允䅁䅁䅅䅁䙁䱁敧敨剴乵⼴䍄䉁䅁䅁兂䅁䅁䅍䅄䅁䅁䅯䅈䅁䅁䅯允䅁䅁䅯兂䅁䅁䅕䅁䅁䝁剂欵䉁䅁䅁允䅁䅁䅕椹捨㡪ㅌ䐲䴸䅉䅅䅁䕁䅁䅁睁䵁䅁䅁权偂䅁䅁权佂䅁䅁兂䅁䅁䅁䭯汦䅑䅅䅁䉁䅁䅁兂穁積積積呐睐杷允䅁䅁䅕䅁䑁䅁䅷䅁䭁䅁䅁䅁䭁䅁䅅䅁䭁䅁䅕䅁䙁䅁䅁䅁䅁佣䅚允䅁䅁䅅䅁䙁䱁敧敨剴乵⼴䍄䉁䅁䅁䅂䅁䅁䅍䅄䅁䅁䅯睔䅁䅁䅯杔䅁䅁䅕䅁䅁䍁汃唵䉁䅁䅁允䅁䅁䅕㑈牘払敧吱䴸䅉䅅䅁䙁䅁䅁睁䵁䅁䅁权慁䅁䅁权呂䅁䅁权䙁䅁䅁兂䅁䅁䅁䡷浲䅑䅅䅁䉁䅁䅁兂䵂㑎䉬䍙㝕䅑杷允䅁䅁䅕䅁䑁䅁䅷䅁䭁䉁䄰䅁䭁䅁䅅䅁䭁䅁䅕䅁䙁䅁䅁䅁权畔䅚允䅁䅁䅅䅁䙁䭁䠵場啯瑲⽣䍄䉁䅁䅁䅂䅁䅁䅍䅄䅁䅁䅯睔䅁䅁䅯杔䅁䅁䅕䅁䅁佁浃唵䉁䅁䅁允䅁䅁䅕㘱睎児塲稰䴸䅉䅅䅁䙁䅁䅁睁䵁䅁䅁权捁䅁䅁权呂䅁䅁权䙁䅁䅁兂䅁䅁䅁䝁浐䅑䅅䅁䉁䅁䅁兂楃扒穢刯畑䅑杷允䅁䅁䅕䅁䑁䅁䅷䅁䭁䅁䅁䅁䭁䙁䅍䅁䭁䅁䅕䅁䙁䅁䅁䅁杂畕䅚允䅁䅁䅅䅁䙁䑁ね䡹⭡稳䅎䍄䉁䅁䅁䅂䅁䅁䅍䅄䅁䅁䅯睔䅁䅁䅯杔䅁䅁䅕䅁䅁䵁汃唵䉁䅁䅁允䅁䅁䅕⽷潕䥘䌯吱䴸䅉䅅䅁䕁䅁䅁睁䵁䅁䅁权偂䅁䅁权佂䅁䅁兂䅁䅁䅁䭷汔䅑䅅䅁䉁䅁䅁兂㝂䭆䠵場啲睐杷允䅁䅁䅕䅁䑁䅁䅷䅁䭁䅁䅁䅁䭁䅁䅅䅁䭁䅁䅕䅁䙁䅁䅁䅁杁⭒䅚允䅁䅁䅅䅁䙁䱁敧敨剴乵⼴䍄䉁䅁䅁䅂䅁䅁䅍䅄䅁䅁䅯睔䅁䅁䅯杔䅁䅁䅕䅁䅁䝁歃唵䉁䅁䅁允䅁䅁䅕㡪ㅌ䙋偹樰䴸䅉䅅䅁䙁䅁䅁睁䵁䅁䅁权慁䅁䅁权呂䅁䅁权䙁䅁䅁兂䅁䅁䅁䙯浢䅑䅅䅁䉁䅁䅁兂䑄匹捨㉪㝉䅑杷允䅁䅁䅕䅁䑁䅁䅷䅁䭁䉁䅯䅁䭁䙁䅍䅁䭁䅁䅕䅁䙁䅁䅁䅁䅃敓䅚允䅁䅁䅅䅁䙁䕁㍷啩杆呒䅴䍄䉁䅁䅁兂䅁䅁䅍䅄䅁䅁䅯䅈䅁䅁䅯睕䅁䅁䅯兂䅁䅁䅕䅁䅁䵁坂欵䉁䅁䅁允䅁䅁䅕匳䝑婧䑖歌䵁䅉䅅䅁䙁䅁䅁睁䵁䅁䅁权䅁䅁䅁权呂䅁䅁权䙁䅁䅁兂䅁䅁䅁䱙汮䅑䅅䅁䉁䅁䅁兂㙃兓䍷祋祣䅑杷允䅁䅁䅕䅁䑁䅁䅷䅁䭁䅁䅁䅁䭁䙁䅍䅁䭁䅁䅕䅁䙁䅁䅁䅁杁⭃䅚允䅁䅁䅅䅁䙁䉁奂扏䥔橬䅊䍄䉁䅁䅁兂䅁䅁䅍䅄䅁䅁䅯杈䅁䅁䅯睕䅁䅁䅯兂䅁䅁䅕䅁䅁䵁䕄唵䉁䅁䅁允䅁䅁䅕呣䬰㘱睍䕌䵁䅉䅅䅁䙁䅁䅁睁䵁䅁䅁权慁䅁䅁权䉁䅁䅁权䙁䅁䅁兂䅁䅁䅁偷汮䅑䅅䅁䉁䅁䅁兂穁積積積橐睐杷允䅁䅁䅕䅁䑁䅁䅷䅁䭁䉁䅯䅁䭁䙁䅍䅁䭁䅁䅕䅁䙁䅁䅁䅁杂佇䅚允䅁䅁䅅䅁䙁䱁穢搯㑒呩䅰䍄䉁䅁䅁兂䅁䅁䅍䅄䅁䅁䅯䅈䅁䅁䅯睕䅁䅁䅯兂䅁䅁䅕䅁䅁䕁扃唵䉁䅁䅁允䅁䅁䅕捷桱扒穙啌䵁䅉䅅䅁䙁䅁䅁睁䵁䅁䅁权敁䅁䅁权䉁䅁䅁权䙁䅁䅁兂䅁䅁䅁䵑汄䅑䅅䅁䉁䅁䅁兂穁積積積呐睐杷允䅁䅁䅕䅁䑁䅁䅷䅁䭁䉁䄴䅁䭁䙁䅍䅁䭁䅁䅕䅁䙁䅁䅁䅁权佲䅖允䅁䅁䅅䅁䙁䡁⭥确癯午䅴䍄䉁䅁䅁䅂䅁䅁䅍䅄䅁䅁䅯睔䅁䅁䅯杔䅁䅁䅕䅁䅁䅁歃唵䉁䅁䅁允䅁䅁䅕㑈牘払敧吱䴸䅉䅅䅁䙁䅁䅁睁䵁䅁䅁权䅁䅁䅁权呂䅁䅁权䙁䅁䅁兂䅁䅁䅁䭷汦䅑䅅䅁䉁䅁䅁兂塄㍯㥁湃硣䅑杷允䅁䅁䅕䅁䑁䅁䅷䅁䭁䉁䅯䅁䭁䙁䅍䅁䭁䅁䅕䅁䙁䅁䅁䅁杄敍䅚允䅁䅁䅅䅁䙁䉁䘫ㄶ㑇樳䅰䍄䉁䅁䅁兂䅁䅁䅍䅄䅁䅁䅯䅁䅁䅁䅯允䅁䅁䅯兂䅁䅁䅕䅁䅁䵁偄唵䉁䅁䅁允䅁䅁䅕児塲㍯㥁樲䴸䅉䅅䅁䙁䅁䅁睁䵁䅁䅁权摁䅁䅁权䉁䅁䅁权䙁䅁䅁兂䅁䅁䅁䝁浶䅑䅅䅁䉁䅁䅁兂畃⭒㙆䭆堷睐杷允䅁䅁䅕䅁䑁䅁䅷䅁䭁䅁䅁䅁䭁䅁䅅䅁䭁䅁䅕䅁䙁䅁䅁䅁杄畦䅚允䅁䅁䅅䅁䙁䱁敧敨剴乵⼴䍄䉁䅁䅁兂䅁䅁䅍䅄䅁䅁䅯䅁䅁䅁䅯睕䅁䅁䅯兂䅁䅁䅕䅁䅁䍁瑂欵䉁䅁䅁允䅁䅁䅕佖汏㡭杔き䵁䅉䅅䅁䙁䅁䅁睁䵁䅁䅁权捁䅁䅁权呂䅁䅁权䙁䅁䅁兂䅁䅁䅁乙汔䅑䅅䅁䉁䅁䅁兂佂桙奂扏畑䅑杷允䅁䅁䅑䅁䑁䅁䅷䅁䭁䕁䄸䅁䭁䕁䄴䅁䙁䅁䅁䅁䅂⭯䅖允䅁䅁䅅䅁䙁䝁浚浚浚瑚⽙䍄䉁䅁䅁兂䅁䅁䅍䅄䅁䅁䅯䅁䅁䅁䅯睕䅁䅁䅯兂䅁䅁䅕䅁䅁䕁祄唵䉁䅁䅁允䅁䅁䅕積積積呏歍䵁䅉䅅䅁䙁䅁䅁睁䵁䅁䅁权捁䅁䅁权䉁䅁䅁权䙁䅁䅁兂䅁䅁䅁乯汈䅑䅅䅁䉁䅁䅁兂穁積積積呐睐杷允䅁䅁䅑䅁䑁䅁䅷䅁䭁䕁䄸䅁䭁䕁䄴䅁䙁䅁䅁䅁权敯䅖允䅁䅁䅅䅁䙁䡁啳歲桦瑥⽑䍄䉁䅁䅁兂䅁䅁䅍䅄䅁䅁䅯先䅁䅁䅯睕䅁䅁䅯兂䅁䅁䅕䅁䅁佁佄唵䉁䅁䅁允䅁䅁䅕噋偹癷潕歌䵁䅉䅅䅁䙁䅁䅁睁䵁䅁䅁权敁䅁䅁权呂䅁䅁权䙁䅁䅁兂䅁䅁䅁䔴浈䅑䅅䅁䉁䅁䅁兂い搯㑒圶歙䅑杷允䅁䅁䅑䅁䑁䅁䅷䅁䭁䕁䄸䅁䭁䕁䄴䅁䙁䅁䅁䅁䅄佯䅖允䅁䅁䅅䅁䙁䉁䘫ㄶ㑇瑈⽕䍄䉁䅁䅁兂䅁䅁䅍䅄䅁䅁䅯先䅁䅁䅯允䅁䅁䅯兂䅁䅁䅕䅁䅁䕁捄唵䉁䅁䅁允䅁䅁䅕㘱睎児塲稰䴸䅉䅅䅁䙁䅁䅁睁䵁䅁䅁权敁䅁䅁权呂䅁䅁权䙁䅁䅁兂䅁䅁䅁䅷浢䅑䅅䅁䉁䅁䅁兂䅁䅁䅁䅁煁䅑杷允䅁䅁䅕䅁䑁䅁䅷䅁䭁䅁䅁䅁䭁䅁䅅䅁䭁䅁䅕䅁䙁䅁䅁䅁䅃甲䅖允䅁䅁䅅䅁䙁佁㙆䭆䠵搴⽯䍄䉁䅁䅁䅂䅁䅁䅍䅄䅁䅁䅯睔䅁䅁䅯杔䅁䅁䅕䅁䅁䭁晃唵䉁䅁䅁允䅁䅁䅕㑈牘払敧吱䴸䅉䅅䅁䕁䅁䅁睁䵁䅁䅁权偂䅁䅁权佂䅁䅁兂䅁䅁䅁䩧氯䅑䅅䅁䉁䅁䅁兂㝂䭆䠵場啲睐杷允䅁䅁䅕䅁䑁䅁䅷䅁䭁䉁䄴䅁䭁䙁䅍䅁䭁䅁䅕䅁䙁䅁䅁䅁杂⭴䅖允䅁䅁䅅䅁䙁䱁穢搯㑒卡䅸䍄䉁䅁䅁兂䅁䅁䅍䅄䅁䅁䅯睈䅁䅁䅯睕䅁䅁䅯兂䅁䅁䅕䅁䅁䭁㝄唵䉁䅁䅁允䅁䅁䅕⽺呤㘴㝖䕍䵁䅉䅅䅁䙁䅁䅁睁䵁䅁䅁权捁䅁䅁权呂䅁䅁权䙁䅁䅁兂䅁䅁䅁䕑浲䅑䅅䅁䉁䅁䅁兂療潅䅐浹畅䅑杷允䅁䅁䅕䅁䑁䅁䅷䅁䭁䉁䄴䅁䭁䙁䅍䅁䭁䅁䅕䅁䙁䅁䅁䅁䅂敚䅚允䅁䅁䅅䅁䙁䩁瑈䑦ㄸ楘䅊䍄䉁䅁䅁䅂䅁䅁䅍䅄䅁䅁䅯睔䅁䅁䅯杔䅁䅁䅕䅁䅁䵁摃唵䉁䅁䅁允䅁䅁䅕㑈牘払敧吱䴸䅉䅅䅁䕁䅁䅁睁䵁䅁䅁权偂䅁䅁权佂䅁䅁兂䅁䅁䅁䩧汶䅑䅅䅁䉁䅁䅁兂䑄匹捨㡪噌睐杷允䅁䅁䅑䅁䑁䅁䅷䅁䭁䕁䄸䅁䭁䕁䄴䅁䙁䅁䅁䅁䅄畭䅖允䅁䅁䅅䅁䙁䍁捬㡪ㅌ䵋⽷䍄䉁䅁䅁兂䅁䅁䅍䅄䅁䅁䅯杈䅁䅁䅯睕䅁䅁䅯兂䅁䅁䅕䅁䅁䍁煂欵䉁䅁䅁允䅁䅁䅕匰扌堫焵啉䵁䅉䅅䅁䕁䅁䅁睁䵁䅁䅁权偂䅁䅁权佂䅁䅁兂䅁䅁䅁䩙汲䅑䅅䅁䉁䅁䅁兂硂児塲㍯乄睐杷允䅁䅁䅕䅁䑁䅁䅷䅁䭁䉁䅷䅁䭁䙁䅍䅁䭁䅁䅕䅁䙁䅁䅁䅁杂敎䅚允䅁䅁䅅䅁䙁䙁㕧䵴㉨楐䄵䍄䉁䅁䅁兂䅁䅁䅍䅄䅁䅁䅯杈䅁䅁䅯睕䅁䅁䅯兂䅁䅁䅕䅁䅁䕁䅁欵䉁䅁䅁允䅁䅁䅕䅁䅁䅁䅁歋䵁䅉䅅䅁䕁䅁䅁睁䵁䅁䅁权偂䅁䅁权佂䅁䅁兂䅁䅁䅁䩷汮䅑䅅䅁䉁䅁䅁兂卂䉵䘶ㄶ䥈睐杷允䅁䅁䅕䅁䑁䅁䅷䅁䭁䉁䄴䅁䭁䅁䅅䅁䭁䅁䅕䅁䙁䅁䅁䅁权畲䅖允䅁䅁䅅䅁䙁䑁積積積㥍⽍䍄䉁䅁䅁兂䅁䅁䅍䅄䅁䅁䅯䅁䅁䅁䅯允䅁䅁䅯兂䅁䅁䅕䅁䅁䵁䅂欵䉁䅁䅁允䅁䅁䅕䉵䘶ㄶ㑇樳䴸䅉䅅䅁䕁䅁䅁睁䵁䅁䅁权偂䅁䅁权佂䅁䅁兂䅁䅁䅁䩯汮䅑䅅䅁䉁䅁䅁兂卂䉵䘶ㄶ䥈睐杷允䅁䅁䅕䅁䑁䅁䅷䅁䭁䅁䅁䅁䭁䙁䅍䅁䭁䅁䅕䅁䙁䅁䅁䅁杁併䅖允䅁䅁䅅䅁䙁䱁䩰䅄牉穊䅊䍄䉁䅁䅁䅂䅁䅁䅍䅄䅁䅁䅯睔䅁䅁䅯杔䅁䅁䅕䅁䅁䝁婃唵䉁䅁䅁允䅁䅁䅕灭婭婭婭呹䴸䅉䅅䅁䙁䅁䅁睁䵁䅁䅁权䅁䅁䅁权䉁䅁䅁权䙁䅁䅁兂䅁䅁䅁䨴汘䅑䅅䅁䉁䅁䅁兂慃婭婭婭婮睐杷允䅁䅁䅕䅁䑁䅁䅷䅁䭁䉁䄸䅁䭁䙁䅍䅁䭁䅁䅕䅁䙁䅁䅁䅁杁⭺䅖允䅁䅁䅅䅁䙁䕁䵯楁䡵樱䅂䍄䉁䅁䅁䅂䅁䅁䅍䅄䅁䅁䅯睔䅁䅁䅯杔䅁䅁䅕䅁䅁䅁婃唵䉁䅁䅁允䅁䅁䅕牕敧敨剴䑹䴸䅉䅅䅁䙁䅁䅁睁䵁䅁䅁权慁䅁䅁权呂䅁䅁权䙁䅁䅁兂䅁䅁䅁䑷浪䅑䅅䅁䉁䅁䅁兂晁敨剴乵㘴䅑杷允䅁䅁䅕䅁䑁䅁䅷䅁䭁䉁䅷䅁䭁䙁䅍䅁䭁䅁䅕䅁䙁䅁䅁䅁杄畐䅚允䅁䅁䅅䅁䙁䉁婦発呤祯䄵䍄䉁䅁䅁䅂䅁䅁䅍䅄䅁䅁䅯睔䅁䅁䅯杔䅁䅁䅕䅁䅁䕁塃唵䉁䅁䅁允䅁䅁䅕牕敧敨剴䑹䴸䅉䅅䅁䙁䅁䅁睁䵁䅁䅁权捁䅁䅁权䉁䅁䅁权䙁䅁䅁兂䅁䅁䅁䙙洷䅑䅅䅁䉁䅁䅁兂㉄䙋偹癷奘睐杷允䅁䅁䅕䅁䑁䅁䅷䅁䭁䉁䄰䅁䭁䙁䅍䅁䭁䅁䅕䅁䙁䅁䅁䅁杁⭑䅚允䅁䅁䅅䅁䙁䕁㉡⼸唳䍵䄵䍄䉁䅁䅁䅂䅁䅁䅍䅄䅁䅁䅯睔䅁䅁䅯杔䅁䅁䅕䅁䅁佁坃唵䉁䅁䅁允䅁䅁䅕場啯歲桦橹䴸䅉䅅䅁䙁䅁䅁睁䵁䅁䅁权慁䅁䅁权呂䅁䅁权䙁䅁䅁兂䅁䅁䅁䱙汮䅑䅅䅁䉁䅁䅁兂⽁噎㘶敓㕷䅑杷允䅁䅁䅕䅁䑁䅁䅷䅁䭁䅁䅁䅁䭁䙁䅍䅁䭁䅁䅕䅁䙁䅁䅁䅁权佚䅚允䅁䅁䅅䅁䙁䭁硲欰椱䐰䅎䍄䉁䅁䅁兂䅁䅁䅍䅄䅁䅁䅯䅁䅁䅁䅯睕䅁䅁䅯兂䅁䅁䅕䅁䅁䥁㉄唵䉁䅁䅁允䅁䅁䅕噋偹癷潖歍䵁䅉䅅䅁䙁䅁䅁睁䵁䅁䅁权摁䅁䅁权䉁䅁䅁权䙁䅁䅁兂䅁䅁䅁䙷浄䅑䅅䅁䉁䅁䅁兂畃⭒㙆䭆堷睐杷允䅁䅁䅕䅁䑁䅁䅷䅁䭁䉁䄴䅁䭁䙁䅍䅁䭁䅁䅕䅁䙁䅁䅁䅁䅄畗䅚允䅁䅁䅅䅁䙁乁㕶浦㡱䍤䅊䍄䉁䅁䅁䅂䅁䅁䅍䅄䅁䅁䅯睔䅁䅁䅯杔䅁䅁䅕䅁䅁䅁坃唵䉁䅁䅁允䅁䅁䅕呣䬰㘱睎呺䴸䅉䅅䅁䙁䅁䅁睁䵁䅁䅁权䅁䅁䅁权呂䅁䅁权䙁䅁䅁兂䅁䅁䅁偉汲䅑䅅䅁䉁䅁䅁兂灁䥘䌯圹祧䅑杷允䅁䅁䅕䅁䑁䅁䅷䅁䭁䉁䅷䅁䭁䙁䅍䅁䭁䅁䅕䅁䙁䅁䅁䅁杂佅䅚允䅁䅁䅅䅁䙁䙁㘶兓䍷祱䄱䍄䉁䅁䅁兂䅁䅁䅍䅄䅁䅁䅯先䅁䅁䅯睕䅁䅁䅯兂䅁䅁䅕䅁䅁䍁䡄唵䉁䅁䅁允䅁䅁䅕䑔䩥坑汄啌䵁䅉䅅䅁䕁䅁䅁睁䵁䅁䅁权偂䅁䅁权佂䅁䅁兂䅁䅁䅁䨴汘䅑䅅䅁䉁䅁䅁兂灁䥘䌯匹䵪睐杷允䅁䅁䅕䅁䑁䅁䅷䅁䭁䅁䅁䅁䭁䅁䅅䅁䭁䅁䅕䅁䙁䅁䅁䅁䅁⭄䅚允䅁䅁䅅䅁䙁䱁敧敨剴乵⼴䍄䉁䅁䅁兂䅁䅁䅍䅄䅁䅁䅯杇䅁䅁䅯睕䅁䅁䅯兂䅁䅁䅕䅁䅁佁ぃ唵䉁䅁䅁允䅁䅁䅕穐敖歵獮問䵁䅉䅅䅁䙁䅁䅁睁䵁䅁䅁权捁䅁䅁权呂䅁䅁权䙁䅁䅁兂䅁䅁䅁䭯汦䅑䅅䅁䉁䅁䅁兂㉄䙋偹牷瑕䅑杷允䅁䅁䅑䅁䑁䅁䅷䅁䭁䕁䄸䅁䭁䕁䄴䅁䙁䅁䅁䅁䅃敬䅖允䅁䅁䅅䅁䙁䱁敧敨剴䵵⼴䍄䉁䅁䅁兂䅁䅁䅍䅄䅁䅁䅯䅁䅁䅁䅯允䅁䅁䅯兂䅁䅁䅕䅁䅁䍁䑂欵䉁䅁䅁允䅁䅁䅕䉵䘶ㄶ㑇樳䴸䅉䅅䅁䙁䅁䅁睁䵁䅁䅁权捁䅁䅁权呂䅁䅁权䙁䅁䅁兂䅁䅁䅁䱧氷䅑䅅䅁䉁䅁䅁兂桄桥畓㉒畅䅑杷允䅁䅁䅑䅁䑁䅁䅷䅁䭁䕁䄸䅁䭁䕁䄴䅁䙁䅁䅁䅁䅁敬䅖允䅁䅁䅅䅁䙁䡁啳歲桦獥⽑䍄䉁䅁䅁兂䅁䅁䅍䅄䅁䅁䅯䅁䅁䅁䅯允䅁䅁䅯兂䅁䅁䅕䅁䅁䕁䙄唵䉁䅁䅁允䅁䅁䅕児塲㍯㥁樲䴸䅉䅅䅁䙁䅁䅁睁䵁䅁䅁权䅁䅁䅁权呂䅁䅁权䙁䅁䅁兂䅁䅁䅁䄴洳䅑䅅䅁䉁䅁䅁兂允䑗ね䩹祙䅑杷允䅁䅁䅑䅁䑁䅁䅷䅁䭁䅁䅁䅁䭁䙁䅑䅁䙁䅁䅁䅁䅃畧䅚允䅁䅁䅅䅁䭁䉁䅳䅁䵁䅉䅅䅁䙁䅁䅁睁䵁䅁䅁权䅁䅁䅁权呂䅁䅁权䙁䅁䅁兂䅁䅁䅁䩁汪䅑䅅䅁䉁䅁䅁兂㡃䩤奍䡂睙䅑杷允䅁䅁䅕䅁䑁䅁䅷䅁䭁䉁䄰䅁䭁䙁䅍䅁䭁䅁䅕䅁䙁䅁䅁䅁䅄故䅚允䅁䅁䅅䅁䙁䱁䩰䅄牉票䄵䍄䉁䅁䅁兂䅁䅁䅍䅄䅁䅁䅯䅈䅁䅁䅯睕䅁䅁䅯兂䅁䅁䅕䅁䅁䍁㑄唵䉁䅁䅁允䅁䅁䅕牘䩰䅄牊啌䵁䅉䅅䅁䙁䅁䅁睁䵁䅁䅁权䅁䅁䅁权呂䅁䅁权䙁䅁䅁兂䅁䅁䅁䥑浌䅑䅅䅁䉁䅁䅁兂⭄䠱灪癊穅䅑杷允䅁䅁䅕䅁䑁䅁䅷䅁䭁䉁䅷䅁䭁䙁䅍䅁䭁䅁䅕䅁䙁䅁䅁䅁权救䅚允䅁䅁䅅䅁䙁䉁婦発呤祯䄵䍄䉁䅁䅁兂䅁䅁䅍䅄䅁䅁䅯先䅁䅁䅯允䅁䅁䅯兂䅁䅁䅕䅁䅁䍁桂欵䉁䅁䅁允䅁䅁䅕歲桦桥畓稱䴸䅉䅅䅁䙁䅁䅁睁䵁䅁䅁权敁䅁䅁权呂䅁䅁权䙁䅁䅁兂䅁䅁䅁佉汐䅑䅅䅁䉁䅁䅁兂硂児塲⽯牁䅑杷允䅁䅁䅕䅁䑁䅁䅷䅁䭁䅁䅁䅁䭁䙁䅍䅁䭁䅁䅕䅁䙁䅁䅁䅁䅃佮䅖允䅁䅁䅅䅁䙁乁橥䑣䬰稹䅂䍄䉁䅁䅁兂䅁䅁䅍䅄䅁䅁䅯䅁䅁䅁䅯睕䅁䅁䅯兂䅁䅁䅕䅁䅁䅁硄唵䉁䅁䅁允䅁䅁䅕積積積呏歍䵁䅉䅅䅁䙁䅁䅁睁䵁䅁䅁权摁䅁䅁权呂䅁䅁权䙁䅁䅁兂䅁䅁䅁䍁浌䅑䅅䅁䉁䅁䅁兂䭁㘱睎捐畯䅑杷允䅁䅁䅕䅁䑁䅁䅷䅁䭁䅁䅁䅁䭁䅁䅅䅁䭁䅁䅕䅁䙁䅁䅁䅁䅂⭘䅚允䅁䅁䅅䅁䙁䱁敧敨剴乵⼴䍄䉁䅁䅁兂䅁䅁䅍䅄䅁䅁䅯䅁䅁䅁䅯睕䅁䅁䅯兂䅁䅁䅕䅁䅁䭁䍁欵䉁䅁䅁允䅁䅁䅕癱午坔睊歍䵁䅉䅅䅁䙁䅁䅁睁䵁䅁䅁权摁䅁䅁权呂䅁䅁权䙁䅁䅁兂䅁䅁䅁䭧汌䅑䅅䅁䉁䅁䅁兂䝂癴㥐䠱瑧䅑杷允䅁䅁䅕䅁䑁䅁䅷䅁䭁䅁䅁䅁䭁䙁䅍䅁䭁䅁䅕䅁䙁䅁䅁䅁杄⭙䅚允䅁䅁䅅䅁䙁䭁硲欰椱䐰䅎䍄䉁䅁䅁兂䅁䅁䅍䅄䅁䅁䅯睈䅁䅁䅯允䅁䅁䅯兂䅁䅁䅕䅁䅁䅁硂欵䉁䅁䅁允䅁䅁䅕牕敧敨剴䐴䴸䅉䅅䅁䙁䅁䅁睁䵁䅁䅁权慁䅁䅁权呂䅁䅁权䙁䅁䅁兂䅁䅁䅁䕙浮䅑䅅䅁䉁䅁䅁兂䵂㑎䉬䕙㝕䅑杷允䅁䅁䅕䅁䑁䅁䅷䅁䭁䉁䅯䅁䭁䅁䅅䅁䭁䅁䅕䅁䙁䅁䅁䅁䅁⬴䅖允䅁䅁䅅䅁䙁偁潙䥘䌯改⽁䍄䉁䅁䅁兂䅁䅁䅍䅄䅁䅁䅯杈䅁䅁䅯睕䅁䅁䅯兂䅁䅁䅕䅁䅁䕁煄唵䉁䅁䅁允䅁䅁䅕㉣剩堷⽷䕌䵁䅉䅅䅁䙁䅁䅁睁䵁䅁䅁权䅁䅁䅁权呂䅁䅁权䙁䅁䅁兂䅁䅁䅁乷決䅑䅅䅁䉁䅁䅁兂婁䙂余摌祉䅑杷允䅁䅁䅕䅁䑁䅁䅷䅁䭁䉁䅯䅁䭁䙁䅍䅁䭁䅁䅕䅁䙁䅁䅁䅁杄伲䅖允䅁䅁䅅䅁䙁䉁癳匳䝑呉䅰䍄䉁䅁䅁兂䅁䅁䅍䅄䅁䅁䅯杇䅁䅁䅯睕䅁䅁䅯兂䅁䅁䅕䅁䅁䝁剂欵䉁䅁䅁允䅁䅁䅕䑔䩥坑䙂く䵁䅉䅅䅁䙁䅁䅁睁䵁䅁䅁权敁䅁䅁权呂䅁䅁权䙁䅁䅁兂䅁䅁䅁䡯浲䅑䅅䅁䉁䅁䅁兂灁䥘䌯圹桧䅑杷允䅁䅁䅕䅁䑁䅁䅷䅁䭁䅁䅁䅁䭁䙁䅍䅁䭁䅁䅕䅁䙁䅁䅁䅁杁佃䅚允䅁䅁䅅䅁䙁䭁硲欰椱䑣䅊䍄䉁䅁䅁兂䅁䅁䅍䅄䅁䅁䅯杇䅁䅁䅯睕䅁䅁䅯兂䅁䅁䅕䅁䅁䍁汃唵䉁䅁䅁允䅁䅁䅕噈歰㥏倫問䵁䅉䅅䅁䙁䅁䅁睁䵁䅁䅁权晁䅁䅁权呂䅁䅁权䙁䅁䅁兂䅁䅁䅁䝯浺䅑䅅䅁䉁䅁䅁兂䭁㘱睎卐硯䅑杷允䅁䅁䅕䅁䑁䅁䅷䅁䭁䅁䅁䅁䭁䙁䅍䅁䭁䅁䅕䅁䙁䅁䅁䅁䅁伵䅖允䅁䅁䅅䅁䙁䉁䕫杖琴樰䅊䍄䉁䅁䅁兂䅁䅁䅍䅄䅁䅁䅯䅁䅁䅁䅯睕䅁䅁䅯兂䅁䅁䅕䅁䅁佁剄唵䉁䅁䅁允䅁䅁䅕䉯癯匳䝑き䵁䅉䅅䅁䙁䅁䅁睁䵁䅁䅁权䅁䅁䅁权呂䅁䅁权䙁䅁䅁兂䅁䅁䅁偷汘䅑䅅䅁䉁䅁䅁兂灁䥘䌯圹祧䅑杷允䅁䅁䅕䅁䑁䅁䅷䅁䭁䉁䄰䅁䭁䙁䅍䅁䭁䅁䅕䅁䙁䅁䅁䅁䅂⭣䅚允䅁䅁䅅䅁䙁偁湃歸㍳卹䄱䍄䉁䅁䅁兂䅁䅁䅍䅄䅁䅁䅯睈䅁䅁䅯睕䅁䅁䅯兂䅁䅁䅕䅁䅁䅁佄唵䉁䅁䅁允䅁䅁䅕杓䍷㑋坦䕍䵁䅉䅅䅁䙁䅁䅁睁䵁䅁䅁权䅁䅁䅁权呂䅁䅁权䙁䅁䅁兂䅁䅁䅁䡉洯䅑䅅䅁䉁䅁䅁兂⭄䠱灪癊穅䅑杷允䅁䅁䅕䅁䑁䅁䅷䅁䭁䉁䅷䅁䭁䅁䅅䅁䭁䅁䅕䅁䙁䅁䅁䅁䅃⭰䅖允䅁䅁䅅䅁䙁䥁䌯匹捨㥪⽉䍄䉁䅁䅁兂䅁䅁䅍䅄䅁䅁䅯䅈䅁䅁䅯睕䅁䅁䅯兂䅁䅁䅕䅁䅁䅁㍄唵䉁䅁䅁允䅁䅁䅕牘䩰䅄牊啌䵁䅉䅅䅁䙁䅁䅁睁䵁䅁䅁权晁䅁䅁权䉁䅁䅁权䙁䅁䅁兂䅁䅁䅁䑙浘䅑䅅䅁䉁䅁䅁兂䥂場啯歲桦睐杷允䅁䅁䅕䅁䑁䅁䅷䅁䭁䅁䅁䅁䭁䙁䅍䅁䭁䅁䅕䅁䙁䅁䅁䅁杁敖䅚允䅁䅁䅅䅁䙁䑁ね䡹⭡稳䅎䍄䉁䅁䅁兂䅁䅁䅍䅄䅁䅁䅯先䅁䅁䅯允䅁䅁䅯兂䅁䅁䅕䅁䅁䅁噁欵䉁䅁䅁允䅁䅁䅕㑈牘払敧吱䴸䅉䅅䅁䙁䅁䅁睁䵁䅁䅁权敁䅁䅁权䉁䅁䅁权䙁䅁䅁兂䅁䅁䅁䵯汶䅑䅅䅁䉁䅁䅁兂穁積積積呐睐杷允䅁䅁䅕䅁䑁䅁䅷䅁䭁䅁䅁䅁䭁䅁䅅䅁䭁䅁䅕䅁䙁䅁䅁䅁䅃佘䅚允䅁䅁䅅䅁䙁䱁敧敨剴乵⼴䍄䉁䅁䅁兂䅁䅁䅍䅄䅁䅁䅯先䅁䅁䅯允䅁䅁䅯兂䅁䅁䅕䅁䅁佁㙃唵䉁䅁䅁允䅁䅁䅕㘱睎児塲稰䴸䅉䅅䅁䙁䅁䅁睁䵁䅁䅁权䅁䅁䅁权呂䅁䅁权䙁䅁䅁兂䅁䅁䅁倴汮䅑䅅䅁䉁䅁䅁兂灁䥘䌯圹祧䅑杷允䅁䅁䅕䅁䑁䅁䅷䅁䭁䅁䅁䅁䭁䙁䅍䅁䭁䅁䅕䅁䙁䅁䅁䅁䅃甴䅖允䅁䅁䅅䅁䙁䉁䕫杖琴樰䅊䍄䉁䅁䅁兂䅁䅁䅍䅄䅁䅁䅯䅁䅁䅁䅯睕䅁䅁䅯兂䅁䅁䅕䅁䅁䭁䥂欵䉁䅁䅁允䅁䅁䅕潅䅐煹䙈き䵁䅉䅅䅁䙁䅁䅁睁䵁䅁䅁权捁䅁䅁权䉁䅁䅁权䙁䅁䅁兂䅁䅁䅁䱯汲䅑䅅䅁䉁䅁䅁兂偃癷潕䥘匯睐杷允䅁䅁䅕䅁䑁䅁䅷䅁䭁䉁䅯䅁䭁䙁䅍䅁䭁䅁䅕䅁䙁䅁䅁䅁杂甶䅖允䅁䅁䅅䅁䙁䵁ㅐ䙋偹橷䅬䍄䉁䅁䅁兂䅁䅁䅍䅄䅁䅁䅯䅁䅁䅁䅯睕䅁䅁䅯兂䅁䅁䅕䅁䅁䝁呁欵䉁䅁䅁允䅁䅁䅕䙅㕧䵴坩歍䵁䅉䅅䅁䙁䅁䅁睁䵁䅁䅁权䅁䅁䅁权呂䅁䅁权䙁䅁䅁兂䅁䅁䅁䝉浈䅑䅅䅁䉁䅁䅁兂煃搸乊瑙穁䅑杷允䅁䅁䅕䅁䑁䅁䅷䅁䭁䉁䄰䅁䭁䅁䅅䅁䭁䅁䅕䅁䙁䅁䅁䅁权低䅚允䅁䅁䅅䅁䙁䭁䠵場啯瑲⽣䍄䉁䅁䅁兂䅁䅁䅍䅄䅁䅁䅯睈䅁䅁䅯睕䅁䅁䅯兂䅁䅁䅕䅁䅁䵁敁欵䉁䅁䅁允䅁䅁䅕牒穢搯㑔䕍䵁䅉䅅䅁䙁䅁䅁睁䵁䅁䅁权䅁䅁䅁权呂䅁䅁权䙁䅁䅁兂䅁䅁䅁䉑浺䅑䅅䅁䉁䅁䅁兂療潅䅐杹穅䅑杷允䅁䅁䅕䅁䑁䅁䅷䅁䭁䅁䅁䅁䭁䙁䅍䅁䭁䅁䅕䅁䙁䅁䅁䅁杁⭙䅚允䅁䅁䅅䅁䙁䭁硲欰椱䐰䅎䍄䉁䅁䅁兂䅁䅁䅍䅄䅁䅁䅯杇䅁䅁䅯睕䅁䅁䅯兂䅁䅁䅕䅁䅁䵁婃唵䉁䅁䅁允䅁䅁䅕瑃橥䑣焳䕏䵁䅉䅅䅁䙁䅁䅁睁䵁䅁䅁权捁䅁䅁权䉁䅁䅁权䙁䅁䅁兂䅁䅁䅁䱑汈䅑䅅䅁䉁䅁䅁兂偃癷潕䥘匯睐杷允䅁䅁䅕䅁䑁䅁䅷䅁䭁䉁䅯䅁䭁䙁䅍䅁䭁䅁䅕䅁䙁䅁䅁䅁䅄效䅚允䅁䅁䅅䅁䙁䱁穢搯㑒呩䅰䍄䉁䅁䅁兂䅁䅁䅍䅄䅁䅁䅯䅁䅁䅁䅯睕䅁䅁䅯兂䅁䅁䅕䅁䅁䝁敁欵䉁䅁䅁允䅁䅁䅕硢䑋䵷䉯き䵁䅉䅅䅁䙁䅁䅁睁䵁䅁䅁权捁䅁䅁权䉁䅁䅁权䙁䅁䅁兂䅁䅁䅁䙷浔䅑䅅䅁䉁䅁䅁兂㉄䙋偹癷奘睐杷允䅁䅁䅕䅁䑁䅁䅷䅁䭁䅁䅁䅁䭁䙁䅍䅁䭁䅁䅕䅁䙁䅁䅁䅁权敌䅚允䅁䅁䅅䅁䙁䍁礲敮渫橨䅎䍄䉁䅁䅁兂䅁䅁䅍䅄䅁䅁䅯杇䅁䅁䅯允䅁䅁䅯兂䅁䅁䅕䅁䅁䝁扃唵䉁䅁䅁允䅁䅁䅕䅁䅁䅁䅁䐴䴸䅉䅅䅁䙁䅁䅁睁䵁䅁䅁权䅁䅁䅁权呂䅁䅁权䙁䅁䅁兂䅁䅁䅁䥑浈䅑䅅䅁䉁䅁䅁兂⭄䠱灪癊穅䅑杷允䅁䅁䅕䅁䑁䅁䅷䅁䭁䅁䅁䅁䭁䙁䅍䅁䭁䅁䅕䅁䙁䅁䅁䅁䅂⭭䅖允䅁䅁䅅䅁䙁乁橥䑣䬰稹䅂䍄䉁䅁䅁兂䅁䅁䅍䅄䅁䅁䅯睈䅁䅁䅯允䅁䅁䅯兂䅁䅁䅕䅁䅁䵁煁欵䉁䅁䅁允䅁䅁䅕体㙆䭆䠵吴䴸䅉䅅䅁䙁䅁䅁睁䵁䅁䅁权䅁䅁䅁权呂䅁䅁权䙁䅁䅁兂䅁䅁䅁䱯汘䅑䅅䅁䉁䅁䅁兂㙃兓䍷祋祣䅑杷允䅁䅁䅕䅁䑁䅁䅷䅁䭁䅁䅁䅁䭁䙁䅍䅁䭁䅁䅕䅁䙁䅁䅁䅁杂畉䅚允䅁䅁䅅䅁䙁佁兘瑉㕶橐䅎䍄䉁䅁䅁兂䅁䅁䅍䅄䅁䅁䅯杇䅁䅁䅯允䅁䅁䅯兂䅁䅁䅕䅁䅁䕁桄唵䉁䅁䅁允䅁䅁䅕椹捨㡪ㅌ䐴䴸䅉䅅䅁䙁䅁䅁睁䵁䅁䅁权捁䅁䅁权呂䅁䅁权䙁䅁䅁兂䅁䅁䅁䕧浈䅑䅅䅁䉁䅁䅁兂塁挲㌷㙕畍䅑杷允䅁䅁䅕䅁䑁䅁䅷䅁䭁䅁䅁䅁䭁䅁䅅䅁䭁䅁䅕䅁䙁䅁䅁䅁䅂當䅖允䅁䅁䅅䅁䙁䑁䬰㘱睎摐⽯䍄䉁䅁䅁兂䅁䅁䅍䅄䅁䅁䅯䅁䅁䅁䅯允䅁䅁䅯兂䅁䅁䅕䅁䅁䝁晄唵䉁䅁䅁允䅁䅁䅕場啯歲桦樲䴸䅉䅅䅁䙁䅁䅁睁䵁䅁䅁权䅁䅁䅁权呂䅁䅁权䙁䅁䅁兂䅁䅁䅁临汄䅑䅅䅁䉁䅁䅁兂权楇搯䅊穙䅑杷允䅁䅁䅕䅁䑁䅁䅷䅁䭁䉁䅯䅁䭁䅁䅅䅁䭁䅁䅕䅁䙁䅁䅁䅁䅂敚䅚允䅁䅁䅅䅁䙁䭁睒児塲⭯⽧䍄䉁䅁䅁兂䅁䅁䅍䅄䅁䅁䅯先䅁䅁䅯允䅁䅁䅯兂䅁䅁䅕䅁䅁䭁煂欵䉁䅁䅁允䅁䅁䅕歲桦桥畓稱䴸䅉䅅䅁䙁䅁䅁睁䵁䅁䅁权敁䅁䅁权䉁䅁䅁权䙁䅁䅁兂䅁䅁䅁䱯汘䅑䅅䅁䉁䅁䅁兂穁積積積呐睐杷允䅁䅁䅕䅁䑁䅁䅷䅁䭁䉁䄸䅁䭁䅁䅅䅁䭁䅁䅕䅁䙁䅁䅁䅁杁佒䅚允䅁䅁䅅䅁䙁䭁睒児塲⭯⽁䍄䉁䅁䅁兂䅁䅁䅍䅄䅁䅁䅯䅁䅁䅁䅯允䅁䅁䅯兂䅁䅁䅕䅁䅁佁䩄唵䉁䅁䅁允䅁䅁䅕児塲㍯㥁樲䴸䅉䅅䅁䙁䅁䅁睁䵁䅁䅁权䅁䅁䅁权呂䅁䅁权䙁䅁䅁兂䅁䅁䅁䕙浺䅑䅅䅁䉁䅁䅁兂十㡧䭄捯穕䅑杷允䅁䅁䅕䅁䑁䅁䅷䅁䭁䉁䄰䅁䭁䙁䅍䅁䭁䅁䅕䅁䙁䅁䅁䅁杄⬯䅖允䅁䅁䅅䅁䙁䝁汄䌰扌匫䄱䍄䉁䅁䅁兂䅁䅁䅍䅄䅁䅁䅯睈䅁䅁䅯睕䅁䅁䅯兂䅁䅁䅕䅁䅁䵁楂欵䉁䅁䅁允䅁䅁䅕匰扌堫䬴啍䵁䅉䅅䅁䙁䅁䅁睁䵁䅁䅁权䅁䅁䅁权䉁䅁䅁权䙁䅁䅁兂䅁䅁䅁䕁浘䅑䅅䅁䉁䅁䅁兂㑃潈牘払敪睐杷允䅁䅁䅕䅁䑁䅁䅷䅁䭁䅁䅁䅁䭁䙁䅍䅁䭁䅁䅕䅁䙁䅁䅁䅁杁⭗䅚允䅁䅁䅅䅁䙁䭁硲欰椱䐰䅎䍄䉁䅁䅁兂䅁䅁䅍䅄䅁䅁䅯䅁䅁䅁䅯睕䅁䅁䅯兂䅁䅁䅕䅁䅁䝁㉂欵䉁䅁䅁允䅁䅁䅕佖汏㡭䅑䕎䵁䅉䅅䅁䙁䅁䅁睁䵁䅁䅁权䅁䅁䅁权呂䅁䅁权䙁䅁䅁兂䅁䅁䅁䩁氯䅑䅅䅁䉁䅁䅁兂塄㍯㥁癃督䅑杷允䅁䅁䅕䅁䑁䅁䅷䅁䭁䅁䅁䅁䭁䙁䅍䅁䭁䅁䅕䅁䙁䅁䅁䅁杁敳䅖允䅁䅁䅅䅁䙁䱁䩰䅄牉穊䅊䍄䉁䅁䅁兂䅁䅁䅍䅄䅁䅁䅯杈䅁䅁䅯允䅁䅁䅯兂䅁䅁䅕䅁䅁䝁桂欵䉁䅁䅁允䅁䅁䅕䅁䅁䅁䅁䐰䴸䅉䅅䅁䙁䅁䅁睁䵁䅁䅁权慁䅁䅁权呂䅁䅁权䙁䅁䅁兂䅁䅁䅁䉷浔䅑䅅䅁䉁䅁䅁兂䝁婧䑖ど㙷䅑杷允䅁䅁䅕䅁䑁䅁䅷䅁䭁䅁䅁䅁䭁䙁䅍䅁䭁䅁䅕䅁䙁䅁䅁䅁杄佧䅚允䅁䅁䅅䅁䙁偁唷佥浫吸䅎䍄䉁䅁䅁兂䅁䅁䅍䅄䅁䅁䅯杇䅁䅁䅯睕䅁䅁䅯兂䅁䅁䅕䅁䅁䝁楄唵䉁䅁䅁允䅁䅁䅕⽷潕䥘椯問䵁䅉䅅䅁䙁䅁䅁睁䵁䅁䅁权䅁䅁䅁权呂䅁䅁权䙁䅁䅁兂䅁䅁䅁䩑汦䅑䅅䅁䉁䅁䅁兂㡃䩤奍䡂睙䅑杷允䅁䅁䅕䅁䑁䅁䅷䅁䭁䅁䅁䅁䭁䙁䅍䅁䭁䅁䅕䅁䙁䅁䅁䅁䅂⭁䅚允䅁䅁䅅䅁䙁䭁硲欰椱䑣䅊䍄䉁䅁䅁兂䅁䅁䅍䅄䅁䅁䅯䅁䅁䅁䅯睕䅁䅁䅯兂䅁䅁䅕䅁䅁䵁䉃欵䉁䅁䅁允䅁䅁䅕琯㑒匶硢き䵁䅉䅅䅁䙁䅁䅁睁䵁䅁䅁权慁䅁䅁权呂䅁䅁权䙁䅁䅁兂䅁䅁䅁䱉汮䅑䅅䅁䉁䅁䅁兂⽁噎㘶敓㕷䅑杷允䅁䅁䅕䅁䑁䅁䅷䅁䭁䅁䅁䅁䭁䅁䅅䅁䭁䅁䅕䅁䙁䅁䅁䅁䅃⬲䅖允䅁䅁䅅䅁䙁佁㙆䭆䠵搴⽯䍄䉁䅁䅁兂䅁䅁䅍䅄䅁䅁䅯睈䅁䅁䅯睕䅁䅁䅯兂䅁䅁䅕䅁䅁䵁䉃欵䉁䅁䅁允䅁䅁䅕余兘瑉㕶䕍䵁䅉䅅䅁䙁䅁䅁睁䵁䅁䅁权䅁䅁䅁权呂䅁䅁权䙁䅁䅁兂䅁䅁䅁䭯汦䅑䅅䅁䉁䅁䅁兂塄㍯㥁湃硣䅑杷允䅁䅁䅕䅁䑁䅁䅷䅁䭁䉁䅯䅁䭁䅁䅅䅁䭁䅁䅕䅁䙁䅁䅁䅁杄申䅖允䅁䅁䅅䅁䙁偁潙䥘䌯改⽁䍄䉁䅁䅁兂䅁䅁䅍䅄䅁䅁䅯杈䅁䅁䅯允䅁䅁䅯兂䅁䅁䅕䅁䅁䭁晄唵䉁䅁䅁允䅁䅁䅕積積積積稰䴸䅉䅅䅁䙁䅁䅁睁䵁䅁䅁权敁䅁䅁权䉁䅁䅁权䙁䅁䅁兂䅁䅁䅁偉汌䅑䅅䅁䉁䅁䅁兂穁積積積呐睐杷允䅁䅁䅕䅁䑁䅁䅷䅁䭁䉁䄴䅁䭁䙁䅍䅁䭁䅁䅕䅁䙁䅁䅁䅁䅄教䅚允䅁䅁䅅䅁䙁䩁瑈䑦ㄸ楘䅊䍄䉁䅁䅁兂䅁䅁䅍䅄䅁䅁䅯䅁䅁䅁䅯允䅁䅁䅯兂䅁䅁䅕䅁䅁䭁㙃唵䉁䅁䅁允䅁䅁䅕児塲㍯㥁樲䴸䅉䅅䅁䙁䅁䅁睁䵁䅁䅁权䅁䅁䅁权呂䅁䅁权䙁䅁䅁兂䅁䅁䅁䡯浦䅑䅅䅁䉁䅁䅁兂啂㘴扗䅸ぁ䅑杷允䅁䅁䅕䅁䑁䅁䅷䅁䭁䉁䅷䅁䭁䙁䅍䅁䭁䅁䅕䅁䙁䅁䅁䅁䅂佺䅖允䅁䅁䅅䅁䙁䥁牘払敧卨䄵䍄䉁䅁䅁兂䅁䅁䅍䅄䅁䅁䅯䅁䅁䅁䅯睕䅁䅁䅯兂䅁䅁䅕䅁䅁䭁㕂欵䉁䅁䅁允䅁䅁䅕佖汏㡭䅑䕎䵁䅉䅅䅁䙁䅁䅁睁䵁䅁䅁权敁䅁䅁权䉁䅁䅁权䙁䅁䅁兂䅁䅁䅁䘴浶䅑䅅䅁䉁䅁䅁兂䅁䅁䅁䅁兄睐杷允䅁䅁䅕䅁䑁䅁䅷䅁䭁䉁䄴䅁䭁䙁䅍䅁䭁䅁䅕䅁䙁䅁䅁䅁杁畉䅚允䅁䅁䅅䅁䙁䉁䕫杖琴楣䅬䍄䉁䅁䅁兂䅁䅁䅍䅄䅁䅁䅯睈䅁䅁䅯允䅁䅁䅯兂䅁䅁䅕䅁䅁䝁㝂欵䉁䅁䅁允䅁䅁䅕牕敧敨剴䐴䴸䅉䅅䅁䙁䅁䅁睁䵁䅁䅁权䅁䅁䅁权呂䅁䅁权䙁䅁䅁兂䅁䅁䅁乧汪䅑䅅䅁䉁䅁䅁兂权楇搯䅊穙䅑杷允䅁䅁䅕䅁䑁䅁䅷䅁䭁䅁䅁䅁䭁䅁䅅䅁䭁䅁䅕䅁䙁䅁䅁䅁杄⭙䅚允䅁䅁䅅䅁䙁䱁敧敨剴乵⼴䍄䉁䅁䅁兂䅁䅁䅍䅄䅁䅁䅯杇䅁䅁䅯睕䅁䅁䅯兂䅁䅁䅕䅁䅁䕁硃唵䉁䅁䅁允䅁䅁䅕穐敖歵獮問䵁䅉䅅䅁䙁䅁䅁睁䵁䅁䅁权䅁䅁䅁权呂䅁䅁权䙁䅁䅁兂䅁䅁䅁䉁浺䅑䅅䅁䉁䅁䅁兂療潅䅐杹穅䅑杷允䅁䅁䅕䅁䑁䅁䅷䅁䭁䅁䅁䅁䭁䙁䅍䅁䭁䅁䅕䅁䙁䅁䅁䅁杂敧䅚允䅁䅁䅅䅁䙁偁唷佥浫吸䅎䍄䉁䅁䅁兂䅁䅁䅍䅄䅁䅁䅯先䅁䅁䅯允䅁䅁䅯兂䅁䅁䅕䅁䅁䕁慃唵䉁䅁䅁允䅁䅁䅕㘱睎児塲稰䴸䅉䅅䅁䙁䅁䅁睁䵁䅁䅁权䅁䅁䅁权呂䅁䅁权䙁䅁䅁兂䅁䅁䅁䥷浄䅑䅅䅁䉁䅁䅁兂⭄䠱灪癊穅䅑杷允䅁䅁䅕䅁䑁䅁䅷䅁䭁䉁䄰䅁䭁䙁䅍䅁䭁䅁䅕䅁䙁䅁䅁䅁杁⭭䅖允䅁䅁䅅䅁䙁䱁へ硫䕧楖䄱䍄䉁䅁䅁兂䅁䅁䅍䅄䅁䅁䅯睈䅁䅁䅯允䅁䅁䅯兂䅁䅁䅕䅁䅁䅁䅄唵䉁䅁䅁允䅁䅁䅕䉵䘶ㄶ㑇樳䴸䅉䅅䅁䙁䅁䅁睁䵁䅁䅁权捁䅁䅁权呂䅁䅁权䙁䅁䅁兂䅁䅁䅁䱉汮䅑䅅䅁䉁䅁䅁兂㍂灶愸硌田䅑杷允䅁䅁䅕䅁䑁䅁䅷䅁䭁䉁䄴䅁䭁䙁䅍䅁䭁䅁䅕䅁䙁䅁䅁䅁䅁畕䅚允䅁䅁䅅䅁䙁佁㠵穐敖楏䅒䍄䉁䅁䅁兂䅁䅁䅍䅄䅁䅁䅯䅁䅁䅁䅯睕䅁䅁䅯兂䅁䅁䅕䅁䅁佁䵂欵䉁䅁䅁允䅁䅁䅕潅䅐煹䙈き䵁䅉䅅䅁䙁䅁䅁睁䵁䅁䅁权䅁䅁䅁权呂䅁䅁权䙁䅁䅁兂䅁䅁䅁倴汲䅑䅅䅁䉁䅁䅁兂灁䥘䌯圹祧䅑杷允䅁䅁䅕䅁䑁䅁䅷䅁䭁䉁䅷䅁䭁䙁䅍䅁䭁䅁䅕䅁䙁䅁䅁䅁䅂佈䅚允䅁䅁䅅䅁䙁䱁摋㘷䝦祃䄵䍄䉁䅁䅁兂䅁䅁䅍䅄䅁䅁䅯䅈䅁䅁䅯睕䅁䅁䅯兂䅁䅁䅕䅁䅁䍁潄唵䉁䅁䅁允䅁䅁䅕桙奂扏䥒歌䵁䅉䅅䅁䙁䅁䅁睁䵁䅁䅁权䅁䅁䅁权呂䅁䅁权䙁䅁䅁兂䅁䅁䅁䅷浐䅑䅅䅁䉁䅁䅁兂煃搸乊湙祁䅑杷允䅁䅁䅕䅁䑁䅁䅷䅁䭁䅁䅁䅁䭁䅁䅅䅁䭁䅁䅕䅁䙁䅁䅁䅁杁敍䅚允䅁䅁䅅䅁䙁䱁敧敨剴乵⼴䍄䉁䅁䅁兂䅁䅁䅍䅄䅁䅁䅯睈䅁䅁䅯允䅁䅁䅯兂䅁䅁䅕䅁䅁䍁捁欵䉁䅁䅁允䅁䅁䅕椹捨㡪ㅌ䐴䴸䅉䅅䅁䙁䅁䅁睁䵁䅁䅁权䅁䅁䅁权呂䅁䅁权䙁䅁䅁兂䅁䅁䅁䥯浄䅑䅅䅁䉁䅁䅁兂⭄䠱灪癊穅䅑杷允䅁䅁䅕䅁䑁䅁䅷䅁䭁䉁䄸䅁䭁䙁䅍䅁䭁䅁䅕䅁䙁䅁䅁䅁䅄畦䅚允䅁䅁䅅䅁䙁䝁汄䌰扌含䅂䍄䉁䅁䅁兂䅁䅁䅍䅄䅁䅁䅯䅁䅁䅁䅯睕䅁䅁䅯兂䅁䅁䅕䅁䅁䝁慂欵䉁䅁䅁允䅁䅁䅕癱午坔兌き䵁䅉䅅䅁䙁䅁䅁睁䵁䅁䅁权䅁䅁䅁权呂䅁䅁权䙁䅁䅁兂䅁䅁䅁䙯浺䅑䅅䅁䉁䅁䅁兂煃搸乊瑙穁䅑杷允䅁䅁䅕䅁䑁䅁䅷䅁䭁䅁䅁䅁䭁䙁䅍䅁䭁䅁䅕䅁䙁䅁䅁䅁权畆䅚允䅁䅁䅅䅁䙁䝁匸㡧䭄呁䅎䍄䉁䅁䅁兂䅁䅁䅍䅄䅁䅁䅯先䅁䅁䅯允䅁䅁䅯兂䅁䅁䅕䅁䅁䥁䱁欵䉁䅁䅁允䅁䅁䅕㑈牘払敧吱䴸䅉䅅䅁䙁䅁䅁睁䵁䅁䅁权敁䅁䅁权呂䅁䅁权䙁䅁䅁兂䅁䅁䅁䉧浢䅑䅅䅁䉁䅁䅁兂婁䙂余塌灉䅑杷允䅁䅁䅕䅁䑁䅁䅷䅁䭁䅁䅁䅁䭁䙁䅍䅁䭁䅁䅕䅁䙁䅁䅁䅁杁佣䅚允䅁䅁䅅䅁䙁䙁橔婰䕶䐴䅎䍄䉁䅁䅁兂䅁䅁䅍䅄䅁䅁䅯䅁䅁䅁䅯睕䅁䅁䅯兂䅁䅁䅕䅁䅁佁坂欵䉁䅁䅁允䅁䅁䅕扏䥔牤昷き䵁䅉䅅䅁䙁䅁䅁睁䵁䅁䅁权捁䅁䅁权䉁䅁䅁权䙁䅁䅁兂䅁䅁䅁乁汔䅑䅅䅁䉁䅁䅁兂穁積積積呐睐杷允䅁䅁䅕䅁䑁䅁䅷䅁䭁䉁䄴䅁䭁䙁䅍䅁䭁䅁䅕䅁䙁䅁䅁䅁䅃敳䅖允䅁䅁䅅䅁䙁䱁穢搯㑒卡䅸䍄䉁䅁䅁兂䅁䅁䅍䅄䅁䅁䅯杈䅁䅁䅯睕䅁䅁䅯兂䅁䅁䅕䅁䅁䥁煂欵䉁䅁䅁允䅁䅁䅕匰扌堫焵啉䵁䅉䅅䅁䙁䅁䅁睁䵁䅁䅁权䅁䅁䅁权呂䅁䅁权䙁䅁䅁兂䅁䅁䅁䕯浮䅑䅅䅁䉁䅁䅁兂十㡧䭄捯穕䅑杷允䅁䅁䅕䅁䑁䅁䅷䅁䭁䉁䄸䅁䭁䅁䅅䅁䭁䅁䅕䅁䙁䅁䅁䅁杂⭹䅖允䅁䅁䅅䅁䙁䭁睒児塲⭯⽁䍄䉁䅁䅁兂䅁䅁䅍䅄䅁䅁䅯䅁䅁䅁䅯允䅁䅁䅯兂䅁䅁䅕䅁䅁䝁牃唵䉁䅁䅁允䅁䅁䅕灭婭婭婭吲䴸䅉䅅䅁䙁䅁䅁睁䵁䅁䅁权䅁䅁䅁权呂䅁䅁权䙁䅁䅁兂䅁䅁䅁䝧浲䅑䅅䅁䉁䅁䅁兂啂㘴扗佸穁䅑杷允䅁䅁䅕䅁䑁䅁䅷䅁䭁䅁䅁䅁䭁䙁䅍䅁䭁䅁䅕䅁䙁䅁䅁䅁杂佧䅚允䅁䅁䅅䅁䙁偁唷佥浫吸䅎䍄䉁䅁䅁兂䅁䅁䅍䅄䅁䅁䅯先䅁䅁䅯睕䅁䅁䅯兂䅁䅁䅕䅁䅁䅁䥄唵䉁䅁䅁允䅁䅁䅕䑔䩥坑汄啌䵁䅉䅅䅁䙁䅁䅁睁䵁䅁䅁权敁䅁䅁权呂䅁䅁权䙁䅁䅁兂䅁䅁䅁偷氯䅑䅅䅁䉁䅁䅁兂䅁䅁䅁䅁煁䅑杷允䅁䅁䅕䅁䑁䅁䅷䅁䭁䅁䅁䅁䭁䙁䅍䅁䭁䅁䅕䅁䙁䅁䅁䅁杂⭸䅖允䅁䅁䅅䅁䙁䝁渳㘫确樸䅊䍄䉁䅁䅁兂䅁䅁䅍䅄䅁䅁䅯䅁䅁䅁䅯睕䅁䅁䅯兂䅁䅁䅕䅁䅁䵁瑄唵䉁䅁䅁允䅁䅁䅕積積積呏歍䵁䅉䅅䅁䙁䅁䅁睁䵁䅁䅁权慁䅁䅁权呂䅁䅁权䙁䅁䅁兂䅁䅁䅁䄴洳䅑䅅䅁䉁䅁䅁兂䝁婧䑖ど㙷䅑杷允䅁䅁䅕䅁䑁䅁䅷䅁䭁䅁䅁䅁䭁䙁䅍䅁䭁䅁䅕䅁䙁䅁䅁䅁杁敦䅚允䅁䅁䅅䅁䙁偁唷佥浫吸䅎䍄䉁䅁䅁兂䅁䅁䅍䅄䅁䅁䅯先䅁䅁䅯允䅁䅁䅯兂䅁䅁䅕䅁䅁佁牂欵䉁䅁䅁允䅁䅁䅕歲桦桥畓稱䴸䅉䅅䅁䙁䅁䅁睁䵁䅁䅁权䅁䅁䅁权呂䅁䅁权䙁䅁䅁兂䅁䅁䅁佷氷䅑䅅䅁䉁䅁䅁兂穁積積㕍祍䅑杷允䅁䅁䅕䅁䑁䅁䅷䅁䭁䅁䅁䅁䭁䙁䅍䅁䭁䅁䅕䅁䙁䅁䅁䅁䅁佧䅚允䅁䅁䅅䅁䙁偁唷佥浫吸䅎䍄䉁䅁䅁兂䅁䅁䅍䅄䅁䅁䅯睈䅁䅁䅯睕䅁䅁䅯兂䅁䅁䅕䅁䅁䍁㥂欵䉁䅁䅁允䅁䅁䅕牡へ硫歧啍䵁䅉䅅䅁䙁䅁䅁睁䵁䅁䅁权䅁䅁䅁权呂䅁䅁权䙁䅁䅁兂䅁䅁䅁䍉浲䅑䅅䅁䉁䅁䅁兂汄䌰扌含稴䅑杷允䅁䅁䅕䅁䑁䅁䅷䅁䭁䅁䅁䅁䭁䙁䅍䅁䭁䅁䅕䅁䙁䅁䅁䅁杁畢䅚允䅁䅁䅅䅁䙁䙁橔婰䕶䐴䅎䍄䉁䅁䅁兂䅁䅁䅍䅄䅁䅁䅯䅁䅁䅁䅯睕䅁䅁䅯兂䅁䅁䅕䅁䅁䅁ㅂ欵䉁䅁䅁允䅁䅁䅕佖汏㡭䅑䕎䵁䅉䅅䅁䙁䅁䅁睁䵁䅁䅁权晁䅁䅁权呂䅁䅁权䙁䅁䅁兂䅁䅁䅁乯汮䅑䅅䅁䉁䅁䅁兂扁㥌欰畂睅䅑杷允䅁䅁䅕䅁䑁䅁䅷䅁䭁䅁䅁䅁䭁䙁䅍䅁䭁䅁䅕䅁䙁䅁䅁䅁杁伱䅖允䅁䅁䅅䅁䙁䭁慁㥌欰橂䅎䍄䉁䅁䅁兂䅁䅁䅍䅄䅁䅁䅯䅈䅁䅁䅯允䅁䅁䅯兂䅁䅁䅕䅁䅁䵁⽁欵䉁䅁䅁允䅁䅁䅕椹捨㡪ㅌ䐲䴸䅉䅅䅁䙁䅁䅁睁䵁䅁䅁权捁䅁䅁权䉁䅁䅁权䙁䅁䅁兂䅁䅁䅁䥑浌䅑䅅䅁䉁䅁䅁兂㉄䙋偹癷奘睐杷允䅁䅁䅕䅁䑁䅁䅷䅁䭁䉁䄰䅁䭁䙁䅍䅁䭁䅁䅕䅁䙁䅁䅁䅁䅂畘䅚允䅁䅁䅅䅁䙁䡁⼰噎㘶卓䄵䍄䉁䅁䅁兂䅁䅁䅍䅄䅁䅁䅯䅁䅁䅁䅯睕䅁䅁䅯兂䅁䅁䅕䅁䅁䥁佂欵䉁䅁䅁允䅁䅁䅕潅䅐煹䙈き䵁䅉䅅䅁䙁䅁䅁睁䵁䅁䅁权捁䅁䅁权呂䅁䅁权䙁䅁䅁兂䅁䅁䅁䝧浄䅑䅅䅁䉁䅁䅁兂楃扒穢刯畑䅑杷允䅁䅁䅕䅁䑁䅁䅷䅁䭁䉁䄴䅁䭁䅁䅅䅁䭁䅁䅕䅁䙁䅁䅁䅁杂⬴䅖允䅁䅁䅅䅁䙁䑁積積積㥍⽍䍄䉁䅁䅁兂䅁䅁䅍䅄䅁䅁䅯杇䅁䅁䅯睕䅁䅁䅯兂䅁䅁䅕䅁䅁䕁杁欵䉁䅁䅁允䅁䅁䅕癴㥐䠱䩩歏䵁䅉䅅䅁䙁䅁䅁睁䵁䅁䅁权捁䅁䅁权呂䅁䅁权䙁䅁䅁兂䅁䅁䅁䕉浢䅑䅅䅁䉁䅁䅁兂療潅䅐浹畅䅑杷允䅁䅁䅕䅁䑁䅁䅷䅁䭁䉁䄰䅁䭁䅁䅅䅁䭁䅁䅕䅁䙁䅁䅁䅁杂位䅚允䅁䅁䅅䅁䙁䭁䠵場啯瑲⽣䍄䉁䅁䅁兂䅁䅁䅍䅄䅁䅁䅯䅁䅁䅁䅯睕䅁䅁䅯兂䅁䅁䅕䅁䅁䭁㝂欵䉁䅁䅁允䅁䅁䅕佖汏㡭䅑䕎䵁䅉䅅䅁䙁䅁䅁睁䵁䅁䅁权䅁䅁䅁权呂䅁䅁权䙁䅁䅁兂䅁䅁䅁䡙洳䅑䅅䅁䉁䅁䅁兂⭄䠱灪癊穅䅑杷允䅁䅁䅕䅁䑁䅁䅷䅁䭁䉁䅷䅁䭁䙁䅍䅁䭁䅁䅕䅁䙁䅁䅁䅁䅁佮䅖允䅁䅁䅅䅁䙁䵁䭈啯㉗祍䄱䍄䉁䅁䅁兂䅁䅁䅍䅄䅁䅁䅯先䅁䅁䅯允䅁䅁䅯兂䅁䅁䅕䅁䅁䥁乄唵䉁䅁䅁允䅁䅁䅕㘱睎児塲稰䴸䅉䅅䅁䙁䅁䅁睁䵁䅁䅁权捁䅁䅁权呂䅁䅁权䙁䅁䅁兂䅁䅁䅁䝁洯䅑䅅䅁䉁䅁䅁兂穂䩡瑈偦琸䅑杷允䅁䅁䅕䅁䑁䅁䅷䅁䭁䉁䄸䅁䭁䙁䅍䅁䭁䅁䅕䅁䙁䅁䅁䅁䅃畁䅚允䅁䅁䅅䅁䙁䥁䅐煹䙆橬䅂䍄䉁䅁䅁兂䅁䅁䅍䅄䅁䅁䅯杈䅁䅁䅯允䅁䅁䅯兂䅁䅁䅕䅁䅁䅁偄唵䉁䅁䅁允䅁䅁䅕積積積積稰䴸䅉䅅䅁䙁䅁䅁睁䵁䅁䅁权䅁䅁䅁权呂䅁䅁权䙁䅁䅁兂䅁䅁䅁䠴洯䅑䅅䅁䉁䅁䅁兂⭄䠱灪癊穅䅑杷允䅁䅁䅕䅁䑁䅁䅷䅁䭁䉁䅷䅁䭁䅁䅅䅁䭁䅁䅕䅁䙁䅁䅁䅁䅁佲䅖允䅁䅁䅅䅁䙁䥁䌯匹捨㥪⽉䍄䉁䅁䅁兂䅁䅁䅍䅄䅁䅁䅯䅁䅁䅁䅯睕䅁䅁䅯兂䅁䅁䅕䅁䅁佁奄唵䉁䅁䅁允䅁䅁䅕䉯癯匳䝑き䵁䅉䅅䅁䙁䅁䅁睁䵁䅁䅁权晁䅁䅁权呂䅁䅁权䙁䅁䅁兂䅁䅁䅁䑑洯䅑䅅䅁䉁䅁䅁兂㍁啩杆吵硁䅑杷允䅁䅁䅕䅁䑁䅁䅷䅁䭁䉁䄰䅁䭁䙁䅍䅁䭁䅁䅕䅁䙁䅁䅁䅁权敚䅚允䅁䅁䅅䅁䙁䡁⼰噎㘶卓䄵䍄䉁䅁䅁兂䅁䅁䅍䅄䅁䅁䅯䅁䅁䅁䅯允䅁䅁䅯兂䅁䅁䅕䅁䅁佁橄唵䉁䅁䅁允䅁䅁䅕場啯歲桦樲䴸䅉䅅䅁䙁䅁䅁睁䵁䅁䅁权䅁䅁䅁权䉁䅁䅁权䙁䅁䅁兂䅁䅁䅁佯汔䅑䅅䅁䉁䅁䅁兂桄桥畓⭒慈睐杷允䅁䅁䅕䅁䑁䅁䅷䅁䭁䉁䄸䅁䭁䙁䅍䅁䭁䅁䅕䅁䙁䅁䅁䅁杄敋䅚允䅁䅁䅅䅁䙁䱁穢搯㑒呃䅆䍄䉁䅁䅁兂䅁䅁䅍䅄䅁䅁䅯䅁䅁䅁䅯睕䅁䅁䅯兂䅁䅁䅕䅁䅁䅁摂欵䉁䅁䅁允䅁䅁䅕癱午坔兌き䵁䅉䅅䅁䙁䅁䅁睁䵁䅁䅁权摁䅁䅁权呂䅁䅁权䙁䅁䅁兂䅁䅁䅁䄴浪䅑䅅䅁䉁䅁䅁兂奃桢䑋䕷畯䅑杷允䅁䅁䅕䅁䑁䅁䅷䅁䭁䉁䄰䅁䭁䙁䅍䅁䭁䅁䅕䅁䙁䅁䅁䅁杄畆䅚允䅁䅁䅅䅁䙁䅁塲㍯㥁楹䄵䍄䉁䅁䅁兂䅁䅁䅍䅄䅁䅁䅯䅁䅁䅁䅯睕䅁䅁䅯兂䅁䅁䅕䅁䅁䅁䍄唵䉁䅁䅁允䅁䅁䅕䘫橐婰䕵歍䵁䅉䅅䅁䙁䅁䅁睁䵁䅁䅁权捁䅁䅁权呂䅁䅁权䙁䅁䅁兂䅁䅁䅁䕑浶䅑䅅䅁䉁䅁䅁兂療潅䅐浹畅䅑杷允䅁䅁䅕䅁䑁䅁䅷䅁䭁䉁䄸䅁䭁䙁䅍䅁䭁䅁䅕䅁䙁䅁䅁䅁杁敤䅚允䅁䅁䅅䅁䙁䝁㡱䩤奍䑊䅆䍄䉁䅁䅁兂䅁䅁䅍䅄䅁䅁䅯䅁䅁䅁䅯睕䅁䅁䅯兂䅁䅁䅕䅁䅁䵁桂欵䉁䅁䅁允䅁䅁䅕癱午坔兌き䵁䅉䅅䅁䙁䅁䅁睁䵁䅁䅁权䅁䅁䅁权呂䅁䅁权䙁䅁䅁兂䅁䅁䅁䑁浈䅑䅅䅁䉁䅁䅁兂瑁灳瘳㑰穙䅑杷允䅁䅁䅕䅁䑁䅁䅷䅁䭁䉁䅷䅁䭁䙁䅍䅁䭁䅁䅕䅁䙁䅁䅁䅁杄敬䅖允䅁䅁䅅䅁䙁偁㥔䠱灪楰䅸䍄䉁䅁䅁兂䅁䅁䅍䅄䅁䅁䅯杈䅁䅁䅯允䅁䅁䅯兂䅁䅁䅕䅁䅁䍁摄唵䉁䅁䅁允䅁䅁䅕積積積積稰䴸䅉䅅䅁䙁䅁䅁睁䵁䅁䅁权䅁䅁䅁权呂䅁䅁权䙁䅁䅁兂䅁䅁䅁䑑浢䅑䅅䅁䉁䅁䅁兂瑁灳瘳㑰穙䅑杷允䅁䅁䅕䅁䑁䅁䅷䅁䭁䉁䅷䅁䭁䙁䅍䅁䭁䅁䅕䅁䙁䅁䅁䅁䅁敵䅖允䅁䅁䅅䅁䙁䡁⭥确癯午䄵䍄䉁䅁䅁兂䅁䅁䅍䅄䅁䅁䅯䅁䅁䅁䅯睕䅁䅁䅯兂䅁䅁䅕䅁䅁䝁㕂欵䉁䅁䅁允䅁䅁䅕佖汏㡭䅑䕎䵁䅉䅅䅁䙁䅁䅁睁䵁䅁䅁权捁䅁䅁权䉁䅁䅁权䙁䅁䅁兂䅁䅁䅁䔴浈䅑䅅䅁䉁䅁䅁兂㉄䙋偹癷奘睐杷允䅁䅁䅕䅁䑁䅁䅷䅁䭁䉁䄸䅁䭁䅁䅅䅁䭁䅁䅕䅁䙁䅁䅁䅁权佁䅚允䅁䅁䅅䅁䙁䅁䅁䅁䅁佁⽁䍄䉁䅁䅁兂䅁䅁䅍䅄䅁䅁䅯䅁䅁䅁䅯睕䅁䅁䅯兂䅁䅁䅕䅁䅁䵁婄唵䉁䅁䅁允䅁䅁䅕䉯癯匳䝑き䵁䅉䅅䅁䙁䅁䅁睁䵁䅁䅁权䅁䅁䅁权呂䅁䅁权䙁䅁䅁兂䅁䅁䅁䝷浐䅑䅅䅁䉁䅁䅁兂煃搸乊瑙穁䅑杷允䅁䅁䅕䅁䑁䅁䅷䅁䭁䉁䄸䅁䭁䅁䅅䅁䭁䅁䅕䅁䙁䅁䅁䅁䅁畋䅚允䅁䅁䅅䅁䙁䕁桪桥畓⭒⽅䍄䉁䅁䅁兂䅁䅁䅍䅄䅁䅁䅯杇䅁䅁䅯睕䅁䅁䅯兂䅁䅁䅕䅁䅁䕁灃唵䉁䅁䅁允䅁䅁䅕噈歰㥏倫問䵁䅉䅅䅁䙁䅁䅁睁䵁䅁䅁权䅁䅁䅁权呂䅁䅁权䙁䅁䅁兂䅁䅁䅁乧汐䅑䅅䅁䉁䅁䅁兂权楇搯䅊穙䅑杷允䅁䅁䅕䅁䑁䅁䅷䅁䭁䅁䅁䅁䭁䙁䅍䅁䭁䅁䅕䅁䙁䅁䅁䅁䅄佣䅚允䅁䅁䅅䅁䙁䙁橔婰䕶䑁䅒䍄䉁䅁䅁兂䅁䅁䅍䅄䅁䅁䅯䅁䅁䅁䅯允䅁䅁䅯兂䅁䅁䅕䅁䅁䥁呄唵䉁䅁䅁允䅁䅁䅕場啯歲桦樲䴸䅉䅅䅁䙁䅁䅁睁䵁䅁䅁权敁䅁䅁权呂䅁䅁权䙁䅁䅁兂䅁䅁䅁乧汔䅑䅅䅁䉁䅁䅁兂汁潂噇㑑獳䅑杷允䅁䅁䅕䅁䑁䅁䅷䅁䭁䉁䄸䅁䭁䅁䅅䅁䭁䅁䅕䅁䙁䅁䅁䅁䅁甫䅖允䅁䅁䅅䅁䙁䕁桪桥畓⭒⽅䍄䉁䅁䅁兂䅁䅁䅍䅄䅁䅁䅯䅁䅁䅁䅯睕䅁䅁䅯兂䅁䅁䅕䅁䅁䵁敂欵䉁䅁䅁允䅁䅁䅕癱午坔兌き䵁䅉䅅䅁䙁䅁䅁睁䵁䅁䅁权慁䅁䅁权呂䅁䅁权䙁䅁䅁兂䅁䅁䅁䭙汐䅑䅅䅁䉁䅁䅁兂䡃瑆佮稹㕍䅑杷允䅁䅁䅕䅁䑁䅁䅷䅁䭁䅁䅁䅁䭁䙁䅍䅁䭁䅁䅕䅁䙁䅁䅁䅁杄佷䅖允䅁䅁䅅䅁䙁偁周㘴扗䑨䅊䍄䉁䅁䅁兂䅁䅁䅍䅄䅁䅁䅯䅁䅁䅁䅯睕䅁䅁䅯兂䅁䅁䅕䅁䅁䍁㍄唵䉁䅁䅁允䅁䅁䅕噋偹癷潖歍䵁䅉䅅䅁䙁䅁䅁睁䵁䅁䅁权䅁䅁䅁权呂䅁䅁权䙁䅁䅁兂䅁䅁䅁䕁浘䅑䅅䅁䉁䅁䅁兂十㡧䭄捯穕䅑杷允䅁䅁䅕䅁䑁䅁䅷䅁䭁䉁䅷䅁䭁䙁䅍䅁䭁䅁䅕䅁䙁䅁䅁䅁杂畕䅚允䅁䅁䅅䅁䙁乁欰潂噇祑䄵䍄䉁䅁䅁兂䅁䅁䅍䅄䅁䅁䅯䅈䅁䅁䅯允䅁䅁䅯兂䅁䅁䅕䅁䅁䵁硄唵䉁䅁䅁允䅁䅁䅕積積積積稰䴸䅉䅅䅁䙁䅁䅁睁䵁䅁䅁权䅁䅁䅁权呂䅁䅁权䙁䅁䅁兂䅁䅁䅁义汄䅑䅅䅁䉁䅁䅁兂瑂⼵灵昸祉䅑杷允䅁䅁䅕䅁䑁䅁䅷䅁䭁䅁䅁䅁䭁䅁䅅䅁䭁䅁䅕䅁䙁䅁䅁䅁䅂伶䅖允䅁䅁䅅䅁䙁䥁牘払敧摨⽳䍄䉁䅁䅁兂䅁䅁䅍䅄䅁䅁䅯睈䅁䅁䅯睕䅁䅁䅯兂䅁䅁䅕䅁䅁䕁⽄唵䉁䅁䅁允䅁䅁䅕⽺呤㘴㝖䕍䵁䅉䅅䅁䙁䅁䅁睁䵁䅁䅁权䅁䅁䅁权呂䅁䅁权䙁䅁䅁兂䅁䅁䅁䍁浶䅑䅅䅁䉁䅁䅁兂汄䌰扌含稴䅑杷允䅁䅁䅕䅁䑁䅁䅷䅁䭁䉁䄸䅁䭁䙁䅍䅁䭁䅁䅕䅁䙁䅁䅁䅁权⬵䅖允䅁䅁䅅䅁䙁䱁昶楇搯䑒䅂䍄䉁䅁䅁兂䅁䅁䅍䅄䅁䅁䅯䅁䅁䅁䅯睕䅁䅁䅯兂䅁䅁䅕䅁䅁䥁流欵䉁䅁䅁允䅁䅁䅕搵楁⼲⭫き䵁䅉䅅䅁䙁䅁䅁睁䵁䅁䅁权捁䅁䅁权䉁䅁䅁权䙁䅁䅁兂䅁䅁䅁䅑浘䅑䅅䅁䉁䅁䅁兂晁敨剴䉵嘷睐杷允䅁䅁䅕䅁䑁䅁䅷䅁䭁䉁䅯䅁䭁䙁䅍䅁䭁䅁䅕䅁䙁䅁䅁䅁䅂⬹䅖允䅁䅁䅅䅁䙁䥁䌯匹捨稷䅬䍄䉁䅁䅁兂䅁䅁䅍䅄䅁䅁䅯䅁䅁䅁䅯睕䅁䅁䅯兂䅁䅁䅕䅁䅁䕁佁欵䉁䅁䅁允䅁䅁䅕䙅㕧䵴坩歍䵁䅉䅅䅁䙁䅁䅁睁䵁䅁䅁权敁䅁䅁权䉁䅁䅁权䙁䅁䅁兂䅁䅁䅁䝉洳䅑䅅䅁䉁䅁䅁兂䅁䅁䅁䅁兄睐杷允䅁䅁䅕䅁䑁䅁䅷䅁䭁䅁䅁䅁䭁䅁䅅䅁䭁䅁䅕䅁䙁䅁䅁䅁䅄敌䅚允䅁䅁䅅䅁䙁䱁敧敨剴乵⼴䍄䉁䅁䅁兂䅁䅁䅍䅄䅁䅁䅯杇䅁䅁䅯睕䅁䅁䅯兂䅁䅁䅕䅁䅁佁㡃唵䉁䅁䅁允䅁䅁䅕歵䵫楁湳歏䵁䅉䅅䅁䙁䅁䅁睁䵁䅁䅁权敁䅁䅁权呂䅁䅁权䙁䅁䅁兂䅁䅁䅁䅯浌䅑䅅䅁䉁䅁䅁兂䅁䅁䅁䅁煁䅑杷允䅁䅁䅕䅁䑁䅁䅷䅁䭁䅁䅁䅁䭁䙁䅍䅁䭁䅁䅕䅁䙁䅁䅁䅁䅃畆䅚允䅁䅁䅅䅁䙁䝁匸㡧䭄呁䅎䍄䉁䅁䅁兂䅁䅁䅍䅄䅁䅁䅯䅁䅁䅁䅯睕䅁䅁䅯兂䅁䅁䅕䅁䅁䵁橄唵䉁䅁䅁允䅁䅁䅕兇坒楄匳歍䵁䅉䅅䅁䙁䅁䅁睁䵁䅁䅁权敁䅁䅁权䉁䅁䅁权䙁䅁䅁兂䅁䅁䅁佑汔䅑䅅䅁䉁䅁䅁兂穁積積積呐睐杷允䅁䅁䅕䅁䑁䅁䅷䅁䭁䅁䅁䅁䭁䙁䅍䅁䭁䅁䅕䅁䙁䅁䅁䅁杁畦䅚允䅁䅁䅅䅁䙁偁唷佥浫吸䅎䍄䉁䅁䅁兂䅁䅁䅍䅄䅁䅁䅯䅁䅁䅁䅯睕䅁䅁䅯兂䅁䅁䅕䅁䅁䵁㝄唵䉁䅁䅁允䅁䅁䅕噋偹癷潖歍䵁䅉䅅䅁䙁䅁䅁睁䵁䅁䅁权䅁䅁䅁权呂䅁䅁权䙁䅁䅁兂䅁䅁䅁䑉浈䅑䅅䅁䉁䅁䅁兂瑁灳瘳㑰穙䅑杷允䅁䅁䅕䅁䑁䅁䅷䅁䭁䅁䅁䅁䭁䙁䅍䅁䭁䅁䅕䅁䙁䅁䅁䅁杁⭤䅚允䅁䅁䅅䅁䙁䙁橔婰䕶䑁䅒䍄䉁䅁䅁兂䅁䅁䅍䅄䅁䅁䅯䅁䅁䅁䅯允䅁䅁䅯兂䅁䅁䅕䅁䅁䥁剂欵䉁䅁䅁允䅁䅁䅕䉵䘶ㄶ㑇樳䴸䅉䅅䅁䙁䅁䅁睁䵁䅁䅁权捁䅁䅁权䉁䅁䅁权䙁䅁䅁兂䅁䅁䅁义氳䅑䅅䅁䉁䅁䅁兂穁積積積呐睐杷允䅁䅁䅕䅁䑁䅁䅷䅁䭁䅁䅁䅁䭁䅁䅅䅁䭁䅁䅕䅁䙁䅁䅁䅁䅂敤䅚允䅁䅁䅅䅁䙁䱁敧敨剴乵⼴䍄䉁䅁䅁兂䅁䅁䅍䅄䅁䅁䅯䅁䅁䅁䅯睕䅁䅁䅯兂䅁䅁䅕䅁䅁䥁時欵䉁䅁䅁允䅁䅁䅕癱午坔兌き䵁䅉䅅䅁䙁䅁䅁睁䵁䅁䅁权䅁䅁䅁权呂䅁䅁权䙁䅁䅁兂䅁䅁䅁䭷汪䅑䅅䅁䉁䅁䅁兂塄㍯㥁湃硣䅑杷允䅁䅁䅕䅁䑁䅁䅷䅁䭁䉁䄰䅁䭁䙁䅍䅁䭁䅁䅕䅁䙁䅁䅁䅁杁畎䅚允䅁䅁䅅䅁䙁䙁余扌摋礷䄵䍄䉁䅁䅁兂䅁䅁䅍䅄䅁䅁䅯䅁䅁䅁䅯允䅁䅁䅯兂䅁䅁䅕䅁䅁䍁汄唵䉁䅁䅁允䅁䅁䅕場啯歲桦樲䴸䅉䅅䅁䙁䅁䅁睁䵁䅁䅁权䅁䅁䅁权呂䅁䅁权䙁䅁䅁兂䅁䅁䅁䠴洳䅑䅅䅁䉁䅁䅁兂⭄䠱灪癊穅䅑杷允䅁䅁䅕䅁䑁䅁䅷䅁䭁䅁䅁䅁䭁䅁䅅䅁䭁䅁䅕䅁䙁䅁䅁䅁䅄敒䅚允䅁䅁䅅䅁䙁䱁敧敨剴乵⼴䍄䉁䅁䅁兂䅁䅁䅍䅄䅁䅁䅯䅁䅁䅁䅯睕䅁䅁䅯兂䅁䅁䅕䅁䅁䍁杂欵䉁䅁䅁允䅁䅁䅕癱午坔兌き䵁䅉䅅䅁䙁䅁䅁睁䵁䅁䅁权䅁䅁䅁权呂䅁䅁权䙁䅁䅁兂䅁䅁䅁䨴決䅑䅅䅁䉁䅁䅁兂塄㍯㥁癃督䅑杷允䅁䅁䅕䅁䑁䅁䅷䅁䭁䅁䅁䅁䭁䙁䅍䅁䭁䅁䅕䅁䙁䅁䅁䅁䅄敦䅚允䅁䅁䅅䅁䙁偁唷佥浫吸䅎䍄䉁䅁䅁兂䅁䅁䅍䅄䅁䅁䅯䅁䅁䅁䅯睕䅁䅁䅯兂䅁䅁䅕䅁䅁䥁㙄唵䉁䅁䅁允䅁䅁䅕噋偹癷潖歍䵁䅉䅅䅁䙁䅁䅁睁䵁䅁䅁权敁䅁䅁权䉁䅁䅁权䙁䅁䅁兂䅁䅁䅁䅙浘䅑䅅䅁䉁䅁䅁兂㝂䭆䠵場啲睐杷允䅁䅁䅕䅁䑁䅁䅷䅁䭁䉁䅷䅁䭁䅁䅅䅁䭁䅁䅕䅁䙁䅁䅁䅁䅄佅䅚允䅁䅁䅅䅁䙁䉁䘫ㄶ㑇瑈⽕䍄䉁䅁䅁兂䅁䅁䅍䅄䅁䅁䅯杈䅁䅁䅯睕䅁䅁䅯兂䅁䅁䅕䅁䅁䅁灁欵䉁䅁䅁允䅁䅁䅕婤奍䙂佢お䵁䅉䅅䅁䙁䅁䅁睁䵁䅁䅁权䅁䅁䅁权䉁䅁䅁权䙁䅁䅁兂䅁䅁䅁伴汔䅑䅅䅁䉁䅁䅁兂桄桥畓⭒慈睐杷允䅁䅁䅕䅁䑁䅁䅷䅁䭁䉁䄸䅁䭁䙁䅍䅁䭁䅁䅕䅁䙁䅁䅁䅁杂攷䅖允䅁䅁䅅䅁䙁䍁扐堫焵䑘䅂䍄䉁䅁䅁兂䅁䅁䅍䅄䅁䅁䅯䅁䅁䅁䅯睕䅁䅁䅯兂䅁䅁䅕䅁䅁佁歂欵䉁䅁䅁允䅁䅁䅕癱午坔兌き䵁䅉䅅䅁䙁䅁䅁睁䵁䅁䅁权䅁䅁䅁权呂䅁䅁权䙁䅁䅁兂䅁䅁䅁䴴汈䅑䅅䅁䉁䅁䅁兂㑄⭕汏㑭祑䅑杷允䅁䅁䅕䅁䑁䅁䅷䅁䭁䉁䅷䅁䭁䙁䅍䅁䭁䅁䅕䅁䙁䅁䅁䅁杄畢䅚允䅁䅁䅅䅁䙁䡁潎敫㠱礯䄱䍄䉁䅁䅁兂䅁䅁䅍䅄䅁䅁䅯䅈䅁䅁䅯允䅁䅁䅯兂䅁䅁䅕䅁䅁䅁浃唵䉁䅁䅁允䅁䅁䅕㡪ㅌ䙋偹樰䴸䅉䅅䅁䙁䅁䅁睁䵁䅁䅁权捁䅁䅁权呂䅁䅁权䙁䅁䅁兂䅁䅁䅁乧汌䅑䅅䅁䉁䅁䅁兂佂桙奂扏畑䅑杷允䅁䅁䅕䅁䑁䅁䅷䅁䭁䅁䅁䅁䭁䙁䅍䅁䭁䅁䅕䅁䙁䅁䅁䅁杂故䅚允䅁䅁䅅䅁䙁䉁奂扏䥔橬䅊䍄䉁䅁䅁兂䅁䅁䅍䅄䅁䅁䅯杇䅁䅁䅯允䅁䅁䅯兂䅁䅁䅕䅁䅁䵁歂欵䉁䅁䅁允䅁䅁䅕䡰㥁瑃橥䐶䴸䅉䅅䅁䙁䅁䅁睁䵁䅁䅁权䅁䅁䅁权呂䅁䅁权䙁䅁䅁兂䅁䅁䅁䙯浄䅑䅅䅁䉁䅁䅁兂㕁䵴㉨瑶稸䅑杷允䅁䅁䅕䅁䑁䅁䅷䅁䭁䅁䅁䅁䭁䙁䅍䅁䭁䅁䅕䅁䙁䅁䅁䅁杄畒䅚允䅁䅁䅅䅁䙁䉁䑋䵷桱呸䅎䍄䉁䅁䅁兂䅁䅁䅍䅄䅁䅁䅯䅁䅁䅁䅯睕䅁䅁䅯兂䅁䅁䅕䅁䅁佁塁欵䉁䅁䅁允䅁䅁䅕硢䑋䵷䉯き䵁䅉䅅䅁䙁䅁䅁睁䵁䅁䅁权䅁䅁䅁权呂䅁䅁权䙁䅁䅁兂䅁䅁䅁䙑浮䅑䅅䅁䉁䅁䅁兂㕁䵴㉨瑶稸䅑杷允䅁䅁䅕䅁䑁䅁䅷䅁䭁䉁䄸䅁䭁䙁䅍䅁䭁䅁䅕䅁䙁䅁䅁䅁杂⬫䅖允䅁䅁䅅䅁䙁䵁㌯⭕汏穥䅂䍄䉁䅁䅁兂䅁䅁䅍䅄䅁䅁䅯䅈䅁䅁䅯允䅁䅁䅯兂䅁䅁䅕䅁䅁䝁慁欵䉁䅁䅁允䅁䅁䅕歲桦桥畓稱䴸䅉䅅䅁䙁䅁䅁睁䵁䅁䅁权䅁䅁䅁权呂䅁䅁权䙁䅁䅁兂䅁䅁䅁䡑洳䅑䅅䅁䉁䅁䅁兂⭄䠱灪癊穅䅑杷允䅁䅁䅕䅁䑁䅁䅷䅁䭁䅁䅁䅁䭁䅁䅅䅁䭁䅁䅕䅁䙁䅁䅁䅁䅂佁䅚允䅁䅁䅅䅁䙁䱁敧敨剴乵⼴䍄䉁䅁䅁兂䅁䅁䅍䅄䅁䅁䅯䅁䅁䅁䅯睕䅁䅁䅯兂䅁䅁䅕䅁䅁䕁湂欵䉁䅁䅁允䅁䅁䅕佖汏㡭杔き䵁䅉䅅䅁䙁䅁䅁睁䵁䅁䅁权䅁䅁䅁权呂䅁䅁权䙁䅁䅁兂䅁䅁䅁䝯浮䅑䅅䅁䉁䅁䅁兂啂㘴扗佸穁䅑杷允䅁䅁䅕䅁䑁䅁䅷䅁䭁䉁䄴䅁䭁䙁䅍䅁䭁䅁䅕䅁䙁䅁䅁䅁䅃电䅖允䅁䅁䅅䅁䙁䡁㥅瑃橥䌸䅴䍄䉁䅁䅁兂䅁䅁䅍䅄䅁䅁䅯杇䅁䅁䅯睕䅁䅁䅯兂䅁䅁䅕䅁䅁䝁慃唵䉁䅁䅁允䅁䅁䅕瑃橥䑣焳䕏䵁䅉䅅䅁䙁䅁䅁睁䵁䅁䅁权䅁䅁䅁权䉁䅁䅁权䙁䅁䅁兂䅁䅁䅁䑯浘䅑䅅䅁䉁䅁䅁兂㑃潈牘払敪睐杷允䅁䅁䅕䅁䑁䅁䅷䅁䭁䅁䅁䅁䭁䙁䅍䅁䭁䅁䅕䅁䙁䅁䅁䅁䅄⭡䅚允䅁䅁䅅䅁䙁䙁橔婰䕶䐴䅎䍄䉁䅁䅁兂䅁䅁䅍䅄䅁䅁䅯䅈䅁䅁䅯睕䅁䅁䅯兂䅁䅁䅕䅁䅁䥁啄唵䉁䅁䅁允䅁䅁䅕浔光䑗ね歌䵁䅉䅅䅁䙁䅁䅁睁䵁䅁䅁权捁䅁䅁权呂䅁䅁权䙁䅁䅁兂䅁䅁䅁䵉汪䅑䅅䅁䉁䅁䅁兂䙃ㄶ㑇潈畕䅑杷允䅁䅁䅕䅁䑁䅁䅷䅁䭁䅁䅁䅁䭁䅁䅅䅁䭁䅁䅕䅁䙁䅁䅁䅁䅄畴䅖允䅁䅁䅅䅁䙁䩁婱婭婭摭⽫䍄䉁䅁䅁兂䅁䅁䅍䅄䅁䅁䅯䅁䅁䅁䅯睕䅁䅁䅯兂䅁䅁䅕䅁䅁䥁⭃唵䉁䅁䅁允䅁䅁䅕䘫橐婰䕵歍䵁䅉䅅䅁䙁䅁䅁睁䵁䅁䅁权摁䅁䅁权呂䅁䅁权䙁䅁䅁兂䅁䅁䅁䩑氷䅑䅅䅁䉁䅁䅁兂䝂癴㥐䠱瑧䅑杷允䅁䅁䅕䅁䑁䅁䅷䅁䭁䅁䅁䅁䭁䙁䅍䅁䭁䅁䅕䅁䙁䅁䅁䅁杁⭓䅚允䅁䅁䅅䅁䙁䉁䑋䵷桱呸䅎䍄䉁䅁䅁兂䅁䅁䅍䅄䅁䅁䅯先䅁䅁䅯睕䅁䅁䅯兂䅁䅁䅕䅁䅁䥁浄唵䉁䅁䅁允䅁䅁䅕䉵䘶ㄶ㑈䕌䵁䅉䅅䅁䙁䅁䅁睁䵁䅁䅁权䅁䅁䅁权呂䅁䅁权䙁䅁䅁兂䅁䅁䅁䭯汌䅑䅅䅁䉁䅁䅁兂塄㍯㥁癃督䅑杷允䅁䅁䅕䅁䑁䅁䅷䅁䭁䅁䅁䅁䭁䙁䅍䅁䭁䅁䅕䅁䙁䅁䅁䅁杂畚䅚允䅁䅁䅅䅁䙁䙁橔婰䕶䐴䅎䍄䉁䅁䅁兂䅁䅁䅍䅄䅁䅁䅯䅁䅁䅁䅯睕䅁䅁䅯兂䅁䅁䅕䅁䅁䝁桁欵䉁䅁䅁允䅁䅁䅕硢䑋䵷䉯き䵁䅉䅅䅁䙁䅁䅁睁䵁䅁䅁权捁䅁䅁权呂䅁䅁权䙁䅁䅁兂䅁䅁䅁䑑洷䅑䅅䅁䉁䅁䅁兂塁挲㌷㙕畍䅑杷允䅁䅁䅕䅁䑁䅁䅷䅁䭁䉁䄴䅁䭁䙁䅍䅁䭁䅁䅕䅁䙁䅁䅁䅁杄由䅖允䅁䅁䅅䅁䙁䍁䝕婧䑖祩䅸䍄䉁䅁䅁兂䅁䅁䅍䅄䅁䅁䅯䅁䅁䅁䅯睕䅁䅁䅯兂䅁䅁䅕䅁䅁佁啂欵䉁䅁䅁允䅁䅁䅕扏䥔牤昷き䵁䅉䅅䅁䙁䅁䅁睁䵁䅁䅁权敁䅁䅁权呂䅁䅁权䙁䅁䅁兂䅁䅁䅁䝑浈䅑䅅䅁䉁䅁䅁兂剃堷⽷噎椴䅑杷允䅁䅁䅕䅁䑁䅁䅷䅁䭁䉁䄴䅁䭁䙁䅍䅁䭁䅁䅕䅁䙁䅁䅁䅁䅃⭣䅚允䅁䅁䅅䅁䙁䍁捬㡪ㅌ䍡䅆䍄䉁䅁䅁兂䅁䅁䅍䅄䅁䅁䅯䅁䅁䅁䅯睕䅁䅁䅯兂䅁䅁䅕䅁䅁䕁㡂欵䉁䅁䅁允䅁䅁䅕佖汏㡭䅑䕎䵁䅉䅅䅁䙁䅁䅁睁䵁䅁䅁权䅁䅁䅁权呂䅁䅁权䙁䅁䅁兂䅁䅁䅁䅯浐䅑䅅䅁䉁䅁䅁兂煃搸乊湙祁䅑杷允䅁䅁䅕䅁䑁䅁䅷䅁䭁䉁䅷䅁䭁䅁䅅䅁䭁䅁䅕䅁䙁䅁䅁䅁权敊䅚允䅁䅁䅅䅁䙁䭁䠵場啯瑲⽣䍄䉁䅁䅁兂䅁䅁䅍䅄䅁䅁䅯䅈䅁䅁䅯允䅁䅁䅯兂䅁䅁䅕䅁䅁䵁浄唵䉁䅁䅁允䅁䅁䅕積積積積稰䴸䅉䅅䅁䙁䅁䅁睁䵁䅁䅁权䅁䅁䅁权呂䅁䅁权䙁䅁䅁兂䅁䅁䅁䑑浈䅑䅅䅁䉁䅁䅁兂瑁灳瘳㑰穙䅑杷允䅁䅁䅕䅁䑁䅁䅷䅁䭁䉁䅷䅁䭁䅁䅅䅁䭁䅁䅕䅁䙁䅁䅁䅁杁⬸䅖允䅁䅁䅅䅁䙁䑁積積積㥍⽍䍄䉁䅁䅁兂䅁䅁䅍䅄䅁䅁䅯杇䅁䅁䅯睕䅁䅁䅯兂䅁䅁䅕䅁䅁佁啁欵䉁䅁䅁允䅁䅁䅕潂噇㑑䵴歏䵁䅉䅅䅁䙁䅁䅁睁䵁䅁䅁权晁䅁䅁权呂䅁䅁权䙁䅁䅁兂䅁䅁䅁䭯決䅑䅅䅁䉁䅁䅁兂㑃潈牘塕睧䅑杷允䅁䅁䅕䅁䑁䅁䅷䅁䭁䅁䅁䅁䭁䙁䅍䅁䭁䅁䅕䅁䙁䅁䅁䅁䅃伸䅖允䅁䅁䅅䅁䙁䑁積積積穫䅊䍄䉁䅁䅁兂䅁䅁䅍䅄䅁䅁䅯杇䅁䅁䅯睕䅁䅁䅯兂䅁䅁䅕䅁䅁䝁㍃唵䉁䅁䅁允䅁䅁䅕穐敖歵獮問䵁䅉䅅䅁䙁䅁䅁睁䵁䅁䅁权䅁䅁䅁权呂䅁䅁权䙁䅁䅁兂䅁䅁䅁乷氷䅑䅅䅁䉁䅁䅁兂婁䙂余摌祉䅑杷允䅁䅁䅕䅁䑁䅁䅷䅁䭁䅁䅁䅁䭁䙁䅍䅁䭁䅁䅕䅁䙁䅁䅁䅁䅁⭤䅚允䅁䅁䅅䅁䙁䙁橔婰䕶䑁䅒䍄䉁䅁䅁兂䅁䅁䅍䅄䅁䅁䅯䅈䅁䅁䅯睕䅁䅁䅯兂䅁䅁䅕䅁䅁䅁⽂欵䉁䅁䅁允䅁䅁䅕塹⭡确癱啌䵁䅉䅅䅁䙁䅁䅁睁䵁䅁䅁权摁䅁䅁权䉁䅁䅁权䙁䅁䅁兂䅁䅁䅁䅧浲䅑䅅䅁䉁䅁䅁兂晁敨剴䉵嘷睐杷允䅁䅁䅕䅁䑁䅁䅷䅁䭁䉁䅷䅁䭁䙁䅍䅁䭁䅁䅕䅁䙁䅁䅁䅁䅃畱䅖允䅁䅁䅅䅁䙁偁潙䥘䌯却䄱䍄䉁䅁䅁兂䅁䅁䅍䅄䅁䅁䅯䅁䅁䅁䅯允䅁䅁䅯兂䅁䅁䅕䅁䅁䕁硃唵䉁䅁䅁允䅁䅁䅕灭婭婭婭吲䴸䅉䅅䅁䙁䅁䅁睁䵁䅁䅁权摁䅁䅁权䉁䅁䅁权䙁䅁䅁兂䅁䅁䅁䵧汔䅑䅅䅁䉁䅁䅁兂塄㍯㥁瑃呦睐杷允䅁䅁䅕䅁䑁䅁䅷䅁䭁䅁䅁䅁䭁䙁䅍䅁䭁䅁䅕䅁䙁䅁䅁䅁权⭖䅚允䅁䅁䅅䅁䙁䑁ね䡹⭡稳䅎䍄䉁䅁䅁兂䅁䅁䅍䅄䅁䅁䅯睈䅁䅁䅯允䅁䅁䅯兂䅁䅁䅕䅁䅁佁䝄唵䉁䅁䅁允䅁䅁䅕䉵䘶ㄶ㑇樳䴸䅉䅅䅁䙁䅁䅁睁䵁䅁䅁权䅁䅁䅁权呂䅁䅁权䙁䅁䅁兂䅁䅁䅁䍷浢䅑䅅䅁䉁䅁䅁兂汄䌰扌含稴䅑杷允䅁䅁䅕䅁䑁䅁䅷䅁䭁䅁䅁䅁䭁䙁䅍䅁䭁䅁䅕䅁䙁䅁䅁䅁杁敕䅚允䅁䅁䅅䅁䙁䑁ね䡹⭡稳䅎䍄䉁䅁䅁兂䅁䅁䅍䅄䅁䅁䅯䅁䅁䅁䅯睕䅁䅁䅯兂䅁䅁䅕䅁䅁䝁㝂欵䉁䅁䅁允䅁䅁䅕佖汏㡭䅑䕎䵁䅉䅅䅁䙁䅁䅁睁䵁䅁䅁权摁䅁䅁权䉁䅁䅁权䙁䅁䅁兂䅁䅁䅁䥧浈䅑䅅䅁䉁䅁䅁兂畃⭒㙆䭆堷睐杷允䅁䅁䅕䅁䑁䅁䅷䅁䭁䅁䅁䅁䭁䙁䅍䅁䭁䅁䅕䅁䙁䅁䅁䅁䅂⭥䅚允䅁䅁䅅䅁䙁䙁橔婰䕶䑁䅒䍄䉁䅁䅁兂䅁䅁䅍䅄䅁䅁䅯䅁䅁䅁䅯睕䅁䅁䅯兂䅁䅁䅕䅁䅁䍁㝂欵䉁䅁䅁允䅁䅁䅕佖汏㡭䅑䕎䵁䅉䅅䅁䙁䅁䅁睁䵁䅁䅁权䅁䅁䅁权䉁䅁䅁权䙁䅁䅁兂䅁䅁䅁䡯浲䅑䅅䅁䉁䅁䅁兂㑃潈牘払敪睐杷允䅁䅁䅕䅁䑁䅁䅷䅁䭁䅁䅁䅁䭁䙁䅍䅁䭁䅁䅕䅁䙁䅁䅁䅁䅄略䅚允䅁䅁䅅䅁䙁䙁橔婰䕶䑁䅒䍄䉁䅁䅁兂䅁䅁䅍䅄䅁䅁䅯䅈䅁䅁䅯睕䅁䅁䅯兂䅁䅁䅕䅁䅁䕁捃唵䉁䅁䅁允䅁䅁䅕捷桱扒穙啌䵁䅉䅅䅁䙁䅁䅁睁䵁䅁䅁权敁䅁䅁权䉁䅁䅁权䙁䅁䅁兂䅁䅁䅁偧汄䅑䅅䅁䉁䅁䅁兂穁積積積呐睐杷允䅁䅁䅕䅁䑁䅁䅷䅁䭁䉁䄸䅁䭁䅁䅅䅁䭁䅁䅕䅁䙁䅁䅁䅁杂畴䅖允䅁䅁䅅䅁䙁䥁牘払敧摨⽳䍄䉁䅁䅁兂䅁䅁䅍䅄䅁䅁䅯䅁䅁䅁䅯睕䅁䅁䅯兂䅁䅁䅕䅁䅁䕁䑂欵䉁䅁䅁允䅁䅁䅕䅁䅁䅁权き䵁䅉䅅䅁䙁䅁䅁睁䵁䅁䅁权䅁䅁䅁权呂䅁䅁权䙁䅁䅁兂䅁䅁䅁䙁浶䅑䅅䅁䉁䅁䅁兂煃搸乊瑙穁䅑杷允䅁䅁䅕䅁䑁䅁䅷䅁䭁䅁䅁䅁䭁䅁䅅䅁䭁䅁䅕䅁䙁䅁䅁䅁䅁佷䅖允䅁䅁䅅䅁䙁䑁䬰㘱睎摐⽯䍄䉁䅁䅁兂䅁䅁䅍䅄䅁䅁䅯睈䅁䅁䅯睕䅁䅁䅯兂䅁䅁䅕䅁䅁䕁㑄唵䉁䅁䅁允䅁䅁䅕⽺呤㘴㝖䕍䵁䅉䅅䅁䙁䅁䅁睁䵁䅁䅁权䅁䅁䅁权呂䅁䅁权䙁䅁䅁兂䅁䅁䅁䱙汄䅑䅅䅁䉁䅁䅁兂㙃兓䍷祋祣䅑杷允䅁䅁䅕䅁䑁䅁䅷䅁䭁䉁䅯䅁䭁䙁䅍䅁䭁䅁䅕䅁䙁䅁䅁䅁䅁畡䅚允䅁䅁䅅䅁䙁䍁搯䅊䉡呖䅴䍄䉁䅁䅁兂䅁䅁䅍䅄䅁䅁䅯䅁䅁䅁䅯睕䅁䅁䅯兂䅁䅁䅕䅁䅁䭁ㅄ唵䉁䅁䅁允䅁䅁䅕噋偹癷潖歍䵁䅉䅅䅁䙁䅁䅁睁䵁䅁䅁权晁䅁䅁权䉁䅁䅁权䙁䅁䅁兂䅁䅁䅁䍑浈䅑䅅䅁䉁䅁䅁兂㉄䙋偹癷杘睐杷允䅁䅁䅕䅁䑁䅁䅷䅁䭁䉁䅷䅁䭁䅁䅅䅁䭁䅁䅕䅁䙁䅁䅁䅁杂⬫䅖允䅁䅁䅅䅁䙁䉁䘫ㄶ㑇瑈⽕䍄䉁䅁䅁兂䅁䅁䅍䅄䅁䅁䅯睈䅁䅁䅯睕䅁䅁䅯兂䅁䅁䅕䅁䅁䥁䑁欵䉁䅁䅁允䅁䅁䅕㡧䭄啯块䕍䵁䅉䅅䅁䙁䅁䅁睁䵁䅁䅁权晁䅁䅁权呂䅁䅁权䙁䅁䅁兂䅁䅁䅁䅧浺䅑䅅䅁䉁䅁䅁兂䕁杖琴牳眰䅑杷允䅁䅁䅕䅁䑁䅁䅷䅁䭁䅁䅁䅁䭁䙁䅍䅁䭁䅁䅕䅁䙁䅁䅁䅁杂略䅚允䅁䅁䅅䅁䙁䙁橔婰䕶䑁䅒䍄䉁䅁䅁兂䅁䅁䅍䅄䅁䅁䅯䅁䅁䅁䅯睕䅁䅁䅯兂䅁䅁䅕䅁䅁佁㑂欵䉁䅁䅁允䅁䅁䅕佖汏㡭䅑䕎䵁䅉䅅䅁䙁䅁䅁睁䵁䅁䅁权摁䅁䅁权呂䅁䅁权䙁䅁䅁兂䅁䅁䅁䉷浪䅑䅅䅁䉁䅁䅁兂䭁㘱睎捐畯䅑杷允䅁䅁䅕䅁䑁䅁䅷䅁䭁䉁䅯䅁䭁䙁䅍䅁䭁䅁䅕䅁䙁䅁䅁䅁䅁敃䅚允䅁䅁䅅䅁䙁䕁㉡⼸唳䑇䅰䍄䉁䅁䅁兂䅁䅁䅍䅄䅁䅁䅯䅁䅁䅁䅯睕䅁䅁䅯兂䅁䅁䅕䅁䅁佁偁欵䉁䅁䅁允䅁䅁䅕䙅㕧䵴坩歍䵁䅉䅅䅁䙁䅁䅁睁䵁䅁䅁权敁䅁䅁权䉁䅁䅁权䙁䅁䅁兂䅁䅁䅁䈴洷䅑䅅䅁䉁䅁䅁兂䑄匹捨㡪噌睐杷允䅁䅁䅕䅁䑁䅁䅷䅁䭁䅁䅁䅁䭁䙁䅍䅁䭁䅁䅕䅁䙁䅁䅁䅁杄敥䅚允䅁䅁䅅䅁䙁䙁橔婰䕶䑁䅒䍄䉁䅁䅁兂䅁䅁䅍䅄䅁䅁䅯先䅁䅁䅯睕䅁䅁䅯兂䅁䅁䅕䅁䅁䥁㝁欵䉁䅁䅁允䅁䅁䅕牒穢搯㑓歌䵁䅉䅅䅁䙁䅁䅁睁䵁䅁䅁权䅁䅁䅁权呂䅁䅁权䙁䅁䅁兂䅁䅁䅁䉁浲䅑䅅䅁䉁䅁䅁兂療潅䅐杹穅䅑杷允䅁䅁䅕䅁䑁䅁䅷䅁䭁䅁䅁䅁䭁䙁䅍䅁䭁䅁䅕䅁䙁䅁䅁䅁䅃⭓䅚允䅁䅁䅅䅁䙁䉁䑋䵷桱呸䅎䍄䉁䅁䅁兂䅁䅁䅍䅄䅁䅁䅯䅁䅁䅁䅯睕䅁䅁䅯兂䅁䅁䅕䅁䅁䭁㙃唵䉁䅁䅁允䅁䅁䅕䘫橐婰䕵歍䵁䅉䅅䅁䙁䅁䅁睁䵁䅁䅁权慁䅁䅁权䉁䅁䅁权䙁䅁䅁兂䅁䅁䅁䄴浌䅑䅅䅁䉁䅁䅁兂浂浚浚浚浢睐杷允䅁䅁䅕䅁䑁䅁䅷䅁䭁䅁䅁䅁䭁䙁䅍䅁䭁䅁䅕䅁䙁䅁䅁䅁杁敉䅚允䅁䅁䅅䅁䙁䝁匸㡧䭄呁䅎䍄䉁䅁䅁兂䅁䅁䅍䅄䅁䅁䅯杈䅁䅁䅯睕䅁䅁䅯兂䅁䅁䅕䅁䅁佁楁欵䉁䅁䅁允䅁䅁䅕兇坒楄礱啋䵁䅉䅅䅁䙁䅁䅁睁䵁䅁䅁权摁䅁䅁权䉁䅁䅁权䙁䅁䅁兂䅁䅁䅁䜴浔䅑䅅䅁䉁䅁䅁兂畃⭒㙆䭆堷睐杷允䅁䅁䅕䅁䑁䅁䅷䅁䭁䉁䄴䅁䭁䙁䅍䅁䭁䅁䅕䅁䙁䅁䅁䅁杄敤䅚允䅁䅁䅅䅁䙁䍁捬㡪ㅌ䍡䅆䍄䉁䅁䅁兂䅁䅁䅍䅄䅁䅁䅯䅁䅁䅁䅯允䅁䅁䅯兂䅁䅁䅕䅁䅁䥁楄唵䉁䅁䅁允䅁䅁䅕場啯歲桦樲䴸䅉䅅䅁䙁䅁䅁睁䵁䅁䅁权䅁䅁䅁权呂䅁䅁权䙁䅁䅁兂䅁䅁䅁䡧浮䅑䅅䅁䉁䅁䅁兂啂㘴扗䅸ぁ䅑杷允䅁䅁䅕䅁䑁䅁䅷䅁䭁䅁䅁䅁䭁䙁䅍䅁䭁䅁䅕䅁䙁䅁䅁䅁杁佭䅖允䅁䅁䅅䅁䙁䱁へ硫䕧橤䅂䍄䉁䅁䅁兂䅁䅁䅍䅄䅁䅁䅯䅁䅁䅁䅯睕䅁䅁䅯兂䅁䅁䅕䅁䅁䕁䕁欵䉁䅁䅁允䅁䅁䅕癱午坔睊歍䵁䅉䅅䅁䙁䅁䅁睁䵁䅁䅁权晁䅁䅁权䉁䅁䅁权䙁䅁䅁兂䅁䅁䅁䭧汈䅑䅅䅁䉁䅁䅁兂硂児塲㍯摄睐杷允䅁䅁䅕䅁䑁䅁䅷䅁䭁䅁䅁䅁䭁䅁䅅䅁䭁䅁䅕䅁䙁䅁䅁䅁杂体䅚允䅁䅁䅅䅁䙁䱁敧敨剴乵⼴䍄䉁䅁䅁兂䅁䅁䅍䅄䅁䅁䅯䅈䅁䅁䅯睕䅁䅁䅯兂䅁䅁䅕䅁䅁䍁畂欵䉁䅁䅁允䅁䅁䅕㉣剩堷⽺啌䵁䅉䅅䅁䙁䅁䅁睁䵁䅁䅁权敁䅁䅁权䉁䅁䅁权䙁䅁䅁兂䅁䅁䅁䭑汶䅑䅅䅁䉁䅁䅁兂穁積積積呐睐杷允䅁䅁䅕䅁䑁䅁䅷䅁䭁䅁䅁䅁䭁䙁䅍䅁䭁䅁䅕䅁䙁䅁䅁䅁䅂⬷䅖允䅁䅁䅅䅁䙁䑁積積積穫䅊䍄䉁䅁䅁兂䅁䅁䅍䅄䅁䅁䅯杇䅁䅁䅯睕䅁䅁䅯兂䅁䅁䅕䅁䅁䵁穂欵䉁䅁䅁允䅁䅁䅕䑔䩥坑汁く䵁䅉䅅䅁䙁䅁䅁睁䵁䅁䅁权晁䅁䅁权呂䅁䅁权䙁䅁䅁兂䅁䅁䅁䑑浔䅑䅅䅁䉁䅁䅁兂⽁噎㘶卓硷䅑杷允䅁䅁䅕䅁䑁䅁䅷䅁䭁䉁䄴䅁䭁䙁䅍䅁䭁䅁䅕䅁䙁䅁䅁䅁杄敭䅖允䅁䅁䅅䅁䙁䅁䉡啬䱏䍢䅬䍄䉁䅁䅁兂䅁䅁䅍䅄䅁䅁䅯睈䅁䅁䅯允䅁䅁䅯兂䅁䅁䅕䅁䅁䍁獃唵䉁䅁䅁允䅁䅁䅯睇䅁䅁杷允䅁䅁䅕䅁䑁䅁䅷䅁䭁䅁䅁䅁䭁䙁䅍䅁䭁䅁䅕䅁䙁䅁䅁䅁杂敚䅚允䅁䅁䅅䅁䙁䙁橔婰䕶䐴䅎䍄䉁䅁䅁兂䅁䅁䅍䅄䅁䅁䅯䅁䅁䅁䅯允䅁䅁䅯兂䅁䅁䅕䅁䅁䭁㙄唵䉁䅁䅁允䅁䅁䅕䉵䘶ㄶ㑇樳䴸䅉䅅䅁䙁䅁䅁睁䵁䅁䅁权䅁䅁䅁权呂䅁䅁权䙁䅁䅁兂䅁䅁䅁䡁浮䅑䅅䅁䉁䅁䅁兂啂㘴扗䅸ぁ䅑杷允䅁䅁䅕䅁䑁䅁䅷䅁䭁䉁䄰䅁䭁䙁䅍䅁䭁䅁䅕䅁䙁䅁䅁䅁䅂⭬䅖允䅁䅁䅅䅁䙁䱁へ硫䕧楖䄱䍄䉁䅁䅁兂䅁䅁䅍䅄䅁䅁䅯䅁䅁䅁䅯睕䅁䅁䅯兂䅁䅁䅕䅁䅁䭁汃唵䉁䅁䅁允䅁䅁䅕㘱睎児㍰啍䵁䅉䅅䅁䙁䅁䅁睁䵁䅁䅁权䅁䅁䅁权䉁䅁䅁权䙁䅁䅁兂䅁䅁䅁䌴浮䅑䅅䅁䉁䅁䅁兂㑃潈牘払敪睐杷允䅁䅁䅕䅁䑁䅁䅷䅁䭁䉁䄴䅁䭁䙁䅍䅁䭁䅁䅕䅁䙁䅁䅁䅁权⭵䅖允䅁䅁䅅䅁䙁䡁㥅瑃橥䍍䅸䍄䉁䅁䅁兂䅁䅁䅍䅄䅁䅁䅯䅁䅁䅁䅯睕䅁䅁䅯兂䅁䅁䅕䅁䅁䭁偁欵䉁䅁䅁允䅁䅁䅕䙅㕧䵴坩歍䵁䅉䅅䅁䙁䅁䅁睁䵁䅁䅁权捁䅁䅁权䉁䅁䅁权䙁䅁䅁兂䅁䅁䅁䑧浺䅑䅅䅁䉁䅁䅁兂㉄䙋偹癷奘睐杷允䅁䅁䅕䅁䑁䅁䅷䅁䭁䅁䅁䅁䭁䅁䅅䅁䭁䅁䅕䅁䙁䅁䅁䅁䅃散䅚允䅁䅁䅅䅁䙁䱁敧敨剴乵⼴䍄䉁䅁䅁兂䅁䅁䅍䅄䅁䅁䅯杇䅁䅁䅯睕䅁䅁䅯兂䅁䅁䅕䅁䅁䵁㡃唵䉁䅁䅁允䅁䅁䅕歵䵫楁湳歏䵁䅉䅅䅁䙁䅁䅁睁䵁䅁䅁权䅁䅁䅁权呂䅁䅁权䙁䅁䅁兂䅁䅁䅁䡷浪䅑䅅䅁䉁䅁䅁兂啂㘴扗䅸ぁ䅑杷允䅁䅁䅕䅁䑁䅁䅷䅁䭁䅁䅁䅁䭁䅁䅅䅁䭁䅁䅕䅁䙁䅁䅁䅁杂⭔䅚允䅁䅁䅅䅁䙁䱁敧敨剴乵⼴䍄䉁䅁䅁兂䅁䅁䅍䅄䅁䅁䅯䅁䅁䅁䅯睕䅁䅁䅯兂䅁䅁䅕䅁䅁䵁偄唵䉁䅁䅁允䅁䅁䅕敢㝦晱祈歍䵁䅉䅅䅁䙁䅁䅁睁䵁䅁䅁权晁䅁䅁权呂䅁䅁权䙁䅁䅁兂䅁䅁䅁䈴浦䅑䅅䅁䉁䅁䅁兂䝂癴㥐倱睧䅑杷允䅁䅁䅕䅁䑁䅁䅷䅁䭁䅁䅁䅁䭁䙁䅍䅁䭁䅁䅕䅁䙁䅁䅁䅁杂攸䅖允䅁䅁䅅䅁䙁䑁積積積穫䅊䍄䉁䅁䅁兂䅁䅁䅍䅄䅁䅁䅯䅁䅁䅁䅯睕䅁䅁䅯兂䅁䅁䅕䅁䅁䝁穁欵䉁䅁䅁允䅁䅁䅕扌摋㘷䝥き䵁䅉䅅䅁䙁䅁䅁睁䵁䅁䅁权䅁䅁䅁权呂䅁䅁权䙁䅁䅁兂䅁䅁䅁䡑浔䅑䅅䅁䉁䅁䅁兂啂㘴扗䅸ぁ䅑杷允䅁䅁䅕䅁䑁䅁䅷䅁䭁䉁䄸䅁䭁䙁䅍䅁䭁䅁䅕䅁䙁䅁䅁䅁䅁畤䅚允䅁䅁䅅䅁䙁䝁㡱䩤奍䑊䅆䍄䉁䅁䅁兂䅁䅁䅍䅄䅁䅁䅯睈䅁䅁䅯睕䅁䅁䅯兂䅁䅁䅕䅁䅁䵁噂欵䉁䅁䅁允䅁䅁䅕呦ㄸ牘灯啍䵁䅉䅅䅁䙁䅁䅁睁䵁䅁䅁权䅁䅁䅁权䉁䅁䅁权䙁䅁䅁兂䅁䅁䅁䍁浮䅑䅅䅁䉁䅁䅁兂㑃潈牘払敪睐杷允䅁䅁䅕䅁䑁䅁䅷䅁䭁䉁䄴䅁䭁䅁䅅䅁䭁䅁䅕䅁䙁䅁䅁䅁䅁畮䅖允䅁䅁䅅䅁䙁䑁積積積㥍⽍䍄䉁䅁䅁兂䅁䅁䅍䅄䅁䅁䅯䅁䅁䅁䅯睕䅁䅁䅯兂䅁䅁䅕䅁䅁䭁桄唵䉁䅁䅁允䅁䅁䅕兇坒楄匳歍䵁䅉䅅䅁䙁䅁䅁睁䵁䅁䅁权䅁䅁䅁权呂䅁䅁权䙁䅁䅁兂䅁䅁䅁䉁浦䅑䅅䅁䉁䅁䅁兂療潅䅐杹穅䅑杷允䅁䅁䅕䅁䑁䅁䅷䅁䭁䉁䅷䅁䭁䙁䅍䅁䭁䅁䅕䅁䙁䅁䅁䅁䅁敃䅚允䅁䅁䅅䅁䙁偁潙䥘䌯卤䄱䍄䉁䅁䅁兂䅁䅁䅍䅄䅁䅁䅯先䅁䅁䅯允䅁䅁䅯兂䅁䅁䅕䅁䅁䭁歂欵䉁䅁䅁允䅁䅁䅕歲桦桥畓稱䴸䅉䅅䅁䙁䅁䅁睁䵁䅁䅁权慁䅁䅁权呂䅁䅁权䙁䅁䅁兂䅁䅁䅁䝉浌䅑䅅䅁䉁䅁䅁兂⭃确癯圳㝑䅑杷允䅁䅁䅕䅁䑁䅁䅷䅁䭁䅁䅁䅁䭁䙁䅍䅁䭁䅁䅕䅁䙁䅁䅁䅁杄畍䅚允䅁䅁䅅䅁䙁䍁礲敮渫橨䅎䍄䉁䅁䅁兂䅁䅁䅍䅄䅁䅁䅯䅁䅁䅁䅯睕䅁䅁䅯兂䅁䅁䅕䅁䅁䝁䑂欵䉁䅁䅁允䅁䅁䅕潅䅐煹䙈き䵁䅉䅅䅁䙁䅁䅁睁䵁䅁䅁权摁䅁䅁权呂䅁䅁权䙁䅁䅁兂䅁䅁䅁䍑洯䅑䅅䅁䉁䅁䅁兂坂楄礲敮甸䅑杷允䅁䅁䅕䅁䑁䅁䅷䅁䭁䅁䅁䅁䭁䙁䅍䅁䭁䅁䅕䅁䙁䅁䅁䅁权畅䅚允䅁䅁䅅䅁䙁䉁奂扏䥔橬䅊䍄䉁䅁䅁兂䅁䅁䅍䅄䅁䅁䅯䅁䅁䅁䅯睕䅁䅁䅯兂䅁䅁䅕䅁䅁䅁楁欵䉁䅁䅁允䅁䅁䅕硢䑋䵷䉯き䵁䅉䅅䅁䙁䅁䅁睁䵁䅁䅁权䅁䅁䅁权呂䅁䅁权䙁䅁䅁兂䅁䅁䅁䔴浔䅑䅅䅁䉁䅁䅁兂十㡧䭄捯穕䅑杷允䅁䅁䅕䅁䑁䅁䅷䅁䭁䉁䄰䅁䭁䙁䅍䅁䭁䅁䅕䅁䙁䅁䅁䅁䅂畸䅖允䅁䅁䅅䅁䙁䕁㍷啩杆匵䄱䍄䉁䅁䅁兂䅁䅁䅍䅄䅁䅁䅯杇䅁䅁䅯睕䅁䅁䅯兂䅁䅁䅕䅁䅁䍁㥂欵䉁䅁䅁允䅁䅁䅕䑔䩥坑汁く䵁䅉䅅䅁䙁䅁䅁睁䵁䅁䅁权摁䅁䅁权䉁䅁䅁权䙁䅁䅁兂䅁䅁䅁䠴浢䅑䅅䅁䉁䅁䅁兂畃⭒㙆䭆堷睐杷允䅁䅁䅕䅁䑁䅁䅷䅁䭁䅁䅁䅁䭁䙁䅍䅁䭁䅁䅕䅁䙁䅁䅁䅁杂敢䅚允䅁䅁䅅䅁䙁䙁橔婰䕶䐴䅎䍄䉁䅁䅁兂䅁䅁䅍䅄䅁䅁䅯杈䅁䅁䅯允䅁䅁䅯兂䅁䅁䅕䅁䅁䕁㙂欵䉁䅁䅁允䅁䅁䅕䅁䅁䅁䅁䐰䴸䅉䅅䅁䙁䅁䅁睁䵁䅁䅁权捁䅁䅁权呂䅁䅁权䙁䅁䅁兂䅁䅁䅁偧汲䅑䅅䅁䉁䅁䅁兂敂歵䵫流瑳䅑杷允䅁䅁䅕䅁䑁䅁䅷䅁䭁䅁䅁䅁䭁䙁䅍䅁䭁䅁䅕䅁䙁䅁䅁䅁䅃攷䅖允䅁䅁䅅䅁䙁䑁積積積穫䅊䍄䉁䅁䅁兂䅁䅁䅍䅄䅁䅁䅯䅁䅁䅁䅯允䅁䅁䅯兂䅁䅁䅕䅁䅁䕁䑁欵䉁䅁䅁允䅁䅁䅕䉵䘶ㄶ㑇樳䴸䅉䅅䅁䙁䅁䅁睁䵁䅁䅁权敁䅁䅁权䉁䅁䅁权䙁䅁䅁兂䅁䅁䅁䩧氯䅑䅅䅁䉁䅁䅁兂穁積積積呐睐杷允䅁䅁䅕䅁䑁䅁䅷䅁䭁䅁䅁䅁䭁䙁䅍䅁䭁䅁䅕䅁䙁䅁䅁䅁杁留䅚允䅁䅁䅅䅁䙁䭁硲欰椱䐰䅎䍄䉁䅁䅁兂䅁䅁䅍䅄䅁䅁䅯䅈䅁䅁䅯允䅁䅁䅯兂䅁䅁䅕䅁䅁䵁歄唵䉁䅁䅁允䅁䅁䅕積積積積稰䴸䅉䅅䅁䙁䅁䅁睁䵁䅁䅁权䅁䅁䅁权呂䅁䅁权䙁䅁䅁兂䅁䅁䅁䭯汢䅑䅅䅁䉁䅁䅁兂塄㍯㥁湃硣䅑杷允䅁䅁䅕䅁䑁䅁䅷䅁䭁䉁䄸䅁䭁䙁䅍䅁䭁䅁䅕䅁䙁䅁䅁䅁杄敒䅚允䅁䅁䅅䅁䙁䅁坒楄礲呈䅆䍄䉁䅁䅁兂䅁䅁䅍䅄䅁䅁䅯䅁䅁䅁䅯睕䅁䅁䅯兂䅁䅁䅕䅁䅁䵁㉂欵䉁䅁䅁允䅁䅁䅕佖汏㡭䅑䕎䵁䅉䅅䅁䙁䅁䅁睁䵁䅁䅁权䅁䅁䅁权䉁䅁䅁权䙁䅁䅁兂䅁䅁䅁䄴浈䅑䅅䅁䉁䅁䅁兂㑃潈牘払敪睐杷允䅁䅁䅕䅁䑁䅁䅷䅁䭁䅁䅁䅁䭁䙁䅍䅁䭁䅁䅕䅁䙁䅁䅁䅁杂敶䅖允䅁䅁䅅䅁䙁偁周㘴扗䑨䅊䍄䉁䅁䅁兂䅁䅁䅍䅄䅁䅁䅯䅈䅁䅁䅯睕䅁䅁䅯兂䅁䅁䅕䅁䅁䥁䅃欵䉁䅁䅁允䅁䅁䅕塹⭡确癱啌䵁䅉䅅䅁䙁䅁䅁睁䵁䅁䅁权敁䅁䅁权䉁䅁䅁权䙁䅁䅁兂䅁䅁䅁䉁洳䅑䅅䅁䉁䅁䅁兂䑄匹捨㡪噌睐杷允䅁䅁䅕䅁䑁䅁䅷䅁䭁䉁䄴䅁䭁䅁䅅䅁䭁䅁䅕䅁䙁䅁䅁䅁䅂畚䅚允䅁䅁䅅䅁䙁䅁䅁䅁䅁乁⽁䍄䉁䅁䅁兂䅁䅁䅍䅄䅁䅁䅯䅁䅁䅁䅯允䅁䅁䅯兂䅁䅁䅕䅁䅁䥁ぁ
